Workbook

Sheet Dados
A1: NUMERO_SS | B1: ANO | C1: SIGLAORGAO | D1: DEPARTCODE | E1: LOCATIONID | F1: PLACEMENTDESC | G1: CRITICIDADE_SS | H1: SITUACAO_SS | I1: DATA_OCORRENCIA_SS | J1: DATA_ABERTURA_SS | K1: DATA_TERMINO_SS | L1: DATA_LIMITE_SS | M1: DESCRICAO_DO_ATIVO | N1: OBJSPECDESC | O1: LOCALIDADE | P1: RURA_URBANO | Q1: HRNAME | R1: TIPOSS | S1: ABRANGENCIA
A2: ETO-COEP 00092/2023 | B2: 2023 | C2: COI | D2: ETO-COEP | E2: AL05010004 | F2: 5902839004 | G2: PROGRAMAVEL | H2: SS PENDENTE | I2: 44822.053 | J2: 45230.789 | L2: 45630.789 | M2: BANCO CAPACITOR DE DISTRIBUIÇÃO GIS | N2: BANCO CAPACITOR - 13.8 | O2: ARAGUAINA | P2: URBANO | Q2: CLEBSON ALVES DUARTE | R2: INDISPONIBILIDADE PARA OPERAÇÃO
A3: ETO-COEP 00013/2023 | B3: 2023 | C3: COI | D3: ETO-COEP | E3: AL01040003 | F3: 7915029003 | G3: EMERGENCIAL | H3: SS PENDENTE | I3: 44933.08 | J3: 44953.653 | L3: 44956.653 | M3: RELIGADOR DE REDE GIS | N3: RELIGADOR DE LINHA - 27kV | O3: GURUPI | P3: URBANO | Q3: Euzilan Mateus Barreira Santos | R3: OBRAS (NOVOS EQUIPAMENTOS) | S3: 7915029003
A4: ETO-COEP 00011/2023 | B4: 2023 | D4: ETO-COEP | E4: AL02096004 | F4: 7923674004 | G4: ALTA | H4: SS PENDENTE | I4: 44936.382 | J4: 44951.737 | L4: 45011.737 | M4: LOCAL INSTAL RELIGADOR DE LINHA GIS | N4: BLOCO RELIGADOR DE LINHA | O4: ARAGUAINA | P4: RURAL | Q4: Euzilan Mateus Barreira Santos | R4: EM OPERAÇÃO COM ANOMALIA | S4: 9023675004
A5: ETO-COEP 00030/2023 | B5: 2023 | C5: COI | D5: ETO-COEP | E5: AL02003036 | F5: 5900438097 | G5: EMERGENCIAL | H5: SS PENDENTE | I5: 44948.821 | J5: 45003.563 | L5: 45006.563 | M5: BANCO CAPACITOR DE DISTRIBUIÇÃO GIS | N5: BANCO CAPACITOR - 13.8 | O5: TALISMA | P5: RURAL | Q5: CLEBSON ALVES DUARTE | R5: INDISPONIBILIDADE PARA OPERAÇÃO
A6: ETO-COEP 00063/2023 | B6: 2023 | C6: COI | D6: ETO-COEP | E6: AL01040003 | F6: 7915029003 | G6: EMERGENCIAL | H6: SS PENDENTE | I6: 45092.172 | J6: 45104.502 | L6: 45107.502 | M6: RELIGADOR DE REDE GIS | N6: RELIGADOR DE LINHA - 27kV | O6: GURUPI | P6: URBANO | Q6: Euzilan Mateus Barreira Santos | R6: OBRAS (NOVOS EQUIPAMENTOS) | S6: 7915029003
A7: ETO-COEP 00148/2025 | B7: 2025 | C7: COI | D7: ETO-COEP | E7: AL07010004 | F7: 5703627004 | G7: ALTA | H7: SS PENDENTE | I7: 45297.624 | J7: 45848.622 | L7: 45908.622 | M7: TRANSFORMADOR DE DISTRIBUIÇÃO GIS | N7: TRANSFORMADOR DE DISTRIBUIÇÃO ENERGISA 13.8Kv | O7: ARAGUAINA | P7: URBANO | Q7: LEONARDO SANTOS DA SILVA | R7: AVISO DE EMERGÊNCIA | S7: 5703627004
A8: ETO-COEP 00018/2024 | B8: 2024 | C8: COI | D8: ETO-COEP | E8: AL04059122 | F8: 5952243122 | G8: EMERGENCIAL | H8: SS PENDENTE | I8: 45340.239 | J8: 45341.67 | L8: 45344.67 | M8: BANCO CAPACITOR DE DISTRIBUIÇÃO GIS | N8: BANCO CAPACITOR - 13.8 | O8: PALMAS | P8: URBANO | Q8: CLEBSON ALVES DUARTE | R8: INDISPONIBILIDADE PARA OPERAÇÃO | S8: 0352243122
A9: ETO-COEP 00082/2025 | B9: 2025 | C9: COI | D9: ETO-COEP | E9: AL02113003 | F9: 5901886003 | G9: EMERGENCIAL | H9: SS PENDENTE | I9: 45397.508 | J9: 45785.375 | L9: 45788.375 | M9: BANCO CAPACITOR DE DISTRIBUIÇÃO GIS | N9: BANCO CAPACITOR - 13.8 | O9: GURUPI | P9: URBANO | Q9: JULIO CESAR RODRIGUES SANTANA | R9: INDISPONIBILIDADE PARA OPERAÇÃO | S9: 0301886003
A10: ETO-COEP 00058/2024 | B10: 2024 | C10: COI | D10: ETO-COEP | E10: AL03103004 | F10: 5924849004 | G10: ALTA | H10: SS PENDENTE | I10: 45406.727 | J10: 45412.487 | L10: 45472.487 | M10: BANCO CAPACITOR DE DISTRIBUIÇÃO GIS | N10: BANCO CAPACITOR - 13.8 | O10: ARAGUAINA | P10: URBANO | Q10: CLEBSON ALVES DUARTE | R10: INDISPONIBILIDADE PARA OPERAÇÃO | S10: 0324849004
A11: ETO-COEP 00060/2024 | B11: 2024 | C11: COI | D11: ETO-COEP | E11: AL05010004 | F11: 5913313004 | G11: EMERGENCIAL | H11: SS PENDENTE | I11: 45408.244 | J11: 45412.488 | L11: 45415.488 | M11: BANCO CAPACITOR DE DISTRIBUIÇÃO GIS | N11: BANCO CAPACITOR - 13.8 | O11: ARAGUAINA | P11: URBANO | Q11: Euzilan Mateus Barreira Santos | R11: INDISPONIBILIDADE PARA OPERAÇÃO | S11: 0313313004
A12: ETO-COEP 00085/2025 | B12: 2025 | C12: COI | D12: ETO-COEP | E12: AL01010004 | F12: 5903718004 | G12: EMERGENCIAL | H12: SS PENDENTE | I12: 45429.543 | J12: 45786.621 | L12: 45789.621 | M12: BANCO CAPACITOR DE DISTRIBUIÇÃO GIS | N12: BANCO CAPACITOR - 13.8 | O12: ARAGUAINA | P12: URBANO | Q12: LEONARDO SANTOS DA SILVA | R12: INDISPONIBILIDADE PARA OPERAÇÃO
A13: ETO-COEP 00084/2025 | B13: 2025 | C13: COI | D13: ETO-COEP | E13: AL02010004 | F13: 5900470004 | G13: ALTA | H13: SS PENDENTE | I13: 45429.543 | J13: 45786.62 | L13: 45846.62 | M13: BANCO CAPACITOR DE DISTRIBUIÇÃO GIS | N13: BANCO CAPACITOR - 13.8 | O13: ARAGUAINA | P13: URBANO | Q13: LEONARDO SANTOS DA SILVA | R13: INDISPONIBILIDADE PARA OPERAÇÃO
A14: ETO-COEP 00083/2024 | B14: 2024 | C14: COI | D14: ETO-COEP | E14: AL01061029 | F14: 5900064029 | G14: ALTA | H14: SS PENDENTE | I14: 45432.497 | J14: 45469.694 | L14: 45529.694 | M14: BANCO CAPACITOR DE DISTRIBUIÇÃO GIS | N14: BANCO CAPACITOR - 13.8 | O14: PALMEIROPOLIS | P14: URBANO | Q14: CLEBSON ALVES DUARTE | R14: INDISPONIBILIDADE PARA OPERAÇÃO | S14: 0300064029
A15: ETO-COEP 00109/2026 | B15: 2026 | C15: COPC | D15: ETO-COEP | E15: LD01059122 | F15: 5852775092 | G15: ALTA | H15: SS PENDENTE | I15: 45447.64 | J15: 46182.426 | L15: 46242.426 | M15: REGULADOR DE TENSÃO DE DISTRIBUIÇÃO GIS | N15: REGULADOR DE TENSAO DE DIST. - 34.5 | O15: NOVO ACORDO | P15: RURAL | Q15: Lorrane Sousa Gonçalves | R15: OBRAS (NOVOS EQUIPAMENTOS) | S15: 9007536092
A16: ETO-COEP 00146/2024 | B16: 2024 | C16: COI | D16: ETO-COEP | E16: AL03062013 | F16: 5900003013 | G16: ALTA | H16: SS PENDENTE | I16: 45537.337 | J16: 45615.441 | L16: 45675.441 | M16: BANCO CAPACITOR DE DISTRIBUIÇÃO GIS | N16: BANCO CAPACITOR - 13.8 | O16: PARAISO DO TOCANTINS | P16: RURAL | Q16: VALDENISIO FILHO RAMOS DE JESUS | R16: INDISPONIBILIDADE PARA OPERAÇÃO | S16: 0300003013
A17: ETO-COEP 00086/2026 | B17: 2026 | C17: COI | D17: ETO-COEP | E17: LD02025012 | F17: 7908686014 | G17: EMERGENCIAL | H17: SS PENDENTE | I17: 45580.697 | J17: 46136.68 | L17: 46139.68 | M17: RELIGADOR DE REDE GIS | N17: RELIGADOR DE LINHA - 38kV | O17: PIUM | P17: URBANO | Q17: VINICIUS CAMARGO COSTA | R17: INDISPONIBILIDADE PARA OPERAÇÃO | S17: 7908686014
A18: ETO-COEP 00119/2025 | B18: 2025 | C18: COPO | D18: ETO-COEP | E18: AL01048007 | F18: 7925573007 | G18: ALTA | H18: SS PENDENTE | I18: 45595.356 | J18: 45839.392 | L18: 45899.392 | M18: RELIGADOR DE REDE GIS | N18: RELIGADOR DE LINHA - 13,8kV | O18: MIRACEMA DO TOCANTINS | P18: URBANO | Q18: JULIA GRAZYELLE BRITO OLIVEIRA | R18: EM OPERAÇÃO COM ANOMALIA | S18: 7925573007
A19: ETO-COEP 00025/2026 | B19: 2026 | C19: COPC | D19: ETO-COEP | E19: AL01018071 | F19: 5854681071 | G19: ALTA | H19: SS PENDENTE | I19: 45617.606 | J19: 46051.354 | L19: 46111.354 | M19: REGULADOR DE TENSÃO DE DISTRIBUIÇÃO GIS | N19: REGULADOR DE TENSAO DE DIST. - 13.8 | O19: BREJINHO DE NAZARE | P19: URBANO | Q19: BOAVENTURA JUNIOR FERREIRA LOPE | R19: OBRAS (NOVOS EQUIPAMENTOS) | S19: 9000001071
A20: ETO-COEP 00162/2024 | B20: 2024 | C20: COI | D20: ETO-COEP | E20: AL02003036 | F20: 7936753097 | G20: EMERGENCIAL | H20: SS PENDENTE | I20: 45628.562 | J20: 45635.713 | L20: 45638.713 | M20: LOCAL INSTAL RELIGADOR DE LINHA GIS | N20: BLOCO RELIGADOR DE LINHA | O20: TALISMA | P20: RURAL | Q20: CLEBSON ALVES DUARTE | R20: OBRAS (NOVOS EQUIPAMENTOS) | S20: 9000457097
A21: ETO-COEP 00138/2025 | B21: 2025 | C21: COI | D21: ETO-COEP | E21: LD03105019 | F21: 5700008077 | G21: URGENTE | H21: SS PENDENTE | I21: 45704.365 | J21: 45841.67 | L21: 45848.67 | M21: POSTE RD GIS | N21: POSTE Concreto Duplo T | O21: GOIATINS | P21: URBANO | Q21: LEONARDO SANTOS DA SILVA | R21: SOLICITAÇÃO DE SERVIÇO | S21: 5755363077
A22: ETO-COEP 00100/2025 | B22: 2025 | C22: COI | D22: ETO-COEP | E22: LD01065015 | F22: 7900001227 | G22: EMERGENCIAL | H22: SS PENDENTE | I22: 45705.51 | J22: 45799.672 | L22: 45802.672 | M22: LOCAL INSTAL RELIGADOR DE LINHA GIS | N22: BLOCO RELIGADOR DE LINHA | O22: RECURSOLANDIA | P22: URBANO | Q22: Lorrane Sousa Gonçalves | R22: AVISO PROTEÇÃO & SELETIVIDADE | S22: 9000001227
A23: ETO-COEP 00133/2025 | B23: 2025 | C23: DEOP | D23: ETO-COEP | E23: LD04010004 | F23: 5700008159 | G23: URGENTE | H23: SS PENDENTE | I23: 45729.425 | J23: 45841.611 | L23: 45848.611 | M23: POSTE RD GIS | N23: POSTE Concreto Duplo T | O23: MURICILANDIA | P23: URBANO | Q23: LEONARDO SANTOS DA SILVA | R23: AVISO DE ANOMALIA | S23: 5700008159
A24: ETO-COEP 00158/2025 | B24: 2025 | C24: COI | D24: ETO-COEP | E24: LD03046026 | F24: 7942485096 | G24: EMERGENCIAL | H24: SS PENDENTE | I24: 45730.788 | J24: 45861.444 | L24: 45864.444 | M24: LOCAL INSTAL RELIGADOR DE LINHA GIS | N24: BLOCO RELIGADOR DE LINHA | O24: PINDORAMA DO TOCANTINS | P24: RURAL | Q24: BOAVENTURA JUNIOR FERREIRA LOPE | R24: INDISPONIBILIDADE PARA OPERAÇÃO | S24: 8800153096
A25: ETO-COEP 00089/2025 | B25: 2025 | C25: COI | D25: ETO-COEP | E25: AL02054060 | F25: 5719217060 | G25: EMERGENCIAL | H25: SS PENDENTE | I25: 45734.78 | J25: 45786.716 | L25: 45789.716 | M25: POSTE RD GIS | N25: POSTE Concreto Duplo T | O25: NOVA OLINDA | P25: URBANO | Q25: LEONARDO SANTOS DA SILVA | R25: AVISO DE ANOMALIA | S25: 5719217060
... A40: ETO-COEP 00145/2025 | B40: 2025 | C40: MANUT | D40: ETO-COEP | E40: AL04040004 | F40: 8804228004 | G40: ALTA | H40: SS PENDENTE | I40: 45769.553 | J40: 45848.621 | L40: 45908.621 | M40: POSTE RD GIS | N40: POSTE Concreto Duplo T | O40: ARAGUAINA | P40: URBANO | Q40: LEONARDO SANTOS DA SILVA | R40: AVISO DE ANOMALIA | S40: 8804228004
A41: ETO-COEP 00073/2025 | B41: 2025 | C41: COI | D41: ETO-COEP | E41: AL02060122 | F41: 5900489122 | G41: EMERGENCIAL | H41: SS PENDENTE | I41: 45770.159 | J41: 45775.684 | L41: 45778.684 | M41: BANCO CAPACITOR DE DISTRIBUIÇÃO GIS | N41: BANCO CAPACITOR - 13.8 | O41: PALMAS | P41: URBANO | Q41: CLEBSON ALVES DUARTE | R41: INDISPONIBILIDADE PARA OPERAÇÃO
A42: ETO-COEP 00074/2025 | B42: 2025 | C42: COI | D42: ETO-COEP | E42: AL06059122 | F42: 5952202122 | G42: EMERGENCIAL | H42: SS PENDENTE | I42: 45771.194 | J42: 45775.699 | L42: 45778.699 | M42: BANCO CAPACITOR DE DISTRIBUIÇÃO GIS | N42: BANCO CAPACITOR - 13.8 | O42: PALMAS | P42: URBANO | Q42: CLEBSON ALVES DUARTE | R42: INDISPONIBILIDADE PARA OPERAÇÃO | S42: 8800388122
A43: ETO-COEP 00075/2025 | B43: 2025 | C43: COI | D43: ETO-COEP | E43: AL07060122 | F43: 5952327122 | G43: EMERGENCIAL | H43: SS PENDENTE | I43: 45771.216 | J43: 45775.701 | L43: 45778.701 | M43: BANCO CAPACITOR DE DISTRIBUIÇÃO GIS | N43: BANCO CAPACITOR - 13.8 | O43: PALMAS | P43: URBANO | Q43: CLEBSON ALVES DUARTE | R43: INDISPONIBILIDADE PARA OPERAÇÃO | S43: 0352228122
A44: ETO-COEP 00076/2025 | B44: 2025 | C44: COI | D44: ETO-COEP | E44: AL08059122 | F44: 5951650122 | G44: EMERGENCIAL | H44: SS PENDENTE | I44: 45772.238 | J44: 45775.702 | L44: 45778.702 | M44: BANCO CAPACITOR DE DISTRIBUIÇÃO GIS | N44: BANCO CAPACITOR - 13.8 | O44: PALMAS | P44: URBANO | Q44: CLEBSON ALVES DUARTE | R44: INDISPONIBILIDADE PARA OPERAÇÃO | S44: 8800777122
A45: ETO-COEP 00079/2025 | B45: 2025 | C45: COI | D45: ETO-COEP | E45: LD02059122 | F45: 7923927122 | G45: EMERGENCIAL | H45: SS PENDENTE | I45: 45774.462 | J45: 45776.576 | L45: 45779.576 | M45: LOCAL INSTAL RELIGADOR DE LINHA GIS | N45: BLOCO RELIGADOR DE LINHA | O45: PALMAS | P45: RURAL | Q45: CLEBSON ALVES DUARTE | R45: INDISPONIBILIDADE PARA OPERAÇÃO | S45: 9023928122
A46: ETO-COEP 00147/2025 | B46: 2025 | C46: COI | D46: ETO-COEP | E46: AL01040004 | F46: 5703750004 | G46: ALTA | H46: SS PENDENTE | I46: 45775.601 | J46: 45848.622 | L46: 45908.622 | M46: POSTE RD GIS | N46: POSTE Concreto Duplo T | O46: ARAGUAINA | P46: URBANO | Q46: LEONARDO SANTOS DA SILVA | R46: AVISO DE ANOMALIA | S46: 5703750004
A47: ETO-COEP 00077/2025 | B47: 2025 | C47: COCM | D47: ETO-COEP | E47: AL05060122 | F47: 5907243122 | G47: EMERGENCIAL | H47: SS PENDENTE | I47: 45775.706 | J47: 45775.706 | L47: 45778.706 | M47: BANCO CAPACITOR DE DISTRIBUIÇÃO GIS | N47: BANCO CAPACITOR - 13.8 | O47: PALMAS | P47: URBANO | Q47: CLEBSON ALVES DUARTE | R47: INDISPONIBILIDADE PARA OPERAÇÃO | S47: 0307243122
A48: ETO-COEP 00103/2025 | B48: 2025 | C48: COI | D48: ETO-COEP | E48: LD02059122 | F48: 7910027196 | G48: EMERGENCIAL | H48: SS PENDENTE | I48: 45785.415 | J48: 45804.75 | L48: 45807.75 | M48: LOCAL INSTAL RELIGADOR DE LINHA GIS | N48: BLOCO RELIGADOR DE LINHA | O48: LAGOA DO TOCANTINS | P48: URBANO | Q48: ZENILSON MOREIRA SANTOS | R48: INDISPONIBILIDADE PARA OPERAÇÃO | S48: 9000347196
A49: ETO-COEP 00095/2025 | B49: 2025 | C49: COI | D49: ETO-COEP | E49: AL02010004 | F49: 5955192004 | G49: EMERGENCIAL | H49: SS PENDENTE | I49: 45790.172 | J49: 45790.313 | L49: 45793.313 | M49: BANCO CAPACITOR DE DISTRIBUIÇÃO GIS | N49: BANCO CAPACITOR - 13.8 | O49: ARAGUAINA | P49: URBANO | Q49: LEONARDO SANTOS DA SILVA | R49: NOTA DE SERVIÇO (NS) - LINHA VIVA | S49: 0355192004
A50: ETO-COEP 00101/2025 | B50: 2025 | C50: MANUT | D50: ETO-COEP | E50: LD02066094 | F50: 5855776094 | G50: URGENTE | H50: SS PENDENTE | I50: 45803.466 | J50: 45803.466 | L50: 45810.466 | M50: REGULADOR DE TENSÃO DE DISTRIBUIÇÃO GIS | N50: REGULADOR DE TENSAO DE DIST. - 34.5 | O50: PEIXE | P50: RURAL | Q50: Lorrane Sousa Gonçalves | R50: SOLICITAÇÃO DE SERVIÇO | S50: 8800173094
A51: ETO-COEP 00102/2025 | B51: 2025 | C51: MANUT | D51: ETO-COEP | E51: LD02010004 | F51: 7900532053 | G51: ALTA | H51: SS PENDENTE | I51: 45803.621 | J51: 45803.621 | L51: 45863.621 | M51: RELIGADOR DE REDE GIS | N51: RELIGADOR DE LINHA - 38kV | O51: PIRAQUE | P51: URBANO | Q51: EDNA MARIA DOS SANTOS PINTO | R51: INDISPONIBILIDADE PARA OPERAÇÃO
A52: ETO-COEP 00179/2025 | B52: 2025 | C52: MANUT | D52: ETO-COEP | E52: AL03109039 | F52: 7922995039 | G52: PROGRAMAVEL | H52: SS PENDENTE | I52: 45806.446 | J52: 45902.449 | L52: 46302.449 | M52: RELIGADOR DE REDE GIS | N52: RELIGADOR DE LINHA - 13,8kV | O52: ARAGUATINS | P52: RURAL | Q52: Allan Pereira de Souza | R52: INDISPONIBILIDADE PARA OPERAÇÃO | S52: 7922995039
A53: ETO-COEP 00162/2025 | B53: 2025 | C53: MANUT | D53: ETO-COEP | E53: LD02109039 | F53: 7928564039 | G53: ALTA | H53: SS PENDENTE | I53: 45806.453 | J53: 45866.659 | L53: 45926.659 | M53: RELIGADOR DE REDE GIS | N53: RELIGADOR DE LINHA - 38kV | O53: ARAGUATINS | P53: RURAL | Q53: Allan Pereira de Souza | R53: INDISPONIBILIDADE PARA OPERAÇÃO | S53: 7928564039
A54: ETO-COEP 00120/2025 | B54: 2025 | C54: COI | D54: ETO-COEP | E54: LD01084002 | F54: 7920024127 | G54: EMERGENCIAL | H54: SS PENDENTE | I54: 45810.34 | J54: 45839.597 | L54: 45842.597 | M54: LOCAL INSTAL RELIGADOR DE LINHA GIS | N54: BLOCO RELIGADOR DE LINHA | O54: PALMEIRAS DO TOCANTINS | P54: URBANO | Q54: Allan Pereira de Souza | R54: INDISPONIBILIDADE PARA OPERAÇÃO | S54: 9001177127
A55: ETO-COEP 00135/2025 | B55: 2025 | C55: COI | D55: ETO-COEP | E55: AL06010004 | F55: 0303612004 | G55: EMERGENCIAL | H55: SS PENDENTE | I55: 45810.457 | J55: 45841.611 | L55: 45844.611 | M55: POSTE RD GIS | N55: POSTE Concreto Duplo T | O55: ARAGUAINA | P55: URBANO | Q55: LEONARDO SANTOS DA SILVA | R55: AVISO DE ANOMALIA | S55: 8859685004
A56: ETO-COEP 00156/2025 | B56: 2025 | C56: COI | D56: ETO-COEP | E56: LD04062013 | F56: 7957126085 | G56: EMERGENCIAL | H56: SS PENDENTE | I56: 45813.568 | J56: 45860.721 | L56: 45863.721 | M56: RELIGADOR DE REDE GIS | N56: RELIGADOR DE LINHA - 38kV | O56: MONTE SANTO DO TOCANTINS | P56: URBANO | Q56: VINICIUS CAMARGO COSTA | R56: INDISPONIBILIDADE PARA OPERAÇÃO | S56: 7957126085
A57: ETO-COEP 00109/2025 | B57: 2025 | C57: COI | D57: ETO-COEP | E57: AL01018071 | F57: 5946473071 | G57: EMERGENCIAL | H57: SS PENDENTE | I57: 45813.687 | J57: 45817.572 | L57: 45820.572 | M57: BANCO CAPACITOR DE DISTRIBUIÇÃO GIS | N57: BANCO CAPACITOR - 13.8 | O57: BREJINHO DE NAZARE | P57: RURAL | Q57: CARLOS ANDRE RODRIGUES BASTOS | R57: NOTA DE SERVIÇO (NS) - LINHA VIVA
A58: ETO-COEP 00108/2025 | B58: 2025 | C58: COI | D58: ETO-COEP | E58: AL01018071 | F58: 5946472071 | G58: EMERGENCIAL | H58: SS PENDENTE | I58: 45813.687 | J58: 45817.571 | L58: 45820.571 | M58: BANCO CAPACITOR DE DISTRIBUIÇÃO GIS | N58: BANCO CAPACITOR - 13.8 | O58: BREJINHO DE NAZARE | P58: RURAL | Q58: BOAVENTURA JUNIOR FERREIRA LOPE | R58: NOTA DE SERVIÇO (NS) - LINHA VIVA
A59: ETO-COEP 00131/2025 | B59: 2025 | C59: COI | D59: ETO-COEP | E59: AL01065015 | F59: 5700232011 | G59: PROGRAMAVEL | H59: SS PENDENTE | I59: 45815.711 | J59: 45841.61 | L59: 46241.61 | M59: POSTE RD GIS | N59: POSTE Concreto Duplo T | O59: TUPIRAMA | P59: URBANO | Q59: KELLITON PEREIRA MARTINS | R59: FORMS SUBST DE POSTES | S59: 5700232011
A60: ETO-COEP 00055/2026 | B60: 2026 | C60: COPC | D60: ETO-COEP | E60: LD04002091 | F60: 5856156091 | G60: PROGRAMAVEL | H60: SS PENDENTE | I60: 45824.66 | J60: 46107.488 | L60: 46507.488 | M60: REGULADOR DE TENSÃO DE DISTRIBUIÇÃO GIS | N60: REGULADOR DE TENSAO DE DIST. - 34.5 | O60: ALMAS | P60: RURAL | Q60: DENER SOARES DE ALBUQUERQUE | R60: INDISPONIBILIDADE PARA OPERAÇÃO | S60: 8832258091
A61: ETO-COEP 00141/2025 | B61: 2025 | C61: COI | D61: ETO-COEP | E61: DESATIVADA | F61: 2ARM-004-7900930040 | G61: EMERGENCIAL | H61: SS PENDENTE | I61: 45828.377 | J61: 45845.617 | L61: 45848.617 | M61: RELIGADOR | N61: Ativos descartados que não permitem exclusão | Q61: EDNA MARIA DOS SANTOS PINTO | R61: INDISPONIBILIDADE PARA OPERAÇÃO
A62: ETO-COEP 00163/2025 | B62: 2025 | C62: COI | D62: ETO-COEP | E62: LD01065015 | F62: 7931219078 | G62: EMERGENCIAL | H62: SS PENDENTE | I62: 45831.37 | J62: 45867.432 | L62: 45870.432 | M62: LOCAL INSTAL RELIGADOR DE LINHA GIS | N62: BLOCO RELIGADOR DE LINHA | O62: ITACAJA | P62: RURAL | Q62: Lorrane Sousa Gonçalves | R62: EM OPERAÇÃO COM ANOMALIA | S62: 9000475078
A63: ETO-COEP 00114/2025 | B63: 2025 | C63: MANUT | D63: ETO-COEP | E63: AL01044024 | F63: 7900275024 | G63: PROGRAMAVEL | H63: SS PENDENTE | I63: 45831.446 | J63: 45831.446 | L63: 46231.446 | M63: RELIGADOR DE REDE GIS | N63: RELIGADOR DE LINHA - 19 | O63: ITAPORA DO TOCANTINS | P63: URBANO | Q63: EDNA MARIA DOS SANTOS PINTO | R63: SOLICITAÇÃO DE SERVIÇO | S63: 7900275024
A64: ETO-COEP 00115/2025 | B64: 2025 | C64: MANUT | D64: ETO-COEP | E64: AL01008032 | F64: 7901216032 | G64: PROGRAMAVEL | H64: SS PENDENTE | I64: 45831.496 | J64: 45831.496 | L64: 46231.496 | M64: RELIGADOR DE REDE GIS | N64: RELIGADOR DE LINHA - 19 | O64: ARAGUACU | P64: RURAL | Q64: EDNA MARIA DOS SANTOS PINTO | R64: SOLICITAÇÃO DE SERVIÇO | S64: 7901216032
A65: ETO-COEP 00143/2025 | B65: 2025 | C65: COI | D65: ETO-COEP | E65: LD02072001 | F65: 7927446001 | G65: EMERGENCIAL | H65: SS PENDENTE | I65: 45834.09 | J65: 45846.727 | L65: 45849.727 | M65: LOCAL INSTAL RELIGADOR DE LINHA GIS | N65: BLOCO RELIGADOR DE LINHA | O65: PORTO NACIONAL | P65: RURAL | Q65: Allan Pereira de Souza | R65: INDISPONIBILIDADE PARA OPERAÇÃO | S65: 9027446001
A66: ETO-COEP 00151/2025 | B66: 2025 | C66: COI | D66: ETO-COEP | E66: LD01100001 | F66: 7930428001 | G66: EMERGENCIAL | H66: SS PENDENTE | I66: 45839.85 | J66: 45854.411 | L66: 45857.411 | M66: LOCAL INSTAL RELIGADOR DE LINHA GIS | N66: BLOCO RELIGADOR DE LINHA | O66: PORTO NACIONAL | P66: RURAL | Q66: BOAVENTURA JUNIOR FERREIRA LOPE | R66: INDISPONIBILIDADE PARA OPERAÇÃO | S66: 9030428001
A67: ETO-COEP 00084/2026 | B67: 2026 | C67: COI | D67: ETO-COEP | E67: AL01062013 | F67: 7900117013 | G67: ALTA | H67: SS PENDENTE | I67: 45840.551 | J67: 46136.678 | L67: 46196.678 | M67: RELIGADOR DE REDE GIS | N67: RELIGADOR DE LINHA - 15,0kV | O67: PARAISO DO TOCANTINS | P67: URBANO | Q67: VINICIUS CAMARGO COSTA | R67: INDISPONIBILIDADE PARA OPERAÇÃO | S67: 7900117013
A68: ETO-COEP 00170/2025 | B68: 2025 | C68: COPC | D68: ETO-COEP | E68: LD01020023 | F68: 5863381155 | G68: ALTA | H68: SS PENDENTE | I68: 45841.411 | J68: 45882.678 | L68: 45942.678 | M68: REGULADOR DE TENSÃO DE DISTRIBUIÇÃO GIS | N68: REGULADOR DE TENSAO DE DIST. - 34.5 | O68: PALMEIRANTE | P68: RURAL | Q68: EDNA MARIA DOS SANTOS PINTO | R68: COMISSIONAMENTO | S68: 8800518155
A69: ETO-COEP 00139/2025 | B69: 2025 | C69: MANUT | D69: ETO-COEP | E69: LD02066094 | F69: 7928241200 | G69: ALTA | H69: SS PENDENTE | I69: 45842.454 | J69: 45842.454 | L69: 45902.454 | M69: LOCAL INSTAL RELIGADOR DE LINHA GIS | N69: BLOCO RELIGADOR DE LINHA | O69: SAO SALVADOR DO TOCANTINS | P69: RURAL | Q69: Allan Pereira de Souza | R69: INDISPONIBILIDADE PARA OPERAÇÃO | S69: 9000422200
A70: ETO-COEP 00140/2025 | B70: 2025 | C70: COI | D70: ETO-COEP | E70: AL01036052 | F70: 5900129052 | G70: EMERGENCIAL | H70: SS PENDENTE | I70: 45845.358 | J70: 45845.421 | L70: 45848.421 | M70: BANCO CAPACITOR DE DISTRIBUIÇÃO GIS | N70: BANCO CAPACITOR - 13.8 | O70: FORMOSO DO ARAGUAIA | P70: URBANO | Q70: JULIO CESAR RODRIGUES SANTANA | R70: AVISO DE ANOMALIA | S70: 0300129052
A71: ETO-COEP 00149/2025 | B71: 2025 | C71: COI | D71: ETO-COEP | E71: LD04002091 | F71: 7955520116 | G71: EMERGENCIAL | H71: SS PENDENTE | I71: 45849.445 | J71: 45849.445 | L71: 45852.445 | M71: LOCAL INSTAL RELIGADOR DE LINHA GIS | N71: BLOCO RELIGADOR DE LINHA | O71: CHAPADA DA NATIVIDADE | P71: RURAL | Q71: Allan Pereira de Souza | R71: INDISPONIBILIDADE PARA OPERAÇÃO | S71: 3333967116
A72: ETO-COEP 00175/2025 | B72: 2025 | C72: COI | D72: ETO-COEP | E72: AL01084002 | F72: 5900010002 | G72: URGENTE | H72: SS PENDENTE | I72: 45850.235 | J72: 45896.338 | L72: 45903.338 | M72: BANCO CAPACITOR DE DISTRIBUIÇÃO GIS | N72: BANCO CAPACITOR - 13.8 | O72: TOCANTINOPOLIS | P72: URBANO | Q72: HELIOMAR PEREIRA SANTOS | R72: AVISO DE ANOMALIA | S72: 0300010002
A73: ETO-COEP 00089/2026 | B73: 2026 | C73: MANUT | D73: ETO-COEP | E73: AL01015049 | F73: 7908705049 | G73: PROGRAMAVEL | H73: SS PENDENTE | I73: 45854.333 | J73: 46142.647 | L73: 46542.647 | M73: LOCAL INSTAL RELIGADOR DE LINHA GIS | N73: BLOCO RELIGADOR DE LINHA | O73: AURORA DO TOCANTINS | P73: RURAL | Q73: DENER SOARES DE ALBUQUERQUE | R73: INDISPONIBILIDADE PARA OPERAÇÃO | S73: 0908705049
A74: ETO-COEP 00176/2025 | B74: 2025 | C74: COPC | D74: ETO-COEP | E74: LD02038009 | F74: 5860500009 | G74: ALTA | H74: SS PENDENTE | I74: 45855.431 | J74: 45898.37 | L74: 45958.37 | M74: REGULADOR DE TENSÃO DE DISTRIBUIÇÃO GIS | N74: REGULADOR DE TENSAO DE DIST. - 34.5 | O74: GUARAI | P74: RURAL | Q74: EDNA MARIA DOS SANTOS PINTO | R74: COMISSIONAMENTO | S74: 7960498009
A75: ETO-COEP 00056/2026 | B75: 2026 | C75: COI | D75: ETO-COEP | E75: LD04002091 | F75: 5856070091 | G75: BAIXA | H75: SS PENDENTE | I75: 45856.459 | J75: 46107.489 | L75: 46287.489 | M75: REGULADOR DE TENSÃO DE DISTRIBUIÇÃO GIS | N75: REGULADOR DE TENSAO DE DIST. - 34.5 | O75: ALMAS | P75: RURAL | Q75: DENER SOARES DE ALBUQUERQUE | R75: INDISPONIBILIDADE PARA OPERAÇÃO
A76: ETO-COEP 00171/2025 | B76: 2025 | C76: COI | D76: ETO-COEP | E76: LD04002091 | F76: 5800438116 | G76: EMERGENCIAL | H76: SS PENDENTE | I76: 45856.5 | J76: 45888.63 | L76: 45891.63 | M76: REGULADOR DE TENSÃO DE DISTRIBUIÇÃO GIS | N76: REGULADOR DE TENSAO DE DIST. - 34.5 | O76: CHAPADA DA NATIVIDADE | P76: RURAL | Q76: Lorrane Sousa Gonçalves | R76: INDISPONIBILIDADE PARA OPERAÇÃO | S76: 9000387116
A77: ETO-COEP 00160/2025 | B77: 2025 | C77: COI | D77: ETO-COEP | E77: LD02072001 | F77: 5854566043 | G77: EMERGENCIAL | H77: SS PENDENTE | I77: 45861.951 | J77: 45863.592 | L77: 45866.592 | M77: REGULADOR DE TENSÃO DE DISTRIBUIÇÃO GIS | N77: REGULADOR DE TENSAO DE DIST. - 34.5 | O77: SILVANOPOLIS | P77: RURAL | Q77: Allan Pereira de Souza | R77: INDISPONIBILIDADE PARA OPERAÇÃO
A78: ETO-COEP 00189/2025 | B78: 2025 | C78: MANUT | D78: ETO-COEP | E78: LD03038009 | F78: 7925704079 | G78: PROGRAMAVEL | H78: SS PENDENTE | I78: 45863.391 | J78: 45915.714 | L78: 46315.714 | M78: RELIGADOR DE REDE GIS | N78: RELIGADOR DE LINHA - 34,5kV | O78: ITAPIRATINS | P78: RURAL | Q78: Allan Pereira de Souza | R78: EM OPERAÇÃO COM ANOMALIA | S78: 7925704079
A79: ETO-COEP 00200/2025 | B79: 2025 | C79: COI | D79: ETO-COEP | E79: AL01012025 | F79: 5700026025 | G79: PROGRAMAVEL | H79: SS PENDENTE | I79: 45868.901 | J79: 45931.364 | L79: 46331.364 | M79: LOCAL INSTAL TRANSFORMADOR DE DISTRIBUIÇÃO GIS | N79: BLOCO TRANSFORMADOR DE DISTRIBUIÇÃO | O79: ARAPOEMA | P79: URBANO | Q79: LEONARDO SANTOS DA SILVA | R79: SOLICITAÇÃO DE SERVIÇO | S79: 0300025025
A80: ETO-COEP 00167/2025 | B80: 2025 | C80: COI | D80: ETO-COEP | E80: AL01054060 | F80: 5844630060 | G80: EMERGENCIAL | H80: SS PENDENTE | I80: 45875.954 | J80: 45877.703 | L80: 45880.703 | M80: REGULADOR DE TENSÃO DE DISTRIBUIÇÃO GIS | N80: REGULADOR DE TENSAO DE DIST. - 13.8 | O80: NOVA OLINDA | P80: RURAL | Q80: Allan Pereira de Souza | R80: INDISPONIBILIDADE PARA OPERAÇÃO | S80: 9001931060
A81: ETO-COEP 00173/2025 | B81: 2025 | C81: COI | D81: ETO-COEP | E81: LD03010004 | F81: 7900535058 | G81: EMERGENCIAL | H81: SS PENDENTE | I81: 45877.724 | J81: 45894.368 | L81: 45897.368 | M81: RELIGADOR DE REDE GIS | N81: RELIGADOR DE LINHA - 38kV | O81: SANTA FE DO ARAGUAIA | P81: RURAL | Q81: EDNA MARIA DOS SANTOS PINTO | R81: INDISPONIBILIDADE PARA OPERAÇÃO | S81: 7900535058
A82: ETO-COEP 00180/2025 | B82: 2025 | C82: COI | D82: ETO-COEP | E82: AL01038009 | F82: 5850308009 | G82: EMERGENCIAL | H82: SS PENDENTE | I82: 45884.035 | J82: 45902.608 | L82: 45905.608 | M82: REGULADOR DE TENSÃO DE DISTRIBUIÇÃO GIS | N82: REGULADOR DE TENSAO DE DIST. - 13.8 | O82: GUARAI | P82: URBANO | Q82: Allan Pereira de Souza | R82: INDISPONIBILIDADE PARA OPERAÇÃO | S82: AL01038009
A83: ETO-COEP 00182/2025 | B83: 2025 | D83: ETO-COEP | E83: LD02036052 | F83: 5855643052 | G83: EMERGENCIAL | H83: SS PENDENTE | I83: 45888.429 | J83: 45903.488 | L83: 45906.488 | M83: REGULADOR DE TENSÃO DE DISTRIBUIÇÃO GIS | N83: REGULADOR DE TENSAO DE DIST. - 34.5 | O83: FORMOSO DO ARAGUAIA | P83: RURAL | Q83: VINICIUS CAMARGO COSTA | R83: EM OPERAÇÃO COM ANOMALIA | S83: 8801154052
A84: ETO-COEP 00208/2025 | B84: 2025 | C84: COI | D84: ETO-COEP | E84: LD02050008 | F84: 7955430075 | G84: EMERGENCIAL | H84: SS PENDENTE | I84: 45889.403 | J84: 45947.669 | L84: 45950.669 | M84: RELIGADOR DE REDE GIS | N84: RELIGADOR DE LINHA - 38kV | O84: DOIS IRMAOS DO TOCANTINS | P84: RURAL | Q84: VINICIUS CAMARGO COSTA | R84: INDISPONIBILIDADE PARA OPERAÇÃO | S84: 7955430075
A85: ETO-COEP 00193/2025 | B85: 2025 | C85: COI | D85: ETO-COEP | E85: AL02054060 | F85: 5719217060 | G85: PROGRAMAVEL | H85: SS PENDENTE | I85: 45889.687 | J85: 45924.416 | L85: 46324.416 | M85: POSTE RD GIS | N85: POSTE Concreto Duplo T | O85: NOVA OLINDA | P85: URBANO | Q85: LEONARDO SANTOS DA SILVA | R85: AVISO DE ANOMALIA | S85: 5719217060
A86: ETO-COEP 00187/2025 | B86: 2025 | C86: COI | D86: ETO-COEP | E86: LD02010153 | F86: 5800371025 | G86: EMERGENCIAL | H86: SS PENDENTE | I86: 45892.049 | J86: 45905.614 | L86: 45908.614 | M86: REGULADOR DE TENSÃO DE DISTRIBUIÇÃO GIS | N86: REGULADOR DE TENSAO DE DIST. - 34.5 | O86: ARAPOEMA | P86: URBANO | Q86: Allan Pereira de Souza | R86: INDISPONIBILIDADE PARA OPERAÇÃO | S86: 9000370025
A87: ETO-COEP 00216/2025 | B87: 2025 | C87: MANUT | D87: ETO-COEP | E87: LD01062013 | F87: 5827102054 | G87: ALTA | H87: SS PENDENTE | I87: 45896.684 | J87: 45959.634 | L87: 46019.634 | M87: REGULADOR DE TENSÃO DE DISTRIBUIÇÃO GIS | N87: REGULADOR DE TENSAO DE DIST. - 34.5 | O87: PUGMIL | P87: RURAL | Q87: Allan Pereira de Souza | R87: INDISPONIBILIDADE PARA OPERAÇÃO | S87: 9000260054
A88: ETO-COEP 00192/2025 | B88: 2025 | C88: DEOP | D88: ETO-COEP | E88: AL07010004 | F88: 5704256004 | G88: EMERGENCIAL | H88: SS PENDENTE | I88: 45901.704 | J88: 45924.41 | L88: 45927.41 | M88: POSTE RD GIS | N88: POSTE Concreto Duplo T | O88: ARAGUAINA | P88: URBANO | Q88: LEONARDO SANTOS DA SILVA | R88: AVISO DE CADASTRO | S88: 5704256004
A89: ETO-COEP 00199/2025 | B89: 2025 | C89: COI | D89: ETO-COEP | E89: AL02017017 | F89: 5855411017 | G89: EMERGENCIAL | H89: SS PENDENTE | I89: 45903.507 | J89: 45930.615 | L89: 45933.615 | M89: REGULADOR DE TENSÃO DE DISTRIBUIÇÃO GIS | N89: REGULADOR DE TENSAO DE DIST. - 13.8 | O89: BARROLANDIA | P89: RURAL | Q89: JULIA GRAZYELLE BRITO OLIVEIRA | R89: INDISPONIBILIDADE PARA OPERAÇÃO | S89: 0320187017
A90: ETO-COEP 00184/2025 | B90: 2025 | C90: MANUT | D90: ETO-COEP | E90: LD05010004 | F90: 7903112004 | G90: PROGRAMAVEL | H90: SS PENDENTE | I90: 45903.681 | J90: 45903.725 | L90: 46303.725 | M90: RELIGADOR DE REDE GIS | N90: RELIGADOR DE LINHA - 38kV | O90: ARAGUAINA | P90: RURAL | Q90: EDNA MARIA DOS SANTOS PINTO | R90: INDISPONIBILIDADE PARA OPERAÇÃO | S90: 7903112004
A91: ETO-COEP 00021/2026 | B91: 2026 | C91: COI | D91: ETO-COEP | E91: AL01102271 | F91: 5803327001 | G91: EMERGENCIAL | H91: SS PENDENTE | I91: 45904.9 | J91: 46044.492 | L91: 46047.492 | M91: REGULADOR DE TENSÃO DE DISTRIBUIÇÃO GIS | N91: REGULADOR DE TENSAO DE DIST. - 13.8 | O91: PORTO NACIONAL | P91: RURAL | Q91: Allan Pereira de Souza | R91: INDISPONIBILIDADE PARA OPERAÇÃO | S91: 8851077001
A92: ETO-COEP 00005/2026 | B92: 2026 | C92: COCM | D92: ETO-COEP | E92: AL02010004 | F92: 5700440004 | G92: ALTA | H92: SS PENDENTE | I92: 45905.393 | J92: 46036.653 | L92: 46096.653 | M92: TRANSFORMADOR DE DISTRIBUIÇÃO GIS | N92: TRANSFORMADOR DE DISTRIBUIÇÃO ENERGISA 13.8Kv | O92: ARAGUAINA | P92: URBANO | Q92: LEONARDO SANTOS DA SILVA | R92: AVISO DE ANOMALIA | S92: 5700440004
A93: ETO-COEP 00198/2025 | B93: 2025 | C93: COPC | D93: ETO-COEP | E93: AL03072001 | F93: 5835587001 | G93: ALTA | H93: SS PENDENTE | I93: 45909.703 | J93: 45930.604 | L93: 45990.604 | M93: REGULADOR DE TENSÃO DE DISTRIBUIÇÃO GIS | N93: REGULADOR DE TENSAO DE DIST. - 13.8 | O93: PORTO NACIONAL | P93: RURAL | Q93: JULIA GRAZYELLE BRITO OLIVEIRA | R93: COMISSIONAMENTO | S93: 3103141001
A94: ETO-COEP 00006/2026 | B94: 2026 | C94: DEOP | D94: ETO-COEP | E94: AL03010004 | F94: 5700244004 | G94: ALTA | H94: SS PENDENTE | I94: 45910.714 | J94: 46036.653 | L94: 46096.653 | M94: POSTE RD GIS | N94: POSTE Madeira Circular | O94: ARAGUAINA | P94: URBANO | Q94: LEONARDO SANTOS DA SILVA | R94: AVISO DE ANOMALIA | S94: 5700244004
A95: ETO-COEP 00047/2026 | B95: 2026 | C95: COI | D95: ETO-COEP | E95: AL05097122 | F95: 5950106122 | G95: EMERGENCIAL | H95: SS PENDENTE | I95: 45920.877 | J95: 46092.344 | L95: 46095.344 | M95: BANCO CAPACITOR DE DISTRIBUIÇÃO GIS | N95: BANCO CAPACITOR - 13.8 | O95: PALMAS | P95: URBANO | Q95: MARCELO COSTA PRIMO | R95: AVISO DE ANOMALIA | S95: 0350106122
... A125: ETO-COEP 00059/2026 | B125: 2026 | C125: COI | D125: ETO-COEP | E125: LD02022033 | F125: 7925744087 | G125: EMERGENCIAL | H125: SS PENDENTE | I125: 46062.991 | J125: 46111.432 | L125: 46114.432 | M125: LOCAL INSTAL RELIGADOR DE LINHA GIS | N125: BLOCO RELIGADOR DE LINHA | O125: GOIANORTE | P125: URBANO | Q125: LARA SOARES FARIAS | R125: INDISPONIBILIDADE PARA OPERAÇÃO | S125: 9025744087
A126: ETO-COEP 00031/2026 | B126: 2026 | D126: ETO-COEP | E126: AL03010004 | F126: 5701123004 | G126: URGENTE | H126: SS PENDENTE | I126: 46063.369 | J126: 46063.427 | L126: 46070.427 | M126: LOCAL INSTAL TRANSFORMADOR DE DISTRIBUIÇÃO GIS | N126: BLOCO TRANSFORMADOR DE DISTRIBUIÇÃO | O126: ARAGUAINA | P126: URBANO | Q126: LEONARDO SANTOS DA SILVA | R126: MELHORIA POSTO DE TRANSFORMAÇÃO | S126: 8804224004
A127: ETO-COEP 00088/2026 | B127: 2026 | C127: COI | D127: ETO-COEP | E127: LD01025012 | F127: 7921202014 | G127: EMERGENCIAL | H127: SS PENDENTE | I127: 46068.858 | J127: 46140.618 | L127: 46143.618 | M127: RELIGADOR | N127: RELIGADOR 34,5 KV | Q127: Allan Pereira de Souza | R127: INDISPONIBILIDADE PARA OPERAÇÃO | S127: 7921202014
A128: ETO-COEP 00035/2026 | B128: 2026 | C128: COI | D128: ETO-COEP | E128: LD03010004 | F128: 8800416159 | G128: EMERGENCIAL | H128: SS PENDENTE | I128: 46069.233 | J128: 46071.638 | L128: 46074.638 | M128: POSTE RD GIS | N128: POSTE Concreto Duplo T | O128: MURICILANDIA | P128: RURAL | Q128: RICARDO DA CONCEICAO MOURA | R128: NOTA DE SERVIÇO (NS) - LINHA VIVA | S128: 8800416159
A129: ETO-COEP 00050/2026 | B129: 2026 | C129: COI | D129: ETO-COEP | E129: LD03046026 | F129: 7953610256 | G129: EMERGENCIAL | H129: SS PENDENTE | I129: 46069.238 | J129: 46099.673 | L129: 46102.673 | M129: LOCAL INSTAL RELIGADOR DE LINHA GIS | N129: BLOCO RELIGADOR DE LINHA | O129: MATEIROS | P129: RURAL | Q129: JULIA GRAZYELLE BRITO OLIVEIRA | R129: INDISPONIBILIDADE PARA OPERAÇÃO | S129: 8800246256
A130: ETO-COEP 00045/2026 | B130: 2026 | C130: COI | D130: ETO-COEP | E130: LD03036052 | F130: 7927396052 | G130: EMERGENCIAL | H130: SS PENDENTE | I130: 46070.793 | J130: 46083.893 | L130: 46086.893 | M130: LOCAL INSTAL RELIGADOR DE LINHA GIS | N130: BLOCO RELIGADOR DE LINHA | O130: FORMOSO DO ARAGUAIA | P130: RURAL | Q130: EDNA MARIA DOS SANTOS PINTO | R130: INDISPONIBILIDADE PARA OPERAÇÃO | S130: 9001632052
A131: ETO-COEP 00051/2026 | B131: 2026 | C131: COI | D131: ETO-COEP | E131: LD01051035 | F131: 7926442035 | G131: EMERGENCIAL | H131: SS PENDENTE | I131: 46071.684 | J131: 46099.677 | L131: 46102.677 | M131: RELIGADOR DE REDE GIS | N131: RELIGADOR DE LINHA - 34,5kV | O131: MONTE DO CARMO | P131: RURAL | Q131: JULIA GRAZYELLE BRITO OLIVEIRA | R131: INDISPONIBILIDADE PARA OPERAÇÃO | S131: 7926442035
A132: ETO-COEP 00074/2026 | B132: 2026 | C132: COPC | D132: ETO-COEP | E132: LD01047073 | F132: 7919270014 | G132: ALTA | H132: SS PENDENTE | I132: 46078.448 | J132: 46129.383 | L132: 46189.383 | M132: LOCAL INSTAL RELIGADOR DE LINHA GIS | N132: BLOCO RELIGADOR DE LINHA | O132: LAGOA DA CONFUSAO | P132: RURAL | Q132: ZENILSON MOREIRA SANTOS | R132: INDISPONIBILIDADE PARA OPERAÇÃO | S132: 8801059073
A133: ETO-COEP 00042/2026 | B133: 2026 | C133: MANUT | D133: ETO-COEP | E133: LD03046026 | F133: 7900505026 | G133: ALTA | H133: SS PENDENTE | I133: 46079.437 | J133: 46079.437 | L133: 46139.437 | M133: RELIGADOR DE REDE GIS | N133: RELIGADOR DE LINHA - 38kV | O133: PONTE ALTA DO TOCANTINS | P133: RURAL | Q133: Allan Pereira de Souza | R133: EM OPERAÇÃO COM ANOMALIA | S133: 7900505026
A134: ETO-COEP 00043/2026 | B134: 2026 | C134: COPO | D134: ETO-COEP | E134: LD02065015 | F134: 8801170015 | G134: ALTA | H134: SS PENDENTE | I134: 46080.62 | J134: 46083.638 | L134: 46143.638 | M134: POSTE RD GIS | N134: POSTE Concreto Duplo T | O134: PEDRO AFONSO | P134: URBANO | Q134: RICARDO DA CONCEICAO MOURA | R134: SOLICITAÇÃO DE SERVIÇO | S134: 8801170015
A135: ETO-COEP 00069/2026 | B135: 2026 | C135: COI | D135: ETO-COEP | E135: LD01059122 | F135: 9000448083 | G135: EMERGENCIAL | H135: SS PENDENTE | I135: 46082.368 | J135: 46125.646 | L135: 46128.646 | M135: POSTE RD GIS | N135: POSTE Concreto Duplo T | O135: APARECIDA DO RIO NEGRO | P135: RURAL | Q135: MARCELO COSTA PRIMO | R135: NOTA DE SERVIÇO (NS) - LINHA VIVA | S135: 9000448083
A136: ETO-COEP 00070/2026 | B136: 2026 | C136: COI | D136: ETO-COEP | E136: LD01059122 | F136: 9000448083 | G136: EMERGENCIAL | H136: SS PENDENTE | I136: 46082.368 | J136: 46125.646 | L136: 46128.646 | M136: POSTE RD GIS | N136: POSTE Concreto Duplo T | O136: APARECIDA DO RIO NEGRO | P136: RURAL | Q136: MARCELO COSTA PRIMO | R136: NOTA DE SERVIÇO (NS) - LINHA VIVA | S136: 8801094083
A137: ETO-COEP 00044/2026 | B137: 2026 | C137: MANUT | D137: ETO-COEP | E137: LD02040003 | F137: 7936038076 | G137: EMERGENCIAL | H137: SS PENDENTE | I137: 46083.664 | J137: 46083.664 | L137: 46086.664 | M137: RELIGADOR DE REDE GIS | N137: RELIGADOR DE LINHA - 38kV | O137: DUERE | P137: RURAL | Q137: ZENILSON MOREIRA SANTOS | R137: INDISPONIBILIDADE PARA OPERAÇÃO | S137: 7936038076
A138: ETO-COEP 00077/2026 | B138: 2026 | C138: COI | D138: ETO-COEP | E138: AL03062013 | F138: 5801866013 | G138: EMERGENCIAL | H138: SS PENDENTE | I138: 46083.666 | J138: 46132.325 | L138: 46135.325 | M138: REGULADOR DE TENSÃO DE DISTRIBUIÇÃO GIS | N138: REGULADOR DE TENSAO DE DIST. - 13.8 | O138: PARAISO DO TOCANTINS | P138: RURAL | Q138: VINICIUS CAMARGO COSTA | R138: INDISPONIBILIDADE PARA OPERAÇÃO | S138: 9001891013
A139: ETO-COEP 00064/2026 | B139: 2026 | C139: COI | D139: ETO-COEP | E139: LD05050008 | F139: 7955946007 | G139: EMERGENCIAL | H139: SS PENDENTE | I139: 46083.898 | J139: 46118.403 | L139: 46121.403 | M139: LOCAL INSTAL RELIGADOR DE LINHA GIS | N139: BLOCO RELIGADOR DE LINHA | O139: MIRACEMA DO TOCANTINS | P139: RURAL | Q139: VINICIUS CAMARGO COSTA | R139: INDISPONIBILIDADE PARA OPERAÇÃO | S139: 6800948007
... A144: ETO-COEP 00063/2026 | B144: 2026 | C144: MANUT | D144: ETO-COEP | E144: LD01434149 | F144: 7944559149 | G144: PROGRAMAVEL | H144: SS PENDENTE | I144: 46098.42 | J144: 46112.457 | L144: 46512.457 | M144: RELIGADOR DE REDE GIS | N144: RELIGADOR DE LINHA - 38kV | O144: CASEARA | P144: RURAL | Q144: VINICIUS CAMARGO COSTA | R144: INDISPONIBILIDADE PARA OPERAÇÃO | S144: 7944559149
A145: ETO-COEP 00068/2026 | B145: 2026 | D145: ETO-COEP | E145: LD05010004 | F145: 7929376022 | G145: EMERGENCIAL | H145: SS PENDENTE | I145: 46106.61 | J145: 46125.453 | L145: 46128.453 | M145: LOCAL INSTAL RELIGADOR DE LINHA GIS | N145: BLOCO RELIGADOR DE LINHA | O145: BABACULANDIA | P145: URBANO | Q145: LARA SOARES FARIAS | R145: INDISPONIBILIDADE PARA OPERAÇÃO | S145: 9001690022
A146: ETO-COEP 00057/2026 | B146: 2026 | C146: SCADA | D146: ETO-COEP | E146: AL04010004 | F146: 7923673004 | G146: PROGRAMAVEL | H146: SS PENDENTE | I146: 46107.659 | J146: 46107.659 | L146: 46507.659 | M146: RELIGADOR DE REDE GIS | N146: RELIGADOR DE LINHA - 15,0kV | O146: ARAGUAINA | P146: URBANO | Q146: ZENILSON MOREIRA SANTOS | R146: INDISPONIBILIDADE PARA OPERAÇÃO | S146: 7923673004
A147: ETO-COEP 00078/2026 | B147: 2026 | C147: COPO | D147: ETO-COEP | E147: LD03062013 | F147: 7926089013 | G147: ALTA | H147: SS PENDENTE | I147: 46108.655 | J147: 46135.332 | L147: 46195.332 | M147: RELIGADOR DE REDE GIS | N147: RELIGADOR DE LINHA - 38kV | O147: PARAISO DO TOCANTINS | P147: RURAL | Q147: Allan Pereira de Souza | R147: INDISPONIBILIDADE PARA OPERAÇÃO | S147: 7926089013
...

Sheet Planilha1

Sheet Dados Tratados
A1: SS | B1: Ano | C1: Descrição | D1: DataOcorrência | E1: Abrangencia | F1: Instalação | G1: Trecho | H1: Localização | I1: Complemento | J1: Sigla Orgao | K1: SolicNome | L1: DescPrioridade | M1: SS-Estados | N1: Data/Hora Limite | O1: Ativos | P1: Qtd_Clientes | Q1: Espécies | R1: SS-Tipos | S1: Término | T1: OSNumero | U1: OS-Estados | V1: PlanDataInicio | W1: PlanDataFinal | X1: DescOrigem | Y1: Condição Operativa COI | Z1: Descrição do Defeito | AA1: Lida | AB1: Processo | AC1: DEPARTCODE | AD1: UF | AE1: Bairro | AF1: Logradouro | AG1: OS SIATT | AH1: SS PRINCIPAL | AI1: SOMA | AJ1: COORDENADA UTM Y | AK1: LOCALIDADE | AL1: COORDENADA UTM X | AM1: EST PRIMÁRIA | AN1: EST SECUNDÁRIA | AO1: EQUIPAMENTO/CATEGORIA | AP1: STATUS | AQ1: ANÁLISE TÉCNICA | AR1: GRUPO ANÁLISE | AS1: EQUIPAMENTO PRINCIPAL | AT1: OBSERVAÇÕES | AU1: POSSÍVEL REPETIÇÃO | AV1: mm | AW1: metros | AX1: ou | AY1: mm2 | AZ1: metros2 | BA1: Atualizações
A2: ETO-COEP 00002/2026 | B2: 2026 | C2: SEGUE SOLICITAÇÃO DE SERVIÇO PARA BANCO CAPACITOR COM CÉLULA DA FASE B QUEIMADA EQUIPE 047OP01 INFORMOU QUE JA FIZERAM TESTE E NÃO ACEITOU ID#81133777 RDU DE FIGUEIROPOLIS | D2: 06/01/2026 09:26:14 | E2: 0300697047 | F2: AL01033047 | G2: 3 | H2: 5900038047 | I2: 190-16323937 | J2: COI | K2: JONATAN ALVES DE SOUZA | L2: EMERGENCIAL | M2: SS PENDENTE | N2: 09/01/2026 09:45:30 | O2: 190.02318 | P2: 0 | Q2: BANCO CAPACITOR DE DISTRIBUIÇÃO GIS | R2: INDISPONIBILIDADE PARA OPERAÇÃO | X2: CORPO (CÉLULA) | Z2: CURTO CIRCUITO | AA2: NÃO | AC2: ETO-COEP | AH2: ETO-RD-GU 00023/2026 | AI2: Não | AJ2: 8657782 | AK2: FIGUEIROPOLIS | AL2: 698997 | AO2: EQUIPAMENTO ESPECIAL | AP2: PENDÊNCIA DCMD | AQ2: REPASSAR DMSL | AR2: ANÁLISE | AS2: A DEFINIR (REPASSE)
A3: ETO-COEP 00005/2026 | B3: 2026 | C3: TROCAR BARRAMENTO DO TRAFO 5700440004 PARA 70MM | D3: 05/09/2025 09:26:08 | E3: 5700440004 | F3: AL02010004 | G3: 3 | H3: 5700440004 | I3: 190-15833293 | J3: COCM | K3: LEONARDO SANTOS DA SILVA | L3: ALTA | M3: SS PENDENTE | N3: 15/03/2026 15:40:18 | O3: 190.0239 | P3: 40 | Q3: TRANSFORMADOR DE DISTRIBUIÇÃO GIS | R3: AVISO DE ANOMALIA | X3: SOBRECARGA PREVENTIVA | Z3: SOBRECARGA | AA3: NÃO | AC3: ETO-COEP | AH3: ETO-RD-AR 01312/2025 | AI3: Não | AJ3: 9204397 | AK3: ARAGUAINA | AL3: 806192 | AO3: PLANO DE MEDIDAS | AP3: PENDÊNCIA DCMD | AQ3: REPASSAR COCM | AR3: REPASSE | AS3: A DEFINIR (REPASSE)
A4: ETO-COEP 00006/2026 | B4: 2026 | C4: FAVOR SUBSTITUIR 150 MTS DE CABO CONVENCIONAL DETERIORADO E CHEIO DE EMENDAS POR CADO MULTIPLEX NO TRAFO 5700244004 ENTRE OS ID : 63111183 AO ID :63239363 SEGUE FOTOS EM ANEXO | D4: 10/09/2025 17:08:23 | E4: 5700244004 | F4: AL03010004 | G4: 3 | H4: 5700244004 | I4: 190-1648091 | J4: DEOP | K4: WESLEY FRANCISCO DE ASSIS ROCH | L4: ALTA | M4: SS PENDENTE | N4: 15/03/2026 15:40:49 | O4: 190.00487 | P4: 90 | Q4: POSTE RD GIS | R4: AVISO DE ANOMALIA | X4: CABOS BT | Z4: DETERIORADA | AA4: NÃO | AC4: ETO-COEP | AD4: Tocantins | AH4: ETO-RD-AR 01339/2025 | AI4: Não | AJ4: 9203692 | AK4: ARAGUAINA | AL4: 806862 | AN4: S1 | AO4: CABOS FORA COEP | AP4: PENDÊNCIA DCMD | AQ4: CABOS | AR4: MANUTENÇÃO | AS4: CABOS | AV4: 35/70 | AW4: 150
A5: ETO-COEP 00007/2026 | B5: 2026 | C5: Bom Dia Segue SS Senhores enviar equipe de manutenção para trocar cabo deteriorado a RDU de Araguaína ID: 76492244 Trafo 5704265004 Instalar cabo entre os ID: 76492244 e 76492235 Endereço: Rua QE21 Lt 64 Jardim Boa sorte Levar: 150 metros de cabo 35mm multiplex Equipe: 004op07 Contato da equipe:99216-8451 | D5: 27/10/2025 11:12:10 | E5: 5704265004 | F5: AL07010004 | G5: 3 | H5: 5704265004 | I5: 190-1842256 | J5: MANUT | K5: ERLAN PEREIRA DE SOUSA | L5: ALTA | M5: SS PENDENTE | N5: 16/03/2026 13:30:16 | O5: 190.00959 | P5: 66 | Q5: POSTE RD GIS | R5: AVISO DE ANOMALIA | X5: CABOS BT | Z5: DETERIORADA | AA5: NÃO | AC5: ETO-COEP | AD5: Tocantins | AH5: ETO-RD-AR 01611/2025 | AI5: Não | AJ5: 9205274 | AK5: ARAGUAINA | AL5: 804541 | AN5: SI-3 | AO5: CABOS FORA COEP | AP5: PENDÊNCIA DCMD | AQ5: CABOS | AR5: MANUTENÇÃO | AS5: CABOS | AV5: 35 | AW5: 150
A6: ETO-COEP 00009/2026 | B6: 2026 | C6: Segue SS para instalar chave faca para manobra na quadra 1203 Sul. ID 57429768 Estrutura N4 Chave de referencia 0300953122. Serviço a ser executado com linha viva ********************************* PARECER COCM COEP gentileza verificar solicitação da operação. Sendo interessante para ETO, gentileza direcionar atendimento ao COCM informando de onde o custo será debitado. | D6: 13/01/2026 22:44:13 | E6: 0300953122 | F6: AL07097122 | G6: 3 | H6: 6800953122 | I6: 190-399314 | J6: COI | K6: HERIK BUARQUE DOS SANTOS | L6: EMERGENCIAL | M6: SS PENDENTE | N6: 19/01/2026 14:33:47 | O6: 190.00993 | P6: 1,097 | Q6: POSTE RD GIS | R6: AVISO DE CADASTRO | X6: CHAVE | Z6: INEXISTENTE | AA6: NÃO | AC6: ETO-COEP | AD6: Tocantins | AH6: ETO-RD-PA 00026/2026 | AI6: Não | AJ6: 8864791 | AK6: PALMAS | AL6: 791175 | AM6: N4 | AN6: S4 | AO6: PLANO DE MEDIDAS | AP6: PENDÊNCIA DCMD | AQ6: CHAVE- FACA | AR6: ANÁLISE | AS6: CHAVE
A7: ETO-COEP 00011/2026 | B7: 2026 | C7: Remover chave 0306784122 para estrutura N4, poste ID#59387277 . Ação oriunda ocorrências relevantes realizada em 16/01 ( desarme AL 4 SE Palmas II). ********************************* PARECER COCM COEP gentileza verificar solicitação da operação. Sendo interessante para ETO, gentileza direcionar atendimento ao COCM informando de onde o custo será debitado. | D7: 16/01/2026 16:08:28 | E7: 8806782122 | F7: AL04059122 | G7: 3 | H7: 8806782122 | I7: 190-441396 | J7: COPO | K7: MIGUEL FRANCISCO PEREIRA | L7: URGENTE | M7: SS PENDENTE | N7: 23/01/2026 16:55:04 | O7: 190.00667 | P7: 582 | Q7: POSTE RD GIS | R7: NOTA DE SERVIÇO (NS) - LINHA VIVA | AA7: NÃO | AC7: ETO-COEP | AD7: Tocantins | AH7: ETO-RD-PA 00044/2026 | AI7: Não | AJ7: 8869067 | AK7: PALMAS | AL7: 794173 | AM7: N4 | AN7: S3 | AO7: EQUIPAMENTO ESPECIAL | AP7: PENDÊNCIA DCMD | AQ7: REPASSAR COCM | AR7: REPASSE | AS7: A DEFINIR (REPASSE)
A8: ETO-COEP 00013/2026 | B8: 2026 | C8: TRAFO ANTIGO com sobrecarga. Potência: 112,5 kVA - Substituir por um de 150 kVA. Tensão: 13,8 kV. *********************************** PARECER COCM CENTRO COEP favor verificar ações para constatações de sobrecarga e direcionar atendimento de substituição se for o caso. | D8: 19/01/2026 21:07:34 | E8: 0300587122 | F8: AL04059122 | G8: 3 | H8: 5702635122 | I8: 190-13722315 | J8: COI | K8: ASTROGILDO PIRES BERNARDO | L8: EMERGENCIAL | M8: SS PENDENTE | N8: 23/01/2026 08:18:40 | O8: 190.02385 | P8: 69 | Q8: LOCAL INSTAL TRANSFORMADOR DE DISTRIBUIÇÃO GIS | R8: AVISO DE ANOMALIA | X8: SOBRECARGA PREVENTIVA | Z8: SOBRECARGA | AA8: NÃO | AC8: ETO-COEP | AH8: DOLP-RD-PA 00097/2026 | AI8: Não | AJ8: 8868117 | AK8: PALMAS | AL8: 792975 | AO8: PLANO DE MEDIDAS | AP8: PENDÊNCIA DCMD | AQ8: REPASSAR COCM | AR8: REPASSE | AS8: A DEFINIR (REPASSE)
A9: ETO-COEP 00015/2026 | B9: 2026 | C9: Segue nota para envia equipe LV instala jogo de chave faca no poste ID-57357485 estrutura N4, Tensão 13.8kv, Cabo AA / 2/0, Acesso livre, Circuito do AL-01 de Luzimangues. Obs. CH para facilitar manobras no trecho. ******************************** PARECER DO COCM COEP favor analisar solicitação da operação de melhoria na rede e se validada retornar demanda ao COCM informando aonde será lançado o custo. | D9: 18/11/2025 10:38:14 | E9: 8803678271 | F9: AL01101271 | G9: 1 | H9: 8803678271 | I9: 190-411989 | J9: COI | K9: SAMUEL PINTO GOMES | L9: PROGRAMAVEL | M9: SS PENDENTE | N9: 24/02/2027 18:25:18 | O9: 190.01019 | P9: 955 | Q9: POSTE RD GIS | R9: NOTA DE SERVIÇO (NS) - LINHA VIVA | X9: OUTROS | Z9: INSPEÇÃO VISUAL | AA9: NÃO | AC9: ETO-COEP | AD9: Tocantins | AH9: ETO-RD-PA 00778/2025 | AI9: Não | AJ9: 8872214 | AK9: PORTO NACIONAL | AL9: 775561 | AM9: N4 | AO9: MELHORIA DE REDE | AP9: PENDÊNCIA DCMD | AQ9: REPASSAR COCM | AR9: REPASSE | AS9: A DEFINIR (REPASSE)
A10: ETO-COEP 00016/2026 | B10: 2026 | C10: rdu Palmas proximo Unimed e hospital Cristo rei id 57403822 sj 57404949 estrutura N4 istalar jogo de chave faca 13,8 NF para manobra id 42151836 sj 57404952 estruutra N4/N3 ch 0300839122 substituir jogo chave lamina po jogo de chave faca 13,8 ************************ PARECER DO COCM COEP favor analisar solicitação da operação de melhoria na rede e se validada retornar demanda ao COCM informando aonde será lançado o custo. | D10: 26/09/2025 18:40:52 | E10: 8801117122 | F10: AL08097122 | G10: 2 | H10: 0300839122 | I10: 190-17402150 | J10: COI | K10: CLEONE PEREIRA DE SOUZA LIMA | L10: EMERGENCIAL | M10: SS PENDENTE | N10: 23/01/2026 18:34:35 | O10: 190.00091 | P10: 718 | Q10: LOCAL INSTAL CHAVE FUSÍVEL GIS | R10: NOTA DE SERVIÇO (NS) - LINHA VIVA | X10: PORTA FUSÍVEL | Z10: INSPEÇÃO VISUAL | AA10: NÃO | AC10: ETO-COEP | AD10: Tocantins | AH10: ETO-RD-PA 00654/2025 | AI10: Não | AJ10: 8869375 | AK10: PALMAS | AL10: 791764 | AO10: MELHORIA DE REDE | AP10: PENDÊNCIA DCMD | AQ10: ENTENDER | AR10: ANÁLISE | AS10: A DEFINIR (análise) | AT10: rdu Palmas proximo Unimed e hospital Cristo rei id 57403822 sj 57404949 estrutura N4 istalar jogo de chave faca 13,8 NF para manobra id 42151836 sj 57404952 estruutra N4/N3 ch 0300839122 substituir jogo chave lamina po jogo de chave faca 13,8 ************************ PARECER DO COCM COEP favor analisar solicitação da operação de melhoria na rede e se validada retornar demanda ao COCM informando aonde será lançado o custo. | AU10: REPETIDA
A11: ETO-COEP 00017/2026 | B11: 2026 | C11: rdu Palmas proximo Unimed e hospital Cristo rei id 57403822 sj 57404949 estrutura N4 istalar jogo de chave faca 13,8 NF para manobra id 42151836 sj 57404952 estruutra N4/N3 ch 0300839122 substituir jogo chave lamina po jogo de chave faca 13,8 **************************** PARECER DO COCM COEP favor analisar solicitação da operação de melhoria na rede e se validada retornar demanda ao COCM informando aonde será lançado o custo. | D11: 26/09/2025 18:40:52 | E11: 8804511122 | F11: AL08097122 | G11: 2 | H11: 8804511122 | I11: 190-398539 | J11: COI | K11: CLEONE PEREIRA DE SOUZA LIMA | L11: EMERGENCIAL | M11: SS PENDENTE | N11: 23/01/2026 18:34:57 | O11: 190.0099 | P11: 437 | Q11: POSTE RD GIS | R11: NOTA DE SERVIÇO (NS) - LINHA VIVA | X11: PORTA FUSÍVEL | Z11: INSPEÇÃO VISUAL | AA11: NÃO | AC11: ETO-COEP | AD11: Tocantins | AH11: ETO-RD-PA 00655/2025 | AI11: Não | AJ11: 8869976 | AK11: PALMAS | AL11: 791764 | AM11: N4 | AN11: S3 | AO11: MELHORIA DE REDE | AP11: PENDÊNCIA DCMD | AQ11: ENTENDER | AR11: ANÁLISE | AS11: A DEFINIR (análise) | AT11: rdu Palmas proximo Unimed e hospital Cristo rei id 57403822 sj 57404949 estrutura N4 istalar jogo de chave faca 13,8 NF para manobra id 42151836 sj 57404952 estruutra N4/N3 ch 0300839122 substituir jogo chave lamina po jogo de chave faca 13,8 ************************ PARECER DO COCM COEP favor analisar solicitação da operação de melhoria na rede e se validada retornar demanda ao COCM informando aonde será lançado o custo.
A12: ETO-COEP 00018/2024 | B12: 2024 | C12: Favor enviar equipe para verificar banco de capacitor :5952243122 danificado fase B e C na quadra 606 Sul | D12: 18/02/2024 05:44:18 | E12: 0352243122 | F12: AL04059122 | G12: 3 | H12: 5952243122 | I12: 190-49522936 | J12: COI | K12: NATANAEL MELQUIADES DOS SANTOS | L12: EMERGENCIAL | M12: SS PENDENTE | N12: 22/02/2024 16:05:01 | O12: 190.02684 | P12: 0 | Q12: BANCO CAPACITOR DE DISTRIBUIÇÃO GIS | R12: INDISPONIBILIDADE PARA OPERAÇÃO | X12: OUTROS | Z12: QUEIMADO | AA12: SIM | AC12: ETO-COEP | AH12: DOLP-RD-PA 00205/2024 | AI12: Não | AJ12: 8868932 | AK12: PALMAS | AL12: 793345 | AO12: EQUIPAMENTO ESPECIAL | AP12: PENDÊNCIA DCMD | AQ12: BANCO DE CAPACITOR | AR12: MANUTENÇÃO | AS12: BANCO DE CAPACITOR
A13: ETO-COEP 00020/2026 | B13: 2026 | C13: Substituição de tanque e controle, os mesmos estão com defeitos. | D13: 22/01/2026 11:05:26 | E13: 7908708116 | F13: LD04002091 | G13: 2 | H13: 7908708116 | I13: 190-17512824 | J13: SCADA | K13: LARA SOARES FARIAS | L13: PROGRAMAVEL | M13: SS PENDENTE | N13: 26/02/2027 11:05:26 | O13: 190.02296 | P13: 219 | Q13: RELIGADOR DE REDE GIS | R13: INDISPONIBILIDADE PARA OPERAÇÃO | AA13: NÃO | AC13: ETO-COEP | AI13: Não | AJ13: 8722032 | AK13: CHAPADA DA NATIVIDADE | AL13: 849089 | AO13: EQUIPAMENTO ESPECIAL | AP13: PENDÊNCIA DCMD | AQ13: TANQUE E CONTROLE | AR13: MANUTENÇÃO | AS13: TANQUE
A14: ETO-COEP 00021/2026 | B14: 2026 | C14: Regulador 5803327001 fora de operação, by passado em campo com painel de comunicação com cabos desconectados tensão 13.8. parecer DMSL: Feedback Equip. Especiais RT 5803327001 RELÉ RUA Sid: 4844 Data: 19/09/2025 Serviço realizado: *Equipamento foi remanejado, 7 km da sua localização sentido Palmas necessário comissionamento completo *Equipamento com um dos cabos umbilicais danificado. * aterramento bucha FC não esta interligada corretamente * para-raios estão no mesmo aterramento da bucha FC. * Tranques muito alto e próximo da rede não permitindo o comissionamento com segurança. * Controle alto demais tem que baixar Equipamento ficou em operação?: não Pendência: sim, precisa comissionar completo OBS; reprogramar equipamento. Bateria(s) substituída(s) NÃO Equipe: Ellisfran, Ana Maria PARECER DMSL: Data 03/12/2025-Equipe: Carliel e Benvindo Serviço executado foi ensaiado as três células Equipamento ficou em operação: Não Pendência: sim, Instalar controle completo, e fazer melhoria na malhar de aterramento | D14: 04/09/2025 21:36:22 | E14: 8851077001 | F14: AL01102271 | G14: 2 | H14: 5803327001 | I14: 190-15851809 | J14: COI | K14: HELDER SILVA CARVALHO | L14: EMERGENCIAL | M14: SS PENDENTE | N14: 25/01/2026 11:48:23 | O14: 190.02318 | P14: 39 | Q14: REGULADOR DE TENSÃO DE DISTRIBUIÇÃO GIS | R14: INDISPONIBILIDADE PARA OPERAÇÃO | X14: FORA DE SERVIÇO | Z14: RELÉ REGULADOR DE TENSÃO | AA14: NÃO | AC14: ETO-COEP | AH14: ETO-DEOP 00014/2025 | AI14: Não | AJ14: 8872358 | AK14: PORTO NACIONAL | AL14: 770823 | AO14: EQUIPAMENTO ESPECIAL | AP14: PENDÊNCIA DCMD | AQ14: INSTALAR CONTROLE E MELHORIA DE ATERRAMENTO | AR14: MANUTENÇÃO | AS14: ATERRAMENTO
A15: ETO-COEP 00024/2026 | B15: 2026 | C15: REALIZAR SUBSTITUIÇÃO DO TANQUE, O MESMO ESTÁ COM DEFEITO. | D15: 27/01/2026 16:33:07 | E15: 7933585074 | F15: LD03028074 | G15: 2 | H15: 7933585074 | I15: 190-59145750 | J15: SCADA | K15: LARA SOARES FARIAS | L15: EMERGENCIAL | M15: SS PENDENTE | N15: 30/01/2026 16:33:07 | O15: 190.02765 | P15: 0 | Q15: RELIGADOR DE REDE GIS | R15: INDISPONIBILIDADE PARA OPERAÇÃO | AA15: NÃO | AC15: ETO-COEP | AI15: Não | AJ15: 8726425 | AK15: DIANOPOLIS | AL15: 986342 | AO15: EQUIPAMENTO ESPECIAL | AP15: PENDÊNCIA DCMD | AQ15: TANQUE | AR15: MANUTENÇÃO | AS15: TANQUE
A16: ETO-COEP 00025/2026 | B16: 2026 | C16: COEP: equipamentos fornecidos. Repasse ao COCM para correção. PARACER DA PROTEÇÃO: Recebemos a solicitação de elaboração de ajustes do RT 5854681071, nota repassada pelo COEP. Duvidas: As pendencias apontadas pelo DMSL foram sanadas? Pois não registro descritivo na SS. Se foram sanadas, a SS não seguiu o fluxo norma, pois não há repassa da nota para o COEP. Podemos seguir com os estudos e comissionamento do ativo? PARECER DMSL: Equipe esteve no RT 5854681071 dia 18/02/2025 porém, as fases A e B estão com a ligação carga/fase invertidas, não contém antena, não contém suporte de antena e não contém rádio GE. Favor, sanar pendências para possibilitar o comissonamento. REGULADOR DE TENSAO N° 5854681071 INSTALADO NA OBRA 0302100570 GENTILEZA, REALIZAR O COMISSIONAMENTO. LAUDO EM ANEXO. COORD EO: 766351, 8781674 PARECER DA PROTEÇÃO ESTUDO DO EQUIPAMENTO DISPONIVEL NO APP DA PROTEÇÃO, NOTA REPASSADA PARA O DMSL COMISSIONAR O EQUIPAMENTO. TEC° EUZILAN MATEUS BARREIRA SANTOS | D16: 21/11/2024 14:32:44 | E16: 9000001071 | F16: AL01018071 | G16: 2 | H16: 5854681071 | I16: 190-26073406 | J16: COPC | K16: Thais Jordanna Jesus Silva | L16: ALTA | M16: SS PENDENTE | N16: 30/03/2026 08:30:03 | O16: 190.02747 | P16: 2,391 | Q16: REGULADOR DE TENSÃO DE DISTRIBUIÇÃO GIS | R16: OBRAS (NOVOS EQUIPAMENTOS) | X16: REGULADOR DE TENSÃO | AA16: NÃO | AC16: ETO-COEP | AH16: ETO-PROT 00437/2024 | AI16: Não | AJ16: 8781673 | AK16: BREJINHO DE NAZARE | AL16: 766351 | AO16: EQUIPAMENTO ESPECIAL | AP16: PENDÊNCIA DMSL | AQ16: REPASSAR DMSL | AR16: REPASSE | AS16: A DEFINIR (REPASSE)
A17: ETO-COEP 00028/2026 | B17: 2026 | C17: FEITO O PRIMEIRO ATAQUE NO RL 7954668084 E O DISPLAY ESTÁ QUEIMADO, NÃO LIGA. OS (99) 106230846 | D17: 03/02/2026 13:31:14 | E17: 6820041084 | F17: LD04062013 | G17: 3 | H17: 7954668084 | I17: 190-37207659 | J17: COI | K17: EVA RAIANE CASTELO BONFIM DA S | L17: EMERGENCIAL | M17: SS PENDENTE | N17: 06/02/2026 17:25:20 | O17: 190.02714 | P17: 142 | Q17: LOCAL INSTAL RELIGADOR DE LINHA GIS | R17: INDISPONIBILIDADE PARA OPERAÇÃO | X17: RELÉ | Z17: QUEIMADO | AA17: NÃO | AC17: ETO-COEP | AH17: ENC-RD-PS 00188/2026 | AI17: Não | AJ17: 8908376 | AK17: DIVINOPOLIS DO TOCANTINS | AL17: 700668 | AO17: EQUIPAMENTO ESPECIAL | AP17: PENDÊNCIA DMSL | AQ17: REPASSAR DMSL | AR17: REPASSE | AS17: A DEFINIR (REPASSE)
A18: ETO-COEP 00029/2026 | B18: 2026 | C18: RELIGADOR BY PASSADO POR DEFEITO, NECESSÁRIO AVALIAÇÃO DO PROBLEMA. parecer dmsl:O religador apresenta defeito no tanque, sendo necessário substituir o tanque o mesmo está tirando a linha, e troca os isoladores. Quando retornar, trazer uma fonte para o equipamento, a mesma foi removida. FICOU EM OPERAÇÃO? Não PENDÊNCIA: Sim, aguardando peças para substituição. | D18: 09/01/2026 09:09:54 | E18: 7927646026 | F18: LD03046026 | G18: 2 | H18: 7927646026 | I18: 190-37070331 | J18: COI | K18: ZENILSON MOREIRA SANTOS | L18: EMERGENCIAL | M18: SS PENDENTE | N18: 07/02/2026 08:52:01 | O18: 190.02703 | P18: 2,201 | Q18: RELIGADOR DE REDE GIS | R18: INDISPONIBILIDADE PARA OPERAÇÃO | AA18: NÃO | AC18: ETO-COEP | AH18: ETO-TELE 00143/2026 | AI18: Não | AJ18: 8841819 | AK18: PONTE ALTA DO TOCANTINS | AL18: 918776 | AO18: EQUIPAMENTO ESPECIAL | AP18: PENDÊNCIA DCMD | AQ18: TANQUE | AR18: MANUTENÇÃO | AS18: TANQUE
A19: ETO-COEP 00031/2026 | B19: 2026 | C19: POR GENTILEZA PROGRAMAR PARA SUBSTITUIÇÃO DO BARRAMENTO DO TRAFO DEVIDO NÃO SER COMPATIVEL COM A POTÊNCIA DO MESMO, NECESSIDADE DE SUBSTITUIÇÃO SE 7 VÃOS | D19: 10/02/2026 08:52:01 | E19: 8804224004 | F19: AL03010004 | G19: 1 | H19: 5701123004 | I19: 190-13659315 | K19: GERCILIO PEDROZA JUNIOR | L19: URGENTE | M19: SS PENDENTE | N19: 17/02/2026 10:15:28 | O19: 190.0234 | P19: 85 | Q19: LOCAL INSTAL TRANSFORMADOR DE DISTRIBUIÇÃO GIS | R19: MELHORIA POSTO DE TRANSFORMAÇÃO | AA19: NÃO | AC19: ETO-COEP | AH19: ETO-RD-AR 00277/2026 | AI19: Não | AJ19: 9203556 | AK19: ARAGUAINA | AL19: 806816 | AO19: PLANO DE MEDIDAS | AP19: PENDÊNCIA DCMD | AQ19: BARRAMENTO | AR19: MANUTENÇÃO | AS19: BARRAMENTO
A20: ETO-COEP 00033/2026 | B20: 2026 | C20: favor verificar RL 7947203070, sem comunicaçao, feito 1° ataque pela equipe 070OP01 e nao retornou a comunicaçao , linformaçao no Scada de bateria. PARECER DMSL: Foi feito análise técnica, a placa do equipamento está queimada nessesario subistituir o equipamento completo -Carliel e Benvindo-05/02 | D20: 23/11/2025 21:48:23 | E20: 8800157070 | F20: LD02065015 | G20: 3 | H20: 7947203070 | I20: 190-68154393 | J20: COI | K20: LAISON OLIVEIRA CARVALHO | L20: EMERGENCIAL | M20: SS PENDENTE | N20: 16/02/2026 08:58:15 | O20: 190.02641 | P20: 1,764 | Q20: LOCAL INSTAL RELIGADOR DE LINHA GIS | R20: INDISPONIBILIDADE PARA OPERAÇÃO | X20: RELIGADOR | Z20: INSPEÇÃO VISUAL | AA20: NÃO | AC20: ETO-COEP | AH20: ETO-TELE 01381/2025 | AI20: Não | AJ20: 8950905 | AK20: RIO SONO | AL20: 851948 | AO20: EQUIPAMENTO ESPECIAL | AP20: PENDÊNCIA DCMD | AQ20: RELIGADOR | AR20: MANUTENÇÃO | AS20: RELIGADOR
A21: ETO-COEP 00035/2026 | B21: 2026 | C21: NOTA PARA EQUIPE DE LINHA VIVA INSTALAR CHAVE FACA PARA MANOBRA ENTRE SANTAFE E DERIVAÇÃO PA COCALANDIA NO ID.: 63243178 EST N4 ACESSO BOM NECESSARIO URGENCIA REFERENCIA AO LADO DA CH 8800521159- | D21: 16/02/2026 05:35:05 | E21: 8800416159 | F21: LD03010004 | G21: 2 | H21: 8800416159 | I21: 190-552234 | J21: COI | K21: ARTHUR MAGALHAES DAS DORES | L21: EMERGENCIAL | M21: SS PENDENTE | N21: 21/02/2026 15:19:06 | O21: 190.00481 | P21: 3,115 | Q21: POSTE RD GIS | R21: NOTA DE SERVIÇO (NS) - LINHA VIVA | X21: CHAVE | Z21: FALTANDO | AA21: NÃO | AC21: ETO-COEP | AD21: Tocantins | AH21: ETO-RD-AR 00317/2026 | AI21: Não | AJ21: 9208353 | AK21: MURICILANDIA | AL21: 762298 | AM21: N4 | AO21: PLANO DE MEDIDAS | AP21: PENDÊNCIA DCMD | AQ21: REPASSAR COCM | AR21: REPASSE | AS21: A DEFINIR (REPASSE)
A22: ETO-COEP 00036/2026 | B22: 2026 | C22: SS ANTIGA: 1500/2025 PARECER DMSL: Serviço Executado: Foi verificado que o tanque do equipamento está danificado, sendo necessário substituir o tanque do equipamento. Equipamento ficou em operação?: Não Pendência: Sim, instalar fonte, disjuntor e DPS, e substituir o tanque. | D22: 16/01/2026 09:24:40 | E22: 7927169001 | F22: AL01102271 | G22: 1 | H22: 7927169001 | I22: 190-17421624 | J22: MANUT | K22: JULIA GRAZYELLE BRITO OLIVEIRA | L22: EMERGENCIAL | M22: SS PENDENTE | N22: 27/02/2026 09:24:40 | O22: 190.0221 | P22: 420 | Q22: RELIGADOR DE REDE GIS | R22: INDISPONIBILIDADE PARA OPERAÇÃO | AA22: NÃO | AC22: ETO-COEP | AI22: Não | AJ22: 8872437 | AK22: PORTO NACIONAL | AL22: 766063 | AO22: EQUIPAMENTO ESPECIAL | AP22: PENDÊNCIA DCMD | AQ22: TANQUE DISJUNTOR DPS | AR22: MANUTENÇÃO | AS22: TANQUE
A23: ETO-COEP 00038/2026 | B23: 2026 | C23: DMSL:Serviço Executado: Houve um curto no equipamento danificando a parte ativa, será necessário fazer a substituição do equipamento completo ( parte ativa e controle) colocar o um cabo pp novo do trafo até o Dj pois o mesmo está sem condições de uso. Obs:. Foi retirado rádio e rele Equipamento ficou em operação?: Não Pendência: Sim, substituir o equipamento completo. | D23: 22/01/2026 11:28:09 | E23: 7908249152 | F23: LD02072001 | G23: 3 | H23: 7908249152 | I23: 190-17512853 | J23: MANUT | K23: JULIA GRAZYELLE BRITO OLIVEIRA | L23: ALTA | M23: SS PENDENTE | N23: 25/04/2026 11:28:09 | O23: 190.02207 | P23: 234 | Q23: RELIGADOR DE REDE GIS | R23: INDISPONIBILIDADE PARA OPERAÇÃO | AA23: NÃO | AC23: ETO-COEP | AI23: Não | AJ23: 8737798 | AK23: SANTA ROSA DO TOCANTINS | AL23: 805385 | AO23: EQUIPAMENTO ESPECIAL | AP23: PENDÊNCIA DCMD | AQ23: RELIGADOR | AR23: MANUTENÇÃO | AS23: RELIGADOR
A24: ETO-COEP 00039/2026 | B24: 2026 | C24: DMSL:Serviço Executado: Foi feita análise técnica a qual foi identificado que o tanque do equipamento entrou em curto o mesmo necessário substituir o tanque | D24: 24/02/2026 11:37:29 | E24: 7926089013 | F24: LD03062013 | G24: 3 | H24: 7926089013 | I24: 190-17512949 | J24: MANUT | K24: JULIA GRAZYELLE BRITO OLIVEIRA | L24: ALTA | M24: SS PENDENTE | N24: 25/04/2026 11:37:29 | O24: 190.02203 | P24: 1,042 | Q24: RELIGADOR DE REDE GIS | R24: INDISPONIBILIDADE PARA OPERAÇÃO | AA24: NÃO | AC24: ETO-COEP | AI24: Não | AJ24: 8867765 | AK24: PARAISO DO TOCANTINS | AL24: 718799 | AO24: EQUIPAMENTO ESPECIAL | AP24: PENDÊNCIA DCMD | AQ24: TANQUE | AR24: MANUTENÇÃO | AS24: TANQUE | AU24: REPETIDA
A25: ETO-COEP 00040/2026 | B25: 2026 | C25: DMSL:Serviço Executado: Foi feita uma análise técnica no equipamento, devido à falta de comunicação. Também foi identificado que o tanque do equipamento está danificado, sendo assim, necessário substituir o tanque e o rádio do equipamento, que está queimado, sendo necessário substituir também. | D25: 28/01/2026 11:41:25 | E25: 7931608059 | F25: AL08099059 | G25: 2 | H25: 7931608059 | I25: 190-17421389 | J25: MANUT | K25: JULIA GRAZYELLE BRITO OLIVEIRA | L25: EMERGENCIAL | M25: SS PENDENTE | N25: 27/02/2026 11:41:25 | O25: 190.02208 | P25: 0 | Q25: RELIGADOR DE REDE GIS | R25: INDISPONIBILIDADE PARA OPERAÇÃO | AA25: NÃO | AC25: ETO-COEP | AI25: Não | AJ25: 8854562 | AK25: PALMAS | AL25: 796501 | AO25: EQUIPAMENTO ESPECIAL | AP25: PENDÊNCIA DCMD | AQ25: TANQUE E RÁDIO | AR25: MANUTENÇÃO | AS25: TANQUE
A26: ETO-COEP 00042/2026 | B26: 2026 | C26: PARECER DMSL: FAVOR REALIZAR A SUBSTITUIÇÃO DO EQUIOAMENTO COMPLETO, FALHA DE ABERTURA PARA PROTEÇÃO | D26: 26/02/2026 10:28:59 | E26: 7900505026 | F26: LD03046026 | G26: 2 | H26: 7900505026 | I26: 190-17512769 | J26: MANUT | K26: JULIA GRAZYELLE BRITO OLIVEIRA | L26: ALTA | M26: SS PENDENTE | N26: 27/04/2026 10:28:59 | O26: 190.02223 | P26: 334 | Q26: RELIGADOR DE REDE GIS | R26: EM OPERAÇÃO COM ANOMALIA | AA26: NÃO | AC26: ETO-COEP | AI26: Não | AJ26: 8796235 | AK26: PONTE ALTA DO TOCANTINS | AL26: 882036 | AO26: EQUIPAMENTO ESPECIAL | AP26: PENDÊNCIA DCMD | AQ26: RELIGADOR | AR26: MANUTENÇÃO | AS26: RELIGADOR
A27: ETO-COEP 00043/2026 | B27: 2026 | C27: Por gentileza instalar Chave Faca com referência ao ID# E.O: 44271354; | D27: 27/02/2026 14:53:22 | E27: 8801170015 | F27: LD02065015 | G27: 1 | H27: 8801170015 | I27: 190-44271354 | J27: COPO | K27: Camila Mell Prado | L27: ALTA | M27: SS PENDENTE | N27: 01/05/2026 15:18:45 | O27: 190.02658 | P27: 257 | Q27: POSTE RD GIS | R27: SOLICITAÇÃO DE SERVIÇO | X27: CHAVE | Z27: INEXISTENTE | AA27: NÃO | AC27: ETO-COEP | AH27: ETO-RD-GR 00294/2026 | AI27: Não | AJ27: 9004568 | AK27: PEDRO AFONSO | AL27: 811516 | AM27: N1 | AN27: SI1 | AO27: PLANO DE MEDIDAS | AP27: PENDÊNCIA DCMD | AQ27: REPASSAR COCM | AR27: REPASSE | AS27: A DEFINIR (REPASSE)
A28: ETO-COEP 00044/2026 | B28: 2026 | C28: Tanque do RLG 7936038076 queimado, favor substituir o mesmo. NS do tanque: 0320118112616 | D28: 02/03/2026 15:56:19 | E28: 7936038076 | F28: LD02040003 | G28: 3 | H28: 7936038076 | I28: 190-17512614 | J28: MANUT | K28: EDNA MARIA DOS SANTOS PINTO | L28: EMERGENCIAL | M28: SS PENDENTE | N28: 05/03/2026 15:56:19 | O28: 190.02209 | P28: 17 | Q28: RELIGADOR DE REDE GIS | R28: INDISPONIBILIDADE PARA OPERAÇÃO | AA28: NÃO | AC28: ETO-COEP | AI28: Não | AJ28: 8742101 | AK28: DUERE | AL28: 666106 | AO28: EQUIPAMENTO ESPECIAL | AP28: PENDÊNCIA DCMD | AQ28: RELIGADOR | AR28: MANUTENÇÃO | AS28: RELIGADOR
A29: ETO-COEP 00045/2026 | B29: 2026 | C29: religador foi bay passado devido mesmo esta saindo fumaca do painel e sem comunicação 7927396052. PARECER DMSL: Após testes, equipe DMSL constatou que apenas o tanque do RLG 7927396052 encontra-se queimado. Favor, substituir parte ativa do equipamento. NS Tanque: 0320123040198 | D29: 17/02/2026 19:02:33 | E29: 9001632052 | F29: LD03036052 | G29: 3 | H29: 7927396052 | I29: 190-21148967 | J29: COI | K29: ZELITO ALVES DELGADO | L29: EMERGENCIAL | M29: SS PENDENTE | N29: 05/03/2026 21:25:22 | O29: 190.02667 | P29: 0 | Q29: LOCAL INSTAL RELIGADOR DE LINHA GIS | R29: INDISPONIBILIDADE PARA OPERAÇÃO | X29: RELIGADOR | Z29: INSPEÇÃO VISUAL | AA29: NÃO | AC29: ETO-COEP | AH29: ETO-TELE 00295/2026 | AI29: Não | AJ29: 8723116 | AK29: FORMOSO DO ARAGUAIA | AL29: 645739 | AO29: EQUIPAMENTO ESPECIAL | AP29: PENDÊNCIA DCMD | AQ29: REPASSAR DMSL | AR29: REPASSE | AS29: A DEFINIR (REPASSE)
A30: ETO-COEP 00046/2026 | B30: 2026 | C30: Acionar equipe de manutencao para subsituir 2 vao de rede do trafo 5739148227 na RDU de Recurssolandia equipe 0227op01 obs. troca cabo por multiplex e inspecioar os flytap que estao com ponto quente nos conector na Rua 02 de outubro | D30: 03/03/2026 20:21:49 | E30: 0300002227 | F30: LD01065015 | G30: 3 | H30: 5739148227 | I30: 190-13671793 | J30: COI | K30: CLEIBER DA SILVA | L30: EMERGENCIAL | M30: SS PENDENTE | N30: 08/03/2026 07:47:09 | O30: 190.02338 | P30: 24 | Q30: LOCAL INSTAL TRANSFORMADOR DE DISTRIBUIÇÃO GIS | R30: AVISO DE ANOMALIA | X30: AVARIADO | Z30: NÃO IDENTIFICADO | AA30: NÃO | AC30: ETO-COEP | AH30: ETO-RD-GR 00311/2026 | AI30: Não | AJ30: 9032221 | AK30: RECURSOLANDIA | AL30: 913609 | AO30: PLANO DE MEDIDAS | AP30: PENDÊNCIA DCMD | AQ30: REPASSAR COCM | AR30: REPASSE | AS30: A DEFINIR (REPASSE)
A31: ETO-COEP 00047/2025 | B31: 2025 | C31: PLANO DE MEDIDA - Transformador 5700078015 com 153 de carregamento para analise de divisão de circuito. Após análise, foi identificado que o transformador 5753469015 possivelmente está a vazio e nas informações fornecidas pela OS de inspeção não foram suficientes para definição. | D31: 21/03/2025 14:31:03 | E31: 0300077015 | F31: AL01065015 | G31: 3 | H31: 5700078015 | I31: 190-13697857 | J31: COEP | K31: Andresa da Silva Lima | L31: URGENTE | M31: SS PENDENTE | N31: 04/04/2025 14:28:22 | O31: 190.02338 | P31: 165 | Q31: LOCAL INSTAL TRANSFORMADOR DE DISTRIBUIÇÃO GIS | R31: PM TRANSFORMADOR | X31: SOBRECARGA PREVENTIVA | Z31: SOBRECARGA | AA31: SIM | AC31: ETO-COEP | AH31: ETO-COPC 00024/2025 | AI31: Não | AJ31: 9006069 | AK31: PEDRO AFONSO | AL31: 811652 | AO31: PLANO DE MEDIDAS | AP31: PENDÊNCIA DCMD | AQ31: FALAR COM A ANDRESSA | AR31: ANÁLISE | AS31: A DEFINIR (análise)
A32: ETO-COEP 00047/2026 | B32: 2026 | C32: favor verificar banco de capacitor 5950106122, com defeito interno, o mesmo nao foi indentificado aparentemente, porem foi a causa da ocorrencia 20253842360922 | D32: 20/09/2025 21:03:12 | E32: 0350106122 | F32: AL05097122 | G32: 3 | H32: 5950106122 | I32: 190-51584304 | J32: COI | K32: LAISON OLIVEIRA CARVALHO | L32: EMERGENCIAL | M32: SS PENDENTE | N32: 14/03/2026 08:15:19 | O32: 190.02661 | P32: 0 | Q32: BANCO CAPACITOR DE DISTRIBUIÇÃO GIS | R32: AVISO DE ANOMALIA | X32: CORPO (CÉLULA) | Z32: CURTO CIRCUITO | AA32: NÃO | AC32: ETO-COEP | AH32: DOLP-RD-PA 01250/2025 | AI32: Não | AJ32: 8868642 | AK32: PALMAS | AL32: 792093 | AO32: EQUIPAMENTO ESPECIAL | AP32: PENDÊNCIA DCMD | AQ32: REPASSAR DMSL | AR32: REPASSE | AS32: A DEFINIR (REPASSE)
A33: ETO-COEP 00048/2026 | B33: 2026 | C33: PARECER DMSL: A PEDIDO DA PCM DO NORTE LARA SOARES REALIZEI A CRIAÇÃO DESSA SS, EM RAZAO DA ANTIGAETO-TELE 337/2026 QUE FOI BAIXADA POR ENGANO DE TAL FORMA SEGUE A MESMA PARA REALIZAR AS TRATATIVAS. PENDENCIA: Religador continua by passado , equipamento está com defeito na parte ativa | D33: 16/03/2026 13:55:26 | E33: 7925871077 | F33: LD03105019 | G33: 2 | H33: 7925871077 | I33: 190-17512510 | J33: MANUT | K33: JULIA GRAZYELLE BRITO OLIVEIRA | L33: PROGRAMAVEL | M33: SS PENDENTE | N33: 20/04/2027 13:55:26 | O33: 190.02205 | P33: 2,846 | Q33: RELIGADOR DE REDE GIS | R33: INDISPONIBILIDADE PARA OPERAÇÃO | AA33: NÃO | AC33: ETO-COEP | AI33: Não | AJ33: 9145475 | AK33: GOIATINS | AL33: 905716 | AO33: EQUIPAMENTO ESPECIAL | AP33: PENDÊNCIA DCMD | AQ33: PARTE ATIVA | AR33: MANUTENÇÃO | AS33: PARTE ATIVA
A34: ETO-COEP 00049/2026 | B34: 2026 | C34: PARECER DMSL: *DATA*16/03/2026 Serviço Executado: É NECESSARIO REALIZAR A SUBSTITUIÇAO COMPLETA DO CONTROLE, EQUIPAMENTO DANIFICADO - FABRICANTE NOJA Equipamento ficou em operação?: Não Pendência: Sim, FAVOR REALIZAR AS CORREÇOES Bateria(s) Substituída(s): Não Data Fabricação/Instalação da(s) bateria(s): 07/2025 Equipe: Benvindo e Kaique PARECER DMSL : Solicitação já cumprida. Chamado 3047281 aberto em caráter emergencial, com comissionamento programado a partir de 02/02/2026. PARECER DA PROTEÇÃO: NOTA REPASSADA PARA DMSL, ABRIR CHAMADOS DE SCADA E COMISSIONAMENTO DO EQUIPAMENTO. ENG° IRLLEY CASTELO BRANCO. RELIGADOR N° 7963661046 INSTALADO NA OBRA 0202500503 GENTILEZA, REALIZAR O COMISSIONAMENTO. LAUDO EM ANEXO. COORD EO: 728315, 8830256 | D34: 30/01/2026 07:59:51 | E34: 8863660046 | F34: LD01056046 | G34: 2 | H34: 7963661046 | I34: 190-53434837 | J34: COPC | K34: Leonardo Sousa de Lima | L34: ALTA | M34: SS PENDENTE | N34: 17/05/2026 16:05:26 | O34: 190.02824 | P34: 1 | Q34: LOCAL INSTAL RELIGADOR DE LINHA GIS | R34: COMISSIONAMENTO | X34: RELIGADOR | AA34: NÃO | AC34: ETO-COEP | AH34: ETO-PROT 00033/2026 | AI34: Não | AJ34: 8830255 | AK34: NOVA ROSALANDIA | AL34: 728313 | AO34: EQUIPAMENTO ESPECIAL | AP34: PENDÊNCIA DMSL | AQ34: REPASSAR DMSL | AR34: REPASSE | AS34: A DEFINIR (REPASSE)
A35: ETO-COEP 00050/2026 | B35: 2026 | C35: PARECER DMSL: Data: 10/03/2026,Serviço Executado: Foi substituído o relé do equipamento, o mesmo estava danificado. Trocado o DPS, o mesmo estava queimado devido ao tanque estar furado. O equipamento ficou em bypass. Equipamento ficou em operação? Não Pendência? Sim, substituir a parte ativa com cordão umbilical.Equipe: Carliel e João Vitor SEGUE SS PARA REGULARIZAR AUTOMAÇÃO DO RL 7953610256 NA INTERLIGAÇÃO COM A COELBA (CHAPADA DA MANGABEIRA) - EQUIPE INFOMOU CURTO INTERNO NO GABINETE DJ AC NÃO FECHA | D35: 16/02/2026 05:43:10 | E35: 8800246256 | F35: LD03046026 | G35: 3 | H35: 7953610256 | I35: 190-43820334 | J35: COI | K35: DIONES COSTA SILVA | L35: EMERGENCIAL | M35: SS PENDENTE | N35: 21/03/2026 16:08:39 | O35: 190.02706 | P35: 5 | Q35: LOCAL INSTAL RELIGADOR DE LINHA GIS | R35: INDISPONIBILIDADE PARA OPERAÇÃO | X35: RELIGADOR | Z35: INSPEÇÃO VISUAL | AA35: NÃO | AC35: ETO-COEP | AH35: ETO-TELE 00292/2026 | AI35: Não | AJ35: 8855553 | AK35: MATEIROS | AL35: 1068871 | AO35: EQUIPAMENTO ESPECIAL | AP35: PENDÊNCIA DMSL | AQ35: REPASSAR DMSL | AR35: REPASSE | AS35: A DEFINIR (REPASSE)
A36: ETO-COEP 00051/2026 | B36: 2026 | C36: PARECER DMSL: Data: 12/03/2026 Serviço Executado: - Análise técnica constatou: - Parte ativa do equipamento danificada: necessita substituição - Trafo danificado: foi feitos testes nas buchas secundárias o mesmo não chega tensão - Vazamento de óleo - Necessita substituição Equipamento ficou em operação? Não Pendências: - Solicitar limpeza de faixa para acesso ao equipamento - Trocar parte ativa do equipamento - Substituir o trafo Equipe: Carliel e João Vitor Segue nota para envia equipe verificar falha de comunicação e automação no RL-7926442035 feito primeiro ataque com equipe 035OP02, porém sem sucesso. | D36: 18/02/2026 16:24:37 | E36: 7926442035 | F36: LD01051035 | G36: 3 | H36: 7926442035 | I36: 190-17513078 | J36: COI | K36: SAMUEL PINTO GOMES | L36: EMERGENCIAL | M36: SS PENDENTE | N36: 21/03/2026 16:15:05 | O36: 190.02206 | P36: 230 | Q36: RELIGADOR DE REDE GIS | R36: INDISPONIBILIDADE PARA OPERAÇÃO | X36: RELIGADOR | Z36: OUTROS | AA36: NÃO | AC36: ETO-COEP | AH36: ETO-TELE 00298/2026 | AI36: Não | AJ36: 8782076 | AK36: MONTE DO CARMO | AL36: 819553 | AO36: EQUIPAMENTO ESPECIAL | AP36: PENDÊNCIA DMSL | AQ36: REPASSAR DMSL | AR36: REPASSE | AS36: A DEFINIR (REPASSE)
A37: ETO-COEP 00054/2026 | B37: 2026 | C37: PARECER DMSL: PENDÊNCIA: Realizar melhoria no aterramento por ser tratar de um terreno muito arenoso, e há pendências por parte do time da proteção, os ajustes do RT não estão disponíveis para inserção no referido equipamento. DATA DA MANUTENÇÃO: 12/03/202 EQUIPE: Brunno e Edeglan. *********************** PARECER DA PROTEÇÃO: FAVOR COMISSIONAR REGULADOR 5865120195 – LD Santa Maria Ramal Centenário e Recursolândia – 34,5kV. AJUSTE REALIZADO, DISPONÍVEL NO APP DA PROTEÇÃO. *********************** INSTALADO NA OBRA 0702400720 GENTILEZA, REALIZAR O COMISSIONAMENTO. LAUDO EM ANEXO. COORD EO: 889017, 9016857 | D37: 11/02/2026 15:21:44 | E37: 8800183195 | F37: LD01065015 | G37: 3 | H37: 5865120195 | I37: 190-38281711 | J37: COPC | K37: Leonardo Sousa de Lima | L37: ALTA | M37: SS PENDENTE | N37: 23/05/2026 15:04:52 | O37: 190.02813 | P37: 2,628 | Q37: REGULADOR DE TENSÃO DE DISTRIBUIÇÃO GIS | R37: COMISSIONAMENTO | X37: REGULADOR DE TENSÃO | AA37: NÃO | AC37: ETO-COEP | AH37: ETO-PROT 00041/2026 | AI37: Não | AJ37: 9016857 | AK37: CENTENARIO | AL37: 889017 | AO37: EQUIPAMENTO ESPECIAL | AP37: PENDÊNCIA DMSL | AQ37: REPASSAR DMSL | AR37: REPASSE | AS37: A DEFINIR (REPASSE) | BA37: Melhoria da malha de aterramento Repassado para ETO-RD-GR- Novo número é 00538/2026
A38: ETO-COEP 00055/2025 | B38: 2025 | C38: substituir 7 vão de rede deteriorados de QP-35 mm multiplex no circuito do trafo 5703610004 - bairro Jardim dos Ipês II- rua 55 qd. 63 lt 34 - RDU Araguaina | D38: 07/11/2024 13:22:39 | E38: 5703610004 | F38: AL06010004 | G38: 3 | H38: 5703610004 | I38: 190-1657490 | J38: COI | K38: VALERIA DE JESUS BORGES CARVAL | L38: URGENTE | M38: SS PENDENTE | N38: 10/04/2025 17:27:50 | O38: 190.00955 | P38: 66 | Q38: POSTE RD GIS | R38: AVISO DE ANOMALIA | X38: CABOS BT | Z38: DETERIORADA | AA38: NÃO | AC38: ETO-COEP | AD38: Tocantins | AH38: ETO-RD-AR 01903/2024 | AI38: Não | AJ38: 9205890 | AK38: ARAGUAINA | AL38: 804712 | AN38: SI-3 | AO38: CABOS FORA COEP | AP38: PENDÊNCIA DCMD | AQ38: CABOS | AR38: MANUTENÇÃO | AS38: CABOS | AU38: REPETIDA | AV38: 0 | AW38: 0
A39: ETO-COEP 00055/2026 | B39: 2026 | C39: DCMD 26.03.2026. SS REPASSADA PARA COEP PROVIDENCIAR MATERIAL. NÃO TEMOS O MATERIAL EM ESTOQUE PARA SUBSTITUIÇÃO. COEP: Equipamento fornecido ao COCM-S para regularização. PARECER DA PROTEÇÃO: EQUIPAMENTOS FURTADOS. PARA AQUISIÇÃO DAS CELULAS DE REPOSIÇÃO, FAVOR CONSULTAR OS DADOS DE PLACA EM ANEXO. PARECER DA PROTEÇÃO: COMISISONAR RT 5856156091 LD DIANOPOLIS A NATIVIDADE. NECESSARIO REALIZAR MEDIÇÕES DA RESISTENCIA DA MALHA DE ATERRAMENTO. AJUSTES DISPONIVEIS NO APP DA PROTEÇÃO. RELIGADOR N° 5856156091 INSTALADO NA OBRA 0502400526 GENTILEZA, REALIZAR O COMISSIONAMENTO. LAUDO EM ANEXO. COORD EO: 899501, 8714782 | D39: 16/06/2025 15:50:51 | E39: 8832258091 | F39: LD04002091 | G39: 1 | H39: 5856156091 | I39: 190-38238593 | J39: COPC | K39: Leonardo Sousa de Lima | L39: PROGRAMAVEL | M39: SS PENDENTE | N39: 30/04/2027 11:42:48 | O39: 190.02786 | P39: 1,586 | Q39: REGULADOR DE TENSÃO DE DISTRIBUIÇÃO GIS | R39: INDISPONIBILIDADE PARA OPERAÇÃO | X39: REGULADOR DE TENSÃO | AA39: NÃO | AC39: ETO-COEP | AH39: ETO-PROT 00198/2025 | AI39: Não | AJ39: 8714782 | AK39: ALMAS | AL39: 899501 | AO39: EQUIPAMENTO ESPECIAL | AP39: PENDÊNCIA DMSL | AQ39: REPASSAR DMSL | AR39: REPASSE | AS39: A DEFINIR (REPASSE)
A40: ETO-COEP 00056/2025 | B40: 2025 | C40: PARECER DMSL: Religador está com o tanque danificado. Não responde a comandos abertura e fechamento local ou remoto, pois está com sinal de curto circuito. Necessário trocar o equipamento. Para raio do trafo está queimado. Chave de saída da fase C está com o olhal quebrado, necessário substituir a chave. Equipamento ficou bypassado em campo. Aberto entrada e saída, com exceção da fase C de saída que ficou fechada. Favor, substituir equipamento completo por NOJA RC10 e sanar demais pendencias. Senhores Favor verificar RL 7900230155 o mesmo sinalizou aberto no SCADA porem a cidade de Palmeirante estava normal , feito um reset no rl e o mesmo subiu fechado. | D40: 29/03/2025 18:25:59 | E40: 9000231155 | F40: LD02105019 | G40: 2 | H40: 7900230155 | I40: 190-17408809 | J40: COI | K40: CLEONE PEREIRA DE SOUZA LIMA | L40: EMERGENCIAL | M40: SS PENDENTE | N40: 07/04/2025 14:14:07 | O40: 190.00019 | P40: 992 | Q40: LOCAL INSTAL RELIGADOR DE LINHA GIS | R40: INDISPONIBILIDADE PARA OPERAÇÃO | X40: RELIGADOR | Z40: INSPEÇÃO VISUAL | AA40: SIM | AC40: ETO-COEP | AD40: Tocantins | AH40: ETO-TELE 00307/2025 | AI40: Não | AJ40: 9129950 | AK40: PALMEIRANTE | AL40: 834706 | AO40: EQUIPAMENTO ESPECIAL | AP40: PENDÊNCIA DCMD | AQ40: REPASSAR DMSL | AR40: REPASSE | AS40: A DEFINIR (REPASSE)
A41: ETO-COEP 00056/2026 | B41: 2026 | C41: COCMS 26.03.26. SS REPASSADA PARA COEP PROVIDENCIAR MATERIAL. NÃO TEMOS AS PÇ EM ESTOQUE PARA FAZER A SUBSTITUIÇÃO. Solicitação de serviço para reposição de equipamentos furtados . COEP: Equipamento fornecido ao COCM-S para regularização. COCMS: Equipamento substituido conforme solicitado. Gentileza comissionar. PARECER DA PROTEÇÃO: SEGUE NOTA REPASSADA PARA DMSL COMISSIONAR. ENG° IRLLEY CASTELO BRANCO PARECER DMSL(23/09/2025): Feito a parte de comunicação, fechando enlace, configuração do rádio GE. Feito a medição de aterramento. Após uma inspeção, foi identificado que o regulador de tensão está instalado errado, carga está para o lado de fonte e fonte está do lado de carga. O certo é a fonte vim de almas, atualmente está vindo de natividade. Favor fazer a instalação correta. | D41: 18/07/2025 11:01:15 | F41: LD04002091 | H41: 5856070091 | I41: 190-55087821 | J41: COI | K41: LEONARDO SIQUEIRA AMORIM | L41: BAIXA | M41: SS PENDENTE | N41: 22/09/2026 11:44:19 | O41: 190.02761 | P41: 0 | Q41: REGULADOR DE TENSÃO DE DISTRIBUIÇÃO GIS | R41: INDISPONIBILIDADE PARA OPERAÇÃO | AA41: NÃO | AC41: ETO-COEP | AH41: ETO-COEP 00153/2025 | AI41: Não | AJ41: 8717852 | AK41: ALMAS | AL41: 905857 | AO41: EQUIPAMENTO ESPECIAL | AP41: PENDÊNCIA DCMD | AQ41: REPASSAR DMSL | AR41: REPASSE | AS41: A DEFINIR (REPASSE)
A42: ETO-COEP 00057/2024 | B42: 2024 | C42: por favor deslocar equipe da manutenção pesada nos bancos capacitor 5900326004 , 5900383004 com vazamento de óleo e os 5924849004 inspecionado com defeito nas fases A,B,C, e o 5900600004 fases A,C com defeito foi informado pela equipe DEC de Araguaína telefone 6399250-4970 | D42: 24/04/2024 17:26:41 | F42: AL04103004 | H42: 5900383004 | I42: 190-16324053 | J42: COI | K42: SIRDEIS ALVES MONTEIRO | L42: EMERGENCIAL | M42: SS PENDENTE | N42: 03/05/2024 11:40:43 | O42: 190.02318 | P42: 0 | Q42: BANCO CAPACITOR DE DISTRIBUIÇÃO GIS | R42: INDISPONIBILIDADE PARA OPERAÇÃO | X42: OUTROS | Z42: VAZAMENTO DE ÓLEO | AA42: NÃO | AC42: ETO-COEP | AH42: ETO-RD-AR 00796/2024 | AI42: Não | AJ42: 9204224 | AK42: ARAGUAINA | AL42: 809973 | AO42: EQUIPAMENTO ESPECIAL | AP42: PENDÊNCIA DCMD | AQ42: REPETIDO | AR42: ANÁLISE | AS42: REPETIDO (revisar) | AT42: ETO-COEP 00057/2024 | BA42: Falta atendimento -COCM Araguaína - No mapa Ts continua fora de operação
A43: ETO-COEP 00057/2026 | B43: 2026 | C43: RELIGADOR COM RELÉ DANIFICADO, REALIZAR SUBSTITUIÇÃO | D43: 26/03/2026 15:48:39 | E43: 7923673004 | F43: AL04010004 | G43: 2 | H43: 7923673004 | I43: 190-17421632 | J43: SCADA | K43: LARA SOARES FARIAS | L43: PROGRAMAVEL | M43: SS PENDENTE | N43: 30/04/2027 15:48:39 | O43: 190.02207 | P43: 0 | Q43: RELIGADOR DE REDE GIS | R43: INDISPONIBILIDADE PARA OPERAÇÃO | AA43: NÃO | AC43: ETO-COEP | AI43: Não | AJ43: 9204335 | AK43: ARAGUAINA | AL43: 808350 | AO43: EQUIPAMENTO ESPECIAL | AP43: PENDÊNCIA DCMD | AQ43: RELÉ | AR43: MANUTENÇÃO | AS43: RELÉ
A44: ETO-COEP 00058/2024 | B44: 2024 | C44: por favor deslocar equipe da manutenção pesada nos bancos capacitor 5900326004 , 5900383004 com vazamento de óleo e os 5924849004 inspecionado com defeito nas fases A,B,C, e o 5900600004 fases A,C com defeito foi informado pela equipe DEC de Araguaína telefone 6399250-4970 | D44: 24/04/2024 17:26:41 | E44: 0324849004 | F44: AL03103004 | G44: 3 | H44: 5924849004 | I44: 190-27730714 | J44: COI | K44: SIRDEIS ALVES MONTEIRO | L44: ALTA | M44: SS PENDENTE | N44: 29/06/2024 11:41:13 | O44: 190.02679 | P44: 0 | Q44: BANCO CAPACITOR DE DISTRIBUIÇÃO GIS | R44: INDISPONIBILIDADE PARA OPERAÇÃO | X44: OUTROS | Z44: VAZAMENTO DE ÓLEO | AA44: NÃO | AC44: ETO-COEP | AH44: ETO-RD-AR 00797/2024 | AI44: Não | AJ44: 9203976 | AK44: ARAGUAINA | AL44: 810560 | AO44: EQUIPAMENTO ESPECIAL | AP44: PENDÊNCIA DCMD | AQ44: REPETIDO | AR44: ANÁLISE | AS44: REPETIDO (revisar) | AT44: ETO-COEP 00057/2024 | BA44: Falta atendimento -COCM Araguaína - No mapa Ts continua fora de operação
A45: ETO-COEP 00058/2026 | B45: 2026 | C45: PARECER DMSL: FEEDBACK EQUIP. ESPECIAIS Nº DO EQUIPAMENTO: 7925733015 TIPO EQUIPAMENTO: Noja RC10 TIPO DE COMUNICAÇÃO: Rádio GE DATA DA MANUTENÇÃO: 24/03/2026 SID: 1475/2026 DESCRIÇÃO: Tanque do equipamento em Curto FICOU EM OPERAÇÃO?: Não PENDÊNCIA: Sim, repassar a nota para DCMD substituir tanque. DADOS DIVERGENTES DA PROGRAMAÇÃO: Não BATERIA SUBSTITUÍDA?: Não TIPO DE BATERIA: Lítio EQUIPE: Edicleber e Jhonata(DEOP) ------------------------------------------------------------------------------------------------------ religador 7925733015 com defeito, equipe fez abertura da chave de saida do mesmo e ele não aceita fehcamento devido provavel curto-circuito interno, enviar equipe para verificar o mesmo ficou by-pass fechado | D45: 13/03/2026 20:07:30 | E45: 9001166015 | F45: LD01414015 | G45: 3 | H45: 7925733015 | I45: 190-17404247 | J45: COI | K45: ARTHUR MAGALHAES DAS DORES | L45: EMERGENCIAL | M45: SS PENDENTE | N45: 02/04/2026 09:54:49 | O45: 190.01239 | P45: 136 | Q45: LOCAL INSTAL RELIGADOR DE LINHA GIS | R45: INDISPONIBILIDADE PARA OPERAÇÃO | X45: RELIGADOR | Z45: QUEIMADO | AA45: NÃO | AC45: ETO-COEP | AD45: Tocantins | AH45: ETO-TELE 00367/2026 | AI45: Não | AJ45: 8984037 | AK45: PEDRO AFONSO | AL45: 813445 | AO45: EQUIPAMENTO ESPECIAL | AP45: PENDÊNCIA DCMD | AQ45: ENTENDER | AR45: ANÁLISE | AS45: A DEFINIR (análise)
A46: ETO-COEP 00059/2024 | B46: 2024 | C46: por favor deslocar equipe da manutenção pesada nos bancos capacitor 5900326004 , 5900383004 com vazamento de óleo e os 5924849004 inspecionado com defeito nas fases A,B,C, e o 5900600004 fases A,C com defeito foi informado pela equipe DEC de Araguaína telefone 6399250-4970 | D46: 24/04/2024 17:26:41 | F46: AL04010004 | H46: 5900600004 | I46: 190-16324009 | J46: COI | K46: SIRDEIS ALVES MONTEIRO | L46: EMERGENCIAL | M46: SS PENDENTE | N46: 03/05/2024 11:41:46 | O46: 190.02318 | P46: 0 | Q46: BANCO CAPACITOR DE DISTRIBUIÇÃO GIS | R46: INDISPONIBILIDADE PARA OPERAÇÃO | X46: OUTROS | Z46: VAZAMENTO DE ÓLEO | AA46: NÃO | AC46: ETO-COEP | AH46: ETO-RD-AR 00798/2024 | AI46: Não | AJ46: 9204643 | AK46: ARAGUAINA | AL46: 807522 | AO46: EQUIPAMENTO ESPECIAL | AP46: PENDÊNCIA DCMD | AQ46: REPETIDO | AR46: ANÁLISE | AS46: REPETIDO (revisar) | AT46: ETO-COEP 00057/2024 | BA46: Falta atendimento -COCM Araguaína - No mapa Ts continua fora de operação
A47: ETO-COEP 00059/2026 | B47: 2026 | C47: PARECER DMSL: FEEDBACK EQUIP. ESPECIAIS Nº DO EQUIPAMENTO: 7925744087 TIPO EQUIPAMENTO: Noja RC 10 TIPO DE COMUNICAÇÃO: Radio GE IP DATA DA MANUTENÇÃO: 19/02/2026 SID: 735/2026 DESCRIÇÃO: foi identificado água dentro da parte interna do tanque e cabo umbilical encharcado de água foi passado essas informações para COS. FICOU EM OPERAÇÃO?: Não PENDÊNCIA: Sim substituir tanque e cabo umbilical DADOS DIVERGENTES DA PROGRAMAÇÃO: Não BATERIA SUBSTITUÍDA?: Não DATA DA BATERIA: 07/05/2025 TIPO DE BATERIA: Lítio EQUIPE: Edeglan e Janio ------------------------------------------------------------------------------------------------- RELIGADOR SEM COMUNICAÇÃO, APOS PRIMEIRO ATAQUE RETORNA E FICAR INDEFINIDO. | D47: 09/02/2026 23:47:44 | E47: 9025744087 | F47: LD02022033 | G47: 3 | H47: 7925744087 | I47: 190-17408622 | J47: COI | K47: CLESIO CARVALHO MOURA | L47: EMERGENCIAL | M47: SS PENDENTE | N47: 02/04/2026 10:22:38 | O47: 190.01237 | P47: 0 | Q47: LOCAL INSTAL RELIGADOR DE LINHA GIS | R47: INDISPONIBILIDADE PARA OPERAÇÃO | X47: RELÉ | Z47: FALTANDO | AA47: NÃO | AC47: ETO-COEP | AD47: Tocantins | AH47: ETO-TELE 00284/2026 | AI47: Não | AJ47: 9029671 | AK47: GOIANORTE | AL47: 727489 | AO47: EQUIPAMENTO ESPECIAL | AP47: PENDÊNCIA DCMD | AQ47: RELIGADOR - TANQUE E CABO UMBILICAL | AR47: MANUTENÇÃO | AS47: RELIGADOR
A48: ETO-COEP 00060/2024 | B48: 2024 | C48: Nota para manutenção substituir banco capacitor 5913313004 na RDU de Araguina o mesmo não aceitou fechamento | D48: 26/04/2024 05:51:18 | E48: 0313313004 | F48: AL05010004 | G48: 3 | H48: 5913313004 | I48: 190-29121990 | J48: COI | K48: CLEIDSON RODRIGUES VIEIRA | L48: EMERGENCIAL | M48: SS PENDENTE | N48: 03/05/2024 11:42:27 | O48: 190.02712 | P48: 0 | Q48: BANCO CAPACITOR DE DISTRIBUIÇÃO GIS | R48: INDISPONIBILIDADE PARA OPERAÇÃO | X48: CORPO (CÉLULA) | Z48: ABERTURA INDEVIDA DA PROTEÇÃO | AA48: NÃO | AC48: ETO-COEP | AH48: ETO-RD-AR 00806/2024 | AI48: Não | AJ48: 9202268 | AK48: ARAGUAINA | AL48: 804877 | AO48: EQUIPAMENTO ESPECIAL | AP48: PENDÊNCIA DCMD | AQ48: BANCO DE CAPACITOR | AR48: MANUTENÇÃO | AS48: BANCO DE CAPACITOR
A49: ETO-COEP 00060/2026 | B49: 2026 | C49: PARECER DMSL: Realizar substituição do equipamento todo e parte ativa. Equipe: Adeilton e Edicleber Data: 12/03 ----------------------------------------------------------------------------- Religador sem comunicação, apos primeiro ataque o mesmo não retornou as comunicação. | D49: 11/03/2026 18:20:05 | E49: 9004017004 | F49: AL05010004 | G49: 2 | H49: 7903569004 | I49: 190-17337604 | J49: COI | K49: CLESIO CARVALHO MOURA | L49: EMERGENCIAL | M49: SS PENDENTE | N49: 02/04/2026 11:02:53 | O49: 190.0001 | P49: 0 | Q49: LOCAL INSTAL RELIGADOR DE LINHA GIS | R49: INDISPONIBILIDADE PARA OPERAÇÃO | X49: RELÉ | Z49: FALTANDO | AA49: NÃO | AC49: ETO-COEP | AD49: Tocantins | AH49: ETO-TELE 00360/2026 | AI49: Não | AJ49: 9202999 | AK49: ARAGUAINA | AL49: 807531 | AO49: EQUIPAMENTO ESPECIAL | AP49: PENDÊNCIA DMSL | AQ49: REPASSAR DMSL | AR49: REPASSE | AS49: A DEFINIR (REPASSE)
A50: ETO-COEP 00061/2026 | B50: 2026 | C50: PARECER DMSL: Serviço Executado: Foi feito análise técnica, testes funcionais e identificado que a parte ativa do equipamento está com defeito. Necessário substituir a parte ativa. FICOU EM OPERAÇÃO? Não- EQUIPE: Carliel e Benvindo Segue SS para verificaçao Rl esta danificado dando passagem de tensão mesmo aberto Sim, quando retornar trazer uma fonte pois a mesma foi removida. | D50: 17/12/2025 05:52:25 | E50: 9001107084 | F50: LD04062013 | G50: 2 | H50: 7901110084 | I50: 190-17407509 | J50: COI | K50: JANES FERREIRA DA SILVA | L50: EMERGENCIAL | M50: SS PENDENTE | N50: 03/04/2026 09:38:27 | O50: 190.00128 | P50: 0 | Q50: LOCAL INSTAL RELIGADOR DE LINHA GIS | R50: INDISPONIBILIDADE PARA OPERAÇÃO | X50: BUCHAS DE PASSAGEM | Z50: CORROSÃO / OXIDAÇÃO | AA50: NÃO | AC50: ETO-COEP | AD50: Tocantins | AH50: ETO-TELE 01495/2025 | AI50: Não | AJ50: 8916959 | AK50: DIVINOPOLIS DO TOCANTINS | AL50: 695579 | AO50: EQUIPAMENTO ESPECIAL | AP50: PENDÊNCIA DCMD | AQ50: PARTE ATIVA | AR50: MANUTENÇÃO | AS50: PARTE ATIVA
A51: ETO-COEP 00062/2026 | B51: 2026 | C51: PARECER DMSL : Equipamento com a placa de alimentação ca em curto, será necessário substituir a placa do equipamento. Equipamento ficou em operação?: Não Pendência: Sim OBS :Data Fabricação/Instalação da(s) bateria(s): 04/2024 Equipe: Benvindo e Kaique- SS ANTIGA 277/2026 BAIXADA POR ENGANO PELA EQUIPE | D51: 31/03/2026 09:53:16 | E51: 7955986084 | F51: LD04062013 | G51: 2 | H51: 7955986084 | I51: 190-28065672 | J51: MANUT | K51: JULIA GRAZYELLE BRITO OLIVEIRA | L51: URGENTE | M51: SS PENDENTE | N51: 07/04/2026 10:56:57 | O51: 190.02736 | P51: 445 | Q51: RELIGADOR DE REDE GIS | R51: INDISPONIBILIDADE PARA OPERAÇÃO | AA51: NÃO | AC51: ETO-COEP | AH51: ETO-RD-PS 00162/2026 | AI51: Não | AJ51: 8916924 | AK51: DIVINOPOLIS DO TOCANTINS | AL51: 695371 | AO51: EQUIPAMENTO ESPECIAL | AP51: PENDÊNCIA DMSL | AQ51: REPASSAR DMSL | AR51: REPASSE | AS51: A DEFINIR (REPASSE)
A52: ETO-COEP 00063/2025 | B52: 2025 | C52: Equipe identificou em campo que o tanque se encontra queimado, solicitamos a substituição | D52: 15/04/2025 16:20:57 | E52: 9001744074 | F52: LD05028074 | G52: 2 | H52: 7908206074 | I52: 190-17404114 | J52: MANUT | K52: Lorrane Sousa Gonçalves | L52: ALTA | M52: SS PENDENTE | N52: 14/06/2025 16:20:57 | O52: 190.00041 | P52: 120 | Q52: LOCAL INSTAL RELIGADOR DE LINHA GIS | R52: INDISPONIBILIDADE PARA OPERAÇÃO | AA52: SIM | AC52: ETO-COEP | AD52: Tocantins | AI52: Não | AJ52: 8699956 | AK52: DIANOPOLIS | AL52: 944748 | AO52: EQUIPAMENTO ESPECIAL | AP52: PENDÊNCIA DCMD | AQ52: TANQUE | AR52: MANUTENÇÃO | AS52: TANQUE
A53: ETO-COEP 00063/2026 | B53: 2026 | C53: Equipamento ficou em operação?: Não Pendência: Sim será necessário substituir a placa Serviço Executado: curto na placa foi tentando recuperar a mesma porém não teve sucesso! Bateria(s)substituída(s)? NÃO Equipe: Kaique e benvido | D53: 17/03/2026 10:04:45 | E53: 7944559149 | F53: LD01434149 | G53: 3 | H53: 7944559149 | I53: 190-35120642 | J53: MANUT | K53: JULIA GRAZYELLE BRITO OLIVEIRA | L53: PROGRAMAVEL | M53: SS PENDENTE | N53: 05/05/2027 10:57:50 | O53: 190.02687 | P53: 256 | Q53: RELIGADOR DE REDE GIS | R53: INDISPONIBILIDADE PARA OPERAÇÃO | AA53: NÃO | AC53: ETO-COEP | AH53: ETO-RD-PS 00163/2026 | AI53: Não | AJ53: 8986227 | AK53: CASEARA | AL53: 630275 | AO53: EQUIPAMENTO ESPECIAL | AP53: PENDÊNCIA DMSL | AQ53: REPASSAR DMSL | AR53: REPASSE | AS53: A DEFINIR (REPASSE)
A54: ETO-COEP 00064/2025 | B54: 2025 | C54: Corrigir anomalia no BC 5900293123 que atende a Bonasa em Aguiarnopolis. Ao fazer teste no mesmo a fase A não aceitou. | D54: 12/04/2025 13:00:22 | E54: 0300293123 | F54: AL02055123 | G54: 3 | H54: 5900293123 | I54: 190-26830949 | J54: COI | K54: ANTONIO FAGNER ALVES RIBEIRO | L54: ALTA | M54: SS PENDENTE | N54: 15/06/2025 07:34:07 | O54: 190.02737 | P54: 0 | Q54: BANCO CAPACITOR DE DISTRIBUIÇÃO GIS | R54: INDISPONIBILIDADE PARA OPERAÇÃO | X54: FORA DE SERVIÇO | Z54: CURTO CIRCUITO | AA54: SIM | AC54: ETO-COEP | AH54: ETO-RD-AG 00455/2025 | AI54: Não | AJ54: 9277884 | AK54: AGUIARNOPOLIS | AL54: 891790 | AO54: EQUIPAMENTO ESPECIAL | AP54: PENDÊNCIA DCMD | AQ54: BANCO DE CAPACITOR | AR54: MANUTENÇÃO | AS54: BANCO DE CAPACITOR
A55: ETO-COEP 00064/2026 | B55: 2026 | C55: PARECER DMSL: Necessário substituir a placa de alimentação ca, a mesma está em curto não conseguimos recuperar. Equipamento ficou em operação?: _Nao Pendência: Sim Bateria(s) Substituída(s)? Não Data Fabricação/Instalação da(s) bateria(s): 06/2024 Equipe: Benvindo e Kaique ---------------------------------------------------------------------- RL 7955946007 SEM COMUNICAÇÃO FEITO PRIMEIRO ATAQUE-- | D55: 02/03/2026 21:33:09 | E55: 6800948007 | F55: LD05050008 | G55: 3 | H55: 7955946007 | I55: 190-21578328 | J55: COI | K55: PAULO AUGUSTO DA SILVA MORAIS | L55: EMERGENCIAL | M55: SS PENDENTE | N55: 09/04/2026 09:40:39 | O55: 190.02731 | P55: 262 | Q55: LOCAL INSTAL RELIGADOR DE LINHA GIS | R55: INDISPONIBILIDADE PARA OPERAÇÃO | X55: RELIGADOR | Z55: INSPEÇÃO VISUAL | AA55: NÃO | AC55: ETO-COEP | AH55: ETO-TELE 00341/2026 | AI55: Não | AJ55: 8929207 | AK55: MIRACEMA DO TOCANTINS | AL55: 787602 | AO55: EQUIPAMENTO ESPECIAL | AP55: PENDÊNCIA DMSL | AQ55: REPASSAR DMSL | AR55: REPASSE | AS55: A DEFINIR (REPASSE)
A56: ETO-COEP 00065/2026 | B56: 2026 | C56: Limpeza de Faixa Rede Media na repetidora Xambioa. | D56: 07/04/2026 15:23:59 | F56: REP.XAMBIOA | I56: REPETIDORA XAMBIOÁ | J56: SCADA | K56: LARA SOARES FARIAS | L56: PROGRAMAVEL | M56: SS PENDENTE | N56: 12/05/2027 15:23:59 | O56: 190.00248 | P56: 0 | Q56: LOC INSTAL REPETIDORA | R56: SOLICITAÇÃO DE SERVIÇO | AA56: NÃO | AC56: ETO-COEP | AD56: Tocantins | AI56: Não | AO56: LIMPEZA DE FAIXA | AP56: PENDÊNCIA DCMD | AQ56: REPASSAR SANDRO | AR56: REPASSE | AS56: A DEFINIR (REPASSE) | AT56: Cancelada - Limpeza de faixa somente pelo aplicativo
A57: ETO-COEP 00066/2026 | B57: 2026 | C57: PARECER DMSL: *FEEDBACK EQUIP. ESPECIAIS* *Nº DO EQUIPAMENTO:* 5800291077 *DATA DA MANUTENÇÃO:* 07/04/2026 *SID:* 1709/2026 *DESCRIÇÃO:* Realizado ensaios nas células do banco 5800291077, identificado fase B em curto *FICOU EM OPERAÇÃO?:* Não *PENDÊNCIA:* SIM *EQUIPE:* Adeilton e Edicleber Realizar substituição da célula da fase B Em curto. _____________________________________________________________ Segue SS para enviar equipe do DMSL para no regulador de tensão 5800291077. O mesmo ficou bay passado devido esta com defeito e causar desarme na LD e penalizar a RDU de Goiatins. Por gentileza enviar equipe urgente. | D57: 03/04/2026 21:12:34 | E57: 8800288077 | F57: LD03105019 | G57: 2 | H57: 5800291077 | I57: 190-49492686 | J57: COI | K57: HERIK BUARQUE DOS SANTOS | L57: EMERGENCIAL | M57: SS PENDENTE | N57: 11/04/2026 14:03:04 | O57: 190.02726 | P57: 2,846 | Q57: REGULADOR DE TENSÃO DE DISTRIBUIÇÃO GIS | R57: INDISPONIBILIDADE PARA OPERAÇÃO | X57: DEFEITO MECANICO | Z57: RELÉ REGULADOR DE TENSÃO | AA57: NÃO | AC57: ETO-COEP | AH57: ETO-TELE 00498/2026 | AI57: Não | AJ57: 9145471 | AK57: GOIATINS | AL57: 905726 | AO57: EQUIPAMENTO ESPECIAL | AP57: PENDÊNCIA DMSL | AQ57: REPASSAR DMSL | AR57: REPASSE | AS57: A DEFINIR (REPASSE)
A58: ETO-COEP 00068/2026 | B58: 2026 | C58: PARECER DMSL: *FEEDBACK EQUIP. ESPECIAIS* *Nº DO EQUIPAMENTO:* 7929376022 *DATA DA MANUTENÇÃO:* 02/04/2026 *SID:* 1677/2026 *DESCRIÇÃO:* Trocar controle completo *PENDÊNCIA:* Sim. *DADOS DIVERGENTES DA PROGRAMAÇÃO:* Não *BATERIA SUBSTITUÍDA?:* Não *EQUIPE:* Adeilton e Edicleber __________________________________________________________ POR GENTILEZA ATENDER SOLICITAÇÃO PRIMEIRO ATAQUE IDENTIFICOU QUE RELE ESTA EM CURTO NOTA ABERTA 224/2026 FOI BAIXADA POREM NÃO FOI CORRIGIDO PROBLEMA EM CAMPO. | D58: 25/03/2026 14:38:13 | E58: 9001690022 | F58: LD05010004 | G58: 3 | H58: 7929376022 | I58: 190-17408409 | K58: GERCILIO PEDROZA JUNIOR | L58: EMERGENCIAL | M58: SS PENDENTE | N58: 16/04/2026 10:51:38 | O58: 190.01269 | P58: 0 | Q58: LOCAL INSTAL RELIGADOR DE LINHA GIS | R58: INDISPONIBILIDADE PARA OPERAÇÃO | AA58: NÃO | AC58: ETO-COEP | AD58: Tocantins | AH58: ETO-TELE 00409/2026 | AI58: Não | AJ58: 9201747 | AK58: BABACULANDIA | AL58: 858418 | AO58: EQUIPAMENTO ESPECIAL | AP58: PENDÊNCIA DCMD | AQ58: REPASSAR DMSL | AR58: REPASSE | AS58: A DEFINIR (REPASSE) | AT58: Vamos fazer
A59: ETO-COEP 00069/2026 | B59: 2026 | C59: Segue ss de 06 chaves faca da rede de 34.500kv no id, 59408745 e no id, 59411689 estrutura HT para ser instalada pela equipe de manutencão linha viva devido tratar se da LD de aparecida a novo acordo, trecho longo de 8 KM sem chaves na linha acesso bom equipe que atendeu 083op01 63992188010 marcelo 63991155898 Dielano favor agilizar o atendimento para facilitar as nossas manobras na LD obs, não tem clientes penalizados porém estamos precisando muito da instalacão desta chave na linha para energisar a fazenda do governador em menos tempo favor agilizar o atendimento | D59: 01/03/2026 08:49:12 | E59: 9000448083 | F59: LD01059122 | G59: 2 | H59: 9000448083 | I59: 190-419413 | J59: COI | K59: JOAO PAULO VASCONCELOS MARINHO | L59: EMERGENCIAL | M59: SS PENDENTE | N59: 16/04/2026 15:29:44 | O59: 190.00412 | P59: 402 | Q59: POSTE RD GIS | R59: NOTA DE SERVIÇO (NS) - LINHA VIVA | X59: CHAVE | Z59: INEXISTENTE | AA59: NÃO | AC59: ETO-COEP | AD59: Tocantins | AH59: DOLP-RD-PA 00304/2026 | AI59: Não | AJ59: 8898809 | AK59: APARECIDA DO RIO NEGRO | AL59: 836182 | AM59: SR1 | AO59: PLANO DE MEDIDAS | AP59: PENDÊNCIA DCMD | AQ59: REPASSAR COCM | AR59: REPASSE | AS59: A DEFINIR (REPASSE) | AU59: REPETIDA
A60: ETO-COEP 00070/2026 | B60: 2026 | C60: Segue ss de 06 chaves faca da rede de 34.500kv no id, 59408745 e no id, 59411689 estrutura HT para ser instalada pela equipe de manutencão linha viva devido tratar se da LD de aparecida a novo acordo, trecho longo de 8 KM sem chaves na linha acesso bom equipe que atendeu 083op01 63992188010 marcelo 63991155898 Dielano favor agilizar o atendimento para facilitar as nossas manobras na LD obs, não tem clientes penalizados porém estamos precisando muito da instalacão desta chave na linha para energisar a fazenda do governador em menos tempo favor agilizar o atendimento | D60: 01/03/2026 08:49:12 | E60: 9000448083 | F60: LD01059122 | G60: 2 | H60: 9000448083 | I60: 190-418433 | J60: COI | K60: JOAO PAULO VASCONCELOS MARINHO | L60: EMERGENCIAL | M60: SS PENDENTE | N60: 16/04/2026 15:30:19 | O60: 190.00413 | P60: 402 | Q60: POSTE RD GIS | R60: NOTA DE SERVIÇO (NS) - LINHA VIVA | X60: CHAVE | Z60: INEXISTENTE | AA60: NÃO | AC60: ETO-COEP | AD60: Tocantins | AH60: DOLP-RD-PA 00305/2026 | AI60: Não | AJ60: 8898765 | AK60: APARECIDA DO RIO NEGRO | AL60: 836741 | AM60: N1 | AO60: PLANO DE MEDIDAS | AP60: PENDÊNCIA DCMD | AQ60: REPASSAR COCM | AR60: REPASSE | AS60: A DEFINIR (REPASSE) | AU60: REPETIDA
A61: ETO-COEP 00071/2026 | B61: 2026 | C61: PARECER DMSL: SS ETO TELE 404/2026 ENCERRADA POR ENGANO Feedback Equipamentos Especiais Local: Rural Ponte Alta Equipe: Benvindo e Kaique Equipamento: 7908302256 Designação: ENEG-0299-TO-H14 SLave: 19 Porta: 20000 REDE 10.163.249.152/30 SKYEDGE 10.163.249.153 RELÉ 10.163.249.154 Aponta - Diver BROADCAST 10.163.249.155 MASK 255.255.255.252 H14:(Eutelsat 8W) ID VSAT:20885 Managed Group: 18 Frequência:11595000 SR:32727 Lnblo - 10.75 (NÃO FUNCIONA) Lnb chaveado colocar em L - lnblo 9.75Ghz 093 A - Buc 13.05 (AN7000 grande 2W,3W,4W) 093 B - Buc 12.80 (AN7233 pequeno de 2W) Se o buc for de 13.05 o "RF Cluster Code" é 093A, se o buc for¿12.80¿é¿093B Enter location CODE: 000M Serviço Executado: Equipamento com a parte ativa com defeito, será necessário fazer a substituição da mesma! Obs. Foi retirado a placa de alimentação ca. Pendência: Sim Equipamento ficou em operação: Não Bateria(s) Substituída(s): não Data Fabricação/Instalação da(s) bateria(s): | D61: 06/04/2026 11:03:44 | E61: 7908302256 | F61: LD03046026 | G61: 2 | H61: 7908302256 | I61: 190-28327585 | J61: MANUT | K61: JULIA GRAZYELLE BRITO OLIVEIRA | L61: ALTA | M61: SS PENDENTE | N61: 13/06/2026 11:03:44 | O61: 190.02703 | P61: 2,103 | Q61: RELIGADOR DE REDE GIS | R61: INDISPONIBILIDADE PARA OPERAÇÃO | AA61: NÃO | AC61: ETO-COEP | AI61: Não | AJ61: 8838426 | AK61: MATEIROS | AL61: 936573 | AO61: EQUIPAMENTO ESPECIAL | AP61: PENDÊNCIA DCMD | AQ61: PARTE ATIVA | AR61: MANUTENÇÃO | AS61: PARTE ATIVA
A62: ETO-COEP 00072/2026 | B62: 2026 | C62: Nota para manutenção substituir religador 7900525015 que está com as buchas de entrada danificadas fase A estourada e bc danificadas Local LD Pedro Afonso A Chaparral | D62: 13/04/2026 21:44:36 | E62: 9000526015 | F62: LD02424015 | G62: 3 | H62: 7900525015 | I62: 190-17404244 | J62: COI | K62: CLEIDSON RODRIGUES VIEIRA | L62: EMERGENCIAL | M62: SS PENDENTE | N62: 17/04/2026 11:08:30 | O62: 190.00063 | P62: 228 | Q62: LOCAL INSTAL RELIGADOR DE LINHA GIS | R62: INDISPONIBILIDADE PARA OPERAÇÃO | X62: BUCHA MT - CARGA (C) | Z62: QUEIMADO | AA62: NÃO | AC62: ETO-COEP | AD62: Tocantins | AH62: ETO-RD-GR 00431/2026 | AI62: Não | AJ62: 8971402 | AK62: PEDRO AFONSO | AL62: 835984 | AO62: EQUIPAMENTO ESPECIAL | AP62: PENDÊNCIA DCMD | AQ62: REPASSAR DMSL | AR62: REPASSE | AS62: A DEFINIR (REPASSE)
A63: ETO-COEP 00073/2025 | B63: 2025 | C63: Segue nota para envia equipe linha viva substituir às 3 células do BC-5900489122 de 600 kVAr, Tensão 13.8kv, Cabo AA / 4/0, Local AVE. NS-01, Obs. Foi identificado fase C com elo queimado após fechamento fase B queimou elo, não foi possível identificar qual celular está danificada devido mesmo ser muito antigos favor substituir às 3 do mesmo. | D63: 23/04/2025 03:49:22 | F63: AL02060122 | H63: 5900489122 | I63: 190-28975995 | J63: COI | K63: SAMUEL PINTO GOMES | L63: EMERGENCIAL | M63: SS PENDENTE | N63: 01/05/2025 16:25:10 | O63: 190.02738 | P63: 0 | Q63: BANCO CAPACITOR DE DISTRIBUIÇÃO GIS | R63: INDISPONIBILIDADE PARA OPERAÇÃO | X63: CORPO (CÉLULA) | Z63: OPERAÇÃO INDEVIDA | AA63: NÃO | AC63: ETO-COEP | AH63: ETO-RD-PA 00296/2025 | AI63: Não | AJ63: 8872709 | AK63: PALMAS | AL63: 791797 | AO63: EQUIPAMENTO ESPECIAL | AP63: PENDÊNCIA DCMD | AQ63: BANCO DE CAPACITOR | AR63: MANUTENÇÃO | AS63: BANCO DE CAPACITOR
A64: ETO-COEP 00073/2026 | B64: 2026 | C64: PARECER DMSL: Fase C. Sentindo carga Chave faca não fechou, realizar substituição. DATA: 09/04/2026 SID 1756/2026 Equipe: Adeilton e Edicleber ___________________________________ PARECER DMSL: Chamado de desenvolvimento 30487776 criado. Favor, programar comissionamento a partir do dia 09/03/2026. (POLOTOC) PARECER DA PROTEÇÃO: ESTUDO REALIZADO. OS AJUSTES ESTÃO DISPONÍVEIS NO APP DA PROTEÇÃO. Estagiário Rafael Pereira Marques ___________ RELIGADOR N° 7967181127 INSTALADO NA OBRA 0652400757 GENTILEZA, REALIZAR O COMISSIONAMENTO. LAUDO EM ANEXO. COORD EO: 874476, 9275510 | D64: 23/01/2026 09:24:55 | E64: 6800580127 | F64: LD01084002 | G64: 3 | H64: 7967181127 | I64: 190-61399933 | J64: COPC | K64: Leonardo Sousa de Lima | L64: ALTA | M64: SS PENDENTE | N64: 15/06/2026 14:14:28 | O64: 190.0282 | P64: 31 | Q64: LOCAL INSTAL RELIGADOR DE LINHA GIS | R64: INDISPONIBILIDADE PARA OPERAÇÃO | X64: RELIGADOR | AA64: NÃO | AC64: ETO-COEP | AH64: ETO-PROT 00027/2026 | AI64: Não | AJ64: 9275509 | AK64: PALMEIRAS DO TOCANTINS | AL64: 874475 | AO64: EQUIPAMENTO ESPECIAL | AP64: PENDÊNCIA DMSL | AQ64: REPASSAR DMSL | AR64: REPASSE | AS64: A DEFINIR (REPASSE)
A65: ETO-COEP 00074/2025 | B65: 2025 | C65: Segue nota para envia equipe linha viva substituir fase A e B do BC-5952202122 de 300 kVAr, Tensão 13.8kv, Local AVE NS-02 Praça dos Girassóis. | D65: 24/04/2025 04:38:59 | E65: 8800388122 | F65: AL06059122 | G65: 2 | H65: 5952202122 | I65: 190-27954026 | J65: COI | K65: SAMUEL PINTO GOMES | L65: EMERGENCIAL | M65: SS PENDENTE | N65: 01/05/2025 16:46:18 | O65: 190.02686 | P65: 463 | Q65: BANCO CAPACITOR DE DISTRIBUIÇÃO GIS | R65: INDISPONIBILIDADE PARA OPERAÇÃO | X65: CORPO (CÉLULA) | Z65: SEM IDENTIFICAÇÃO | AA65: NÃO | AC65: ETO-COEP | AH65: ETO-RD-PA 00300/2025 | AI65: Não | AJ65: 8873137 | AK65: PALMAS | AL65: 792508 | AO65: EQUIPAMENTO ESPECIAL | AP65: PENDÊNCIA DCMD | AQ65: BANCO DE CAPACITOR | AR65: MANUTENÇÃO | AS65: BANCO DE CAPACITOR
A66: ETO-COEP 00074/2026 | B66: 2026 | C66: PARECER DMSL: Substituir Equipamento completo problema na placa de alimentação e na parte ativa, falta colocar placa de identificação correta na topologia, baixar o controle. Equipamento ficou em operação?: nao Pendência: sim Bateria(s) substituída(s)? NÃO Equipe: Kaique/ Benvindo ---------------------------------------------- PARECER DA PROTEÇÃO: Prosseguir com o comissionamento. Ajustes de religador permanecem os mesmos, disponíveis no APP da Proteção. ******************************** RELIGADOR N°7919270014 REMANEJADO NA OBRA 0212501060 GENTILEZA, REALIZAR O COMISSIONAMENTO. LAUDO EM ANEXO. COORD EO: 617422, 8830787 | D66: 25/02/2026 10:44:37 | E66: 8801059073 | F66: LD01047073 | G66: 2 | H66: 7919270014 | I66: 190-17407946 | J66: COPC | K66: Leonardo Sousa de Lima | L66: ALTA | M66: SS PENDENTE | N66: 16/06/2026 09:11:41 | O66: 190.01184 | P66: 52 | Q66: LOCAL INSTAL RELIGADOR DE LINHA GIS | R66: INDISPONIBILIDADE PARA OPERAÇÃO | X66: RELIGADOR | AA66: NÃO | AC66: ETO-COEP | AD66: Tocantins | AH66: ETO-PROT 00053/2026 | AI66: Não | AJ66: 8830790 | AK66: LAGOA DA CONFUSAO | AL66: 617420 | AO66: EQUIPAMENTO ESPECIAL | AP66: PENDÊNCIA DMSL | AQ66: REPASSAR DMSL | AR66: REPASSE | AS66: A DEFINIR (REPASSE)
A67: ETO-COEP 00075/2025 | B67: 2025 | C67: Segue nota para envia equipe linha viva substituir às 3 células do BC-5952327122, Obs. Identificada fase A e C aberta e em campo e curto na fase B, Equipamento ficou isolado para substituição, Tensão 13.8kv, Local próximo QD-409 Norte. | D67: 24/04/2025 05:10:24 | E67: 0352228122 | F67: AL07060122 | G67: 3 | H67: 5952327122 | I67: 190-49471228 | J67: COI | K67: SAMUEL PINTO GOMES | L67: EMERGENCIAL | M67: SS PENDENTE | N67: 01/05/2025 16:49:05 | O67: 190.02681 | P67: 0 | Q67: BANCO CAPACITOR DE DISTRIBUIÇÃO GIS | R67: INDISPONIBILIDADE PARA OPERAÇÃO | X67: CORPO (CÉLULA) | Z67: SEM IDENTIFICAÇÃO | AA67: NÃO | AC67: ETO-COEP | AH67: ETO-RD-PA 00301/2025 | AI67: Não | AJ67: 8876072 | AK67: PALMAS | AL67: 791229 | AO67: EQUIPAMENTO ESPECIAL | AP67: PENDÊNCIA DCMD | AQ67: BANCO DE CAPACITOR | AR67: MANUTENÇÃO | AS67: BANCO DE CAPACITOR
A68: ETO-COEP 00076/2025 | B68: 2025 | C68: Segue SS para substituição do banco capacitor com defeito fase B,C 5951650122 | D68: 25/04/2025 05:42:35 | E68: 8800777122 | F68: AL08059122 | G68: 2 | H68: 5951650122 | I68: 190-33029844 | J68: COI | K68: JANES FERREIRA DA SILVA | L68: EMERGENCIAL | M68: SS PENDENTE | N68: 01/05/2025 16:50:51 | O68: 190.02684 | P68: 792 | Q68: BANCO CAPACITOR DE DISTRIBUIÇÃO GIS | R68: INDISPONIBILIDADE PARA OPERAÇÃO | X68: CORPO (CÉLULA) | Z68: CORPO QUEIMADO, DANIFICADO, ETC | AA68: NÃO | AC68: ETO-COEP | AH68: DOLP-RD-PA 00593/2025 | AI68: Não | AJ68: 8870267 | AK68: PALMAS | AL68: 792537 | AO68: EQUIPAMENTO ESPECIAL | AP68: PENDÊNCIA DCMD | AQ68: BANCO DE CAPACITOR | AR68: MANUTENÇÃO | AS68: BANCO DE CAPACITOR
A69: ETO-COEP 00076/2026 | B69: 2026 | C69: PARECER DMSL: Realizar a substituição do transformador. (Furtado) Equipe: Adeilton e Edicleber SID 1874/2026 17/04/2026 ______________________________________ PARECER DMSL: Chamado de desenvolvimento 30484170 criado. Favor, programar comissionamento a partir do dia 20/02/26. POLOCOL PARECER DA PROTEÇÃO: Planilha com as informações anexada. É sugerido que sejam conferidas as medições da malha de aterramento do equipamento antes da sua inserção no sistema. Isso é fundamental para garantir a segurança e a eficiência do equipamento. Os ajustes estão disponíveis no APP da proteção. Estagiário Rafael Pereira Marques. _____________________ RELIGADOR N° 7962635060 INSTALADO NA OBRA 0602401143 GENTILEZA, REALIZAR O COMISSIONAMENTO. LAUDO EM ANEXO. COORD EO: 789405, 9172143 | D69: 22/12/2025 14:36:41 | E69: 3319797060 | F69: AL01054060 | G69: 3 | H69: 7962635060 | I69: 190-44718396 | J69: COPC | K69: Leonardo Sousa de Lima | L69: ALTA | M69: SS PENDENTE | N69: 16/06/2026 14:55:05 | O69: 190.02812 | P69: 14 | Q69: LOCAL INSTAL RELIGADOR DE LINHA GIS | R69: INDISPONIBILIDADE PARA OPERAÇÃO | X69: RELIGADOR | AA69: SIM | AC69: ETO-COEP | AH69: ETO-PROT 00391/2025 | AI69: Não | AJ69: 9172142 | AK69: ARAGUAINA | AL69: 789404 | AO69: EQUIPAMENTO ESPECIAL | AP69: PENDÊNCIA DMSL | AQ69: REPASSAR DMSL | AR69: REPASSE | AS69: A DEFINIR (REPASSE)
A70: ETO-COEP 00077/2025 | B70: 2025 | C70: BC-5907243122 isolado mesmo assim feito teste porém fase B não aceitou 03:13 / 24/04/2025. Favor verificar disponibilidade de equipamento e encaminhar novamente para subistituição do mesmo. | D70: 28/04/2025 16:57:05 | E70: 0307243122 | F70: AL05060122 | G70: 3 | H70: 5907243122 | I70: 190-53370143 | J70: COCM | K70: Felipe Divino Alves Monteiro | L70: EMERGENCIAL | M70: SS PENDENTE | N70: 01/05/2025 16:57:05 | O70: 190.02743 | P70: 0 | Q70: BANCO CAPACITOR DE DISTRIBUIÇÃO GIS | R70: INDISPONIBILIDADE PARA OPERAÇÃO | X70: OUTROS | Z70: SEM IDENTIFICAÇÃO | AA70: SIM | AC70: ETO-COEP | AI70: Não | AJ70: 8873316 | AK70: PALMAS | AL70: 791164 | AO70: EQUIPAMENTO ESPECIAL | AP70: PENDÊNCIA DCMD | AQ70: BANCO DE CAPACITOR | AR70: MANUTENÇÃO | AS70: BANCO DE CAPACITOR
A71: ETO-COEP 00077/2026 | B71: 2026 | C71: PARECER DMSL: RT 5801866013 Serviço Executado: Feito a medição da malha de terra. Identificado infiltração na caixa de passagem da célula da fase C do banco regulador de tensão, será necessário fazer a substituição da mesma! Ficar atento na hora da substituição, deverá ser substituída a célula do lado da BR. Obs.: Será necessário baixar todo o banco pelo menos um metro, as buchas estão muito próximas a parte energizada não oferecem segurança para equipe no momento do ensaio elétrico. Equipamento ficou em operação?: Não Possui nobreak: Sim Possui antena: Sim Possui rádio:Sim Pendência: Sim Data da bateria: Equipe: Benvindo e Kaique. _______________________________________________ RT 5801866013 BY PASSADO DEVIDO DEFEITO EM CELULA BEMVINDO ESTEVE NO LOCAL JUNTO AO COD . NECESSARIO TRATATIVA PARA MESMA . FASE DANIFICADO C | D71: 02/03/2026 15:58:27 | E71: 9001891013 | F71: AL03062013 | G71: 1 | H71: 5801866013 | I71: 190-35644534 | J71: COI | K71: Felipe Batista Ferrreira | L71: EMERGENCIAL | M71: SS PENDENTE | N71: 23/04/2026 07:47:57 | O71: 190.02615 | P71: 663 | Q71: REGULADOR DE TENSÃO DE DISTRIBUIÇÃO GIS | R71: INDISPONIBILIDADE PARA OPERAÇÃO | X71: EQUIPAMENTO | Z71: QUEIMADO | AA71: NÃO | AC71: ETO-COEP | AH71: ETO-TELE 00339/2026 | AI71: Não | AJ71: 8870961 | AK71: PARAISO DO TOCANTINS | AL71: 733022 | AO71: EQUIPAMENTO ESPECIAL | AP71: PENDÊNCIA DMSL | AQ71: REPASSAR DMSL | AR71: REPASSE | AS71: A DEFINIR (REPASSE)
A72: ETO-COEP 00078/2026 | B72: 2026 | C72: PARECER DMSL: Feedback Equip. Especiais RLG 7926089013, RELÉ NOJA RC10 SID 1805/2026 DATA 15/04/2026 Serviço Executado: Favor realizar a troca da parte ativa do equipamento --reprogramar para atualizar a base juntamente com escada Equipamento ficou em operação: Não Pendência: sim atualizar a base e subistituir o tanque Bateria(s) substituída(s)? Não Data de Fabricação/Instalação da(s) bateria(s): Equipe: Carliel e João Vitor Fernando e Elson --------------------------------------------------------------------------------- ATUALIZAR AJUSTES DO RL 7926089013 LD PARAISO I A PIUM. IMPLEMENTAÇÃO DA FUNÇÃO 27, SUBTENSÃO. AJUSTES DISPONIVEIS NO APP DA PROTEÇÃO. | D72: 27/03/2026 15:42:46 | E72: 7926089013 | F72: LD03062013 | G72: 3 | H72: 7926089013 | I72: 190-17512949 | J72: COPO | K72: CLEBSON ALVES DUARTE | L72: ALTA | M72: SS PENDENTE | N72: 22/06/2026 07:58:05 | O72: 190.02203 | P72: 1,042 | Q72: RELIGADOR DE REDE GIS | R72: INDISPONIBILIDADE PARA OPERAÇÃO | X72: RELIGADOR | Z72: RELÉ DE PROTEÇÃO | AA72: NÃO | AC72: ETO-COEP | AH72: ETO-TELE 00418/2026 | AI72: Não | AJ72: 8867765 | AK72: PARAISO DO TOCANTINS | AL72: 718799 | AO72: EQUIPAMENTO ESPECIAL | AP72: PENDÊNCIA DMSL | AQ72: REPASSAR DMSL | AR72: REPASSE | AS72: A DEFINIR (REPASSE) | AU72: REPETIDA
A73: ETO-COEP 00079/2025 | B73: 2025 | C73: Segue nota para envia manutenção substituir tanque do RL-7923927122 em curto, Anomalia identificada desarme das LD, s Palmas / Aparecida e Palmas Taquaruçu, Acesso livre, Tensão 34,5kv, Local RL de Interligação entre 424R / 414R. | D73: 27/04/2025 11:04:53 | E73: 9023928122 | F73: LD02059122 | G73: 1 | H73: 7923927122 | I73: 190-17403330 | J73: COI | K73: SAMUEL PINTO GOMES | L73: EMERGENCIAL | M73: SS PENDENTE | N73: 02/05/2025 13:50:00 | O73: 190.01217 | P73: 0 | Q73: LOCAL INSTAL RELIGADOR DE LINHA GIS | R73: INDISPONIBILIDADE PARA OPERAÇÃO | X73: RELIGADOR | Z73: QUEIMADO | AA73: SIM | AC73: ETO-COEP | AD73: Tocantins | AH73: DOLP-RD-PA 00602/2025 | AI73: Não | AJ73: 8867579 | AK73: PALMAS | AL73: 798247 | AO73: EQUIPAMENTO ESPECIAL | AP73: PENDÊNCIA DCMD | AQ73: TANQUE | AR73: MANUTENÇÃO | AS73: TANQUE
A74: ETO-COEP 00080/2026 | B74: 2026 | C74: Favor providenciar manutenção no RL 7900573047, o mesmo estar em curto conforme fotos anexadas. Equipamento ficou bay passado em campo. PARECER DMSL: Equipe: FABIO AP./JOÃO MARCOS Data Executada: 15/10/2025 Serviço Executado: Foi constatado que o equipamento esta queimado na parte ativa placa, tanque e relé. Por favor fazer a substituição pelo Noja RC10. | D74: 09/10/2025 10:05:50 | E74: 8800576047 | F74: AL02033047 | G74: 2 | H74: 7900573047 | I74: 190-19172791 | J74: COI | K74: ANTONIO FAGNER ALVES RIBEIRO | L74: EMERGENCIAL | M74: SS PENDENTE | N74: 27/04/2026 08:52:40 | O74: 190.00282 | P74: 40 | Q74: LOCAL INSTAL RELIGADOR DE LINHA GIS | R74: INDISPONIBILIDADE PARA OPERAÇÃO | AA74: NÃO | AC74: ETO-COEP | AD74: Tocantins | AH74: ETO-TELE 01188/2025 | AI74: Não | AJ74: 8657414 | AK74: FIGUEIROPOLIS | AL74: 698555 | AO74: EQUIPAMENTO ESPECIAL | AP74: PENDÊNCIA DCMD | AQ74: RELIGADOR | AR74: MANUTENÇÃO | AS74: RELIGADOR
A75: ETO-COEP 00081/2026 | B75: 2026 | C75: PARECER DMSL: A antena do rádio do RLG 7957620015 fica próximo da BT, onde a mesma veio a encostar no cabo da fase o que ocasionou um curto-circuito no rádio, que passou para todos os componentes do controle. Sendo asim se faz necessário a substituição do controle por inteiro, pois o curto danificou o rádio, módulo sim, relé e fonte. Fornecer também além do controle completo, a antena e o cabo umbilical que apresenta sinais de danos. rl 7957620015 com anomalia na antena de comunicação do mesmo, e painel não acende equipe fez primeira ataque e o mesmo não retornou comunicação, rl ficou by passado NECESSITA URGENCIA O MESMO PERTENCE CIRCUITO DO ALIMENTADOR 2 DE PEDRO AFONSO ATEDE RDU DE BOM JESUS | D75: 08/05/2025 13:02:03 | E75: 8800009015 | F75: AL02065015 | G75: 2 | H75: 7957620015 | I75: 190-22432476 | J75: COI | K75: ARTHUR MAGALHAES DAS DORES | L75: EMERGENCIAL | M75: SS PENDENTE | N75: 27/04/2026 14:04:28 | O75: 190.02741 | P75: 1,485 | Q75: LOCAL INSTAL RELIGADOR DE LINHA GIS | R75: INDISPONIBILIDADE PARA OPERAÇÃO | X75: COMANDO MECÂNICO | Z75: QUEIMADO | AA75: NÃO | AC75: ETO-COEP | AH75: ETO-TELE 00523/2025 | AI75: Não | AJ75: 9007081 | AK75: PEDRO AFONSO | AL75: 810847 | AO75: EQUIPAMENTO ESPECIAL | AP75: PENDÊNCIA DCMD | AQ75: RELIGADOR | AR75: MANUTENÇÃO | AS75: RELIGADOR | BB75: 1
A76: ETO-COEP 00082/2025 | B76: 2025 | C76: Segundo informações do técnico supervisor Danilo, enviar equipe para dá manutenção nos bancos capacitores 5900358003,5900364003 e 5901886003, ambos ficam na RDU de Gurupi na 13.8kV. | D76: 15/04/2024 12:12:03 | E76: 0301886003 | F76: AL02113003 | G76: 3 | H76: 5901886003 | I76: 190-28087333 | J76: COI | K76: WESLEY MARCAL MENDES DE OLIVEI | L76: EMERGENCIAL | M76: SS PENDENTE | N76: 11/05/2025 09:00:33 | O76: 190.02679 | P76: 0 | Q76: BANCO CAPACITOR DE DISTRIBUIÇÃO GIS | R76: INDISPONIBILIDADE PARA OPERAÇÃO | X76: OUTROS | Z76: QUEIMADO | AA76: NÃO | AC76: ETO-COEP | AH76: ETO-RD-GU 00587/2024 | AI76: Não | AJ76: 8701914 | AK76: GURUPI | AL76: 711988 | AO76: EQUIPAMENTO ESPECIAL | AP76: PENDÊNCIA DCMD | AQ76: REPETIDO | AR76: ANÁLISE | AS76: REPETIDO (revisar) | AT76: ETO-COEP 00082/2025
A77: ETO-COEP 00082/2026 | B77: 2026 | C77: Segue SS para verficar religador de poste 7933766059. Religador esta com defeito na parte ativa no tanque Porte gentilezaenviar equipe verificar. Endereço: Taquari PARECER DMSL: RLG 7933766059 RELÉ NOJA RC 10 Mestre 2 Rep. taquaruçu GE SID: 5457/2025 Data: 15/10/2025 Serviço Executado: Houve um curto na parte ativa do equipamento danificando a mesma, será necessário fazer a substituição somente do tanque, parte ativa. *Equipamento ficou em operação?:*Nao Pendência: Sim, substituir parte ativa. Equipe: Benvindo, Juliano e Sérgio. | D77: 08/10/2025 17:28:34 | E77: 9007788059 | F77: AL01099059 | G77: 2 | H77: 7933766059 | I77: 190-17409267 | J77: COI | K77: HERIK BUARQUE DOS SANTOS | L77: EMERGENCIAL | M77: SS PENDENTE | N77: 27/04/2026 14:31:39 | O77: 190.01316 | P77: 5,329 | Q77: LOCAL INSTAL RELIGADOR DE LINHA GIS | R77: INDISPONIBILIDADE PARA OPERAÇÃO | X77: BUCHA MT - CARGA (C) | Z77: INSPEÇÃO VISUAL | AA77: NÃO | AC77: ETO-COEP | AD77: Tocantins | AH77: ETO-TELE 01183/2025 | AI77: Não | AJ77: 8855224 | AK77: PALMAS | AL77: 792195 | AO77: EQUIPAMENTO ESPECIAL | AP77: PENDÊNCIA DCMD | AQ77: RELIGADOR - PARTE ATIVA | AR77: MANUTENÇÃO | AS77: RELIGADOR
A78: ETO-COEP 00083/2024 | B78: 2024 | C78: Segue SS do banco de capacitor 5900064029 com defeito 5900064029 RDU de Palmeiropolis Fase A com vazamento de oleo FAse B e C tambem com defeito. Por gentileza favor verificar a troca do mesmo | D78: 20/05/2024 11:55:14 | E78: 0300064029 | F78: AL01061029 | G78: 3 | H78: 5900064029 | I78: 190-28087184 | J78: COI | K78: HERIK BUARQUE DOS SANTOS | L78: ALTA | M78: SS PENDENTE | N78: 25/08/2024 16:39:39 | O78: 190.02679 | P78: 0 | Q78: BANCO CAPACITOR DE DISTRIBUIÇÃO GIS | R78: INDISPONIBILIDADE PARA OPERAÇÃO | X78: FORA DE SERVIÇO | Z78: CORPO QUEIMADO, DANIFICADO, ETC | AA78: SIM | AC78: ETO-COEP | AH78: ETO-RD-GU 00772/2024 | AI78: Não | AJ78: 8556741 | AK78: PALMEIROPOLIS | AL78: 781207 | AO78: EQUIPAMENTO ESPECIAL | AP78: PENDÊNCIA DCMD | AQ78: BANCO DE CAPACITOR | AR78: MANUTENÇÃO | AS78: BANCO DE CAPACITOR
A79: ETO-COEP 00083/2025 | B79: 2025 | C79: Segundo informações do técnico supervisor Danilo, enviar equipe para dá manutenção nos bancos capacitores 5900358003,5900364003 e 5901886003, ambos ficam na RDU de Gurupi na 13.8kV. | D79: 15/04/2024 12:12:03 | F79: AL02113003 | H79: 5900364003 | I79: 190-16323908 | J79: COI | K79: WESLEY MARCAL MENDES DE OLIVEI | L79: EMERGENCIAL | M79: SS PENDENTE | N79: 11/05/2025 09:00:53 | O79: 190.02318 | P79: 0 | Q79: BANCO CAPACITOR DE DISTRIBUIÇÃO GIS | R79: INDISPONIBILIDADE PARA OPERAÇÃO | X79: OUTROS | Z79: QUEIMADO | AA79: NÃO | AC79: ETO-COEP | AH79: ETO-RD-GU 00584/2024 | AI79: Não | AJ79: 8702115 | AK79: GURUPI | AL79: 711094 | AO79: EQUIPAMENTO ESPECIAL | AP79: PENDÊNCIA DCMD | AQ79: REPETIDO | AR79: ANÁLISE | AS79: REPETIDO (revisar) | AT79: ETO-COEP 00082/2025
A80: ETO-COEP 00083/2026 | B80: 2026 | C80: Bom dia, Segue SS para verificação RL sem comunicação com painel apagado equipe DEOP fez primeiro ataque sem sucesso RL 7931610122 RDU de Palmas. Feedback Equipamentos Especiais DMSL: *RLG 7931610122 RDU Palmas *Noja rc10 Data: 14/10/2025 SID: 5412 Dados de comunicação divergentes da programação: Não. Serviço Executado: Houve um curto no equipamento danificando a parte ativa, e antena! Será necessário fazer a substituição somente da parte ativa (tanque) e da antena. Equipamento ficou em operação?: Não Pendência: Sim, substituir a parte ativa. Bateria(s) substituída(s)?: Não Data Fabricação/Instalação da(s) bateria(s): 2024 Equipe: Benvindo, Juliano e Sérgio. | D80: 10/10/2025 07:22:51 | E80: 9007740122 | F80: AL08060122 | G80: 2 | H80: 7931610122 | I80: 190-17408268 | J80: COI | K80: JANES FERREIRA DA SILVA | L80: EMERGENCIAL | M80: SS PENDENTE | N80: 27/04/2026 14:32:01 | O80: 190.01279 | P80: 2,464 | Q80: LOCAL INSTAL RELIGADOR DE LINHA GIS | R80: INDISPONIBILIDADE PARA OPERAÇÃO | X80: RELIGADOR | Z80: CORROSÃO / OXIDAÇÃO | AA80: NÃO | AC80: ETO-COEP | AD80: Tocantins | AH80: ETO-TELE 01190/2025 | AI80: Não | AJ80: 8874945 | AK80: PALMAS | AL80: 793159 | AO80: EQUIPAMENTO ESPECIAL | AP80: PENDÊNCIA DCMD | AQ80: PARTE ATIVA | AR80: MANUTENÇÃO | AS80: PARTE ATIVA
A81: ETO-COEP 00084/2025 | B81: 2025 | C81: por favor deslocar equipe da manutenção nos bancos capacitor 5900470004 , 5903718004 , 5900668004 para faze manutenção eles esta com chave aberto em campo foi informado pela equipe do plantão 004op02 | D81: 17/05/2024 13:02:00 | F81: AL02010004 | H81: 5900470004 | I81: 190-16324007 | J81: COI | K81: SIRDEIS ALVES MONTEIRO | L81: ALTA | M81: SS PENDENTE | N81: 08/07/2025 14:53:19 | O81: 190.02318 | P81: 0 | Q81: BANCO CAPACITOR DE DISTRIBUIÇÃO GIS | R81: INDISPONIBILIDADE PARA OPERAÇÃO | X81: OUTROS | Z81: CAPACITOR MAL FIXADO | AA81: NÃO | AC81: ETO-COEP | AH81: ETO-RD-AR 00925/2024 | AI81: Não | AJ81: 9204328 | AK81: ARAGUAINA | AL81: 807159 | AO81: EQUIPAMENTO ESPECIAL | AP81: PENDÊNCIA DCMD | AQ81: REPETIDO | AR81: ANÁLISE | AS81: REPETIDO (revisar) | AT81: ETO-COEP 00084/2025
A82: ETO-COEP 00084/2026 | B82: 2026 | C82: Segue nota para correção de anomalia e provável substituição de religador , religador 7900117013 -RDU - Paraiso . OBS: equipe DMSL Elisfran estava atualizando firmware no equipamento , porém relé parou de funcionar devido essa atualização , sendo necessário sua substituição . em campo o modelo e cooper Form6 , segundo tecnico deve ser substituído por um Noja . Repassado para o COEP para aquisição do equipamento e posterior repasse para o COCM. | D82: 02/07/2025 13:13:59 | E82: 7900117013 | F82: AL01062013 | G82: 1 | H82: 7900117013 | I82: 190-17421714 | J82: COI | K82: DIOMAR FERREIRA PEREIRA | L82: ALTA | M82: SS PENDENTE | N82: 23/06/2026 16:16:24 | O82: 190.0222 | P82: 4,535 | Q82: RELIGADOR DE REDE GIS | R82: INDISPONIBILIDADE PARA OPERAÇÃO | X82: RELÉ | Z82: ILEGÍVEL | AA82: NÃO | AC82: ETO-COEP | AH82: ETO-TELE 00791/2025 | AI82: Não | AJ82: 8875436 | AK82: PARAISO DO TOCANTINS | AL82: 731274 | AO82: EQUIPAMENTO ESPECIAL | AP82: PENDÊNCIA DCMD | AQ82: RELIGADOR | AR82: MANUTENÇÃO | AS82: RELIGADOR
A83: ETO-COEP 00085/2025 | B83: 2025 | C83: por favor deslocar equipe da manutenção nos bancos capacitor 5900470004 , 5903718004 , 5900668004 para faze manutenção eles esta com chave aberto em campo foi informado pela equipe do plantão 004op02 | D83: 17/05/2024 13:02:00 | F83: AL01010004 | H83: 5903718004 | I83: 190-16323930 | J83: COI | K83: SIRDEIS ALVES MONTEIRO | L83: EMERGENCIAL | M83: SS PENDENTE | N83: 12/05/2025 14:53:41 | O83: 190.02318 | P83: 0 | Q83: BANCO CAPACITOR DE DISTRIBUIÇÃO GIS | R83: INDISPONIBILIDADE PARA OPERAÇÃO | X83: OUTROS | Z83: CAPACITOR MAL FIXADO | AA83: NÃO | AC83: ETO-COEP | AH83: ETO-RD-AR 00927/2024 | AI83: Não | AJ83: 9200598 | AK83: ARAGUAINA | AL83: 803747 | AO83: EQUIPAMENTO ESPECIAL | AP83: PENDÊNCIA DCMD | AQ83: REPETIDO | AR83: ANÁLISE | AS83: REPETIDO (revisar) | AT83: ETO-COEP 00084/2025
A84: ETO-COEP 00085/2026 | B84: 2026 | C84: RL 7938137007 NO RL INSTALAR BATERIA NOVA E RADIO A PEDIDO DE KAROLINY DMSL ACESSO LIVRE PARECER DMSL: * equipamento esta com a bucha da fase A com problemas(solta), necessário substituir * Trafo do serviço auxiliar esta vazando óleo, necessário substituir | D84: 26/12/2025 18:06:25 | E84: 9002298007 | F84: AL02017017 | G84: 3 | H84: 7938137007 | I84: 190-17408695 | J84: MANUT | K84: ANDERSON FAZAN SOARES | L84: EMERGENCIAL | M84: SS PENDENTE | N84: 27/04/2026 16:18:10 | O84: 190.01291 | P84: 285 | Q84: LOCAL INSTAL RELIGADOR DE LINHA GIS | R84: INDISPONIBILIDADE PARA OPERAÇÃO | X84: RELIGADOR | Z84: QUEIMADO | AA84: NÃO | AC84: ETO-COEP | AD84: Tocantins | AH84: ETO-TELE 01528/2025 | AI84: Não | AJ84: 8894217 | AK84: MIRACEMA DO TOCANTINS | AL84: 765777 | AO84: EQUIPAMENTO ESPECIAL | AP84: PENDÊNCIA DCMD | AQ84: BUCHA - TRAFO COM VAZAMENTO DE ÓLEO | AR84: MANUTENÇÃO | AS84: TRANSFORMADOR
A85: ETO-COEP 00086/2026 | B85: 2026 | C85: NOTA DMSL: Favor substituir o tanque, ele não está efetuando os comandos enviados. Não substituir o controle pois o mesmo funciona como repetidor de outros equipamentos. Segue nota para verificar falha de fechamento religador 7908686014- Pium . OBS: equipamento não fechou local e remoto , fica sinalizando no painel para verificar alarmes ! | D85: 15/10/2024 16:43:55 | E85: 7908686014 | F85: LD02025012 | G85: 1 | H85: 7908686014 | I85: 190-17512665 | J85: COI | K85: DIOMAR FERREIRA PEREIRA | L85: EMERGENCIAL | M85: SS PENDENTE | N85: 27/04/2026 16:18:48 | O85: 190.02296 | P85: 0 | Q85: RELIGADOR DE REDE GIS | R85: INDISPONIBILIDADE PARA OPERAÇÃO | X85: RELIGADOR | Z85: ILEGÍVEL | AA85: NÃO | AC85: ETO-COEP | AH85: ETO-TELE 00867/2024 | AI85: Não | AJ85: 8845185 | AK85: PIUM | AL85: 698568 | AO85: EQUIPAMENTO ESPECIAL | AP85: PENDÊNCIA DMSL | AQ85: TANQUE | AR85: MANUTENÇÃO | AS85: TANQUE
A86: ETO-COEP 00087/2026 | B86: 2026 | C86: Favor verificar o RL 7900453110, pois o mesmo aceita comando de fechamento, porém fecha em campo e no SCADA continua aberto e só abre através de equipe em campo. Parecer Dmsl:Equipamento está com defeito na parte ativa, não aceita o comando de fechamento. Será necessário substituir o equipamento completo. Equipamento ficou em operação?: _SIM_a pedido do COS ficou em operação, a operação está ciente da necessidade de substituir. Pendência: Sim, será necessário substituir o equipamento. | D86: 22/04/2025 09:55:49 | E86: 9000453110 | F86: LD03040003 | G86: 2 | H86: 7900453110 | I86: 190-17412271 | J86: COI | K86: WESLEY MARCAL MENDES DE OLIVEI | L86: EMERGENCIAL | M86: SS PENDENTE | N86: 30/04/2026 14:47:11 | O86: 190.00131 | P86: 0 | Q86: LOCAL INSTAL RELIGADOR DE LINHA GIS | R86: INDISPONIBILIDADE PARA OPERAÇÃO | X86: RELÉ | Z86: INSPEÇÃO VISUAL | AA86: NÃO | AC86: ETO-COEP | AD86: Tocantins | AH86: ETO-TELE 00410/2025 | AI86: Não | AJ86: 8773164 | AK86: SANTA RITA DO TOCANTINS | AL86: 727212 | AO86: EQUIPAMENTO ESPECIAL | AP86: PENDÊNCIA DCMD | AQ86: RELIGADOR | AR86: MANUTENÇÃO | AS86: RELIGADOR
A87: ETO-COEP 00088/2025 | B87: 2025 | C87: substituir 7 vão de rede deteriorados de QP-35 mm multiplex no circuito do trafo 5703610004 - bairro Jardim dos Ipês II- rua 55 qd. 63 lt 34 - RDU Araguaina | D87: 07/11/2024 13:22:39 | E87: 5703610004 | F87: AL06010004 | G87: 3 | H87: 5703610004 | I87: 190-1657495 | J87: COI | K87: VALERIA DE JESUS BORGES CARVAL | L87: URGENTE | M87: SS PENDENTE | N87: 16/05/2025 17:10:30 | O87: 190.00955 | P87: 66 | Q87: POSTE RD GIS | R87: AVISO DE ANOMALIA | X87: CABOS BT | Z87: DETERIORADA | AA87: NÃO | AC87: ETO-COEP | AD87: Tocantins | AH87: ETO-RD-AR 01898/2024 | AI87: Não | AJ87: 9206052 | AK87: ARAGUAINA | AL87: 804830 | AN87: SI-1 | AO87: CABOS FORA COEP | AP87: PENDÊNCIA DCMD | AQ87: CABOS | AR87: MANUTENÇÃO | AS87: CABOS | AU87: REPETIDA | AV87: 35 | AW87: =7*35 -> 245
A88: ETO-COEP 00088/2026 | B88: 2026 | C88: PARECER DMSL: Serviço Executado: _ indentificado o problema na parte ativa será necessário fazer a substituição da mesmo, feito a medição do aterramento. Preciso substituir para raio da fase c. Equipamento ficou em operação?: _NAO Pendência: _Sim Bateria(s) substituída(s)? _Não Data Fabricação/Instalação da(s) bateria(s):_ Equipe: _Benvindo e kaique ---------------------------------------------------------------------------------- RL com defeito no rele, fica só reiniciando ficou By passado OS atendimento primeiro ataque 106530226 | D88: 15/02/2026 20:35:18 | E88: 7921202014 | F88: LD01025012 | G88: 3 | H88: 7921202014 | I88: EQP-7921202014 | J88: COI | K88: WANDERLEY TAVARES DA SILVA | L88: EMERGENCIAL | M88: SS PENDENTE | N88: 01/05/2026 14:49:25 | O88: 190.01188 | P88: 543 | Q88: RELIGADOR | R88: INDISPONIBILIDADE PARA OPERAÇÃO | AA88: NÃO | AC88: ETO-COEP | AD88: Tocantins | AH88: ETO-RD-PA 00109/2026 | AI88: Não | AO88: EQUIPAMENTO ESPECIAL | AP88: PENDÊNCIA DCMD | AQ88: RELÉ | AR88: MANUTENÇÃO | AS88: RELÉ
A89: ETO-COEP 00089/2025 | B89: 2025 | C89: SUBSTITUIR REDE BT DETERIORADA TODO CIRCUITO DO TR-5719217060 230MT BARRAMENTO DO TRAFO CABO MUTIPLEX 70MM TRIFÁSICO. 1.350,00mt DE CABOS MUTIPLEX 35MM TRIFÁSICO RDU NOVA OLINDA | D89: 18/03/2025 18:43:46 | E89: 5719217060 | F89: AL02054060 | G89: 3 | H89: 5719217060 | I89: 190-1861817 | J89: COI | K89: JOELSON SILVA DE SOUSA | L89: EMERGENCIAL | M89: SS PENDENTE | N89: 12/05/2025 17:11:38 | O89: 190.01225 | P89: 61 | Q89: POSTE RD GIS | R89: AVISO DE ANOMALIA | X89: CABOS BT | Z89: RACHADA / DETERIORADA | AA89: NÃO | AC89: ETO-COEP | AD89: Tocantins | AH89: ETO-RD-AR 00446/2025 | AI89: Não | AJ89: 9154452 | AK89: NOVA OLINDA | AL89: 785494 | AN89: SI-3 | AO89: CABOS FORA COEP | AP89: PENDÊNCIA DCMD | AQ89: CABOS | AR89: MANUTENÇÃO | AS89: CABOS | AU89: REPETIDA | AV89: 70 | AW89: 1.350,00mt
A90: ETO-COEP 00089/2026 | B90: 2026 | C90: Manutenção no RL 7908705049 PARECER DMSL(28/08/2025): Equipe foi fazer manutenção no RL e constatou que o tanque e o relé do mesmo se encontra queimado, providenciar substituição. PARECER COCMS 30/04/2026 CRIADO OBRA 0512600135 PARA REQUISIÇÃO MATERIAL | D90: 16/07/2025 08:00:04 | E90: 0908705049 | F90: AL01015049 | G90: 2 | H90: 7908705049 | I90: 190-17414963 | J90: MANUT | K90: Lorrane Sousa Gonçalves | L90: PROGRAMAVEL | M90: SS PENDENTE | N90: 04/06/2027 15:31:25 | O90: 190.00037 | P90: 1,354 | Q90: LOCAL INSTAL RELIGADOR DE LINHA GIS | R90: INDISPONIBILIDADE PARA OPERAÇÃO | AA90: NÃO | AC90: ETO-COEP | AD90: Tocantins | AH90: ETO-TELE 00824/2025 | AI90: Não | AJ90: 8589651 | AK90: AURORA DO TOCANTINS | AL90: 998978 | AO90: EQUIPAMENTO ESPECIAL | AP90: PENDÊNCIA DCMD | AQ90: RELIGADOR - OBRA GERADA | AR90: MANUTENÇÃO | AS90: RELIGADOR
A91: ETO-COEP 00090/2025 | B91: 2025 | C91: SUBSTITUIR REDE BT DETERIORADA TODO CIRCUITO DO TR-5719218060 230MT BARRAMENTO DO TRAFO CABO MUTIPLEX 70MM TRIFÁSICO. 810MT DE CABOS MUTIPLEX 35MM TRIFÁSICO RDU NOVA OLINDA | D91: 18/03/2025 19:19:46 | E91: 5719218060 | F91: AL02054060 | G91: 3 | H91: 5719218060 | I91: 190-1854126 | J91: COI | K91: JOELSON SILVA DE SOUSA | L91: EMERGENCIAL | M91: SS PENDENTE | N91: 12/05/2025 17:12:00 | O91: 190.01225 | P91: 27 | Q91: POSTE RD GIS | R91: AVISO DE ANOMALIA | X91: CABOS BT | Z91: RACHADA / DETERIORADA | AA91: NÃO | AC91: ETO-COEP | AD91: Tocantins | AH91: ETO-RD-AR 00448/2025 | AI91: Não | AJ91: 9154627 | AK91: NOVA OLINDA | AL91: 785397 | AN91: SI-1 | AO91: CABOS FORA COEP | AP91: PENDÊNCIA DCMD | AQ91: CABOS | AR91: MANUTENÇÃO | AS91: CABOS | AV91: 70 | AW91: 810 | AY91: 35 | AZ91: 230
A92: ETO-COEP 00091/2025 | B92: 2025 | C92: PARECER DMSL: Não foi possível comissionar o equipamento 7956063152 pois o mesmo estava sem cordão umbilical, sem rádio e conexões, e sem alimentação do trafo no equipamento. Favor, sanar pendências. GENTILEZA COMISSIONAR RELIGADOR, PARTE CONSTRUTIVA FISCALIZADA. EQUIPAMENTO: NOJA POWER Nº SERIE: 0320124013012 CONTROLE: NOJA POWER MODELO: RC-10ES Nº SERIE: 0101523100769. PARECER DA PROTEÇÃO: AJUSTE DISPONIBILIZADO NO APP DA PROTEÇÃO, NTA REPASSADA PARA DMSL COMISSIONAR, RL ORIGINARIO DE DEMANDA DE CLIENTE GRUPO A. ENG° IRLLEY CASTELO BRANCO | D92: 09/09/2024 16:59:08 | E92: 9000376152 | F92: LD02072001 | G92: 3 | H92: 7956063152 | I92: 190-46139181 | J92: COCM | K92: RICARDO GONCALVES ROCHA | L92: ALTA | M92: SS PENDENTE | N92: 11/07/2025 08:06:21 | O92: 190.02735 | P92: 865 | Q92: LOCAL INSTAL RELIGADOR DE LINHA GIS | R92: OBRAS (NOVOS EQUIPAMENTOS) | X92: RELIGADOR | Z92: INSPEÇÃO VISUAL | AA92: NÃO | AC92: ETO-COEP | AH92: ETO-PROT 00260/2024 | AI92: Não | AJ92: 8732887 | AK92: SANTA ROSA DO TOCANTINS | AL92: 816179 | AO92: EQUIPAMENTO ESPECIAL | AP92: PENDÊNCIA DMSL | AQ92: REPASSAR DMSL | AR92: REPASSE | AS92: A DEFINIR (REPASSE)
A93: ETO-COEP 00093/2025 | B93: 2025 | C93: acionar equipe de manutencao para troca de vao de rede deteriorada em Nova Olinda trafo 5701907060 localidade Nova Olinda IND RUA GONCALVES DIAS, 301 - QDRA 07A. LT 01A equipe 060op01 OBS.: substiuir 350m de cabo de BT deteriorado na RDU de nova olinda | D93: 18/04/2025 16:46:33 | E93: 5701907060 | F93: AL02054060 | G93: 3 | H93: 5701907060 | I93: 190-1690500 | J93: COI | K93: CLEIBER DA SILVA | L93: PROGRAMAVEL | M93: SS PENDENTE | N93: 16/06/2026 15:42:10 | O93: 190.00564 | P93: 81 | Q93: POSTE RD GIS | R93: AVISO DE INCONSISTÊNCIA | X93: CABOS BT | Z93: CABO CONDUTOR BAIXO | AA93: NÃO | AC93: ETO-COEP | AD93: Tocantins | AH93: ETO-RD-AR 00683/2025 | AI93: Não | AJ93: 9156432 | AK93: NOVA OLINDA | AL93: 784166 | AN93: SI-1 | AO93: CABOS FORA COEP | AP93: PENDÊNCIA DCMD | AQ93: CABOS | AR93: MANUTENÇÃO | AS93: CABOS | AV93: 35/70 | AW93: 350
A94: ETO-COEP 00094/2025 | B94: 2025 | C94: Substituir caixa de controle do RL 7934698002-RDU TOCANTINÓPOLIS, onde a mesma se encontra destruída em campo.. OBS: Segue em anexo fotos da carcaça do Controle do Religador-7934968002.RDU Tocantinópolis. | D94: 06/05/2025 09:04:17 | E94: 9000629002 | F94: AL02084002 | G94: 2 | H94: 7934698002 | I94: 190-17338880 | J94: COI | K94: DELIO NUNES OSCAR | L94: ALTA | M94: SS PENDENTE | N94: 11/07/2025 16:39:16 | O94: 190.01304 | P94: 123 | Q94: LOCAL INSTAL RELIGADOR DE LINHA GIS | R94: INDISPONIBILIDADE PARA OPERAÇÃO | T94: ETO-RD-AG 000364/2026 | U94: CRIADA | X94: ARMÁRIO DE CONTROLE | Z94: FALTANDO | AA94: SIM | AC94: ETO-COEP | AD94: Tocantins | AH94: ETO-RD-AG 00534/2025 | AI94: Não | AJ94: 9297006 | AK94: TOCANTINOPOLIS | AL94: 895699 | AO94: EQUIPAMENTO ESPECIAL | AP94: PENDÊNCIA DCMD | AQ94: CAIXA DE CONTROLE | AR94: MANUTENÇÃO | AS94: CAIXA DE CONTROLE
A95: ETO-COEP 00095/2025 | B95: 2025 | C95: Segue nota para envia equipe linha viva substituir célula no BC-5955192004 fase B danificada dando passa de tensão e corrente se possível refazer aterramento do equipamento, Tensão 13.8kv, Acesso livre, Local RDU de Araguaína Avenida Conego João Lima. | D95: 13/05/2025 04:07:29 | E95: 0355192004 | F95: AL02010004 | G95: 3 | H95: 5955192004 | I95: 190-48582604 | J95: COI | K95: SAMUEL PINTO GOMES | L95: EMERGENCIAL | M95: SS PENDENTE | N95: 16/05/2025 07:31:24 | O95: 190.02735 | P95: 0 | Q95: BANCO CAPACITOR DE DISTRIBUIÇÃO GIS | R95: NOTA DE SERVIÇO (NS) - LINHA VIVA | X95: CORPO (CÉLULA) | Z95: VAZAMENTO | AA95: NÃO | AC95: ETO-COEP | AH95: ETO-RD-AR 00827/2025 | AI95: Não | AJ95: 9204342 | AK95: ARAGUAINA | AL95: 807636 | AO95: EQUIPAMENTO ESPECIAL | AP95: PENDÊNCIA DCMD | AQ95: BANCO DE CAPACITOR | AR95: MANUTENÇÃO | AS95: BANCO DE CAPACITOR
A96: ETO-COEP 00096/2025 | B96: 2025 | C96: por favor deslocar equipe da manutenção nos bancos capacitor 5900470004 , 5903718004 , 5900668004 para faze manutenção eles esta com chave aberto em campo foi informado pela equipe do plantão 004op02 | D96: 17/05/2024 13:02:00 | F96: AL06010004 | H96: 5900668004 | I96: 190-16324054 | J96: COI | K96: SIRDEIS ALVES MONTEIRO | L96: ALTA | M96: SS PENDENTE | N96: 12/07/2025 16:02:35 | O96: 190.02318 | P96: 0 | Q96: BANCO CAPACITOR DE DISTRIBUIÇÃO GIS | R96: INDISPONIBILIDADE PARA OPERAÇÃO | X96: OUTROS | Z96: CAPACITOR MAL FIXADO | AA96: NÃO | AC96: ETO-COEP | AH96: ETO-RD-AR 00926/2024 | AI96: Não | AJ96: 9206735 | AK96: ARAGUAINA | AL96: 807898 | AO96: EQUIPAMENTO ESPECIAL | AP96: PENDÊNCIA DCMD | AQ96: REPETIDO | AR96: ANÁLISE | AS96: REPETIDO (revisar) | AT96: ETO-COEP 00084/2025
A97: ETO-COEP 00099/2025 | B97: 2025 | C97: Equipamento TAVRIDA, no SCADA não estão refletindo as correntes reais do sistema, favor corrigir junto ao time SCADA. Fase A - 28A Fase B - 5A Fase C - 5A Neutro - 25A PARECER DMSL: Verificado que o equipamento não esta medindo as correntes da fases B e C, entramos em contato com o suporte técnico da Tavrida, realizamos testes no cordão umbilical, mesmo assim ainda marca incorretamente. Repassar a nota para o DCMD substituir o equipamento, o operador Daniel pediu ara deixar o equipamento em operação, para poder realizar futuras manobras | D97: 02/04/2025 09:20:02 | E97: 7949660066 | F97: LD03038009 | G97: 3 | H97: 7949660066 | I97: 190-29963572 | J97: COPO | K97: IRLLEY J A C BRANCO | L97: ALTA | M97: SS PENDENTE | N97: 21/07/2025 15:53:31 | O97: 190.0268 | P97: 3,272 | Q97: RELIGADOR DE REDE GIS | R97: EM OPERAÇÃO COM ANOMALIA | X97: RELÉ | Z97: ABERTURA INDEVIDA DA PROTEÇÃO | AA97: NÃO | AC97: ETO-COEP | AH97: ETO-TELE 00317/2025 | AI97: Não | AJ97: 9065613 | AK97: TUPIRATINS | AL97: 800516 | AO97: EQUIPAMENTO ESPECIAL | AP97: PENDÊNCIA DCMD | AQ97: COMPRA | AR97: COMPRA | AS97: A DEFINIR (compra)
A98: ETO-COEP 00100/2025 | B98: 2025 | C98: Solicitação de serviço para analise de ocorrência. Defeito a jusante do RL 7949688227 onde houve atuação da retaguarda penalizando cargas Urbanas - RL 7900001227. PARECER DA PROTEÇÃO: REVISAR AJUSTES DE PROTEÇÃO E REALIZAR O TESTE FUNCIONAL COM MALA DE CARGA PARA VERIFICAR ABERTURA DO EQUIPAMENTO. ENG° IRLLEYC CASTELO BRANCO PARECER DMSL: Foi verificado que o equipamento nao esta medindo as correntes corretamente, entramos em contato com o suporte da COOPER, o mesmo informou que o sensor interno que mede a corrente esta com defeito A medição esta variando de 5 a 5min, Ano de fabricação do equipamento 2009 COOPER Form6, equipamento obsoleto. Solicitar ao DCMD a substituição do equipamento, o mesmo nao esta medindo as correntes corretamente, equipamento obsoleto | D98: 17/02/2025 12:13:43 | E98: 9000001227 | F98: LD01065015 | G98: 3 | H98: 7900001227 | I98: 190-17404066 | J98: COI | K98: LEONARDO SIQUEIRA AMORIM | L98: EMERGENCIAL | M98: SS PENDENTE | N98: 25/05/2025 16:08:11 | O98: 190.00061 | P98: 985 | Q98: LOCAL INSTAL RELIGADOR DE LINHA GIS | R98: AVISO PROTEÇÃO & SELETIVIDADE | AA98: NÃO | AC98: ETO-COEP | AD98: Tocantins | AH98: ETO-PROT 00069/2025 | AI98: Não | AJ98: 9031806 | AK98: RECURSOLANDIA | AL98: 913706 | AO98: EQUIPAMENTO ESPECIAL | AP98: PENDÊNCIA DCMD | AQ98: RELIGADOR | AR98: MANUTENÇÃO | AS98: RELIGADOR
A99: ETO-COEP 00101/2025 | B99: 2025 | C99: Refazer aterramento pois o mesmo encontra-se exposto | D99: 26/05/2025 11:10:45 | E99: 8800173094 | F99: LD02066094 | G99: 1 | H99: 5855776094 | I99: 190-53748088 | J99: MANUT | K99: Lorrane Sousa Gonçalves | L99: URGENTE | M99: SS PENDENTE | N99: 02/06/2025 11:10:45 | O99: 190.02747 | P99: 773 | Q99: REGULADOR DE TENSÃO DE DISTRIBUIÇÃO GIS | R99: SOLICITAÇÃO DE SERVIÇO | AA99: NÃO | AC99: ETO-COEP | AI99: Não | AJ99: 8640008 | AK99: PEIXE | AL99: 782530 | AO99: EQUIPAMENTO ESPECIAL | AP99: PENDÊNCIA DCMD | AQ99: REPASSAR COCM | AR99: REPASSE | AS99: A DEFINIR (REPASSE) | AT99: ATERRAMENTO
A100: ETO-COEP 00102/2025 | B100: 2025 | C100: Favor, realizar substituição completa do RLG 7900532053 que encontra-se com defeito devido entrada de água no cordão umbilical e danos causados por abelhas. O rádio também precisa ser fornecido pois o existente está danificado. | D100: 26/05/2025 14:53:43 | F100: LD02010004 | H100: 7900532053 | I100: 190-17512744 | J100: MANUT | K100: EDNA MARIA DOS SANTOS PINTO | L100: ALTA | M100: SS PENDENTE | N100: 25/07/2025 14:53:43 | O100: 190.02226 | P100: 0 | Q100: RELIGADOR DE REDE GIS | R100: INDISPONIBILIDADE PARA OPERAÇÃO | X100: FORA DE SERVIÇO | AA100: SIM | AC100: ETO-COEP | AI100: Não | AJ100: 9250367 | AK100: PIRAQUE | AL100: 799329 | AO100: EQUIPAMENTO ESPECIAL | AP100: PENDÊNCIA DCMD | AQ100: RELIGADOR | AR100: MANUTENÇÃO | AS100: RELIGADOR
...

Sheet Dashboard
B2: RELATÓRIO DE SOLICITAÇÕES DE SERVIÇO PENDENTES
B4: DCMD • Energisa Tocantins
B6: TOTAL SS | D6: PEND. DCMD | F6: PEND. DMSL | H6: REPETIDAS | J6: CONCLUÍDAS
B7: 183 | D7: 148 | F7: 34 | H7: 20 | J7: 1
B11: POR EQUIPAMENTO / CATEGORIA | G11: POR STATUS
B12: Categoria | C12: Qtd | D12: % | G12: Status | H12: Qtd | I12: %
B13: EQUIPAMENTO ESPECIAL | C13: 136 | D13: 0.7431694 | G13: PENDÊNCIA DCMD | H13: 148 | I13: 0.80874317
B14: CABOS FORA COEP | C14: 30 | D14: 0.16393443 | G14: PENDÊNCIA DMSL | H14: 34 | I14: 0.18579235
B15: PLANO DE MEDIDAS | C15: 12 | D15: 0.06557377 | G15: CONCLUÍDO | H15: 1 | I15: 0.0054644809
B16: MELHORIA DE REDE | C16: 3 | D16: 0.016393443
B17: LIMPEZA DE FAIXA | C17: 2 | D17: 0.010928962
B20: POR GRUPO DE ANÁLISE | G20: GRUPO × STATUS
B21: Grupo | C21: Qtd | D21: % | G21: Grupo | H21: CONCLUÍDO | I21: PENDÊNCIA DCMD | J21: PENDÊNCIA DMSL | K21: Total
B22: MANUTENÇÃO | C22: 107 | D22: 0.58469945 | G22: ANÁLISE | H22: 0 | I22: 19 | J22: 1 | K22: 20
B23: REPASSE | C23: 54 | D23: 0.29508197 | G23: COMPRA | H23: 0 | I23: 2 | J23: 0 | K23: 2
B24: ANÁLISE | C24: 20 | D24: 0.10928962 | G24: MANUTENÇÃO | H24: 1 | I24: 104 | J24: 2 | K24: 107
B25: COMPRA | C25: 2 | D25: 0.010928962 | G25: REPASSE | H25: 0 | I25: 23 | J25: 31 | K25: 54
G26: Total | H26: 1 | I26: 148 | J26: 34 | K26: 183

Sheet Análise Detalhada
B2: ANÁLISE DETALHADA — LACUNAS DE INFORMAÇÃO E SUBGRUPOS
B3: Detalhamento do que falta em cada categoria e subgrupos por tipo de equipamento
B5: 1. STATUS DO CADASTRO — O QUE FALTA | L5: 2. RELIGADOR — DETALHAMENTO POR SUBGRUPO
B6: Categoria | C6: Qtd | L6: Categoria | M6: Qtd
B7: Equipamento identificado | C7: 80 | F7: Equipamento identificado | I7: 80 (44.2%) | L7: Religador (genérico) | M7: 19 | P7: Religador (genérico) | S7: 19 (70.4%)
B8: CABOS sem bitola/vão/tensão | C8: 30 | F8: CABOS sem bitola/vão/tensão | I8: 30 (16.6%) | L8: Bucha | M8: 1 | P8: Bucha | S8: 1 (3.7%)
B9: A definir (repasse) | C9: 54 | F9: A definir (repasse) | I9: 54 (29.8%) | L9: Compra | M9: 1 | P9: Compra | S9: 1 (3.7%)
B10: A definir (análise) | C10: 7 | F10: A definir (análise) | I10: 7 (3.9%) | L10: Controle/Caixa | M10: 1 | P10: Controle/Caixa | S10: 1 (3.7%)
B11: Possíveis repetidas | C11: 10 | F11: Possíveis repetidas | I11: 10 (5.5%) | L11: Tanque + Módulo | M11: 1 | P11: Tanque + Módulo | S11: 1 (3.7%)
L12: Sistema Comunicação | M12: 1 | P12: Sistema Comunicação | S12: 1 (3.7%)
F13: TOTAL | I13: 181 | L13: Tanque + Cabo umbilical | M13: 1 | P13: Tanque + Cabo umbilical | S13: 1 (3.7%)
L14: Obra gerada | M14: 1 | P14: Obra gerada | S14: 1 (3.7%)
L15: Parte Ativa | M15: 1 | P15: Parte Ativa | S15: 1 (3.7%)
P17: TOTAL | S17: 27
B22: 3. CABOS — LACUNAS DE INFORMAÇÃO TÉCNICA | L22: 4. REPASSES — DESTINOS
B23: Categoria | C23: Qtd | L23: Categoria | M23: Qtd
B24: Únicas - sem detalhe técnico | C24: 18 | F24: Únicas - sem detalhe técnico | I24: 18 (60.0%) | L24: Repassar DMSL | M24: 39 | P24: Repassar DMSL | S24: 39 (72.2%)
B25: Possíveis repetidas | C25: 12 | F25: Possíveis repetidas | I25: 12 (40.0%) | L25: Repassar COCM | M25: 12 | P25: Repassar COCM | S25: 12 (22.2%)
L26: OG existente | M26: 2 | P26: OG existente | S26: 2 (3.7%)
F27: TOTAL | I27: 30 | L27: Outros | M27: 1 | P27: Outros | S27: 1 (1.9%)
P29: TOTAL | S29: 54
B39: INSIGHTS PRINCIPAIS
B40: • 30 SS de CABOS (16%) estão sem nenhuma informação técnica (bitola, vãos, tensão) — bloqueio para orçamento preciso
B41: • 54 SS estão em REPASSE (30%) — depende de outras coordenações para evoluir
B42: • 10 SS marcadas como possivelmente repetidas — requerem revisão antes de tratar
B43: • 19 das 27 SS de RELIGADOR estão sem detalhamento do componente a substituir
B44: • Equipamento identificado com clareza: 80 de 183 SS (44%)

Sheet Pendências DMSL
C2: PENDÊNCIAS DO DMSL
C3: Tipo de equipamento extraído da Descrição (Parecer DMSL) | Nº Equipamento e Nº Obra identificados
C5: TOTAIS POR TIPO DE EQUIPAMENTO (extraído da Descrição)
C6: TOTAL DMSL | F6: RELIGADOR | I6: REGULADOR TENSÃO | K6: TANQUE | L6: TRANSFORMADOR | M6: OUTROS
C7: 33 | F7: 17 | I7: 8 | K7: 1 | L7: 1 | M7: 6
C11: DISTRIBUIÇÃO POR TIPO DE EQUIPAMENTO | P11: TOP LOCALIDADES
C12: Tipo | E12: Qtd | P12: Localidade | U12: Qtd
C13: RELIGADOR | D13: PARECER DA PROTEÇÃO: COMISSIONAR DO RT 5855606027 LD SERRA GERAIS E TAGUATINGA. NECESSARIO CONFERRIR MEDIÇÕES DA MALHA DE ATERRAMENTO ANTES DE INSERIR O ATIVO EM OPERAÇÃO. AJUSTES DISPONIVIEIS NO APP DA PROTEÇÃO. REGULADOR DE TENSAO N° 5855606027 REMANEJADO NA OBRA 0502500015 GENTILEZA, REALIZAR O COMISSIONAMENTO. LAUDO EM ANEXO. COORD EO: 990668, 8661389 TOP ANTIGA: 5838182027 PARECER DMSL: Realizado o comissionamento do RT nas fases A e C e na fase B foi constatado um curto elétrico na parte da caixa de comando. Foi feita toda parte de comunicação e configuração do rádio, inserindo ajustes de proteção. Número de série da placa fase B 017153. | E13: 17 | J13: RELIGADOR | M13: 17 (50.0%) | P13: ARAGUAINA | U13: 3
C14: REGULADOR TENSÃO | E14: 8 | J14: REGULADOR TENSÃO | M14: 8 (23.5%) | P14: PALMEIRAS DO TOCANTINS | U14: 2
C15: REPASSAR DMSL | E15: 4 | J15: REPASSAR DMSL | M15: 4 (11.8%) | P15: MIRACEMA DO TOCANTINS | U15: 2
C16: TANQUE | E16: 1 | J16: TANQUE | M16: 1 (2.9%) | P16: DIVINOPOLIS DO TOCANTINS | U16: 2
C17: TRANSFORMADOR | E17: 1 | J17: TRANSFORMADOR | M17: 1 (2.9%) | P17: PARAISO DO TOCANTINS | U17: 2
C18: ATERRAMENTO | E18: 1 | J18: ATERRAMENTO | M18: 1 (2.9%) | P18: FIGUEIROPOLIS | U18: 2
C19: CONTROLE | E19: 1 | J19: CONTROLE | M19: 1 (2.9%) | P19: ARAPOEMA | U19: 1
C20: BANCO CAPACITOR | E20: 1 | J20: BANCO CAPACITOR | M20: 1 (2.9%) | P20: SANTA ROSA DO TOCANTINS | U20: 1
F23: ⚡ RELIGADOR (17 SS)
C24: Código SS | D24: Descrição | E24: Ano | F24: Localidade | G24: Nº Equipamento | I24: Nº Obra | J24: Abrangência | K24: Instalação | L24: Análise Técnica | M24: Data Ocorrência | N24: Repetida? | O24: Observações
B25: =TRIM(C25) -> ETO-COEP 00152/2024 | C25: ETO-COEP 00152/2024 | D25: PARECER DMSL: FAVOR, INSTALAR POSTE DE 12 METROS AO LADO DO RELIGADOR 7955825037 PARA POSSIBILITAR O ESTABELECIMENTO DA COMUNICAÇÃO DO MESMO. RELIGADOR N° 7955825037 INSTALADO NA OBRA 0402300790 GENTILEZA, REALIZAR O COMISSIONAMENTO. LAUDO EM ANEXO. COORD EO: 719564, 8734324 PARECER DA PROTEÇÃO: AJUSTE DISPONIBILIZADO NO APP DA PROTEÇÃO, NOTA REPASSADA PARA DMSL COMISSIONAR, ID ORIGEM: 3320033037, PN 2024. ENG° IRLLEY CASTELO BRANCO | E25: 2024 | F25: ALIANCA DO TOCANTINS | G25: 7955825037 | H25: =_xlfn.XLOOKUP(C25,'Dados Tratados'!A:A,'Dados Tratados'!H:H) -> 7955825037 | I25: 0402300790 | J25: 3320033037 | K25: LD03040003 | L25: REPASSAR DMSL | M25: 08/11/2024 | N25: Não | O25: Ta Em Operação comunicando pelo Scada normal, pedir pro COCM Gurupi confirmar se foi feita o poste, se foi instalado qual foi a SS - | P25: Cancelada
B26: =TRIM(C26) -> ETO-COEP 00060/2026 | C26: ETO-COEP 00060/2026 | D26: PARECER DMSL: Realizar substituição do equipamento todo e parte ativa. Equipe: Adeilton e Edicleber Data: 12/03 ----------------------------------------------------------------------------- Religador sem comunicação, apos primeiro ataque o mesmo não retornou as comunicação. | E26: 2026 | F26: ARAGUAINA | H26: =_xlfn.XLOOKUP(C26,'Dados Tratados'!A:A,'Dados Tratados'!H:H) -> 7903569004 | J26: 9004017004 | K26: AL05010004 | L26: REPASSAR DMSL | M26: 11/03/2026
B27: =TRIM(C27) -> ETO-COEP 00076/2026 | C27: ETO-COEP 00076/2026 | D27: PARECER DMSL: Realizar a substituição do transformador. (Furtado) Equipe: Adeilton e Edicleber SID 1874/2026 17/04/2026 ______________________________________ PARECER DMSL: Chamado de desenvolvimento 30484170 criado. Favor, programar comissionamento a partir do dia 20/02/26. POLOCOL PARECER DA PROTEÇÃO: Planilha com as informações anexada. É sugerido que sejam conferidas as medições da malha de aterramento do equipamento antes da sua inserção no sistema. Isso é fundamental para garantir a segurança e a eficiência do equipamento. Os ajustes estão disponíveis no APP da proteção. Estagiário Rafael Pereira Marques. _____________________ RELIGADOR N° 7962635060 INSTALADO NA OBRA 0602401143 GENTILEZA, REALIZAR O COMISSIONAMENTO. LAUDO EM ANEXO. COORD EO: 789405, 9172143 | E27: 2026 | F27: ARAGUAINA | G27: 30484170 | H27: =_xlfn.XLOOKUP(C27,'Dados Tratados'!A:A,'Dados Tratados'!H:H) -> 7962635060 | I27: 0602401143 | J27: 3319797060 | K27: AL01054060 | L27: REPASSAR DMSL | M27: 22/12/2025 | P27: Repassada
B28: =TRIM(C28) -> ETO-COEP 00125/2024 | C28: ETO-COEP 00125/2024 | D28: PARECER DMSL: EQUIPAMENTO 7955175004 FOI INSTALADO SEM O CABO UMBILICAL. FAVOR, SANAR A PENDÊNCIA PARA PROSSEGUIRMOS COM O COMISSIONAMETNO. RELIGADOR N° 7955175004 INSTALADO NA OBRA 0602300755 GENTILEZA, REALIZAR O COMISSIONAMENTO. LAUDO EM ANEXO. COORD EO: 808265, 9205592 PARECER DA PROTEÇÃO: AJUSTE DISPONIBILIZADO NO APP DA PROTEÇÃO, NOTA REPASSADA PARA DMSL COMISSIONAR, RL PN 2024 ID ORIGEM: COODR.7 POLO ARAGUAÍNA. ENG° IRLLEY CASTELO BRANCO. | E28: 2024 | F28: ARAGUAINA | G28: 7955175004 | H28: =_xlfn.XLOOKUP(C28,'Dados Tratados'!A:A,'Dados Tratados'!H:H) -> 7955175004 | I28: 0602300755 | J28: 8855167004 | K28: AL02040004 | L28: REPASSAR DMSL | M28: 10/09/2024 | O28: Ta com cabo umbilical, pode cancelar , só confirmar Parecer João:SS Cancelada , equipamento em operação pelo Scada, como não tem como ele estar em operação sem o cordão umbilical, cancelamos a SS | P28: Cancelada
B29: =TRIM(C29) -> ETO-COEP 00157/2024 | C29: ETO-COEP 00157/2024 | D29: FAVOR RELIZAR MANUTENÇAO NO EQUIPAMENTO O MESMO ESTA COM FALTA DE ITENS NECESSARIOS PARA SE REALIZAR O COMISSIONAMENTO. RELIGADOR N° 7956117005 INSTALADO NA OBRA 0502300584 GENTILEZA, REALIZAR O COMISSIONAMENTO. LAUDO EM ANEXO. COORD EO: 939068, 8569277 PARECER DA PROTEÇÃO: FAVOR COMISSIONAR O RL 7956117005 AL 01 ARRAIAS - PN 2024. AJUSTES DIPONIVEIS NO APP DA PROTEÇÃO. PONTO ORIGEM PN 2024 - UTM: 939117;8569319 | E29: 2024 | F29: ARRAIAS | G29: 7956117005 | H29: =_xlfn.XLOOKUP(C29,'Dados Tratados'!A:A,'Dados Tratados'!H:H) -> 7956117005 | I29: 0502300584 | J29: 0300056005 | K29: AL01013005 | L29: REPASSAR DMSL | M29: 11/11/2024 | O29: Já instalado e está em operação - Confirmar se pode excluir | P29: Cancelada
B30: =TRIM(C30) -> ETO-COEP 00168/2025 | C30: ETO-COEP 00168/2025 | D30: Foi realizado primeiro ataque no religador 7908196047, e o mesmo nao voltou a comunicação para o centro de operação. favor enviar equipe para devidas tratativas PARECER DMSL: Trocar o equipamento completo, equipamento antigo e sem supervisão | E30: 2025 | F30: FIGUEIROPOLIS | G30: 7908196047 | H30: =_xlfn.XLOOKUP(C30,'Dados Tratados'!A:A,'Dados Tratados'!H:H) -> 7908196047 | I30: 0402401150 | J30: 8859726047 | K30: AL02033047 | L30: ENTENDER COM DMSL | M30: 29/09/2025 | N30: SIM | O30: Equipamento no Mapa ta em operação , mas no Scada tá Bypassado, além de que tem 2 SS para ele 215/2025 e 168/2025 | P30: Ver com o Miguel no Scada novamente
B31: =TRIM(C31) -> ETO-COEP 00215/2025 | C31: ETO-COEP 00215/2025 | D31: RELIGADOR N° 7908196047 REMANEJADO NA OBRA 0402401150 GENTILEZA, REALIZAR O COMISSIONAMENTO. LAUDO EM ANEXO. COORD EO: 698485, 8657287 PARECER DA PROTEÇÃO: AJUSTE DISPONIBILIZADO NO APP DA PROTEÇÃO, NOTA REPASSADA PARA DMSL COMISSIONAR, POLO GURUPI, RL APENAS REMANEJADO DA REDE VELHA PARA REDE NOVA, EQUIPAMENTO COOPER, SE MANTEVE O MESMO NÚMERO DE ATIVO. ENG° IRLLEY CASTELO BRANCO. PARECER DMSL: Constatado curto-circuito no tanque do religador, impedindo as operações de abertura e fechamento do equipamento. Solicita-se a substituição completa do religador, incluindo tanque e unidade de controle. | E31: 2025 | F31: FIGUEIROPOLIS | G31: 7908196047 | H31: =_xlfn.XLOOKUP(C31,'Dados Tratados'!A:A,'Dados Tratados'!H:H) -> 7908196047 | I31: 0402401150 | J31: 8859726047 | K31: AL02033047 | L31: ENTENDER COM DMSL | M31: 29/09/2025 | N31: SIM | O31: Equipamento no Mapa ta em operação , mas no Scada tá Bypassado, além de que tem 2 SS para ele 215/2025 e 168/2025 | P31: Ver com o Miguel no Scada novamente
B32: =TRIM(C32) -> ETO-COEP 00074/2026 | C32: ETO-COEP 00074/2026 | D32: PARECER DMSL: Substituir Equipamento completo problema na placa de alimentação e na parte ativa, falta colocar placa de identificação correta na topologia, baixar o controle. Equipamento ficou em operação?: nao Pendência: sim Bateria(s) substituída(s)? NÃO Equipe: Kaique/ Benvindo ---------------------------------------------- PARECER DA PROTEÇÃO: Prosseguir com o comissionamento. Ajustes de religador permanecem os mesmos, disponíveis no APP da Proteção. ******************************** RELIGADOR N°7919270014 REMANEJADO NA OBRA 0212501060 GENTILEZA, REALIZAR O COMISSIONAMENTO. LAUDO EM ANEXO. COORD EO: 617422, 8830787 | E32: 2026 | F32: LAGOA DA CONFUSAO | G32: 7919270014 | H32: =_xlfn.XLOOKUP(C32,'Dados Tratados'!A:A,'Dados Tratados'!H:H) -> 7919270014 | I32: 0212501060 | J32: 8801059073 | K32: LD01047073 | L32: REPASSAR DMSL | M32: 25/02/2026 | N32: Não
B33: =TRIM(C33) -> ETO-COEP 00119/2025 | C33: ETO-COEP 00119/2025 | D33: PARECER DMSL: Favor, solicitamos que o tanque do equipameneto 7925573007 seja retirado da base para que possamos realizar o ensaio do mesmo. Equipe do DMSL já esteve no equipamento anteriormetne porém as chaves estavam emperradas e não consequimos apoio da equipe de linha viva no momento que a equipe estava no RLG. Equipamento com erro de medição de neutro, corrente alta com sistema equilibrado não refletindo a real situação. Precisamos de intervenção corretiva, as hipoteses podem ser aterramento, mal contato, sensor do tanque, cabo umbilical, calibração ou proprio relé. Equipe de linha-viva já esteve no local para atender a SS, Porém foram testadas todas as chaves e não havia nenhuma emperrada. Equipe do DMSL já pode retornar para dar sequência na Atividade. PARECER DMSL DIA 24/06/2025: Serviço executado: Teste com mala de corrente virtual, e física, para indentificar onde e o problema no neutro que está lendo corrente muito alto. Foi descoberto diante dos testes que a parte ativa está com problemas, quando ligamos a mala física e não injetamos corrente, o neutro registra uma corrente alta, está detectado alguma indução. Necessário substituir a parte ativa do equipamento. Quando substituir lembrar de colocar a base normal com os quatro grupos. Equipamento ficou em operação?: Sim, em modo seccionalizador a pedido da proteção Pendência: sim, substituir parte ativa | E33: 2025 | F33: MIRACEMA DO TOCANTINS | G33: 7925573007 | H33: =_xlfn.XLOOKUP(C33,'Dados Tratados'!A:A,'Dados Tratados'!H:H) -> 7925573007 | J33: 7925573007 | K33: AL01048007 | L33: REPASSAR DMSL | M33: 30/10/2024 | N33: Não | O33: Equipamento em comunicação normal, confirmar com os COCM Paraíso (Vinicius Camargo) - Precisa fazer substituição da parte ativa
B34: =TRIM(C34) -> ETO-COEP 00049/2026 | C34: ETO-COEP 00049/2026 | D34: PARECER DMSL: *DATA*16/03/2026 Serviço Executado: É NECESSARIO REALIZAR A SUBSTITUIÇAO COMPLETA DO CONTROLE, EQUIPAMENTO DANIFICADO - FABRICANTE NOJA Equipamento ficou em operação?: Não Pendência: Sim, FAVOR REALIZAR AS CORREÇOES Bateria(s) Substituída(s): Não Data Fabricação/Instalação da(s) bateria(s): 07/2025 Equipe: Benvindo e Kaique PARECER DMSL : Solicitação já cumprida. Chamado 3047281 aberto em caráter emergencial, com comissionamento programado a partir de 02/02/2026. PARECER DA PROTEÇÃO: NOTA REPASSADA PARA DMSL, ABRIR CHAMADOS DE SCADA E COMISSIONAMENTO DO EQUIPAMENTO. ENG° IRLLEY CASTELO BRANCO. RELIGADOR N° 7963661046 INSTALADO NA OBRA 0202500503 GENTILEZA, REALIZAR O COMISSIONAMENTO. LAUDO EM ANEXO. COORD EO: 728315, 8830256 | E34: 2026 | F34: NOVA ROSALANDIA | G34: 7963661046 | H34: =_xlfn.XLOOKUP(C34,'Dados Tratados'!A:A,'Dados Tratados'!H:H) -> 7963661046 | I34: 0202500503 | J34: 8863660046 | K34: LD01056046 | L34: REPASSAR DMSL | M34: 30/01/2026 | O34: Controle Danificado- Outro controle , ver se está na garantia Já foi colocado em Operação , foi comissionado , aí depois deram o feedback do controle danificado
B35: =TRIM(C35) -> ETO-COEP 00188/2025 | C35: ETO-COEP 00188/2025 | D35: PARECER DMSL: Foi alinhado com Irlley da proteção que será necessário substituir o equipamento RLG 7905357122 pois o relé possui limitações no ajuste e por não ser possível acessá-lo para coletar eventos, se tratando de um modelo obsoleto. Foi alinhado que o equipamento permanecerá em operação até que seja substituído. Favor, realizar substiuição por um modelo NOJA RC10 e programar a poda de árvores próxima do equipamento. Boa noite Segue SS para verificação de ajuste de proteção do RL 7905357122 poste a abalroado de ID 57407652 os cabos MT ficou encostanto na arvore pegando fogo e o RL não atuou a proteção. Parecer da proteção: Conferir os ajustes de proteção do RC01, reincidente em não abrir. Realizar teste funcional com mala de carga. Eng° Irlley Castelo Branco | E35: 2025 | F35: PALMAS | G35: 7905357122 | H35: =_xlfn.XLOOKUP(C35,'Dados Tratados'!A:A,'Dados Tratados'!H:H) -> 7905357122 | J35: 7905357122 | K35: AL03097122 | L35: REPASSAR DMSL | M35: 18/05/2024 | O35: Aguardando troca de Relé, tá em operação
B36: =TRIM(C36) -> ETO-COEP 00073/2026 | C36: ETO-COEP 00073/2026 | D36: PARECER DMSL: Fase C. Sentindo carga Chave faca não fechou, realizar substituição. DATA: 09/04/2026 SID 1756/2026 Equipe: Adeilton e Edicleber ___________________________________ PARECER DMSL: Chamado de desenvolvimento 30487776 criado. Favor, programar comissionamento a partir do dia 09/03/2026. (POLOTOC) PARECER DA PROTEÇÃO: ESTUDO REALIZADO. OS AJUSTES ESTÃO DISPONÍVEIS NO APP DA PROTEÇÃO. Estagiário Rafael Pereira Marques ___________ RELIGADOR N° 7967181127 INSTALADO NA OBRA 0652400757 GENTILEZA, REALIZAR O COMISSIONAMENTO. LAUDO EM ANEXO. COORD EO: 874476, 9275510 | E36: 2026 | F36: PALMEIRAS DO TOCANTINS | G36: 30487776 | H36: =_xlfn.XLOOKUP(C36,'Dados Tratados'!A:A,'Dados Tratados'!H:H) -> 7967181127 | I36: 0652400757 | J36: 6800580127 | K36: LD01084002 | L36: REPASSAR DMSL | M36: 23/01/2026 | N36: SIM
B37: =TRIM(C37) -> ETO-COEP 00120/2025 | C37: ETO-COEP 00120/2025 | D37: PARECER DMSL: Após testes, equipe DMSL constatou que o relé e a parte ativa do equipamento 7920024127 estão com defeito, sendo necessária a substituição completa por um modelo NOJA RC 10. Favor, subsituir também a chave de saída da fase A que está com o anel de abertura quebrado. RL 7920024127 está desarmando em campo e no SCADA continua fechado, só sinaliza aberto no SCADA quando a equipe faz o resert no equipamento em campo. | E37: 2025 | F37: PALMEIRAS DO TOCANTINS | G37: 7920024127 | H37: =_xlfn.XLOOKUP(C37,'Dados Tratados'!A:A,'Dados Tratados'!H:H) -> 7920024127 | J37: 9001177127 | K37: LD01084002 | L37: RELIGADOR | M37: 02/06/2025 | N37: SIM
B38: =TRIM(C38) -> ETO-COEP 00078/2026 | C38: ETO-COEP 00078/2026 | D38: PARECER DMSL: Feedback Equip. Especiais RLG 7926089013, RELÉ NOJA RC10 SID 1805/2026 DATA 15/04/2026 Serviço Executado: Favor realizar a troca da parte ativa do equipamento --reprogramar para atualizar a base juntamente com escada Equipamento ficou em operação: Não Pendência: sim atualizar a base e subistituir o tanque Bateria(s) substituída(s)? Não Data de Fabricação/Instalação da(s) bateria(s): Equipe: Carliel e João Vitor Fernando e Elson --------------------------------------------------------------------------------- ATUALIZAR AJUSTES DO RL 7926089013 LD PARAISO I A PIUM. IMPLEMENTAÇÃO DA FUNÇÃO 27, SUBTENSÃO. AJUSTES DISPONIVEIS NO APP DA PROTEÇÃO. | E38: 2026 | F38: PARAISO DO TOCANTINS | G38: 7926089013 | H38: =_xlfn.XLOOKUP(C38,'Dados Tratados'!A:A,'Dados Tratados'!H:H) -> 7926089013 | J38: 7926089013 | K38: LD03062013 | L38: REPASSAR DMSL | M38: 27/03/2026 | N38: SIM | O38: Problema na parte a parte ativa equipamento inteiro
B39: =TRIM(C39) -> ETO-COEP 00086/2026 | C39: ETO-COEP 00086/2026 | D39: NOTA DMSL: Favor substituir o tanque, ele não está efetuando os comandos enviados. Não substituir o controle pois o mesmo funciona como repetidor de outros equipamentos. Segue nota para verificar falha de fechamento religador 7908686014- Pium . OBS: equipamento não fechou local e remoto , fica sinalizando no painel para verificar alarmes ! | E39: 2026 | F39: PIUM | G39: 7908686014 | H39: =_xlfn.XLOOKUP(C39,'Dados Tratados'!A:A,'Dados Tratados'!H:H) -> 7908686014 | J39: 7908686014 | K39: LD02025012 | L39: TANQUE | M39: 15/10/2024 | O39: Tem que trocar o Tanque
B40: =TRIM(C40) -> ETO-COEP 00170/2024 | C40: ETO-COEP 00170/2024 | D40: PARECER DMSL: NÃO FOI POSSÍVEL COMISSIONAR O EQUIPAMENTO DEVIDO A AUSÊNCIA DO RÁDIO GE. FAVOR, PROVIDENCIAR O RÁDIO. RELIGADOR N° 7959990070 INSTALADO NA OBRA 0102400139 GENTILEZA, REALIZAR O COMISSIONAMENTO. LAUDO EM ANEXO. COORD EO: 849610, 8957866 PARECER DA PROTEÇÃO: AJUSTE DISPONIBILIZADO NO APP DA PROTEÇÃO, NOTA REPASSADA PARA DMSL COMISSIONAR, RL ORIGINARIO DO ID: 3300730070 PN 2024. ENG° IRLLEY CASTELO BRANCO. | E40: 2024 | F40: RIO SONO | G40: 7959990070 | H40: =_xlfn.XLOOKUP(C40,'Dados Tratados'!A:A,'Dados Tratados'!H:H) -> 7959990070 | I40: 0102400139 | J40: 8800157070 | K40: LD02065015 | L40: REPASSAR DMSL | M40: 30/09/2024 | O40: Está em funcionamento , pode rirar
B41: =TRIM(C41) -> ETO-COEP 00091/2025 | C41: ETO-COEP 00091/2025 | D41: PARECER DMSL: Não foi possível comissionar o equipamento 7956063152 pois o mesmo estava sem cordão umbilical, sem rádio e conexões, e sem alimentação do trafo no equipamento. Favor, sanar pendências. GENTILEZA COMISSIONAR RELIGADOR, PARTE CONSTRUTIVA FISCALIZADA. EQUIPAMENTO: NOJA POWER Nº SERIE: 0320124013012 CONTROLE: NOJA POWER MODELO: RC-10ES Nº SERIE: 0101523100769. PARECER DA PROTEÇÃO: AJUSTE DISPONIBILIZADO NO APP DA PROTEÇÃO, NTA REPASSADA PARA DMSL COMISSIONAR, RL ORIGINARIO DE DEMANDA DE CLIENTE GRUPO A. ENG° IRLLEY CASTELO BRANCO | E41: 2025 | F41: SANTA ROSA DO TOCANTINS | G41: 7956063152 | H41: =_xlfn.XLOOKUP(C41,'Dados Tratados'!A:A,'Dados Tratados'!H:H) -> 7956063152 | J41: 9000376152 | K41: LD02072001 | L41: REPASSAR DMSL | M41: 09/09/2024 | O41: Já comissionado em operação
B42: =TRIM(C42) -> ETO-COEP 00141/2025 | C42: ETO-COEP 00141/2025 | D42: PARECER DMSL: Favor, realizar substituição completa do equipamento 7900930040, pois o mesmo trata-se de modelo obsoleto NOJA RC01 e esteve envolvido em ocorrência relevante. Realizar substituição por modelo NOJA RC10. Segue nota para verificar falha de comunicação no RL 7900930040 - Aragominas . equipamento desarmou e perdeu sua comunicação , registro intervenção N: 20253690827473 . | E42: 2025 | G42: 7900930040 | H42: =_xlfn.XLOOKUP(C42,'Dados Tratados'!A:A,'Dados Tratados'!H:H) -> 2ARM-004-7900930040 | K42: 2ARM | L42: REPASSAR DMSL | M42: 20/06/2025 | O42: Já trocado o Relé , já foi trocado , já pode baixar como concluída
C45: 🔧 REGULADOR TENSÃO (8 SS)
C46: Código SS | E46: Ano | F46: Localidade | G46: Nº Equipamento | I46: Nº Obra | J46: Abrangência | K46: Instalação | L46: Análise Técnica | M46: Data Ocorrência | N46: Repetida?
C47: ETO-COEP 00055/2026 | D47: DCMD 26.03.2026. SS REPASSADA PARA COEP PROVIDENCIAR MATERIAL. NÃO TEMOS O MATERIAL EM ESTOQUE PARA SUBSTITUIÇÃO. COEP: Equipamento fornecido ao COCM-S para regularização. PARECER DA PROTEÇÃO: EQUIPAMENTOS FURTADOS. PARA AQUISIÇÃO DAS CELULAS DE REPOSIÇÃO, FAVOR CONSULTAR OS DADOS DE PLACA EM ANEXO. PARECER DA PROTEÇÃO: COMISISONAR RT 5856156091 LD DIANOPOLIS A NATIVIDADE. NECESSARIO REALIZAR MEDIÇÕES DA RESISTENCIA DA MALHA DE ATERRAMENTO. AJUSTES DISPONIVEIS NO APP DA PROTEÇÃO. RELIGADOR N° 5856156091 INSTALADO NA OBRA 0502400526 GENTILEZA, REALIZAR O COMISSIONAMENTO. LAUDO EM ANEXO. COORD EO: 899501, 8714782 | E47: 2026 | F47: ALMAS | G47: =_xlfn.XLOOKUP(C47,'Dados Tratados'!A:A,'Dados Tratados'!H:H) -> 5856156091 | I47: 0502400526 | J47: 8832258091 | K47: LD04002091 | L47: REPASSAR DMSL | M47: 16/06/2025 | N47: Ver se já chegou
C48: ETO-COEP 00112/2025 | D48: PARECER DMSL: Equipe esteve no RT 5856825025 dia 10/06/2025 porém não foi possível colocar o equipamento em operação devido defeito no controle. Favor, substituir controle e fornecer o rádio e centelhador para que seja possível colocar comunicação no equipamento. PARECER DA PROTEÇÃO: COMISSIONAR RT 5856825025 LD BERNARDO SAYÃO A ARAPOEMA. NECESSARIO CONFERIR MEDIÇÕES DA MALHA DE ATERRAMENTO. AJUSTES DISPONIVEIS NO APP DA PROTEÇÃO. REGULADOR DE TENSAO N° 5856825025 INSTALADO NA OBRA 0602400710 GENTILEZA, REALIZAR O COMISSIONAMENTO. LAUDO EM ANEXO. COORD EO: 719554, 9150284 | E48: 2025 | F48: ARAPOEMA | G48: =_xlfn.XLOOKUP(C48,'Dados Tratados'!A:A,'Dados Tratados'!H:H) -> 5856825025 | I48: 0602400710 | J48: 8837969025 | K48: LD02010153 | L48: REPASSAR DMSL | M48: 25/03/2025
C49: ETO-COEP 00025/2026 | D49: COEP: equipamentos fornecidos. Repasse ao COCM para correção. PARACER DA PROTEÇÃO: Recebemos a solicitação de elaboração de ajustes do RT 5854681071, nota repassada pelo COEP. Duvidas: As pendencias apontadas pelo DMSL foram sanadas? Pois não registro descritivo na SS. Se foram sanadas, a SS não seguiu o fluxo norma, pois não há repassa da nota para o COEP. Podemos seguir com os estudos e comissionamento do ativo? PARECER DMSL: Equipe esteve no RT 5854681071 dia 18/02/2025 porém, as fases A e B estão com a ligação carga/fase invertidas, não contém antena, não contém suporte de antena e não contém rádio GE. Favor, sanar pendências para possibilitar o comissonamento. REGULADOR DE TENSAO N° 5854681071 INSTALADO NA OBRA 0302100570 GENTILEZA, REALIZAR O COMISSIONAMENTO. LAUDO EM ANEXO. COORD EO: 766351, 8781674 PARECER DA PROTEÇÃO ESTUDO DO EQUIPAMENTO DISPONIVEL NO APP DA PROTEÇÃO, NOTA REPASSADA PARA O DMSL COMISSIONAR O EQUIPAMENTO. TEC° EUZILAN MATEUS BARREIRA SANTOS | E49: 2026 | F49: BREJINHO DE NAZARE | G49: =_xlfn.XLOOKUP(C49,'Dados Tratados'!A:A,'Dados Tratados'!H:H) -> 5854681071 | I49: 0302100570 | J49: 9000001071 | K49: AL01018071 | L49: REPASSAR DMSL | M49: 21/11/2024
C50: ETO-COEP 00217/2025 | D50: PARECER DMSL: Durante testes foi constatado que o controle apresenta defeito, impossibilitando a finalização do comissionamento. Favor, substituir controle RUA. "PARECER DA PROTEÇÃO: COMISSIONAR RT 5862546023 AL 01 COLINAS. NECESSARIO CONFERIR MEDIÇÕES DA MALHA DE ATERRAMENTO ANTES DE INSERIR O ATIVO NO SISTEMA. AJUSTES DISPONIVIEIS NO APP DA PROTEÇÃO. ************************************************************** REGULADOR N° 5862546023 INSTALADO NA OBRA 0702500104 GENTILEZA, REALIZAR O COMISSIONAMENTO. LAUDO EM ANEXO. COORD EO: 775889, 9112829" | E50: 2025 | F50: COLINAS DO TOCANTINS | G50: =_xlfn.XLOOKUP(C50,'Dados Tratados'!A:A,'Dados Tratados'!H:H) -> 5862546023 | I50: 0702500104 | J50: 8813300023 | K50: AL01020023 | L50: REPASSAR DMSL | M50: 04/11/2025
C51: ETO-COEP 00066/2026 | D51: PARECER DMSL: *FEEDBACK EQUIP. ESPECIAIS* *Nº DO EQUIPAMENTO:* 5800291077 *DATA DA MANUTENÇÃO:* 07/04/2026 *SID:* 1709/2026 *DESCRIÇÃO:* Realizado ensaios nas células do banco 5800291077, identificado fase B em curto *FICOU EM OPERAÇÃO?:* Não *PENDÊNCIA:* SIM *EQUIPE:* Adeilton e Edicleber Realizar substituição da célula da fase B Em curto. _____________________________________________________________ Segue SS para enviar equipe do DMSL para no regulador de tensão 5800291077. O mesmo ficou bay passado devido esta com defeito e causar desarme na LD e penalizar a RDU de Goiatins. Por gentileza enviar equipe urgente. | E51: 2026 | F51: GOIATINS | G51: =_xlfn.XLOOKUP(C51,'Dados Tratados'!A:A,'Dados Tratados'!H:H) -> 5800291077 | J51: 8800288077 | K51: LD03105019 | L51: REPASSAR DMSL | M51: 03/04/2026
C52: ETO-COEP 00170/2025 | D52: PARECER DMSL: Malha de aterramento está dando 738, muito acima do aceitável para operação do RT. Necessário realizar melhoria na malha. PARECER DA PROTEÇÃO: COMISSIONAR RT 5863381155 LD COLINAS A B SAYAO E PALMEIRANTE. NECESSARIO CONFERIR MALHA DE ATERRAMENTO ANTES DE INSERIR O ATIVO NO SISTEMA. AJUSTES DISPONIVEIS NO APP DA PROTEÇÃO. REGULADOR N° 5863381155 INSTALADO NA OBRA 0702500302 GENTILEZA, REALIZAR O COMISSIONAMENTO. LAUDO EM ANEXO. COORD EO: 800396, 9107697 | E52: 2025 | F52: PALMEIRANTE | G52: =_xlfn.XLOOKUP(C52,'Dados Tratados'!A:A,'Dados Tratados'!H:H) -> 5863381155 | I52: 0702500302 | J52: 8800518155 | K52: LD01020023 | L52: REPASSAR DMSL | M52: 03/07/2025
C53: ETO-COEP 00077/2026 | D53: PARECER DMSL: RT 5801866013 Serviço Executado: Feito a medição da malha de terra. Identificado infiltração na caixa de passagem da célula da fase C do banco regulador de tensão, será necessário fazer a substituição da mesma! Ficar atento na hora da substituição, deverá ser substituída a célula do lado da BR. Obs.: Será necessário baixar todo o banco pelo menos um metro, as buchas estão muito próximas a parte energizada não oferecem segurança para equipe no momento do ensaio elétrico. Equipamento ficou em operação?: Não Possui nobreak: Sim Possui antena: Sim Possui rádio:Sim Pendência: Sim Data da bateria: Equipe: Benvindo e Kaique. _______________________________________________ RT 5801866013 BY PASSADO DEVIDO DEFEITO EM CELULA BEMVINDO ESTEVE NO LOCAL JUNTO AO COD . NECESSARIO TRATATIVA PARA MESMA . FASE DANIFICADO C | E53: 2026 | F53: PARAISO DO TOCANTINS | G53: =_xlfn.XLOOKUP(C53,'Dados Tratados'!A:A,'Dados Tratados'!H:H) -> 5801866013 | J53: 9001891013 | K53: AL03062013 | L53: REPASSAR DMSL | M53: 02/03/2026
C54: ETO-COEP 00198/2025 | D54: PARECER DA PROTEÇÃO: COMISSIONAR RT 5835587001 AL 03 PORTO NACIONAL. NECESSARIO CONFERIR MEDIÇÕES DA MALHA DE ATERRAMENTO ANTES DE INSERIR O ATIVO NO SISTEMA. AJUSTES DISPONIVIEIS NO APP DA PROTEÇÃO. ************************************************************** REGULADOR N° 5835587001 REMANEJADO NA OBRA 0302400526 GENTILEZA, REALIZAR O COMISSIONAMENTO. LAUDO EM ANEXO. COORD EO: 790054, 8821052 parecer dmsl: Data: 23/09/2025 SID: 3949 Serviço realizado: Será necessário substituir a célula da fase B do banco regulador de tensão! * Substituir a placa E * ¿Fazer melhoria na malha de terra do equipamento * ¿Não tem comunicação, necessário levar radio GE, antena com suporte e cabos. * ¿Quando retornar levar rele, nobreack e baterias novas. * ¿Tem que desenhar, desenvolver e testar com Scada. | E54: 2025 | F54: PORTO NACIONAL | G54: =_xlfn.XLOOKUP(C54,'Dados Tratados'!A:A,'Dados Tratados'!H:H) -> 5835587001 | I54: 0302400526 | J54: 3103141001 | K54: AL03072001 | L54: REPASSAR DMSL | M54: 09/09/2025
C57: 🛢️ TANQUE (1 SS)
C58: Código SS | E58: Ano | F58: Localidade | G58: Nº Equipamento | I58: Nº Obra | J58: Abrangência | K58: Instalação | L58: Análise Técnica | M58: Data Ocorrência | N58: Repetida?
C59: ETO-COEP 00050/2026 | D59: =_xlfn.XLOOKUP(C59,'Dados Tratados'!A:A,'Dados Tratados'!C:C,"") -> PARECER DMSL: Data: 10/03/2026,Serviço Executado: Foi substituído o relé do equipamento, o mesmo estava danificado. Trocado o DPS, o mesmo estava queimado devido ao tanque estar furado. O equipamento ficou em bypass. Equipamento ficou em operação? Não Pendência? Sim, substituir a parte ativa com cordão umbilical.Equipe: Carliel e João Vitor SEGUE SS PARA REGULARIZAR AUTOMAÇÃO DO RL 7953610256 NA INTERLIGAÇÃO COM A COELBA (CHAPADA DA MANGABEIRA) - EQUIPE INFOMOU CURTO INTERNO NO GABINETE DJ AC NÃO FECHA | E59: 2026 | F59: MATEIROS | G59: 7953610256 | J59: 8800246256 | K59: LD03046026 | L59: REPASSAR DMSL | M59: 16/02/2026
C62: ⚙️ TRANSFORMADOR (1 SS)
C63: Código SS | E63: Ano | F63: Localidade | G63: Nº Equipamento | I63: Nº Obra | J63: Abrangência | K63: Instalação | L63: Análise Técnica | M63: Data Ocorrência | N63: Repetida?
C64: ETO-COEP 00051/2026 | D64: =_xlfn.XLOOKUP(C64,'Dados Tratados'!A:A,'Dados Tratados'!C:C,"") -> PARECER DMSL: Data: 12/03/2026 Serviço Executado: - Análise técnica constatou: - Parte ativa do equipamento danificada: necessita substituição - Trafo danificado: foi feitos testes nas buchas secundárias o mesmo não chega tensão - Vazamento de óleo - Necessita substituição Equipamento ficou em operação? Não Pendências: - Solicitar limpeza de faixa para acesso ao equipamento - Trocar parte ativa do equipamento - Substituir o trafo Equipe: Carliel e João Vitor Segue nota para envia equipe verificar falha de comunicação e automação no RL-7926442035 feito primeiro ataque com equipe 035OP02, porém sem sucesso. | E64: 2026 | F64: MONTE DO CARMO | G64: 7926442035 | J64: 7926442035 | K64: LD01051035 | L64: REPASSAR DMSL | M64: 18/02/2026
C69: 📟 CONTROLE (1 SS)
C70: Código SS | E70: Ano | F70: Localidade | G70: Nº Equipamento | I70: Nº Obra | J70: Abrangência | K70: Instalação | L70: Análise Técnica | M70: Data Ocorrência | N70: Repetida?
C71: ETO-COEP 00068/2026 | D71: =_xlfn.XLOOKUP(C71,'Dados Tratados'!A:A,'Dados Tratados'!C:C,"") -> PARECER DMSL: *FEEDBACK EQUIP. ESPECIAIS* *Nº DO EQUIPAMENTO:* 7929376022 *DATA DA MANUTENÇÃO:* 02/04/2026 *SID:* 1677/2026 *DESCRIÇÃO:* Trocar controle completo *PENDÊNCIA:* Sim. *DADOS DIVERGENTES DA PROGRAMAÇÃO:* Não *BATERIA SUBSTITUÍDA?:* Não *EQUIPE:* Adeilton e Edicleber __________________________________________________________ POR GENTILEZA ATENDER SOLICITAÇÃO PRIMEIRO ATAQUE IDENTIFICOU QUE RELE ESTA EM CURTO NOTA ABERTA 224/2026 FOI BAIXADA POREM NÃO FOI CORRIGIDO PROBLEMA EM CAMPO. | E71: 2026 | F71: BABACULANDIA | G71: 7929376022 | J71: 9001690022 | K71: LD05010004 | L71: REPASSAR DMSL | M71: 25/03/2026
C74: ⏚ ATERRAMENTO (1 SS)
C75: Código SS | E75: Ano | F75: Localidade | G75: Nº Equipamento | I75: Nº Obra | J75: Abrangência | K75: Instalação | L75: Análise Técnica | M75: Data Ocorrência | N75: Repetida?
C76: ETO-COEP 00054/2026 | D76: =_xlfn.XLOOKUP(C76,'Dados Tratados'!A:A,'Dados Tratados'!C:C,"") -> PARECER DMSL: PENDÊNCIA: Realizar melhoria no aterramento por ser tratar de um terreno muito arenoso, e há pendências por parte do time da proteção, os ajustes do RT não estão disponíveis para inserção no referido equipamento. DATA DA MANUTENÇÃO: 12/03/202 EQUIPE: Brunno e Edeglan. *********************** PARECER DA PROTEÇÃO: FAVOR COMISSIONAR REGULADOR 5865120195 – LD Santa Maria Ramal Centenário e Recursolândia – 34,5kV. AJUSTE REALIZADO, DISPONÍVEL NO APP DA PROTEÇÃO. *********************** INSTALADO NA OBRA 0702400720 GENTILEZA, REALIZAR O COMISSIONAMENTO. LAUDO EM ANEXO. COORD EO: 889017, 9016857 | E76: 2026 | F76: CENTENARIO | G76: 5865120195 | I76: 0702400720 | J76: 8800183195 | K76: LD01065015 | L76: REPASSAR DMSL | M76: 11/02/2026
C79: 🔁 REPASSAR DMSL (4 SS)
C80: Código SS | E80: Ano | F80: Localidade | G80: Nº Equipamento | I80: Nº Obra | J80: Abrangência | K80: Instalação | L80: Análise Técnica | M80: Data Ocorrência | N80: Repetida?
C81: ETO-COEP 00063/2026 | D81: Equipamento ficou em operação?: Não Pendência: Sim será necessário substituir a placa Serviço Executado: curto na placa foi tentando recuperar a mesma porém não teve sucesso! Bateria(s)substituída(s)? NÃO Equipe: Kaique e benvido | E81: 2026 | F81: CASEARA | J81: 7944559149 | K81: LD01434149 | L81: REPASSAR DMSL | M81: 17/03/2026
C82: ETO-COEP 00028/2026 | D82: FEITO O PRIMEIRO ATAQUE NO RL 7954668084 E O DISPLAY ESTÁ QUEIMADO, NÃO LIGA. OS (99) 106230846 | E82: 2026 | F82: DIVINOPOLIS DO TOCANTINS | G82: 7954668084 | J82: 6820041084 | K82: LD04062013 | L82: REPASSAR DMSL | M82: 03/02/2026 | N82: Precisa trocar mesmo , comprar outro
C83: ETO-COEP 00062/2026 | D83: PARECER DMSL : Equipamento com a placa de alimentação ca em curto, será necessário substituir a placa do equipamento. Equipamento ficou em operação?: Não Pendência: Sim OBS :Data Fabricação/Instalação da(s) bateria(s): 04/2024 Equipe: Benvindo e Kaique- SS ANTIGA 277/2026 BAIXADA POR ENGANO PELA EQUIPE | E83: 2026 | F83: DIVINOPOLIS DO TOCANTINS | J83: 7955986084 | K83: LD04062013 | L83: REPASSAR DMSL | M83: 31/03/2026
C84: ETO-COEP 00064/2026 | D84: PARECER DMSL: Necessário substituir a placa de alimentação ca, a mesma está em curto não conseguimos recuperar. Equipamento ficou em operação?: _Nao Pendência: Sim Bateria(s) Substituída(s)? Não Data Fabricação/Instalação da(s) bateria(s): 06/2024 Equipe: Benvindo e Kaique ---------------------------------------------------------------------- RL 7955946007 SEM COMUNICAÇÃO FEITO PRIMEIRO ATAQUE-- | E84: 2026 | F84: MIRACEMA DO TOCANTINS | G84: 7955946007 | J84: 6800948007 | K84: LD05050008 | L84: REPASSAR DMSL | M84: 02/03/2026
C88: BASE COMPLETA — TODAS AS 34 SS COM DESCRIÇÃO
C89: Código da Solicitação | E89: Ano | F89: DataOcorrência | G89: LOCALIDADE | I89: TIPO_EQUIP | J89: NUM_EQUIPAMENTO | K89: NUM_OBRA | L89: Abrangencia | M89: Instalação | N89: Localização | O89: ANÁLISE TÉCNICA | P89: DescPrioridade | Q89: OSNumero | R89: POSSÍVEL REPETIÇÃO | S89: Descrição
C90: ETO-COEP 00054/2026 | D90: PARECER DMSL: PENDÊNCIA: Realizar melhoria no aterramento por ser tratar de um terreno muito arenoso, e há pendências por parte do time da proteção, os ajustes do RT não estão disponíveis para inserção no referido equipamento. DATA DA MANUTENÇÃO: 12/03/2026 EQUIPE: Brunno e Edeglan. *********************** PARECER DA PROTEÇÃO: FAVOR COMISSIONAR REGULADOR 5865120195 – LD Santa Maria Ramal Centenário e Recursolândia – 34,5kV. AJUSTE REALIZADO, DISPONÍVEL NO APP DA PROTEÇÃO. *********************** INSTALADO NA OBRA 0702400720 GENTILEZA, REALIZAR O COMISSIONAMENTO. LAUDO EM ANEXO. COORD EO: 889017, 9016857 | E90: 2026 | F90: 11/02/2026 15:21:44 | G90: CENTENARIO | I90: ATERRAMENTO | J90: 5865120195 | K90: 0702400720 | L90: 8800183195 | M90: LD01065015 | N90: 5865120195 | O90: REPASSAR DMSL | P90: ALTA | S90: =_xlfn.XLOOKUP(C90,'Dados Tratados'!A:A,'Dados Tratados'!C:C,"") -> PARECER DMSL: PENDÊNCIA: Realizar melhoria no aterramento por ser tratar de um terreno muito arenoso, e há pendências por parte do time da proteção, os ajustes do RT não estão disponíveis para inserção no referido equipamento. DATA DA MANUTENÇÃO: 12/03/202 EQUIPE: Brunno e Edeglan. *********************** PARECER DA PROTEÇÃO: FAVOR COMISSIONAR REGULADOR 5865120195 – LD Santa Maria Ramal Centenário e Recursolândia – 34,5kV. AJUSTE REALIZADO, DISPONÍVEL NO APP DA PROTEÇÃO. *********************** INSTALADO NA OBRA 0702400720 GENTILEZA, REALIZAR O COMISSIONAMENTO. LAUDO EM ANEXO. COORD EO: 889017, 9016857 | T90: Melhoria da malha de aterramento | U90: Repassado para ETO-RD-GR- Novo número é 00538/2026
C91: ETO-COEP 00002/2026 | D91: SEGUE SOLICITAÇÃO DE SERVIÇO PARA BANCO CAPACITOR COM CÉLULA DA FASE B QUEIMADA EQUIPE 047OP01 INFORMOU QUE JA FIZERAM TESTE E NÃO ACEITOU ID#81133777 RDU DE FIGUEIROPOLIS | E91: 2026 | F91: 06/01/2026 09:26:14 | G91: FIGUEIROPOLIS | I91: BANCO CAPACITOR | J91: 81133777 | L91: 0300697047 | M91: AL01033047 | N91: 5900038047 | O91: REPASSAR DMSL | P91: EMERGENCIAL | S91: =_xlfn.XLOOKUP(C91,'Dados Tratados'!A:A,'Dados Tratados'!C:C,"") -> SEGUE SOLICITAÇÃO DE SERVIÇO PARA BANCO CAPACITOR COM CÉLULA DA FASE B QUEIMADA EQUIPE 047OP01 INFORMOU QUE JA FIZERAM TESTE E NÃO ACEITOU ID#81133777 RDU DE FIGUEIROPOLIS
C92: ETO-COEP 00068/2026 | D92: PARECER DMSL: *FEEDBACK EQUIP. ESPECIAIS* *Nº DO EQUIPAMENTO:* 7929376022 *DATA DA MANUTENÇÃO:* 02/04/2026 *SID:* 1677/2026 *DESCRIÇÃO:* Trocar controle completo *PENDÊNCIA:* Sim. *DADOS DIVERGENTES DA PROGRAMAÇÃO:* Não *BATERIA SUBSTITUÍDA?:* Não *EQUIPE:* Adeilton e Edicleber __________________________________________________________ POR GENTILEZA ATENDER SOLICITAÇÃO PRIMEIRO ATAQUE IDENTIFICOU QUE RELE ESTA EM CURTO NOTA ABERTA 224/2026 FOI BAIXADA POREM NÃO FOI CORRIGIDO PROBLEMA EM CAMPO. | E92: 2026 | F92: 25/03/2026 14:38:13 | G92: BABACULANDIA | I92: CONTROLE | J92: 7929376022 | L92: 9001690022 | M92: LD05010004 | N92: 7929376022 | O92: REPASSAR DMSL | P92: EMERGENCIAL | S92: =_xlfn.XLOOKUP(C92,'Dados Tratados'!A:A,'Dados Tratados'!C:C,"") -> PARECER DMSL: *FEEDBACK EQUIP. ESPECIAIS* *Nº DO EQUIPAMENTO:* 7929376022 *DATA DA MANUTENÇÃO:* 02/04/2026 *SID:* 1677/2026 *DESCRIÇÃO:* Trocar controle completo *PENDÊNCIA:* Sim. *DADOS DIVERGENTES DA PROGRAMAÇÃO:* Não *BATERIA SUBSTITUÍDA?:* Não *EQUIPE:* Adeilton e Edicleber __________________________________________________________ POR GENTILEZA ATENDER SOLICITAÇÃO PRIMEIRO ATAQUE IDENTIFICOU QUE RELE ESTA EM CURTO NOTA ABERTA 224/2026 FOI BAIXADA POREM NÃO FOI CORRIGIDO PROBLEMA EM CAMPO.
C93: ETO-COEP 00055/2026 | D93: DCMD 26.03.2026. SS REPASSADA PARA COEP PROVIDENCIAR MATERIAL. NÃO TEMOS O MATERIAL EM ESTOQUE PARA SUBSTITUIÇÃO. COEP: Equipamento fornecido ao COCM-S para regularização. PARECER DA PROTEÇÃO: EQUIPAMENTOS FURTADOS. PARA AQUISIÇÃO DAS CELULAS DE REPOSIÇÃO, FAVOR CONSULTAR OS DADOS DE PLACA EM ANEXO. PARECER DA PROTEÇÃO: COMISISONAR RT 5856156091 LD DIANOPOLIS A NATIVIDADE. NECESSARIO REALIZAR MEDIÇÕES DA RESISTENCIA DA MALHA DE ATERRAMENTO. AJUSTES DISPONIVEIS NO APP DA PROTEÇÃO. RELIGADOR N° 5856156091 INSTALADO NA OBRA 0502400526 GENTILEZA, REALIZAR O COMISSIONAMENTO. LAUDO EM ANEXO. COORD EO: 899501, 8714782 | E93: 2026 | F93: 16/06/2025 15:50:51 | G93: ALMAS | I93: REGULADOR TENSÃO | J93: 5856156091 | K93: 0502400526 | L93: 8832258091 | M93: LD04002091 | N93: 5856156091 | O93: REPASSAR DMSL | P93: PROGRAMAVEL | S93: =_xlfn.XLOOKUP(C93,'Dados Tratados'!A:A,'Dados Tratados'!C:C,"") -> DCMD 26.03.2026. SS REPASSADA PARA COEP PROVIDENCIAR MATERIAL. NÃO TEMOS O MATERIAL EM ESTOQUE PARA SUBSTITUIÇÃO. COEP: Equipamento fornecido ao COCM-S para regularização. PARECER DA PROTEÇÃO: EQUIPAMENTOS FURTADOS. PARA AQUISIÇÃO DAS CELULAS DE REPOSIÇÃO, FAVOR CONSULTAR OS DADOS DE PLACA EM ANEXO. PARECER DA PROTEÇÃO: COMISISONAR RT 5856156091 LD DIANOPOLIS A NATIVIDADE. NECESSARIO REALIZAR MEDIÇÕES DA RESISTENCIA DA MALHA DE ATERRAMENTO. AJUSTES DISPONIVEIS NO APP DA PROTEÇÃO. RELIGADOR N° 5856156091 INSTALADO NA OBRA 0502400526 GENTILEZA, REALIZAR O COMISSIONAMENTO. LAUDO EM ANEXO. COORD EO: 899501, 8714782
C94: ETO-COEP 00112/2025 | D94: PARECER DMSL: Equipe esteve no RT 5856825025 dia 10/06/2025 porém não foi possível colocar o equipamento em operação devido defeito no controle. Favor, substituir controle e fornecer o rádio e centelhador para que seja possível colocar comunicação no equipamento. PARECER DA PROTEÇÃO: COMISSIONAR RT 5856825025 LD BERNARDO SAYÃO A ARAPOEMA. NECESSARIO CONFERIR MEDIÇÕES DA MALHA DE ATERRAMENTO. AJUSTES DISPONIVEIS NO APP DA PROTEÇÃO. REGULADOR DE TENSAO N° 5856825025 INSTALADO NA OBRA 0602400710 GENTILEZA, REALIZAR O COMISSIONAMENTO. LAUDO EM ANEXO. COORD EO: 719554, 9150284 | E94: 2025 | F94: 25/03/2025 08:35:38 | G94: ARAPOEMA | I94: REGULADOR TENSÃO | J94: 5856825025 | K94: 0602400710 | L94: 8837969025 | M94: LD02010153 | N94: 5856825025 | O94: REPASSAR DMSL | P94: ALTA | S94: =_xlfn.XLOOKUP(C94,'Dados Tratados'!A:A,'Dados Tratados'!C:C,"") -> PARECER DMSL: Equipe esteve no RT 5856825025 dia 10/06/2025 porém não foi possível colocar o equipamento em operação devido defeito no controle. Favor, substituir controle e fornecer o rádio e centelhador para que seja possível colocar comunicação no equipamento. PARECER DA PROTEÇÃO: COMISSIONAR RT 5856825025 LD BERNARDO SAYÃO A ARAPOEMA. NECESSARIO CONFERIR MEDIÇÕES DA MALHA DE ATERRAMENTO. AJUSTES DISPONIVEIS NO APP DA PROTEÇÃO. REGULADOR DE TENSAO N° 5856825025 INSTALADO NA OBRA 0602400710 GENTILEZA, REALIZAR O COMISSIONAMENTO. LAUDO EM ANEXO. COORD EO: 719554, 9150284
C95: ETO-COEP 00025/2026 | D95: COEP: equipamentos fornecidos. Repasse ao COCM para correção. PARACER DA PROTEÇÃO: Recebemos a solicitação de elaboração de ajustes do RT 5854681071, nota repassada pelo COEP. Duvidas: As pendencias apontadas pelo DMSL foram sanadas? Pois não registro descritivo na SS. Se foram sanadas, a SS não seguiu o fluxo norma, pois não há repassa da nota para o COEP. Podemos seguir com os estudos e comissionamento do ativo? PARECER DMSL: Equipe esteve no RT 5854681071 dia 18/02/2025 porém, as fases A e B estão com a ligação carga/fase invertidas, não contém antena, não contém suporte de antena e não contém rádio GE. Favor, sanar pendências para possibilitar o comissonamento. REGULADOR DE TENSAO N° 5854681071 INSTALADO NA OBRA 0302100570 GENTILEZA, REALIZAR O COMISSIONAMENTO. LAUDO EM ANEXO. COORD EO: 766351, 8781674 PARECER DA PROTEÇÃO ESTUDO DO EQUIPAMENTO DISPONIVEL NO APP DA PROTEÇÃO, NOTA REPASSADA PARA O DMSL COMISSIONAR O EQUIPAMENTO. TEC° EUZILAN MATEUS BARREIRA SANTOS | E95: 2026 | F95: 21/11/2024 14:32:44 | G95: BREJINHO DE NAZARE | I95: REGULADOR TENSÃO | J95: 5854681071 | K95: 0302100570 | L95: 9000001071 | M95: AL01018071 | N95: 5854681071 | O95: REPASSAR DMSL | P95: ALTA | S95: =_xlfn.XLOOKUP(C95,'Dados Tratados'!A:A,'Dados Tratados'!C:C,"") -> COEP: equipamentos fornecidos. Repasse ao COCM para correção. PARACER DA PROTEÇÃO: Recebemos a solicitação de elaboração de ajustes do RT 5854681071, nota repassada pelo COEP. Duvidas: As pendencias apontadas pelo DMSL foram sanadas? Pois não registro descritivo na SS. Se foram sanadas, a SS não seguiu o fluxo norma, pois não há repassa da nota para o COEP. Podemos seguir com os estudos e comissionamento do ativo? PARECER DMSL: Equipe esteve no RT 5854681071 dia 18/02/2025 porém, as fases A e B estão com a ligação carga/fase invertidas, não contém antena, não contém suporte de antena e não contém rádio GE. Favor, sanar pendências para possibilitar o comissonamento. REGULADOR DE TENSAO N° 5854681071 INSTALADO NA OBRA 0302100570 GENTILEZA, REALIZAR O COMISSIONAMENTO. LAUDO EM ANEXO. COORD EO: 766351, 8781674 PARECER DA PROTEÇÃO ESTUDO DO EQUIPAMENTO DISPONIVEL NO APP DA PROTEÇÃO, NOTA REPASSADA PARA O DMSL COMISSIONAR O EQUIPAMENTO. TEC° EUZILAN MATEUS BARREIRA SANTOS
C96: ETO-COEP 00217/2025 | D96: PARECER DMSL: Durante testes foi constatado que o controle apresenta defeito, impossibilitando a finalização do comissionamento. Favor, substituir controle RUA. "PARECER DA PROTEÇÃO: COMISSIONAR RT 5862546023 AL 01 COLINAS. NECESSARIO CONFERIR MEDIÇÕES DA MALHA DE ATERRAMENTO ANTES DE INSERIR O ATIVO NO SISTEMA. AJUSTES DISPONIVIEIS NO APP DA PROTEÇÃO. ************************************************************** REGULADOR N° 5862546023 INSTALADO NA OBRA 0702500104 GENTILEZA, REALIZAR O COMISSIONAMENTO. LAUDO EM ANEXO. COORD EO: 775889, 9112829" | E96: 2025 | F96: 04/11/2025 10:00:01 | G96: COLINAS DO TOCANTINS | I96: REGULADOR TENSÃO | J96: 5862546023 | K96: 0702500104 | L96: 8813300023 | M96: AL01020023 | N96: 5862546023 | O96: REPASSAR DMSL | P96: PROGRAMAVEL | S96: =_xlfn.XLOOKUP(C96,'Dados Tratados'!A:A,'Dados Tratados'!C:C,"") -> PARECER DMSL: Durante testes foi constatado que o controle apresenta defeito, impossibilitando a finalização do comissionamento. Favor, substituir controle RUA. "PARECER DA PROTEÇÃO: COMISSIONAR RT 5862546023 AL 01 COLINAS. NECESSARIO CONFERIR MEDIÇÕES DA MALHA DE ATERRAMENTO ANTES DE INSERIR O ATIVO NO SISTEMA. AJUSTES DISPONIVIEIS NO APP DA PROTEÇÃO. ************************************************************** REGULADOR N° 5862546023 INSTALADO NA OBRA 0702500104 GENTILEZA, REALIZAR O COMISSIONAMENTO. LAUDO EM ANEXO. COORD EO: 775889, 9112829"
C97: ETO-COEP 00066/2026 | D97: PARECER DMSL: *FEEDBACK EQUIP. ESPECIAIS* *Nº DO EQUIPAMENTO:* 5800291077 *DATA DA MANUTENÇÃO:* 07/04/2026 *SID:* 1709/2026 *DESCRIÇÃO:* Realizado ensaios nas células do banco 5800291077, identificado fase B em curto *FICOU EM OPERAÇÃO?:* Não *PENDÊNCIA:* SIM *EQUIPE:* Adeilton e Edicleber Realizar substituição da célula da fase B Em curto. _____________________________________________________________ Segue SS para enviar equipe do DMSL para no regulador de tensão 5800291077. O mesmo ficou bay passado devido esta com defeito e causar desarme na LD e penalizar a RDU de Goiatins. Por gentileza enviar equipe urgente. | E97: 2026 | F97: 03/04/2026 21:12:34 | G97: GOIATINS | I97: REGULADOR TENSÃO | J97: 5800291077 | L97: 8800288077 | M97: LD03105019 | N97: 5800291077 | O97: REPASSAR DMSL | P97: EMERGENCIAL | S97: =_xlfn.XLOOKUP(C97,'Dados Tratados'!A:A,'Dados Tratados'!C:C,"") -> PARECER DMSL: *FEEDBACK EQUIP. ESPECIAIS* *Nº DO EQUIPAMENTO:* 5800291077 *DATA DA MANUTENÇÃO:* 07/04/2026 *SID:* 1709/2026 *DESCRIÇÃO:* Realizado ensaios nas células do banco 5800291077, identificado fase B em curto *FICOU EM OPERAÇÃO?:* Não *PENDÊNCIA:* SIM *EQUIPE:* Adeilton e Edicleber Realizar substituição da célula da fase B Em curto. _____________________________________________________________ Segue SS para enviar equipe do DMSL para no regulador de tensão 5800291077. O mesmo ficou bay passado devido esta com defeito e causar desarme na LD e penalizar a RDU de Goiatins. Por gentileza enviar equipe urgente.
C98: ETO-COEP 00170/2025 | D98: PARECER DMSL: Malha de aterramento está dando 738, muito acima do aceitável para operação do RT. Necessário realizar melhoria na malha. PARECER DA PROTEÇÃO: COMISSIONAR RT 5863381155 LD COLINAS A B SAYAO E PALMEIRANTE. NECESSARIO CONFERIR MALHA DE ATERRAMENTO ANTES DE INSERIR O ATIVO NO SISTEMA. AJUSTES DISPONIVEIS NO APP DA PROTEÇÃO. REGULADOR N° 5863381155 INSTALADO NA OBRA 0702500302 GENTILEZA, REALIZAR O COMISSIONAMENTO. LAUDO EM ANEXO. COORD EO: 800396, 9107697 | E98: 2025 | F98: 03/07/2025 09:52:24 | G98: PALMEIRANTE | I98: REGULADOR TENSÃO | J98: 5863381155 | K98: 0702500302 | L98: 8800518155 | M98: LD01020023 | N98: 5863381155 | O98: REPASSAR DMSL | P98: ALTA | S98: =_xlfn.XLOOKUP(C98,'Dados Tratados'!A:A,'Dados Tratados'!C:C,"") -> PARECER DMSL: Malha de aterramento está dando 738, muito acima do aceitável para operação do RT. Necessário realizar melhoria na malha. PARECER DA PROTEÇÃO: COMISSIONAR RT 5863381155 LD COLINAS A B SAYAO E PALMEIRANTE. NECESSARIO CONFERIR MALHA DE ATERRAMENTO ANTES DE INSERIR O ATIVO NO SISTEMA. AJUSTES DISPONIVEIS NO APP DA PROTEÇÃO. REGULADOR N° 5863381155 INSTALADO NA OBRA 0702500302 GENTILEZA, REALIZAR O COMISSIONAMENTO. LAUDO EM ANEXO. COORD EO: 800396, 9107697
C99: ETO-COEP 00077/2026 | D99: PARECER DMSL: RT 5801866013 Serviço Executado: Feito a medição da malha de terra. Identificado infiltração na caixa de passagem da célula da fase C do banco regulador de tensão, será necessário fazer a substituição da mesma! Ficar atento na hora da substituição, deverá ser substituída a célula do lado da BR. Obs.: Será necessário baixar todo o banco pelo menos um metro, as buchas estão muito próximas a parte energizada não oferecem segurança para equipe no momento do ensaio elétrico. Equipamento ficou em operação?: Não Possui nobreak: Sim Possui antena: Sim Possui rádio:Sim Pendência: Sim Data da bateria: Equipe: Benvindo e Kaique. _______________________________________________ RT 5801866013 BY PASSADO DEVIDO DEFEITO EM CELULA BEMVINDO ESTEVE NO LOCAL JUNTO AO COD . NECESSARIO TRATATIVA PARA MESMA . FASE DANIFICADO C | E99: 2026 | F99: 02/03/2026 15:58:27 | G99: PARAISO DO TOCANTINS | I99: REGULADOR TENSÃO | J99: 5801866013 | L99: 9001891013 | M99: AL03062013 | N99: 5801866013 | O99: REPASSAR DMSL | P99: EMERGENCIAL | S99: =_xlfn.XLOOKUP(C99,'Dados Tratados'!A:A,'Dados Tratados'!C:C,"") -> PARECER DMSL: RT 5801866013 Serviço Executado: Feito a medição da malha de terra. Identificado infiltração na caixa de passagem da célula da fase C do banco regulador de tensão, será necessário fazer a substituição da mesma! Ficar atento na hora da substituição, deverá ser substituída a célula do lado da BR. Obs.: Será necessário baixar todo o banco pelo menos um metro, as buchas estão muito próximas a parte energizada não oferecem segurança para equipe no momento do ensaio elétrico. Equipamento ficou em operação?: Não Possui nobreak: Sim Possui antena: Sim Possui rádio:Sim Pendência: Sim Data da bateria: Equipe: Benvindo e Kaique. _______________________________________________ RT 5801866013 BY PASSADO DEVIDO DEFEITO EM CELULA BEMVINDO ESTEVE NO LOCAL JUNTO AO COD . NECESSARIO TRATATIVA PARA MESMA . FASE DANIFICADO C
C100: ETO-COEP 00198/2025 | D100: PARECER DA PROTEÇÃO: COMISSIONAR RT 5835587001 AL 03 PORTO NACIONAL. NECESSARIO CONFERIR MEDIÇÕES DA MALHA DE ATERRAMENTO ANTES DE INSERIR O ATIVO NO SISTEMA. AJUSTES DISPONIVIEIS NO APP DA PROTEÇÃO. ************************************************************** REGULADOR N° 5835587001 REMANEJADO NA OBRA 0302400526 GENTILEZA, REALIZAR O COMISSIONAMENTO. LAUDO EM ANEXO. COORD EO: 790054, 8821052 parecer dmsl: Data: 23/09/2025 SID: 3949 Serviço realizado: Será necessário substituir a célula da fase B do banco regulador de tensão! * Substituir a placa E * ¿Fazer melhoria na malha de terra do equipamento * ¿Não tem comunicação, necessário levar radio GE, antena com suporte e cabos. * ¿Quando retornar levar rele, nobreack e baterias novas. * ¿Tem que desenhar, desenvolver e testar com Scada. | E100: 2025 | F100: 09/09/2025 16:52:57 | G100: PORTO NACIONAL | I100: REGULADOR TENSÃO | J100: 5835587001 | K100: 0302400526 | L100: 3103141001 | M100: AL03072001 | N100: 5835587001 | O100: REPASSAR DMSL | P100: ALTA | S100: =_xlfn.XLOOKUP(C100,'Dados Tratados'!A:A,'Dados Tratados'!C:C,"") -> PARECER DA PROTEÇÃO: COMISSIONAR RT 5835587001 AL 03 PORTO NACIONAL. NECESSARIO CONFERIR MEDIÇÕES DA MALHA DE ATERRAMENTO ANTES DE INSERIR O ATIVO NO SISTEMA. AJUSTES DISPONIVIEIS NO APP DA PROTEÇÃO. ************************************************************** REGULADOR N° 5835587001 REMANEJADO NA OBRA 0302400526 GENTILEZA, REALIZAR O COMISSIONAMENTO. LAUDO EM ANEXO. COORD EO: 790054, 8821052 parecer dmsl: Data: 23/09/2025 SID: 3949 Serviço realizado: Será necessário substituir a célula da fase B do banco regulador de tensão! * Substituir a placa E * ¿Fazer melhoria na malha de terra do equipamento * ¿Não tem comunicação, necessário levar radio GE, antena com suporte e cabos. * ¿Quando retornar levar rele, nobreack e baterias novas. * ¿Tem que desenhar, desenvolver e testar com Scada.
C101: ETO-COEP 00152/2024 | D101: PARECER DMSL: FAVOR, INSTALAR POSTE DE 12 METROS AO LADO DO RELIGADOR 7955825037 PARA POSSIBILITAR O ESTABELECIMENTO DA COMUNICAÇÃO DO MESMO. RELIGADOR N° 7955825037 INSTALADO NA OBRA 0402300790 GENTILEZA, REALIZAR O COMISSIONAMENTO. LAUDO EM ANEXO. COORD EO: 719564, 8734324 PARECER DA PROTEÇÃO: AJUSTE DISPONIBILIZADO NO APP DA PROTEÇÃO, NOTA REPASSADA PARA DMSL COMISSIONAR, ID ORIGEM: 3320033037, PN 2024. ENG° IRLLEY CASTELO BRANCO | E101: 2024 | F101: 08/11/2024 08:29:21 | G101: ALIANCA DO TOCANTINS | I101: RELIGADOR | J101: 7955825037 | K101: 0402300790 | L101: 3320033037 | M101: LD03040003 | N101: 7955825037 | O101: REPASSAR DMSL | P101: ALTA | S101: =_xlfn.XLOOKUP(C101,'Dados Tratados'!A:A,'Dados Tratados'!C:C,"") -> PARECER DMSL: FAVOR, INSTALAR POSTE DE 12 METROS AO LADO DO RELIGADOR 7955825037 PARA POSSIBILITAR O ESTABELECIMENTO DA COMUNICAÇÃO DO MESMO. RELIGADOR N° 7955825037 INSTALADO NA OBRA 0402300790 GENTILEZA, REALIZAR O COMISSIONAMENTO. LAUDO EM ANEXO. COORD EO: 719564, 8734324 PARECER DA PROTEÇÃO: AJUSTE DISPONIBILIZADO NO APP DA PROTEÇÃO, NOTA REPASSADA PARA DMSL COMISSIONAR, ID ORIGEM: 3320033037, PN 2024. ENG° IRLLEY CASTELO BRANCO
C102: ETO-COEP 00125/2024 | D102: PARECER DMSL: EQUIPAMENTO 7955175004 FOI INSTALADO SEM O CABO UMBILICAL. FAVOR, SANAR A PENDÊNCIA PARA PROSSEGUIRMOS COM O COMISSIONAMETNO. RELIGADOR N° 7955175004 INSTALADO NA OBRA 0602300755 GENTILEZA, REALIZAR O COMISSIONAMENTO. LAUDO EM ANEXO. COORD EO: 808265, 9205592 PARECER DA PROTEÇÃO: AJUSTE DISPONIBILIZADO NO APP DA PROTEÇÃO, NOTA REPASSADA PARA DMSL COMISSIONAR, RL PN 2024 ID ORIGEM: COODR.7 POLO ARAGUAÍNA. ENG° IRLLEY CASTELO BRANCO. | E102: 2024 | F102: 10/09/2024 13:37:17 | G102: ARAGUAINA | I102: RELIGADOR | J102: 7955175004 | K102: 0602300755 | L102: 8855167004 | M102: AL02040004 | N102: 7955175004 | O102: REPASSAR DMSL | P102: ALTA | S102: =_xlfn.XLOOKUP(C102,'Dados Tratados'!A:A,'Dados Tratados'!C:C,"") -> PARECER DMSL: EQUIPAMENTO 7955175004 FOI INSTALADO SEM O CABO UMBILICAL. FAVOR, SANAR A PENDÊNCIA PARA PROSSEGUIRMOS COM O COMISSIONAMETNO. RELIGADOR N° 7955175004 INSTALADO NA OBRA 0602300755 GENTILEZA, REALIZAR O COMISSIONAMENTO. LAUDO EM ANEXO. COORD EO: 808265, 9205592 PARECER DA PROTEÇÃO: AJUSTE DISPONIBILIZADO NO APP DA PROTEÇÃO, NOTA REPASSADA PARA DMSL COMISSIONAR, RL PN 2024 ID ORIGEM: COODR.7 POLO ARAGUAÍNA. ENG° IRLLEY CASTELO BRANCO.
C103: ETO-COEP 00076/2026 | D103: PARECER DMSL: Realizar a substituição do transformador. (Furtado) Equipe: Adeilton e Edicleber SID 1874/2026 17/04/2026 ______________________________________ PARECER DMSL: Chamado de desenvolvimento 30484170 criado. Favor, programar comissionamento a partir do dia 20/02/26. POLOCOL PARECER DA PROTEÇÃO: Planilha com as informações anexada. É sugerido que sejam conferidas as medições da malha de aterramento do equipamento antes da sua inserção no sistema. Isso é fundamental para garantir a segurança e a eficiência do equipamento. Os ajustes estão disponíveis no APP da proteção. Estagiário Rafael Pereira Marques. _____________________ RELIGADOR N° 7962635060 INSTALADO NA OBRA 0602401143 GENTILEZA, REALIZAR O COMISSIONAMENTO. LAUDO EM ANEXO. COORD EO: 789405, 9172143 | E103: 2026 | F103: 22/12/2025 14:36:41 | G103: ARAGUAINA | I103: RELIGADOR | J103: 30484170 | K103: 0602401143 | L103: 3319797060 | M103: AL01054060 | N103: 7962635060 | O103: REPASSAR DMSL | P103: ALTA | S103: =_xlfn.XLOOKUP(C103,'Dados Tratados'!A:A,'Dados Tratados'!C:C,"") -> PARECER DMSL: Realizar a substituição do transformador. (Furtado) Equipe: Adeilton e Edicleber SID 1874/2026 17/04/2026 ______________________________________ PARECER DMSL: Chamado de desenvolvimento 30484170 criado. Favor, programar comissionamento a partir do dia 20/02/26. POLOCOL PARECER DA PROTEÇÃO: Planilha com as informações anexada. É sugerido que sejam conferidas as medições da malha de aterramento do equipamento antes da sua inserção no sistema. Isso é fundamental para garantir a segurança e a eficiência do equipamento. Os ajustes estão disponíveis no APP da proteção. Estagiário Rafael Pereira Marques. _____________________ RELIGADOR N° 7962635060 INSTALADO NA OBRA 0602401143 GENTILEZA, REALIZAR O COMISSIONAMENTO. LAUDO EM ANEXO. COORD EO: 789405, 9172143
C104: ETO-COEP 00060/2026 | D104: PARECER DMSL: Realizar substituição do equipamento todo e parte ativa. Equipe: Adeilton e Edicleber Data: 12/03 ----------------------------------------------------------------------------- Religador sem comunicação, apos primeiro ataque o mesmo não retornou as comunicação. | E104: 2026 | F104: 11/03/2026 18:20:05 | G104: ARAGUAINA | I104: RELIGADOR | L104: 9004017004 | M104: AL05010004 | N104: 7903569004 | O104: REPASSAR DMSL | P104: EMERGENCIAL | S104: =_xlfn.XLOOKUP(C104,'Dados Tratados'!A:A,'Dados Tratados'!C:C,"") -> PARECER DMSL: Realizar substituição do equipamento todo e parte ativa. Equipe: Adeilton e Edicleber Data: 12/03 ----------------------------------------------------------------------------- Religador sem comunicação, apos primeiro ataque o mesmo não retornou as comunicação.
C105: ETO-COEP 00157/2024 | D105: FAVOR RELIZAR MANUTENÇAO NO EQUIPAMENTO O MESMO ESTA COM FALTA DE ITENS NECESSARIOS PARA SE REALIZAR O COMISSIONAMENTO. RELIGADOR N° 7956117005 INSTALADO NA OBRA 0502300584 GENTILEZA, REALIZAR O COMISSIONAMENTO. LAUDO EM ANEXO. COORD EO: 939068, 8569277 PARECER DA PROTEÇÃO: FAVOR COMISSIONAR O RL 7956117005 AL 01 ARRAIAS - PN 2024. AJUSTES DIPONIVEIS NO APP DA PROTEÇÃO. PONTO ORIGEM PN 2024 - UTM: 939117;8569319 | E105: 2024 | F105: 11/11/2024 10:00:16 | G105: ARRAIAS | I105: RELIGADOR | J105: 7956117005 | K105: 0502300584 | L105: 0300056005 | M105: AL01013005 | N105: 7956117005 | O105: REPASSAR DMSL | P105: ALTA | S105: =_xlfn.XLOOKUP(C105,'Dados Tratados'!A:A,'Dados Tratados'!C:C,"") -> FAVOR RELIZAR MANUTENÇAO NO EQUIPAMENTO O MESMO ESTA COM FALTA DE ITENS NECESSARIOS PARA SE REALIZAR O COMISSIONAMENTO. RELIGADOR N° 7956117005 INSTALADO NA OBRA 0502300584 GENTILEZA, REALIZAR O COMISSIONAMENTO. LAUDO EM ANEXO. COORD EO: 939068, 8569277 PARECER DA PROTEÇÃO: FAVOR COMISSIONAR O RL 7956117005 AL 01 ARRAIAS - PN 2024. AJUSTES DIPONIVEIS NO APP DA PROTEÇÃO. PONTO ORIGEM PN 2024 - UTM: 939117;8569319
C106: ETO-COEP 00215/2025 | D106: RELIGADOR N° 7908196047 REMANEJADO NA OBRA 0402401150 GENTILEZA, REALIZAR O COMISSIONAMENTO. LAUDO EM ANEXO. COORD EO: 698485, 8657287 PARECER DA PROTEÇÃO: AJUSTE DISPONIBILIZADO NO APP DA PROTEÇÃO, NOTA REPASSADA PARA DMSL COMISSIONAR, POLO GURUPI, RL APENAS REMANEJADO DA REDE VELHA PARA REDE NOVA, EQUIPAMENTO COOPER, SE MANTEVE O MESMO NÚMERO DE ATIVO. ENG° IRLLEY CASTELO BRANCO. PARECER DMSL: Constatado curto-circuito no tanque do religador, impedindo as operações de abertura e fechamento do equipamento. Solicita-se a substituição completa do religador, incluindo tanque e unidade de controle. | E106: 2025 | F106: 29/09/2025 15:15:26 | G106: FIGUEIROPOLIS | I106: RELIGADOR | J106: 7908196047 | K106: 0402401150 | L106: 8859726047 | M106: AL02033047 | N106: 7908196047 | O106: ENTENDER COM DMSL | P106: ALTA | R106: REPETIDA | S106: =_xlfn.XLOOKUP(C106,'Dados Tratados'!A:A,'Dados Tratados'!C:C,"") -> RELIGADOR N° 7908196047 REMANEJADO NA OBRA 0402401150 GENTILEZA, REALIZAR O COMISSIONAMENTO. LAUDO EM ANEXO. COORD EO: 698485, 8657287 PARECER DA PROTEÇÃO: AJUSTE DISPONIBILIZADO NO APP DA PROTEÇÃO, NOTA REPASSADA PARA DMSL COMISSIONAR, POLO GURUPI, RL APENAS REMANEJADO DA REDE VELHA PARA REDE NOVA, EQUIPAMENTO COOPER, SE MANTEVE O MESMO NÚMERO DE ATIVO. ENG° IRLLEY CASTELO BRANCO. PARECER DMSL: Constatado curto-circuito no tanque do religador, impedindo as operações de abertura e fechamento do equipamento. Solicita-se a substituição completa do religador, incluindo tanque e unidade de controle. | T106: Depois
