Workbook

Sheet Gerencial
A1: DESTINO_SS | B1: (Vários itens) | F1: Criticidade | G1: Quantidade | I1: Total
G2: RL | H2: RT
A3: Qtd | B3: Cód | F3: Muito Alta | G3: 9 | H3: 2 | I3: =SUM(G3:H3) -> 11
A4: Criticidade | B4: 58 | C4: 79 | D4: Total Geral | F4: Alta | G4: 9 | H4: 3 | I4: =SUM(G4:H4) -> 12
A5: Muito Alta | B5: 3 | C5: 11 | D5: 14 | F5: Média | G5: 9 | H5: 4 | I5: =SUM(G5:H5) -> 13
A6: Alta | B6: 3 | C6: 6 | D6: 9 | F6: Baixa | G6: 9 | H6: 5 | I6: =SUM(G6:H6) -> 14
A7: Média | B7: 5 | C7: 10 | D7: 15 | F7: Em definição | G7: 28 | H7: 9 | I7: =SUM(G7:H7) -> 37
A8: Baixa | B8: 4 | C8: 11 | D8: 15 | F8: Total Geral | G8: 64 | H8: 23 | I8: =SUM(I3:I7) -> 87
A9: Em definição | C9: 2 | D9: 2
A10: Total Geral | B10: 15 | C10: 40 | D10: 55

Sheet Pendentes
A1: ANO_SS | B1: SS_ORIGINAL | C1: DESTINO_SS | D1: COD_RELIGADOR | E1: TIPO | F1: DTA_ABERTURA | G1: COD_LOC | H1: LOCALIDADE | I1: POLO | J1: REGIONAL | K1: ALIMENTADOR | L1: DESCRICAO | M1: Premissa 1 | N1: Premissa 2 | O1: Premissa 3 | P1: Premissa 4 | Q1: Premissa 5 | R1: Premissa 6 | S1: Premissa 7 | T1: Premissa 8 | U1: Priorização | V1: Criticidade | W1: Observação após análise
A2: 2026 | B2: ETO-RD-DP 00479/2026 | C2: ETO-RD-DP | D2: 5856070091 | E2: 58 | F2: 46230 | G2: 91 | H2: ALMAS | I2: DIANOPOLIS | J2: SUL | K2: LD04002091 | L2: PARECER DMSL: não foi regularizado a instalação do equipamento, nota repassada conforme alinhado com o supervisor.____________________________________________COCMS 26.03.26. SS REPASSADA PARA COEP PROVIDENCIAR MATERIAL. NÃO TEMOS AS PÇ EM ESTOQUE PARA FAZER A SUBSTITUIÇÃO. Solicitação de serviço para reposição de equipamentos furtados .COEP: Equipamento fornecido ao COCM-S para regularização.COCMS: Equipamento substituido conforme solicitado. Gentileza comissionar.PARECER DA PROTEÇÃO:SEGUE NOTA REPASSADA PARA DMSL COMISSIONAR.ENG° IRLLEY CASTELO BRANCOPARECER DMSL(23/09/2025): Feito a parte de comunicação, fechando enlace, configuração do rádio GE. Feito a medição de aterramento. Após uma inspeção, foi identificado que o regulador de tensão está instalado errado, carga está para o lado de fonte e fonte está do lado de carga. O certo é a fonte vim de almas, atualmente está vindo de natividade. Favor fazer a instalação correta. | M2: 40 | N2: 20 | O2: 20 | P2: 20 | Q2: 0 | R2: - | S2: - | T2: - | U2: 100 | V2: Muito Alta | W2: Atendimento da região da Engegold, Nativa, cidade Natividade e Chapada da Natividade
A3: 2026 | B3: ETO-PROT 00158/2026 | C3: ETO-PROT | D3: 5854566043 | E3: 58 | F3: 46231 | G3: 43 | H3: SILVANOPOLIS | I3: PORTO NACIONAL | J3: CENTRO | K3: LD02072001 | L3: 24/07/2026 - PARECE COCM: EQUIPAMENTO SUBSTITUIDO NA OBRA 0312600352 OS: ETO-RD-PO 1873/202622/07/2026 PARECER COEP: EQUIPAMENTO ENTREGUE AOS COCM´SPRAZO DE 7 DIAS CONTANDO O SLA.PARECER COEP: EQUIPAMENTO ENTREGUE AOS COCM´S FAVOR SUSBSTTUIR , E AGUARDO O PRAZO DE PREVISÃO DE SUBSTIUIÇÃOboa noite,segue SS para as devidas tratativas com equipe de manutenção com apoio de equipe de linha viva substituir regulador de tensão 5854566043 queimado célula fase c, LD Porto / Silvanópolis mesmo deverá ser substituído com apoio de equipe de linha viva PARECER DMSL: Foi realizado inspeção visual e ensaios de isolação, relação de transformação e resistência de enrolamento. A fase B está danificada e será necessário substituir a mesma. Malha de aterramento está relativamente boa e conectada. Fase A e C passaram nos ensaios. Substituir fase B. | M3: 40 | N3: 20 | O3: 20 | P3: 10 | Q3: 20 | R3: - | S3: - | T3: - | U3: 110 | V3: Muito Alta | W3: Aumento de reclamações no atendimento de Silvanópolis por Porto Nacional no período seco (Outra fonte com defeito também)
A4: 2026 | B4: ETO-COEP 00123/2026 | C4: ETO-COEP | D4: 7928564039 | E4: 79 | F4: 46210 | G4: 39 | H4: ARAGUATINS | I4: AUGUSTINOPOLIS | J4: NORTE | K4: LD02109039 | L4: PARECER COEP: EQUIPAMENTO SELECIONADO PARA COMPRATroca do sistema de comunicação do equipamentoDMSL 28/07/2025: Equipamento com tanque, modulo e rele com defeito, solicitar troca do equipamento ao DCMD.Fotos vão ser enviadas por e-mail | M4: 5 | N4: 10 | O4: 5 | P4: 0 | Q4: 0 | R4: 10 | S4: 0 | T4: 0 | U4: 30 | V4: Média | W4: Transferência entre 424R Araguatins e 434R Augustinópolis
A5: 2026 | B5: ETO-RD-DP 00409/2026 | C5: ETO-RD-DP | D5: 7908705049 | E5: 79 | F5: 46209 | G5: 49 | H5: AURORA DO TOCANTINS | I5: DIANOPOLIS | J5: SUL | K5: AL01015049 | L5: EQUIPAMENTO ENTREGUE, SOLICITO PREVISÃO PARA SUBSTITUIÇÃO:PARECER COEP: PREVISÃO DE ENTREGA AOS COCM'S 01/07Manutenção no RL 7908705049PARECER DMSL(28/08/2025): Equipe foi fazer manutenção no RL e constatou que o tanque e o relé do mesmo se encontra queimado, providenciar substituição.PARECER COCMS 30/04/2026CRIADO OBRA 0512600135 PARA REQUISIÇÃO MATERIAL | M5: 15 | N5: 20 | O5: 5 | P5: 15 | Q5: 15 | R5: 0 | S5: 10 | T5: 15 | U5: 95 | V5: Muito Alta | W5: Proteção da baixa do TF de força da SE Aurora
A6: 2026 | B6: ETO-COEP 00124/2026 | C6: ETO-COEP | D6: 7923673004 | E6: 79 | F6: 46210 | G6: 4 | H6: ARAGUAINA | I6: ARAGUAINA | J6: NORTE | K6: AL04010004 | L6: PARECER COEP: Verificar Disponibilidade de equipamento no Scada e enviar modelo e tensão para a compra.RELIGADOR COM RELÉ DANIFICADO, REALIZAR SUBSTITUIÇÃO | M6: 15 | N6: 20 | O6: 15 | P6: 15 | Q6: 15 | R6: 10 | S6: 0 | T6: 15 | U6: 105 | V6: Muito Alta | W6: Transferência de cargas na RDU de Araguaína (2797 UCs)
A7: 2026 | B7: ETO-COEP 00040/2026 | C7: ETO-COEP | D7: 7931608059 | E7: 79 | F7: 46077 | G7: 59 | H7: TAQUARALTO | I7: TAQUARALTO | J7: CENTRO | K7: AL05099059 | L7: PARECER COEP: EQUIPAMENTO SELECIONADO PARA COMPRADMSL:Serviço Executado: Foi feita uma análise técnica no equipamento, devido à falta de comunicação. Também foi identificado que o tanque do equipamento está danificado, sendo assim, necessário substituir o tanque e o rádio do equipamento, que está queimado, sendo necessário substituir também. | M7: 15 | N7: 20 | O7: 15 | P7: 15 | Q7: 15 | R7: 10 | S7: 0 | T7: 15 | U7: 105 | V7: Muito Alta | W7: Transferência dos bairros Morada do Sol, Vale do Sol, Morada do Sol II, Nova Esperança, Sõa João, Araras I e II e Jardim Laila em Taquaralto (6033 UCs)
A8: 2025 | B8: ETO-COEP 00184/2025 | C8: ETO-COEP | D8: 7903112004 | E8: 79 | F8: 45903 | G8: 4 | H8: ARAGUAINA | I8: ARAGUAINA | J8: NORTE | K8: LD05010004 | L8: 20/07 PARECER COEP: EQUIPAMENTO SELECIONADO PARA COMPRAApós testes no RLG 7903112004 foi constatado defeito no mesmo e como se trata de um modelo COOPER FORM6 que está obsoleto e não possuímos peças sobressalentes, faz-se necessária substituição completa por modelo NOJA RC10. | M8: 15 | N8: 10 | O8: 5 | P8: 15 | Q8: 0 | R8: 10 | S8: 0 | T8: 0 | U8: 55 | V8: Alta | W8: Transferência de Babaçulândia, 4 RLs sendo 2 operando
A9: 2026 | B9: ETO-COEP 00152/2026 | C9: ETO-COEP | D9: 7903569004 | E9: 79 | F9: 46223 | G9: 4 | H9: ARAGUAINA | I9: ARAGUAINA | J9: NORTE | K9: AL05010004 | L9: PARECER COEP 28/07/2026 : EQUIPAMENTO SELECIONADO PARA COMPRAEquipamento baypassado PARECER DMSL em 12/03: Realizar substituição do equipamento todo e parte ativa. | M9: 15 | N9: 20 | O9: 5 | P9: 15 | Q9: 15 | R9: 10 | S9: 0 | T9: 15 | U9: 95 | V9: Muito Alta | W9: Transferência dos bairros JD Santa Helena, Jd Filadelfiae Setor Caraja em Araguaína (2053 UCs), AL 254R de AR I e AL 214R de AR III
A10: 2026 | B10: ETO-COEP 00131/2026 | C10: ETO-COEP | D10: 7947203070 | E10: 79 | F10: 46211 | G10: 70 | H10: RIO SONO | I10: TAQUARALTO | J10: CENTRO | K10: LD02424015 | L10: 13/07 PARECER COEP: SELECIONADO PARA COMPRA CONTROLE favor verificar RL 7947203070, sem comunicaçao, feito 1° ataque pela equipe 070OP01 e nao retornou a comunicaçao , linformaçao no Scada de bateria.PARECER DMSL: Foi feito análise técnica, a placa do equipamento está queimada nessesario subistituir o equipamento completo -Carliel e Benvindo-05/02 | M10: 10 | N10: 20 | O10: 15 | P10: 15 | Q10: 15 | R10: 10 | S10: 0 | T10: 15 | U10: 100 | V10: Muito Alta | W10: Transferência da RDU de Lizarda (1650 UCs) para fonte alternativa
A11: 2026 | B11: ETO-TELE 01040/2026 | C11: ETO-TELE | D11: 5800371025 | E11: 58 | F11: 46233 | G11: 25 | H11: ARAPOEMA | I11: COLINAS DO TOCANTINS | J11: NORTE | K11: LD02010153 | L11: 16/07/2026 PARECER COEP: ALINHADO COM O KELLITON REALIZAR SUBSTITUIÇÃO DO CONTROLE DE TUPIRAMA, ALINHADO COM O JEAN QUE OS CABOS COMPATIBILIZADORES VÃO CHEGAR 16/08 , ATÉ ESSA DATA MANTER ESSA SS E CONTROLE RUA, DEPOIS REPASSAR PARA O DMSLPARECER COEP: AVALIAR COM O LEANDRO, PROVAVELMENTE SÓ COMPRAPARECER DMSL: Após testes foi constatado defeito nos relés da fase A e B, Modelo Toshiba TBR 1000. Se possível, substituir os relés das 3 fases por controle RUA, disponibilizar os cabos de ligação entre o tanque e o controle para possibilitar a compatibilização do equipamento. Fornecer kit de comunicação, rádio, antena, etc.Segue nota para veriifcar falha em regulador de tensão N: 5800371025 dentro S/E Arapoema , equipamento esta com 2 reles com falha marca toshiba .Parecer DCMD: foi substituido célula 30/07/2026. o mesmo está liberado para ser colocado em operação | M11: 0 | N11: 20 | O11: 20 | P11: 10 | Q11: 20 | R11: - | S11: - | T11: - | U11: 70 | V11: Alta | W11: Aumento de reclamações no atendimento de Arapoema no período seco
A12: 2026 | B12: ETO-COEP 00156/2026 | C12: ETO-COEP | D12: 5855411017 | E12: 58 | F12: 46227 | G12: 17 | H12: BARROLANDIA | I12: MIRACEMA DO TOCANTINS | J12: CENTRO | K12: AL02017017 | L12: 20/07 PARECER COCM: NÃO RECEBEMOS MATERIAL10/07 PARECER COEP: EQUIPAMENTO ENTREGUE AOS COCM´S FAVOR INFORMAR PRAZO DE SUBSTUIÇÃO PARA O DMSL E REPASSAR DEPOIS PARA PROTEÇÃO REALIZAR OS AJUSTES E DESCREVER NA SS O SERVIÇO REALIZADOPARECER COEP: EQUIPAMENTO EM ROTA DE ENTREGASEM COMUNICAÇÃO, FALHA DE ALIMENTAÇÃO - REALIZADO PRIMEIRO ATAQUE SEM SUCESSO.PARECER DMSL: 17/09/2025 Equipamento ficou em operação? Não Pendência: sim. Equipamento ficou Bay passado levar controle COMPLETO para trocar. ellisfran | M12: 0 | N12: 0 | O12: 0 | P12: 10 | Q12: 20 | R12: - | S12: - | T12: - | U12: 30 | V12: Baixa | W12: Atendimento do Assentamento Irmã Adelaide
A13: 2026 | B13: ETO-COEP 00059/2026 | C13: ETO-COEP | D13: 7925744087 | E13: 79 | F13: 46111 | G13: 87 | H13: GOIANORTE | I13: GUARAI | J13: NORTE | K13: LD02022033 | L13: PARECER COEP: EQUIPAMENTO SELECIONADO PARA COMPRAPARECER DMSL: FEEDBACK EQUIP. ESPECIAISNº DO EQUIPAMENTO: 7925744087TIPO EQUIPAMENTO: Noja RC 10TIPO DE COMUNICAÇÃO: Radio GE IPDATA DA MANUTENÇÃO: 19/02/2026SID: 735/2026 DESCRIÇÃO: foi identificado água dentro da parte interna do tanque e cabo umbilical encharcado de água foi passado essas informações para COS.FICOU EM OPERAÇÃO?: Não PENDÊNCIA: Sim substituir tanque e cabo umbilicalDADOS DIVERGENTES DA PROGRAMAÇÃO: NãoBATERIA SUBSTITUÍDA?: Não DATA DA BATERIA: 07/05/2025TIPO DE BATERIA: Lítio EQUIPE: Edeglan e Janio-------------------------------------------------------------------------------------------------RELIGADOR SEM COMUNICAÇÃO, APOS PRIMEIRO ATAQUE RETORNA E FICAR INDEFINIDO. | M13: 15 | N13: 20 | O13: 5 | P13: 15 | Q13: 15 | R13: 10 | S13: 0 | T13: 15 | U13: 95 | V13: Muito Alta | W13: Transferência de Goianorte, fonte principal operando
A14: 2026 | B14: ETO-COEP 00168/2026 | C14: ETO-COEP | D14: 7908196047 | E14: 79 | F14: 46237 | G14: 47 | H14: FIGUEIROPOLIS | I14: FORMOSO DO ARAGUAIA | J14: SUL | K14: AL02033047 | L14: 03/08/2026 PARECER DMSL: FOI CONFIRMADO PELO VONES DO DCMD QUE O EQUIPAMENTO AINDA NÃO FOI SUBSTITUÍDO. FAVOR, APÓS SUBSTITUIÇÃO, REPASSAR A NOTA PARA A PROTEÇÃO PARA REVISAR OS AJUSTES, POIS TRATA-SE DE ALTERAÇÃO DO MODELO DO EQUIPAMENTO.13/07/2026 PARECER COEP: EQUIPAMENTO REMANEJADO FAVOR FAZER O COMISSIONAMENTORELIGADOR N° 7908196047 REMANEJADO NA OBRA 0402401150 GENTILEZA, REALIZAR O COMISSIONAMENTO. LAUDO EM ANEXO. COORD EO: 698485, 8657287PARECER DA PROTEÇÃO:AJUSTE DISPONIBILIZADO NO APP DA PROTEÇÃO, NOTA REPASSADA PARA DMSL COMISSIONAR, POLO GURUPI, RL APENAS REMANEJADO DA REDE VELHA PARA REDE NOVA, EQUIPAMENTO COOPER, SE MANTEVE O MESMO NÚMERO DE ATIVO.ENG° IRLLEY CASTELO BRANCO.PARECER DMSL: Constatado curto-circuito no tanque do religador, impedindo as operações de abertura e fechamento do equipamento. Solicita-se a substituição completa do religador, incluindo tanque e unidade de controle. | M14: 5 | N14: 5 | O14: 5 | P14: 0 | Q14: 0 | R14: 0 | S14: 10 | T14: 0 | U14: 25 | V14: Baixa | W14: Seccionamento do Rural e energização do 224R
A15: 2026 | B15: ETO-PROT 00154/2026 | C15: ETO-PROT | D15: 7900117013 | E15: 79 | F15: 46224 | G15: 13 | H15: PARAISO DO TOCANTINS | I15: PARAISO DO TOCANTINS | J15: CENTRO | K15: AL01062013 | L15: 15/07 PARECER COCM: EQUIPAMENTO FOI SUBSTITUÍDO OBRA 021260042210/07 PARECER COEP: EQUIPAMENTO ENTREGUE AOS COCM´S FAVOR INFORMAR PRAZO DE SUBSTUIÇÃO PARA O DMSL E REPASSAR DEPOIS PARA PROTEÇÃO REALIZAR OS AJUSTES E DESCREVER NA SS O SERVIÇO REALIZADOPARECER COEP: PREVISÃO DE ENTREGA AOS COCM'S 01/07Segue nota para correção de anomalia e provável substituição de religador , religador 7900117013 -RDU - Paraiso .OBS: equipe DMSL Elisfran estava atualizando firmware no equipamento , porém relé parou de funcionar devido essa atualização , sendo necessário sua substituição .em campo o modelo e cooper Form6 , segundo tecnico deve ser substituído por um Noja .Repassado para o COEP para aquisição do equipamento e posterior repasse para o COCM. | M15: 15 | N15: 20 | O15: 15 | P15: 15 | Q15: 15 | R15: 0 | S15: 0 | T15: 15 | U15: 95 | V15: Muito Alta | W15: Transferência do 214R de Paraíso I, Centro Comercial de Paraíso
A16: 2026 | B16: ETO-PROT 00153/2026 | C16: ETO-PROT | D16: 7900573047 | E16: 79 | F16: 46223 | G16: 47 | H16: FIGUEIROPOLIS | I16: FORMOSO DO ARAGUAIA | J16: SUL | K16: AL02033047 | L16: 10/07 PARECER COEP: EQUIPAMENTO ENTREGUE AOS COCM´S FAVOR INFORMAR PRAZO DE SUBSTUIÇÃO PARA O DMSL E REPASSAR DEPOIS PARA PROTEÇÃO REALIZAR OS AJUSTES E DESCREVER NA SS O SERVIÇO REALIZADOPARECER COEP: AGUARDANDO COCM'S GERAREM AS OBRAS PARA PODER ENTREGAR MATERIALFavor providenciar manutenção no RL 7900573047, o mesmo estar em curto conforme fotos anexadas. Equipamento ficou bay passado em campo.PARECER DMSL: Equipe: FABIO AP./JOÃO MARCOSData Executada: 15/10/2025Serviço Executado:Foi constatado que o equipamento esta queimado na parte ativa placa, tanque e relé. Por favor fazer a substituição pelo Noja RC10. | M16: 5 | N16: 5 | O16: 15 | P16: 0 | Q16: 15 | R16: 10 | S16: 0 | T16: 15 | U16: 65 | V16: Alta | W16: Transferência da Bunge, Saneatins e secadora
A17: 2026 | B17: ETO-TELE 01107/2026 | C17: ETO-TELE | D17: 7929376022 | E17: 79 | F17: 46247 | G17: 22 | H17: BABACULANDIA | I17: ARAGUAINA | J17: NORTE | K17: LD05010004 | L17: 13/08/2026 PARECER COEP: EQUIPAMENTO FOI TROCADO A PEÇA , CONFIRMAMOS COM O LEONARDO DE ARAGUAÍNA , LAUDO EM ANEXO , FAVOR REALIZAR COMISSIONAMENTOPARECER COEP: PROBLEMA NO ENVIO COCM'S CONTROLE ENVIADO FOI O NOJA , DEVIDO A FALTA DO MODELO NA SS (GRAVE)PARECER DMSL: *FEEDBACK EQUIP. ESPECIAIS**Nº DO EQUIPAMENTO:* 7929376022 *DATA DA MANUTENÇÃO:* 02/04/2026*SID:* 1677/2026*DESCRIÇÃO:* Trocar controle completo*PENDÊNCIA:* Sim.*DADOS DIVERGENTES DA PROGRAMAÇÃO:* Não*BATERIA SUBSTITUÍDA?:* Não*EQUIPE:* Adeilton e Edicleber __________________________________________________________POR GENTILEZA ATENDER SOLICITAÇÃO PRIMEIRO ATAQUE IDENTIFICOU QUE RELE ESTA EM CURTO NOTA ABERTA 224/2026 FOI BAIXADA POREM NÃO FOI CORRIGIDO PROBLEMA EM CAMPO. | M17: 15 | N17: 20 | O17: 5 | P17: 15 | Q17: 15 | R17: 10 | S17: 0 | T17: 15 | U17: 95 | V17: Muito Alta | W17: Transferência de Babaçulândia, fonte principal operando
A18: 2025 | B18: ETO-COEP 00221/2025 | C18: ETO-COEP | D18: 5800961074 | E18: 58 | F18: 45996 | G18: 74 | H18: DIANOPOLIS | I18: DIANOPOLIS | J18: SUL | K18: LD03028074 | L18: PARECER COEP: EQUIPAMENTO SELECIONADO PARA COMPRASubstituir as 3 células- Melhoria na malha de aterramento - Melhoria no circuito de aterramento qua aterra as células.- Substituir conectores paralelos | M18: 20 | N18: 0 | O18: 0 | P18: 20 | Q18: 0 | R18: - | S18: - | T18: - | U18: 40 | V18: Média | W18: Atendimento da COELBA e GA Alessandro Maurício (1600 kVA)
A19: 2026 | B19: ETO-SE-PCM 00092/2026 | C19: ETO-SE-PCM | D19: 7933726256 | E19: 79 | F19: 46251 | G19: 256 | H19: MATEIROS | I19: PONTE ALTA TOCANTINS | J19: CENTRO | K19: LD03046026 | L19: 17/08/2026 PARECER DA PROTEÇÃO:NOTA REPASSADA PARA DMSL COMISSIONARENG° IRLLEY CASTELO BRANCO07/07 Equipamento foi substituido na OS: ETO-RD-PO 1859/2026 OBRA 031260035101/07 PARECER COEP: REDIRECIONADO PARA O POSTO DO COCM´S EQUIPAMENTO CHEGOU NO LOCAL, FAVOR ENTRAR EM CONTATO COM O DMSL, DEVIDO A URGÊNCIA DO EQUIPAMENTO EM OPERAÇÃO.30/06 PARECER COEP: DEVIDO A ALINHAMENTO COM COI UTILIZAREMOS PARTE ATIVA QUE ORIGINALMENTE FOI ENCOMENDADA PARA 7933726256PARECER DMSL: N° do Equipamento: _RLG 7933726256 MateirosTipo de Equipamento: _RLG NOJA RC 10 REL IIData: _06/05/2026SID: _2288/2026-Serviço Executado: _Equipamento com defeito na parte ativa, será necessário fazer a substituição da parte ativa e fazer melhoria na malha de terra!Equipamento ficou em operação?: _NaoPendência: _SimBateria(s) substituída(s)? NÃOData Fabricação/Instalação da(s) bateria(s):_06/2025Equipe: _Benvindo e Almir-------------------------------------------------------------------------------Religador 7933726256, sem comunicação apos primeiroa ataque não retornou as comunicação. | M19: 15 | N19: 10 | O19: 15 | P19: 15 | Q19: 15 | R19: 10 | S19: 0 | T19: 15 | U19: 95 | V19: Muito Alta | W19: Transferência da cidade de Mateiros (733 UCs) para o gerador
A20: 2026 | B20: ETO-COEP 00024/2026 | C20: ETO-COEP | D20: 7933585074 | E20: 79 | F20: 46049 | G20: 74 | H20: DIANOPOLIS | I20: DIANOPOLIS | J20: SUL | K20: LD03028074 | L20: 30/06 PARECER COEP: EQUIPAMENTO SELECIONADO PARA COMPRAREALIZAR SUBSTITUIÇÃO DO TANQUE, O MESMO ESTÁ COM DEFEITO. | M20: 5 | N20: 5 | O20: 15 | P20: 0 | Q20: 0 | R20: 0 | S20: 10 | T20: 0 | U20: 35 | V20: Média | W20: Atendimento da COELBA
A21: 2026 | B21: ETO-SE-PA 00107/2026 | C21: ETO-SE-PA | D21: 7900594026 | E21: 79 | F21: 46219 | G21: 26 | H21: PONTE ALTA TOCANTINS | I21: PONTE ALTA TOCANTINS | J21: CENTRO | K21: LD03046026 | L21: PARECER DA PROTEÇÃO:16/07/2026 AJUSTES DISPONIBILIZADOS NO APP DA PROTEÇÃO15/07/2026 EQUIPAMENTO SUBSTITUIDO NA OS ETO-RD-PO 1860 OBRA 031260035414/07/2026 PARECER COCM/ COEP: DE ACORDO COM O EDSON CURCINO FOI FEITA S SUBSTITUIÇÃO DO EQUIPAMENTO , SEGUE PARA PROTEÇÃO ELABORAR AJUSTE10/07 PARECER COEP: EQUIPAMENTO DESLOCADO QUE ESTAVA EM GUARAÍ FOI ALINHADO COM O VALMOR QUE SERIA SUBSTITUIDO DIA 07/07/2026 , FAVOR PASSAR PARA PROTEÇÃO 7900594026PARECER COEP: AGUARDANDO COCM'S PARA ABRIR REQUISIÇÃOPARECER DMSL 10/06/2026: Tem uma nota aberta para esse equipamento solicitando a substituição desde 20/10/2025, como a nota não foi atendida estamos repassando para área responsável. Nota em aberto repassada ETO-COEP 210/2025.Segue nota para verificar intermitência de comunicação nos religadores 7908301026 , 7911120026, 7947959026 , 7908692026, 7900594026 rural- Ponte Alta . | M21: 15 | N21: 20 | O21: 15 | P21: 15 | Q21: 15 | R21: 0 | S21: 0 | T21: 15 | U21: 95 | V21: Muito Alta | W21: Religador responsável pela proteção da barra da SE Ponte Alta (2381 UCs)
A22: 2026 | B22: ETO-COEP 00151/2026 | C22: ETO-COEP | D22: 5840227063 | E22: 58 | F22: 46223 | G22: 63 | H22: BANDEIRANTES DO TOCANTINS | I22: COLINAS DO TOCANTINS | J22: NORTE | K22: LD01054060 | L22: PARECER COEP 27/07/2026 : EM PROCESSO DE AQUISIÇÃOPARECER DMSL 13/07/2026: Realizados ensaios de isolação nas três células, e foi identificado curto na fase A, sendo necessário a sua substituição. Os cabos das buchas ficaram desconectados para melhor identificação no momento da sua substituiçãSEGUE PARA O DMSL AVALIAR ANTES DE SEGUIRMOS COM O SERVIÇOSEGUE PARA REALIZAR TROCA---------------------------------------------------------Boa noite,Segue SS para tratativas regulador de tensão 5840227063 fase C em curto | M22: 0 | N22: 20 | O22: 20 | P22: 10 | Q22: 10 | R22: - | S22: - | T22: - | U22: 60 | V22: Média | W22: Atendimento da RDU Bandeirantes e clientes rurais
A23: 2026 | B23: ETO-COEP 00061/2026 | C23: ETO-COEP | D23: 7901110084 | E23: 79 | F23: 46112 | G23: 84 | H23: DIVINOPOLIS | I23: DIVINOPOLIS | J23: CENTRO | K23: LD04062013 | L23: PARECER COEP: EQUIPAMENTO SELECIONADO PARA COMPRAPARECER DMSL: Serviço Executado: Foi feito análise técnica, testes funcionais e identificado que a parte ativa do equipamento está com defeito. Necessário substituir a parte ativa.FICOU EM OPERAÇÃO? Não- EQUIPE: Carliel e BenvindoSegue SS para verificaçao Rl esta danificado dando passagem de tensão mesmo aberto Sim, quando retornar trazer uma fonte pois a mesma foi removida. | M23: 5 | N23: 5 | O23: 0 | P23: 0 | Q23: 0 | R23: 0 | S23: 10 | T23: 0 | U23: 20 | V23: Baixa | W23: Localizado na fonte principal de atendimento de Divinópolis e Abreulândia
A24: 2026 | B24: ETO-COEP 00133/2026 | C24: ETO-COEP | D24: 7955986084 | E24: 79 | F24: 46211 | G24: 84 | H24: DIVINOPOLIS | I24: DIVINOPOLIS | J24: CENTRO | K24: LD04062013 | L24: 14/07/2026 PARECER COEP : SUBSTIUIR CONTROLE COMPLETOPARECER DMSL: Equipamento com a placa de alimentação ca em curto, será necessário substituir a placa do equipamento. (Antiga nota era pra ter sido repassada porém foi baixada indevidamente pela equipe) | M24: 5 | N24: 5 | O24: 0 | P24: 0 | Q24: 15 | R24: 10 | S24: 0 | T24: 0 | U24: 35 | V24: Média | W24: Transferência de cargas do 444R da SE Paraíso I
A25: 2026 | B25: ETO-COEP 00141/2026 | C25: ETO-COEP | D25: 7927413001 | E25: 79 | F25: 46216 | G25: 1 | H25: PORTO NACIONAL | I25: PORTO NACIONAL | J25: CENTRO | K25: LD01072001 | L25: 22/07/2026 EQUIPAMENTO SLEECIONADO PARA COMPRAPARECER DMSL: *Segue feedback**Equipamento:* RLG 7927413001 *RELÉ TAVRIDA*Data:* 16/04/2026*SID:* 1817/2026*Serviço executado:* Placa de alimentação do equipamento com defeito, VERIFICAR SE É POSSIVEL substituir o equipamento completo.*Equipamento ficou em operação?*_Não*Pendência:*_Sim*Bateria(s) substituída(s)?*_Nao *Equipe:* Benvindo e Kaique-------------------------------------------------------------------------------------------------Religador 7927413001 sem comunicação foi realizado primeiro ataque porem a comunicação não retornou. Favor enviar equipe para devidas trattivas | M25: 15 | N25: 5 | O25: 15 | P25: 15 | Q25: 15 | R25: 10 | S25: 0 | T25: 15 | U25: 90 | V25: Muito Alta | W25: Transferência do Distrito Ind de Porto Nacional e GAs
A26: 2026 | B26: ETO-PROT 00159/2026 | C26: ETO-PROT | D26: 7908686014 | E26: 79 | F26: 46231 | G26: 14 | H26: PIUM | I26: PARAISO DO TOCANTINS | J26: CENTRO | K26: LD02025012 | L26: 24/07 PARECER COCM: EQUIPAMENTO FOI SUBSTITUIDO OBRA 021260042510/07 PARECER COEP: EQUIPAMENTO ENTREGUE AOS COCM´S FAVOR INFORMAR PRAZO DE SUBSTUIÇÃO PARA O DMSL E REPASSAR DEPOIS PARA PROTEÇÃO REALIZAR OS AJUSTES E DESCREVER NA SS O SERVIÇO REALIZADO06/07 PARECER COEP: PREVISÃO DE ENTREGA DE ACORDO COM CALENDÁRIO LOGISITCO NOVO 06/07NOTA DMSL: Favor substituir o tanque, ele não está efetuando os comandos enviados. Não substituir o controle pois o mesmo funciona como repetidor de outros equipamentos.Segue nota para verificar falha de fechamento religador 7908686014- Pium .OBS: equipamento não fechou local e remoto , fica sinalizando no painel para verificar alarmes ! | M26: 15 | N26: 20 | O26: 0 | P26: 15 | Q26: 15 | R26: 10 | S26: 0 | T26: 15 | U26: 90 | V26: Muito Alta | W26: Fonte principal de Pium, RL de transferência operando
A27: 2026 | B27: ETO-SE-PCM 00091/2026 | C27: ETO-SE-PCM | D27: 5865120195 | E27: 58 | F27: 46251 | G27: 195 | H27: CENTENARIO | I27: GUARAI | J27: NORTE | K27: LD01065015 | L27: PARECER DMSL:PENDÊNCIA: Realizar melhoria no aterramento por ser tratar de um terreno muito arenoso, e há pendências por parte do time da proteção, os ajustes do RT não estão disponíveis para inserção no referido equipamento.DATA DA MANUTENÇÃO: 12/03/202EQUIPE: Brunno e Edeglan.***********************PARECER DA PROTEÇÃO - 17/08/2026:FAVOR COMISSIONAR REGULADOR 5865120195 – LD Santa Maria Ramal Centenário e Recursolândia – 34,5kV. AJUSTE REALIZADO, DISPONÍVEL NO APP DA PROTEÇÃO.*********************** INSTALADO NA OBRA 0702400720 GENTILEZA, REALIZAR O COMISSIONAMENTO.LAUDO EM ANEXO.COORD EO: 889017, 901685708-07-2026 PARECER: FOI FEITO A MELHORIA NO REGULADOR CONFORME FOTOS EM ANEXO. | M27: 20 | N27: 20 | O27: 20 | P27: 10 | Q27: 0 | R27: - | S27: - | T27: - | U27: 70 | V27: Alta | W27: Atendimento das RDUs de Centenário, Recursolândia e clientes rurais
A28: 2026 | B28: ETO-COEP 00169/2026 | C28: ETO-COEP | D28: 5800440256 | E28: 58 | F28: 46240 | G28: 256 | H28: MATEIROS | I28: PONTE ALTA TOCANTINS | J28: CENTRO | K28: LD03046026 | L28: PARECER DMSL 06/08: Substituir célula da Fase B do banco de Regulador de tensão e realizar melhorias na malha de aterramento do ReguladorBoa noite,Segue SS para as devidas tratativas, verificar flutuação de tensão do regulador 5800440256 pois a tensão está oscilando de 16kv a 23kv favor verificar esta anomalia pois cliente BRK está abrindo reclamação todas as noites. | M28: 20 | N28: 20 | O28: 20 | P28: 10 | Q28: 20 | R28: - | S28: - | T28: - | U28: 90 | V28: Muito Alta | W28: Aumento de reclamações no atendimento de São Felix e Mateiros no período seco
A29: 2026 | B29: ETO-TELE 00896/2026 | C29: ETO-TELE | D29: 7943790134 | E29: 79 | F29: 46183 | G29: 134 | H29: ESPERANTINA | I29: AUGUSTINOPOLIS | J29: NORTE | K29: LD02109039 | L29: PARECER DCMD:Serviço realizado , substituição da parte ativa do RELIGADOR 7943790134 - Favor realizar comissionamento | M29: 15 | N29: 10 | O29: 5 | P29: 15 | Q29: 15 | R29: 10 | S29: 0 | T29: 15 | U29: 85 | V29: Muito Alta | W29: Transferência de Esperantina, fonte principal operando
A30: 2026 | B30: ETO-COEP 00045/2026 | C30: ETO-COEP | D30: 7927396052 | E30: 79 | F30: 46083 | G30: 52 | H30: FORMOSO DO ARAGUAIA | I30: FORMOSO DO ARAGUAIA | J30: SUL | K30: LD03036052 | L30: PARECER COEP: EQUIPAMENTO SELECIONADO PARA COMPRAreligador foi bay passado devido mesmo esta saindo fumaca do painel e sem comunicação 7927396052.PARECER DMSL: Após testes, equipe DMSL constatou que apenas o tanque do RLG 7927396052 encontra-se queimado. Favor, substituir parte ativa do equipamento.NS Tanque: 0320123040198 | M30: 5 | N30: 5 | O30: 0 | P30: 0 | Q30: 15 | R30: 10 | S30: 0 | T30: 0 | U30: 35 | V30: Média | W30: Equipamento localizado Fonte principal de atendimento a SE Cobrape
A31: 2026 | B31: ETO-COEP 00087/2026 | C31: ETO-COEP | D31: 7900453110 | E31: 79 | F31: 46139 | G31: 110 | H31: SANTA RITA DO TOCANTINS | I31: PORTO NACIONAL | J31: CENTRO | K31: LD03040003 | L31: 10/07/2026 EQUIPAMENTO SELECIONADO PARA COMPRA PARTE ATIVA30/06.PARECER COEP: ALINHADO COM O ALLAN REMANEJAMOS PARTE ATIVA PARA ATENDER 7933726256PARECER COEP: Aproveitar controle cooper se possível em outro local, previsão de chegada do material dia 01/07 para substituiçãoFavor verificar o RL 7900453110, pois o mesmo aceita comando de fechamento, porém fecha em campo e no SCADA continua aberto e só abre através de equipe em campo. Parecer Dmsl:Equipamento está com defeito na parte ativa, não aceita o comando de fechamento. Será necessário substituir o equipamento completo.Equipamento ficou em operação?: _SIM_a pedido do COS ficou em operação, a operação está ciente da necessidade de substituir.Pendência: Sim, será necessário substituir o equipamento. | M31: 15 | N31: 10 | O31: 5 | P31: 15 | Q31: 15 | R31: 10 | S31: 0 | T31: 15 | U31: 85 | V31: Muito Alta | W31: Transferência de Santa Rita, fonte principal operando
A32: 2026 | B32: ETO-COEP 00048/2026 | C32: ETO-COEP | D32: 7925871077 | E32: 79 | F32: 46097 | G32: 77 | H32: GOIATINS | I32: ARAGUAINA | J32: NORTE | K32: LD03105019 | L32: 27/07 PARECER COEP: EM PROCESSO DE AQUISIÇÃOPARECER DMSL: A PEDIDO DA PCM DO NORTE LARA SOARES REALIZEI A CRIAÇÃO DESSA SS, EM RAZAO DA ANTIGAETO-TELE 337/2026 QUE FOI BAIXADA POR ENGANO DE TAL FORMA SEGUE A MESMA PARA REALIZAR AS TRATATIVAS. PENDENCIA: Religador continua by passado, equipamento está com defeito na parte ativa | M32: 15 | N32: 10 | O32: 15 | P32: 15 | Q32: 15 | R32: 10 | S32: 0 | T32: 0 | U32: 80 | V32: Muito Alta | W32: Transferência de Goiatins e GAs (2492 UCs)
A33: 2026 | B33: ETO-COEP 00063/2026 | C33: ETO-COEP | D33: 7944559149 | E33: 79 | F33: 46112 | G33: 149 | H33: CASEARA | I33: DIVINOPOLIS | J33: CENTRO | K33: LD01434149 | L33: 14/07/2026 PARECER COEP: EQUIPAMENTO SELECIONADO PARA COMPRA Equipamento ficou em operação?: NãoPendência: Sim será necessário substituir a placaServiço Executado: curto na placa foi tentando recuperar a mesma porém não teve sucesso!Bateria(s)substituída(s)? NÃOEquipe: Kaique e benvido | M33: 5 | N33: 10 | O33: 0 | P33: 0 | Q33: 15 | R33: 10 | S33: 0 | T33: 0 | U33: 40 | V33: Média | W33: Atendimento de cargas rurais entre Caseara e Araguacema (221 UCs)
A34: 2026 | B34: ETO-COEP 00149/2026 | C34: ETO-COEP | D34: 5803327001 | E34: 58 | F34: 46223 | G34: 1 | H34: PORTO NACIONAL | I34: PORTO NACIONAL | J34: CENTRO | K34: AL01102271 | L34: 01/07 PARECER COEP: FOI CONFIRMADO COM A OPERAÇÃO QUE O EQUIPAMENTO SEGUIU O FLUXO INTEIRO DE COMISSIONAMENTO, PROTEÇÃO, FAVOR EXPLICAR O QUE FOI REALIZADO E SE EQUIPAMENTO ESTÁ OPERANDO, SENÃO ESTIVER EXPLICAR O QUE FOI FEITO NELE30/06PARECER COEP: REPASSAR DIRETAMENTE PARA OS COCM'SRegulador 5803327001 fora de operação, by passado em campo com painel de comunicação com cabos desconectados tensão 13.8.parecer DMSL: Feedback Equip. EspeciaisRT 5803327001RELÉ RUASid: 4844Data: 19/09/2025Serviço realizado:*Equipamento foi remanejado, 7 km da sua localização sentido Palmas necessário comissionamento completo*Equipamento com um dos cabos umbilicais danificado.* aterramento bucha FC não esta interligada corretamente * para-raios estão no mesmo aterramento da bucha FC.* Tranques muito alto e próximo da rede não permitindo o comissionamento com segurança.* Controle alto demais tem que baixar Equipamento ficou em operação?: nãoPendência: sim, precisa comissionar completoOBS | M34: 40 | N34: 0 | O34: 0 | P34: 20 | Q34: 20 | R34: - | S34: - | T34: - | U34: 80 | V34: Alta | W34: Em caso de perca da fonte principal é necessário esse RT para alimentação da Frísia
A35: 2026 | B35: ETO-SE-PCM 00090/2026 | C35: ETO-SE-PCM | D35: 7900230155 | E35: 79 | F35: 46251 | G35: 155 | H35: PALMEIRANTE | I35: COLINAS DO TOCANTINS | J35: NORTE | K35: LD02105019 | L35: PARECER DA PROTEÇÃO - 17/08/2026:SEGUE NOTA PARA COMISSIONAMENTO JUNTO COM TIME SCADA, EQUIPAMENTO JA NO DESENHO ADMS.ENG° IRLLEY CASTELO BRANCO07/07/2026 PARECER COEP: MATERIAL ENVIADO , CONFORME ALINHANDO COM O WANDER REALIZAR SUBSTIUIÇÂO DO EQUIPAMENTO, FAVOR ESCREVER PARECER COCM ANTES DE PASSAR PARA PROTEÇÂO, DO QUE FOI REALIZADO01/07/2026 PARECER COEP: PROBLEMA NO ENVIO DO MATERIAL PARECER DMSL: Religador está com o tanque danificado. Não responde a comandos abertura e fechamento local ou remoto, pois está com sinal de curto circuito. Necessário trocar o equipamento. Para raio do trafo está queimado. Chave de saída da fase C está com o olhal quebrado, necessário substituir a chave. Equipamento ficou bypassado em campo. Aberto entrada e saída, com exceção da fase C de saída que ficou fechada. Favor, substituir equipamento completo por NOJA RC10 e sanar demais pendencias.Senhores Favor verificar RL 7900230155 o mesmo sinalizou aberto no SCADA porem a cidade de Palmeirante estava normal , feito um reset no rl e o mesmo subiu fechado.08/07/2026 PARECER DCMD: EQUIPE ETO-LVGR01 DE GUARAI ESTEVE NO RL 7900230155 DIA 25-06-2026 E FEZ TODAS A PENDENCIAS DO RL, OBS: EQUIPE SO NAO CONECTOU O CABO DO TRAFO NO RL. RL ESTA PRONTO PARA O COMISSIONAMENTO | M35: 15 | N35: 20 | O35: 5 | P35: 15 | Q35: 0 | R35: 10 | S35: 0 | T35: 15 | U35: 80 | V35: Muito Alta | W35: Fonte principal de Palmeirante, RL de transferência operando
A36: 2026 | B36: ETO-COEP 00114/2026 | C36: ETO-COEP | D36: 7913662076 | E36: 79 | F36: 46183 | G36: 76 | H36: DUERE | I36: GURUPI | J36: SUL | K36: AL01031076 | L36: 27/07 PARECER COEP: TANQUE DANIFICADO DA 13,5Aberto nota para substituir tanque danificado e chave de entrada fase B danificadaPARECER DMSL: Foi confirmado pela equipe DMSL o defeito do tanque, favor seguir com a substituição e correção da chave de entrada fase B danificada. | M36: 5 | N36: 5 | O36: 0 | P36: 0 | Q36: 0 | R36: 10 | S36: 0 | T36: 0 | U36: 20 | V36: Baixa | W36: Atendimento do Ramal do Bacuri (168 UCs)
A37: 2026 | B37: ETO-PROT 00165/2026 | C37: ETO-PROT | D37: 7908708116 | E37: 79 | F37: 46246 | G37: 116 | H37: CHAPADA DA NATIVIDADE | I37: DIANOPOLIS | J37: SUL | K37: LD04002091 | L37: COCMS: 12/08/2026PART ATIVA DO RELIGADOR FOI SUBSTITUIDA.GENTILEZA COMISSIONAR EQUIPAMENTO. SUBSTITUIR PARTE ATIVA DO RELIGADOR 7908708116. LV. ABRIR JUNTE DE ENTRADA E SAIDA DO RELIGADOR PARA POSSIBILITAR SUBSTITUIÇÃO DO MESMO. | M37: 5 | N37: 5 | O37: 0 | P37: 0 | Q37: 0 | R37: 0 | S37: 10 | T37: 0 | U37: 20 | V37: Baixa | W37: Atendimento do PA Xobo (194 UCs)
A38: 2026 | B38: ETO-COEP 00078/2026 | C38: ETO-COEP | D38: 7926089013 | E38: 79 | F38: 46135 | G38: 13 | H38: PARAISO DO TOCANTINS | I38: PARAISO DO TOCANTINS | J38: CENTRO | K38: LD03062013 | L38: PARECER COEP: EQUIPAMENTO SELECIONADO PARA COMPRAPARECER DMSL: Feedback Equip. EspeciaisRLG 7926089013,RELÉ NOJA RC10SID 1805/2026DATA 15/04/2026Serviço Executado: Favor realizar a troca da parte ativa do equipamento --reprogramar para atualizar a base juntamente com escada Equipamento ficou em operação: Não Pendência: sim atualizar a base e subistituir o tanque Bateria(s) substituída(s)? Não Data de Fabricação/Instalação da(s) bateria(s): Equipe: Carliel e João Vitor Fernando e Elson---------------------------------------------------------------------------------ATUALIZAR AJUSTES DO RL 7926089013 LD PARAISO I A PIUM. IMPLEMENTAÇÃO DA FUNÇÃO 27, SUBTENSÃO.AJUSTES DISPONIVEIS NO APP DA PROTEÇÃO. | M38: 15 | N38: 10 | O38: 5 | P38: 15 | Q38: 15 | R38: 10 | S38: 0 | T38: 0 | U38: 70 | V38: Alta | W38: Transferência da RDU de Chapada de Areia (937 UCs) para fonte alternativa
A39: 2026 | B39: ETO-PROT 00152/2026 | C39: ETO-PROT | D39: 7925087021 | E39: 79 | F39: 46223 | G39: 21 | H39: PARANA | I39: PEIXE | J39: SUL | K39: LD01010021 | L39: 10/07 PARECER COEP: EQUIPAMENTO ENTREGUE AOS COCM´S FAVOR INFORMAR PRAZO DE SUBSTUIÇÃO PARA O DMSL E REPASSAR DEPOIS PARA PROTEÇÃO REALIZAR OS AJUSTES E DESCREVER NA SS O SERVIÇO REALIZADOPARECER COEP: EM ROTA DE ENTREGA, VERIFICAR PREVISÃO DE CHEGADARealizar a substituição do tanque do equipamento. | M39: 15 | N39: 10 | O39: 5 | P39: 0 | Q39: 15 | R39: 10 | S39: 0 | T39: 15 | U39: 70 | V39: Alta | W39: Primeiro RL do 414R de Paranã, RL a jusante na LD também está bay-passado (630 UCs)
A40: 2026 | B40: ETO-PROT 00151/2026 | C40: ETO-PROT | D40: 5801866013 | E40: 58 | F40: 46220 | G40: 13 | H40: PARAISO DO TOCANTINS | I40: PARAISO DO TOCANTINS | J40: CENTRO | K40: AL03062013 | L40: 15/07 PARECER COCM, FOI ATENDIDA PELA OS ETO-RD-PS 1616/2026 OBRA-021260053910/07 PARECER COEP: EQUIPAMENTO ENTREGUE AOS COCM´S FAVOR INFORMAR PRAZO DE SUBSTUIÇÃO PARA O DMSL E REPASSAR DEPOIS PARA PROTEÇÃO REALIZAR OS AJUSTES E DESCREVER NA SS O SERVIÇO REALIZADOPARECER COEP: EM PROCESSO DE ENTREGAPARECER DMSL: RT 5801866013Serviço Executado: Feito a medição da malha de terra. Identificado infiltração na caixa de passagem da célula da fase C do banco regulador de tensão, será necessário fazer a substituição da mesma! Ficar atento na hora da substituição, deverá ser substituída a célula do lado da BR.Obs.: Será necessário baixar todo o banco pelo menos um metro, as buchas estão muito próximas a parte energizada não oferecem segurança para equipe no momento do ensaio elétrico.Equipamento ficou em operação?: Não Possui nobreak: SimPossui antena: SimPossui rádio:SimPendência: SimData da bateria: Equipe: Benvindo e Kaique._______________________________________________RT 5801866013BY PASSADO DEVIDO DEFEITO EM CELULA BEMVINDO ESTEVE NO LOCAL JUNTO AO COD .NECESSARIO TRATATIVA PARA MESMA .FASE DANIFICADO C | M40: 0 | N40: 20 | O40: 20 | P40: 20 | Q40: 10 | R40: - | S40: - | T40: - | U40: 70 | V40: Alta | W40: Atendimento da RDU Luzimangues Industrial por fonte alternativa
A41: 2026 | B41: ETO-COEP 00154/2026 | C41: ETO-COEP | D41: 7910027196 | E41: 79 | F41: 46225 | G41: 196 | H41: LAGOA DO TOCANTINS | I41: TAQUARALTO | J41: CENTRO | K41: LD02059122 | L41: 13/07/2026 PARECER COEP: NÃO FAZ SENTIDO FAZER A TROCA DE EQUIPAMENTO COMPLETO APENAS POR CAUSA DA FASE B , QUE PARECE SER UM ERRO DE CALIBRAÇÃO.PARECER DMSL: EQUIPAMENTO FICOU EM OPERACAO, RESTABELCIDO PELA KAROL ação remota com a velp porém ele também deve ser realizado substituição por conta da fase B 7910027196 ta com a leitura incorreta na tensão da fase B. Subsituição do Equipamento Completo exceto o Radio. (Antiga nota era pra ter sido repassada porém foi baixada indevidamente pela equipe)PARECER DMSL(22/07/26): O religador está fora de operação desde 11/2025. Necessitando substituição completa em função do defeito de leitura de corrente da fase B. Preservar apenas o radio e antena. | M41: 5 | N41: 5 | O41: 0 | P41: 0 | Q41: 0 | R41: 0 | S41: 10 | T41: 0 | U41: 20 | V41: Baixa | W41: Atendimento do Ramal do Rio Preto (197 UCs)
A42: 2025 | B42: ETO-RD-PS 00323/2025 | C42: ETO-RD-PS | D42: 5853360007 | E42: 58 | F42: 45946 | G42: 7 | H42: MIRACEMA DO TOCANTINS | I42: MIRACEMA DO TOCANTINS | J42: CENTRO | K42: LD05050008 | L42: REALIZAR TESTES NO EQUIPAMENTO E CONFERIR MEDIÇÕES DA MALHA DE ATERRAMENTO. ESTANDO OK, COMISSIONAR EQUIPAMENTO E COLOCA-LO EM OPERAÇÃO.AJUSTES DISPONIVEIS NO APP DA PROTEÇÃdmsl : N° do Equipamento:*RT 5853360007 MIRACEMASID: 2493/2025Data: 13/05/2025Serviço Executado Provavelmente ocorreu uma descarga no equipamento comprometendo a malha!Será necessário fazer melhoria da malha de aterramento, fazer toda interligação da mesma! Feito ensaios de isolação das 3 células do equipamento, isolação está ok, quando retornar para colocar em operação levar 3 baterias de 7a.Equipamento ficou em operação?: Não Equipe: Benvindo e Jardel | M42: 0 | N42: 20 | O42: 20 | P42: 10 | Q42: 20 | R42: - | S42: - | T42: - | U42: 70 | V42: Alta | W42: Aumento de reclamações no atendimento de Miracema no período seco
A43: 2026 | B43: ETO-PROT 00157/2026 | C43: ETO-PROT | D43: 7953610256 | E43: 79 | F43: 46231 | G43: 256 | H43: MATEIROS | I43: PONTE ALTA TOCANTINS | J43: CENTRO | K43: LD03046026 | L43: 24/07/2026 - PARECE COCM: EQUIPAMENTO SUBSTIUIDO NA OS:ETO-RD-PO 2020/202614/07/2026 - PARECER COEP: REALOCAR TANQUE 34,5 SOBRESSALENTE DE PARAÍSO PARA ATENDER PARECER DMSL: Data: 10/03/2026,Serviço Executado: Foi substituído o relé do equipamento, o mesmo estava danificado. Trocado o DPS, o mesmo estava queimado devido ao tanque estar furado. O equipamento ficou em bypass.Equipamento ficou em operação? NãoPendência? Sim, substituir a parte ativa com cordão umbilical.Equipe: Carliel e João VitorSEGUE SS PARA REGULARIZAR AUTOMAÇÃO DO RL 7953610256 NA INTERLIGAÇÃO COM A COELBA (CHAPADA DA MANGABEIRA) - EQUIPE INFOMOU CURTO INTERNO NO GABINETE DJ AC NÃO FECHA | M43: 5 | N43: 5 | O43: 15 | P43: 15 | Q43: 0 | R43: 0 | S43: 10 | T43: 15 | U43: 65 | V43: Alta | W43: Atenidmento da COELBA (Alto potencial de compensação)
A44: 2026 | B44: ETO-COEP 00134/2026 | C44: ETO-COEP | D44: 7955946007 | E44: 79 | F44: 46211 | G44: 7 | H44: MIRACEMA DO TOCANTINS | I44: MIRACEMA DO TOCANTINS | J44: CENTRO | K44: LD05050008 | L44: 13/07/2026 PARECER COEP: SUBSTITUIR CONTOLE OU MANDAR MANUTENCIONAR EM CASO DE PRIORIDADE ALTAPARECER DMSL: Necessário substituir a placa de alimentação ca, a mesma está em curto não conseguimos recuperar. (Antiga nota era pra ter sido repassada porém foi baixada indevidamente pela equipe) | M44: 5 | N44: 5 | O44: 5 | P44: 0 | Q44: 0 | R44: 0 | S44: 10 | T44: 0 | U44: 25 | V44: Baixa | W44: Alimentação do serviço auxiliar da Investco e clientes rurais (260 UCs)
A45: 2026 | B45: ETO-TELE 00986/2026 | C45: ETO-TELE | D45: 5846328094 | E45: 58 | F45: 46211 | G45: 94 | H45: PEIXE | I45: PEIXE | J45: SUL | K45: LD04040003 | L45: COCM SUL - 07/07/2026 - FOI REALIZADO MELHORIA DE ATERRAMENTO E FEITO A MANUTENÇÕES E TODAS AS CHAVES E SUBSTITUIDO OS CONECTORES.PARECER COEP: MELHORIA DE ATERRAMENTO É COCM'S, FAVOR ENCAMINHAR DIRETAMENTE PARA ELES, COCM'S REALIZAR MELHORIA DE ATERRAMENTO POR FAVORPor genteliiza verificar RT 5846328094 situação de equipamento, se encontra by passado em campoPARECER DMSL:Favor, realizar melhoria de aterramento que se encontra alta e substituir todos os conectores das buchas por conectores estrangulador. | M45: 0 | N45: 20 | O45: 20 | P45: 10 | Q45: 10 | R45: - | S45: - | T45: - | U45: 60 | V45: Média | W45: Atendimento da RDU Sucupira e clientes rurais
A46: 2026 | B46: ETO-TELE 01102/2026 | C46: ETO-TELE | D46: 5844630060 | E46: 58 | F46: 46246 | G46: 60 | H46: NOVA OLINDA | I46: COLINAS DO TOCANTINS | J46: NORTE | K46: AL01054060 | L46: Segue nota para verificar falha em comandos via supervisório e constantes travamento no regulador de tensão 5844630060 - rural- Nova Olinda .Foi executado comandos no relé via supervisório, porém sem sucesso , em campo o equipamento está com a fase B travada no -16 .Obs: equipamento ficou fora de operação bay passado , favor agilizar atendimento ! | M46: 20 | N46: 0 | O46: 0 | P46: 10 | Q46: 0 | R46: - | S46: - | T46: - | U46: 30 | V46: Baixa | W46: Atendimento dos ramais PA Remansão e Água Branca
A47: 2025 | B47: ETO-COEP 00120/2025 | C47: ETO-COEP | D47: 7920024127 | E47: 79 | F47: 45839 | G47: 127 | H47: PALMEIRAS DO TOCANTINS | I47: TOCANTINOPOLIS | J47: NORTE | K47: LD01084002 | L47: 30/06 PARECER COEP: AGUARDANDO O RETORNO DO DMSL , PARA ENTENDER SE O PROBLEMA É NA COMUNICAÇÃO OU PARTE ATIVA, JÁ QUE O EQUIPAMENTO EM QUESTÃO SEGUE COMUNICANDOPARECER DMSL: Após testes, equipe DMSL constatou que o relé e a parte ativa do equipamento 7920024127 estão com defeito, sendo necessária a substituição completa por um modelo NOJA RC 10. Favor, subsituir também a chave de saída da fase A que está com o anel de abertura quebrado.RL 7920024127 está desarmando em campo e no SCADA continua fechado, só sinaliza aberto no SCADA quando a equipe faz o resert no equipamento em campo. | M47: 15 | N47: 10 | O47: 5 | P47: 15 | Q47: 0 | R47: 10 | S47: 0 | T47: 0 | U47: 55 | V47: Alta | W47: Transferência de Palmeiras, 3 fontes operando
A48: 2026 | B48: ETO-COEP 00148/2026 | C48: ETO-COEP | D48: 7923927122 | E48: 79 | F48: 46219 | G48: 122 | H48: PALMAS | I48: PALMAS | J48: CENTRO | K48: LD02059122 | L48: PARECER DMSL 16/07: Nota solicitada ao DMSL com a informação de que o tanque precisa ser substituído. Estou encaminhando a nota para a área responsável.Segue nota para envia manutenção substituir tanque do RL-7923927122 em curto, Anomalia identificada desarme das LD, s Palmas / Aparecida e Palmas Taquaruçu, Acesso livre, Tensão 34,5kv, Local RL de Interligação entre 424R / 414R. | M48: 15 | N48: 0 | O48: 0 | P48: 0 | Q48: 0 | R48: 10 | S48: 0 | T48: 0 | U48: 25 | V48: Baixa | W48: Transferência entre 414R e 424R SE Palmas II
A49: 2026 | B49: ETO-COEP 00029/2026 | C49: ETO-COEP | D49: 7927646026 | E49: 79 | F49: 46057 | G49: 26 | H49: PONTE ALTA TOCANTINS | I49: PONTE ALTA TOCANTINS | J49: CENTRO | K49: LD03046026 | L49: PARECER COEP: EQUIPAMENTO SELECIONADO PARA COMPRARELIGADOR BY PASSADO POR DEFEITO, NECESSÁRIO AVALIAÇÃO DO PROBLEMA.parecer dmsl:O religador apresenta defeito no tanque, sendo necessário substituir o tanque o mesmo está tirando a linha, e troca os isoladores. Quando retornar, trazer uma fonte para o equipamento, a mesma foi removida.FICOU EM OPERAÇÃO? NãoPENDÊNCIA: Sim, aguardando peças para substituição. | M49: 15 | N49: 10 | O49: 5 | P49: 0 | Q49: 15 | R49: 0 | S49: 10 | T49: 0 | U49: 55 | V49: Alta | W49: Opção de isolação de São Félix e Mateiros para alimentação por gerador
A50: 2026 | B50: ETO-PROT 00156/2026 | C50: ETO-PROT | D50: 7927169001 | E50: 79 | F50: 46224 | G50: 1 | H50: PORTO NACIONAL | I50: PORTO NACIONAL | J50: CENTRO | K50: AL01102271 | L50: PARECER COEP: EQUIPAMENTO ENTREGUE, SEGUE SS PARA O COCM´S , PARA REALIZAR O ATENDIMENTO,FAVOR ADICIONAR O PARECER PARA MANDAR PARA PROTEÇÃOSS ANTIGA: 1500/2025 PARECER DMSL: Serviço Executado: Foi verificado que o tanque do equipamento está danificado, sendo necessário substituir o tanque do equipamento.Equipamento ficou em operação?: NãoPendência: Sim, instalar fonte, disjuntor e DPS, e substituir o tanque.***** Parecer COCM******Subsituido Tranque do RL pela Ordem de Serviço DLP-MPPA01 247/2026 RELATORIO EM ANEXO DA O.S EXECUTORA | M50: 5 | N50: 5 | O50: 15 | P50: 0 | Q50: 15 | R50: 0 | S50: 0 | T50: 15 | U50: 55 | V50: Alta | W50: Transferência dos Grupos A - VLI e Frisia
A51: 2026 | B51: ETO-COEP 00150/2026 | C51: ETO-COEP | D51: 7930428001 | E51: 79 | F51: 46223 | G51: 1 | H51: PORTO NACIONAL | I51: PORTO NACIONAL | J51: CENTRO | K51: LD01100001 | L51: PARECER DMSL DATA 16/07/2026: será necessário fazer a substituição da parte ativa do equipamento.PARECER COEP: Equipamento Funcionando no SCADA , favor reavaliar a necessidade de substituição e se necessário mandar o modelo do equipamento.Segue nota para substituir Taque do RL-7930428001 na LD Porto Nacional / São João, Identificado pela Int-20253617520441 equipamento dando passagem na fase A ficou bay-passado até substituição, Tensão 34,5kva, Acesso livre. | M51: 5 | N51: 5 | O51: 15 | P51: 0 | Q51: 15 | R51: 10 | S51: 0 | T51: 0 | U51: 50 | V51: Alta | W51: Transferência dos Grupos A - Ramal do Rossato (TF 225kVA e TF 750kVA)
A52: 2026 | B52: ETO-PROT 00164/2026 | C52: ETO-PROT | D52: 5827102054 | E52: 58 | F52: 46245 | G52: 54 | H52: PUGMIL | I52: PARAISO DO TOCANTINS | J52: CENTRO | K52: LD01062013 | L52: PARECER COCM: FOI SUBSTITUÍDO OS EQUIPAMENTO FEITO A MELHORIA DO ATERRAMENTO ATENDIDO PELA OBRA N-0212600609PARECER COEP:NÃO É POSSÍVEL RETORNAR COM O CONTROLE COMPLETO , MAS DARIA PARA FAZER A MELHORIA NA MALHA DE ATERRAMENTO , ENCAMINHANDO PARA OS COCM'S PARA REALIZAREM A MELHORIAparecer DMSL: :Nobreack com defeito, rele queimado, cabo de comunicação entre o rádio e o rele danificado, malha de aterramento está com a resistência alta!Feito reparo no cabo, substituído nobreack, e rele. Se possível retornar com controle completo pq o q está em campo teve infiltração de água, abrir chamado no scada para atualizar base do equipamento pois o mesmo está com a base antiga, fazer correção da malha de aterramento.Equipamento ficou em operação?: Não Pendência: sim, levar controle novo, fazer correção da malha de terra, levar suporte para fixar antena. OBS | M52: 0 | N52: 20 | O52: 20 | P52: 10 | Q52: 0 | R52: - | S52: - | T52: - | U52: 50 | V52: Média | W52: Aumento de reclamações no atendimento de Pugmil no período seco
A53: 2025 | B53: ETO-COEP 00173/2025 | C53: ETO-COEP | D53: 7900535058 | E53: 79 | F53: 45894 | G53: 58 | H53: SANTA FE DO ARAGUAIA | I53: ARAGUAINA | J53: NORTE | K53: LD03010004 | L53: PARECER COEP: EQUIPAMENTO SELECIONADO PARA COMPRAPARECER DMSL: Equipamento 7900535058 encontra-se com o relé danificado, firmware corrompido, o mesmo não inicia. Devido ao fato de não possuirmos mais peças de reposição para religador cooper, se faz necessário a substituição de todo conjunto por um Noja RC10.envar equipe para verificar rlo 7900535058 foi feito primeiro ataque com equipe 040op36 o mesmo esta com RELE TRAVADO E FICOU FORA DE OPERAÇÃO, ATENDE RDR DE SANTA FÉ SAIDA DA CIDADEEQUIPE INFORMOU ABELHAS NA CAIXA DO PAINEL DE COMANDO | M53: 5 | N53: 10 | O53: 5 | P53: 0 | Q53: 15 | R53: 10 | S53: 0 | T53: 0 | U53: 45 | V53: Média | W53: Atendimento 3 povoados, na perca 4 ficam fora (900 UCs)
A54: 2026 | B54: ETO-COEP 00058/2026 | C54: ETO-COEP | D54: 7925733015 | E54: 79 | F54: 46111 | G54: 15 | H54: PEDRO AFONSO | I54: GUARAI | J54: NORTE | K54: LD01414015 | L54: PARECER COEP: EQUIPAMENTO SELECIONADO PARA COMPRAPARECER DMSL: FEEDBACK EQUIP. ESPECIAISNº DO EQUIPAMENTO: 7925733015TIPO EQUIPAMENTO: Noja RC10TIPO DE COMUNICAÇÃO: Rádio GEDATA DA MANUTENÇÃO: 24/03/2026SID: 1475/2026DESCRIÇÃO: Tanque do equipamento em CurtoFICOU EM OPERAÇÃO?: Não PENDÊNCIA: Sim, repassar a nota para DCMD substituir tanque.DADOS DIVERGENTES DA PROGRAMAÇÃO: NãoBATERIA SUBSTITUÍDA?: Não TIPO DE BATERIA: Lítio EQUIPE: Edicleber e Jhonata(DEOP)------------------------------------------------------------------------------------------------------religador 7925733015 com defeito, equipe fez abertura da chave de saida do mesmo e ele não aceita fehcamento devido provavel curto-circuito interno, enviar equipe para verificar o mesmo ficou by-pass fechado | M54: 5 | N54: 5 | O54: 0 | P54: 0 | Q54: 15 | R54: 10 | S54: 0 | T54: 0 | U54: 35 | V54: Média | W54: Transferência do Ramal Agrovila (73 UCs)
A55: 2026 | B55: ETO-COEP 00157/2026 | C55: ETO-COEP | D55: 7927713200 | E55: 79 | F55: 46230 | G55: 200 | H55: SAO SALVADOR DO TOCANTINS | I55: PEIXE | J55: SUL | K55: LD02010021 | L55: segue SS para REALIZAR SUBSTITUIÇÃO DO TANQUE do RL 7927713200 danificado , com equipe de manutencao tensao 34,5kv mesmo atende Povoado retiro na rural de sao salvador . | M55: 5 | N55: 5 | O55: 5 | P55: 0 | Q55: 15 | R55: 10 | S55: 0 | T55: 0 | U55: 40 | V55: Média | W55: Transferência do Ramal do Retiro (246UCs), fonte principal by-passado
A56: 2026 | B56: ETO-COEP 00125/2026 | C56: ETO-COEP | D56: 7900525015 | E56: 79 | F56: 46210 | G56: 15 | H56: PEDRO AFONSO | I56: GUARAI | J56: NORTE | K56: LD02424015 | L56: PARECER COEP: É PARA REALIZAR A SUBSTITUIÇÃO DO RELIGADOR OU DAS BUCHAS, CASO SEJA BUCHAS , REPASSAR PARA OS COCM'S , CASO NÃO SEJA ESPECIFIQUE O MODELO , E A TENSÃO, FICO NO AGUARDO DO RETORNONota para manutenção substituir religador 7900525015 que está com as buchas de entrada danificadas fase A estourada e bc danificadas Local LD Pedro Afonso A Chaparral | M56: 5 | N56: 5 | O56: 0 | P56: 0 | Q56: 15 | R56: 10 | S56: 0 | T56: 0 | U56: 35 | V56: Média | W56: Tranferência do Ramal do Chaparral (251 UCs)
A57: 2026 | B57: ETO-COEP 00129/2026 | C57: ETO-COEP | D57: 7937102148 | E57: 79 | F57: 46210 | G57: 148 | H57: SAO VALERIO DA NATIVIDADE | I57: PEIXE | J57: SUL | K57: LD01066094 | L57: PARECER COEP: REAVALIAR DISPONIBILIDADE DO EQUIPAMENTO NO SCADA ASSIM COMO , FORNECER MODELO DO EQUIPAMENTO E FAIXA DE TENSÃO PARA COMPRA / AQUISIÇÃOTanque com defeito, realizar substituição do tanque. | M57: 5 | N57: 5 | O57: 5 | P57: 0 | Q57: 15 | R57: 10 | S57: 0 | T57: 0 | U57: 40 | V57: Média | W57: Fonte principal do Ramal Serranópolis (181 UCs), RL de transferência operando
A58: 2026 | B58: ETO-COEP 00038/2026 | C58: ETO-COEP | D58: 7908249152 | E58: 79 | F58: 46077 | G58: 152 | H58: SANTA ROSA DO TOCANTINS | I58: PORTO NACIONAL | J58: CENTRO | K58: LD02072001 | L58: 14/07/2026 PARECER COEP: EQUIPAMENTO SELECIONADO PARA COMPRADMSL:Serviço Executado: Houve um curto no equipamento danificando a parte ativa, será necessário fazer a substituição do equipamento completo ( parte ativa e controle) colocar o um cabo pp novo do trafo até o Dj pois o mesmo está sem condições de uso. Obs:. Foi retirado rádio e rele Equipamento ficou em operação?: Não Pendência: Sim, substituir o equipamento completo. | M58: 5 | N58: 5 | O58: 0 | P58: 0 | Q58: 15 | R58: 10 | S58: 0 | T58: 0 | U58: 35 | V58: Média | W58: Atendimento de zona rural em Santa Rosa (160 UCs)
A59: 2025 | B59: ETO-COEP 00158/2025 | C59: ETO-COEP | D59: 7942485096 | E59: 79 | F59: 45861 | G59: 96 | H59: PINDORAMA DO TOCANTINS | I59: PONTE ALTA TOCANTINS | J59: CENTRO | K59: LD03046026 | L59: 30/06 PARECER COEP: EQUIPAMENTO SELECIONADO PARA COMPRARELIGADOR COM DEFEITO 7942485096, ESTA DANDO PASSAGEM ESTANDO ABERTO. NÃO ACEITA COMANDOS. FICOU BY PASSADO EM CAMPO PARA MANUTENÇÃO.PARECER DMSL: Ao testar o tanque, foi constatado que o mesmo está danificado e precisa ser substituído.Substituir somente o tanque. Deixar claro na nota para o dcmd substituir somente o tanque. Não tem necessidade de substituir o controle. | M59: 5 | N59: 5 | O59: 5 | P59: 0 | Q59: 0 | R59: 10 | S59: 0 | T59: 0 | U59: 25 | V59: Baixa | W59: Transferência da PCH Bagagem
A60: 2026 | B60: ETO-COEP 00132/2026 | C60: ETO-COEP | D60: 7921202014 | E60: 79 | F60: 46211 | G60: 14 | H60: PIUM | I60: PARAISO DO TOCANTINS | J60: CENTRO | K60: LD01025012 | L60: PARECER COEP: EQUIPAMENTO SELECIONADO PARA COMPRA , DEVERIA SER SUBSTITUIDO PARTE ATIVAPARECER DMSL: Serviço Executado: _ indentificado o problema na parte ativa será necessário fazer a substituição da mesmo, feito a medição do aterramento. Preciso substituir para raio da fase c.Equipamento ficou em operação?: _NAOPendência: _SimBateria(s) substituída(s)? _NãoData Fabricação/Instalação da(s) bateria(s):_Equipe: _Benvindo e kaique----------------------------------------------------------------------------------RL com defeito no rele, fica só reiniciando ficou By passado OS atendimento primeiro ataque 106530226 | M60: 5 | N60: 5 | O60: 5 | P60: 0 | Q60: 0 | R60: 10 | S60: 0 | T60: 0 | U60: 25 | V60: Baixa | W60: Atendimento de Clientes rurais (483 UCs)
A61: 2026 | B61: ETO-PROT 00155/2026 | C61: ETO-PROT | D61: 7942572059 | E61: 79 | F61: 46224 | G61: 59 | H61: TAQUARALTO | I61: TAQUARALTO | J61: CENTRO | K61: LD02059122 | L61: PARECER COEP: EQUIPAMENTO COM MELHORIA DE ATERRAMENTO É COM A ETO-RD-PA , NÃO PASSA PELO FLUXO DE AQUISIÇÃO DO COEP, FAVOR REALIZAR MELHORIA DE ATERRAMENTO ETO-RD-PAPARECER DMSL 19/05/2026: É necessário fazer melhorias na malha de aterramento.segue nota para RL 794252059 o mesmo esta sem comunicaçao, foi feito primeiro ataque, porem a comunicaçao nao voltou, obs ramal do marasca.**** Parcecer do COCM CENTRO-****FEITO A MALHAR DE ATERRAMENTO ATENDIDA PELA ORDEM DE SERVIÇO DLP-MLPA02 91/2026 COM RELATORIO EM ANEXO A O.S | M61: 5 | N61: 5 | O61: 15 | P61: 0 | Q61: 0 | R61: 0 | S61: 10 | T61: 0 | U61: 35 | V61: Média | W61: Atendimento do Ramal do Marasca e GAs (108 UCs)
A62: 2025 | B62: ETO-COEP 00143/2025 | C62: ETO-COEP | D62: 7927446001 | E62: 79 | F62: 45846 | G62: 1 | H62: PORTO NACIONAL | I62: PORTO NACIONAL | J62: CENTRO | K62: LD02072001 | L62: 30/06 PARECER COEP: EQUIPAMENTO COMPLETOSegue para verificação RL sem comunicação feito primeiro ataque sem sucesso.PARECER DMSL:Data:* _08/07/2025Serviço Executado: Placa de alimentação danificada, devido a curto, não temos material sobressalente para manutenção! Favor substituir o equipamento completo.Obs.: O rádio ficou dentro do controle, favor orientar a equipe que for substituir colocar dentro do controle novo.Equipamento ficou em operação?: Não Pendência: Sim, substituir equipamento completo. | M62: 5 | N62: 5 | O62: 5 | P62: 0 | Q62: 0 | R62: 10 | S62: 0 | T62: 0 | U62: 25 | V62: Baixa | W62: Alimentação de Monte do Carmo por Porto Nacional
A63: 2026 | B63: ETO-COEP 00128/2026 | C63: ETO-COEP | D63: 7928241200 | E63: 79 | F63: 46210 | G63: 200 | H63: SAO SALVADOR DO TOCANTINS | I63: PEIXE | J63: SUL | K63: LD02066094 | L63: PARECER COEP: EQUIPAMENTO SELECIONADO PARA COMPRAPARECER DMSL: Tinha uma nota aberta 422/2025 e logo após a equipe resolver a comunicação ela foi baixada, porém a equipe relatou que ''na estrada ontem o COS nos avisou para voltar que na hora de colocar em operação ele tirou a linha fora. Hoje retornamos nele e fizemos ensaios elétricos e foi constatado que o tanque está em curto. Passa direto aí para o Dcmd para substituição do tanque.'' | M63: 5 | N63: 5 | O63: 5 | P63: 0 | Q63: 0 | R63: 10 | S63: 0 | T63: 0 | U63: 25 | V63: Baixa | W63: Fonte principal do Ramal do Retiro (246UCs), RL transferência by-passado
A64: 2026 | B64: ETO-COEP 00158/2026 | C64: ETO-COEP | D64: 5862236091 | E64: 58 | F64: 46230 | G64: 91 | H64: ALMAS | I64: DIANOPOLIS | J64: SUL | K64: LD05002091 | L64: 27/07 PARECER COEP: PEÇAS REDIRECIONADAS 5856070091 PRIORIDADE MAIOR20/07 PARECER COEP: EQUIPAMENTO ENTREGUE , FAVOR EDITAR A SS COM A DATA PREVISTA DE SUBSTITUIÇÃO NO PARECER DOS COCM´S Realizar substituição da FASE B.Célula da fase B estava com a tampa do contador de tape aberta, pegou chuva e molhou os contatos danificando a peça toda. | M64: 0 | N64: 0 | O64: 0 | P64: 20 | Q64: 0 | R64: - | S64: - | T64: - | U64: 20 | V64: Baixa | W64: Atendimento da LD Vale Rio Doce (Nova Aura Mineradora)
A65: 2026 | B65: ETO-COEP 00095/2026 | C65: ETO-COEP | D65: 5836786094 | E65: 58 | F65: 46160 | G65: 94 | H65: PEIXE | I65: PEIXE | J65: SUL | K65: LD01066094 | L65: 24/07 PARECER COEP:EQUIPAMENTO EM LOGISTICA DE ENTREGA Favor levar outro regulador de tensão, pois o mesmo foi furtado em campo. | M65: 0 | N65: 0 | O65: 0 | P65: 10 | Q65: 10 | R65: - | S65: - | T65: - | U65: 20 | V65: Baixa | W65: Atendimento de clientes rurais na LD Peixe Angical - Peixe
A66: 2026 | B66: ETO-COEP 00159/2026 | C66: ETO-COEP | D66: 7919270014 | E66: 79 | F66: 46230 | G66: 14 | H66: PIUM | I66: PARAISO DO TOCANTINS | J66: CENTRO | K66: LD01047073 | L66: 27/07/2026 PARECER COEP: EM PROCESSO DE AQUISIÇÃO , COMPLETOPARECER COEP: AGUARDANDO RETORNO DO DMSL, EQUIPAMENTO FOI INSTALADO NOVO NA OBRA 0212501060, ENTENDER O PORQUE NÃO FOI REALIZADO COMISSIONAMENTOPARECER DMSL: Substituir Equipamento completo problema na placa de alimentação e na parte ativa, falta colocar placa de identificação correta na topologia, baixar o controle.Equipamento ficou em operação?: naoPendência: simBateria(s) substituída(s)? NÃOEquipe: Kaique/ Benvindo13/07/2026 PARECER COEP: SUBSTITUIÇÃO REALZIADA , FAVOR COMISSIONARPARECER DMSL (22/07/26): Solicito que o laudo de substituição seja anexado, e a SS seja repassada para proteção atribuir a ordem de ajuste, antes de repassar para ETO-TELE.----------------------------------------------PARECER DA PROTEÇÃO: Prosseguir com o comissionamento. Ajustes de religador permanecem os mesmos, disponíveis no APP da Proteção.********************************RELIGADOR N°7919270014 REMANEJADO NA OBRA 0212501060 GENTILEZA, REALIZAR O COMISSIONAMENTO. LAUDO EM ANEXO. COORD EO: 617422, 8830787 | M66: 5 | N66: 5 | O66: 0 | P66: 0 | Q66: 0 | R66: 10 | S66: 0 | T66: 0 | U66: 20 | V66: Baixa | W66: Atendimento de Clientes rurais (48 UCs)
A67: 2026 | B67: ETO-COEP 00051/2026 | C67: ETO-COEP | D67: 7926442035 | E67: 79 | F67: 46099 | G67: 35 | H67: MONTE DO CARMO | I67: PONTE ALTA TOCANTINS | J67: CENTRO | K67: LD01051035 | L67: PARECER COEP: EQUIPAMENTO SELECIONADO PARA COMPRAPARECER DMSL: Data: 12/03/2026 Serviço Executado:- Análise técnica constatou:- Parte ativa do equipamento danificada: necessita substituição- Trafo danificado: foi feitos testes nas buchas secundárias o mesmo não chega tensão - Vazamento de óleo - Necessita substituiçãoEquipamento ficou em operação? NãoPendências:- Solicitar limpeza de faixa para acesso ao equipamento- Trocar parte ativa do equipamento- Substituir o trafoEquipe: Carliel e João VitorSegue nota para envia equipe verificar falha de comunicação e automação no RL-7926442035 feito primeiro ataque com equipe 035OP02, porém sem sucesso. | M67: 5 | N67: 5 | O67: 0 | P67: 0 | Q67: 0 | R67: 0 | S67: 10 | T67: 0 | U67: 20 | V67: Baixa | W67: Atenidmento do PA Principado (200 UCs)
A68: 2026 | B68: ETO-COEP 00144/2026 | C68: ETO-COEP | D68: 7938137007 | E68: 79 | F68: 46218 | G68: 7 | H68: MIRACEMA DO TOCANTINS | I68: MIRACEMA DO TOCANTINS | J68: CENTRO | K68: AL02017017 | L68: PARECER DMSL 09/07/2026: GENTILEZA VERIFICAR HAVIA UMA NOTA ABERTA, EQUIPE RETORNOU EM CAMPO E NÃO FOI REALIZADAserviço realizado na SS ENC-RD-PS 1397/2025, REPASSANDO PARA COMISSIONARRL 7938137007 NO RL INSTALAR BATERIA NOVA E RADIO A PEDIDO DE KAROLINY DMSLACESSO LIVREPARECER DMSL: * equipamento esta com a bucha da fase A com problemas(solta), necessário substituir* Trafo do serviço auxiliar esta vazando óleo, necessário substituir- Material ainda não foi entregue para substituição 15/07/2026 | M68: 5 | N68: 5 | O68: 5 | P68: 0 | Q68: 0 | R68: 0 | S68: 0 | T68: 0 | U68: 15 | V68: Baixa | W68: Transferência do Irmã Adelaide (470 UCs)
A69: 2026 | B69: ETO-COEP 00160/2026 | C69: ETO-COEP | D69: 5856156091 | E69: 58 | F69: 46230 | G69: 91 | H69: ALMAS | I69: DIANOPOLIS | J69: SUL | K69: LD04002091 | L69: 27/07/2026 PARECER COEP: EQUIPAMENTO SELECIONADO PARA COMPRA, PORÉM PODEMOS DESATIVAR DE ACORDO COM A ASPODCMD 26.03.2026. SS REPASSADA PARA COEP PROVIDENCIAR MATERIAL. NÃO TEMOS O MATERIAL EM ESTOQUE PARA SUBSTITUIÇÃO. COEP: Equipamento fornecido ao COCM-S para regularização.PARECER COEP: EQUIPAMENTOS JÁ FORNECIDOS PARA OS COCM'S PARA REGULARIZAÇÃOPARECER DA PROTEÇÃO:EQUIPAMENTOS FURTADOS. PARA AQUISIÇÃO DAS CELULAS DE REPOSIÇÃO, FAVOR CONSULTAR OS DADOS DE PLACA EM ANEXO.PARECER DA PROTEÇÃO:COMISISONAR RT 5856156091 LD DIANOPOLIS A NATIVIDADE. NECESSARIO REALIZAR MEDIÇÕES DA RESISTENCIA DA MALHA DE ATERRAMENTO.AJUSTES DISPONIVEIS NO APP DA PROTEÇÃO.RELIGADOR N° 5856156091 INSTALADO NA OBRA 0502400526 GENTILEZA, REALIZAR O COMISSIONAMENTO. LAUDO EM ANEXO. COORD EO: 899501, 8714782 | M69: 0 | N69: 0 | O69: 0 | P69: 0 | Q69: 0 | R69: - | S69: - | T69: - | U69: 0 | V69: Baixa | W69: Equipamento novo furtado antes de ser colocado em operação
A70: 2026 | B70: ETO-COEP 00164/2026 | C70: ETO-COEP | D70: 5858783119 | E70: 58 | F70: 46234 | G70: 119 | H70: SAO BENTO DO TOCANTINS | I70: TOCANTINOPOLIS | J70: NORTE | K70: LD03005098 | L70: PARECER DMSL 31/07/2026: RT 5858783119 SE ECONTRA NA MESMA SITUAÇÃO INFORMADA NO DIA 16/06/2026. FAVOR, REGULARIZAR A SITUAÇÃO DO EQUIPAMENTO, SUBSTITUINDO OS 3 TANQUES E INSTALAR NOVOS PARA-RAIOS.27/07/2026 PARECER COEP: FIZEMOS UMA VISITA AO EQUIPAMENTO , EQUIPAMENTO SE ENCONTRA EM OPERAÇÃO E SEM SINAL DE AVARIA FAVOR AVALIAR PARECER DMSL A SS FOTOS COM O LUANDERSSON OU JOAO ANTONIO LAGARES 20/07 PARECER COEP: EQUIPAMENTO SELECIONADO PARA COMPRA , DEVIDO AO ERRO NA INSTALAÇÃO E O FURTOPARECER DMSL: 16/06/2025-SERVIÇO EXECUTADO: Ao chegar no equipamento para realizar comissionamento, foi constatato que as 3 células estavam com a tampa de inspeção abertas e sem os para-raios. Constatado também que foi furtado todo o óleo isolante das 3 células, sendo necessário a substituição das 3 células. FICOU EM OPERAÇÃO?: Não PENDÊNCIA: Substituir as 3 células | M70: 0 | N70: 0 | O70: 0 | P70: 0 | Q70: 0 | R70: - | S70: - | T70: - | U70: 0 | V70: Baixa | W70: Equipamento não inserido no SCADA
A71: 2026 | B71: ETO-COEP 00138/2026 | C71: ETO-COEP | D71: 7930359149 | E71: 79 | F71: 46216 | G71: 149 | H71: CASEARA | I71: DIVINOPOLIS | J71: CENTRO | K71: LD03414149 | L71: PARECER DMSL 07/07/2026: equipamento tem que ser subistuido pois não faz comando, parte ativa com defeito FEITO O PRIMEIRO ATAQUE NO RELIGADOR 7930359149 E MESMO NÃO ACEITA COMANDO NEM LOCAL E NEM REMOTO SEGUNDO EQUIPE 149OP02 E PLACA DO RL ESTA CARBONIZADA COM SINAL DE CURTO. | U71: 0 | V71: Falta definir
A72: 2026 | B72: ETO-COEP 00147/2026 | C72: ETO-COEP | D72: 7953211079 | E72: 79 | F72: 46219 | G72: 79 | H72: ITAPIRATINS | I72: GUARAI | J72: NORTE | K72: LD03038009 | L72: 20/07 PARECER COEP: EQUIPAMENTO SELECIONADO PARA COMPRASegue nota para substituir relé religador avariado marca noja , equipamento N: 7953211079 - Itapiratins .Obs: informação repassado pelo técnico DMSL Bruno . | U72: 0 | V72: Falta definir
A73: 2026 | B73: ETO-TELE 00929/2026 | C73: ETO-TELE | D73: 7949648145 | E73: 79 | F73: 46186 | G73: 145 | H73: MAURILANDIA DO TOCANTINS | I73: AUGUSTINOPOLIS | J73: NORTE | K73: AL02043081 | L73: FEITO PRIMEIRO ATAQUE COM A EQUIPE LOCAL E NÃO VOLTOU A COMUNICAR. PROVIDENCIAR MANUTENÇÃO PARA O MESMO. | U73: 0 | V73: Falta definir
A74: 2026 | B74: ETO-TELE 00938/2026 | C74: ETO-TELE | D74: 7908300096 | E74: 79 | F74: 46191 | G74: 96 | H74: PINDORAMA DO TOCANTINS | I74: PONTE ALTA TOCANTINS | J74: CENTRO | K74: LD03046026 | L74: Segue nota para verificar falha intermitência na comunicação RL 7908300096 RDU- Pindorama . | U74: 0 | V74: Falta definir
A75: 2026 | B75: ETO-TELE 01029/2026 | C75: ETO-TELE | D75: 7900722193 | E75: 79 | F75: 46227 | G75: 193 | H75: CAMPOS LINDOS | I75: ARAGUAINA | J75: NORTE | K75: PS01112193 | L75: Religador sem comunicação, apos primeiro ataque não retornou a comunicação. | U75: 0 | V75: Falta definir
A76: 2026 | B76: ETO-TELE 00985/2026 | C76: ETO-TELE | D76: 5839141113 | E76: 58 | F76: 46210 | G76: 113 | H76: COUTO MAGALHAES | I76: GUARAI | J76: NORTE | K76: AL01024113 | L76: Segue nota para averiguar ajuste regulador de tensão N: 5839141113 - RDU - Couto Magalhães , e verificar falha de comunicação .Equipe operacional verificou que vários transformadores urbanos estão com nível de tensão baixa .Foi feito primeiro ataque regulador está comutando normalmente as 3 fases , porém não está no nível adequado !Em campo regulador estava no Tap R1 - 02 , R2 + 01 , R3 +03Medições feitas :Transformador 5700010113 - NA: 205 NB: 206 NC: 210Transformador 5700011113 - NA: 204 NB: 206 NC: 209Transformador 5700333113 -NA: 205 NB: 207 NC: 208OBS: solicitar equipe para realizar medição aterramento , e verificar ajuste junto ao time proteção . verificar falha de comunicação no equipamento . | U76: 0 | V76: Falta definir
A77: 2026 | B77: ETO-TELE 01027/2026 | C77: ETO-TELE | D77: 7923110021 | E77: 79 | F77: 46226 | G77: 21 | H77: PARANA | I77: PEIXE | J77: SUL | K77: LD03010021 | L77: Segue SS para verificar falha de comunicação no religador 7923110021. Equipe foi no local realizar primeiro ataque e informou que o radio de comunicação encontra-se com defeito | U77: 0 | V77: Falta definir
A78: 2026 | B78: ETO-TELE 01058/2026 | C78: ETO-TELE | D78: 7950296049 | E78: 79 | F78: 46243 | G78: 49 | H78: AURORA DO TOCANTINS | I78: DIANOPOLIS | J78: SUL | K78: LD02110005 | L78: religador de poste 7950296049 com falha no dispaly do equipamento tensão 34.5 kv acesso livre indisponivel para operação e aberto em campo e sem comunicação . | V78: Falta definir
A79: 2026 | B79: ETO-TELE 01057/2026 | C79: ETO-TELE | D79: 7909594004 | E79: 79 | F79: 46243 | G79: 4 | H79: ARAGUAINA | I79: ARAGUAINA | J79: NORTE | K79: AL04040004 | L79: Religador sem comunicação, apos primeiro ataque não retornou as comunicação. | V79: Falta definir
A80: 2026 | B80: ETO-TELE 01048/2026 | C80: ETO-TELE | D80: 7961515047 | E80: 79 | F80: 46239 | G80: 47 | H80: FIGUEIROPOLIS | I80: FORMOSO DO ARAGUAIA | J80: SUL | K80: AL01033047 | L80: segue nota equipamento RL 7961515047 desarmou em campo e nao sinalizou no AMDS mesmo nao estar comunicando , feito primeiro ataque equepe 047op01 e com orientaçoes da EDNA DMSL , mesmo nao voltou a comunicaçao , ficou em operacao e sem comunicar . | V80: Falta definir
A81: 2026 | B81: ETO-COEP 00153/2026 | C81: ETO-COEP | D81: 5825703064 | E81: 58 | F81: 46224 | G81: 64 | H81: BRASILANDIA DO TOCANTINS | I81: GUARAI | J81: NORTE | K81: LD02020023 | L81: PARECER DMSL: Foi identificado que a fase A esta em curto (892Kbps) no teste de Megometro, o curto afetou o rele RUA 01 e rompeu o jamper da chave faca para a linha de distribuição.PROVIDENCIAR MANUTENÇÃO PARA O REGULADOR 5825703064 POIS O MESMO ESTA EM CURTO E FASE A DE SAIDE ESTA ROMPIDO. | V81: Falta definir
A82: 2026 | B82: ETO-TELE 01098/2026 | C82: ETO-TELE | D82: 7938048113 | E82: 79 | F82: 46244 | G82: 113 | H82: COUTO MAGALHAES | I82: GUARAI | J82: NORTE | K82: LD02020023 | L82: Enviar equipe da TELE, para sanar defeito de comunicação do RL 7938048113, não aceita comandos de fechamento e nem de abertura remoto.Situação no sistema ABERTO NO ADMS, porém fechado normalmente em campo | V82: Falta definir
A83: 2026 | B83: ETO-RD-PO 00183/2026 | C83: ETO-RD-PO | D83: 7931219078 | E83: 79 | F83: 46211 | G83: 78 | H83: ITACAJA | I83: GUARAI | J83: NORTE | K83: LD01065015 | L83: 08/07/2026 PARECER COEP: SUBSTITUIÇÃO DE TRAFO AUXILIAR ENCAMINHADO PARA REALIZAR A TROCA , FAVOR COLOCAR O PARECER AQUI E MANDAR DEPOIS PARA PROTEÇÃO , POR FAVORPARECER COEP: SUBSTITUIÇÃO DO TRAFO É DIRETO COM OS COCM'S, NÃO TEM COMPRA DE EQUIPAMENTO ESPECIAL.PARECER DMSL (25/07/2025): Realizada atualização da base do relé. Feito comissionamento com SCADA (Kauana) e testes com COS (Daniel). Equipamento reinserido no SEP sem anomalias. PENDÊNCIA: Sim. Substituir Trafo auxiliar, pois o mesmo está com vazamento significativo de óleo isolante, o que irá causar a avaria podendo afetar todo controle do religador.FAZER INSPEÇÃO E MANUTENÇÃO DO RL 7931219078. RELIGADOR CHAVE ESTA MUDANDO SOZINHA PARA LOCAL. | V83: Falta definir
A84: 2026 | B84: ETO-TELEAR 00008/2026 | C84: ETO-TELEAR | D84: 7949656024 | E84: 79 | F84: 46246 | G84: 24 | H84: ITAPORA DO TOCANTINS | I84: GUARAI | J84: NORTE | K84: LD02020023 | L84: Favor deslocar equipe no religador 7949656024 foi realizado primeiro ataque no mesmo, porem sem sucesso.Religador se encontra fechado em campo e aberto no ADMS. | V84: Falta definir
A85: 2026 | B85: ETO-TELE 01051/2026 | C85: ETO-TELE | D85: 7944353028 | E85: 79 | F85: 46241 | G85: 28 | H85: NATIVIDADE | I85: DIANOPOLIS | J85: SUL | K85: LD04002091 | L85: Religador de poste 7944353028 sem comunicação com coi equipe 091op02 feito primeiro ataque os 99 porem não retornou a comunição enviar equipe ao local verificar possivel falha. | V85: Falta definir
A86: 2026 | B86: ETO-TELE 01111/2026 | C86: ETO-TELE | D86: 7925126060 | E86: 79 | F86: 46252 | G86: 60 | H86: NOVA OLINDA | I86: COLINAS DO TOCANTINS | J86: NORTE | K86: AL02054060 | L86: Foi feito o primeiro ataque não retornou a comunicaçãoRL 7925126060 com apoio do Jean | V86: Falta definir
A87: 2026 | B87: ETO-TELE 01100/2026 | C87: ETO-TELE | D87: 7908709122 | E87: 79 | F87: 46245 | G87: 122 | H87: PALMAS | I87: PALMAS | J87: CENTRO | K87: AL01059122 | L87: Segue SS aberta para Religador 7908709122equipe sinergia fez o primeiro ataque porem ,o mesmo não voltou a comunicação.equipe sinergia.contato equipe 63 98414-0477 almir | V87: Falta definir
A88: 2026 | B88: ETO-TELE 01110/2026 | C88: ETO-TELE | D88: 7905320122 | E88: 79 | F88: 46250 | G88: 122 | H88: PALMAS | I88: PALMAS | J88: CENTRO | K88: AL06060122 | L88: Segue nota para verificar falha sinalização status religador 7905320122 - rdu- Palmas .Equipamento está fechado em campo porem está sinalizando aberto . | V88: Falta definir
A89: 2026 | B89: ETO-TELE 01059/2026 | C89: ETO-TELE | D89: 7926242029 | E89: 79 | F89: 46243 | G89: 29 | H89: PALMEIROPOLIS | I89: PEIXE | J89: SUL | K89: LD02010021 | L89: religador 7926242029 sem comunicação com sistema em operação com anomalia insdisponivel para operação acesso bom porem veiculo não chega ao local .feito primeiro ataque sem sucesso | V89: Falta definir
... A94: 2026 | B94: ETO-TELE 01052/2026 | C94: ETO-TELE | D94: 7925727002 | E94: 79 | F94: 46241 | G94: 2 | H94: TOCANTINOPOLIS | I94: TOCANTINOPOLIS | J94: NORTE | K94: AL02084002 | L94: Segue nota para verificar falha de comunicação no religador 7925727002 quando falta CA , Local RDU- Tocantinopolis .Equipamento perde a comunicação quando falta CA ! | V94: Falta definir

Sheet Premissas por Equipamento
A1: Ativo | B1: Tipo | C1: Localidade | D1: Polo | E1: Regional | F1: SS aberta | G1: Parecer COEP | H1: SS DCMD | I1: Status DCMD | J1: Previsão DCMD | K1: SS Proteção | L1: Status Proteção | M1: Previsão Proteção | N1: SS DMSL | O1: Status DMSL | P1: Previsão DMSL | Q1: Status COI | R1: Observação | S1: Check de concluídas | T1: Defeito identificado | U1: Quantidade | V1: Descrição SS | W1: Premissa 1 | X1: Premissa 2 | Y1: Premissa 3 | Z1: Premissa 4 | AA1: Premissa 5 | AB1: Premissa 6 | AC1: Premissa 7 | AD1: Premissa 8 | AE1: Priorização | AF1: Criticidade | AG1: Observação após análise
A2: 5800291077 | B2: 58 | C2: GOIATINS | D2: ARAGUAINA | E2: NORTE | F2: CONCLUÍDA | S2: Ok | W2: 40 | X2: 20 | Y2: 20 | Z2: 20 | AA2: 20 | AB2: - | AC2: - | AD2: - | AE2: 120 | AF2: Muito Alta | AG2: Aumento de reclamações no atendimento de Goiatins e GAs relevantes na região
A3: 5854566043 | B3: 58 | C3: SILVANOPOLIS | D3: PORTO NACIONAL | E3: CENTRO | F3: ETO-RD-PO 00213/2026 | G3: Em fase de ajustes | R3: Pendente laudo da empreteira | S3: Em andamento | T3: Célula | U3: 1 | V3: 22/07/2026 PARECER COEP: EQUIPAMENTO ENTREGUE AOS COCM´SPRAZO DE 7 DIAS CONTANDO O SLA.PARECER COEP: EQUIPAMENTO ENTREGUE AOS COCM´S FAVOR SUSBSTTUIR , E AGUARDO O PRAZO DE PREVISÃO DE SUBSTIUIÇÃOboa noite,segue SS para as devidas tratativas com equipe de manutenção com apoio de equipe de linha viva substituir regulador de tensão 5854566043 queimado célula fase c, LD Porto / Silvanópolis mesmo deverá ser substituído com apoio de equipe de linha viva PARECER DMSL: Foi realizado inspeção visual e ensaios de isolação, relação de transformação e resistência de enrolamento. A fase B está danificada e será necessário substituir a mesma. Malha de aterramento está relativamente boa e conectada. Fase A e C passaram nos ensaios. Substituir fase B. | W3: 40 | X3: 20 | Y3: 20 | Z3: 10 | AA3: 20 | AB3: - | AC3: - | AD3: - | AE3: 110 | AF3: Muito Alta | AG3: Aumento de reclamações no atendimento de Silvanópolis por Porto Nacional no período seco (Outra fonte com defeito também)
A4: 5800859011 | B4: 58 | C4: TUPIRAMA | D4: GUARAI | E4: NORTE | F4: ETO-RD-GR 00735/2026 | G4: Aguardando comissionamento | R4: Previsão de substituição 27/08 | S4: Em andamento | T4: Controle | U4: 1 | V4: 16/07/2026 PARECER COEP: ALINHADO COM O JEAN DO DMSL E O KELLITON , KELLITON IRÁ FAZER A INSTALAÇÃO DO CONTROLE RUA E O JEAN IRÁ REALIZAR O COMISSIONAMENTO , FAZENDO A COMPATIBILIZAÇÃO DOS CABOS ASSIM COMO FICARÁ UM CONTROLE RUA NO NOSSO ESTOQUE SOBRESSALENTE PARA ATENDER O DE ARAPOEMA, ATÉ A CHEGADA DOS CABOS QUE O JEAN ME DEU REPORTE DE QUE SERIA ATÉ O DIA 16/08 , FAVOR COCM'S REALIZAREM A INSTALAÇÃO E GUARDAR CONTROLE RUA SOBRESSALENTE PARA ARAPOEMAPEÇA ENVIADA: CONTROLEPARECER DMSL: *FEEDBACK EQUIP. ESPECIAIS**Nº DO EQUIPAMENTO:* 5800859011*TIPO EQUIPAMENTO:* RT ITB *TIPO DE COMUNICAÇÃO:* Não *DATA DA MANUTENÇÃO:* 09/06/2026*SID:* 3195/2026*DESCRIÇÃO:* _ Foi identificado relé da fase C com defeito conforme orientação da supervisão e necessário realiza retrofit para instalação de controle rua.*FICOU EM OPERAÇÃO* Não*PENDÊNCIA:* Realizado Retrofit *DADOS DIVERGENTES DA PROGRAMAÇÃO:* Não*BATERIA SUBSTITUÍDA?:* Não*TIPO DE BATERIA:**EQUIPE:* Edeglan e Brunno.Observação: trocar por um controle RUA.------------------------------------------------------------------------------------------Enviar equipe do DMSL, para fazer correção no RT 5800859011, o mesmo está com o displey da fase C apagado , dificutando realizar manobras no mesmo, emvirtude disso o mesmo ficou BAY PASSADO EM CAMPO | W4: 40 | X4: 20 | Y4: 20 | Z4: 10 | AA4: 20 | AB4: - | AC4: - | AD4: - | AE4: 110 | AF4: Muito Alta | AG4: Atendimento de parte da RDU Guaraí por fonte alternativa
A5: 5836764032 | B5: 58 | C5: ARAGUACU | D5: ALVORADA | E5: SUL | F5: CONCLUÍDA | S5: Ok | W5: 40 | X5: 20 | Y5: 20 | Z5: 10 | AA5: 20 | AB5: - | AC5: - | AD5: - | AE5: 110 | AF5: Muito Alta | AG5: Aumento de reclamações no atendimento de Araguaçu no período seco
A6: 7923673004 | B6: 79 | C6: ARAGUAINA | D6: ARAGUAINA | E6: NORTE | F6: ETO-COEP 00124/2026 | G6: Em processo de aquisição | R6: Estava aguardando retorno DMSL | S6: Pendente | T6: Tanque + controle | U6: 1 | V6: PARECER COEP: Verificar Disponibilidade de equipamento no Scada e enviar modelo e tensão para a compra.RELIGADOR COM RELÉ DANIFICADO, REALIZAR SUBSTITUIÇÃO | W6: 15 | X6: 20 | Y6: 15 | Z6: 15 | AA6: 15 | AB6: 10 | AC6: 0 | AD6: 15 | AE6: 105 | AF6: Muito Alta | AG6: Transferência de cargas na RDU de Araguaína (2797 UCs)
A7: 7931608059 | B7: 79 | C7: TAQUARALTO | D7: TAQUARALTO | E7: CENTRO | F7: ETO-COEP 00040/2026 | G7: Em processo de aquisição | S7: Pendente | T7: Tanque e rádio | U7: 1 | V7: PARECER COEP: EQUIPAMENTO SELECIONADO PARA COMPRADMSL:Serviço Executado: Foi feita uma análise técnica no equipamento, devido à falta de comunicação. Também foi identificado que o tanque do equipamento está danificado, sendo assim, necessário substituir o tanque e o rádio do equipamento, que está queimado, sendo necessário substituir também. | W7: 15 | X7: 20 | Y7: 15 | Z7: 15 | AA7: 15 | AB7: 10 | AC7: 0 | AD7: 15 | AE7: 105 | AF7: Muito Alta | AG7: Transferência dos bairros Morada do Sol, Vale do Sol, Morada do Sol II, Nova Esperança, Sõa João, Araras I e II e Jardim Laila em Taquaralto (6033 UCs)
A8: 7931610122 | B8: 79 | C8: PALMAS | D8: PALMAS | E8: CENTRO | F8: ETO-TELE 01025/2026 | G8: Aguardando comissionamento | O8: SS ATENDIDA | S8: Em andamento | T8: Tanque e antena | U8: 1 | V8: PARECER DA PROTEÇÃO:FAVOR COMISSIONAR RELIGADOR. AJUSTES PERMANECEM OS MESMOS E DISPONÍVEIS NO APP DA PROTEÇÃO.Estagiário Rafael P Marques.******************30/06 PARECER COEP: EQUIPAMENTO ENTREGUE, SEGUE SS PARA O COCM´S , PARA REALIZAR O ATENDIMENTO,FAVOR ADICIONAR O PARECER PARA MANDAR PARA PROTEÇÃOBom dia,Segue SS para verificação RL sem comunicação com painel apagado equipe DEOP fez primeiro ataque sem sucesso RL 7931610122 RDU de Palmas.Feedback Equipamentos Especiais DMSL: *RLG 7931610122 RDU Palmas*Noja rc10 Data: 14/10/2025SID: 5412Dados de comunicação divergentes da programação: Não. Serviço Executado: Houve um curto no equipamento danificando a parte ativa, e antena! Será necessário fazer a substituição somente da parte ativa (tanque) e da antena.Equipamento ficou em operação?: Não Pendência: Sim, substituir a parte ativa.Bateria(s) substituída(s)?: NãoData Fabricação/Instalação da(s) bateria(s): 2024Equipe: Benvindo, Juliano e Sérgio.***** Parecer do COCM CENTRO*****Equipamento Substituido em campo pela Ordem de ServiÇO DLP-MPPA01 243/2026, ONDE OS RELATORIO ESTÃO ANEXADO.--------------------------------------------------------Parecer DMSL:Equipamento substituído porém não informado se antena também foi substituída. Levar antena para caso da mesmo não ter sido substituída. | W8: 15 | X8: 20 | Y8: 15 | Z8: 15 | AA8: 15 | AB8: 10 | AC8: 0 | AD8: 15 | AE8: 105 | AF8: Muito Alta | AG8: Transferência entre 284R SE Palmas IV e 2294R SE Palmas II
A9: 7900648055 | B9: 79 | C9: ARAGUACEMA | D9: DIVINOPOLIS | E9: CENTRO | F9: CONCLUÍDA | S9: Ok | W9: 15 | X9: 20 | Y9: 15 | Z9: 15 | AA9: 15 | AB9: 10 | AC9: 0 | AD9: 15 | AE9: 105 | AF9: Muito Alta | AG9: Transferência da RDU de Araguacema (1506 UCs)
A10: 7947203070 | B10: 79 | C10: RIO SONO | D10: TAQUARALTO | E10: CENTRO | F10: ETO-COEP 00131/2026 | G10: Em processo de aquisição | S10: Pendente | T10: Controle | U10: 1 | V10: 13/07 PARECER COEP: SELECIONADO PARA COMPRA CONTROLE favor verificar RL 7947203070, sem comunicaçao, feito 1° ataque pela equipe 070OP01 e nao retornou a comunicaçao , linformaçao no Scada de bateria.PARECER DMSL: Foi feito análise técnica, a placa do equipamento está queimada nessesario subistituir o equipamento completo -Carliel e Benvindo-05/02 | W10: 10 | X10: 20 | Y10: 15 | Z10: 15 | AA10: 15 | AB10: 10 | AC10: 0 | AD10: 15 | AE10: 100 | AF10: Muito Alta | AG10: Transferência da RDU de Lizarda (1650 UCs) para fonte alternativa
A11: 5856070091 | B11: 58 | C11: ALMAS | D11: DIANOPOLIS | E11: SUL | F11: ETO-RD-DP 00479/2026 | G11: Equipamento entregue ao COCM | R11: Previsão de substituição 07/08// Nova previsão de entrega 21/08 se a DB Machado for para o Sul | S11: Em andamento | T11: Células + controle | U11: 3 | V11: PARECER DMSL: não foi regularizado a instalação do equipamento, nota repassada conforme alinhado com o supervisor.____________________________________________COCMS 26.03.26. SS REPASSADA PARA COEP PROVIDENCIAR MATERIAL. NÃO TEMOS AS PÇ EM ESTOQUE PARA FAZER A SUBSTITUIÇÃO. Solicitação de serviço para reposição de equipamentos furtados .COEP: Equipamento fornecido ao COCM-S para regularização.COCMS: Equipamento substituido conforme solicitado. Gentileza comissionar.PARECER DA PROTEÇÃO:SEGUE NOTA REPASSADA PARA DMSL COMISSIONAR.ENG° IRLLEY CASTELO BRANCOPARECER DMSL(23/09/2025): Feito a parte de comunicação, fechando enlace, configuração do rádio GE. Feito a medição de aterramento. Após uma inspeção, foi identificado que o regulador de tensão está instalado errado, carga está para o lado de fonte e fonte está do lado de carga. O certo é a fonte vim de almas, atualmente está vindo de natividade. Favor fazer a instalação correta. | W11: 40 | X11: 20 | Y11: 20 | Z11: 20 | AA11: 0 | AB11: - | AC11: - | AD11: - | AE11: 100 | AF11: Muito Alta | AG11: Atendimento da região da Engegold, Nativa, cidade Natividade e Chapada da Natividade
A12: 7903569004 | B12: 79 | C12: ARAGUAINA | D12: ARAGUAINA | E12: NORTE | F12: CONCLUÍDA | W12: 15 | X12: 20 | Y12: 5 | Z12: 15 | AA12: 15 | AB12: 10 | AC12: 0 | AD12: 15 | AE12: 95 | AF12: Muito Alta | AG12: Transferência dos bairros JD Santa Helena, Jd Filadelfiae Setor Caraja em Araguaína (2053 UCs), AL 254R de AR I e AL 214R de AR III
A13: 7925744087 | B13: 79 | C13: GOIANORTE | D13: GUARAI | E13: NORTE | F13: ETO-COEP 00059/2026 | G13: Em processo de aquisição | R13: Mandar reformar | S13: Pendente | T13: Tanque e cabo umbilical | U13: 1 | V13: PARECER COEP: EQUIPAMENTO SELECIONADO PARA COMPRAPARECER DMSL: FEEDBACK EQUIP. ESPECIAISNº DO EQUIPAMENTO: 7925744087TIPO EQUIPAMENTO: Noja RC 10TIPO DE COMUNICAÇÃO: Radio GE IPDATA DA MANUTENÇÃO: 19/02/2026SID: 735/2026 DESCRIÇÃO: foi identificado água dentro da parte interna do tanque e cabo umbilical encharcado de água foi passado essas informações para COS.FICOU EM OPERAÇÃO?: Não PENDÊNCIA: Sim substituir tanque e cabo umbilicalDADOS DIVERGENTES DA PROGRAMAÇÃO: NãoBATERIA SUBSTITUÍDA?: Não DATA DA BATERIA: 07/05/2025TIPO DE BATERIA: Lítio EQUIPE: Edeglan e Janio-------------------------------------------------------------------------------------------------RELIGADOR SEM COMUNICAÇÃO, APOS PRIMEIRO ATAQUE RETORNA E FICAR INDEFINIDO. | W13: 15 | X13: 20 | Y13: 5 | Z13: 15 | AA13: 15 | AB13: 10 | AC13: 0 | AD13: 15 | AE13: 95 | AF13: Muito Alta | AG13: Transferência de Goianorte, fonte principal operando
A14: 7900117013 | B14: 79 | C14: PARAISO DO TOCANTINS | D14: PARAISO DO TOCANTINS | E14: CENTRO | F14: ETO-PROT 00154/2026 | G14: Em fase de ajustes | S14: Em andamento | T14: Controle | U14: 1 | V14: 15/07 PARECER COCM: EQUIPAMENTO FOI SUBSTITUÍDO OBRA 021260042210/07 PARECER COEP: EQUIPAMENTO ENTREGUE AOS COCM´S FAVOR INFORMAR PRAZO DE SUBSTUIÇÃO PARA O DMSL E REPASSAR DEPOIS PARA PROTEÇÃO REALIZAR OS AJUSTES E DESCREVER NA SS O SERVIÇO REALIZADOPARECER COEP: PREVISÃO DE ENTREGA AOS COCM'S 01/07Segue nota para correção de anomalia e provável substituição de religador , religador 7900117013 -RDU - Paraiso .OBS: equipe DMSL Elisfran estava atualizando firmware no equipamento , porém relé parou de funcionar devido essa atualização , sendo necessário sua substituição .em campo o modelo e cooper Form6 , segundo tecnico deve ser substituído por um Noja .Repassado para o COEP para aquisição do equipamento e posterior repasse para o COCM. | W14: 15 | X14: 20 | Y14: 15 | Z14: 15 | AA14: 15 | AB14: 0 | AC14: 0 | AD14: 15 | AE14: 95 | AF14: Muito Alta | AG14: Transferência do 214R de Paraíso I, Centro Comercial de Paraíso
A15: 7929376022 | B15: 79 | C15: BABACULANDIA | D15: ARAGUAINA | E15: NORTE | F15: ETO-COEP 00120/2026 | G15: Concuído DCMD | R15: Construir Reporte | S15: Em andamento | T15: Tanque + controle | U15: 1 | V15: PARECER COEP: PROBLEMA NO ENVIO COCM'S CONTROLE ENVIADO FOI O NOJA , DEVIDO A FALTA DO MODELO NA SS (GRAVE)PARECER DMSL: *FEEDBACK EQUIP. ESPECIAIS**Nº DO EQUIPAMENTO:* 7929376022 *DATA DA MANUTENÇÃO:* 02/04/2026*SID:* 1677/2026*DESCRIÇÃO:* Trocar controle completo*PENDÊNCIA:* Sim.*DADOS DIVERGENTES DA PROGRAMAÇÃO:* Não*BATERIA SUBSTITUÍDA?:* Não*EQUIPE:* Adeilton e Edicleber __________________________________________________________POR GENTILEZA ATENDER SOLICITAÇÃO PRIMEIRO ATAQUE IDENTIFICOU QUE RELE ESTA EM CURTO NOTA ABERTA 224/2026 FOI BAIXADA POREM NÃO FOI CORRIGIDO PROBLEMA EM CAMPO. | W15: 15 | X15: 20 | Y15: 5 | Z15: 15 | AA15: 15 | AB15: 10 | AC15: 0 | AD15: 15 | AE15: 95 | AF15: Muito Alta | AG15: Transferência de Babaçulândia, fonte principal operando
A16: 7908705049 | B16: 79 | C16: AURORA DO TOCANTINS | D16: DIANOPOLIS | E16: SUL | F16: ETO-RD-DP 00409/2026 | G16: Equipamento entregue ao COCM | R16: Previsão de substituição 07/08 // 22/08 Se a DB Machado for pro Sul | S16: Em andamento | T16: Tanque + controle | U16: 1 | V16: EQUIPAMENTO ENTREGUE, SOLICITO PREVISÃO PARA SUBSTITUIÇÃO:PARECER COEP: PREVISÃO DE ENTREGA AOS COCM'S 01/07Manutenção no RL 7908705049PARECER DMSL(28/08/2025): Equipe foi fazer manutenção no RL e constatou que o tanque e o relé do mesmo se encontra queimado, providenciar substituição.PARECER COCMS 30/04/2026CRIADO OBRA 0512600135 PARA REQUISIÇÃO MATERIAL | W16: 15 | X16: 20 | Y16: 5 | Z16: 15 | AA16: 15 | AB16: 0 | AC16: 10 | AD16: 15 | AE16: 95 | AF16: Muito Alta | AG16: Proteção da baixa do TF de força da SE Aurora
A17: 7933726256 | B17: 79 | C17: MATEIROS | D17: PONTE ALTA TOCANTINS | E17: CENTRO | F17: ETO-PROT 00145/2026 | G17: Em fase de ajustes | R17: Destinada parte ativa do RL 7900453110 | S17: Em andamento | T17: Tanque | U17: 1 | V17: 07/07 Equipamento foi substituido na OS: ETO-RD-PO 1859/2026 OBRA 031260035101/07 PARECER COEP: REDIRECIONADO PARA O POSTO DO COCM´S EQUIPAMENTO CHEGOU NO LOCAL, FAVOR ENTRAR EM CONTATO COM O DMSL, DEVIDO A URGÊNCIA DO EQUIPAMENTO EM OPERAÇÃO.30/06 PARECER COEP: DEVIDO A ALINHAMENTO COM COI UTILIZAREMOS PARTE ATIVA QUE ORIGINALMENTE FOI ENCOMENDADA PARA 7933726256PARECER DMSL: N° do Equipamento: _RLG 7933726256 MateirosTipo de Equipamento: _RLG NOJA RC 10 REL IIData: _06/05/2026SID: _2288/2026-Serviço Executado: _Equipamento com defeito na parte ativa, será necessário fazer a substituição da parte ativa e fazer melhoria na malha de terra!Equipamento ficou em operação?: _NaoPendência: _SimBateria(s) substituída(s)? NÃOData Fabricação/Instalação da(s) bateria(s):_06/2025Equipe: _Benvindo e Almir-------------------------------------------------------------------------------Religador 7933726256, sem comunicação apos primeiroa ataque não retornou as comunicação. | W17: 15 | X17: 10 | Y17: 15 | Z17: 15 | AA17: 15 | AB17: 10 | AC17: 0 | AD17: 15 | AE17: 95 | AF17: Muito Alta | AG17: Transferência da cidade de Mateiros (733 UCs) para o gerador
A18: 7933766059 | B18: 79 | C18: TAQUARALTO | D18: TAQUARALTO | E18: CENTRO | F18: ETO-TELE 01024/2026 | G18: Aguardando comissionamento | O18: SS ATENDIDA | S18: Em andamento | T18: Tanque | U18: 1 | V18: PARECER DA PROTEÇÃO:RECOMISSIONAR RELIGADOR, AJUSTES DE PROTEÇÃO PERMANECEM OS MESMOS.Estagiário Rafael P Marques****************************PARECER COEP: EQUIPAMENTO ENTREGUE, SEGUE SS PARA O COCM´S , PARA REALIZAR O ATENDIMENTO,FAVOR ADICIONAR O PARECER PARA MANDAR PARA PROTEÇÃOSegue SS para verficar religador de poste 7933766059.Religador esta com defeito na parte ativa no tanque Porte gentilezaenviar equipe verificar.Endereço: TaquariPARECER DMSL: RLG 7933766059 RELÉ NOJA RC 10Mestre 2 Rep. taquaruçu GESID: 5457/2025Data: 15/10/2025Serviço Executado: Houve um curto na parte ativa do equipamento danificando a mesma, será necessário fazer a substituição somente do tanque, parte ativa.*Equipamento ficou em operação?:*Nao Pendência: Sim, substituir parte ativa.Equipe: Benvindo, Juliano e Sérgio.****** Parecer do COCM Centro***Equipámento Substituido em Campo pela Ordem de ServIÇO DLP-MPPA01 244/2026, ONDE OS RELATORIO ESTÃO ANEXADO.. | W18: 15 | X18: 20 | Y18: 5 | Z18: 15 | AA18: 15 | AB18: 0 | AC18: 10 | AD18: 15 | AE18: 95 | AF18: Muito Alta | AG18: Seccionamento de trecho do Setor Taquari
A19: 7900594026 | B19: 79 | C19: PONTE ALTA TOCANTINS | D19: PONTE ALTA TOCANTINS | E19: CENTRO | F19: ETO-SE-PA 00107/2026 | G19: Aguardando comissionamento | S19: Em andamento | T19: Tanque + controle | U19: 1 | V19: PARECER DA PROTEÇÃO:16/07/2026 AJUSTES DISPONIBILIZADOS NO APP DA PROTEÇÃO15/07/2026 EQUIPAMENTO SUBSTITUIDO NA OS ETO-RD-PO 1860 OBRA 031260035414/07/2026 PARECER COCM/ COEP: DE ACORDO COM O EDSON CURCINO FOI FEITA S SUBSTITUIÇÃO DO EQUIPAMENTO , SEGUE PARA PROTEÇÃO ELABORAR AJUSTE10/07 PARECER COEP: EQUIPAMENTO DESLOCADO QUE ESTAVA EM GUARAÍ FOI ALINHADO COM O VALMOR QUE SERIA SUBSTITUIDO DIA 07/07/2026 , FAVOR PASSAR PARA PROTEÇÃO 7900594026PARECER COEP: AGUARDANDO COCM'S PARA ABRIR REQUISIÇÃOPARECER DMSL 10/06/2026: Tem uma nota aberta para esse equipamento solicitando a substituição desde 20/10/2025, como a nota não foi atendida estamos repassando para área responsável. Nota em aberto repassada ETO-COEP 210/2025.Segue nota para verificar intermitência de comunicação nos religadores 7908301026 , 7911120026, 7947959026 , 7908692026, 7900594026 rural- Ponte Alta . | W19: 15 | X19: 20 | Y19: 15 | Z19: 15 | AA19: 15 | AB19: 0 | AC19: 0 | AD19: 15 | AE19: 95 | AF19: Muito Alta | AG19: Religador responsável pela proteção da barra da SE Ponte Alta (2381 UCs)
A20: 7921040031 | B20: 79 | C20: RIO DOS BOIS | D20: MIRACEMA DO TOCANTINS | E20: CENTRO | F20: CONCLUÍDA | S20: Ok | W20: 15 | X20: 20 | Y20: 5 | Z20: 15 | AA20: 15 | AB20: 10 | AC20: 0 | AD20: 15 | AE20: 95 | AF20: Muito Alta | AG20: Fonte principal de Rio dos Bois, RL de transferência operando
A21: 7957620015 | B21: 79 | C21: PEDRO AFONSO | D21: GUARAI | E21: NORTE | F21: CONCLUÍDA | S21: Ok | W21: 15 | X21: 20 | Y21: 15 | Z21: 15 | AA21: 15 | AB21: 0 | AC21: 0 | AD21: 15 | AE21: 95 | AF21: Muito Alta | AG21: Atendimento da RDU de Bom Jesus e parcial da RDU de Pedro Afonso
A22: 7927413001 | B22: 79 | C22: PORTO NACIONAL | D22: PORTO NACIONAL | E22: CENTRO | F22: ETO-COEP 00141/2026 | G22: Em processo de aquisição | S22: Pendente | T22: Tanque + controle | U22: 1 | V22: 22/07/2026 EQUIPAMENTO SLEECIONADO PARA COMPRAPARECER DMSL: *Segue feedback**Equipamento:* RLG 7927413001 *RELÉ TAVRIDA*Data:* 16/04/2026*SID:* 1817/2026*Serviço executado:* Placa de alimentação do equipamento com defeito, VERIFICAR SE É POSSIVEL substituir o equipamento completo.*Equipamento ficou em operação?*_Não*Pendência:*_Sim*Bateria(s) substituída(s)?*_Nao *Equipe:* Benvindo e Kaique-------------------------------------------------------------------------------------------------Religador 7927413001 sem comunicação foi realizado primeiro ataque porem a comunicação não retornou. Favor enviar equipe para devidas trattivas | W22: 15 | X22: 5 | Y22: 15 | Z22: 15 | AA22: 15 | AB22: 10 | AC22: 0 | AD22: 15 | AE22: 90 | AF22: Muito Alta | AG22: Transferência do Distrito Ind de Porto Nacional e GAs
A23: 7908686014 | B23: 79 | C23: PIUM | D23: PARAISO DO TOCANTINS | E23: CENTRO | F23: ETO-RD-PS 00302/2026 | G23: Concluído DCMD | R23: Verificar se já foi repassado | S23: Em andamento | T23: Tanque | U23: 1 | V23: 10/07 PARECER COEP: EQUIPAMENTO ENTREGUE AOS COCM´S FAVOR INFORMAR PRAZO DE SUBSTUIÇÃO PARA O DMSL E REPASSAR DEPOIS PARA PROTEÇÃO REALIZAR OS AJUSTES E DESCREVER NA SS O SERVIÇO REALIZADO06/07 PARECER COEP: PREVISÃO DE ENTREGA DE ACORDO COM CALENDÁRIO LOGISITCO NOVO 06/07NOTA DMSL: Favor substituir o tanque, ele não está efetuando os comandos enviados. Não substituir o controle pois o mesmo funciona como repetidor de outros equipamentos.Segue nota para verificar falha de fechamento religador 7908686014- Pium .OBS: equipamento não fechou local e remoto , fica sinalizando no painel para verificar alarmes ! | W23: 15 | X23: 20 | Y23: 0 | Z23: 15 | AA23: 15 | AB23: 10 | AC23: 0 | AD23: 15 | AE23: 90 | AF23: Muito Alta | AG23: Fonte principal de Pium, RL de transferência operando
A24: 5800440256 | B24: 58 | C24: MATEIROS | D24: PONTE ALTA TOCANTINS | E24: CENTRO | F24: CONCLUÍDA | S24: Ok | W24: 20 | X24: 20 | Y24: 20 | Z24: 10 | AA24: 20 | AB24: - | AC24: - | AD24: - | AE24: 90 | AF24: Muito Alta | AG24: Aumento de reclamações no atendimento de São Felix e Mateiros no período seco
A25: 7943790134 | B25: 79 | C25: ESPERANTINA | D25: AUGUSTINOPOLIS | E25: NORTE | F25: ETO-TELE 00896/2026 | G25: Aguardando comissionamento | O25: SS PENDENTE | P25: 46261 | S25: Em andamento | T25: Tanque | U25: 1 | V25: PARECER DCMD:Serviço realizado , substituição da parte ativa do RELIGADOR 7943790134 - Favor realizar comissionamento | W25: 15 | X25: 10 | Y25: 5 | Z25: 15 | AA25: 15 | AB25: 10 | AC25: 0 | AD25: 15 | AE25: 85 | AF25: Muito Alta | AG25: Transferência de Esperantina, fonte principal operando
A26: 7900453110 | B26: 79 | C26: SANTA RITA DO TOCANTINS | D26: PORTO NACIONAL | E26: CENTRO | F26: ETO-COEP 00087/2026 | G26: Em processo de aquisição | R26: Previsão de entrega 20/10 | S26: Pendente | T26: Tanque | U26: 1 | V26: 10/07/2026 EQUIPAMENTO SELECIONADO PARA COMPRA PARTE ATIVA30/06.PARECER COEP: ALINHADO COM O ALLAN REMANEJAMOS PARTE ATIVA PARA ATENDER 7933726256PARECER COEP: Aproveitar controle cooper se possível em outro local, previsão de chegada do material dia 01/07 para substituiçãoFavor verificar o RL 7900453110, pois o mesmo aceita comando de fechamento, porém fecha em campo e no SCADA continua aberto e só abre através de equipe em campo. Parecer Dmsl:Equipamento está com defeito na parte ativa, não aceita o comando de fechamento. Será necessário substituir o equipamento completo.Equipamento ficou em operação?: _SIM_a pedido do COS ficou em operação, a operação está ciente da necessidade de substituir.Pendência: Sim, será necessário substituir o equipamento. | W26: 15 | X26: 10 | Y26: 5 | Z26: 15 | AA26: 15 | AB26: 10 | AC26: 0 | AD26: 15 | AE26: 85 | AF26: Muito Alta | AG26: Transferência de Santa Rita, fonte principal operando
A27: 7925871077 | B27: 79 | C27: GOIATINS | D27: ARAGUAINA | E27: NORTE | F27: ETO-COEP 00048/2026 | G27: Em processo de aquisição | R27: Previsão de entrega 20/10 | S27: Pendente | T27: Tanque | U27: 1 | V27: 30/06 PARECER COEP: AGUARDANDO RETORNO DO DMSLPARECER DMSL: A PEDIDO DA PCM DO NORTE LARA SOARES REALIZEI A CRIAÇÃO DESSA SS, EM RAZAO DA ANTIGAETO-TELE 337/2026 QUE FOI BAIXADA POR ENGANO DE TAL FORMA SEGUE A MESMA PARA REALIZAR AS TRATATIVAS. PENDENCIA: Religador continua by passado, equipamento está com defeito na parte ativa | W27: 15 | X27: 10 | Y27: 15 | Z27: 15 | AA27: 15 | AB27: 10 | AC27: 0 | AD27: 0 | AE27: 80 | AF27: Muito Alta | AG27: Transferência de Goiatins e GAs (2492 UCs)
A28: 5803327001 | B28: 58 | C28: PORTO NACIONAL | D28: PORTO NACIONAL | E28: CENTRO | F28: ETO-COEP 00149/2026 | G28: Em processo logístico | R28: Previsão de entrega 10/08 | S28: Em andamento | T28: Controle e aterramento | U28: 1 | V28: 01/07 PARECER COEP: FOI CONFIRMADO COM A OPERAÇÃO QUE O EQUIPAMENTO SEGUIU O FLUXO INTEIRO DE COMISSIONAMENTO, PROTEÇÃO, FAVOR EXPLICAR O QUE FOI REALIZADO E SE EQUIPAMENTO ESTÁ OPERANDO, SENÃO ESTIVER EXPLICAR O QUE FOI FEITO NELE30/06PARECER COEP: REPASSAR DIRETAMENTE PARA OS COCM'SRegulador 5803327001 fora de operação, by passado em campo com painel de comunicação com cabos desconectados tensão 13.8.parecer DMSL: Feedback Equip. EspeciaisRT 5803327001RELÉ RUASid: 4844Data: 19/09/2025Serviço realizado:*Equipamento foi remanejado, 7 km da sua localização sentido Palmas necessário comissionamento completo*Equipamento com um dos cabos umbilicais danificado.* aterramento bucha FC não esta interligada corretamente * para-raios estão no mesmo aterramento da bucha FC.* Tranques muito alto e próximo da rede não permitindo o comissionamento com segurança.* Controle alto demais tem que baixar Equipamento ficou em operação?: nãoPendência: sim, precisa comissionar completoOBS | W28: 40 | X28: 0 | Y28: 0 | Z28: 20 | AA28: 20 | AB28: - | AC28: - | AD28: - | AE28: 80 | AF28: Alta | AG28: Em caso de perca da fonte principal é necessário esse RT para alimentação da Frísia
A29: 7900230155 | B29: 79 | C29: PALMEIRANTE | D29: COLINAS DO TOCANTINS | E29: NORTE | F29: ETO-PROT 00143/2026 | G29: Em fase de ajustes | S29: Em andamento | T29: Tanque e PR do trafo e chave | U29: 1 | V29: 07/07/2026 PARECER COEP: MATERIAL ENVIADO , CONFORME ALINHANDO COM O WANDER REALIZAR SUBSTIUIÇÂO DO EQUIPAMENTO, FAVOR ESCREVER PARECER COCM ANTES DE PASSAR PARA PROTEÇÂO, DO QUE FOI REALIZADO01/07/2026 PARECER COEP: PROBLEMA NO ENVIO DO MATERIAL PARECER DMSL: Religador está com o tanque danificado. Não responde a comandos abertura e fechamento local ou remoto, pois está com sinal de curto circuito. Necessário trocar o equipamento. Para raio do trafo está queimado. Chave de saída da fase C está com o olhal quebrado, necessário substituir a chave. Equipamento ficou bypassado em campo. Aberto entrada e saída, com exceção da fase C de saída que ficou fechada. Favor, substituir equipamento completo por NOJA RC10 e sanar demais pendencias.Senhores Favor verificar RL 7900230155 o mesmo sinalizou aberto no SCADA porem a cidade de Palmeirante estava normal , feito um reset no rl e o mesmo subiu fechado.08/07/2026 PARECER DCMD: EQUIPE ETO-LVGR01 DE GUARAI ESTEVE NO RL 7900230155 DIA 25-06-2026 E FEZ TODAS A PENDENCIAS DO RL, OBS: EQUIPE SO NAO CONECTOU O CABO DO TRAFO NO RL. RL ESTA PRONTO PARA O COMISSIONAMENTO | W29: 15 | X29: 20 | Y29: 5 | Z29: 15 | AA29: 0 | AB29: 10 | AC29: 0 | AD29: 15 | AE29: 80 | AF29: Muito Alta | AG29: Fonte principal de Palmeirante, RL de transferência operando
A30: 7900543083 | B30: 79 | C30: APARECIDA DO RIO NEGRO | D30: TAQUARALTO | E30: CENTRO | S30: Ok | W30: 15 | X30: 20 | Y30: 5 | Z30: 15 | AA30: 0 | AB30: 0 | AC30: 10 | AD30: 15 | AE30: 80 | AF30: Muito Alta | AG30: Atendimento da RDU de Aparecida do Rio Negro
A31: 7900930040 | B31: 79 | C31: ARAGOMINAS | D31: ARAGUAINA | E31: NORTE | F31: CONCLUÍDA | S31: Ok | W31: 15 | X31: 20 | Y31: 5 | Z31: 15 | AA31: 0 | AB31: 0 | AC31: 10 | AD31: 15 | AE31: 80 | AF31: Muito Alta | AG31: Proteção da baixa do TF de força da SE Aragominas
A32: 7931383086 | B32: 79 | C32: MARIANOPOLIS | D32: DIVINOPOLIS | E32: CENTRO | F32: CONCLUÍDA | S32: Ok | W32: 15 | X32: 20 | Y32: 5 | Z32: 15 | AA32: 0 | AB32: 10 | AC32: 0 | AD32: 15 | AE32: 80 | AF32: Muito Alta | AG32: Fonte principal de Marianópolis, RL transferência operando
A33: 7908302256 | B33: 79 | C33: MATEIROS | D33: PONTE ALTA TOCANTINS | E33: CENTRO | F33: ETO-TELE 00997/2026 | G33: Primeiro ataque DMSL | O33: SS ATENDIDA | V33: RL teve nota baixada (ETO-TELE 970/2026) pore´m eqp continua fora de operação, solicito programação para equipe verificar em campo | W33: 5 | X33: 10 | Y33: 5 | Z33: 15 | AA33: 15 | AB33: 10 | AC33: 0 | AD33: 15 | AE33: 75 | AF33: Alta | AG33: Isolação de trecho e transferência das cidades de São Felix e Mateiros para gerador, além de atendimento de clientes rurais
A34: 5800371025 | B34: 58 | C34: ARAPOEMA | D34: COLINAS DO TOCANTINS | E34: NORTE | F34: ETO-RD-GR 00766/2026 | G34: Equipamento entregue ao COCM | R34: Previsão de substituição 28/07 | S34: Em andamento | T34: Controle | U34: 1 | V34: 16/07/2026 PARECER COEP: ALINHADO COM O KELLITON REALIZAR SUBSTITUIÇÃO DO CONTROLE DE TUPIRAMA, ALINHADO COM O JEAN QUE OS CABOS COMPATIBILIZADORES VÃO CHEGAR 16/08 , ATÉ ESSA DATA MANTER ESSA SS E CONTROLE RUA, DEPOIS REPASSAR PARA O DMSLPARECER COEP: AVALIAR COM O LEANDRO, PROVAVELMENTE SÓ COMPRAPARECER DMSL: Após testes foi constatado defeito nos relés da fase A e B, Modelo Toshiba TBR 1000. Se possível, substituir os relés das 3 fases por controle RUA, disponibilizar os cabos de ligação entre o tanque e o controle para possibilitar a compatibilização do equipamento. Fornecer kit de comunicação, rádio, antena, etc.Segue nota para veriifcar falha em regulador de tensão N: 5800371025 dentro S/E Arapoema , equipamento esta com 2 reles com falha marca toshiba . | W34: 0 | X34: 20 | Y34: 20 | Z34: 10 | AA34: 20 | AB34: - | AC34: - | AD34: - | AE34: 70 | AF34: Alta | AG34: Aumento de reclamações no atendimento de Arapoema no período seco
A35: 7926089013 | B35: 79 | C35: PARAISO DO TOCANTINS | D35: PARAISO DO TOCANTINS | E35: CENTRO | F35: ETO-COEP 00078/2026 | G35: Em processo de aquisição | R35: Previsão de entrega 20/10 | S35: Pendente | T35: Tanque | U35: 1 | V35: PARECER COEP: EQUIPAMENTO SELECIONADO PARA COMPRAPARECER DMSL: Feedback Equip. EspeciaisRLG 7926089013,RELÉ NOJA RC10SID 1805/2026DATA 15/04/2026Serviço Executado: Favor realizar a troca da parte ativa do equipamento --reprogramar para atualizar a base juntamente com escada Equipamento ficou em operação: Não Pendência: sim atualizar a base e subistituir o tanque Bateria(s) substituída(s)? Não Data de Fabricação/Instalação da(s) bateria(s): Equipe: Carliel e João Vitor Fernando e Elson---------------------------------------------------------------------------------ATUALIZAR AJUSTES DO RL 7926089013 LD PARAISO I A PIUM. IMPLEMENTAÇÃO DA FUNÇÃO 27, SUBTENSÃO.AJUSTES DISPONIVEIS NO APP DA PROTEÇÃO. | W35: 15 | X35: 10 | Y35: 5 | Z35: 15 | AA35: 15 | AB35: 10 | AC35: 0 | AD35: 0 | AE35: 70 | AF35: Alta | AG35: Transferência da RDU de Chapada de Areia (937 UCs) para fonte alternativa
A36: 7925087021 | B36: 79 | C36: PARANA | D36: PEIXE | E36: SUL | F36: ETO-PROT 00152/2026 | G36: Em fase de ajustes | S36: Em andamento | T36: Tanque | U36: 1 | V36: 10/07 PARECER COEP: EQUIPAMENTO ENTREGUE AOS COCM´S FAVOR INFORMAR PRAZO DE SUBSTUIÇÃO PARA O DMSL E REPASSAR DEPOIS PARA PROTEÇÃO REALIZAR OS AJUSTES E DESCREVER NA SS O SERVIÇO REALIZADOPARECER COEP: EM ROTA DE ENTREGA, VERIFICAR PREVISÃO DE CHEGADARealizar a substituição do tanque do equipamento. | W36: 15 | X36: 10 | Y36: 5 | Z36: 0 | AA36: 15 | AB36: 10 | AC36: 0 | AD36: 15 | AE36: 70 | AF36: Alta | AG36: Primeiro RL do 414R de Paranã, RL a jusante na LD também está bay-passado (630 UCs)
A37: 5801866013 | B37: 58 | C37: PARAISO DO TOCANTINS | D37: PARAISO DO TOCANTINS | E37: CENTRO | F37: ETO-PROT 00151/2026 | G37: Em fase de ajustes | S37: Em andamento | T37: Célula | U37: 1 | V37: 15/07 PARECER COCM, FOI ATENDIDA PELA OS ETO-RD-PS 1616/2026 OBRA-021260053910/07 PARECER COEP: EQUIPAMENTO ENTREGUE AOS COCM´S FAVOR INFORMAR PRAZO DE SUBSTUIÇÃO PARA O DMSL E REPASSAR DEPOIS PARA PROTEÇÃO REALIZAR OS AJUSTES E DESCREVER NA SS O SERVIÇO REALIZADOPARECER COEP: EM PROCESSO DE ENTREGAPARECER DMSL: RT 5801866013Serviço Executado: Feito a medição da malha de terra. Identificado infiltração na caixa de passagem da célula da fase C do banco regulador de tensão, será necessário fazer a substituição da mesma! Ficar atento na hora da substituição, deverá ser substituída a célula do lado da BR.Obs.: Será necessário baixar todo o banco pelo menos um metro, as buchas estão muito próximas a parte energizada não oferecem segurança para equipe no momento do ensaio elétrico.Equipamento ficou em operação?: Não Possui nobreak: SimPossui antena: SimPossui rádio:SimPendência: SimData da bateria: Equipe: Benvindo e Kaique._______________________________________________RT 5801866013BY PASSADO DEVIDO DEFEITO EM CELULA BEMVINDO ESTEVE NO LOCAL JUNTO AO COD .NECESSARIO TRATATIVA PARA MESMA .FASE DANIFICADO C | W37: 0 | X37: 20 | Y37: 20 | Z37: 20 | AA37: 10 | AB37: - | AC37: - | AD37: - | AE37: 70 | AF37: Alta | AG37: Atendimento da RDU Luzimangues Industrial por fonte alternativa
A38: 5865120195 | B38: 58 | C38: CENTENARIO | D38: GUARAI | E38: NORTE | F38: ETO-PROT 00144/2026 | G38: Em fase de ajustes | S38: Em andamento | T38: Melhoria de aterramento | U38: 1 | V38: PARECER DMSL:PENDÊNCIA: Realizar melhoria no aterramento por ser tratar de um terreno muito arenoso, e há pendências por parte do time da proteção, os ajustes do RT não estão disponíveis para inserção no referido equipamento.DATA DA MANUTENÇÃO: 12/03/202EQUIPE: Brunno e Edeglan.***********************PARECER DA PROTEÇÃO:FAVOR COMISSIONAR REGULADOR 5865120195 – LD Santa Maria Ramal Centenário e Recursolândia – 34,5kV. AJUSTE REALIZADO, DISPONÍVEL NO APP DA PROTEÇÃO.*********************** INSTALADO NA OBRA 0702400720 GENTILEZA, REALIZAR O COMISSIONAMENTO.LAUDO EM ANEXO.COORD EO: 889017, 901685708-07-2026 PARECER: FOI FEITO A MELHORIA NO REGULADOR CONFORME FOTOS EM ANEXO. | W38: 20 | X38: 20 | Y38: 20 | Z38: 10 | AA38: 0 | AB38: - | AC38: - | AD38: - | AE38: 70 | AF38: Alta | AG38: Atendimento das RDUs de Centenário, Recursolândia e clientes rurais
A39: 5853360007 | B39: 58 | C39: MIRACEMA DO TOCANTINS | D39: MIRACEMA DO TOCANTINS | E39: CENTRO | F39: ETO-RD-PS 00323/2025 | G39: Problema na autorização de passagem | R39: Cliente não autorizou entrar na propriedade | T39: Melhoria de aterramento | U39: 1 | V39: REALIZAR TESTES NO EQUIPAMENTO E CONFERIR MEDIÇÕES DA MALHA DE ATERRAMENTO. ESTANDO OK, COMISSIONAR EQUIPAMENTO E COLOCA-LO EM OPERAÇÃO.AJUSTES DISPONIVEIS NO APP DA PROTEÇÃdmsl : N° do Equipamento:*RT 5853360007 MIRACEMASID: 2493/2025Data: 13/05/2025Serviço Executado Provavelmente ocorreu uma descarga no equipamento comprometendo a malha!Será necessário fazer melhoria da malha de aterramento, fazer toda interligação da mesma! Feito ensaios de isolação das 3 células do equipamento, isolação está ok, quando retornar para colocar em operação levar 3 baterias de 7a.Equipamento ficou em operação?: Não Equipe: Benvindo e Jardel | W39: 0 | X39: 20 | Y39: 20 | Z39: 10 | AA39: 20 | AB39: - | AC39: - | AD39: - | AE39: 70 | AF39: Alta | AG39: Aumento de reclamações no atendimento de Miracema no período seco
A40: 5800366016 | B40: 58 | C40: WANDERLANDIA | D40: TOCANTINOPOLIS | E40: NORTE | F40: CONCLUÍDA | S40: Ok | W40: 0 | X40: 20 | Y40: 20 | Z40: 20 | AA40: 10 | AB40: - | AC40: - | AD40: - | AE40: 70 | AF40: Alta | AG40: Aumento de reclamações no atendimento de Wanderlândia no período seco
A41: 7955523028 | B41: 79 | C41: NATIVIDADE | D41: DIANOPOLIS | E41: SUL | F41: CONCLUÍDA | S41: Ok | W41: 15 | X41: 10 | Y41: 5 | Z41: 15 | AA41: 15 | AB41: 10 | AC41: 0 | AD41: 0 | AE41: 70 | AF41: Alta | AG41: Equipamento para apoio na transferência de cargas na região de Natividade
A42: 7900573047 | B42: 79 | C42: FIGUEIROPOLIS | D42: ALVORADA | E42: SUL | F42: ETO-PROT 00153/2026 | G42: Em fase de ajustes | S42: Em andamento | T42: Tanque + controle | U42: 1 | V42: 10/07 PARECER COEP: EQUIPAMENTO ENTREGUE AOS COCM´S FAVOR INFORMAR PRAZO DE SUBSTUIÇÃO PARA O DMSL E REPASSAR DEPOIS PARA PROTEÇÃO REALIZAR OS AJUSTES E DESCREVER NA SS O SERVIÇO REALIZADOPARECER COEP: AGUARDANDO COCM'S GERAREM AS OBRAS PARA PODER ENTREGAR MATERIALFavor providenciar manutenção no RL 7900573047, o mesmo estar em curto conforme fotos anexadas. Equipamento ficou bay passado em campo.PARECER DMSL: Equipe: FABIO AP./JOÃO MARCOSData Executada: 15/10/2025Serviço Executado:Foi constatado que o equipamento esta queimado na parte ativa placa, tanque e relé. Por favor fazer a substituição pelo Noja RC10. | W42: 5 | X42: 5 | Y42: 15 | Z42: 0 | AA42: 15 | AB42: 10 | AC42: 0 | AD42: 15 | AE42: 65 | AF42: Alta | AG42: Transferência da Bunge, Saneatins e secadora
A43: 7953610256 | B43: 79 | C43: MATEIROS | D43: PONTE ALTA TOCANTINS | E43: CENTRO | F43: ETO-RD-PO 00208/2026 | G43: Concluído DCMD | R43: Pendente laudo da empreteira | T43: Tanque e cabo umbilical | U43: 1 | V43: 14/07/2026 - PARECER COEP: REALOCAR TANQUE 34,5 SOBRESSALENTE DE PARAÍSO PARA ATENDER PARECER DMSL: Data: 10/03/2026,Serviço Executado: Foi substituído o relé do equipamento, o mesmo estava danificado. Trocado o DPS, o mesmo estava queimado devido ao tanque estar furado. O equipamento ficou em bypass.Equipamento ficou em operação? NãoPendência? Sim, substituir a parte ativa com cordão umbilical.Equipe: Carliel e João VitorSEGUE SS PARA REGULARIZAR AUTOMAÇÃO DO RL 7953610256 NA INTERLIGAÇÃO COM A COELBA (CHAPADA DA MANGABEIRA) - EQUIPE INFOMOU CURTO INTERNO NO GABINETE DJ AC NÃO FECHA | W43: 5 | X43: 5 | Y43: 15 | Z43: 15 | AA43: 0 | AB43: 0 | AC43: 10 | AD43: 15 | AE43: 65 | AF43: Alta | AG43: Atenidmento da COELBA (Alto potencial de compensação)
A44: 5800438116 | B44: 58 | C44: CHAPADA DA NATIVIDADE | D44: DIANOPOLIS | E44: SUL | F44: ETO-RD-DP 00404/2026 | G44: Concluído DCMD e DMSL | R44: Previsão de substituição 07/08 | S44: Em andamento | T44: Célula | U44: 2 | V44: 01/07 PARECER COEP: DENER INFORMOU QUE TEM AS PEÇAS SOBRESSALENTES DE OBRA PARA UTILIZAR, REPASSEREI AO POSTO DO ETO-RD-DP PARA AS TRATATIVAS, FAVOR INFORMAR PREVISÃO DE SUBSTIUIÇÃO E PREENCHER A PLANILHA ASSIM COMO PREENCHER A DESCRIÃO ANTES DE PASSAR PARA PROTEÇÃO FAZER OS AJUSTES30/06PARECER COEP: AGUARDANDO COCM'S CRIAREM OBRA PARA ENTREGA DO MATERIALSegue nota para normalizar falha em regulador N:5800438116 - Chapada da natividade .equipamento está com fase B e C travada .OBS: a fase B esta sinalizando falha , equipamento não insere TAP negativo na fase B e C , o mesmo ficou no TAP zerado e bloqueado .PARECER DMSL (18/08/2025): Foi feito teste de elevar e abaixar nas fases B e C e o mesmo só aceita elevar os taps, constatando que o mercanismo da chave reversoura polaridade está com defeito. Número de série fase B EI7030 e Número de série fase C EI7040. Substituir as fases B e C.Foi constatado que a placa F do controle está com defeito. | W44: 0 | X44: 20 | Y44: 20 | Z44: 20 | AA44: 0 | AB44: - | AC44: - | AD44: - | AE44: 60 | AF44: Média | AG44: Atendimento da região da Engegold, Nativa, cidade Natividade e Chapada da Natividade (Fonte alternativa)
A45: 5800090147 | B45: 58 | C45: TAIPAS DO TOCANTINS | D45: DIANOPOLIS | E45: SUL | F45: CONCLUÍDA | S45: Ok | W45: 0 | X45: 20 | Y45: 20 | Z45: 10 | AA45: 10 | AB45: - | AC45: - | AD45: - | AE45: 60 | AF45: Média | AG45: Atendimento de Taipas
A46: 5840227063 | B46: 58 | C46: BANDEIRANTES DO TOCANTINS | D46: COLINAS DO TOCANTINS | E46: NORTE | F46: ETO-COEP 00151/2026 | G46: Em processo de aquisição | S46: Pendente | T46: Célula | U46: 1 | V46: PARECER DMSL 13/07/2026: Realizados ensaios de isolação nas três células, e foi identificado curto na fase A, sendo necessário a sua substituição. Os cabos das buchas ficaram desconectados para melhor identificação no momento da sua substituiçãSEGUE PARA O DMSL AVALIAR ANTES DE SEGUIRMOS COM O SERVIÇOSEGUE PARA REALIZAR TROCA---------------------------------------------------------Boa noite,Segue SS para tratativas regulador de tensão 5840227063 fase C em curto | W46: 0 | X46: 20 | Y46: 20 | Z46: 10 | AA46: 10 | AB46: - | AC46: - | AD46: - | AE46: 60 | AF46: Média | AG46: Atendimento da RDU Bandeirantes e clientes rurais
A47: 5846328094 | B47: 58 | C47: PEIXE | D47: PEIXE | E47: SUL | F47: ETO-TELE 00986/2026 | G47: Aguardando comissionamento | O47: SS PENDENTE | P47: 24/08/206 | S47: Em andamento | T47: Melhoria de aterramento | U47: 1 | V47: COCM SUL - 07/07/2026 - FOI REALIZADO MELHORIA DE ATERRAMENTO E FEITO A MANUTENÇÕES E TODAS AS CHAVES E SUBSTITUIDO OS CONECTORES.PARECER COEP: MELHORIA DE ATERRAMENTO É COCM'S, FAVOR ENCAMINHAR DIRETAMENTE PARA ELES, COCM'S REALIZAR MELHORIA DE ATERRAMENTO POR FAVORPor genteliiza verificar RT 5846328094 situação de equipamento, se encontra by passado em campoPARECER DMSL:Favor, realizar melhoria de aterramento que se encontra alta e substituir todos os conectores das buchas por conectores estrangulador. | W47: 0 | X47: 20 | Y47: 20 | Z47: 10 | AA47: 10 | AB47: - | AC47: - | AD47: - | AE47: 60 | AF47: Média | AG47: Atendimento da RDU Sucupira e clientes rurais
A48: 5851753086 | B48: 58 | C48: MARIANOPOLIS | D48: DIVINOPOLIS | E48: CENTRO | F48: ETO-TELE 00881/2026 | G48: Aguardando comissionamento | O48: SS ATENDIDA | S48: Em andamento | T48: Melhoria de aterramento | U48: 1 | V48: PARECER DMSL: FAVOR SOLUCIONAR PENDENCIAS RT: 5851753086Relé R.U.A Data: _19/05/2026Sid: 2740/2026Possui rádio?: SimPossui antena?: SimPossui módulo nobreak?: SimServiço Executado: * Feito testes no equipamento,o mesmo está normal.* Será necessário fazer melhorias na malha de terra e colocar em operação.Equipamento ficou em operação? Não Pendência: Sim. É necessário fazer melhorias na malha de aterramento.Bateria(s) substituída(s)? _nao Data Fabricação/Instalação da(s) bateria(s): 12/2025Equipe: Jean e BenvindoPARECER DCMD: FEITO MELHORIA NA MALHA DO ATERRAMENTO, FAVOR ENVIAR EQUIPE PARA COLOCA-LO EM OPERAÇÃORT 5851753086MESMO ESTA BY-PASSADO EM CAMPO EQUIPE SINERGIA 086OP01 ESTEVE NO LOCAL APARENTIMENTE SEM DEFEITO APARENTE MESMO FOI BY PASSADO POR TER TIRADO LINHA.DESDE ENTAO MESMO NAO VOLTOU PARA OPERAÇÃO .FAVOR VERIFICAR PARA TESTES POSSIVEIS .PARA QUE O MESMO VOLTA COM DISPONIBILIDADE PARA OPERAÇÃO . | W48: 0 | X48: 20 | Y48: 20 | Z48: 10 | AA48: 10 | AB48: - | AC48: - | AD48: - | AE48: 60 | AF48: Média | AG48: Atendimento da RDU Marianópolis e clientes rurais
A49: 7903112004 | B49: 79 | C49: ARAGUAINA | D49: ARAGUAINA | E49: NORTE | F49: ETO-COEP 00184/2025 | G49: Concluído DCMD | R49: Verificar se já foi repassado | S49: Em andamento | T49: Tanque | U49: 1 | V49: 20/07 PARECER COEP: EQUIPAMENTO SELECIONADO PARA COMPRAApós testes no RLG 7903112004 foi constatado defeito no mesmo e como se trata de um modelo COOPER FORM6 que está obsoleto e não possuímos peças sobressalentes, faz-se necessária substituição completa por modelo NOJA RC10. | W49: 15 | X49: 10 | Y49: 5 | Z49: 15 | AA49: 0 | AB49: 10 | AC49: 0 | AD49: 0 | AE49: 55 | AF49: Alta | AG49: Transferência de Babaçulândia, 4 RLs sendo 2 operando
A50: 7920024127 | B50: 79 | C50: PALMEIRAS DO TOCANTINS | D50: TOCANTINOPOLIS | E50: NORTE | F50: ETO-COEP 00120/2025 | G50: Em processo de aquisição | S50: Pendente | T50: Tanque + controle e chave | U50: 1 | V50: 30/06 PARECER COEP: AGUARDANDO O RETORNO DO DMSL , PARA ENTENDER SE O PROBLEMA É NA COMUNICAÇÃO OU PARTE ATIVA, JÁ QUE O EQUIPAMENTO EM QUESTÃO SEGUE COMUNICANDOPARECER DMSL: Após testes, equipe DMSL constatou que o relé e a parte ativa do equipamento 7920024127 estão com defeito, sendo necessária a substituição completa por um modelo NOJA RC 10. Favor, subsituir também a chave de saída da fase A que está com o anel de abertura quebrado.RL 7920024127 está desarmando em campo e no SCADA continua fechado, só sinaliza aberto no SCADA quando a equipe faz o resert no equipamento em campo. | W50: 15 | X50: 10 | Y50: 5 | Z50: 15 | AA50: 0 | AB50: 10 | AC50: 0 | AD50: 0 | AE50: 55 | AF50: Alta | AG50: Transferência de Palmeiras, 3 fontes operando
A51: 7927646026 | B51: 79 | C51: PONTE ALTA TOCANTINS | D51: PONTE ALTA TOCANTINS | E51: CENTRO | F51: ETO-COEP 00029/2026 | G51: Em processo de aquisição | S51: Pendente | T51: Tanque | U51: 1 | V51: PARECER COEP: EQUIPAMENTO SELECIONADO PARA COMPRARELIGADOR BY PASSADO POR DEFEITO, NECESSÁRIO AVALIAÇÃO DO PROBLEMA.parecer dmsl:O religador apresenta defeito no tanque, sendo necessário substituir o tanque o mesmo está tirando a linha, e troca os isoladores. Quando retornar, trazer uma fonte para o equipamento, a mesma foi removida.FICOU EM OPERAÇÃO? NãoPENDÊNCIA: Sim, aguardando peças para substituição. | W51: 15 | X51: 10 | Y51: 5 | Z51: 0 | AA51: 15 | AB51: 0 | AC51: 10 | AD51: 0 | AE51: 55 | AF51: Alta | AG51: Opção de isolação de São Félix e Mateiros para alimentação por gerador
A52: 7927169001 | B52: 79 | C52: PORTO NACIONAL | D52: PORTO NACIONAL | E52: CENTRO | F52: ETO-PROT 00156/2026 | G52: Em fase de ajustes | S52: Em andamento | T52: Tanque | V52: PARECER COEP: EQUIPAMENTO ENTREGUE, SEGUE SS PARA O COCM´S , PARA REALIZAR O ATENDIMENTO,FAVOR ADICIONAR O PARECER PARA MANDAR PARA PROTEÇÃOSS ANTIGA: 1500/2025 PARECER DMSL: Serviço Executado: Foi verificado que o tanque do equipamento está danificado, sendo necessário substituir o tanque do equipamento.Equipamento ficou em operação?: NãoPendência: Sim, instalar fonte, disjuntor e DPS, e substituir o tanque.***** Parecer COCM******Subsituido Tranque do RL pela Ordem de Serviço DLP-MPPA01 247/2026 RELATORIO EM ANEXO DA O.S EXECUTORA | W52: 5 | X52: 5 | Y52: 15 | Z52: 0 | AA52: 15 | AB52: 0 | AC52: 0 | AD52: 15 | AE52: 55 | AF52: Alta | AG52: Transferência dos Grupos A - VLI e Frisia
A53: 7900018004 | B53: 79 | C53: ARAGUAINA | D53: ARAGUAINA | E53: NORTE | F53: CONCLUÍDA | S53: Ok | W53: 15 | X53: 10 | Y53: 5 | Z53: 15 | AA53: 0 | AB53: 10 | AC53: 0 | AD53: 0 | AE53: 55 | AF53: Alta | AG53: Transferência de Aragominas, 3 fontes operando
A54: 7934698002 | B54: 79 | C54: TOCANTINOPOLIS | D54: TOCANTINOPOLIS | E54: NORTE | F54: CONCLUÍDA | S54: Ok | W54: 5 | X54: 5 | Y54: 5 | Z54: 0 | AA54: 15 | AB54: 0 | AC54: 10 | AD54: 15 | AE54: 55 | AF54: Alta | AG54: Atendimento do PA Mumbuca (106 UCs), no desarme a jusante penaliza parte da RDU de Tocantinópolis (1384 UCs)
A55: 7930428001 | B55: 79 | C55: PORTO NACIONAL | D55: PORTO NACIONAL | E55: CENTRO | F55: ETO-COEP 00150/2026 | G55: Em processo de aquisição | S55: Pendente | T55: Tanque | U55: 1 | V55: PARECER DMSL DATA 16/07/2026: será necessário fazer a substituição da parte ativa do equipamento.PARECER COEP: Equipamento Funcionando no SCADA , favor reavaliar a necessidade de substituição e se necessário mandar o modelo do equipamento.Segue nota para substituir Taque do RL-7930428001 na LD Porto Nacional / São João, Identificado pela Int-20253617520441 equipamento dando passagem na fase A ficou bay-passado até substituição, Tensão 34,5kva, Acesso livre. | W55: 5 | X55: 5 | Y55: 15 | Z55: 0 | AA55: 15 | AB55: 10 | AC55: 0 | AD55: 0 | AE55: 50 | AF55: Alta | AG55: Transferência dos Grupos A - Ramal do Rossato (TF 225kVA e TF 750kVA)
A56: 7936038076 | B56: 79 | C56: DUERE | D56: GURUPI | E56: SUL | F56: CONCLUÍDA | G56: Em processo de aquisição | R56: Cancelada errada pelo DMSL | S56: Pendente | W56: 5 | X56: 5 | Y56: 15 | Z56: 0 | AA56: 15 | AB56: 10 | AC56: 0 | AD56: 0 | AE56: 50 | AF56: Alta | AG56: Transferência do Grupo A - Xavante (TF 1087,5 kVA) e outros GA menores
A57: 7955520116 | B57: 79 | C57: CHAPADA DA NATIVIDADE | D57: DIANOPOLIS | E57: SUL | F57: CONCLUÍDA | G57: Em processo de aquisição | R57: Cancelada errada pelo DMSL | S57: Pendente | T57: Tanque | U57: 1 | W57: 5 | X57: 5 | Y57: 15 | Z57: 0 | AA57: 0 | AB57: 10 | AC57: 0 | AD57: 15 | AE57: 50 | AF57: Alta | AG57: Transferência do Grupo A - Engegold (TF 7500 kVA)
A58: 5800291035 | B58: 58 | C58: MONTE DO CARMO | D58: PONTE ALTA TOCANTINS | E58: CENTRO | F58: ETO-RD-PO 00097/2026 | G58: Aguardando comissionamento | S58: Em andamento | T58: Melhoria de aterramento | U58: 1 | V58: PARECER DMSL: Feito testes funcionais nas 3 células do banco as mesmas corresponderam aos testes. Será necessário fazer a correção da malha de terra, baixar o banco completo pois está muito alto dificultando as atividades da equipe, substituir as 3 chaves facas do lado Fonte e as 3 do lado Carga instalar suporte inclinado das chaves para facilitar as manobras. Colocar cinta no controle RUA abaixar o mesmo, pois está muito alto e fixado com um mosquetão oval, quando retornar para colocar em operação levar 3 baterias de 7a e rele rua.Obs.: Fizeram melhoria na malha de terra, mas não está dentro do aceitável! As outras pendências continuam, favor corrigir. Equipamento ficou em operação?: Não - Equipe: Benvindo e Kaique- SS ANTIGA ETO-TELE 358/2026 | W58: 0 | X58: 20 | Y58: 20 | Z58: 10 | AA58: 0 | AB58: - | AC58: - | AD58: - | AE58: 50 | AF58: Média | AG58: Aumento de reclamações no atendimento de Silvanópolis por Monte do Carmo no período seco
A59: 5827102054 | B59: 58 | C59: PUGMIL | D59: PARAISO DO TOCANTINS | E59: CENTRO | F59: ETO-RD-PS 00289/2026 | G59: Aguardando comissionamento | R59: Concluído poço para melhoria de aterramento aberto | T59: Melhoria de aterramento | U59: 1 | V59: PARECER COEP:NÃO É POSSÍVEL RETORNAR COM O CONTROLE COMPLETO , MAS DARIA PARA FAZER A MELHORIA NA MALHA DE ATERRAMENTO , ENCAMINHANDO PARA OS COCM'S PARA REALIZAREM A MELHORIAparecer DMSL: :Nobreack com defeito, rele queimado, cabo de comunicação entre o rádio e o rele danificado, malha de aterramento está com a resistência alta!Feito reparo no cabo, substituído nobreack, e rele. Se possível retornar com controle completo pq o q está em campo teve infiltração de água, abrir chamado no scada para atualizar base do equipamento pois o mesmo está com a base antiga, fazer correção da malha de aterramento.Equipamento ficou em operação?: Não Pendência: sim, levar controle novo, fazer correção da malha de terra, levar suporte para fixar antena. OBS | W59: 0 | X59: 20 | Y59: 20 | Z59: 10 | AA59: 0 | AB59: - | AC59: - | AD59: - | AE59: 50 | AF59: Média | AG59: Aumento de reclamações no atendimento de Pugmil no período seco
A60: 5850308009 | B60: 58 | C60: GUARAI | D60: GUARAI | E60: NORTE | F60: CONCLUÍDA | S60: Ok | W60: 0 | X60: 20 | Y60: 20 | Z60: 0 | AA60: 10 | AB60: - | AC60: - | AD60: - | AE60: 50 | AF60: Média | AG60: Atendimento de parte da RDU de Guaraí e ramal da PRF/Repetidora
A61: 7900535058 | B61: 79 | C61: SANTA FE DO ARAGUAIA | D61: ARAGUAINA | E61: NORTE | F61: ETO-COEP 00173/2025 | G61: Em processo de aquisição | S61: Pendente | T61: Controle | U61: 1 | V61: PARECER COEP: EQUIPAMENTO SELECIONADO PARA COMPRAPARECER DMSL: Equipamento 7900535058 encontra-se com o relé danificado, firmware corrompido, o mesmo não inicia. Devido ao fato de não possuirmos mais peças de reposição para religador cooper, se faz necessário a substituição de todo conjunto por um Noja RC10.envar equipe para verificar rlo 7900535058 foi feito primeiro ataque com equipe 040op36 o mesmo esta com RELE TRAVADO E FICOU FORA DE OPERAÇÃO, ATENDE RDR DE SANTA FÉ SAIDA DA CIDADEEQUIPE INFORMOU ABELHAS NA CAIXA DO PAINEL DE COMANDO | W61: 5 | X61: 10 | Y61: 5 | Z61: 0 | AA61: 15 | AB61: 10 | AC61: 0 | AD61: 0 | AE61: 45 | AF61: Média | AG61: Atendimento 3 povoados, na perca 4 ficam fora (900 UCs)
A62: 7927713200 | B62: 79 | C62: SAO SALVADOR DO TOCANTINS | D62: PEIXE | E62: SUL | F62: CONCLUÍDA | G62: Em processo de aquisição | R62: Cancelada errada pelo DMSL | S62: Pendente | T62: Tanque | U62: 1 | W62: 5 | X62: 5 | Y62: 5 | Z62: 0 | AA62: 15 | AB62: 10 | AC62: 0 | AD62: 0 | AE62: 40 | AF62: Média | AG62: Transferência do Ramal do Retiro (246UCs), fonte principal by-passado
A63: 7937102148 | B63: 79 | C63: SAO VALERIO DA NATIVIDADE | D63: PEIXE | E63: SUL | F63: ETO-COEP 00129/2026 | G63: Em processo de aquisição | S63: Pendente | T63: Tanque | U63: 1 | V63: PARECER COEP: REAVALIAR DISPONIBILIDADE DO EQUIPAMENTO NO SCADA ASSIM COMO , FORNECER MODELO DO EQUIPAMENTO E FAIXA DE TENSÃO PARA COMPRA / AQUISIÇÃOTanque com defeito, realizar substituição do tanque. | W63: 5 | X63: 5 | Y63: 5 | Z63: 0 | AA63: 15 | AB63: 10 | AC63: 0 | AD63: 0 | AE63: 40 | AF63: Média | AG63: Fonte principal do Ramal Serranópolis (181 UCs), RL de transferência operando
A64: 7944559149 | B64: 79 | C64: CASEARA | D64: DIVINOPOLIS | E64: CENTRO | F64: ETO-COEP 00063/2026 | G64: Em processo de aquisição | S64: Pendente | T64: Controle | U64: 1 | V64: 14/07/2026 PARECER COEP: EQUIPAMENTO SELECIONADO PARA COMPRA Equipamento ficou em operação?: NãoPendência: Sim será necessário substituir a placaServiço Executado: curto na placa foi tentando recuperar a mesma porém não teve sucesso!Bateria(s)substituída(s)? NÃOEquipe: Kaique e benvido | W64: 5 | X64: 10 | Y64: 0 | Z64: 0 | AA64: 15 | AB64: 10 | AC64: 0 | AD64: 0 | AE64: 40 | AF64: Média | AG64: Atendimento de cargas rurais entre Caseara e Araguacema (221 UCs)
A65: 5800961074 | B65: 58 | C65: DIANOPOLIS | D65: DIANOPOLIS | E65: SUL | F65: ETO-COEP 00221/2025 | G65: Equipamento em Logistica | R65: Vamos retirar de uma obra de construção de uma linha antiga e usar na manutenção | S65: Pendente | T65: Células + melhoria de aterramento | U65: 3 | V65: PARECER COEP: EQUIPAMENTO SELECIONADO PARA COMPRASubstituir as 3 células- Melhoria na malha de aterramento - Melhoria no circuito de aterramento qua aterra as células.- Substituir conectores paralelos | W65: 20 | X65: 0 | Y65: 0 | Z65: 20 | AA65: 0 | AB65: - | AC65: - | AD65: - | AE65: 40 | AF65: Média | AG65: Atendimento da COELBA e GA Alessandro Maurício (1600 kVA)
A66: 7908249152 | B66: 79 | C66: SANTA ROSA DO TOCANTINS | D66: PORTO NACIONAL | E66: CENTRO | F66: ETO-COEP 00038/2026 | G66: Em processo de aquisição | S66: Pendente | T66: Tanque + controle | U66: 1 | V66: 14/07/2026 PARECER COEP: EQUIPAMENTO SELECIONADO PARA COMPRADMSL:Serviço Executado: Houve um curto no equipamento danificando a parte ativa, será necessário fazer a substituição do equipamento completo ( parte ativa e controle) colocar o um cabo pp novo do trafo até o Dj pois o mesmo está sem condições de uso. Obs:. Foi retirado rádio e rele Equipamento ficou em operação?: Não Pendência: Sim, substituir o equipamento completo. | W66: 5 | X66: 5 | Y66: 0 | Z66: 0 | AA66: 15 | AB66: 10 | AC66: 0 | AD66: 0 | AE66: 35 | AF66: Média | AG66: Atendimento de zona rural em Santa Rosa (160 UCs)
A67: 7922995039 | B67: 79 | C67: ARAGUATINS | D67: AUGUSTINOPOLIS | E67: NORTE | F67: ETO-PROT 00135/2026 | S67: Em operação | V67: PARECER COEP: Equipamento em operação, instalado com sucesso, segue para Proteção para ajustesPARECER DMSL: Após testes, equipe DMSL constatou que o RLG 7922995039 encontra-se com parte ativa e controle danificados. Favor, realizar substituição completa do equipamento.Troca do sistema de comunicação do equipamento | W67: 5 | X67: 5 | Y67: 0 | Z67: 0 | AA67: 15 | AB67: 10 | AC67: 0 | AD67: 0 | AE67: 35 | AF67: Média | AG67: Atendimento do PA Esperança Viva (396 UCs)
A68: 7925733015 | B68: 79 | C68: PEDRO AFONSO | D68: GUARAI | E68: NORTE | F68: ETO-COEP 00058/2026 | G68: Em processo de aquisição | O68: Validado | S68: Pendente | T68: Tanque | U68: 1 | V68: PARECER COEP: EQUIPAMENTO SELECIONADO PARA COMPRAPARECER DMSL: FEEDBACK EQUIP. ESPECIAISNº DO EQUIPAMENTO: 7925733015TIPO EQUIPAMENTO: Noja RC10TIPO DE COMUNICAÇÃO: Rádio GEDATA DA MANUTENÇÃO: 24/03/2026SID: 1475/2026DESCRIÇÃO: Tanque do equipamento em CurtoFICOU EM OPERAÇÃO?: Não PENDÊNCIA: Sim, repassar a nota para DCMD substituir tanque.DADOS DIVERGENTES DA PROGRAMAÇÃO: NãoBATERIA SUBSTITUÍDA?: Não TIPO DE BATERIA: Lítio EQUIPE: Edicleber e Jhonata(DEOP)------------------------------------------------------------------------------------------------------religador 7925733015 com defeito, equipe fez abertura da chave de saida do mesmo e ele não aceita fehcamento devido provavel curto-circuito interno, enviar equipe para verificar o mesmo ficou by-pass fechado | W68: 5 | X68: 5 | Y68: 0 | Z68: 0 | AA68: 15 | AB68: 10 | AC68: 0 | AD68: 0 | AE68: 35 | AF68: Média | AG68: Transferência do Ramal Agrovila (73 UCs)
A69: 7927396052 | B69: 79 | C69: FORMOSO DO ARAGUAIA | D69: FORMOSO DO ARAGUAIA | E69: SUL | F69: ETO-COEP 00045/2026 | G69: Em processo de aquisição | S69: Pendente | T69: Tanque | U69: 1 | V69: PARECER COEP: EQUIPAMENTO SELECIONADO PARA COMPRAreligador foi bay passado devido mesmo esta saindo fumaca do painel e sem comunicação 7927396052.PARECER DMSL: Após testes, equipe DMSL constatou que apenas o tanque do RLG 7927396052 encontra-se queimado. Favor, substituir parte ativa do equipamento.NS Tanque: 0320123040198 | W69: 5 | X69: 5 | Y69: 0 | Z69: 0 | AA69: 15 | AB69: 10 | AC69: 0 | AD69: 0 | AE69: 35 | AF69: Média | AG69: Equipamento localizado Fonte principal de atendimento a SE Cobrape
A70: 7933585074 | B70: 79 | C70: DIANOPOLIS | D70: DIANOPOLIS | E70: SUL | F70: ETO-COEP 00024/2026 | G70: Em processo de aquisição | R70: Estava aguardando retorno DMSL | S70: Pendente | T70: Tanque | U70: 1 | V70: 30/06 PARECER COEP: EQUIPAMENTO SELECIONADO PARA COMPRAREALIZAR SUBSTITUIÇÃO DO TANQUE, O MESMO ESTÁ COM DEFEITO. | W70: 5 | X70: 5 | Y70: 15 | Z70: 0 | AA70: 0 | AB70: 0 | AC70: 10 | AD70: 0 | AE70: 35 | AF70: Média | AG70: Atendimento da COELBA
A71: 7942572059 | B71: 79 | C71: TAQUARALTO | D71: TAQUARALTO | E71: CENTRO | F71: ETO-PROT 00155/2026 | G71: Aguardando comissionamento | S71: Em operação | V71: PARECER COEP: EQUIPAMENTO COM MELHORIA DE ATERRAMENTO É COM A ETO-RD-PA , NÃO PASSA PELO FLUXO DE AQUISIÇÃO DO COEP, FAVOR REALIZAR MELHORIA DE ATERRAMENTO ETO-RD-PAPARECER DMSL 19/05/2026: É necessário fazer melhorias na malha de aterramento.segue nota para RL 794252059 o mesmo esta sem comunicaçao, foi feito primeiro ataque, porem a comunicaçao nao voltou, obs ramal do marasca.**** Parcecer do COCM CENTRO-****FEITO A MALHAR DE ATERRAMENTO ATENDIDA PELA ORDEM DE SERVIÇO DLP-MLPA02 91/2026 COM RELATORIO EM ANEXO A O.S | W71: 5 | X71: 5 | Y71: 15 | Z71: 0 | AA71: 0 | AB71: 0 | AC71: 10 | AD71: 0 | AE71: 35 | AF71: Média | AG71: Atendimento do Ramal do Marasca e GAs (108 UCs)
A72: 7944319149 | B72: 79 | C72: CASEARA | D72: DIVINOPOLIS | E72: CENTRO | F72: CONCLUÍDA | S72: Ok | W72: 5 | X72: 5 | Y72: 15 | Z72: 0 | AA72: 0 | AB72: 0 | AC72: 10 | AD72: 0 | AE72: 35 | AF72: Média | AG72: Atendimento do Grupo A - Matosul (TF 1500 kVA)
A73: 7955986084 | B73: 79 | C73: DIVINOPOLIS | D73: DIVINOPOLIS | E73: CENTRO | F73: ETO-COEP 00133/2026 | G73: Em processo de aquisição | S73: Pendente | V73: 14/07/2026 PARECER COEP : SUBSTIUIR CONTROLE COMPLETOPARECER DMSL: Equipamento com a placa de alimentação ca em curto, será necessário substituir a placa do equipamento. (Antiga nota era pra ter sido repassada porém foi baixada indevidamente pela equipe) | W73: 5 | X73: 5 | Y73: 0 | Z73: 0 | AA73: 15 | AB73: 10 | AC73: 0 | AD73: 0 | AE73: 35 | AF73: Média | AG73: Transferência de cargas do 444R da SE Paraíso I
A74: 7967181127 | B74: 79 | C74: PALMEIRAS DO TOCANTINS | D74: TOCANTINOPOLIS | E74: NORTE | F74: CONCLUÍDA | G74: Linha viva substiui as chaves pode ser que esteja dentro de operação | W74: 5 | X74: 5 | Y74: 0 | Z74: 0 | AA74: 15 | AB74: 10 | AC74: 0 | AD74: 0 | AE74: 35 | AF74: Média | AG74: Transferência de Palmeiras, 3 RLs sendo 2 operando
A75: 7900525015 | B75: 79 | C75: PEDRO AFONSO | D75: GUARAI | E75: NORTE | F75: ETO-COEP 00125/2026 | G75: Em processo de aquisição | S75: Pendente | T75: Tanque | U75: 1 | V75: PARECER COEP: É PARA REALIZAR A SUBSTITUIÇÃO DO RELIGADOR OU DAS BUCHAS, CASO SEJA BUCHAS , REPASSAR PARA OS COCM'S , CASO NÃO SEJA ESPECIFIQUE O MODELO , E A TENSÃO, FICO NO AGUARDO DO RETORNONota para manutenção substituir religador 7900525015 que está com as buchas de entrada danificadas fase A estourada e bc danificadas Local LD Pedro Afonso A Chaparral | W75: 5 | X75: 5 | Y75: 0 | Z75: 0 | AA75: 15 | AB75: 10 | AC75: 0 | AD75: 0 | AE75: 35 | AF75: Média | AG75: Tranferência do Ramal do Chaparral (251 UCs)
A76: 7928564039 | B76: 79 | C76: ARAGUATINS | D76: AUGUSTINOPOLIS | E76: NORTE | F76: ETO-COEP 00123/2026 | G76: Em processo de aquisição | S76: Pendente | T76: Tanque + controle | U76: 1 | V76: PARECER COEP: EQUIPAMENTO SELECIONADO PARA COMPRATroca do sistema de comunicação do equipamentoDMSL 28/07/2025: Equipamento com tanque, modulo e rele com defeito, solicitar troca do equipamento ao DCMD.Fotos vão ser enviadas por e-mail | W76: 5 | X76: 10 | Y76: 5 | Z76: 0 | AA76: 0 | AB76: 10 | AC76: 0 | AD76: 0 | AE76: 30 | AF76: Média | AG76: Transferência entre 424R Araguatins e 434R Augustinópolis
A77: 7957126085 | B77: 79 | C77: MONTE SANTO DO TOCANTINS | D77: PARAISO DO TOCANTINS | E77: CENTRO | F77: CONCLUÍDA | S77: Ok | W77: 5 | X77: 10 | Y77: 5 | Z77: 0 | AA77: 0 | AB77: 10 | AC77: 0 | AD77: 0 | AE77: 30 | AF77: Média | AG77: 444R de Paraíso I, atendimento de Monte Santo, devido defeito a RDU está manobrada para o 454R
A78: 5841308190 | B78: 58 | C78: NOVO JARDIM | D78: DIANOPOLIS | E78: SUL | F78: CONCLUÍDA | S78: Desmobilizado | T78: - | W78: 0 | X78: 20 | Y78: 0 | Z78: 10 | AA78: 0 | AB78: - | AC78: - | AD78: - | AE78: 30 | AF78: Baixa | AG78: Equipamento obsoleto com a entrada da SE Serras Gerais
A79: 5844630060 | B79: 58 | C79: NOVA OLINDA | D79: COLINAS DO TOCANTINS | E79: NORTE | F79: CONCLUÍDA | G79: Equipamento entregue aos COCM's | R79: Previsão de entrega 20/07 // Foi entregue a eles verificar o porque eles baixaram | S79: Em andamento | T79: Célula | U79: 1 | W79: 20 | X79: 0 | Y79: 0 | Z79: 10 | AA79: 0 | AB79: - | AC79: - | AD79: - | AE79: 30 | AF79: Baixa | AG79: Atendimento dos ramais PA Remansão e Água Branca
A80: 5855411017 | B80: 58 | C80: BARROLANDIA | D80: MIRACEMA DO TOCANTINS | E80: CENTRO | F80: ETO-COEP 00156/2026 | G80: Em processo de aquisição | S80: Pendente | T80: Controle | U80: 1 | V80: 20/07 PARECER COCM: NÃO RECEBEMOS MATERIAL10/07 PARECER COEP: EQUIPAMENTO ENTREGUE AOS COCM´S FAVOR INFORMAR PRAZO DE SUBSTUIÇÃO PARA O DMSL E REPASSAR DEPOIS PARA PROTEÇÃO REALIZAR OS AJUSTES E DESCREVER NA SS O SERVIÇO REALIZADOPARECER COEP: EQUIPAMENTO EM ROTA DE ENTREGASEM COMUNICAÇÃO, FALHA DE ALIMENTAÇÃO - REALIZADO PRIMEIRO ATAQUE SEM SUCESSO.PARECER DMSL: 17/09/2025 Equipamento ficou em operação? Não Pendência: sim. Equipamento ficou Bay passado levar controle COMPLETO para trocar. ellisfran | W80: 0 | X80: 0 | Y80: 0 | Z80: 10 | AA80: 20 | AB80: - | AC80: - | AD80: - | AE80: 30 | AF80: Baixa | AG80: Atendimento do Assentamento Irmã Adelaide
A81: 7900505026 | B81: 79 | C81: PONTE ALTA TOCANTINS | D81: PONTE ALTA TOCANTINS | E81: CENTRO | F81: CONCLUÍDA | S81: Ok | W81: 5 | X81: 5 | Y81: 5 | Z81: 0 | AA81: 0 | AB81: 0 | AC81: 10 | AD81: 0 | AE81: 25 | AF81: Baixa | AG81: Atendimento do Ramal do Gato (288 UCs) e UFV Videira, no desarme a jusante penaliza a cidade de Pindorama
A82: 7908196047 | B82: 79 | C82: FIGUEIROPOLIS | D82: ALVORADA | E82: SUL | F82: ETO-TELE 01002/2026 | G82: Em processo de aquisição | O82: SS REPASSADA | S82: Pendente | T82: Tanque + controle | U82: 1 | V82: 13/07/2026 PARECER COEP: EQUIPAMENTO REMANEJADO FAVOR FAZER O COMISSIONAMENTORELIGADOR N° 7908196047 REMANEJADO NA OBRA 0402401150 GENTILEZA, REALIZAR O COMISSIONAMENTO. LAUDO EM ANEXO. COORD EO: 698485, 8657287PARECER DA PROTEÇÃO:AJUSTE DISPONIBILIZADO NO APP DA PROTEÇÃO, NOTA REPASSADA PARA DMSL COMISSIONAR, POLO GURUPI, RL APENAS REMANEJADO DA REDE VELHA PARA REDE NOVA, EQUIPAMENTO COOPER, SE MANTEVE O MESMO NÚMERO DE ATIVO.ENG° IRLLEY CASTELO BRANCO.PARECER DMSL: Constatado curto-circuito no tanque do religador, impedindo as operações de abertura e fechamento do equipamento. Solicita-se a substituição completa do religador, incluindo tanque e unidade de controle. | W82: 5 | X82: 5 | Y82: 5 | Z82: 0 | AA82: 0 | AB82: 0 | AC82: 10 | AD82: 0 | AE82: 25 | AF82: Baixa | AG82: Seccionamento do Rural e energização do 224R
A83: 7921202014 | B83: 79 | C83: PIUM | D83: PARAISO DO TOCANTINS | E83: CENTRO | F83: ETO-COEP 00132/2026 | G83: Em processo de aquisição | S83: Pendente | T83: Tanque | U83: 1 | V83: PARECER COEP: EQUIPAMENTO SELECIONADO PARA COMPRA , DEVERIA SER SUBSTITUIDO PARTE ATIVAPARECER DMSL: Serviço Executado: _ indentificado o problema na parte ativa será necessário fazer a substituição da mesmo, feito a medição do aterramento. Preciso substituir para raio da fase c.Equipamento ficou em operação?: _NAOPendência: _SimBateria(s) substituída(s)? _NãoData Fabricação/Instalação da(s) bateria(s):_Equipe: _Benvindo e kaique----------------------------------------------------------------------------------RL com defeito no rele, fica só reiniciando ficou By passado OS atendimento primeiro ataque 106530226 | W83: 5 | X83: 5 | Y83: 5 | Z83: 0 | AA83: 0 | AB83: 10 | AC83: 0 | AD83: 0 | AE83: 25 | AF83: Baixa | AG83: Atendimento de Clientes rurais (483 UCs)
A84: 7923927122 | B84: 79 | C84: PALMAS | D84: PALMAS | E84: CENTRO | F84: ETO-COEP 00148/2026 | G84: Em processo de aquisição | S84: Pendente | T84: Tanque | U84: 1 | V84: PARECER DMSL 16/07: Nota solicitada ao DMSL com a informação de que o tanque precisa ser substituído. Estou encaminhando a nota para a área responsável.Segue nota para envia manutenção substituir tanque do RL-7923927122 em curto, Anomalia identificada desarme das LD, s Palmas / Aparecida e Palmas Taquaruçu, Acesso livre, Tensão 34,5kv, Local RL de Interligação entre 424R / 414R. | W84: 15 | X84: 0 | Y84: 0 | Z84: 0 | AA84: 0 | AB84: 10 | AC84: 0 | AD84: 0 | AE84: 25 | AF84: Baixa | AG84: Transferência entre 414R e 424R SE Palmas II
A85: 7927446001 | B85: 79 | C85: PORTO NACIONAL | D85: PORTO NACIONAL | E85: CENTRO | F85: ETO-COEP 00143/2025 | G85: Em processo de aquisição | S85: Pendente | T85: Tanque + controle | U85: 1 | V85: 30/06 PARECER COEP: EQUIPAMENTO COMPLETOSegue para verificação RL sem comunicação feito primeiro ataque sem sucesso.PARECER DMSL:Data:* _08/07/2025Serviço Executado: Placa de alimentação danificada, devido a curto, não temos material sobressalente para manutenção! Favor substituir o equipamento completo.Obs.: O rádio ficou dentro do controle, favor orientar a equipe que for substituir colocar dentro do controle novo.Equipamento ficou em operação?: Não Pendência: Sim, substituir equipamento completo. | W85: 5 | X85: 5 | Y85: 5 | Z85: 0 | AA85: 0 | AB85: 10 | AC85: 0 | AD85: 0 | AE85: 25 | AF85: Baixa | AG85: Alimentação de Monte do Carmo por Porto Nacional
A86: 7928241200 | B86: 79 | C86: SAO SALVADOR DO TOCANTINS | D86: PEIXE | E86: SUL | F86: ETO-COEP 00128/2026 | G86: Em processo de aquisição | S86: Pendente | T86: Tanque | U86: 1 | V86: PARECER COEP: EQUIPAMENTO SELECIONADO PARA COMPRAPARECER DMSL: Tinha uma nota aberta 422/2025 e logo após a equipe resolver a comunicação ela foi baixada, porém a equipe relatou que ''na estrada ontem o COS nos avisou para voltar que na hora de colocar em operação ele tirou a linha fora. Hoje retornamos nele e fizemos ensaios elétricos e foi constatado que o tanque está em curto. Passa direto aí para o Dcmd para substituição do tanque.'' | W86: 5 | X86: 5 | Y86: 5 | Z86: 0 | AA86: 0 | AB86: 10 | AC86: 0 | AD86: 0 | AE86: 25 | AF86: Baixa | AG86: Fonte principal do Ramal do Retiro (246UCs), RL transferência by-passado
A87: 7942485096 | B87: 79 | C87: PINDORAMA DO TOCANTINS | D87: PONTE ALTA TOCANTINS | E87: CENTRO | F87: ETO-COEP 00158/2025 | G87: Em processo de aquisição | S87: Pendente | T87: Tanque | U87: 1 | V87: 30/06 PARECER COEP: EQUIPAMENTO SELECIONADO PARA COMPRARELIGADOR COM DEFEITO 7942485096, ESTA DANDO PASSAGEM ESTANDO ABERTO. NÃO ACEITA COMANDOS. FICOU BY PASSADO EM CAMPO PARA MANUTENÇÃO.PARECER DMSL: Ao testar o tanque, foi constatado que o mesmo está danificado e precisa ser substituído.Substituir somente o tanque. Deixar claro na nota para o dcmd substituir somente o tanque. Não tem necessidade de substituir o controle. | W87: 5 | X87: 5 | Y87: 5 | Z87: 0 | AA87: 0 | AB87: 10 | AC87: 0 | AD87: 0 | AE87: 25 | AF87: Baixa | AG87: Transferência da PCH Bagagem
A88: 7955430075 | B88: 79 | C88: DOIS IRMAOS DO TOCANTINS | D88: DIVINOPOLIS | E88: CENTRO | F88: CONCLUÍDA | S88: Ok | W88: 5 | X88: 5 | Y88: 5 | Z88: 0 | AA88: 0 | AB88: 0 | AC88: 10 | AD88: 0 | AE88: 25 | AF88: Baixa | AG88: Atendimento do Ramal do Boleu (13 UCs), no desarme a jusante penaliza parte 303 UCs rurais
A89: 7955686076 | B89: 79 | C89: DUERE | D89: GURUPI | E89: SUL | F89: CONCLUÍDA | S89: Ok | W89: 5 | X89: 5 | Y89: 0 | Z89: 0 | AA89: 15 | AB89: 0 | AC89: 0 | AD89: 0 | AE89: 25 | AF89: Baixa | AG89: Fonte alternativa de atendimento do Ramal Bacuri (217 UCs)
A90: 7955946007 | B90: 79 | C90: MIRACEMA DO TOCANTINS | D90: MIRACEMA DO TOCANTINS | E90: CENTRO | F90: ETO-COEP 00134/2026 | G90: Em processo de aquisição | S90: Pendente | T90: Controle | U90: 1 | V90: 13/07/2026 PARECER COEP: SUBSTITUIR CONTOLE OU MANDAR MANUTENCIONAR EM CASO DE PRIORIDADE ALTAPARECER DMSL: Necessário substituir a placa de alimentação ca, a mesma está em curto não conseguimos recuperar. (Antiga nota era pra ter sido repassada porém foi baixada indevidamente pela equipe) | W90: 5 | X90: 5 | Y90: 5 | Z90: 0 | AA90: 0 | AB90: 0 | AC90: 10 | AD90: 0 | AE90: 25 | AF90: Baixa | AG90: Alimentação do serviço auxiliar da Investco e clientes rurais (260 UCs)
A91: 7901110084 | B91: 79 | C91: DIVINOPOLIS | D91: DIVINOPOLIS | E91: CENTRO | F91: ETO-COEP 00061/2026 | G91: Em processo de aquisição | S91: Pendente | T91: Tanque | U91: 1 | V91: PARECER COEP: EQUIPAMENTO SELECIONADO PARA COMPRAPARECER DMSL: Serviço Executado: Foi feito análise técnica, testes funcionais e identificado que a parte ativa do equipamento está com defeito. Necessário substituir a parte ativa.FICOU EM OPERAÇÃO? Não- EQUIPE: Carliel e BenvindoSegue SS para verificaçao Rl esta danificado dando passagem de tensão mesmo aberto Sim, quando retornar trazer uma fonte pois a mesma foi removida. | W91: 5 | X91: 5 | Y91: 0 | Z91: 0 | AA91: 0 | AB91: 0 | AC91: 10 | AD91: 0 | AE91: 20 | AF91: Baixa | AG91: Localizado na fonte principal de atendimento de Divinópolis e Abreulândia
A92: 7908206074 | B92: 79 | C92: DIANOPOLIS | D92: DIANOPOLIS | E92: SUL | F92: CONCLUÍDA | S92: Ok | W92: 5 | X92: 5 | Y92: 0 | Z92: 0 | AA92: 0 | AB92: 0 | AC92: 10 | AD92: 0 | AE92: 20 | AF92: Baixa | AG92: Atendimento do PA Novo Plano (102 UCs)
A93: 7908708116 | B93: 79 | C93: CHAPADA DA NATIVIDADE | D93: DIANOPOLIS | E93: SUL | F93: CONCLUÍDA | G93: Equipamento Fora de operação | R93: Cancelada errada pelo DMSL | S93: Pendente | T93: Tanque + controle | W93: 5 | X93: 5 | Y93: 0 | Z93: 0 | AA93: 0 | AB93: 0 | AC93: 10 | AD93: 0 | AE93: 20 | AF93: Baixa | AG93: Atendimento do PA Xobo (194 UCs)
A94: 7910027196 | B94: 79 | C94: LAGOA DO TOCANTINS | D94: TAQUARALTO | E94: CENTRO | F94: CONCLUÍDA | G94: Em processo de aquisição | S94: Pendente | T94: Tanque + controle | U94: 1 | W94: 5 | X94: 5 | Y94: 0 | Z94: 0 | AA94: 0 | AB94: 0 | AC94: 10 | AD94: 0 | AE94: 20 | AF94: Baixa | AG94: Atendimento do Ramal do Rio Preto (197 UCs)
A95: 7913662076 | B95: 79 | C95: DUERE | D95: GURUPI | E95: SUL | F95: ETO-COEP 00114/2026 | G95: Em processo de aquisição | R95: 1 controle NOJA sobrando | S95: Pendente | T95: Tanque | U95: 1 | V95: 30/06 PARECER COEP: AGUARDANDO RETORNO DO DMSL PARA ENTENDER EXATAMENTE O QUE TENHO QUE SUBSTITUIRAberto nota para substituir tanque danificado e chave de entrada fase B danificadaPARECER DMSL: Foi confirmado pela equipe DMSL o defeito do tanque, favor seguir com a substituição e correção da chave de entrada fase B danificada. | W95: 5 | X95: 5 | Y95: 0 | Z95: 0 | AA95: 0 | AB95: 10 | AC95: 0 | AD95: 0 | AE95: 20 | AF95: Baixa | AG95: Atendimento do Ramal do Bacuri (168 UCs)
A96: 5862236091 | B96: 58 | C96: ALMAS | D96: DIANOPOLIS | E96: SUL | F96: ETO-RD-DP 00457/2026 | G96: Em processo de aquisição | S96: Pendente | T96: Célula | U96: 1 | V96: 20/07 PARECER COEP: EQUIPAMENTO ENTREGUE , FAVOR EDITAR A SS COM A DATA PREVISTA DE SUBSTITUIÇÃO NO PARECER DOS COCM´S Realizar substituição da FASE B.Célula da fase B estava com a tampa do contador de tape aberta, pegou chuva e molhou os contatos danificando a peça toda. | W96: 0 | X96: 0 | Y96: 0 | Z96: 20 | AA96: 0 | AB96: - | AC96: - | AD96: - | AE96: 20 | AF96: Baixa | AG96: Atendimento da LD Vale Rio Doce (Nova Aura Mineradora)
A97: 5836786094 | B97: 58 | C97: PEIXE | D97: PEIXE | E97: SUL | F97: ETO-COEP 00095/2026 | G97: Em processo logístico | R97: Previsão de entrega 16/08 | S97: Em andamento | T97: Célula | U97: 1 | V97: 24/07 PARECER COEP:EQUIPAMENTO EM LOGISTICA DE ENTREGA Favor levar outro regulador de tensão, pois o mesmo foi furtado em campo. | W97: 0 | X97: 0 | Y97: 0 | Z97: 10 | AA97: 10 | AB97: - | AC97: - | AD97: - | AE97: 20 | AF97: Baixa | AG97: Atendimento de clientes rurais na LD Peixe Angical - Peixe
A98: 7919270014 | B98: 79 | C98: PIUM | D98: PARAISO DO TOCANTINS | E98: CENTRO | F98: ETO-RD-PS 00327/2026 | G98: Em processo de aquisição | S98: Pendente | V98: PARECER COEP: AGUARDANDO RETORNO DO DMSL, EQUIPAMENTO FOI INSTALADO NOVO NA OBRA 0212501060, ENTENDER O PORQUE NÃO FOI REALIZADO COMISSIONAMENTOPARECER DMSL: Substituir Equipamento completo problema na placa de alimentação e na parte ativa, falta colocar placa de identificação correta na topologia, baixar o controle.Equipamento ficou em operação?: naoPendência: simBateria(s) substituída(s)? NÃOEquipe: Kaique/ Benvindo13/07/2026 PARECER COEP: SUBSTITUIÇÃO REALZIADA , FAVOR COMISSIONARPARECER DMSL (22/07/26): Solicito que o laudo de substituição seja anexado, e a SS seja repassada para proteção atribuir a ordem de ajuste, antes de repassar para ETO-TELE.----------------------------------------------PARECER DA PROTEÇÃO: Prosseguir com o comissionamento. Ajustes de religador permanecem os mesmos, disponíveis no APP da Proteção.********************************RELIGADOR N°7919270014 REMANEJADO NA OBRA 0212501060 GENTILEZA, REALIZAR O COMISSIONAMENTO. LAUDO EM ANEXO. COORD EO: 617422, 8830787 | W98: 5 | X98: 5 | Y98: 0 | Z98: 0 | AA98: 0 | AB98: 10 | AC98: 0 | AD98: 0 | AE98: 20 | AF98: Baixa | AG98: Atendimento de Clientes rurais (48 UCs)
A99: 7926442035 | B99: 79 | C99: MONTE DO CARMO | D99: PONTE ALTA TOCANTINS | E99: CENTRO | F99: ETO-COEP 00051/2026 | G99: Em processo de aquisição | R99: 1 controle NOJA sobrando | S99: Pendente | T99: Trafo auxiliar e tanque | U99: 1 | V99: PARECER COEP: EQUIPAMENTO SELECIONADO PARA COMPRAPARECER DMSL: Data: 12/03/2026 Serviço Executado:- Análise técnica constatou:- Parte ativa do equipamento danificada: necessita substituição- Trafo danificado: foi feitos testes nas buchas secundárias o mesmo não chega tensão - Vazamento de óleo - Necessita substituiçãoEquipamento ficou em operação? NãoPendências:- Solicitar limpeza de faixa para acesso ao equipamento- Trocar parte ativa do equipamento- Substituir o trafoEquipe: Carliel e João VitorSegue nota para envia equipe verificar falha de comunicação e automação no RL-7926442035 feito primeiro ataque com equipe 035OP02, porém sem sucesso. | W99: 5 | X99: 5 | Y99: 0 | Z99: 0 | AA99: 0 | AB99: 0 | AC99: 10 | AD99: 0 | AE99: 20 | AF99: Baixa | AG99: Atenidmento do PA Principado (200 UCs)
A100: 7954668084 | B100: 79 | C100: DIVINOPOLIS | D100: DIVINOPOLIS | E100: CENTRO | F100: CONCLUÍDA | S100: Ok | W100: 5 | X100: 5 | Y100: 0 | Z100: 0 | AA100: 0 | AB100: 0 | AC100: 10 | AD100: 0 | AE100: 20 | AF100: Baixa | AG100: Atendimento do PA Piedade (125 UCs)
...

Sheet Planilha1
D2: Parecer COEP | E2: Equipamento entregue ao COCM
A3: Rótulos de Linha | B3: Contagem de Ativo
A4: Muito Alta | B4: 30 | D4: Rótulos de Linha | E4: Contagem de Ativo
A5: Aguardando comissionamento | B5: 5 | D5: Muito Alta | E5: 2
A6: Em fase de ajustes | B6: 4 | D6: Previsão de substituição 07/08// Nova previsão de entrega 21/08 se a DB Machado for para o Sul | E6: 1
A7: Em processo de aquisição | B7: 7 | D7: Previsão de substituição 07/08 // 22/08 Se a DB Machado for pro Sul | E7: 1
A8: Equipamento entregue ao COCM | B8: 2 | D8: Alta | E8: 1
A9: Concluído | B9: 10 | D9: Previsão de substituição 28/07 | E9: 1
A10: Concuído DCMD | B10: 1 | D10: Total Geral | E10: 3
A11: Concluído DCMD | B11: 1
A12: Alta | B12: 21
A13: Em fase de ajustes | B13: 5
A14: Em processo de aquisição | B14: 6 | D14: Parecer COEP | E14: Em processo logístico
A15: Em processo logístico | B15: 1
A16: Equipamento entregue ao COCM | B16: 1 | D16: Rótulos de Linha | E16: Contagem de Ativo
A17: Primeiro ataque DMSL | B17: 1 | D17: Alta | E17: 1
A18: Problema na autorização de passagem | B18: 1 | D18: Previsão de entrega 10/08 | E18: 1
A19: Concluído | B19: 4 | D19: Baixa | E19: 1
A20: Concluído DCMD | B20: 1 | D20: Previsão de entrega 16/08 | E20: 1
A21: Concluído DCMD | B21: 1 | D21: Total Geral | E21: 2
A22: Média | B22: 25
A23: Aguardando comissionamento | B23: 5
A24: Em processo de aquisição | B24: 12
A25: Concluído | B25: 5
A26: Concluído DCMD e DMSL | B26: 1
A27: Equipamento em Logistica | B27: 1
A28: Linha viva substiui as chaves pode ser que esteja dentro de operação | B28: 1
A29: Baixa | B29: 27
A30: Aguardando parecer DMSL | B30: 1
A31: Em processo de aquisição | B31: 16
A32: Em processo logístico | B32: 1
A33: REPASSAR O DMSL (EQUIPAMENTO OPERANDO NO SCADA) | B33: 1
... A37: Total Geral | B37: 103

Sheet Concluídas
A1: ANO_SS | B1: SS_ORIGINAL | C1: DESTINO_SS | D1: COD_RELIGADOR | E1: DTA_ABERTURA | F1: DTA_CONCLUSAO | G1: COD_LOC | H1: LOCALIDADE | I1: POLO | J1: REGIONAL | K1: ALIMENTADOR | L1: DESCRICAO
A2: 2026 | B2: ETO-TELE 00963/2026 | C2: ETO-TELE | D2: 7903569004 | E2: 46202 | F2: 46210 | G2: 4 | H2: ARAGUAINA | I2: ARAGUAINA | J2: NORTE | K2: AL05010004 | L2: PARECER COEP: Equipamento está em operação no Scada, preciso da especificação do modelo do equipamento para realizar a compraPARECER DMSL:Realizar substituição do equipamento todo e parte ativa.Equipe: Adeilton e EdicleberData: 12/03-----------------------------------------------------------------------------Religador sem comunicação, apos primeiro ataque o mesmo não retornou as comunicação.
A3: 2026 | B3: ETO-TELE 00941/2026 | C3: ETO-TELE | D3: 7954668084 | E3: 46192 | F3: 46210 | G3: 84 | H3: DIVINOPOLIS | I3: DIVINOPOLIS | J3: CENTRO | K3: LD04062013 | L3: FEITO O PRIMEIRO ATAQUE NO RL 7954668084 E O DISPLAY ESTÁ QUEIMADO, NÃO LIGA.OS (99) 106230846PRECISA SER FEITO A ANÀLISE DO DMSL, PARA A COMPRA DO EQUIPAMENTO
A4: 2026 | B4: ETO-TELE 00959/2026 | C4: ETO-TELE | D4: 7908708116 | E4: 46202 | F4: 46211 | G4: 116 | H4: CHAPADA DA NATIVIDADE | I4: DIANOPOLIS | J4: SUL | K4: LD04002091 | L4: PARECER COEP: Equipamento em operação no SCADA, favor revisitar ou explicar defeito e modelo do equipamento.Substituição de tanque e controle, os mesmos estão com defeitos.
A5: 2026 | B5: ETO-TELE 00962/2026 | C5: ETO-TELE | D5: 7936038076 | E5: 46202 | F5: 46211 | G5: 76 | H5: DUERE | I5: GURUPI | J5: SUL | K5: LD02040003 | L5: PARECER COEP: Equipamento em operação no SCADA, se for necessário , favor especificar peça e modelo para substituiçãoTanque do RLG 7936038076 queimado, favor substituir o mesmo.NS do tanque: 0320118112616
A6: 2026 | B6: ETO-TELE 00961/2026 | C6: ETO-TELE | D6: 7955520116 | E6: 46202 | F6: 46211 | G6: 116 | H6: CHAPADA DA NATIVIDADE | I6: DIANOPOLIS | J6: SUL | K6: LD04002091 | L6: PARECER COEP: Equipamento em operação no Scada, além de não especificar o defeito, ainda não especificou marca e modelo para substituiçãoSolicitação de serviço para substituição de parte ativa de RL [7955520116] danificada conforme imagens anexadas.
A7: 2026 | B7: ETO-TELE 00960/2026 | C7: ETO-TELE | D7: 7927713200 | E7: 46202 | F7: 46211 | G7: 200 | H7: SAO SALVADOR DO TOCANTINS | I7: PEIXE | J7: SUL | K7: LD02010021 | L7: PARECER COEP: Equipamento em operação no SCADA, favor reavaliar necessidade de substituição ,assim como especificar modelo das peças a serem substituidas e os defeitos.REALIZAR SUBSTITUIÇÃO DO TANQUE.
A8: 2026 | B8: ETO-TELE 00861/2026 | C8: ETO-TELE | D8: 7957021094 | E8: 46162 | F8: 46213 | G8: 94 | H8: PEIXE | I8: PEIXE | J8: SUL | K8: LD01066094 | L8: SEGUE SS DE RELIGADOR COM CURTO INTERNO, DJUNTOR DE BT NÃO ACEITA.
A9: 2026 | B9: ETO-PROT 00147/2026 | C9: ETO-PROT | D9: 5800657026 | E9: 46216 | F9: 46216 | G9: 26 | H9: PONTE ALTA TOCANTINS | I9: PONTE ALTA TOCANTINS | J9: CENTRO | K9: LD03046026 | L9: Segue nota para verificar ajustes no regulador de tensão 5800657026 S/E Ponte Alta , motivo constantes reclamações de tensão na LD , foi identificado que no período das 17:30 às 22:00 a tensão reduz muito , os reguladores de tensão na LD não conseguem controlar o nivel de tensão ficando a tensão entorno de 18,5 KV , principalmente na fase A no regulador 5864441026 . No regulador 5800440256 a fase que fica mais baixa e a fase C .Obs: Nesse período crítico o nível de tensão no Dj 414 da S/E Ponte alta fica entorno de 33 KV , porém o regulador de tensão da S/E ponte Alta N: 5800657026 foi identificado que estava em Tap's abaixo do 4 , tendo possibilidade de melhorar o nível de tensão .Foi feito testes reguladores comutou normal , porém não ficou no nível ideal !Parecer da proteção:Qualquer alteração no Regulador de Tensão (RT) da SE Ponte Alta impactará diretamente o barramento de 13,8 kV. Atualmente, o transformador encontra-se ajustado no TAP 4 (33,638 kV), e uma mudança nesse ajuste poderá ocasionar novas reclamações de tensão por parte dos consumidores atendidos nesse nível de tensão.Por outro lado, caso o transformador 34,5/13,8 kV seja ajustado para a posição nominal, poderemos ter reclamações de tensão baixa na rede de distribuição urbana (RDU), considerando que não possuímos controle sobre os TAPs dos transformadores de distribuição. Em contrapartida, essa alteração proporcionaria maior margem operacional para o ajuste do RT do sistema de 34,5 kV.Diante desse cenário, é imprescindível embasar qualquer tomada de decisão em dados de campo. Como primeira etapa, sugiro realizar um levantamento amostral dos TAPs dos transformadores de distribuição localizados na região central da cidade de Ponte Alta, de forma a identificar a posição em que atualmente estão operando.Além disso, considero importante realizarmos uma reunião técnica para conduzir um estudo de engenharia mais aprofundado. As decisões relativas aos ajustes operacionais devem ser
A10: 2026 | B10: ETO-PROT 00134/2026 | C10: ETO-PROT | D10: 5820790038 | E10: 46200 | F10: 46216 | G10: 38 | H10: TAGUATINGA | I10: DIANOPOLIS | J10: SUL | K10: LD01414027 | L10: Segue nota para verificar falha em regulador de tensão N: 5820790038- Rural - Taguatinga .A mineradora Nativo está constantemente reclamando de tensão baixa, porém equipamento está regulando inserindo taps negativosE tensão ficando entorno de 19,7 kv .Favor analisar ajustes , ou possíveis falhas como aterramento . Parecer da proteção:Alterado a tensão de referência de 20.120 para 21.000.Eng° Irlley Castelo Branco.
A11: 2026 | B11: ETO-TELE 00978/2026 | C11: ETO-TELE | D11: 7948412064 | E11: 46203 | F11: 46216 | G11: 64 | H11: BRASILANDIA DO TOCANTINS | I11: GUARAI | J11: NORTE | K11: LD02020023 | L11: FOI REALIZADO O PRIMEIRO ATAQUE E O MESMO NÃO RETORNOU A COMUNICAÇÃO
A12: 2026 | B12: ETO-RD-PS 00303/2026 | C12: ETO-RD-PS | D12: 5801866013 | E12: 46213 | F12: 46217 | G12: 13 | H12: PARAISO DO TOCANTINS | I12: PARAISO DO TOCANTINS | J12: CENTRO | K12: AL03062013 | L12: 10/07 PARECER COEP: EQUIPAMENTO ENTREGUE AOS COCM´S FAVOR INFORMAR PRAZO DE SUBSTUIÇÃO PARA O DMSL E REPASSAR DEPOIS PARA PROTEÇÃO REALIZAR OS AJUSTES E DESCREVER NA SS O SERVIÇO REALIZADOPARECER COEP: EM PROCESSO DE ENTREGAPARECER DMSL: RT 5801866013Serviço Executado: Feito a medição da malha de terra. Identificado infiltração na caixa de passagem da célula da fase C do banco regulador de tensão, será necessário fazer a substituição da mesma! Ficar atento na hora da substituição, deverá ser substituída a célula do lado da BR.Obs.: Será necessário baixar todo o banco pelo menos um metro, as buchas estão muito próximas a parte energizada não oferecem segurança para equipe no momento do ensaio elétrico.Equipamento ficou em operação?: Não Possui nobreak: SimPossui antena: SimPossui rádio:SimPendência: SimData da bateria: Equipe: Benvindo e Kaique._______________________________________________RT 5801866013BY PASSADO DEVIDO DEFEITO EM CELULA BEMVINDO ESTEVE NO LOCAL JUNTO AO COD .NECESSARIO TRATATIVA PARA MESMA .FASE DANIFICADO C
A13: 2026 | B13: ETO-TELE 00924/2026 | C13: ETO-TELE | D13: 7925713040 | E13: 46183 | F13: 46220 | G13: 40 | H13: ARAGOMINAS | I13: ARAGUAINA | J13: NORTE | K13: LD03010004 | L13: SEGUE SS PARA REGULARIZAR FALTA DE COMUNICAÇÃO DO RELIGADOR 7925713040
... A42: 2026 | B42: ETO-TELE 01050/2026 | C42: ETO-TELE | D42: 7928462040 | E42: 46240 | F42: 46252 | G42: 40 | H42: ARAGOMINAS | I42: ARAGUAINA | J42: NORTE | K42: LD04010004 | L42: PROVIDENCIAR MANUTENÇÃO PARA O RELIGADOR 7928462040 POIS O MESMO ESTA PERDENDO COMUNICAÇÃO . FOI FEITO PRIMEIRO ATAQUE COM EQUIPE 004OIP22 E LOGO PERDEU A COMUNICAÇÃO.

Sheet Criticidade por Equipamento Joa
A1: Ativo | B1: Coluna1 | C1: Tipo | D1: Localidade | E1: Polo | F1: Regional | G1: SS aberta | H1: Parecer COEP | I1: Observação | J1: Coluna2 | K1: Check de concluídas | L1: Defeito identificado | M1: Quantidade | N1: Descrição SS | O1: Premissa 1 | P1: Premissa 2 | Q1: Premissa 3 | R1: Premissa 4 | S1: Premissa 5 | T1: Premissa 6 | U1: Premissa 7 | V1: Premissa 8 | W1: Priorização | X1: Criticidade | Y1: Observação após análise | AA1: Legenda
A2: 5800090147 | B2: =_xlfn.XLOOKUP(Table2[[#This Row],[Ativo]],Joao!B:B,Joao!Z:Z) -> #N/A | C2: =MID(Table2[[#This Row],[Ativo]],1,2) -> 58 | D2: TAIPAS DO TOCANTINS | E2: DIANOPOLIS | F2: SUL | G2: =IFERROR(_xlfn.XLOOKUP(Table2[[#This Row],[Ativo]],Pendentes[COD_RELIGADOR],Pendentes[SS_ORIGINAL]),"CONCLUÍDA") -> CONCLUÍDA | H2: Cancelada em operação | K2: Ok | N2: =IFERROR(_xlfn.XLOOKUP(Table2[[#This Row],[Ativo]],Pendentes[COD_RELIGADOR],Pendentes[DESCRICAO]),"") | O2: 0 | P2: 20 | Q2: 20 | R2: 10 | S2: 10 | T2: - | U2: - | V2: - | W2: =SUM(Table2[[#This Row],[Premissa 1]:[Premissa 8]]) -> 60 | X2: Média | Y2: Atendimento de Taipas | AA2: (*) | AB2: Não houve ataque do DMSL
A3: 5800291035 | B3: =_xlfn.XLOOKUP(Table2[[#This Row],[Ativo]],Joao!B:B,Joao!Z:Z) -> #N/A | C3: =MID(Table2[[#This Row],[Ativo]],1,2) -> 58 | D3: MONTE DO CARMO | E3: PONTE ALTA TOCANTINS | F3: CENTRO | G3: =IFERROR(_xlfn.XLOOKUP(Table2[[#This Row],[Ativo]],Pendentes[COD_RELIGADOR],Pendentes[SS_ORIGINAL]),"CONCLUÍDA") -> CONCLUÍDA | H3: Aguardando comissionamento | I3: Concluído Melhoria de aterramento | K3: Em andamento | L3: Melhoria de aterramento | M3: 1 | N3: PARECER DMSL: Feito testes funcionais nas 3 células do banco as mesmas corresponderam aos testes. Será necessário fazer a correção da malha de terra, baixar o banco completo pois está muito alto dificultando as atividades da equipe, substituir as 3 chaves facas do lado Fonte e as 3 do lado Carga instalar suporte inclinado das chaves para facilitar as manobras. Colocar cinta no controle RUA abaixar o mesmo, pois está muito alto e fixado com um mosquetão oval, quando retornar para colocar em operação levar 3 baterias de 7a e rele rua.Obs.: Fizeram melhoria na malha de terra, mas não está dentro do aceitável! As outras pendências continuam, favor corrigir. Equipamento ficou em operação?: Não - Equipe: Benvindo e Kaique- SS ANTIGA ETO-TELE 358/2026 | O3: 0 | P3: 20 | Q3: 20 | R3: 10 | S3: 0 | T3: - | U3: - | V3: - | W3: =SUM(Table2[[#This Row],[Premissa 1]:[Premissa 8]]) -> 50 | X3: Média | Y3: Aumento de reclamações no atendimento de Silvanópolis por Monte do Carmo no período seco
A4: 5800291077 | B4: =_xlfn.XLOOKUP(Table2[[#This Row],[Ativo]],Joao!B:B,Joao!Z:Z) -> #N/A | C4: =MID(Table2[[#This Row],[Ativo]],1,2) -> 58 | D4: GOIATINS | E4: ARAGUAINA | F4: NORTE | G4: =IFERROR(_xlfn.XLOOKUP(Table2[[#This Row],[Ativo]],Pendentes[COD_RELIGADOR],Pendentes[SS_ORIGINAL]),"CONCLUÍDA") -> CONCLUÍDA | H4: Cancelada em operação | K4: Ok | N4: =IFERROR(_xlfn.XLOOKUP(Table2[[#This Row],[Ativo]],Pendentes[COD_RELIGADOR],Pendentes[DESCRICAO]),"") | O4: 40 | P4: 20 | Q4: 20 | R4: 20 | S4: 20 | T4: - | U4: - | V4: - | W4: =SUM(Table2[[#This Row],[Premissa 1]:[Premissa 8]]) -> 120 | X4: Muito Alta | Y4: Aumento de reclamações no atendimento de Goiatins e GAs relevantes na região
A5: 5800366016 | B5: =_xlfn.XLOOKUP(Table2[[#This Row],[Ativo]],Joao!B:B,Joao!Z:Z) -> #N/A | C5: =MID(Table2[[#This Row],[Ativo]],1,2) -> 58 | D5: WANDERLANDIA | E5: TOCANTINOPOLIS | F5: NORTE | G5: =IFERROR(_xlfn.XLOOKUP(Table2[[#This Row],[Ativo]],Pendentes[COD_RELIGADOR],Pendentes[SS_ORIGINAL]),"CONCLUÍDA") -> CONCLUÍDA | H5: Cancelada em operação | K5: Ok | N5: =IFERROR(_xlfn.XLOOKUP(Table2[[#This Row],[Ativo]],Pendentes[COD_RELIGADOR],Pendentes[DESCRICAO]),"") | O5: 0 | P5: 20 | Q5: 20 | R5: 20 | S5: 10 | T5: - | U5: - | V5: - | W5: =SUM(Table2[[#This Row],[Premissa 1]:[Premissa 8]]) -> 70 | X5: Alta | Y5: Aumento de reclamações no atendimento de Wanderlândia no período seco
A6: 5800371025 | B6: =_xlfn.XLOOKUP(Table2[[#This Row],[Ativo]],Joao!B:B,Joao!Z:Z) -> 0 | C6: =MID(Table2[[#This Row],[Ativo]],1,2) -> 58 | D6: ARAPOEMA | E6: COLINAS DO TOCANTINS | F6: NORTE | G6: =IFERROR(_xlfn.XLOOKUP(Table2[[#This Row],[Ativo]],Pendentes[COD_RELIGADOR],Pendentes[SS_ORIGINAL]),"CONCLUÍDA") -> ETO-TELE 01040/2026 | H6: Aguardando comissionamento | I6: Concluído Reporte Kelliton | K6: Em andamento | L6: Controle | M6: 1 | N6: =IFERROR(_xlfn.XLOOKUP(Table2[[#This Row],[Ativo]],Pendentes[COD_RELIGADOR],Pendentes[DESCRICAO]),"") -> 16/07/2026 PARECER COEP: ALINHADO COM O KELLITON REALIZAR SUBSTITUIÇÃO DO CONTROLE DE TUPIRAMA, ALINHADO COM O JEAN QUE OS CABOS COMPATIBILIZADORES VÃO CHEGAR 16/08 , ATÉ ESSA DATA MANTER ESSA SS E CONTROLE RUA, DEPOIS REPASSAR PARA O DMSLPARECER COEP: AVALIAR COM O LEANDRO, PROVAVELMENTE SÓ COMPRAPARECER DMSL: Após testes foi constatado defeito nos relés da fase A e B, Modelo Toshiba TBR 1000. Se possível, substituir os relés das 3 fases por controle RUA, disponibilizar os cabos de ligação entre o tanque e o controle para possibilitar a compatibilização do equipamento. Fornecer kit de comunicação, rádio, antena, etc.Segue nota para veriifcar falha em regulador de tensão N: 5800371025 dentro S/E Arapoema , equipamento esta com 2 reles com falha marca toshiba .Parecer DCMD: foi substituido célula 30/07/2026. o mesmo está liberado para ser colocado em operação | O6: 0 | P6: 20 | Q6: 20 | R6: 10 | S6: 20 | T6: - | U6: - | V6: - | W6: =SUM(Table2[[#This Row],[Premissa 1]:[Premissa 8]]) -> 70 | X6: Alta | Y6: Aumento de reclamações no atendimento de Arapoema no período seco
A7: 5800438116 | B7: =_xlfn.XLOOKUP(Table2[[#This Row],[Ativo]],Joao!B:B,Joao!Z:Z) -> NÃO PRECISA REQUISITAR EQUIPAMENTO, VAMOS UTILIZAR EQ RETIRADO DE OBRA DE CONSTRUÇÃO. | C7: =MID(Table2[[#This Row],[Ativo]],1,2) -> 58 | D7: CHAPADA DA NATIVIDADE | E7: DIANOPOLIS | F7: SUL | G7: =IFERROR(_xlfn.XLOOKUP(Table2[[#This Row],[Ativo]],Pendentes[COD_RELIGADOR],Pendentes[SS_ORIGINAL]),"CONCLUÍDA") -> CONCLUÍDA | H7: Concluído DCMD e DMSL | I7: Reporte Dener | K7: Em andamento | L7: Célula | M7: 2 | N7: =IFERROR(_xlfn.XLOOKUP(Table2[[#This Row],[Ativo]],Pendentes[COD_RELIGADOR],Pendentes[DESCRICAO]),"") | O7: 0 | P7: 20 | Q7: 20 | R7: 20 | S7: 0 | T7: - | U7: - | V7: - | W7: =SUM(Table2[[#This Row],[Premissa 1]:[Premissa 8]]) -> 60 | X7: Média | Y7: Atendimento da região da Engegold, Nativa, cidade Natividade e Chapada da Natividade (Fonte alternativa)
A8: 5800440256 | B8: =_xlfn.XLOOKUP(Table2[[#This Row],[Ativo]],Joao!B:B,Joao!Z:Z) -> #N/A | C8: =MID(Table2[[#This Row],[Ativo]],1,2) -> 58 | D8: MATEIROS | E8: PONTE ALTA TOCANTINS | F8: CENTRO | G8: =IFERROR(_xlfn.XLOOKUP(Table2[[#This Row],[Ativo]],Pendentes[COD_RELIGADOR],Pendentes[SS_ORIGINAL]),"CONCLUÍDA") -> ETO-COEP 00169/2026 | H8: Cancelada em operação | K8: Ok | N8: =IFERROR(_xlfn.XLOOKUP(Table2[[#This Row],[Ativo]],Pendentes[COD_RELIGADOR],Pendentes[DESCRICAO]),"") -> PARECER DMSL 06/08: Substituir célula da Fase B do banco de Regulador de tensão e realizar melhorias na malha de aterramento do ReguladorBoa noite,Segue SS para as devidas tratativas, verificar flutuação de tensão do regulador 5800440256 pois a tensão está oscilando de 16kv a 23kv favor verificar esta anomalia pois cliente BRK está abrindo reclamação todas as noites. | O8: 20 | P8: 20 | Q8: 20 | R8: 10 | S8: 20 | T8: - | U8: - | V8: - | W8: =SUM(Table2[[#This Row],[Premissa 1]:[Premissa 8]]) -> 90 | X8: Muito Alta | Y8: Aumento de reclamações no atendimento de São Felix e Mateiros no período seco
A9: 5800859011 | B9: =_xlfn.XLOOKUP(Table2[[#This Row],[Ativo]],Joao!B:B,Joao!Z:Z) -> 0 | C9: =MID(Table2[[#This Row],[Ativo]],1,2) -> 58 | D9: TUPIRAMA | E9: GUARAI | F9: NORTE | G9: =IFERROR(_xlfn.XLOOKUP(Table2[[#This Row],[Ativo]],Pendentes[COD_RELIGADOR],Pendentes[SS_ORIGINAL]),"CONCLUÍDA") -> CONCLUÍDA | H9: Concluído DCMD | I9: Equipamento alinhado com o Jean para colocar os cabos compatibilizadores , vamos só instalar o controle e o suporte | J9: Report Kelliton | K9: Em andamento | L9: Controle | M9: 1 | N9: =IFERROR(_xlfn.XLOOKUP(Table2[[#This Row],[Ativo]],Pendentes[COD_RELIGADOR],Pendentes[DESCRICAO]),"") | O9: 40 | P9: 20 | Q9: 20 | R9: 10 | S9: 20 | T9: - | U9: - | V9: - | W9: =SUM(Table2[[#This Row],[Premissa 1]:[Premissa 8]]) -> 110 | X9: Muito Alta | Y9: Atendimento de parte da RDU Guaraí por fonte alternativa
A10: 5800961074 | B10: =_xlfn.XLOOKUP(Table2[[#This Row],[Ativo]],Joao!B:B,Joao!Z:Z) -> #N/A | C10: =MID(Table2[[#This Row],[Ativo]],1,2) -> 58 | D10: DIANOPOLIS | E10: DIANOPOLIS | F10: SUL | G10: =IFERROR(_xlfn.XLOOKUP(Table2[[#This Row],[Ativo]],Pendentes[COD_RELIGADOR],Pendentes[SS_ORIGINAL]),"CONCLUÍDA") -> ETO-COEP 00221/2025 | H10: Equipamento em Logistica | I10: Vamos retirar de uma obra de construção de uma linha antiga e usar na manutenção | K10: Pendente | L10: Células + melhoria de aterramento | M10: 3 | N10: =IFERROR(_xlfn.XLOOKUP(Table2[[#This Row],[Ativo]],Pendentes[COD_RELIGADOR],Pendentes[DESCRICAO]),"") -> PARECER COEP: EQUIPAMENTO SELECIONADO PARA COMPRASubstituir as 3 células- Melhoria na malha de aterramento - Melhoria no circuito de aterramento qua aterra as células.- Substituir conectores paralelos | O10: 20 | P10: 0 | Q10: 0 | R10: 20 | S10: 0 | T10: - | U10: - | V10: - | W10: =SUM(Table2[[#This Row],[Premissa 1]:[Premissa 8]]) -> 40 | X10: Média | Y10: Atendimento da COELBA e GA Alessandro Maurício (1600 kVA)
A11: 5801866013 | B11: =_xlfn.XLOOKUP(Table2[[#This Row],[Ativo]],Joao!B:B,Joao!Z:Z) -> Aguardando previsão de substituição | C11: =MID(Table2[[#This Row],[Ativo]],1,2) -> 58 | D11: PARAISO DO TOCANTINS | E11: PARAISO DO TOCANTINS | F11: CENTRO | G11: =IFERROR(_xlfn.XLOOKUP(Table2[[#This Row],[Ativo]],Pendentes[COD_RELIGADOR],Pendentes[SS_ORIGINAL]),"CONCLUÍDA") -> ETO-PROT 00151/2026 | H11: Em fase de ajustes | K11: Em andamento | L11: Célula | M11: 1 | N11: =IFERROR(_xlfn.XLOOKUP(Table2[[#This Row],[Ativo]],Pendentes[COD_RELIGADOR],Pendentes[DESCRICAO]),"") -> 15/07 PARECER COCM, FOI ATENDIDA PELA OS ETO-RD-PS 1616/2026 OBRA-021260053910/07 PARECER COEP: EQUIPAMENTO ENTREGUE AOS COCM´S FAVOR INFORMAR PRAZO DE SUBSTUIÇÃO PARA O DMSL E REPASSAR DEPOIS PARA PROTEÇÃO REALIZAR OS AJUSTES E DESCREVER NA SS O SERVIÇO REALIZADOPARECER COEP: EM PROCESSO DE ENTREGAPARECER DMSL: RT 5801866013Serviço Executado: Feito a medição da malha de terra. Identificado infiltração na caixa de passagem da célula da fase C do banco regulador de tensão, será necessário fazer a substituição da mesma! Ficar atento na hora da substituição, deverá ser substituída a célula do lado da BR.Obs.: Será necessário baixar todo o banco pelo menos um metro, as buchas estão muito próximas a parte energizada não oferecem segurança para equipe no momento do ensaio elétrico.Equipamento ficou em operação?: Não Possui nobreak: SimPossui antena: SimPossui rádio:SimPendência: SimData da bateria: Equipe: Benvindo e Kaique._______________________________________________RT 5801866013BY PASSADO DEVIDO DEFEITO EM CELULA BEMVINDO ESTEVE NO LOCAL JUNTO AO COD .NECESSARIO TRATATIVA PARA MESMA .FASE DANIFICADO C | O11: 0 | P11: 20 | Q11: 20 | R11: 20 | S11: 10 | T11: - | U11: - | V11: - | W11: =SUM(Table2[[#This Row],[Premissa 1]:[Premissa 8]]) -> 70 | X11: Alta | Y11: Atendimento da RDU Luzimangues Industrial por fonte alternativa
A12: 5803327001 | B12: =_xlfn.XLOOKUP(Table2[[#This Row],[Ativo]],Joao!B:B,Joao!Z:Z) -> #N/A | C12: =MID(Table2[[#This Row],[Ativo]],1,2) -> 58 | D12: PORTO NACIONAL | E12: PORTO NACIONAL | F12: CENTRO | G12: =IFERROR(_xlfn.XLOOKUP(Table2[[#This Row],[Ativo]],Pendentes[COD_RELIGADOR],Pendentes[SS_ORIGINAL]),"CONCLUÍDA") -> ETO-COEP 00149/2026 | H12: Em processo logístico | I12: Aguardando o Marcelo Primo gerar a obra em abertura contabil | K12: Em andamento | L12: Controle e aterramento | M12: 1 | N12: =IFERROR(_xlfn.XLOOKUP(Table2[[#This Row],[Ativo]],Pendentes[COD_RELIGADOR],Pendentes[DESCRICAO]),"") -> 01/07 PARECER COEP: FOI CONFIRMADO COM A OPERAÇÃO QUE O EQUIPAMENTO SEGUIU O FLUXO INTEIRO DE COMISSIONAMENTO, PROTEÇÃO, FAVOR EXPLICAR O QUE FOI REALIZADO E SE EQUIPAMENTO ESTÁ OPERANDO, SENÃO ESTIVER EXPLICAR O QUE FOI FEITO NELE30/06PARECER COEP: REPASSAR DIRETAMENTE PARA OS COCM'SRegulador 5803327001 fora de operação, by passado em campo com painel de comunicação com cabos desconectados tensão 13.8.parecer DMSL: Feedback Equip. EspeciaisRT 5803327001RELÉ RUASid: 4844Data: 19/09/2025Serviço realizado:*Equipamento foi remanejado, 7 km da sua localização sentido Palmas necessário comissionamento completo*Equipamento com um dos cabos umbilicais danificado.* aterramento bucha FC não esta interligada corretamente * para-raios estão no mesmo aterramento da bucha FC.* Tranques muito alto e próximo da rede não permitindo o comissionamento com segurança.* Controle alto demais tem que baixar Equipamento ficou em operação?: nãoPendência: sim, precisa comissionar completoOBS | O12: 40 | P12: 0 | Q12: 0 | R12: 20 | S12: 20 | T12: - | U12: - | V12: - | W12: =SUM(Table2[[#This Row],[Premissa 1]:[Premissa 8]]) -> 80 | X12: Alta | Y12: Em caso de perca da fonte principal é necessário esse RT para alimentação da Frísia
A13: 5820790038 | B13: =_xlfn.XLOOKUP(Table2[[#This Row],[Ativo]],Joao!B:B,Joao!Z:Z) -> #N/A | C13: =MID(Table2[[#This Row],[Ativo]],1,2) -> 58 | D13: TAGUATINGA | E13: DIANOPOLIS | F13: SUL | G13: =IFERROR(_xlfn.XLOOKUP(Table2[[#This Row],[Ativo]],Pendentes[COD_RELIGADOR],Pendentes[SS_ORIGINAL]),"CONCLUÍDA") -> CONCLUÍDA | H13: Cancelada em operação | N13: =IFERROR(_xlfn.XLOOKUP(Table2[[#This Row],[Ativo]],Pendentes[COD_RELIGADOR],Pendentes[DESCRICAO]),"") | W13: =SUM(Table2[[#This Row],[Premissa 1]:[Premissa 8]]) -> 0
A14: 5827102054 | B14: =_xlfn.XLOOKUP(Table2[[#This Row],[Ativo]],Joao!B:B,Joao!Z:Z) -> Cancelar a obra tentar vedação do equipamento Melhoria de aterramento | C14: =MID(Table2[[#This Row],[Ativo]],1,2) -> 58 | D14: PUGMIL | E14: PARAISO DO TOCANTINS | F14: CENTRO | G14: =IFERROR(_xlfn.XLOOKUP(Table2[[#This Row],[Ativo]],Pendentes[COD_RELIGADOR],Pendentes[SS_ORIGINAL]),"CONCLUÍDA") -> ETO-PROT 00164/2026 | H14: Aguardando comissionamento | I14: Concluído poço para melhoria de aterramento aberto | L14: Melhoria de aterramento | M14: 1 | N14: =IFERROR(_xlfn.XLOOKUP(Table2[[#This Row],[Ativo]],Pendentes[COD_RELIGADOR],Pendentes[DESCRICAO]),"") -> PARECER COCM: FOI SUBSTITUÍDO OS EQUIPAMENTO FEITO A MELHORIA DO ATERRAMENTO ATENDIDO PELA OBRA N-0212600609PARECER COEP:NÃO É POSSÍVEL RETORNAR COM O CONTROLE COMPLETO , MAS DARIA PARA FAZER A MELHORIA NA MALHA DE ATERRAMENTO , ENCAMINHANDO PARA OS COCM'S PARA REALIZAREM A MELHORIAparecer DMSL: :Nobreack com defeito, rele queimado, cabo de comunicação entre o rádio e o rele danificado, malha de aterramento está com a resistência alta!Feito reparo no cabo, substituído nobreack, e rele. Se possível retornar com controle completo pq o q está em campo teve infiltração de água, abrir chamado no scada para atualizar base do equipamento pois o mesmo está com a base antiga, fazer correção da malha de aterramento.Equipamento ficou em operação?: Não Pendência: sim, levar controle novo, fazer correção da malha de terra, levar suporte para fixar antena. OBS | O14: 0 | P14: 20 | Q14: 20 | R14: 10 | S14: 0 | T14: - | U14: - | V14: - | W14: =SUM(Table2[[#This Row],[Premissa 1]:[Premissa 8]]) -> 50 | X14: Média | Y14: Aumento de reclamações no atendimento de Pugmil no período seco
A15: 5836764032 | B15: =_xlfn.XLOOKUP(Table2[[#This Row],[Ativo]],Joao!B:B,Joao!Z:Z) -> #N/A | C15: =MID(Table2[[#This Row],[Ativo]],1,2) -> 58 | D15: ARAGUACU | E15: ALVORADA | F15: SUL | G15: =IFERROR(_xlfn.XLOOKUP(Table2[[#This Row],[Ativo]],Pendentes[COD_RELIGADOR],Pendentes[SS_ORIGINAL]),"CONCLUÍDA") -> CONCLUÍDA | H15: Cancelada em operação | K15: Ok | N15: =IFERROR(_xlfn.XLOOKUP(Table2[[#This Row],[Ativo]],Pendentes[COD_RELIGADOR],Pendentes[DESCRICAO]),"") | O15: 40 | P15: 20 | Q15: 20 | R15: 10 | S15: 20 | T15: - | U15: - | V15: - | W15: =SUM(Table2[[#This Row],[Premissa 1]:[Premissa 8]]) -> 110 | X15: Muito Alta | Y15: Aumento de reclamações no atendimento de Araguaçu no período seco
A16: 5836786094 | B16: =_xlfn.XLOOKUP(Table2[[#This Row],[Ativo]],Joao!B:B,Joao!Z:Z) -> Aguardando criação da Obra | C16: =MID(Table2[[#This Row],[Ativo]],1,2) -> 58 | D16: PEIXE | E16: PEIXE | F16: SUL | G16: =IFERROR(_xlfn.XLOOKUP(Table2[[#This Row],[Ativo]],Pendentes[COD_RELIGADOR],Pendentes[SS_ORIGINAL]),"CONCLUÍDA") -> ETO-COEP 00095/2026 | H16: Em processo logístico | I16: Previsão de entrega 16/08 | K16: Em andamento | L16: Célula | M16: 1 | N16: =IFERROR(_xlfn.XLOOKUP(Table2[[#This Row],[Ativo]],Pendentes[COD_RELIGADOR],Pendentes[DESCRICAO]),"") -> 24/07 PARECER COEP:EQUIPAMENTO EM LOGISTICA DE ENTREGA Favor levar outro regulador de tensão, pois o mesmo foi furtado em campo. | O16: 0 | P16: 0 | Q16: 0 | R16: 10 | S16: 10 | T16: - | U16: - | V16: - | W16: =SUM(Table2[[#This Row],[Premissa 1]:[Premissa 8]]) -> 20 | X16: Baixa | Y16: Atendimento de clientes rurais na LD Peixe Angical - Peixe
A17: 5839141113 | B17: =_xlfn.XLOOKUP(Table2[[#This Row],[Ativo]],Joao!B:B,Joao!Z:Z) -> #N/A | C17: =MID(Table2[[#This Row],[Ativo]],1,2) -> 58 | G17: =IFERROR(_xlfn.XLOOKUP(Table2[[#This Row],[Ativo]],Pendentes[COD_RELIGADOR],Pendentes[SS_ORIGINAL]),"CONCLUÍDA") -> ETO-TELE 00985/2026 | H17: Primeiro ataque DMSL | N17: =IFERROR(_xlfn.XLOOKUP(Table2[[#This Row],[Ativo]],Pendentes[COD_RELIGADOR],Pendentes[DESCRICAO]),"") -> Segue nota para averiguar ajuste regulador de tensão N: 5839141113 - RDU - Couto Magalhães , e verificar falha de comunicação .Equipe operacional verificou que vários transformadores urbanos estão com nível de tensão baixa .Foi feito primeiro ataque regulador está comutando normalmente as 3 fases , porém não está no nível adequado !Em campo regulador estava no Tap R1 - 02 , R2 + 01 , R3 +03Medições feitas :Transformador 5700010113 - NA: 205 NB: 206 NC: 210Transformador 5700011113 - NA: 204 NB: 206 NC: 209Transformador 5700333113 -NA: 205 NB: 207 NC: 208OBS: solicitar equipe para realizar medição aterramento , e verificar ajuste junto ao time proteção . verificar falha de comunicação no equipamento . | W17: =SUM(Table2[[#This Row],[Premissa 1]:[Premissa 8]]) -> 0
A18: 5840227063 | B18: =_xlfn.XLOOKUP(Table2[[#This Row],[Ativo]],Joao!B:B,Joao!Z:Z) -> #N/A | C18: =MID(Table2[[#This Row],[Ativo]],1,2) -> 58 | D18: BANDEIRANTES DO TOCANTINS | E18: COLINAS DO TOCANTINS | F18: NORTE | G18: =IFERROR(_xlfn.XLOOKUP(Table2[[#This Row],[Ativo]],Pendentes[COD_RELIGADOR],Pendentes[SS_ORIGINAL]),"CONCLUÍDA") -> ETO-COEP 00151/2026 | H18: Em processo de aquisição | K18: Pendente | L18: Célula | M18: 1 | N18: =IFERROR(_xlfn.XLOOKUP(Table2[[#This Row],[Ativo]],Pendentes[COD_RELIGADOR],Pendentes[DESCRICAO]),"") -> PARECER COEP 27/07/2026 : EM PROCESSO DE AQUISIÇÃOPARECER DMSL 13/07/2026: Realizados ensaios de isolação nas três células, e foi identificado curto na fase A, sendo necessário a sua substituição. Os cabos das buchas ficaram desconectados para melhor identificação no momento da sua substituiçãSEGUE PARA O DMSL AVALIAR ANTES DE SEGUIRMOS COM O SERVIÇOSEGUE PARA REALIZAR TROCA---------------------------------------------------------Boa noite,Segue SS para tratativas regulador de tensão 5840227063 fase C em curto | O18: 0 | P18: 20 | Q18: 20 | R18: 10 | S18: 10 | T18: - | U18: - | V18: - | W18: =SUM(Table2[[#This Row],[Premissa 1]:[Premissa 8]]) -> 60 | X18: Média | Y18: Atendimento da RDU Bandeirantes e clientes rurais
A19: 5841308190 | B19: =_xlfn.XLOOKUP(Table2[[#This Row],[Ativo]],Joao!B:B,Joao!Z:Z) -> #N/A | C19: =MID(Table2[[#This Row],[Ativo]],1,2) -> 58 | D19: NOVO JARDIM | E19: DIANOPOLIS | F19: SUL | G19: =IFERROR(_xlfn.XLOOKUP(Table2[[#This Row],[Ativo]],Pendentes[COD_RELIGADOR],Pendentes[SS_ORIGINAL]),"CONCLUÍDA") -> CONCLUÍDA | H19: Desmobilizado | I19: Tratativas do Allan | K19: Desmobilizado | L19: - | N19: =IFERROR(_xlfn.XLOOKUP(Table2[[#This Row],[Ativo]],Pendentes[COD_RELIGADOR],Pendentes[DESCRICAO]),"") | O19: 0 | P19: 20 | Q19: 0 | R19: 10 | S19: 0 | T19: - | U19: - | V19: - | W19: =SUM(Table2[[#This Row],[Premissa 1]:[Premissa 8]]) -> 30 | X19: Baixa | Y19: Equipamento obsoleto com a entrada da SE Serras Gerais
A20: 5844630060 | B20: =_xlfn.XLOOKUP(Table2[[#This Row],[Ativo]],Joao!B:B,Joao!Z:Z) -> Entrega 16/07 | C20: =MID(Table2[[#This Row],[Ativo]],1,2) -> 58 | D20: NOVA OLINDA | E20: COLINAS DO TOCANTINS | F20: NORTE | G20: =IFERROR(_xlfn.XLOOKUP(Table2[[#This Row],[Ativo]],Pendentes[COD_RELIGADOR],Pendentes[SS_ORIGINAL]),"CONCLUÍDA") -> ETO-TELE 01102/2026 | H20: Equipamento entregue aos COCM's | I20: Previsão de entrega 20/07 // Foi entregue a eles verificar o porque eles baixaram | K20: Em andamento | L20: Célula | M20: 1 | N20: =IFERROR(_xlfn.XLOOKUP(Table2[[#This Row],[Ativo]],Pendentes[COD_RELIGADOR],Pendentes[DESCRICAO]),"") -> Segue nota para verificar falha em comandos via supervisório e constantes travamento no regulador de tensão 5844630060 - rural- Nova Olinda .Foi executado comandos no relé via supervisório, porém sem sucesso , em campo o equipamento está com a fase B travada no -16 .Obs: equipamento ficou fora de operação bay passado , favor agilizar atendimento ! | O20: 20 | P20: 0 | Q20: 0 | R20: 10 | S20: 0 | T20: - | U20: - | V20: - | W20: =SUM(Table2[[#This Row],[Premissa 1]:[Premissa 8]]) -> 30 | X20: Baixa | Y20: Atendimento dos ramais PA Remansão e Água Branca
A21: 5846328094 | B21: =_xlfn.XLOOKUP(Table2[[#This Row],[Ativo]],Joao!B:B,Joao!Z:Z) -> #N/A | C21: =MID(Table2[[#This Row],[Ativo]],1,2) -> 58 | D21: PEIXE | E21: PEIXE | F21: SUL | G21: =IFERROR(_xlfn.XLOOKUP(Table2[[#This Row],[Ativo]],Pendentes[COD_RELIGADOR],Pendentes[SS_ORIGINAL]),"CONCLUÍDA") -> ETO-TELE 00986/2026 | H21: Aguardando comissionamento | K21: Em andamento | L21: Melhoria de aterramento | M21: 1 | N21: =IFERROR(_xlfn.XLOOKUP(Table2[[#This Row],[Ativo]],Pendentes[COD_RELIGADOR],Pendentes[DESCRICAO]),"") -> COCM SUL - 07/07/2026 - FOI REALIZADO MELHORIA DE ATERRAMENTO E FEITO A MANUTENÇÕES E TODAS AS CHAVES E SUBSTITUIDO OS CONECTORES.PARECER COEP: MELHORIA DE ATERRAMENTO É COCM'S, FAVOR ENCAMINHAR DIRETAMENTE PARA ELES, COCM'S REALIZAR MELHORIA DE ATERRAMENTO POR FAVORPor genteliiza verificar RT 5846328094 situação de equipamento, se encontra by passado em campoPARECER DMSL:Favor, realizar melhoria de aterramento que se encontra alta e substituir todos os conectores das buchas por conectores estrangulador. | O21: 0 | P21: 20 | Q21: 20 | R21: 10 | S21: 10 | T21: - | U21: - | V21: - | W21: =SUM(Table2[[#This Row],[Premissa 1]:[Premissa 8]]) -> 60 | X21: Média | Y21: Atendimento da RDU Sucupira e clientes rurais
A22: 5848305116 | B22: =_xlfn.XLOOKUP(Table2[[#This Row],[Ativo]],Joao!B:B,Joao!Z:Z) -> #N/A | C22: =MID(Table2[[#This Row],[Ativo]],1,2) -> 58 | G22: =IFERROR(_xlfn.XLOOKUP(Table2[[#This Row],[Ativo]],Pendentes[COD_RELIGADOR],Pendentes[SS_ORIGINAL]),"CONCLUÍDA") -> CONCLUÍDA | H22: Primeiro ataque DMSL | N22: =IFERROR(_xlfn.XLOOKUP(Table2[[#This Row],[Ativo]],Pendentes[COD_RELIGADOR],Pendentes[DESCRICAO]),"") | W22: =SUM(Table2[[#This Row],[Premissa 1]:[Premissa 8]]) -> 0
A23: 5850308009 | B23: =_xlfn.XLOOKUP(Table2[[#This Row],[Ativo]],Joao!B:B,Joao!Z:Z) -> Equipamento em operação em campo de acordo com a visita do Luanderson tem fotos Equipamento já em operação , realocar controle de Regulador para Arapoema 5800371025 | C23: =MID(Table2[[#This Row],[Ativo]],1,2) -> 58 | D23: GUARAI | E23: GUARAI | F23: NORTE | G23: =IFERROR(_xlfn.XLOOKUP(Table2[[#This Row],[Ativo]],Pendentes[COD_RELIGADOR],Pendentes[SS_ORIGINAL]),"CONCLUÍDA") -> CONCLUÍDA | H23: Cancelada em operação | K23: Ok | N23: =IFERROR(_xlfn.XLOOKUP(Table2[[#This Row],[Ativo]],Pendentes[COD_RELIGADOR],Pendentes[DESCRICAO]),"") | O23: 0 | P23: 20 | Q23: 20 | R23: 0 | S23: 10 | T23: - | U23: - | V23: - | W23: =SUM(Table2[[#This Row],[Premissa 1]:[Premissa 8]]) -> 50 | X23: Média | Y23: Atendimento de parte da RDU de Guaraí e ramal da PRF/Repetidora
A24: 5851753086 | B24: =_xlfn.XLOOKUP(Table2[[#This Row],[Ativo]],Joao!B:B,Joao!Z:Z) -> #N/A | C24: =MID(Table2[[#This Row],[Ativo]],1,2) -> 58 | D24: MARIANOPOLIS | E24: DIVINOPOLIS | F24: CENTRO | G24: =IFERROR(_xlfn.XLOOKUP(Table2[[#This Row],[Ativo]],Pendentes[COD_RELIGADOR],Pendentes[SS_ORIGINAL]),"CONCLUÍDA") -> CONCLUÍDA | H24: Aguardando comissionamento | K24: Em andamento | L24: Melhoria de aterramento | M24: 1 | N24: =IFERROR(_xlfn.XLOOKUP(Table2[[#This Row],[Ativo]],Pendentes[COD_RELIGADOR],Pendentes[DESCRICAO]),"") | O24: 0 | P24: 20 | Q24: 20 | R24: 10 | S24: 10 | T24: - | U24: - | V24: - | W24: =SUM(Table2[[#This Row],[Premissa 1]:[Premissa 8]]) -> 60 | X24: Média | Y24: Atendimento da RDU Marianópolis e clientes rurais
A25: 5853360007 | B25: =_xlfn.XLOOKUP(Table2[[#This Row],[Ativo]],Joao!B:B,Joao!Z:Z) -> Melhoria de aterramento | C25: =MID(Table2[[#This Row],[Ativo]],1,2) -> 58 | D25: MIRACEMA DO TOCANTINS | E25: MIRACEMA DO TOCANTINS | F25: CENTRO | G25: =IFERROR(_xlfn.XLOOKUP(Table2[[#This Row],[Ativo]],Pendentes[COD_RELIGADOR],Pendentes[SS_ORIGINAL]),"CONCLUÍDA") -> ETO-RD-PS 00323/2025 | H25: Problema na autorização de passagem | I25: Cliente não autorizou entrar na propriedade | L25: Melhoria de aterramento | M25: 1 | N25: =IFERROR(_xlfn.XLOOKUP(Table2[[#This Row],[Ativo]],Pendentes[COD_RELIGADOR],Pendentes[DESCRICAO]),"") -> REALIZAR TESTES NO EQUIPAMENTO E CONFERIR MEDIÇÕES DA MALHA DE ATERRAMENTO. ESTANDO OK, COMISSIONAR EQUIPAMENTO E COLOCA-LO EM OPERAÇÃO.AJUSTES DISPONIVEIS NO APP DA PROTEÇÃdmsl : N° do Equipamento:*RT 5853360007 MIRACEMASID: 2493/2025Data: 13/05/2025Serviço Executado Provavelmente ocorreu uma descarga no equipamento comprometendo a malha!Será necessário fazer melhoria da malha de aterramento, fazer toda interligação da mesma! Feito ensaios de isolação das 3 células do equipamento, isolação está ok, quando retornar para colocar em operação levar 3 baterias de 7a.Equipamento ficou em operação?: Não Equipe: Benvindo e Jardel | O25: 0 | P25: 20 | Q25: 20 | R25: 10 | S25: 20 | T25: - | U25: - | V25: - | W25: =SUM(Table2[[#This Row],[Premissa 1]:[Premissa 8]]) -> 70 | X25: Alta | Y25: Aumento de reclamações no atendimento de Miracema no período seco
A26: 5854566043 | B26: =_xlfn.XLOOKUP(Table2[[#This Row],[Ativo]],Joao!B:B,Joao!Z:Z) -> Aguardando previsão de substituição | C26: =MID(Table2[[#This Row],[Ativo]],1,2) -> 58 | D26: SILVANOPOLIS | E26: PORTO NACIONAL | F26: CENTRO | G26: =IFERROR(_xlfn.XLOOKUP(Table2[[#This Row],[Ativo]],Pendentes[COD_RELIGADOR],Pendentes[SS_ORIGINAL]),"CONCLUÍDA") -> ETO-PROT 00158/2026 | H26: Concluído DCMD24/07 | J26: Report Edson | K26: Em andamento | L26: Célula | M26: 1 | N26: =IFERROR(_xlfn.XLOOKUP(Table2[[#This Row],[Ativo]],Pendentes[COD_RELIGADOR],Pendentes[DESCRICAO]),"") -> 24/07/2026 - PARECE COCM: EQUIPAMENTO SUBSTITUIDO NA OBRA 0312600352 OS: ETO-RD-PO 1873/202622/07/2026 PARECER COEP: EQUIPAMENTO ENTREGUE AOS COCM´SPRAZO DE 7 DIAS CONTANDO O SLA.PARECER COEP: EQUIPAMENTO ENTREGUE AOS COCM´S FAVOR SUSBSTTUIR , E AGUARDO O PRAZO DE PREVISÃO DE SUBSTIUIÇÃOboa noite,segue SS para as devidas tratativas com equipe de manutenção com apoio de equipe de linha viva substituir regulador de tensão 5854566043 queimado célula fase c, LD Porto / Silvanópolis mesmo deverá ser substituído com apoio de equipe de linha viva PARECER DMSL: Foi realizado inspeção visual e ensaios de isolação, relação de transformação e resistência de enrolamento. A fase B está danificada e será necessário substituir a mesma. Malha de aterramento está relativamente boa e conectada. Fase A e C passaram nos ensaios. Substituir fase B. | O26: 40 | P26: 20 | Q26: 20 | R26: 10 | S26: 20 | T26: - | U26: - | V26: - | W26: =SUM(Table2[[#This Row],[Premissa 1]:[Premissa 8]]) -> 110 | X26: Muito Alta | Y26: Aumento de reclamações no atendimento de Silvanópolis por Porto Nacional no período seco (Outra fonte com defeito também)
A27: 5855411017 | B27: =_xlfn.XLOOKUP(Table2[[#This Row],[Ativo]],Joao!B:B,Joao!Z:Z) -> Aguardando previsão de substituição | C27: =MID(Table2[[#This Row],[Ativo]],1,2) -> 58 | D27: BARROLANDIA | E27: MIRACEMA DO TOCANTINS | F27: CENTRO | G27: =IFERROR(_xlfn.XLOOKUP(Table2[[#This Row],[Ativo]],Pendentes[COD_RELIGADOR],Pendentes[SS_ORIGINAL]),"CONCLUÍDA") -> ETO-COEP 00156/2026 | H27: Em processo de aquisição | K27: Pendente | L27: Controle | M27: 1 | N27: =IFERROR(_xlfn.XLOOKUP(Table2[[#This Row],[Ativo]],Pendentes[COD_RELIGADOR],Pendentes[DESCRICAO]),"") -> 20/07 PARECER COCM: NÃO RECEBEMOS MATERIAL10/07 PARECER COEP: EQUIPAMENTO ENTREGUE AOS COCM´S FAVOR INFORMAR PRAZO DE SUBSTUIÇÃO PARA O DMSL E REPASSAR DEPOIS PARA PROTEÇÃO REALIZAR OS AJUSTES E DESCREVER NA SS O SERVIÇO REALIZADOPARECER COEP: EQUIPAMENTO EM ROTA DE ENTREGASEM COMUNICAÇÃO, FALHA DE ALIMENTAÇÃO - REALIZADO PRIMEIRO ATAQUE SEM SUCESSO.PARECER DMSL: 17/09/2025 Equipamento ficou em operação? Não Pendência: sim. Equipamento ficou Bay passado levar controle COMPLETO para trocar. ellisfran | O27: 0 | P27: 0 | Q27: 0 | R27: 10 | S27: 20 | T27: - | U27: - | V27: - | W27: =SUM(Table2[[#This Row],[Premissa 1]:[Premissa 8]]) -> 30 | X27: Baixa | Y27: Atendimento do Assentamento Irmã Adelaide
A28: 5856070091 | B28: =_xlfn.XLOOKUP(Table2[[#This Row],[Ativo]],Joao!B:B,Joao!Z:Z) -> REQUISITAR 03 PEÇAS POIS 02 PÇ FOI RETIRADA PARA INSTALAÇÃO EM OBRA DE CONSTRUÇÃO. | C28: =MID(Table2[[#This Row],[Ativo]],1,2) -> 58 | D28: ALMAS | E28: DIANOPOLIS | F28: SUL | G28: =IFERROR(_xlfn.XLOOKUP(Table2[[#This Row],[Ativo]],Pendentes[COD_RELIGADOR],Pendentes[SS_ORIGINAL]),"CONCLUÍDA") -> ETO-RD-DP 00479/2026 | H28: Equipamento entregue ao COCM | I28: Previsão de substituição 07/08// Nova previsão de entrega 21/08 se a DB Machado for para o Sul | K28: Em andamento | L28: Células + controle | M28: 3 | N28: =IFERROR(_xlfn.XLOOKUP(Table2[[#This Row],[Ativo]],Pendentes[COD_RELIGADOR],Pendentes[DESCRICAO]),"") -> PARECER DMSL: não foi regularizado a instalação do equipamento, nota repassada conforme alinhado com o supervisor.____________________________________________COCMS 26.03.26. SS REPASSADA PARA COEP PROVIDENCIAR MATERIAL. NÃO TEMOS AS PÇ EM ESTOQUE PARA FAZER A SUBSTITUIÇÃO. Solicitação de serviço para reposição de equipamentos furtados .COEP: Equipamento fornecido ao COCM-S para regularização.COCMS: Equipamento substituido conforme solicitado. Gentileza comissionar.PARECER DA PROTEÇÃO:SEGUE NOTA REPASSADA PARA DMSL COMISSIONAR.ENG° IRLLEY CASTELO BRANCOPARECER DMSL(23/09/2025): Feito a parte de comunicação, fechando enlace, configuração do rádio GE. Feito a medição de aterramento. Após uma inspeção, foi identificado que o regulador de tensão está instalado errado, carga está para o lado de fonte e fonte está do lado de carga. O certo é a fonte vim de almas, atualmente está vindo de natividade. Favor fazer a instalação correta. | O28: 40 | P28: 20 | Q28: 20 | R28: 20 | S28: 0 | T28: - | U28: - | V28: - | W28: =SUM(Table2[[#This Row],[Premissa 1]:[Premissa 8]]) -> 100 | X28: Muito Alta | Y28: Atendimento da região da Engegold, Nativa, cidade Natividade e Chapada da Natividade
A29: 5856156091 | B29: =_xlfn.XLOOKUP(Table2[[#This Row],[Ativo]],Joao!B:B,Joao!Z:Z) -> #N/A | C29: =MID(Table2[[#This Row],[Ativo]],1,2) -> 58 | D29: ALMAS | E29: DIANOPOLIS | F29: SUL | G29: =IFERROR(_xlfn.XLOOKUP(Table2[[#This Row],[Ativo]],Pendentes[COD_RELIGADOR],Pendentes[SS_ORIGINAL]),"CONCLUÍDA") -> ETO-COEP 00160/2026 | H29: Em processo de aquisição | I29: Furtado 2 vezes | K29: Pendente | L29: Células + controle | M29: 3 | N29: =IFERROR(_xlfn.XLOOKUP(Table2[[#This Row],[Ativo]],Pendentes[COD_RELIGADOR],Pendentes[DESCRICAO]),"") -> 27/07/2026 PARECER COEP: EQUIPAMENTO SELECIONADO PARA COMPRA, PORÉM PODEMOS DESATIVAR DE ACORDO COM A ASPODCMD 26.03.2026. SS REPASSADA PARA COEP PROVIDENCIAR MATERIAL. NÃO TEMOS O MATERIAL EM ESTOQUE PARA SUBSTITUIÇÃO. COEP: Equipamento fornecido ao COCM-S para regularização.PARECER COEP: EQUIPAMENTOS JÁ FORNECIDOS PARA OS COCM'S PARA REGULARIZAÇÃOPARECER DA PROTEÇÃO:EQUIPAMENTOS FURTADOS. PARA AQUISIÇÃO DAS CELULAS DE REPOSIÇÃO, FAVOR CONSULTAR OS DADOS DE PLACA EM ANEXO.PARECER DA PROTEÇÃO:COMISISONAR RT 5856156091 LD DIANOPOLIS A NATIVIDADE. NECESSARIO REALIZAR MEDIÇÕES DA RESISTENCIA DA MALHA DE ATERRAMENTO.AJUSTES DISPONIVEIS NO APP DA PROTEÇÃO.RELIGADOR N° 5856156091 INSTALADO NA OBRA 0502400526 GENTILEZA, REALIZAR O COMISSIONAMENTO. LAUDO EM ANEXO. COORD EO: 899501, 8714782 | O29: 0 | P29: 0 | Q29: 0 | R29: 0 | S29: 0 | T29: - | U29: - | V29: - | W29: =SUM(Table2[[#This Row],[Premissa 1]:[Premissa 8]]) -> 0 | X29: Baixa | Y29: Equipamento novo furtado antes de ser colocado em operação
A30: 5858783119 | B30: =_xlfn.XLOOKUP(Table2[[#This Row],[Ativo]],Joao!B:B,Joao!Z:Z) -> Redirecionado para atender 5854566043 e 5862236091 | C30: =MID(Table2[[#This Row],[Ativo]],1,2) -> 58 | D30: SAO BENTO DO TOCANTINS | E30: TOCANTINOPOLIS | F30: NORTE | G30: =IFERROR(_xlfn.XLOOKUP(Table2[[#This Row],[Ativo]],Pendentes[COD_RELIGADOR],Pendentes[SS_ORIGINAL]),"CONCLUÍDA") -> ETO-COEP 00164/2026 | H30: Aguardando parecer DMSL | K30: Pendente | N30: =IFERROR(_xlfn.XLOOKUP(Table2[[#This Row],[Ativo]],Pendentes[COD_RELIGADOR],Pendentes[DESCRICAO]),"") -> PARECER DMSL 31/07/2026: RT 5858783119 SE ECONTRA NA MESMA SITUAÇÃO INFORMADA NO DIA 16/06/2026. FAVOR, REGULARIZAR A SITUAÇÃO DO EQUIPAMENTO, SUBSTITUINDO OS 3 TANQUES E INSTALAR NOVOS PARA-RAIOS.27/07/2026 PARECER COEP: FIZEMOS UMA VISITA AO EQUIPAMENTO , EQUIPAMENTO SE ENCONTRA EM OPERAÇÃO E SEM SINAL DE AVARIA FAVOR AVALIAR PARECER DMSL A SS FOTOS COM O LUANDERSSON OU JOAO ANTONIO LAGARES 20/07 PARECER COEP: EQUIPAMENTO SELECIONADO PARA COMPRA , DEVIDO AO ERRO NA INSTALAÇÃO E O FURTOPARECER DMSL: 16/06/2025-SERVIÇO EXECUTADO: Ao chegar no equipamento para realizar comissionamento, foi constatato que as 3 células estavam com a tampa de inspeção abertas e sem os para-raios. Constatado também que foi furtado todo o óleo isolante das 3 células, sendo necessário a substituição das 3 células. FICOU EM OPERAÇÃO?: Não PENDÊNCIA: Substituir as 3 células | O30: 0 | P30: 0 | Q30: 0 | R30: 0 | S30: 0 | T30: - | U30: - | V30: - | W30: =SUM(Table2[[#This Row],[Premissa 1]:[Premissa 8]]) -> 0 | X30: Baixa | Y30: Equipamento não inserido no SCADA
A31: 5862236091 | B31: =_xlfn.XLOOKUP(Table2[[#This Row],[Ativo]],Joao!B:B,Joao!Z:Z) -> #N/A | C31: =MID(Table2[[#This Row],[Ativo]],1,2) -> 58 | D31: ALMAS | E31: DIANOPOLIS | F31: SUL | G31: =IFERROR(_xlfn.XLOOKUP(Table2[[#This Row],[Ativo]],Pendentes[COD_RELIGADOR],Pendentes[SS_ORIGINAL]),"CONCLUÍDA") -> ETO-COEP 00158/2026 | H31: Em processo de aquisição | K31: Pendente | L31: Célula | M31: 1 | N31: =IFERROR(_xlfn.XLOOKUP(Table2[[#This Row],[Ativo]],Pendentes[COD_RELIGADOR],Pendentes[DESCRICAO]),"") -> 27/07 PARECER COEP: PEÇAS REDIRECIONADAS 5856070091 PRIORIDADE MAIOR20/07 PARECER COEP: EQUIPAMENTO ENTREGUE , FAVOR EDITAR A SS COM A DATA PREVISTA DE SUBSTITUIÇÃO NO PARECER DOS COCM´S Realizar substituição da FASE B.Célula da fase B estava com a tampa do contador de tape aberta, pegou chuva e molhou os contatos danificando a peça toda. | O31: 0 | P31: 0 | Q31: 0 | R31: 20 | S31: 0 | T31: - | U31: - | V31: - | W31: =SUM(Table2[[#This Row],[Premissa 1]:[Premissa 8]]) -> 20 | X31: Baixa | Y31: Atendimento da LD Vale Rio Doce (Nova Aura Mineradora)
A32: 5865120195 | B32: =_xlfn.XLOOKUP(Table2[[#This Row],[Ativo]],Joao!B:B,Joao!Z:Z) -> #N/A | C32: =MID(Table2[[#This Row],[Ativo]],1,2) -> 58 | D32: CENTENARIO | E32: GUARAI | F32: NORTE | G32: =IFERROR(_xlfn.XLOOKUP(Table2[[#This Row],[Ativo]],Pendentes[COD_RELIGADOR],Pendentes[SS_ORIGINAL]),"CONCLUÍDA") -> ETO-SE-PCM 00091/2026 | H32: Em fase de ajustes | K32: Em andamento | L32: Melhoria de aterramento | M32: 1 | N32: =IFERROR(_xlfn.XLOOKUP(Table2[[#This Row],[Ativo]],Pendentes[COD_RELIGADOR],Pendentes[DESCRICAO]),"") -> PARECER DMSL:PENDÊNCIA: Realizar melhoria no aterramento por ser tratar de um terreno muito arenoso, e há pendências por parte do time da proteção, os ajustes do RT não estão disponíveis para inserção no referido equipamento.DATA DA MANUTENÇÃO: 12/03/202EQUIPE: Brunno e Edeglan.***********************PARECER DA PROTEÇÃO - 17/08/2026:FAVOR COMISSIONAR REGULADOR 5865120195 – LD Santa Maria Ramal Centenário e Recursolândia – 34,5kV. AJUSTE REALIZADO, DISPONÍVEL NO APP DA PROTEÇÃO.*********************** INSTALADO NA OBRA 0702400720 GENTILEZA, REALIZAR O COMISSIONAMENTO.LAUDO EM ANEXO.COORD EO: 889017, 901685708-07-2026 PARECER: FOI FEITO A MELHORIA NO REGULADOR CONFORME FOTOS EM ANEXO. | O32: 20 | P32: 20 | Q32: 20 | R32: 10 | S32: 0 | T32: - | U32: - | V32: - | W32: =SUM(Table2[[#This Row],[Premissa 1]:[Premissa 8]]) -> 70 | X32: Alta | Y32: Atendimento das RDUs de Centenário, Recursolândia e clientes rurais
A33: 7900001096 | B33: =_xlfn.XLOOKUP(Table2[[#This Row],[Ativo]],Joao!B:B,Joao!Z:Z) -> #N/A | C33: =MID(Table2[[#This Row],[Ativo]],1,2) -> 79 | G33: =IFERROR(_xlfn.XLOOKUP(Table2[[#This Row],[Ativo]],Pendentes[COD_RELIGADOR],Pendentes[SS_ORIGINAL]),"CONCLUÍDA") -> CONCLUÍDA | H33: Primeiro ataque DMSL | N33: =IFERROR(_xlfn.XLOOKUP(Table2[[#This Row],[Ativo]],Pendentes[COD_RELIGADOR],Pendentes[DESCRICAO]),"") | W33: =SUM(Table2[[#This Row],[Premissa 1]:[Premissa 8]]) -> 0
A34: 7900018004 | B34: =_xlfn.XLOOKUP(Table2[[#This Row],[Ativo]],Joao!B:B,Joao!Z:Z) -> Concluido | C34: =MID(Table2[[#This Row],[Ativo]],1,2) -> 79 | D34: ARAGUAINA | E34: ARAGUAINA | F34: NORTE | G34: =IFERROR(_xlfn.XLOOKUP(Table2[[#This Row],[Ativo]],Pendentes[COD_RELIGADOR],Pendentes[SS_ORIGINAL]),"CONCLUÍDA") -> CONCLUÍDA | H34: Concluído DCMD | I34: Reporte do Wander | K34: Ok | N34: =IFERROR(_xlfn.XLOOKUP(Table2[[#This Row],[Ativo]],Pendentes[COD_RELIGADOR],Pendentes[DESCRICAO]),"") | O34: 15 | P34: 10 | Q34: 5 | R34: 15 | S34: 0 | T34: 10 | U34: 0 | V34: 0 | W34: =SUM(Table2[[#This Row],[Premissa 1]:[Premissa 8]]) -> 55 | X34: Alta | Y34: Transferência de Aragominas, 3 fontes operando
A35: 7900117013 | B35: =_xlfn.XLOOKUP(Table2[[#This Row],[Ativo]],Joao!B:B,Joao!Z:Z) -> Calendário logistco vai sair hoje 29/05/2026, assim que tiver rota de entrga avisamos | C35: =MID(Table2[[#This Row],[Ativo]],1,2) -> 79 | D35: PARAISO DO TOCANTINS | E35: PARAISO DO TOCANTINS | F35: CENTRO | G35: =IFERROR(_xlfn.XLOOKUP(Table2[[#This Row],[Ativo]],Pendentes[COD_RELIGADOR],Pendentes[SS_ORIGINAL]),"CONCLUÍDA") -> ETO-PROT 00154/2026 | H35: Em fase de ajustes | K35: Em andamento | L35: Controle | M35: 1 | N35: =IFERROR(_xlfn.XLOOKUP(Table2[[#This Row],[Ativo]],Pendentes[COD_RELIGADOR],Pendentes[DESCRICAO]),"") -> 15/07 PARECER COCM: EQUIPAMENTO FOI SUBSTITUÍDO OBRA 021260042210/07 PARECER COEP: EQUIPAMENTO ENTREGUE AOS COCM´S FAVOR INFORMAR PRAZO DE SUBSTUIÇÃO PARA O DMSL E REPASSAR DEPOIS PARA PROTEÇÃO REALIZAR OS AJUSTES E DESCREVER NA SS O SERVIÇO REALIZADOPARECER COEP: PREVISÃO DE ENTREGA AOS COCM'S 01/07Segue nota para correção de anomalia e provável substituição de religador , religador 7900117013 -RDU - Paraiso .OBS: equipe DMSL Elisfran estava atualizando firmware no equipamento , porém relé parou de funcionar devido essa atualização , sendo necessário sua substituição .em campo o modelo e cooper Form6 , segundo tecnico deve ser substituído por um Noja .Repassado para o COEP para aquisição do equipamento e posterior repasse para o COCM. | O35: 15 | P35: 20 | Q35: 15 | R35: 15 | S35: 15 | T35: 0 | U35: 0 | V35: 15 | W35: =SUM(Table2[[#This Row],[Premissa 1]:[Premissa 8]]) -> 95 | X35: Muito Alta | Y35: Transferência do 214R de Paraíso I, Centro Comercial de Paraíso
A36: 7900230155 | B36: =_xlfn.XLOOKUP(Table2[[#This Row],[Ativo]],Joao!B:B,Joao!Z:Z) -> Concluido | C36: =MID(Table2[[#This Row],[Ativo]],1,2) -> 79 | D36: PALMEIRANTE | E36: COLINAS DO TOCANTINS | F36: NORTE | G36: =IFERROR(_xlfn.XLOOKUP(Table2[[#This Row],[Ativo]],Pendentes[COD_RELIGADOR],Pendentes[SS_ORIGINAL]),"CONCLUÍDA") -> ETO-SE-PCM 00090/2026 | H36: Em fase de ajustes | I36: Reporte Wandersson | K36: Em andamento | L36: Tanque e PR do trafo e chave | M36: 1 | N36: =IFERROR(_xlfn.XLOOKUP(Table2[[#This Row],[Ativo]],Pendentes[COD_RELIGADOR],Pendentes[DESCRICAO]),"") -> PARECER DA PROTEÇÃO - 17/08/2026:SEGUE NOTA PARA COMISSIONAMENTO JUNTO COM TIME SCADA, EQUIPAMENTO JA NO DESENHO ADMS.ENG° IRLLEY CASTELO BRANCO07/07/2026 PARECER COEP: MATERIAL ENVIADO , CONFORME ALINHANDO COM O WANDER REALIZAR SUBSTIUIÇÂO DO EQUIPAMENTO, FAVOR ESCREVER PARECER COCM ANTES DE PASSAR PARA PROTEÇÂO, DO QUE FOI REALIZADO01/07/2026 PARECER COEP: PROBLEMA NO ENVIO DO MATERIAL PARECER DMSL: Religador está com o tanque danificado. Não responde a comandos abertura e fechamento local ou remoto, pois está com sinal de curto circuito. Necessário trocar o equipamento. Para raio do trafo está queimado. Chave de saída da fase C está com o olhal quebrado, necessário substituir a chave. Equipamento ficou bypassado em campo. Aberto entrada e saída, com exceção da fase C de saída que ficou fechada. Favor, substituir equipamento completo por NOJA RC10 e sanar demais pendencias.Senhores Favor verificar RL 7900230155 o mesmo sinalizou aberto no SCADA porem a cidade de Palmeirante estava normal , feito um reset no rl e o mesmo subiu fechado.08/07/2026 PARECER DCMD: EQUIPE ETO-LVGR01 DE GUARAI ESTEVE NO RL 7900230155 DIA 25-06-2026 E FEZ TODAS A PENDENCIAS DO RL, OBS: EQUIPE SO NAO CONECTOU O CABO DO TRAFO NO RL. RL ESTA PRONTO PARA O COMISSIONAMENTO | O36: 15 | P36: 20 | Q36: 5 | R36: 15 | S36: 0 | T36: 10 | U36: 0 | V36: 15 | W36: =SUM(Table2[[#This Row],[Premissa 1]:[Premissa 8]]) -> 80 | X36: Muito Alta | Y36: Fonte principal de Palmeirante, RL de transferência operando
A37: 7900259096 | B37: =_xlfn.XLOOKUP(Table2[[#This Row],[Ativo]],Joao!B:B,Joao!Z:Z) -> #N/A | C37: =MID(Table2[[#This Row],[Ativo]],1,2) -> 79 | G37: =IFERROR(_xlfn.XLOOKUP(Table2[[#This Row],[Ativo]],Pendentes[COD_RELIGADOR],Pendentes[SS_ORIGINAL]),"CONCLUÍDA") -> CONCLUÍDA | H37: Primeiro ataque DMSL | N37: =IFERROR(_xlfn.XLOOKUP(Table2[[#This Row],[Ativo]],Pendentes[COD_RELIGADOR],Pendentes[DESCRICAO]),"") | W37: =SUM(Table2[[#This Row],[Premissa 1]:[Premissa 8]]) -> 0
A38: 7900451096 | B38: =_xlfn.XLOOKUP(Table2[[#This Row],[Ativo]],Joao!B:B,Joao!Z:Z) -> #N/A | C38: =MID(Table2[[#This Row],[Ativo]],1,2) -> 79 | G38: =IFERROR(_xlfn.XLOOKUP(Table2[[#This Row],[Ativo]],Pendentes[COD_RELIGADOR],Pendentes[SS_ORIGINAL]),"CONCLUÍDA") -> CONCLUÍDA | H38: Primeiro ataque DMSL | N38: =IFERROR(_xlfn.XLOOKUP(Table2[[#This Row],[Ativo]],Pendentes[COD_RELIGADOR],Pendentes[DESCRICAO]),"") | W38: =SUM(Table2[[#This Row],[Premissa 1]:[Premissa 8]]) -> 0
A39: 7900453110 | B39: =_xlfn.XLOOKUP(Table2[[#This Row],[Ativo]],Joao!B:B,Joao!Z:Z) -> Equipamento entregue, redirecionaremos para o Caso 7933726256 | C39: =MID(Table2[[#This Row],[Ativo]],1,2) -> 79 | D39: SANTA RITA DO TOCANTINS | E39: PORTO NACIONAL | F39: CENTRO | G39: =IFERROR(_xlfn.XLOOKUP(Table2[[#This Row],[Ativo]],Pendentes[COD_RELIGADOR],Pendentes[SS_ORIGINAL]),"CONCLUÍDA") -> ETO-COEP 00087/2026 | H39: Em processo de aquisição | I39: Equipamento entregue, redirecionaremos para o Caso 7933726256 | K39: Pendente | L39: Tanque | M39: 1 | N39: =IFERROR(_xlfn.XLOOKUP(Table2[[#This Row],[Ativo]],Pendentes[COD_RELIGADOR],Pendentes[DESCRICAO]),"") -> 10/07/2026 EQUIPAMENTO SELECIONADO PARA COMPRA PARTE ATIVA30/06.PARECER COEP: ALINHADO COM O ALLAN REMANEJAMOS PARTE ATIVA PARA ATENDER 7933726256PARECER COEP: Aproveitar controle cooper se possível em outro local, previsão de chegada do material dia 01/07 para substituiçãoFavor verificar o RL 7900453110, pois o mesmo aceita comando de fechamento, porém fecha em campo e no SCADA continua aberto e só abre através de equipe em campo. Parecer Dmsl:Equipamento está com defeito na parte ativa, não aceita o comando de fechamento. Será necessário substituir o equipamento completo.Equipamento ficou em operação?: _SIM_a pedido do COS ficou em operação, a operação está ciente da necessidade de substituir.Pendência: Sim, será necessário substituir o equipamento. | O39: 15 | P39: 10 | Q39: 5 | R39: 15 | S39: 15 | T39: 10 | U39: 0 | V39: 15 | W39: =SUM(Table2[[#This Row],[Premissa 1]:[Premissa 8]]) -> 85 | X39: Muito Alta | Y39: Transferência de Santa Rita, fonte principal operando
A40: 7900505026 | B40: =_xlfn.XLOOKUP(Table2[[#This Row],[Ativo]],Joao!B:B,Joao!Z:Z) -> #N/A | C40: =MID(Table2[[#This Row],[Ativo]],1,2) -> 79 | D40: PONTE ALTA TOCANTINS | E40: PONTE ALTA TOCANTINS | F40: CENTRO | G40: =IFERROR(_xlfn.XLOOKUP(Table2[[#This Row],[Ativo]],Pendentes[COD_RELIGADOR],Pendentes[SS_ORIGINAL]),"CONCLUÍDA") -> CONCLUÍDA | H40: Cancelada em operação | K40: Ok | N40: =IFERROR(_xlfn.XLOOKUP(Table2[[#This Row],[Ativo]],Pendentes[COD_RELIGADOR],Pendentes[DESCRICAO]),"") | O40: 5 | P40: 5 | Q40: 5 | R40: 0 | S40: 0 | T40: 0 | U40: 10 | V40: 0 | W40: =SUM(Table2[[#This Row],[Premissa 1]:[Premissa 8]]) -> 25 | X40: Baixa | Y40: Atendimento do Ramal do Gato (288 UCs) e UFV Videira, no desarme a jusante penaliza a cidade de Pindorama
