Workbook

Sheet Gerencial
A1: DESTINO_SS | B1: (Vários itens) | F1: Criticidade | G1: Quantidade | I1: Total
G2: RL | H2: RT
A3: Qtd | B3: Cód | F3: Muito Alta | G3: 9 | H3: 2 | I3: =SUM(G3:H3) -> 11
A4: Criticidade | B4: 58 | C4: 79 | D4: Total Geral | F4: Alta | G4: 9 | H4: 3 | I4: =SUM(G4:H4) -> 12
A5: Muito Alta | B5: 3 | C5: 11 | D5: 14 | F5: Média | G5: 9 | H5: 4 | I5: =SUM(G5:H5) -> 13
A6: Alta | B6: 3 | C6: 6 | D6: 9 | F6: Baixa | G6: 9 | H6: 5 | I6: =SUM(G6:H6) -> 14
A7: Média | B7: 5 | C7: 9 | D7: 14 | F7: Em definição | G7: 28 | H7: 9 | I7: =SUM(G7:H7) -> 37
A8: Baixa | B8: 4 | C8: 11 | D8: 15 | F8: Total Geral | G8: 64 | H8: 23 | I8: =SUM(I3:I7) -> 87
A9: Em definição | C9: 3 | D9: 3
A10: Total Geral | B10: 15 | C10: 40 | D10: 55

Sheet Pendentes
A1: ANO_SS | B1: SS_ORIGINAL | C1: DESTINO_SS | D1: COD_RELIGADOR | E1: TIPO | F1: DTA_ABERTURA | G1: COD_LOC | H1: LOCALIDADE | I1: POLO | J1: REGIONAL | K1: ALIMENTADOR | L1: DESCRICAO | M1: Premissa 1 | N1: Premissa 2 | O1: Premissa 3 | P1: Premissa 4 | Q1: Premissa 5 | R1: Premissa 6 | S1: Premissa 7 | T1: Premissa 8 | U1: Priorização | V1: Criticidade | W1: Observação após análise
A2: 2026 | B2: ETO-RD-PO 00213/2026 | C2: ETO-RD-PO | D2: 5854566043 | E2: 58 | F2: 46225 | G2: 43 | H2: SILVANOPOLIS | I2: PORTO NACIONAL | J2: CENTRO | K2: LD02072001 | L2: 22/07/2026 PARECER COEP: EQUIPAMENTO ENTREGUE AOS COCM´SPRAZO DE 7 DIAS CONTANDO O SLA.PARECER COEP: EQUIPAMENTO ENTREGUE AOS COCM´S FAVOR SUSBSTTUIR , E AGUARDO O PRAZO DE PREVISÃO DE SUBSTIUIÇÃOboa noite,segue SS para as devidas tratativas com equipe de manutenção com apoio de equipe de linha viva substituir regulador de tensão 5854566043 queimado célula fase c, LD Porto / Silvanópolis mesmo deverá ser substituído com apoio de equipe de linha viva PARECER DMSL: Foi realizado inspeção visual e ensaios de isolação, relação de transformação e resistência de enrolamento. A fase B está danificada e será necessário substituir a mesma. Malha de aterramento está relativamente boa e conectada. Fase A e C passaram nos ensaios. Substituir fase B. | M2: 40 | N2: 20 | O2: 20 | P2: 10 | Q2: 20 | R2: - | S2: - | T2: - | U2: 110 | V2: Muito Alta | W2: Aumento de reclamações no atendimento de Silvanópolis por Porto Nacional no período seco (Outra fonte com defeito também)
A3: 2026 | B3: ETO-RD-GR 00735/2026 | C3: ETO-RD-GR | D3: 5800859011 | E3: 58 | F3: 46219 | G3: 11 | H3: TUPIRAMA | I3: GUARAI | J3: NORTE | K3: AL01065015 | L3: 16/07/2026 PARECER COEP: ALINHADO COM O JEAN DO DMSL E O KELLITON , KELLITON IRÁ FAZER A INSTALAÇÃO DO CONTROLE RUA E O JEAN IRÁ REALIZAR O COMISSIONAMENTO , FAZENDO A COMPATIBILIZAÇÃO DOS CABOS ASSIM COMO FICARÁ UM CONTROLE RUA NO NOSSO ESTOQUE SOBRESSALENTE PARA ATENDER O DE ARAPOEMA, ATÉ A CHEGADA DOS CABOS QUE O JEAN ME DEU REPORTE DE QUE SERIA ATÉ O DIA 16/08 , FAVOR COCM'S REALIZAREM A INSTALAÇÃO E GUARDAR CONTROLE RUA SOBRESSALENTE PARA ARAPOEMAPEÇA ENVIADA: CONTROLEPARECER DMSL: *FEEDBACK EQUIP. ESPECIAIS**Nº DO EQUIPAMENTO:* 5800859011*TIPO EQUIPAMENTO:* RT ITB *TIPO DE COMUNICAÇÃO:* Não *DATA DA MANUTENÇÃO:* 09/06/2026*SID:* 3195/2026*DESCRIÇÃO:* _ Foi identificado relé da fase C com defeito conforme orientação da supervisão e necessário realiza retrofit para instalação de controle rua.*FICOU EM OPERAÇÃO* Não*PENDÊNCIA:* Realizado Retrofit *DADOS DIVERGENTES DA PROGRAMAÇÃO:* Não*BATERIA SUBSTITUÍDA?:* Não*TIPO DE BATERIA:**EQUIPE:* Edeglan e Brunno.Observação: trocar por um controle RUA.------------------------------------------------------------------------------------------Enviar equipe do DMSL, para fazer correção no RT 5800859011, o mesmo está com o displey da fase C apagado , dificutando realizar manobras no mesmo, emvirtude disso o mesmo ficou BAY PASSADO EM CAMPO | M3: 40 | N3: 20 | O3: 20 | P3: 10 | Q3: 20 | R3: - | S3: - | T3: - | U3: 110 | V3: Muito Alta | W3: Atendimento de parte da RDU Guaraí por fonte alternativa
A4: 2026 | B4: ETO-COEP 00124/2026 | C4: ETO-COEP | D4: 7923673004 | E4: 79 | F4: 46210 | G4: 4 | H4: ARAGUAINA | I4: ARAGUAINA | J4: NORTE | K4: AL04010004 | L4: PARECER COEP: Verificar Disponibilidade de equipamento no Scada e enviar modelo e tensão para a compra.RELIGADOR COM RELÉ DANIFICADO, REALIZAR SUBSTITUIÇÃO | M4: 15 | N4: 20 | O4: 15 | P4: 15 | Q4: 15 | R4: 10 | S4: 0 | T4: 15 | U4: 105 | V4: Muito Alta | W4: Transferência de cargas na RDU de Araguaína (2797 UCs)
A5: 2026 | B5: ETO-COEP 00040/2026 | C5: ETO-COEP | D5: 7931608059 | E5: 79 | F5: 46077 | G5: 59 | H5: TAQUARALTO | I5: TAQUARALTO | J5: CENTRO | K5: AL05099059 | L5: PARECER COEP: EQUIPAMENTO SELECIONADO PARA COMPRADMSL:Serviço Executado: Foi feita uma análise técnica no equipamento, devido à falta de comunicação. Também foi identificado que o tanque do equipamento está danificado, sendo assim, necessário substituir o tanque e o rádio do equipamento, que está queimado, sendo necessário substituir também. | M5: 15 | N5: 20 | O5: 15 | P5: 15 | Q5: 15 | R5: 10 | S5: 0 | T5: 15 | U5: 105 | V5: Muito Alta | W5: Transferência dos bairros Morada do Sol, Vale do Sol, Morada do Sol II, Nova Esperança, Sõa João, Araras I e II e Jardim Laila em Taquaralto (6033 UCs)
A6: 2026 | B6: ETO-TELE 01025/2026 | C6: ETO-TELE | D6: 7931610122 | E6: 79 | F6: 46225 | G6: 122 | H6: PALMAS | I6: PALMAS | J6: CENTRO | K6: AL08060122 | L6: PARECER DA PROTEÇÃO:FAVOR COMISSIONAR RELIGADOR. AJUSTES PERMANECEM OS MESMOS E DISPONÍVEIS NO APP DA PROTEÇÃO.Estagiário Rafael P Marques.******************30/06 PARECER COEP: EQUIPAMENTO ENTREGUE, SEGUE SS PARA O COCM´S , PARA REALIZAR O ATENDIMENTO,FAVOR ADICIONAR O PARECER PARA MANDAR PARA PROTEÇÃOBom dia,Segue SS para verificação RL sem comunicação com painel apagado equipe DEOP fez primeiro ataque sem sucesso RL 7931610122 RDU de Palmas.Feedback Equipamentos Especiais DMSL: *RLG 7931610122 RDU Palmas*Noja rc10 Data: 14/10/2025SID: 5412Dados de comunicação divergentes da programação: Não. Serviço Executado: Houve um curto no equipamento danificando a parte ativa, e antena! Será necessário fazer a substituição somente da parte ativa (tanque) e da antena.Equipamento ficou em operação?: Não Pendência: Sim, substituir a parte ativa.Bateria(s) substituída(s)?: NãoData Fabricação/Instalação da(s) bateria(s): 2024Equipe: Benvindo, Juliano e Sérgio.***** Parecer do COCM CENTRO*****Equipamento Substituido em campo pela Ordem de ServiÇO DLP-MPPA01 243/2026, ONDE OS RELATORIO ESTÃO ANEXADO.--------------------------------------------------------Parecer DMSL:Equipamento substituído porém não informado se antena também foi substituída. Levar antena para caso da mesmo não ter sido substituída. | M6: 15 | N6: 20 | O6: 15 | P6: 15 | Q6: 15 | R6: 10 | S6: 0 | T6: 15 | U6: 105 | V6: Muito Alta | W6: Transferência entre 284R SE Palmas IV e 2294R SE Palmas II
A7: 2026 | B7: ETO-RD-DP 00479/2026 | C7: ETO-RD-DP | D7: 5856070091 | E7: 58 | F7: 46230 | G7: 91 | H7: ALMAS | I7: DIANOPOLIS | J7: SUL | K7: LD04002091 | L7: PARECER DMSL: não foi regularizado a instalação do equipamento, nota repassada conforme alinhado com o supervisor.____________________________________________COCMS 26.03.26. SS REPASSADA PARA COEP PROVIDENCIAR MATERIAL. NÃO TEMOS AS PÇ EM ESTOQUE PARA FAZER A SUBSTITUIÇÃO. Solicitação de serviço para reposição de equipamentos furtados .COEP: Equipamento fornecido ao COCM-S para regularização.COCMS: Equipamento substituido conforme solicitado. Gentileza comissionar.PARECER DA PROTEÇÃO:SEGUE NOTA REPASSADA PARA DMSL COMISSIONAR.ENG° IRLLEY CASTELO BRANCOPARECER DMSL(23/09/2025): Feito a parte de comunicação, fechando enlace, configuração do rádio GE. Feito a medição de aterramento. Após uma inspeção, foi identificado que o regulador de tensão está instalado errado, carga está para o lado de fonte e fonte está do lado de carga. O certo é a fonte vim de almas, atualmente está vindo de natividade. Favor fazer a instalação correta. | M7: 40 | N7: 20 | O7: 20 | P7: 20 | Q7: 0 | R7: - | S7: - | T7: - | U7: 100 | V7: Muito Alta | W7: Atendimento da região da Engegold, Nativa, cidade Natividade e Chapada da Natividade
A8: 2026 | B8: ETO-COEP 00131/2026 | C8: ETO-COEP | D8: 7947203070 | E8: 79 | F8: 46211 | G8: 70 | H8: RIO SONO | I8: TAQUARALTO | J8: CENTRO | K8: LD02424015 | L8: 13/07 PARECER COEP: SELECIONADO PARA COMPRA CONTROLE favor verificar RL 7947203070, sem comunicaçao, feito 1° ataque pela equipe 070OP01 e nao retornou a comunicaçao , linformaçao no Scada de bateria.PARECER DMSL: Foi feito análise técnica, a placa do equipamento está queimada nessesario subistituir o equipamento completo -Carliel e Benvindo-05/02 | M8: 10 | N8: 20 | O8: 15 | P8: 15 | Q8: 15 | R8: 10 | S8: 0 | T8: 15 | U8: 100 | V8: Muito Alta | W8: Transferência da RDU de Lizarda (1650 UCs) para fonte alternativa
A9: 2026 | B9: ETO-RD-DP 00409/2026 | C9: ETO-RD-DP | D9: 7908705049 | E9: 79 | F9: 46209 | G9: 49 | H9: AURORA DO TOCANTINS | I9: DIANOPOLIS | J9: SUL | K9: AL01015049 | L9: EQUIPAMENTO ENTREGUE, SOLICITO PREVISÃO PARA SUBSTITUIÇÃO:PARECER COEP: PREVISÃO DE ENTREGA AOS COCM'S 01/07Manutenção no RL 7908705049PARECER DMSL(28/08/2025): Equipe foi fazer manutenção no RL e constatou que o tanque e o relé do mesmo se encontra queimado, providenciar substituição.PARECER COCMS 30/04/2026CRIADO OBRA 0512600135 PARA REQUISIÇÃO MATERIAL | M9: 15 | N9: 20 | O9: 5 | P9: 15 | Q9: 15 | R9: 0 | S9: 10 | T9: 15 | U9: 95 | V9: Muito Alta | W9: Proteção da baixa do TF de força da SE Aurora
A10: 2026 | B10: ETO-COEP 00059/2026 | C10: ETO-COEP | D10: 7925744087 | E10: 79 | F10: 46111 | G10: 87 | H10: GOIANORTE | I10: GUARAI | J10: NORTE | K10: LD02022033 | L10: PARECER COEP: EQUIPAMENTO SELECIONADO PARA COMPRAPARECER DMSL: FEEDBACK EQUIP. ESPECIAISNº DO EQUIPAMENTO: 7925744087TIPO EQUIPAMENTO: Noja RC 10TIPO DE COMUNICAÇÃO: Radio GE IPDATA DA MANUTENÇÃO: 19/02/2026SID: 735/2026 DESCRIÇÃO: foi identificado água dentro da parte interna do tanque e cabo umbilical encharcado de água foi passado essas informações para COS.FICOU EM OPERAÇÃO?: Não PENDÊNCIA: Sim substituir tanque e cabo umbilicalDADOS DIVERGENTES DA PROGRAMAÇÃO: NãoBATERIA SUBSTITUÍDA?: Não DATA DA BATERIA: 07/05/2025TIPO DE BATERIA: Lítio EQUIPE: Edeglan e Janio-------------------------------------------------------------------------------------------------RELIGADOR SEM COMUNICAÇÃO, APOS PRIMEIRO ATAQUE RETORNA E FICAR INDEFINIDO. | M10: 15 | N10: 20 | O10: 5 | P10: 15 | Q10: 15 | R10: 10 | S10: 0 | T10: 15 | U10: 95 | V10: Muito Alta | W10: Transferência de Goianorte, fonte principal operando
A11: 2026 | B11: ETO-PROT 00154/2026 | C11: ETO-PROT | D11: 7900117013 | E11: 79 | F11: 46224 | G11: 13 | H11: PARAISO DO TOCANTINS | I11: PARAISO DO TOCANTINS | J11: CENTRO | K11: AL01062013 | L11: 15/07 PARECER COCM: EQUIPAMENTO FOI SUBSTITUÍDO OBRA 021260042210/07 PARECER COEP: EQUIPAMENTO ENTREGUE AOS COCM´S FAVOR INFORMAR PRAZO DE SUBSTUIÇÃO PARA O DMSL E REPASSAR DEPOIS PARA PROTEÇÃO REALIZAR OS AJUSTES E DESCREVER NA SS O SERVIÇO REALIZADOPARECER COEP: PREVISÃO DE ENTREGA AOS COCM'S 01/07Segue nota para correção de anomalia e provável substituição de religador , religador 7900117013 -RDU - Paraiso .OBS: equipe DMSL Elisfran estava atualizando firmware no equipamento , porém relé parou de funcionar devido essa atualização , sendo necessário sua substituição .em campo o modelo e cooper Form6 , segundo tecnico deve ser substituído por um Noja .Repassado para o COEP para aquisição do equipamento e posterior repasse para o COCM. | M11: 15 | N11: 20 | O11: 15 | P11: 15 | Q11: 15 | R11: 0 | S11: 0 | T11: 15 | U11: 95 | V11: Muito Alta | W11: Transferência do 214R de Paraíso I, Centro Comercial de Paraíso
A12: 2026 | B12: ETO-COEP 00120/2026 | C12: ETO-COEP | D12: 7929376022 | E12: 79 | F12: 46203 | G12: 22 | H12: BABACULANDIA | I12: ARAGUAINA | J12: NORTE | K12: LD05010004 | L12: PARECER COEP: PROBLEMA NO ENVIO COCM'S CONTROLE ENVIADO FOI O NOJA , DEVIDO A FALTA DO MODELO NA SS (GRAVE)PARECER DMSL: *FEEDBACK EQUIP. ESPECIAIS**Nº DO EQUIPAMENTO:* 7929376022 *DATA DA MANUTENÇÃO:* 02/04/2026*SID:* 1677/2026*DESCRIÇÃO:* Trocar controle completo*PENDÊNCIA:* Sim.*DADOS DIVERGENTES DA PROGRAMAÇÃO:* Não*BATERIA SUBSTITUÍDA?:* Não*EQUIPE:* Adeilton e Edicleber __________________________________________________________POR GENTILEZA ATENDER SOLICITAÇÃO PRIMEIRO ATAQUE IDENTIFICOU QUE RELE ESTA EM CURTO NOTA ABERTA 224/2026 FOI BAIXADA POREM NÃO FOI CORRIGIDO PROBLEMA EM CAMPO. | M12: 15 | N12: 20 | O12: 5 | P12: 15 | Q12: 15 | R12: 10 | S12: 0 | T12: 15 | U12: 95 | V12: Muito Alta | W12: Transferência de Babaçulândia, fonte principal operando
A13: 2026 | B13: ETO-PROT 00145/2026 | C13: ETO-PROT | D13: 7933726256 | E13: 79 | F13: 46212 | G13: 256 | H13: MATEIROS | I13: PONTE ALTA TOCANTINS | J13: CENTRO | K13: LD03046026 | L13: 07/07 Equipamento foi substituido na OS: ETO-RD-PO 1859/2026 OBRA 031260035101/07 PARECER COEP: REDIRECIONADO PARA O POSTO DO COCM´S EQUIPAMENTO CHEGOU NO LOCAL, FAVOR ENTRAR EM CONTATO COM O DMSL, DEVIDO A URGÊNCIA DO EQUIPAMENTO EM OPERAÇÃO.30/06 PARECER COEP: DEVIDO A ALINHAMENTO COM COI UTILIZAREMOS PARTE ATIVA QUE ORIGINALMENTE FOI ENCOMENDADA PARA 7933726256PARECER DMSL: N° do Equipamento: _RLG 7933726256 MateirosTipo de Equipamento: _RLG NOJA RC 10 REL IIData: _06/05/2026SID: _2288/2026-Serviço Executado: _Equipamento com defeito na parte ativa, será necessário fazer a substituição da parte ativa e fazer melhoria na malha de terra!Equipamento ficou em operação?: _NaoPendência: _SimBateria(s) substituída(s)? NÃOData Fabricação/Instalação da(s) bateria(s):_06/2025Equipe: _Benvindo e Almir-------------------------------------------------------------------------------Religador 7933726256, sem comunicação apos primeiroa ataque não retornou as comunicação. | M13: 15 | N13: 10 | O13: 15 | P13: 15 | Q13: 15 | R13: 10 | S13: 0 | T13: 15 | U13: 95 | V13: Muito Alta | W13: Transferência da cidade de Mateiros (733 UCs) para o gerador
A14: 2026 | B14: ETO-TELE 01024/2026 | C14: ETO-TELE | D14: 7933766059 | E14: 79 | F14: 46225 | G14: 59 | H14: TAQUARALTO | I14: TAQUARALTO | J14: CENTRO | K14: AL01099059 | L14: PARECER DA PROTEÇÃO:RECOMISSIONAR RELIGADOR, AJUSTES DE PROTEÇÃO PERMANECEM OS MESMOS.Estagiário Rafael P Marques****************************PARECER COEP: EQUIPAMENTO ENTREGUE, SEGUE SS PARA O COCM´S , PARA REALIZAR O ATENDIMENTO,FAVOR ADICIONAR O PARECER PARA MANDAR PARA PROTEÇÃOSegue SS para verficar religador de poste 7933766059.Religador esta com defeito na parte ativa no tanque Porte gentilezaenviar equipe verificar.Endereço: TaquariPARECER DMSL: RLG 7933766059 RELÉ NOJA RC 10Mestre 2 Rep. taquaruçu GESID: 5457/2025Data: 15/10/2025Serviço Executado: Houve um curto na parte ativa do equipamento danificando a mesma, será necessário fazer a substituição somente do tanque, parte ativa.*Equipamento ficou em operação?:*Nao Pendência: Sim, substituir parte ativa.Equipe: Benvindo, Juliano e Sérgio.****** Parecer do COCM Centro***Equipámento Substituido em Campo pela Ordem de ServIÇO DLP-MPPA01 244/2026, ONDE OS RELATORIO ESTÃO ANEXADO.. | M14: 15 | N14: 20 | O14: 5 | P14: 15 | Q14: 15 | R14: 0 | S14: 10 | T14: 15 | U14: 95 | V14: Muito Alta | W14: Seccionamento de trecho do Setor Taquari
A15: 2026 | B15: ETO-SE-PA 00107/2026 | C15: ETO-SE-PA | D15: 7900594026 | E15: 79 | F15: 46219 | G15: 26 | H15: PONTE ALTA TOCANTINS | I15: PONTE ALTA TOCANTINS | J15: CENTRO | K15: LD03046026 | L15: PARECER DA PROTEÇÃO:16/07/2026 AJUSTES DISPONIBILIZADOS NO APP DA PROTEÇÃO15/07/2026 EQUIPAMENTO SUBSTITUIDO NA OS ETO-RD-PO 1860 OBRA 031260035414/07/2026 PARECER COCM/ COEP: DE ACORDO COM O EDSON CURCINO FOI FEITA S SUBSTITUIÇÃO DO EQUIPAMENTO , SEGUE PARA PROTEÇÃO ELABORAR AJUSTE10/07 PARECER COEP: EQUIPAMENTO DESLOCADO QUE ESTAVA EM GUARAÍ FOI ALINHADO COM O VALMOR QUE SERIA SUBSTITUIDO DIA 07/07/2026 , FAVOR PASSAR PARA PROTEÇÃO 7900594026PARECER COEP: AGUARDANDO COCM'S PARA ABRIR REQUISIÇÃOPARECER DMSL 10/06/2026: Tem uma nota aberta para esse equipamento solicitando a substituição desde 20/10/2025, como a nota não foi atendida estamos repassando para área responsável. Nota em aberto repassada ETO-COEP 210/2025.Segue nota para verificar intermitência de comunicação nos religadores 7908301026 , 7911120026, 7947959026 , 7908692026, 7900594026 rural- Ponte Alta . | M15: 15 | N15: 20 | O15: 15 | P15: 15 | Q15: 15 | R15: 0 | S15: 0 | T15: 15 | U15: 95 | V15: Muito Alta | W15: Religador responsável pela proteção da barra da SE Ponte Alta (2381 UCs)
A16: 2026 | B16: ETO-COEP 00141/2026 | C16: ETO-COEP | D16: 7927413001 | E16: 79 | F16: 46216 | G16: 1 | H16: PORTO NACIONAL | I16: PORTO NACIONAL | J16: CENTRO | K16: LD01072001 | L16: 22/07/2026 EQUIPAMENTO SLEECIONADO PARA COMPRAPARECER DMSL: *Segue feedback**Equipamento:* RLG 7927413001 *RELÉ TAVRIDA*Data:* 16/04/2026*SID:* 1817/2026*Serviço executado:* Placa de alimentação do equipamento com defeito, VERIFICAR SE É POSSIVEL substituir o equipamento completo.*Equipamento ficou em operação?*_Não*Pendência:*_Sim*Bateria(s) substituída(s)?*_Nao *Equipe:* Benvindo e Kaique-------------------------------------------------------------------------------------------------Religador 7927413001 sem comunicação foi realizado primeiro ataque porem a comunicação não retornou. Favor enviar equipe para devidas trattivas | M16: 15 | N16: 5 | O16: 15 | P16: 15 | Q16: 15 | R16: 10 | S16: 0 | T16: 15 | U16: 90 | V16: Muito Alta | W16: Transferência do Distrito Ind de Porto Nacional e GAs
A17: 2026 | B17: ETO-RD-PS 00302/2026 | C17: ETO-RD-PS | D17: 7908686014 | E17: 79 | F17: 46213 | G17: 14 | H17: PIUM | I17: PARAISO DO TOCANTINS | J17: CENTRO | K17: LD02025012 | L17: 10/07 PARECER COEP: EQUIPAMENTO ENTREGUE AOS COCM´S FAVOR INFORMAR PRAZO DE SUBSTUIÇÃO PARA O DMSL E REPASSAR DEPOIS PARA PROTEÇÃO REALIZAR OS AJUSTES E DESCREVER NA SS O SERVIÇO REALIZADO06/07 PARECER COEP: PREVISÃO DE ENTREGA DE ACORDO COM CALENDÁRIO LOGISITCO NOVO 06/07NOTA DMSL: Favor substituir o tanque, ele não está efetuando os comandos enviados. Não substituir o controle pois o mesmo funciona como repetidor de outros equipamentos.Segue nota para verificar falha de fechamento religador 7908686014- Pium .OBS: equipamento não fechou local e remoto , fica sinalizando no painel para verificar alarmes ! | M17: 15 | N17: 20 | O17: 0 | P17: 15 | Q17: 15 | R17: 10 | S17: 0 | T17: 15 | U17: 90 | V17: Muito Alta | W17: Fonte principal de Pium, RL de transferência operando
A18: 2026 | B18: ETO-TELE 00896/2026 | C18: ETO-TELE | D18: 7943790134 | E18: 79 | F18: 46183 | G18: 134 | H18: ESPERANTINA | I18: AUGUSTINOPOLIS | J18: NORTE | K18: LD02109039 | L18: PARECER DCMD:Serviço realizado , substituição da parte ativa do RELIGADOR 7943790134 - Favor realizar comissionamento | M18: 15 | N18: 10 | O18: 5 | P18: 15 | Q18: 15 | R18: 10 | S18: 0 | T18: 15 | U18: 85 | V18: Muito Alta | W18: Transferência de Esperantina, fonte principal operando
A19: 2026 | B19: ETO-COEP 00087/2026 | C19: ETO-COEP | D19: 7900453110 | E19: 79 | F19: 46139 | G19: 110 | H19: SANTA RITA DO TOCANTINS | I19: PORTO NACIONAL | J19: CENTRO | K19: LD03040003 | L19: 10/07/2026 EQUIPAMENTO SELECIONADO PARA COMPRA PARTE ATIVA30/06.PARECER COEP: ALINHADO COM O ALLAN REMANEJAMOS PARTE ATIVA PARA ATENDER 7933726256PARECER COEP: Aproveitar controle cooper se possível em outro local, previsão de chegada do material dia 01/07 para substituiçãoFavor verificar o RL 7900453110, pois o mesmo aceita comando de fechamento, porém fecha em campo e no SCADA continua aberto e só abre através de equipe em campo. Parecer Dmsl:Equipamento está com defeito na parte ativa, não aceita o comando de fechamento. Será necessário substituir o equipamento completo.Equipamento ficou em operação?: _SIM_a pedido do COS ficou em operação, a operação está ciente da necessidade de substituir.Pendência: Sim, será necessário substituir o equipamento. | M19: 15 | N19: 10 | O19: 5 | P19: 15 | Q19: 15 | R19: 10 | S19: 0 | T19: 15 | U19: 85 | V19: Muito Alta | W19: Transferência de Santa Rita, fonte principal operando
... A21: 2026 | B21: ETO-COEP 00048/2026 | C21: ETO-COEP | D21: 7925871077 | E21: 79 | F21: 46097 | G21: 77 | H21: GOIATINS | I21: ARAGUAINA | J21: NORTE | K21: LD03105019 | L21: 30/06 PARECER COEP: AGUARDANDO RETORNO DO DMSLPARECER DMSL: A PEDIDO DA PCM DO NORTE LARA SOARES REALIZEI A CRIAÇÃO DESSA SS, EM RAZAO DA ANTIGAETO-TELE 337/2026 QUE FOI BAIXADA POR ENGANO DE TAL FORMA SEGUE A MESMA PARA REALIZAR AS TRATATIVAS. PENDENCIA: Religador continua by passado, equipamento está com defeito na parte ativa | M21: 15 | N21: 10 | O21: 15 | P21: 15 | Q21: 15 | R21: 10 | S21: 0 | T21: 0 | U21: 80 | V21: Muito Alta | W21: Transferência de Goiatins e GAs (2492 UCs)
A22: 2026 | B22: ETO-COEP 00149/2026 | C22: ETO-COEP | D22: 5803327001 | E22: 58 | F22: 46223 | G22: 1 | H22: PORTO NACIONAL | I22: PORTO NACIONAL | J22: CENTRO | K22: AL01102271 | L22: 01/07 PARECER COEP: FOI CONFIRMADO COM A OPERAÇÃO QUE O EQUIPAMENTO SEGUIU O FLUXO INTEIRO DE COMISSIONAMENTO, PROTEÇÃO, FAVOR EXPLICAR O QUE FOI REALIZADO E SE EQUIPAMENTO ESTÁ OPERANDO, SENÃO ESTIVER EXPLICAR O QUE FOI FEITO NELE30/06PARECER COEP: REPASSAR DIRETAMENTE PARA OS COCM'SRegulador 5803327001 fora de operação, by passado em campo com painel de comunicação com cabos desconectados tensão 13.8.parecer DMSL: Feedback Equip. EspeciaisRT 5803327001RELÉ RUASid: 4844Data: 19/09/2025Serviço realizado:*Equipamento foi remanejado, 7 km da sua localização sentido Palmas necessário comissionamento completo*Equipamento com um dos cabos umbilicais danificado.* aterramento bucha FC não esta interligada corretamente * para-raios estão no mesmo aterramento da bucha FC.* Tranques muito alto e próximo da rede não permitindo o comissionamento com segurança.* Controle alto demais tem que baixar Equipamento ficou em operação?: nãoPendência: sim, precisa comissionar completoOBS | M22: 40 | N22: 0 | O22: 0 | P22: 20 | Q22: 20 | R22: - | S22: - | T22: - | U22: 80 | V22: Alta | W22: Em caso de perca da fonte principal é necessário esse RT para alimentação da Frísia
A23: 2026 | B23: ETO-PROT 00143/2026 | C23: ETO-PROT | D23: 7900230155 | E23: 79 | F23: 46211 | G23: 155 | H23: PALMEIRANTE | I23: COLINAS DO TOCANTINS | J23: NORTE | K23: LD02105019 | L23: 07/07/2026 PARECER COEP: MATERIAL ENVIADO , CONFORME ALINHANDO COM O WANDER REALIZAR SUBSTIUIÇÂO DO EQUIPAMENTO, FAVOR ESCREVER PARECER COCM ANTES DE PASSAR PARA PROTEÇÂO, DO QUE FOI REALIZADO01/07/2026 PARECER COEP: PROBLEMA NO ENVIO DO MATERIAL PARECER DMSL: Religador está com o tanque danificado. Não responde a comandos abertura e fechamento local ou remoto, pois está com sinal de curto circuito. Necessário trocar o equipamento. Para raio do trafo está queimado. Chave de saída da fase C está com o olhal quebrado, necessário substituir a chave. Equipamento ficou bypassado em campo. Aberto entrada e saída, com exceção da fase C de saída que ficou fechada. Favor, substituir equipamento completo por NOJA RC10 e sanar demais pendencias.Senhores Favor verificar RL 7900230155 o mesmo sinalizou aberto no SCADA porem a cidade de Palmeirante estava normal , feito um reset no rl e o mesmo subiu fechado.08/07/2026 PARECER DCMD: EQUIPE ETO-LVGR01 DE GUARAI ESTEVE NO RL 7900230155 DIA 25-06-2026 E FEZ TODAS A PENDENCIAS DO RL, OBS: EQUIPE SO NAO CONECTOU O CABO DO TRAFO NO RL. RL ESTA PRONTO PARA O COMISSIONAMENTO | M23: 15 | N23: 20 | O23: 5 | P23: 15 | Q23: 0 | R23: 10 | S23: 0 | T23: 15 | U23: 80 | V23: Muito Alta | W23: Fonte principal de Palmeirante, RL de transferência operando
A24: 2026 | B24: ETO-TELE 00997/2026 | C24: ETO-TELE | D24: 7908302256 | E24: 79 | F24: 46213 | G24: 256 | H24: MATEIROS | I24: PONTE ALTA TOCANTINS | J24: CENTRO | K24: LD03046026 | L24: RL teve nota baixada (ETO-TELE 970/2026) pore´m eqp continua fora de operação, solicito programação para equipe verificar em campo | M24: 5 | N24: 10 | O24: 5 | P24: 15 | Q24: 15 | R24: 10 | S24: 0 | T24: 15 | U24: 75 | V24: Alta | W24: Isolação de trecho e transferência das cidades de São Felix e Mateiros para gerador, além de atendimento de clientes rurais
A25: 2026 | B25: ETO-RD-GR 00766/2026 | C25: ETO-RD-GR | D25: 5800371025 | E25: 58 | F25: 46230 | G25: 25 | H25: ARAPOEMA | I25: COLINAS DO TOCANTINS | J25: NORTE | K25: LD02010153 | L25: 16/07/2026 PARECER COEP: ALINHADO COM O KELLITON REALIZAR SUBSTITUIÇÃO DO CONTROLE DE TUPIRAMA, ALINHADO COM O JEAN QUE OS CABOS COMPATIBILIZADORES VÃO CHEGAR 16/08 , ATÉ ESSA DATA MANTER ESSA SS E CONTROLE RUA, DEPOIS REPASSAR PARA O DMSLPARECER COEP: AVALIAR COM O LEANDRO, PROVAVELMENTE SÓ COMPRAPARECER DMSL: Após testes foi constatado defeito nos relés da fase A e B, Modelo Toshiba TBR 1000. Se possível, substituir os relés das 3 fases por controle RUA, disponibilizar os cabos de ligação entre o tanque e o controle para possibilitar a compatibilização do equipamento. Fornecer kit de comunicação, rádio, antena, etc.Segue nota para veriifcar falha em regulador de tensão N: 5800371025 dentro S/E Arapoema , equipamento esta com 2 reles com falha marca toshiba . | M25: 0 | N25: 20 | O25: 20 | P25: 10 | Q25: 20 | R25: - | S25: - | T25: - | U25: 70 | V25: Alta | W25: Aumento de reclamações no atendimento de Arapoema no período seco
A26: 2026 | B26: ETO-PROT 00144/2026 | C26: ETO-PROT | D26: 5865120195 | E26: 58 | F26: 46211 | G26: 195 | H26: CENTENARIO | I26: GUARAI | J26: NORTE | K26: LD01065015 | L26: PARECER DMSL:PENDÊNCIA: Realizar melhoria no aterramento por ser tratar de um terreno muito arenoso, e há pendências por parte do time da proteção, os ajustes do RT não estão disponíveis para inserção no referido equipamento.DATA DA MANUTENÇÃO: 12/03/202EQUIPE: Brunno e Edeglan.***********************PARECER DA PROTEÇÃO:FAVOR COMISSIONAR REGULADOR 5865120195 – LD Santa Maria Ramal Centenário e Recursolândia – 34,5kV. AJUSTE REALIZADO, DISPONÍVEL NO APP DA PROTEÇÃO.*********************** INSTALADO NA OBRA 0702400720 GENTILEZA, REALIZAR O COMISSIONAMENTO.LAUDO EM ANEXO.COORD EO: 889017, 901685708-07-2026 PARECER: FOI FEITO A MELHORIA NO REGULADOR CONFORME FOTOS EM ANEXO. | M26: 20 | N26: 20 | O26: 20 | P26: 10 | Q26: 0 | R26: - | S26: - | T26: - | U26: 70 | V26: Alta | W26: Atendimento das RDUs de Centenário, Recursolândia e clientes rurais
A27: 2026 | B27: ETO-COEP 00078/2026 | C27: ETO-COEP | D27: 7926089013 | E27: 79 | F27: 46135 | G27: 13 | H27: PARAISO DO TOCANTINS | I27: PARAISO DO TOCANTINS | J27: CENTRO | K27: LD03062013 | L27: PARECER COEP: EQUIPAMENTO SELECIONADO PARA COMPRAPARECER DMSL: Feedback Equip. EspeciaisRLG 7926089013,RELÉ NOJA RC10SID 1805/2026DATA 15/04/2026Serviço Executado: Favor realizar a troca da parte ativa do equipamento --reprogramar para atualizar a base juntamente com escada Equipamento ficou em operação: Não Pendência: sim atualizar a base e subistituir o tanque Bateria(s) substituída(s)? Não Data de Fabricação/Instalação da(s) bateria(s): Equipe: Carliel e João Vitor Fernando e Elson---------------------------------------------------------------------------------ATUALIZAR AJUSTES DO RL 7926089013 LD PARAISO I A PIUM. IMPLEMENTAÇÃO DA FUNÇÃO 27, SUBTENSÃO.AJUSTES DISPONIVEIS NO APP DA PROTEÇÃO. | M27: 15 | N27: 10 | O27: 5 | P27: 15 | Q27: 15 | R27: 10 | S27: 0 | T27: 0 | U27: 70 | V27: Alta | W27: Transferência da RDU de Chapada de Areia (937 UCs) para fonte alternativa
A28: 2026 | B28: ETO-PROT 00152/2026 | C28: ETO-PROT | D28: 7925087021 | E28: 79 | F28: 46223 | G28: 21 | H28: PARANA | I28: PEIXE | J28: SUL | K28: LD01010021 | L28: 10/07 PARECER COEP: EQUIPAMENTO ENTREGUE AOS COCM´S FAVOR INFORMAR PRAZO DE SUBSTUIÇÃO PARA O DMSL E REPASSAR DEPOIS PARA PROTEÇÃO REALIZAR OS AJUSTES E DESCREVER NA SS O SERVIÇO REALIZADOPARECER COEP: EM ROTA DE ENTREGA, VERIFICAR PREVISÃO DE CHEGADARealizar a substituição do tanque do equipamento. | M28: 15 | N28: 10 | O28: 5 | P28: 0 | Q28: 15 | R28: 10 | S28: 0 | T28: 15 | U28: 70 | V28: Alta | W28: Primeiro RL do 414R de Paranã, RL a jusante na LD também está bay-passado (630 UCs)
A29: 2026 | B29: ETO-PROT 00151/2026 | C29: ETO-PROT | D29: 5801866013 | E29: 58 | F29: 46220 | G29: 13 | H29: PARAISO DO TOCANTINS | I29: PARAISO DO TOCANTINS | J29: CENTRO | K29: AL03062013 | L29: 15/07 PARECER COCM, FOI ATENDIDA PELA OS ETO-RD-PS 1616/2026 OBRA-021260053910/07 PARECER COEP: EQUIPAMENTO ENTREGUE AOS COCM´S FAVOR INFORMAR PRAZO DE SUBSTUIÇÃO PARA O DMSL E REPASSAR DEPOIS PARA PROTEÇÃO REALIZAR OS AJUSTES E DESCREVER NA SS O SERVIÇO REALIZADOPARECER COEP: EM PROCESSO DE ENTREGAPARECER DMSL: RT 5801866013Serviço Executado: Feito a medição da malha de terra. Identificado infiltração na caixa de passagem da célula da fase C do banco regulador de tensão, será necessário fazer a substituição da mesma! Ficar atento na hora da substituição, deverá ser substituída a célula do lado da BR.Obs.: Será necessário baixar todo o banco pelo menos um metro, as buchas estão muito próximas a parte energizada não oferecem segurança para equipe no momento do ensaio elétrico.Equipamento ficou em operação?: Não Possui nobreak: SimPossui antena: SimPossui rádio:SimPendência: SimData da bateria: Equipe: Benvindo e Kaique._______________________________________________RT 5801866013BY PASSADO DEVIDO DEFEITO EM CELULA BEMVINDO ESTEVE NO LOCAL JUNTO AO COD .NECESSARIO TRATATIVA PARA MESMA .FASE DANIFICADO C | M29: 0 | N29: 20 | O29: 20 | P29: 20 | Q29: 10 | R29: - | S29: - | T29: - | U29: 70 | V29: Alta | W29: Atendimento da RDU Luzimangues Industrial por fonte alternativa
A30: 2025 | B30: ETO-RD-PS 00323/2025 | C30: ETO-RD-PS | D30: 5853360007 | E30: 58 | F30: 45946 | G30: 7 | H30: MIRACEMA DO TOCANTINS | I30: MIRACEMA DO TOCANTINS | J30: CENTRO | K30: LD05050008 | L30: REALIZAR TESTES NO EQUIPAMENTO E CONFERIR MEDIÇÕES DA MALHA DE ATERRAMENTO. ESTANDO OK, COMISSIONAR EQUIPAMENTO E COLOCA-LO EM OPERAÇÃO.AJUSTES DISPONIVEIS NO APP DA PROTEÇÃdmsl : N° do Equipamento:*RT 5853360007 MIRACEMASID: 2493/2025Data: 13/05/2025Serviço Executado Provavelmente ocorreu uma descarga no equipamento comprometendo a malha!Será necessário fazer melhoria da malha de aterramento, fazer toda interligação da mesma! Feito ensaios de isolação das 3 células do equipamento, isolação está ok, quando retornar para colocar em operação levar 3 baterias de 7a.Equipamento ficou em operação?: Não Equipe: Benvindo e Jardel | M30: 0 | N30: 20 | O30: 20 | P30: 10 | Q30: 20 | R30: - | S30: - | T30: - | U30: 70 | V30: Alta | W30: Aumento de reclamações no atendimento de Miracema no período seco
A31: 2026 | B31: ETO-PROT 00153/2026 | C31: ETO-PROT | D31: 7900573047 | E31: 79 | F31: 46223 | G31: 47 | H31: FIGUEIROPOLIS | I31: FORMOSO DO ARAGUAIA | J31: SUL | K31: AL02033047 | L31: 10/07 PARECER COEP: EQUIPAMENTO ENTREGUE AOS COCM´S FAVOR INFORMAR PRAZO DE SUBSTUIÇÃO PARA O DMSL E REPASSAR DEPOIS PARA PROTEÇÃO REALIZAR OS AJUSTES E DESCREVER NA SS O SERVIÇO REALIZADOPARECER COEP: AGUARDANDO COCM'S GERAREM AS OBRAS PARA PODER ENTREGAR MATERIALFavor providenciar manutenção no RL 7900573047, o mesmo estar em curto conforme fotos anexadas. Equipamento ficou bay passado em campo.PARECER DMSL: Equipe: FABIO AP./JOÃO MARCOSData Executada: 15/10/2025Serviço Executado:Foi constatado que o equipamento esta queimado na parte ativa placa, tanque e relé. Por favor fazer a substituição pelo Noja RC10. | M31: 5 | N31: 5 | O31: 15 | P31: 0 | Q31: 15 | R31: 10 | S31: 0 | T31: 15 | U31: 65 | V31: Alta | W31: Transferência da Bunge, Saneatins e secadora
A32: 2026 | B32: ETO-RD-PO 00208/2026 | C32: ETO-RD-PO | D32: 7953610256 | E32: 79 | F32: 46219 | G32: 256 | H32: MATEIROS | I32: PONTE ALTA TOCANTINS | J32: CENTRO | K32: LD03046026 | L32: 14/07/2026 - PARECER COEP: REALOCAR TANQUE 34,5 SOBRESSALENTE DE PARAÍSO PARA ATENDER PARECER DMSL: Data: 10/03/2026,Serviço Executado: Foi substituído o relé do equipamento, o mesmo estava danificado. Trocado o DPS, o mesmo estava queimado devido ao tanque estar furado. O equipamento ficou em bypass.Equipamento ficou em operação? NãoPendência? Sim, substituir a parte ativa com cordão umbilical.Equipe: Carliel e João VitorSEGUE SS PARA REGULARIZAR AUTOMAÇÃO DO RL 7953610256 NA INTERLIGAÇÃO COM A COELBA (CHAPADA DA MANGABEIRA) - EQUIPE INFOMOU CURTO INTERNO NO GABINETE DJ AC NÃO FECHA | M32: 5 | N32: 5 | O32: 15 | P32: 15 | Q32: 0 | R32: 0 | S32: 10 | T32: 15 | U32: 65 | V32: Alta | W32: Atenidmento da COELBA (Alto potencial de compensação)
A33: 2026 | B33: ETO-RD-DP 00404/2026 | C33: ETO-RD-DP | D33: 5800438116 | E33: 58 | F33: 46204 | G33: 116 | H33: CHAPADA DA NATIVIDADE | I33: DIANOPOLIS | J33: SUL | K33: LD04002091 | L33: 01/07 PARECER COEP: DENER INFORMOU QUE TEM AS PEÇAS SOBRESSALENTES DE OBRA PARA UTILIZAR, REPASSEREI AO POSTO DO ETO-RD-DP PARA AS TRATATIVAS, FAVOR INFORMAR PREVISÃO DE SUBSTIUIÇÃO E PREENCHER A PLANILHA ASSIM COMO PREENCHER A DESCRIÃO ANTES DE PASSAR PARA PROTEÇÃO FAZER OS AJUSTES30/06PARECER COEP: AGUARDANDO COCM'S CRIAREM OBRA PARA ENTREGA DO MATERIALSegue nota para normalizar falha em regulador N:5800438116 - Chapada da natividade .equipamento está com fase B e C travada .OBS: a fase B esta sinalizando falha , equipamento não insere TAP negativo na fase B e C , o mesmo ficou no TAP zerado e bloqueado .PARECER DMSL (18/08/2025): Foi feito teste de elevar e abaixar nas fases B e C e o mesmo só aceita elevar os taps, constatando que o mercanismo da chave reversoura polaridade está com defeito. Número de série fase B EI7030 e Número de série fase C EI7040. Substituir as fases B e C.Foi constatado que a placa F do controle está com defeito. | M33: 0 | N33: 20 | O33: 20 | P33: 20 | Q33: 0 | R33: - | S33: - | T33: - | U33: 60 | V33: Média | W33: Atendimento da região da Engegold, Nativa, cidade Natividade e Chapada da Natividade (Fonte alternativa)
A34: 2026 | B34: ETO-COEP 00151/2026 | C34: ETO-COEP | D34: 5840227063 | E34: 58 | F34: 46223 | G34: 63 | H34: BANDEIRANTES DO TOCANTINS | I34: COLINAS DO TOCANTINS | J34: NORTE | K34: LD01054060 | L34: PARECER DMSL 13/07/2026: Realizados ensaios de isolação nas três células, e foi identificado curto na fase A, sendo necessário a sua substituição. Os cabos das buchas ficaram desconectados para melhor identificação no momento da sua substituiçãSEGUE PARA O DMSL AVALIAR ANTES DE SEGUIRMOS COM O SERVIÇOSEGUE PARA REALIZAR TROCA---------------------------------------------------------Boa noite,Segue SS para tratativas regulador de tensão 5840227063 fase C em curto | M34: 0 | N34: 20 | O34: 20 | P34: 10 | Q34: 10 | R34: - | S34: - | T34: - | U34: 60 | V34: Média | W34: Atendimento da RDU Bandeirantes e clientes rurais
A35: 2026 | B35: ETO-TELE 00881/2026 | C35: ETO-TELE | D35: 5851753086 | E35: 58 | F35: 46175 | G35: 86 | H35: MARIANOPOLIS | I35: DIVINOPOLIS | J35: CENTRO | K35: LD05062013 | L35: PARECER DMSL: FAVOR SOLUCIONAR PENDENCIAS RT: 5851753086Relé R.U.A Data: _19/05/2026Sid: 2740/2026Possui rádio?: SimPossui antena?: SimPossui módulo nobreak?: SimServiço Executado: * Feito testes no equipamento,o mesmo está normal.* Será necessário fazer melhorias na malha de terra e colocar em operação.Equipamento ficou em operação? Não Pendência: Sim. É necessário fazer melhorias na malha de aterramento.Bateria(s) substituída(s)? _nao Data Fabricação/Instalação da(s) bateria(s): 12/2025Equipe: Jean e BenvindoPARECER DCMD: FEITO MELHORIA NA MALHA DO ATERRAMENTO, FAVOR ENVIAR EQUIPE PARA COLOCA-LO EM OPERAÇÃORT 5851753086MESMO ESTA BY-PASSADO EM CAMPO EQUIPE SINERGIA 086OP01 ESTEVE NO LOCAL APARENTIMENTE SEM DEFEITO APARENTE MESMO FOI BY PASSADO POR TER TIRADO LINHA.DESDE ENTAO MESMO NAO VOLTOU PARA OPERAÇÃO .FAVOR VERIFICAR PARA TESTES POSSIVEIS .PARA QUE O MESMO VOLTA COM DISPONIBILIDADE PARA OPERAÇÃO . | M35: 0 | N35: 20 | O35: 20 | P35: 10 | Q35: 10 | R35: - | S35: - | T35: - | U35: 60 | V35: Média | W35: Atendimento da RDU Marianópolis e clientes rurais
A36: 2026 | B36: ETO-TELE 00986/2026 | C36: ETO-TELE | D36: 5846328094 | E36: 58 | F36: 46211 | G36: 94 | H36: PEIXE | I36: PEIXE | J36: SUL | K36: LD04040003 | L36: COCM SUL - 07/07/2026 - FOI REALIZADO MELHORIA DE ATERRAMENTO E FEITO A MANUTENÇÕES E TODAS AS CHAVES E SUBSTITUIDO OS CONECTORES.PARECER COEP: MELHORIA DE ATERRAMENTO É COCM'S, FAVOR ENCAMINHAR DIRETAMENTE PARA ELES, COCM'S REALIZAR MELHORIA DE ATERRAMENTO POR FAVORPor genteliiza verificar RT 5846328094 situação de equipamento, se encontra by passado em campoPARECER DMSL:Favor, realizar melhoria de aterramento que se encontra alta e substituir todos os conectores das buchas por conectores estrangulador. | M36: 0 | N36: 20 | O36: 20 | P36: 10 | Q36: 10 | R36: - | S36: - | T36: - | U36: 60 | V36: Média | W36: Atendimento da RDU Sucupira e clientes rurais
A37: 2025 | B37: ETO-COEP 00184/2025 | C37: ETO-COEP | D37: 7903112004 | E37: 79 | F37: 45903 | G37: 4 | H37: ARAGUAINA | I37: ARAGUAINA | J37: NORTE | K37: LD05010004 | L37: 20/07 PARECER COEP: EQUIPAMENTO SELECIONADO PARA COMPRAApós testes no RLG 7903112004 foi constatado defeito no mesmo e como se trata de um modelo COOPER FORM6 que está obsoleto e não possuímos peças sobressalentes, faz-se necessária substituição completa por modelo NOJA RC10. | M37: 15 | N37: 10 | O37: 5 | P37: 15 | Q37: 0 | R37: 10 | S37: 0 | T37: 0 | U37: 55 | V37: Alta | W37: Transferência de Babaçulândia, 4 RLs sendo 2 operando
A38: 2025 | B38: ETO-COEP 00120/2025 | C38: ETO-COEP | D38: 7920024127 | E38: 79 | F38: 45839 | G38: 127 | H38: PALMEIRAS DO TOCANTINS | I38: TOCANTINOPOLIS | J38: NORTE | K38: LD01084002 | L38: 30/06 PARECER COEP: AGUARDANDO O RETORNO DO DMSL , PARA ENTENDER SE O PROBLEMA É NA COMUNICAÇÃO OU PARTE ATIVA, JÁ QUE O EQUIPAMENTO EM QUESTÃO SEGUE COMUNICANDOPARECER DMSL: Após testes, equipe DMSL constatou que o relé e a parte ativa do equipamento 7920024127 estão com defeito, sendo necessária a substituição completa por um modelo NOJA RC 10. Favor, subsituir também a chave de saída da fase A que está com o anel de abertura quebrado.RL 7920024127 está desarmando em campo e no SCADA continua fechado, só sinaliza aberto no SCADA quando a equipe faz o resert no equipamento em campo. | M38: 15 | N38: 10 | O38: 5 | P38: 15 | Q38: 0 | R38: 10 | S38: 0 | T38: 0 | U38: 55 | V38: Alta | W38: Transferência de Palmeiras, 3 fontes operando
A39: 2026 | B39: ETO-COEP 00029/2026 | C39: ETO-COEP | D39: 7927646026 | E39: 79 | F39: 46057 | G39: 26 | H39: PONTE ALTA TOCANTINS | I39: PONTE ALTA TOCANTINS | J39: CENTRO | K39: LD03046026 | L39: PARECER COEP: EQUIPAMENTO SELECIONADO PARA COMPRARELIGADOR BY PASSADO POR DEFEITO, NECESSÁRIO AVALIAÇÃO DO PROBLEMA.parecer dmsl:O religador apresenta defeito no tanque, sendo necessário substituir o tanque o mesmo está tirando a linha, e troca os isoladores. Quando retornar, trazer uma fonte para o equipamento, a mesma foi removida.FICOU EM OPERAÇÃO? NãoPENDÊNCIA: Sim, aguardando peças para substituição. | M39: 15 | N39: 10 | O39: 5 | P39: 0 | Q39: 15 | R39: 0 | S39: 10 | T39: 0 | U39: 55 | V39: Alta | W39: Opção de isolação de São Félix e Mateiros para alimentação por gerador
A40: 2026 | B40: ETO-PROT 00156/2026 | C40: ETO-PROT | D40: 7927169001 | E40: 79 | F40: 46224 | G40: 1 | H40: PORTO NACIONAL | I40: PORTO NACIONAL | J40: CENTRO | K40: AL01102271 | L40: PARECER COEP: EQUIPAMENTO ENTREGUE, SEGUE SS PARA O COCM´S , PARA REALIZAR O ATENDIMENTO,FAVOR ADICIONAR O PARECER PARA MANDAR PARA PROTEÇÃOSS ANTIGA: 1500/2025 PARECER DMSL: Serviço Executado: Foi verificado que o tanque do equipamento está danificado, sendo necessário substituir o tanque do equipamento.Equipamento ficou em operação?: NãoPendência: Sim, instalar fonte, disjuntor e DPS, e substituir o tanque.***** Parecer COCM******Subsituido Tranque do RL pela Ordem de Serviço DLP-MPPA01 247/2026 RELATORIO EM ANEXO DA O.S EXECUTORA | M40: 5 | N40: 5 | O40: 15 | P40: 0 | Q40: 15 | R40: 0 | S40: 0 | T40: 15 | U40: 55 | V40: Alta | W40: Transferência dos Grupos A - VLI e Frisia
A41: 2026 | B41: ETO-RD-PO 00097/2026 | C41: ETO-RD-PO | D41: 5800291035 | E41: 58 | F41: 46112 | G41: 35 | H41: MONTE DO CARMO | I41: PONTE ALTA TOCANTINS | J41: CENTRO | K41: LD01051035 | L41: PARECER DMSL: Feito testes funcionais nas 3 células do banco as mesmas corresponderam aos testes. Será necessário fazer a correção da malha de terra, baixar o banco completo pois está muito alto dificultando as atividades da equipe, substituir as 3 chaves facas do lado Fonte e as 3 do lado Carga instalar suporte inclinado das chaves para facilitar as manobras. Colocar cinta no controle RUA abaixar o mesmo, pois está muito alto e fixado com um mosquetão oval, quando retornar para colocar em operação levar 3 baterias de 7a e rele rua.Obs.: Fizeram melhoria na malha de terra, mas não está dentro do aceitável! As outras pendências continuam, favor corrigir. Equipamento ficou em operação?: Não - Equipe: Benvindo e Kaique- SS ANTIGA ETO-TELE 358/2026 | M41: 0 | N41: 20 | O41: 20 | P41: 10 | Q41: 0 | R41: - | S41: - | T41: - | U41: 50 | V41: Média | W41: Aumento de reclamações no atendimento de Silvanópolis por Monte do Carmo no período seco
A42: 2026 | B42: ETO-COEP 00150/2026 | C42: ETO-COEP | D42: 7930428001 | E42: 79 | F42: 46223 | G42: 1 | H42: PORTO NACIONAL | I42: PORTO NACIONAL | J42: CENTRO | K42: LD01100001 | L42: PARECER DMSL DATA 16/07/2026: será necessário fazer a substituição da parte ativa do equipamento.PARECER COEP: Equipamento Funcionando no SCADA , favor reavaliar a necessidade de substituição e se necessário mandar o modelo do equipamento.Segue nota para substituir Taque do RL-7930428001 na LD Porto Nacional / São João, Identificado pela Int-20253617520441 equipamento dando passagem na fase A ficou bay-passado até substituição, Tensão 34,5kva, Acesso livre. | M42: 5 | N42: 5 | O42: 15 | P42: 0 | Q42: 15 | R42: 10 | S42: 0 | T42: 0 | U42: 50 | V42: Alta | W42: Transferência dos Grupos A - Ramal do Rossato (TF 225kVA e TF 750kVA)
A43: 2026 | B43: ETO-RD-PS 00289/2026 | C43: ETO-RD-PS | D43: 5827102054 | E43: 58 | F43: 46202 | G43: 54 | H43: PUGMIL | I43: PARAISO DO TOCANTINS | J43: CENTRO | K43: LD01062013 | L43: PARECER COEP:NÃO É POSSÍVEL RETORNAR COM O CONTROLE COMPLETO , MAS DARIA PARA FAZER A MELHORIA NA MALHA DE ATERRAMENTO , ENCAMINHANDO PARA OS COCM'S PARA REALIZAREM A MELHORIAparecer DMSL: :Nobreack com defeito, rele queimado, cabo de comunicação entre o rádio e o rele danificado, malha de aterramento está com a resistência alta!Feito reparo no cabo, substituído nobreack, e rele. Se possível retornar com controle completo pq o q está em campo teve infiltração de água, abrir chamado no scada para atualizar base do equipamento pois o mesmo está com a base antiga, fazer correção da malha de aterramento.Equipamento ficou em operação?: Não Pendência: sim, levar controle novo, fazer correção da malha de terra, levar suporte para fixar antena. OBS | M43: 0 | N43: 20 | O43: 20 | P43: 10 | Q43: 0 | R43: - | S43: - | T43: - | U43: 50 | V43: Média | W43: Aumento de reclamações no atendimento de Pugmil no período seco
A44: 2025 | B44: ETO-COEP 00173/2025 | C44: ETO-COEP | D44: 7900535058 | E44: 79 | F44: 45894 | G44: 58 | H44: SANTA FE DO ARAGUAIA | I44: ARAGUAINA | J44: NORTE | K44: LD03010004 | L44: PARECER COEP: EQUIPAMENTO SELECIONADO PARA COMPRAPARECER DMSL: Equipamento 7900535058 encontra-se com o relé danificado, firmware corrompido, o mesmo não inicia. Devido ao fato de não possuirmos mais peças de reposição para religador cooper, se faz necessário a substituição de todo conjunto por um Noja RC10.envar equipe para verificar rlo 7900535058 foi feito primeiro ataque com equipe 040op36 o mesmo esta com RELE TRAVADO E FICOU FORA DE OPERAÇÃO, ATENDE RDR DE SANTA FÉ SAIDA DA CIDADEEQUIPE INFORMOU ABELHAS NA CAIXA DO PAINEL DE COMANDO | M44: 5 | N44: 10 | O44: 5 | P44: 0 | Q44: 15 | R44: 10 | S44: 0 | T44: 0 | U44: 45 | V44: Média | W44: Atendimento 3 povoados, na perca 4 ficam fora (900 UCs)
A45: 2025 | B45: ETO-COEP 00221/2025 | C45: ETO-COEP | D45: 5800961074 | E45: 58 | F45: 45996 | G45: 74 | H45: DIANOPOLIS | I45: DIANOPOLIS | J45: SUL | K45: LD03028074 | L45: PARECER COEP: EQUIPAMENTO SELECIONADO PARA COMPRASubstituir as 3 células- Melhoria na malha de aterramento - Melhoria no circuito de aterramento qua aterra as células.- Substituir conectores paralelos | M45: 20 | N45: 0 | O45: 0 | P45: 20 | Q45: 0 | R45: - | S45: - | T45: - | U45: 40 | V45: Média | W45: Atendimento da COELBA e GA Alessandro Maurício (1600 kVA)
A46: 2026 | B46: ETO-COEP 00063/2026 | C46: ETO-COEP | D46: 7944559149 | E46: 79 | F46: 46112 | G46: 149 | H46: CASEARA | I46: DIVINOPOLIS | J46: CENTRO | K46: LD01434149 | L46: 14/07/2026 PARECER COEP: EQUIPAMENTO SELECIONADO PARA COMPRA Equipamento ficou em operação?: NãoPendência: Sim será necessário substituir a placaServiço Executado: curto na placa foi tentando recuperar a mesma porém não teve sucesso!Bateria(s)substituída(s)? NÃOEquipe: Kaique e benvido | M46: 5 | N46: 10 | O46: 0 | P46: 0 | Q46: 15 | R46: 10 | S46: 0 | T46: 0 | U46: 40 | V46: Média | W46: Atendimento de cargas rurais entre Caseaarra e Araguacema (221 UCs)
A47: 2026 | B47: ETO-COEP 00129/2026 | C47: ETO-COEP | D47: 7937102148 | E47: 79 | F47: 46210 | G47: 148 | H47: SAO VALERIO DA NATIVIDADE | I47: PEIXE | J47: SUL | K47: LD01066094 | L47: PARECER COEP: REAVALIAR DISPONIBILIDADE DO EQUIPAMENTO NO SCADA ASSIM COMO , FORNECER MODELO DO EQUIPAMENTO E FAIXA DE TENSÃO PARA COMPRA / AQUISIÇÃOTanque com defeito, realizar substituição do tanque. | M47: 5 | N47: 5 | O47: 5 | P47: 0 | Q47: 15 | R47: 10 | S47: 0 | T47: 0 | U47: 40 | V47: Média | W47: Fonte principal do Ramal Serranópolis (181 UCs), RL de transferência operando
A48: 2026 | B48: ETO-PROT 00135/2026 | C48: ETO-PROT | D48: 7922995039 | E48: 79 | F48: 46202 | G48: 39 | H48: ARAGUATINS | I48: AUGUSTINOPOLIS | J48: NORTE | K48: AL03109039 | L48: PARECER COEP: Equipamento em operação, instalado com sucesso, segue para Proteção para ajustesPARECER DMSL: Após testes, equipe DMSL constatou que o RLG 7922995039 encontra-se com parte ativa e controle danificados. Favor, realizar substituição completa do equipamento.Troca do sistema de comunicação do equipamento | M48: 5 | N48: 5 | O48: 0 | P48: 0 | Q48: 15 | R48: 10 | S48: 0 | T48: 0 | U48: 35 | V48: Média | W48: Atendimento do PA Esperança Viva (396 UCs)
A49: 2026 | B49: ETO-COEP 00024/2026 | C49: ETO-COEP | D49: 7933585074 | E49: 79 | F49: 46049 | G49: 74 | H49: DIANOPOLIS | I49: DIANOPOLIS | J49: SUL | K49: LD03028074 | L49: 30/06 PARECER COEP: EQUIPAMENTO SELECIONADO PARA COMPRAREALIZAR SUBSTITUIÇÃO DO TANQUE, O MESMO ESTÁ COM DEFEITO. | M49: 5 | N49: 5 | O49: 15 | P49: 0 | Q49: 0 | R49: 0 | S49: 10 | T49: 0 | U49: 35 | V49: Média | W49: Atendimento da COELBA
A50: 2026 | B50: ETO-COEP 00133/2026 | C50: ETO-COEP | D50: 7955986084 | E50: 79 | F50: 46211 | G50: 84 | H50: DIVINOPOLIS | I50: DIVINOPOLIS | J50: CENTRO | K50: LD04062013 | L50: 14/07/2026 PARECER COEP : SUBSTIUIR CONTROLE COMPLETOPARECER DMSL: Equipamento com a placa de alimentação ca em curto, será necessário substituir a placa do equipamento. (Antiga nota era pra ter sido repassada porém foi baixada indevidamente pela equipe) | M50: 5 | N50: 5 | O50: 0 | P50: 0 | Q50: 15 | R50: 10 | S50: 0 | T50: 0 | U50: 35 | V50: Média | W50: Transferência de cargas do 444R da SE Paraíso I
A51: 2026 | B51: ETO-COEP 00045/2026 | C51: ETO-COEP | D51: 7927396052 | E51: 79 | F51: 46083 | G51: 52 | H51: FORMOSO DO ARAGUAIA | I51: FORMOSO DO ARAGUAIA | J51: SUL | K51: LD03036052 | L51: PARECER COEP: EQUIPAMENTO SELECIONADO PARA COMPRAreligador foi bay passado devido mesmo esta saindo fumaca do painel e sem comunicação 7927396052.PARECER DMSL: Após testes, equipe DMSL constatou que apenas o tanque do RLG 7927396052 encontra-se queimado. Favor, substituir parte ativa do equipamento.NS Tanque: 0320123040198 | M51: 5 | N51: 5 | O51: 0 | P51: 0 | Q51: 15 | R51: 10 | S51: 0 | T51: 0 | U51: 35 | V51: Média | W51: Equipamento localizado Fonte principal de atendimento a SE Cobrape
A52: 2026 | B52: ETO-COEP 00058/2026 | C52: ETO-COEP | D52: 7925733015 | E52: 79 | F52: 46111 | G52: 15 | H52: PEDRO AFONSO | I52: GUARAI | J52: NORTE | K52: LD01414015 | L52: PARECER COEP: EQUIPAMENTO SELECIONADO PARA COMPRAPARECER DMSL: FEEDBACK EQUIP. ESPECIAISNº DO EQUIPAMENTO: 7925733015TIPO EQUIPAMENTO: Noja RC10TIPO DE COMUNICAÇÃO: Rádio GEDATA DA MANUTENÇÃO: 24/03/2026SID: 1475/2026DESCRIÇÃO: Tanque do equipamento em CurtoFICOU EM OPERAÇÃO?: Não PENDÊNCIA: Sim, repassar a nota para DCMD substituir tanque.DADOS DIVERGENTES DA PROGRAMAÇÃO: NãoBATERIA SUBSTITUÍDA?: Não TIPO DE BATERIA: Lítio EQUIPE: Edicleber e Jhonata(DEOP)------------------------------------------------------------------------------------------------------religador 7925733015 com defeito, equipe fez abertura da chave de saida do mesmo e ele não aceita fehcamento devido provavel curto-circuito interno, enviar equipe para verificar o mesmo ficou by-pass fechado | M52: 5 | N52: 5 | O52: 0 | P52: 0 | Q52: 15 | R52: 10 | S52: 0 | T52: 0 | U52: 35 | V52: Média | W52: Transferência do Ramal Agrovila (73 UCs)
A53: 2026 | B53: ETO-COEP 00125/2026 | C53: ETO-COEP | D53: 7900525015 | E53: 79 | F53: 46210 | G53: 15 | H53: PEDRO AFONSO | I53: GUARAI | J53: NORTE | K53: LD02424015 | L53: PARECER COEP: É PARA REALIZAR A SUBSTITUIÇÃO DO RELIGADOR OU DAS BUCHAS, CASO SEJA BUCHAS , REPASSAR PARA OS COCM'S , CASO NÃO SEJA ESPECIFIQUE O MODELO , E A TENSÃO, FICO NO AGUARDO DO RETORNONota para manutenção substituir religador 7900525015 que está com as buchas de entrada danificadas fase A estourada e bc danificadas Local LD Pedro Afonso A Chaparral | M53: 5 | N53: 5 | O53: 0 | P53: 0 | Q53: 15 | R53: 10 | S53: 0 | T53: 0 | U53: 35 | V53: Média | W53: Tranferência do Ramal do Chaparral (251 UCs)
A54: 2026 | B54: ETO-COEP 00038/2026 | C54: ETO-COEP | D54: 7908249152 | E54: 79 | F54: 46077 | G54: 152 | H54: SANTA ROSA DO TOCANTINS | I54: PORTO NACIONAL | J54: CENTRO | K54: LD02072001 | L54: 14/07/2026 PARECER COEP: EQUIPAMENTO SELECIONADO PARA COMPRADMSL:Serviço Executado: Houve um curto no equipamento danificando a parte ativa, será necessário fazer a substituição do equipamento completo ( parte ativa e controle) colocar o um cabo pp novo do trafo até o Dj pois o mesmo está sem condições de uso. Obs:. Foi retirado rádio e rele Equipamento ficou em operação?: Não Pendência: Sim, substituir o equipamento completo. | M54: 5 | N54: 5 | O54: 0 | P54: 0 | Q54: 15 | R54: 10 | S54: 0 | T54: 0 | U54: 35 | V54: Média | W54: Atendimento de zona rural em Santa Rosa (160 UCs)
A55: 2026 | B55: ETO-PROT 00155/2026 | C55: ETO-PROT | D55: 7942572059 | E55: 79 | F55: 46224 | G55: 59 | H55: TAQUARALTO | I55: TAQUARALTO | J55: CENTRO | K55: LD02059122 | L55: PARECER COEP: EQUIPAMENTO COM MELHORIA DE ATERRAMENTO É COM A ETO-RD-PA , NÃO PASSA PELO FLUXO DE AQUISIÇÃO DO COEP, FAVOR REALIZAR MELHORIA DE ATERRAMENTO ETO-RD-PAPARECER DMSL 19/05/2026: É necessário fazer melhorias na malha de aterramento.segue nota para RL 794252059 o mesmo esta sem comunicaçao, foi feito primeiro ataque, porem a comunicaçao nao voltou, obs ramal do marasca.**** Parcecer do COCM CENTRO-****FEITO A MALHAR DE ATERRAMENTO ATENDIDA PELA ORDEM DE SERVIÇO DLP-MLPA02 91/2026 COM RELATORIO EM ANEXO A O.S | M55: 5 | N55: 5 | O55: 15 | P55: 0 | Q55: 0 | R55: 0 | S55: 10 | T55: 0 | U55: 35 | V55: Média | W55: Atendimento do Ramal do Marasca e GAs (108 UCs)
A56: 2026 | B56: ETO-COEP 00123/2026 | C56: ETO-COEP | D56: 7928564039 | E56: 79 | F56: 46210 | G56: 39 | H56: ARAGUATINS | I56: AUGUSTINOPOLIS | J56: NORTE | K56: LD02109039 | L56: PARECER COEP: EQUIPAMENTO SELECIONADO PARA COMPRATroca do sistema de comunicação do equipamentoDMSL 28/07/2025: Equipamento com tanque, modulo e rele com defeito, solicitar troca do equipamento ao DCMD.Fotos vão ser enviadas por e-mail | M56: 5 | N56: 10 | O56: 5 | P56: 0 | Q56: 0 | R56: 10 | S56: 0 | T56: 0 | U56: 30 | V56: Média | W56: Transferência entre 424R Araguatins e 434R Augustinópolis
A57: 2026 | B57: ETO-COEP 00156/2026 | C57: ETO-COEP | D57: 5855411017 | E57: 58 | F57: 46227 | G57: 17 | H57: BARROLANDIA | I57: MIRACEMA DO TOCANTINS | J57: CENTRO | K57: AL02017017 | L57: 20/07 PARECER COCM: NÃO RECEBEMOS MATERIAL10/07 PARECER COEP: EQUIPAMENTO ENTREGUE AOS COCM´S FAVOR INFORMAR PRAZO DE SUBSTUIÇÃO PARA O DMSL E REPASSAR DEPOIS PARA PROTEÇÃO REALIZAR OS AJUSTES E DESCREVER NA SS O SERVIÇO REALIZADOPARECER COEP: EQUIPAMENTO EM ROTA DE ENTREGASEM COMUNICAÇÃO, FALHA DE ALIMENTAÇÃO - REALIZADO PRIMEIRO ATAQUE SEM SUCESSO.PARECER DMSL: 17/09/2025 Equipamento ficou em operação? Não Pendência: sim. Equipamento ficou Bay passado levar controle COMPLETO para trocar. ellisfran | M57: 0 | N57: 0 | O57: 0 | P57: 10 | Q57: 20 | R57: - | S57: - | T57: - | U57: 30 | V57: Baixa | W57: Atendimento do Assentamento Irmã Adelaide
A58: 2026 | B58: ETO-TELE 01002/2026 | C58: ETO-TELE | D58: 7908196047 | E58: 79 | F58: 46216 | G58: 47 | H58: FIGUEIROPOLIS | I58: FORMOSO DO ARAGUAIA | J58: SUL | K58: AL02033047 | L58: 13/07/2026 PARECER COEP: EQUIPAMENTO REMANEJADO FAVOR FAZER O COMISSIONAMENTORELIGADOR N° 7908196047 REMANEJADO NA OBRA 0402401150 GENTILEZA, REALIZAR O COMISSIONAMENTO. LAUDO EM ANEXO. COORD EO: 698485, 8657287PARECER DA PROTEÇÃO:AJUSTE DISPONIBILIZADO NO APP DA PROTEÇÃO, NOTA REPASSADA PARA DMSL COMISSIONAR, POLO GURUPI, RL APENAS REMANEJADO DA REDE VELHA PARA REDE NOVA, EQUIPAMENTO COOPER, SE MANTEVE O MESMO NÚMERO DE ATIVO.ENG° IRLLEY CASTELO BRANCO.PARECER DMSL: Constatado curto-circuito no tanque do religador, impedindo as operações de abertura e fechamento do equipamento. Solicita-se a substituição completa do religador, incluindo tanque e unidade de controle. | M58: 5 | N58: 5 | O58: 5 | P58: 0 | Q58: 0 | R58: 0 | S58: 10 | T58: 0 | U58: 25 | V58: Baixa | W58: Seccionamento do Rural e energização do 224R
A59: 2026 | B59: ETO-COEP 00134/2026 | C59: ETO-COEP | D59: 7955946007 | E59: 79 | F59: 46211 | G59: 7 | H59: MIRACEMA DO TOCANTINS | I59: MIRACEMA DO TOCANTINS | J59: CENTRO | K59: LD05050008 | L59: 13/07/2026 PARECER COEP: SUBSTITUIR CONTOLE OU MANDAR MANUTENCIONAR EM CASO DE PRIORIDADE ALTAPARECER DMSL: Necessário substituir a placa de alimentação ca, a mesma está em curto não conseguimos recuperar. (Antiga nota era pra ter sido repassada porém foi baixada indevidamente pela equipe) | M59: 5 | N59: 5 | O59: 5 | P59: 0 | Q59: 0 | R59: 0 | S59: 10 | T59: 0 | U59: 25 | V59: Baixa | W59: Alimentação do serviço auxiliar da Investco e clientes rurais (260 UCs)
A60: 2026 | B60: ETO-COEP 00148/2026 | C60: ETO-COEP | D60: 7923927122 | E60: 79 | F60: 46219 | G60: 122 | H60: PALMAS | I60: PALMAS | J60: CENTRO | K60: LD02059122 | L60: PARECER DMSL 16/07: Nota solicitada ao DMSL com a informação de que o tanque precisa ser substituído. Estou encaminhando a nota para a área responsável.Segue nota para envia manutenção substituir tanque do RL-7923927122 em curto, Anomalia identificada desarme das LD, s Palmas / Aparecida e Palmas Taquaruçu, Acesso livre, Tensão 34,5kv, Local RL de Interligação entre 424R / 414R. | M60: 15 | N60: 0 | O60: 0 | P60: 0 | Q60: 0 | R60: 10 | S60: 0 | T60: 0 | U60: 25 | V60: Baixa | W60: Transferência entre 414R e 424R SE Palmas II
A61: 2025 | B61: ETO-COEP 00158/2025 | C61: ETO-COEP | D61: 7942485096 | E61: 79 | F61: 45861 | G61: 96 | H61: PINDORAMA DO TOCANTINS | I61: PONTE ALTA TOCANTINS | J61: CENTRO | K61: LD03046026 | L61: 30/06 PARECER COEP: EQUIPAMENTO SELECIONADO PARA COMPRARELIGADOR COM DEFEITO 7942485096, ESTA DANDO PASSAGEM ESTANDO ABERTO. NÃO ACEITA COMANDOS. FICOU BY PASSADO EM CAMPO PARA MANUTENÇÃO.PARECER DMSL: Ao testar o tanque, foi constatado que o mesmo está danificado e precisa ser substituído.Substituir somente o tanque. Deixar claro na nota para o dcmd substituir somente o tanque. Não tem necessidade de substituir o controle. | M61: 5 | N61: 5 | O61: 5 | P61: 0 | Q61: 0 | R61: 10 | S61: 0 | T61: 0 | U61: 25 | V61: Baixa | W61: Transferência da PCH Bagagem
A62: 2026 | B62: ETO-COEP 00132/2026 | C62: ETO-COEP | D62: 7921202014 | E62: 79 | F62: 46211 | G62: 14 | H62: PIUM | I62: PARAISO DO TOCANTINS | J62: CENTRO | K62: LD01025012 | L62: PARECER COEP: EQUIPAMENTO SELECIONADO PARA COMPRA , DEVERIA SER SUBSTITUIDO PARTE ATIVAPARECER DMSL: Serviço Executado: _ indentificado o problema na parte ativa será necessário fazer a substituição da mesmo, feito a medição do aterramento. Preciso substituir para raio da fase c.Equipamento ficou em operação?: _NAOPendência: _SimBateria(s) substituída(s)? _NãoData Fabricação/Instalação da(s) bateria(s):_Equipe: _Benvindo e kaique----------------------------------------------------------------------------------RL com defeito no rele, fica só reiniciando ficou By passado OS atendimento primeiro ataque 106530226 | M62: 5 | N62: 5 | O62: 5 | P62: 0 | Q62: 0 | R62: 10 | S62: 0 | T62: 0 | U62: 25 | V62: Baixa | W62: Atendimento de Clientes rurais (483 UCs)
A63: 2025 | B63: ETO-COEP 00143/2025 | C63: ETO-COEP | D63: 7927446001 | E63: 79 | F63: 45846 | G63: 1 | H63: PORTO NACIONAL | I63: PORTO NACIONAL | J63: CENTRO | K63: LD02072001 | L63: 30/06 PARECER COEP: EQUIPAMENTO COMPLETOSegue para verificação RL sem comunicação feito primeiro ataque sem sucesso.PARECER DMSL:Data:* _08/07/2025Serviço Executado: Placa de alimentação danificada, devido a curto, não temos material sobressalente para manutenção! Favor substituir o equipamento completo.Obs.: O rádio ficou dentro do controle, favor orientar a equipe que for substituir colocar dentro do controle novo.Equipamento ficou em operação?: Não Pendência: Sim, substituir equipamento completo. | M63: 5 | N63: 5 | O63: 5 | P63: 0 | Q63: 0 | R63: 10 | S63: 0 | T63: 0 | U63: 25 | V63: Baixa | W63: Alimentação de Monte do Carmo por Porto Nacional
A64: 2026 | B64: ETO-COEP 00128/2026 | C64: ETO-COEP | D64: 7928241200 | E64: 79 | F64: 46210 | G64: 200 | H64: SAO SALVADOR DO TOCANTINS | I64: PEIXE | J64: SUL | K64: LD02066094 | L64: PARECER COEP: EQUIPAMENTO SELECIONADO PARA COMPRAPARECER DMSL: Tinha uma nota aberta 422/2025 e logo após a equipe resolver a comunicação ela foi baixada, porém a equipe relatou que ''na estrada ontem o COS nos avisou para voltar que na hora de colocar em operação ele tirou a linha fora. Hoje retornamos nele e fizemos ensaios elétricos e foi constatado que o tanque está em curto. Passa direto aí para o Dcmd para substituição do tanque.'' | M64: 5 | N64: 5 | O64: 5 | P64: 0 | Q64: 0 | R64: 10 | S64: 0 | T64: 0 | U64: 25 | V64: Baixa | W64: Fonte principal do Ramal do Retiro (246UCs), RL transferência by-passado
A65: 2026 | B65: ETO-COEP 00061/2026 | C65: ETO-COEP | D65: 7901110084 | E65: 79 | F65: 46112 | G65: 84 | H65: DIVINOPOLIS | I65: DIVINOPOLIS | J65: CENTRO | K65: LD04062013 | L65: PARECER COEP: EQUIPAMENTO SELECIONADO PARA COMPRAPARECER DMSL: Serviço Executado: Foi feito análise técnica, testes funcionais e identificado que a parte ativa do equipamento está com defeito. Necessário substituir a parte ativa.FICOU EM OPERAÇÃO? Não- EQUIPE: Carliel e BenvindoSegue SS para verificaçao Rl esta danificado dando passagem de tensão mesmo aberto Sim, quando retornar trazer uma fonte pois a mesma foi removida. | M65: 5 | N65: 5 | O65: 0 | P65: 0 | Q65: 0 | R65: 0 | S65: 10 | T65: 0 | U65: 20 | V65: Baixa | W65: Localizado na fonte principal de atendimento de Divinópolis e Abreulândia
A66: 2026 | B66: ETO-COEP 00114/2026 | C66: ETO-COEP | D66: 7913662076 | E66: 79 | F66: 46183 | G66: 76 | H66: DUERE | I66: GURUPI | J66: SUL | K66: AL01031076 | L66: 30/06 PARECER COEP: AGUARDANDO RETORNO DO DMSL PARA ENTENDER EXATAMENTE O QUE TENHO QUE SUBSTITUIRAberto nota para substituir tanque danificado e chave de entrada fase B danificadaPARECER DMSL: Foi confirmado pela equipe DMSL o defeito do tanque, favor seguir com a substituição e correção da chave de entrada fase B danificada. | M66: 5 | N66: 5 | O66: 0 | P66: 0 | Q66: 0 | R66: 10 | S66: 0 | T66: 0 | U66: 20 | V66: Baixa | W66: Atendimento do Ramal do Bacuri (168 UCs)
A67: 2026 | B67: ETO-RD-DP 00457/2026 | C67: ETO-RD-DP | D67: 5862236091 | E67: 58 | F67: 46223 | G67: 91 | H67: ALMAS | I67: DIANOPOLIS | J67: SUL | K67: LD05002091 | L67: 20/07 PARECER COEP: EQUIPAMENTO ENTREGUE , FAVOR EDITAR A SS COM A DATA PREVISTA DE SUBSTITUIÇÃO NO PARECER DOS COCM´S Realizar substituição da FASE B.Célula da fase B estava com a tampa do contador de tape aberta, pegou chuva e molhou os contatos danificando a peça toda. | M67: 0 | N67: 0 | O67: 0 | P67: 20 | Q67: 0 | R67: - | S67: - | T67: - | U67: 20 | V67: Baixa | W67: Atendimento da LD Vale Rio Doce (Nova Aura Mineradora)
A68: 2026 | B68: ETO-COEP 00095/2026 | C68: ETO-COEP | D68: 5836786094 | E68: 58 | F68: 46160 | G68: 94 | H68: PEIXE | I68: PEIXE | J68: SUL | K68: LD01066094 | L68: 24/07 PARECER COEP:EQUIPAMENTO EM LOGISTICA DE ENTREGA Favor levar outro regulador de tensão, pois o mesmo foi furtado em campo. | M68: 0 | N68: 0 | O68: 0 | P68: 10 | Q68: 10 | R68: - | S68: - | T68: - | U68: 20 | V68: Baixa | W68: Atendimento de clientes rurais na LD Peixe Angical - Peixe
A69: 2026 | B69: ETO-RD-PS 00327/2026 | C69: ETO-RD-PS | D69: 7919270014 | E69: 79 | F69: 46225 | G69: 14 | H69: PIUM | I69: PARAISO DO TOCANTINS | J69: CENTRO | K69: LD01047073 | L69: PARECER COEP: AGUARDANDO RETORNO DO DMSL, EQUIPAMENTO FOI INSTALADO NOVO NA OBRA 0212501060, ENTENDER O PORQUE NÃO FOI REALIZADO COMISSIONAMENTOPARECER DMSL: Substituir Equipamento completo problema na placa de alimentação e na parte ativa, falta colocar placa de identificação correta na topologia, baixar o controle.Equipamento ficou em operação?: naoPendência: simBateria(s) substituída(s)? NÃOEquipe: Kaique/ Benvindo13/07/2026 PARECER COEP: SUBSTITUIÇÃO REALZIADA , FAVOR COMISSIONARPARECER DMSL (22/07/26): Solicito que o laudo de substituição seja anexado, e a SS seja repassada para proteção atribuir a ordem de ajuste, antes de repassar para ETO-TELE.----------------------------------------------PARECER DA PROTEÇÃO: Prosseguir com o comissionamento. Ajustes de religador permanecem os mesmos, disponíveis no APP da Proteção.********************************RELIGADOR N°7919270014 REMANEJADO NA OBRA 0212501060 GENTILEZA, REALIZAR O COMISSIONAMENTO. LAUDO EM ANEXO. COORD EO: 617422, 8830787 | M69: 5 | N69: 5 | O69: 0 | P69: 0 | Q69: 0 | R69: 10 | S69: 0 | T69: 0 | U69: 20 | V69: Baixa | W69: Atendimento de Clientes rurais (48 UCs)
A70: 2026 | B70: ETO-COEP 00051/2026 | C70: ETO-COEP | D70: 7926442035 | E70: 79 | F70: 46099 | G70: 35 | H70: MONTE DO CARMO | I70: PONTE ALTA TOCANTINS | J70: CENTRO | K70: LD01051035 | L70: PARECER COEP: EQUIPAMENTO SELECIONADO PARA COMPRAPARECER DMSL: Data: 12/03/2026 Serviço Executado:- Análise técnica constatou:- Parte ativa do equipamento danificada: necessita substituição- Trafo danificado: foi feitos testes nas buchas secundárias o mesmo não chega tensão - Vazamento de óleo - Necessita substituiçãoEquipamento ficou em operação? NãoPendências:- Solicitar limpeza de faixa para acesso ao equipamento- Trocar parte ativa do equipamento- Substituir o trafoEquipe: Carliel e João VitorSegue nota para envia equipe verificar falha de comunicação e automação no RL-7926442035 feito primeiro ataque com equipe 035OP02, porém sem sucesso. | M70: 5 | N70: 5 | O70: 0 | P70: 0 | Q70: 0 | R70: 0 | S70: 10 | T70: 0 | U70: 20 | V70: Baixa | W70: Atenidmento do PA Principado (200 UCs)
A71: 2026 | B71: ETO-COEP 00144/2026 | C71: ETO-COEP | D71: 7938137007 | E71: 79 | F71: 46218 | G71: 7 | H71: MIRACEMA DO TOCANTINS | I71: MIRACEMA DO TOCANTINS | J71: CENTRO | K71: AL02017017 | L71: PARECER DMSL 09/07/2026: GENTILEZA VERIFICAR HAVIA UMA NOTA ABERTA, EQUIPE RETORNOU EM CAMPO E NÃO FOI REALIZADAserviço realizado na SS ENC-RD-PS 1397/2025, REPASSANDO PARA COMISSIONARRL 7938137007 NO RL INSTALAR BATERIA NOVA E RADIO A PEDIDO DE KAROLINY DMSLACESSO LIVREPARECER DMSL: * equipamento esta com a bucha da fase A com problemas(solta), necessário substituir* Trafo do serviço auxiliar esta vazando óleo, necessário substituir- Material ainda não foi entregue para substituição 15/07/2026 | M71: 5 | N71: 5 | O71: 5 | P71: 0 | Q71: 0 | R71: 0 | S71: 0 | T71: 0 | U71: 15 | V71: Baixa | W71: Transferência do Irmã Adelaide (470 UCs)
A72: 2026 | B72: ETO-RD-DP 00403/2026 | C72: ETO-RD-DP | D72: 5856156091 | E72: 58 | F72: 46202 | G72: 91 | H72: ALMAS | I72: DIANOPOLIS | J72: SUL | K72: LD04002091 | L72: DCMD 26.03.2026. SS REPASSADA PARA COEP PROVIDENCIAR MATERIAL. NÃO TEMOS O MATERIAL EM ESTOQUE PARA SUBSTITUIÇÃO. COEP: Equipamento fornecido ao COCM-S para regularização.PARECER COEP: EQUIPAMENTOS JÁ FORNECIDOS PARA OS COCM'S PARA REGULARIZAÇÃOPARECER DA PROTEÇÃO:EQUIPAMENTOS FURTADOS. PARA AQUISIÇÃO DAS CELULAS DE REPOSIÇÃO, FAVOR CONSULTAR OS DADOS DE PLACA EM ANEXO.PARECER DA PROTEÇÃO:COMISISONAR RT 5856156091 LD DIANOPOLIS A NATIVIDADE. NECESSARIO REALIZAR MEDIÇÕES DA RESISTENCIA DA MALHA DE ATERRAMENTO.AJUSTES DISPONIVEIS NO APP DA PROTEÇÃO.RELIGADOR N° 5856156091 INSTALADO NA OBRA 0502400526 GENTILEZA, REALIZAR O COMISSIONAMENTO. LAUDO EM ANEXO. COORD EO: 899501, 8714782 | M72: 0 | N72: 0 | O72: 0 | P72: 0 | Q72: 0 | R72: - | S72: - | T72: - | U72: 0 | V72: Baixa | W72: Equipamento novo furtado antes de ser colocado em operação
A73: 2026 | B73: ETO-TELE 01032/2026 | C73: ETO-TELE | D73: 5858783119 | E73: 58 | F73: 46230 | G73: 119 | H73: SAO BENTO DO TOCANTINS | I73: TOCANTINOPOLIS | J73: NORTE | K73: LD03005098 | L73: 27/07/2026 PARECER COEP: FIZEMOS UMA VISITA AO EQUIPAMENTO , EQUIPAMENTO SE ENCONTRA EM OPERAÇÃO E SEM SINAL DE AVARIA FAVOR AVALIAR PARECER DMSL A SS FOTOS COM O LUANDERSSON OU JOAO ANTONIO LAGARES 20/07 PARECER COEP: EQUIPAMENTO SELECIONADO PARA COMPRA , DEVIDO AO ERRO NA INSTALAÇÃO E O FURTOPARECER DMSL: 16/06/2025-SERVIÇO EXECUTADO: Ao chegar no equipamento para realizar comissionamento, foi constatato que as 3 células estavam com a tampa de inspeção abertas e sem os para-raios. Constatado também que foi furtado todo o óleo isolante das 3 células, sendo necessário a substituição das 3 células. FICOU EM OPERAÇÃO?: Não PENDÊNCIA: Substituir as 3 células | M73: 0 | N73: 0 | O73: 0 | P73: 0 | Q73: 0 | R73: - | S73: - | T73: - | U73: 0 | V73: Baixa | W73: Equipamento novo furtado antes de ser colocado em operação, não inserido no SCADA
A74: 2026 | B74: ETO-TELE 00982/2026 | C74: ETO-TELE | D74: 7955832052 | E74: 79 | F74: 46207 | G74: 52 | H74: FORMOSO DO ARAGUAIA | I74: FORMOSO DO ARAGUAIA | J74: SUL | K74: LD01035052 | L74: SEGUE SOLICITAÇÃO DE SERVIÇO PARA REALIZAR VERIFICAÇÃO DO RL 7955832052 EQUIPAMENTO DE INTEELIGAÇÃO O MESMO ESTA SEM COMUNICAÇÃO ...FOI REALIZADO PRIMEIRO ATAQUE COM EQUIPE SINERGIA DE FORMOSO EO EQUIPAMENTO NÃO VOLTOU | U74: 0 | V74: Falta definir
A75: 2026 | B75: ETO-COEP 00138/2026 | C75: ETO-COEP | D75: 7930359149 | E75: 79 | F75: 46216 | G75: 149 | H75: CASEARA | I75: DIVINOPOLIS | J75: CENTRO | K75: LD03414149 | L75: PARECER DMSL 07/07/2026: equipamento tem que ser subistuido pois não faz comando, parte ativa com defeito FEITO O PRIMEIRO ATAQUE NO RELIGADOR 7930359149 E MESMO NÃO ACEITA COMANDO NEM LOCAL E NEM REMOTO SEGUNDO EQUIPE 149OP02 E PLACA DO RL ESTA CARBONIZADA COM SINAL DE CURTO. | U75: 0 | V75: Falta definir
A76: 2026 | B76: ETO-TELE 00932/2026 | C76: ETO-TELE | D76: 7902098003 | E76: 79 | F76: 46188 | G76: 3 | H76: GURUPI | I76: GURUPI | J76: SUL | K76: AL01041003 | L76: Segue SS de religador 7902098003 sem comunicação. Foi realizado o primeiro ataque porem o mesmo não retornou a comunicação. | U76: 0 | V76: Falta definir
A77: 2026 | B77: ETO-COEP 00147/2026 | C77: ETO-COEP | D77: 7953211079 | E77: 79 | F77: 46219 | G77: 79 | H77: ITAPIRATINS | I77: GUARAI | J77: NORTE | K77: LD03038009 | L77: 20/07 PARECER COEP: EQUIPAMENTO SELECIONADO PARA COMPRASegue nota para substituir relé religador avariado marca noja , equipamento N: 7953211079 - Itapiratins .Obs: informação repassado pelo técnico DMSL Bruno . | U77: 0 | V77: Falta definir
A78: 2026 | B78: ETO-TELE 00929/2026 | C78: ETO-TELE | D78: 7949648145 | E78: 79 | F78: 46186 | G78: 145 | H78: MAURILANDIA DO TOCANTINS | I78: AUGUSTINOPOLIS | J78: NORTE | K78: AL02043081 | L78: FEITO PRIMEIRO ATAQUE COM A EQUIPE LOCAL E NÃO VOLTOU A COMUNICAR. PROVIDENCIAR MANUTENÇÃO PARA O MESMO. | U78: 0 | V78: Falta definir
A79: 2026 | B79: ETO-TELE 00938/2026 | C79: ETO-TELE | D79: 7908300096 | E79: 79 | F79: 46191 | G79: 96 | H79: PINDORAMA DO TOCANTINS | I79: PONTE ALTA TOCANTINS | J79: CENTRO | K79: LD03046026 | L79: Segue nota para verificar falha intermitência na comunicação RL 7908300096 RDU- Pindorama . | U79: 0 | V79: Falta definir
A80: 2026 | B80: ETO-TELE 00892/2026 | C80: ETO-TELE | D80: 7953570026 | E80: 79 | F80: 46179 | G80: 26 | H80: PONTE ALTA TOCANTINS | I80: PONTE ALTA TOCANTINS | J80: CENTRO | K80: LD03046026 | L80: Segue RL 7953570026 O MESMO FOI FEITO PRIMEIRO ATAQUE, painel do religador acendeu porem não voltou a comunicação junto ao SCADA, equipe fez teste em comando local, tudo normal porem sem retorno de comunicação, rl na SE DE PONTE ALTA | U80: 0 | V80: Falta definir
A81: 2026 | B81: DG-RD-PO 00444/2026 | C81: DG-RD-PO | D81: 7911120026 | E81: 79 | F81: 46204 | G81: 26 | H81: PONTE ALTA TOCANTINS | I81: PONTE ALTA TOCANTINS | J81: CENTRO | K81: LD03046026 | L81: Segue nota para recuperar malha de aterramento no RL 7911120026 RDU- Ponte Alta .OBS: Provavelmente foi furtado cabos de aterramento . | U81: 0 | V81: Falta definir
A82: 2026 | B82: ETO-TELE 01019/2026 | C82: ETO-TELE | D82: 7908716091 | E82: 79 | F82: 46223 | G82: 91 | H82: ALMAS | I82: DIANOPOLIS | J82: SUL | K82: LD03046026 | L82: Segue nota para verificar falha de comunicação no religador 7908716091 - Rural - Almas .Equipamento perdeu a comunicação quando faltou CA , porém mesmo ao retorna o CA não retornou à comunicação ! | V82: Falta definir
A83: 2026 | B83: ETO-TELE 01005/2026 | C83: ETO-TELE | D83: 5848305116 | E83: 58 | F83: 46218 | G83: 116 | H83: CHAPADA DA NATIVIDADE | I83: DIANOPOLIS | J83: SUL | K83: LD04002091 | L83: Segue nota para verificar falha e constantes travamento no regulador de tensão 5848305116 - chapada da Natividade .Foi identificado que regulador está com divergência em TAP"S analógico e digital .Foi executado comandos no relé para comutar TAP na fase AB foi executado no relé , porém não alterou analógico e nem fez barulho algum , a princípio a fase C está normal . | V83: Falta definir
A84: 2026 | B84: ETO-TELE 01007/2026 | C84: ETO-TELE | D84: 7961368005 | E84: 79 | F84: 46219 | G84: 5 | H84: ARRAIAS | I84: DIANOPOLIS | J84: SUL | K84: LD01110005 | L84: Favor verifcar Religador 7961368005 , equipamento sem comunicação , feito primeiro ataque com equipe operacional , porem não ouve retorno . | V84: Falta definir
A85: 2026 | B85: ETO-TELE 01026/2026 | C85: ETO-TELE | D85: 7929663074 | E85: 79 | F85: 46226 | G85: 74 | H85: DIANOPOLIS | I85: DIANOPOLIS | J85: SUL | K85: LD05028074 | L85: Segue nota para verificar falha de comunicação no religador 7929663074 rural - Dianópolis .Equipamento perde a comunicação quando falta CA ! | V85: Falta definir
A86: 2026 | B86: ETO-TELE 01029/2026 | C86: ETO-TELE | D86: 7900722193 | E86: 79 | F86: 46227 | G86: 193 | H86: CAMPOS LINDOS | I86: ARAGUAINA | J86: NORTE | K86: PS01112193 | L86: Religador sem comunicação, apos primeiro ataque não retornou a comunicação. | V86: Falta definir
A87: 2026 | B87: ETO-TELE 00999/2026 | C87: ETO-TELE | D87: 7955792076 | E87: 79 | F87: 46215 | G87: 76 | H87: DUERE | I87: GURUPI | J87: SUL | K87: LD02040003 | L87: RELIGADOR DE POSTE 7955792076 SEM COMUNIÇÃO COM COI ,FEITO PRIMEIRO ATAQUE COM EQUIPE OPERACIONAL O MESMO NÃO RETORNOU A COMUNICAÇÃO ENVIAR EQUIPE ESPECIAL VERIFICAR EM CAMPO | V87: Falta definir
A88: 2026 | B88: ETO-TELE 00985/2026 | C88: ETO-TELE | D88: 5839141113 | E88: 58 | F88: 46210 | G88: 113 | H88: COUTO MAGALHAES | I88: GUARAI | J88: NORTE | K88: AL01024113 | L88: Segue nota para averiguar ajuste regulador de tensão N: 5839141113 - RDU - Couto Magalhães , e verificar falha de comunicação .Equipe operacional verificou que vários transformadores urbanos estão com nível de tensão baixa .Foi feito primeiro ataque regulador está comutando normalmente as 3 fases , porém não está no nível adequado !Em campo regulador estava no Tap R1 - 02 , R2 + 01 , R3 +03Medições feitas :Transformador 5700010113 - NA: 205 NB: 206 NC: 210Transformador 5700011113 - NA: 204 NB: 206 NC: 209Transformador 5700333113 -NA: 205 NB: 207 NC: 208OBS: solicitar equipe para realizar medição aterramento , e verificar ajuste junto ao time proteção . verificar falha de comunicação no equipamento . | V88: Falta definir
A89: 2026 | B89: ETO-TELE 00998/2026 | C89: ETO-TELE | D89: 7908683122 | E89: 79 | F89: 46213 | G89: 122 | H89: PALMAS | I89: PALMAS | J89: CENTRO | K89: AL10059122 | L89: rl 7908683122 retirado de operaçao devido falha na base do rele equipamento. | V89: Falta definir
A90: 2026 | B90: ETO-TELE 01027/2026 | C90: ETO-TELE | D90: 7923110021 | E90: 79 | F90: 46226 | G90: 21 | H90: PARANA | I90: PEIXE | J90: SUL | K90: LD03010021 | L90: Segue SS para verificar falha de comunicação no religador 7923110021. Equipe foi no local realizar primeiro ataque e informou que o radio de comunicação encontra-se com defeito | V90: Falta definir
A91: 2026 | B91: ETO-TELE 01018/2026 | C91: ETO-TELE | D91: 7900001096 | E91: 79 | F91: 46223 | G91: 96 | H91: PINDORAMA DO TOCANTINS | I91: PONTE ALTA TOCANTINS | J91: CENTRO | K91: LD03046026 | L91: Segue nota para falha de comunicação no religador 7900001096 - Rural - Pindorama .Equipamento perdeu a comunicação quando faltou CA , porém mesmo ao retorna o CA não retornou a comunicação !Feito primeiro ataque sem sucesso ! | V91: Falta definir
A92: 2026 | B92: ETO-TELE 01020/2026 | C92: ETO-TELE | D92: 7900451096 | E92: 79 | F92: 46223 | G92: 96 | H92: PINDORAMA DO TOCANTINS | I92: PONTE ALTA TOCANTINS | J92: CENTRO | K92: LD03046026 | L92: Segue nota para verificar falha de comunicação no religador 7900451096 - Rural - Pindorama .Equipamento perde a comunicação quando falta CA ! | V92: Falta definir
A93: 2026 | B93: ETO-TELE 01021/2026 | C93: ETO-TELE | D93: 7900259096 | E93: 79 | F93: 46223 | G93: 96 | H93: PINDORAMA DO TOCANTINS | I93: PONTE ALTA TOCANTINS | J93: CENTRO | K93: LD03046026 | L93: Boa noite .Segue nota para verificar falha de comunicação no religador 7900259096 - Pindorama .Equipamento perde a comunicação quando falta CA ! | V93: Falta definir
A94: 2026 | B94: ETO-TELE 01008/2026 | C94: ETO-TELE | D94: 7962734119 | E94: 79 | F94: 46219 | G94: 119 | H94: SAO BENTO DO TOCANTINS | I94: TOCANTINOPOLIS | J94: NORTE | K94: LD03005098 | L94: por favor deslocar equipe da manutenção no RL 7962734119 por que foi feito o primeiro ataque no mesmo mais não voltou comunção no sistema escada | V94: Falta definir

Sheet Premissas por Equipamento
A1: Ativo | B1: Tipo | C1: Localidade | D1: Polo | E1: Regional | F1: SS aberta | G1: Parecer COEP | H1: Observação | I1: Check de concluídas | J1: Defeito identificado | K1: Quantidade | L1: Descrição SS | M1: Premissa 1 | N1: Premissa 2 | O1: Premissa 3 | P1: Premissa 4 | Q1: Premissa 5 | R1: Premissa 6 | S1: Premissa 7 | T1: Premissa 8 | U1: Priorização | V1: Criticidade | W1: Observação após análise
A2: 5800291077 | B2: 58 | C2: GOIATINS | D2: ARAGUAINA | E2: NORTE | F2: CONCLUÍDA | I2: Ok | M2: 40 | N2: 20 | O2: 20 | P2: 20 | Q2: 20 | R2: - | S2: - | T2: - | U2: 120 | V2: Muito Alta | W2: Aumento de reclamações no atendimento de Goiatins e GAs relevantes na região
A3: 5854566043 | B3: 58 | C3: SILVANOPOLIS | D3: PORTO NACIONAL | E3: CENTRO | F3: ETO-RD-PO 00213/2026 | G3: Substituido 24/07/2026 | H3: Laudo da empreteira | I3: Em andamento | J3: Célula | K3: 1 | L3: 22/07/2026 PARECER COEP: EQUIPAMENTO ENTREGUE AOS COCM´SPRAZO DE 7 DIAS CONTANDO O SLA.PARECER COEP: EQUIPAMENTO ENTREGUE AOS COCM´S FAVOR SUSBSTTUIR , E AGUARDO O PRAZO DE PREVISÃO DE SUBSTIUIÇÃOboa noite,segue SS para as devidas tratativas com equipe de manutenção com apoio de equipe de linha viva substituir regulador de tensão 5854566043 queimado célula fase c, LD Porto / Silvanópolis mesmo deverá ser substituído com apoio de equipe de linha viva PARECER DMSL: Foi realizado inspeção visual e ensaios de isolação, relação de transformação e resistência de enrolamento. A fase B está danificada e será necessário substituir a mesma. Malha de aterramento está relativamente boa e conectada. Fase A e C passaram nos ensaios. Substituir fase B. | M3: 40 | N3: 20 | O3: 20 | P3: 10 | Q3: 20 | R3: - | S3: - | T3: - | U3: 110 | V3: Muito Alta | W3: Aumento de reclamações no atendimento de Silvanópolis por Porto Nacional no período seco (Outra fonte com defeito também)
A4: 5800859011 | B4: 58 | C4: TUPIRAMA | D4: GUARAI | E4: NORTE | F4: ETO-RD-GR 00735/2026 | G4: Equipamento entregue ao COCM | H4: Previsão de Substituição 28/07 | I4: Em andamento | J4: Controle | K4: 1 | L4: 16/07/2026 PARECER COEP: ALINHADO COM O JEAN DO DMSL E O KELLITON , KELLITON IRÁ FAZER A INSTALAÇÃO DO CONTROLE RUA E O JEAN IRÁ REALIZAR O COMISSIONAMENTO , FAZENDO A COMPATIBILIZAÇÃO DOS CABOS ASSIM COMO FICARÁ UM CONTROLE RUA NO NOSSO ESTOQUE SOBRESSALENTE PARA ATENDER O DE ARAPOEMA, ATÉ A CHEGADA DOS CABOS QUE O JEAN ME DEU REPORTE DE QUE SERIA ATÉ O DIA 16/08 , FAVOR COCM'S REALIZAREM A INSTALAÇÃO E GUARDAR CONTROLE RUA SOBRESSALENTE PARA ARAPOEMAPEÇA ENVIADA: CONTROLEPARECER DMSL: *FEEDBACK EQUIP. ESPECIAIS**Nº DO EQUIPAMENTO:* 5800859011*TIPO EQUIPAMENTO:* RT ITB *TIPO DE COMUNICAÇÃO:* Não *DATA DA MANUTENÇÃO:* 09/06/2026*SID:* 3195/2026*DESCRIÇÃO:* _ Foi identificado relé da fase C com defeito conforme orientação da supervisão e necessário realiza retrofit para instalação de controle rua.*FICOU EM OPERAÇÃO* Não*PENDÊNCIA:* Realizado Retrofit *DADOS DIVERGENTES DA PROGRAMAÇÃO:* Não*BATERIA SUBSTITUÍDA?:* Não*TIPO DE BATERIA:**EQUIPE:* Edeglan e Brunno.Observação: trocar por um controle RUA.------------------------------------------------------------------------------------------Enviar equipe do DMSL, para fazer correção no RT 5800859011, o mesmo está com o displey da fase C apagado , dificutando realizar manobras no mesmo, emvirtude disso o mesmo ficou BAY PASSADO EM CAMPO | M4: 40 | N4: 20 | O4: 20 | P4: 10 | Q4: 20 | R4: - | S4: - | T4: - | U4: 110 | V4: Muito Alta | W4: Atendimento de parte da RDU Guaraí por fonte alternativa
A5: 5836764032 | B5: 58 | C5: ARAGUACU | D5: ALVORADA | E5: SUL | F5: CONCLUÍDA | I5: Ok | M5: 40 | N5: 20 | O5: 20 | P5: 10 | Q5: 20 | R5: - | S5: - | T5: - | U5: 110 | V5: Muito Alta | W5: Aumento de reclamações no atendimento de Araguaçu no período seco
A6: 7923673004 | B6: 79 | C6: ARAGUAINA | D6: ARAGUAINA | E6: NORTE | F6: ETO-COEP 00124/2026 | G6: Em processo de aquisição | H6: Estava aguardando retorno DMSL | J6: Completo | K6: 1 | L6: PARECER COEP: Verificar Disponibilidade de equipamento no Scada e enviar modelo e tensão para a compra.RELIGADOR COM RELÉ DANIFICADO, REALIZAR SUBSTITUIÇÃO | M6: 15 | N6: 20 | O6: 15 | P6: 15 | Q6: 15 | R6: 10 | S6: 0 | T6: 15 | U6: 105 | V6: Muito Alta | W6: Transferência de cargas na RDU de Araguaína (2797 UCs)
A7: 7931608059 | B7: 79 | C7: TAQUARALTO | D7: TAQUARALTO | E7: CENTRO | F7: ETO-COEP 00040/2026 | G7: Em processo de aquisição | J7: Tanque e rádio | K7: 1 | L7: PARECER COEP: EQUIPAMENTO SELECIONADO PARA COMPRADMSL:Serviço Executado: Foi feita uma análise técnica no equipamento, devido à falta de comunicação. Também foi identificado que o tanque do equipamento está danificado, sendo assim, necessário substituir o tanque e o rádio do equipamento, que está queimado, sendo necessário substituir também. | M7: 15 | N7: 20 | O7: 15 | P7: 15 | Q7: 15 | R7: 10 | S7: 0 | T7: 15 | U7: 105 | V7: Muito Alta | W7: Transferência dos bairros Morada do Sol, Vale do Sol, Morada do Sol II, Nova Esperança, Sõa João, Araras I e II e Jardim Laila em Taquaralto (6033 UCs)
A8: 7931610122 | B8: 79 | C8: PALMAS | D8: PALMAS | E8: CENTRO | F8: ETO-TELE 01025/2026 | G8: Concluído DCMD | H8: Previsão de substituição 16/07 | I8: Em andamento | J8: Tanque e antena | K8: 1 | L8: PARECER DA PROTEÇÃO:FAVOR COMISSIONAR RELIGADOR. AJUSTES PERMANECEM OS MESMOS E DISPONÍVEIS NO APP DA PROTEÇÃO.Estagiário Rafael P Marques.******************30/06 PARECER COEP: EQUIPAMENTO ENTREGUE, SEGUE SS PARA O COCM´S , PARA REALIZAR O ATENDIMENTO,FAVOR ADICIONAR O PARECER PARA MANDAR PARA PROTEÇÃOBom dia,Segue SS para verificação RL sem comunicação com painel apagado equipe DEOP fez primeiro ataque sem sucesso RL 7931610122 RDU de Palmas.Feedback Equipamentos Especiais DMSL: *RLG 7931610122 RDU Palmas*Noja rc10 Data: 14/10/2025SID: 5412Dados de comunicação divergentes da programação: Não. Serviço Executado: Houve um curto no equipamento danificando a parte ativa, e antena! Será necessário fazer a substituição somente da parte ativa (tanque) e da antena.Equipamento ficou em operação?: Não Pendência: Sim, substituir a parte ativa.Bateria(s) substituída(s)?: NãoData Fabricação/Instalação da(s) bateria(s): 2024Equipe: Benvindo, Juliano e Sérgio.***** Parecer do COCM CENTRO*****Equipamento Substituido em campo pela Ordem de ServiÇO DLP-MPPA01 243/2026, ONDE OS RELATORIO ESTÃO ANEXADO.--------------------------------------------------------Parecer DMSL:Equipamento substituído porém não informado se antena também foi substituída. Levar antena para caso da mesmo não ter sido substituída. | M8: 15 | N8: 20 | O8: 15 | P8: 15 | Q8: 15 | R8: 10 | S8: 0 | T8: 15 | U8: 105 | V8: Muito Alta | W8: Transferência entre 284R SE Palmas IV e 2294R SE Palmas II
A9: 7900648055 | B9: 79 | C9: ARAGUACEMA | D9: DIVINOPOLIS | E9: CENTRO | F9: CONCLUÍDA | M9: 15 | N9: 20 | O9: 15 | P9: 15 | Q9: 15 | R9: 10 | S9: 0 | T9: 15 | U9: 105 | V9: Muito Alta | W9: Transferência da RDU de Araguacema (1506 UCs)
A10: 7947203070 | B10: 79 | C10: RIO SONO | D10: TAQUARALTO | E10: CENTRO | F10: ETO-COEP 00131/2026 | G10: Em processo de aquisição | H10: Estava aguardando retorno DMSL | J10: Controle | K10: 1 | L10: 13/07 PARECER COEP: SELECIONADO PARA COMPRA CONTROLE favor verificar RL 7947203070, sem comunicaçao, feito 1° ataque pela equipe 070OP01 e nao retornou a comunicaçao , linformaçao no Scada de bateria.PARECER DMSL: Foi feito análise técnica, a placa do equipamento está queimada nessesario subistituir o equipamento completo -Carliel e Benvindo-05/02 | M10: 10 | N10: 20 | O10: 15 | P10: 15 | Q10: 15 | R10: 10 | S10: 0 | T10: 15 | U10: 100 | V10: Muito Alta | W10: Transferência da RDU de Lizarda (1650 UCs) para fonte alternativa
A11: 5856070091 | B11: 58 | C11: ALMAS | D11: DIANOPOLIS | E11: SUL | F11: ETO-RD-DP 00479/2026 | G11: Equipamento entregue ao COCM | H11: Previsão de instalação 30/07/2026 | I11: Em andamento | J11: Células + controle | K11: 3 | L11: PARECER DMSL: não foi regularizado a instalação do equipamento, nota repassada conforme alinhado com o supervisor.____________________________________________COCMS 26.03.26. SS REPASSADA PARA COEP PROVIDENCIAR MATERIAL. NÃO TEMOS AS PÇ EM ESTOQUE PARA FAZER A SUBSTITUIÇÃO. Solicitação de serviço para reposição de equipamentos furtados .COEP: Equipamento fornecido ao COCM-S para regularização.COCMS: Equipamento substituido conforme solicitado. Gentileza comissionar.PARECER DA PROTEÇÃO:SEGUE NOTA REPASSADA PARA DMSL COMISSIONAR.ENG° IRLLEY CASTELO BRANCOPARECER DMSL(23/09/2025): Feito a parte de comunicação, fechando enlace, configuração do rádio GE. Feito a medição de aterramento. Após uma inspeção, foi identificado que o regulador de tensão está instalado errado, carga está para o lado de fonte e fonte está do lado de carga. O certo é a fonte vim de almas, atualmente está vindo de natividade. Favor fazer a instalação correta. | M11: 40 | N11: 20 | O11: 20 | P11: 20 | Q11: 0 | R11: - | S11: - | T11: - | U11: 100 | V11: Muito Alta | W11: Atendimento da região da Engegold, Nativa, cidade Natividade e Chapada da Natividade
A12: 7903569004 | B12: 79 | C12: ARAGUAINA | D12: ARAGUAINA | E12: NORTE | F12: CONCLUÍDA | M12: 15 | N12: 20 | O12: 5 | P12: 15 | Q12: 15 | R12: 10 | S12: 0 | T12: 15 | U12: 95 | V12: Muito Alta | W12: Transferência dos bairros JD Santa Helena, Jd Filadelfiae Setor Caraja em Araguaína (2053 UCs), AL 254R de AR I e AL 214R de AR III
A13: 7925744087 | B13: 79 | C13: GOIANORTE | D13: GUARAI | E13: NORTE | F13: ETO-COEP 00059/2026 | G13: Em processo de aquisição | H13: Mandar reformar | J13: Tanque e cabo umbilical | K13: 1 | L13: PARECER COEP: EQUIPAMENTO SELECIONADO PARA COMPRAPARECER DMSL: FEEDBACK EQUIP. ESPECIAISNº DO EQUIPAMENTO: 7925744087TIPO EQUIPAMENTO: Noja RC 10TIPO DE COMUNICAÇÃO: Radio GE IPDATA DA MANUTENÇÃO: 19/02/2026SID: 735/2026 DESCRIÇÃO: foi identificado água dentro da parte interna do tanque e cabo umbilical encharcado de água foi passado essas informações para COS.FICOU EM OPERAÇÃO?: Não PENDÊNCIA: Sim substituir tanque e cabo umbilicalDADOS DIVERGENTES DA PROGRAMAÇÃO: NãoBATERIA SUBSTITUÍDA?: Não DATA DA BATERIA: 07/05/2025TIPO DE BATERIA: Lítio EQUIPE: Edeglan e Janio-------------------------------------------------------------------------------------------------RELIGADOR SEM COMUNICAÇÃO, APOS PRIMEIRO ATAQUE RETORNA E FICAR INDEFINIDO. | M13: 15 | N13: 20 | O13: 5 | P13: 15 | Q13: 15 | R13: 10 | S13: 0 | T13: 15 | U13: 95 | V13: Muito Alta | W13: Transferência de Goianorte, fonte principal operando
A14: 7900117013 | B14: 79 | C14: PARAISO DO TOCANTINS | D14: PARAISO DO TOCANTINS | E14: CENTRO | F14: ETO-PROT 00154/2026 | G14: Concluído DCMD | H14: Previsão de entrega 15/07 | I14: Em andamento | J14: Controle | K14: 1 | L14: 15/07 PARECER COCM: EQUIPAMENTO FOI SUBSTITUÍDO OBRA 021260042210/07 PARECER COEP: EQUIPAMENTO ENTREGUE AOS COCM´S FAVOR INFORMAR PRAZO DE SUBSTUIÇÃO PARA O DMSL E REPASSAR DEPOIS PARA PROTEÇÃO REALIZAR OS AJUSTES E DESCREVER NA SS O SERVIÇO REALIZADOPARECER COEP: PREVISÃO DE ENTREGA AOS COCM'S 01/07Segue nota para correção de anomalia e provável substituição de religador , religador 7900117013 -RDU - Paraiso .OBS: equipe DMSL Elisfran estava atualizando firmware no equipamento , porém relé parou de funcionar devido essa atualização , sendo necessário sua substituição .em campo o modelo e cooper Form6 , segundo tecnico deve ser substituído por um Noja .Repassado para o COEP para aquisição do equipamento e posterior repasse para o COCM. | M14: 15 | N14: 20 | O14: 15 | P14: 15 | Q14: 15 | R14: 0 | S14: 0 | T14: 15 | U14: 95 | V14: Muito Alta | W14: Transferência do 214R de Paraíso I, Centro Comercial de Paraíso
A15: 7929376022 | B15: 79 | C15: BABACULANDIA | D15: ARAGUAINA | E15: NORTE | F15: ETO-COEP 00120/2026 | G15: Em processo logístico | H15: Previsão de entrega 16/07 | I15: Em andamento | J15: Tanque + controle | K15: 1 | L15: PARECER COEP: PROBLEMA NO ENVIO COCM'S CONTROLE ENVIADO FOI O NOJA , DEVIDO A FALTA DO MODELO NA SS (GRAVE)PARECER DMSL: *FEEDBACK EQUIP. ESPECIAIS**Nº DO EQUIPAMENTO:* 7929376022 *DATA DA MANUTENÇÃO:* 02/04/2026*SID:* 1677/2026*DESCRIÇÃO:* Trocar controle completo*PENDÊNCIA:* Sim.*DADOS DIVERGENTES DA PROGRAMAÇÃO:* Não*BATERIA SUBSTITUÍDA?:* Não*EQUIPE:* Adeilton e Edicleber __________________________________________________________POR GENTILEZA ATENDER SOLICITAÇÃO PRIMEIRO ATAQUE IDENTIFICOU QUE RELE ESTA EM CURTO NOTA ABERTA 224/2026 FOI BAIXADA POREM NÃO FOI CORRIGIDO PROBLEMA EM CAMPO. | M15: 15 | N15: 20 | O15: 5 | P15: 15 | Q15: 15 | R15: 10 | S15: 0 | T15: 15 | U15: 95 | V15: Muito Alta | W15: Transferência de Babaçulândia, fonte principal operando
A16: 7908705049 | B16: 79 | C16: AURORA DO TOCANTINS | D16: DIANOPOLIS | E16: SUL | F16: ETO-RD-DP 00409/2026 | G16: Equipamento entregue ao COCM | H16: Previsão de substituição 20/07 | I16: Em andamento | J16: Tanque + controle | K16: 1 | L16: EQUIPAMENTO ENTREGUE, SOLICITO PREVISÃO PARA SUBSTITUIÇÃO:PARECER COEP: PREVISÃO DE ENTREGA AOS COCM'S 01/07Manutenção no RL 7908705049PARECER DMSL(28/08/2025): Equipe foi fazer manutenção no RL e constatou que o tanque e o relé do mesmo se encontra queimado, providenciar substituição.PARECER COCMS 30/04/2026CRIADO OBRA 0512600135 PARA REQUISIÇÃO MATERIAL | M16: 15 | N16: 20 | O16: 5 | P16: 15 | Q16: 15 | R16: 0 | S16: 10 | T16: 15 | U16: 95 | V16: Muito Alta | W16: Proteção da baixa do TF de força da SE Aurora
A17: 7933726256 | B17: 79 | C17: MATEIROS | D17: PONTE ALTA TOCANTINS | E17: CENTRO | F17: ETO-PROT 00145/2026 | G17: Em fase de ajustes | H17: Destinada parte ativa do RL 7900453110 | I17: Em andamento | J17: Tanque | K17: 1 | L17: 07/07 Equipamento foi substituido na OS: ETO-RD-PO 1859/2026 OBRA 031260035101/07 PARECER COEP: REDIRECIONADO PARA O POSTO DO COCM´S EQUIPAMENTO CHEGOU NO LOCAL, FAVOR ENTRAR EM CONTATO COM O DMSL, DEVIDO A URGÊNCIA DO EQUIPAMENTO EM OPERAÇÃO.30/06 PARECER COEP: DEVIDO A ALINHAMENTO COM COI UTILIZAREMOS PARTE ATIVA QUE ORIGINALMENTE FOI ENCOMENDADA PARA 7933726256PARECER DMSL: N° do Equipamento: _RLG 7933726256 MateirosTipo de Equipamento: _RLG NOJA RC 10 REL IIData: _06/05/2026SID: _2288/2026-Serviço Executado: _Equipamento com defeito na parte ativa, será necessário fazer a substituição da parte ativa e fazer melhoria na malha de terra!Equipamento ficou em operação?: _NaoPendência: _SimBateria(s) substituída(s)? NÃOData Fabricação/Instalação da(s) bateria(s):_06/2025Equipe: _Benvindo e Almir-------------------------------------------------------------------------------Religador 7933726256, sem comunicação apos primeiroa ataque não retornou as comunicação. | M17: 15 | N17: 10 | O17: 15 | P17: 15 | Q17: 15 | R17: 10 | S17: 0 | T17: 15 | U17: 95 | V17: Muito Alta | W17: Transferência da cidade de Mateiros (733 UCs) para o gerador
A18: 7933766059 | B18: 79 | C18: TAQUARALTO | D18: TAQUARALTO | E18: CENTRO | F18: ETO-TELE 01024/2026 | G18: Equipamento entregue ao COCM | H18: Previsão de substituição 16/07 | I18: Em andamento | J18: Tanque | K18: 1 | L18: PARECER DA PROTEÇÃO:RECOMISSIONAR RELIGADOR, AJUSTES DE PROTEÇÃO PERMANECEM OS MESMOS.Estagiário Rafael P Marques****************************PARECER COEP: EQUIPAMENTO ENTREGUE, SEGUE SS PARA O COCM´S , PARA REALIZAR O ATENDIMENTO,FAVOR ADICIONAR O PARECER PARA MANDAR PARA PROTEÇÃOSegue SS para verficar religador de poste 7933766059.Religador esta com defeito na parte ativa no tanque Porte gentilezaenviar equipe verificar.Endereço: TaquariPARECER DMSL: RLG 7933766059 RELÉ NOJA RC 10Mestre 2 Rep. taquaruçu GESID: 5457/2025Data: 15/10/2025Serviço Executado: Houve um curto na parte ativa do equipamento danificando a mesma, será necessário fazer a substituição somente do tanque, parte ativa.*Equipamento ficou em operação?:*Nao Pendência: Sim, substituir parte ativa.Equipe: Benvindo, Juliano e Sérgio.****** Parecer do COCM Centro***Equipámento Substituido em Campo pela Ordem de ServIÇO DLP-MPPA01 244/2026, ONDE OS RELATORIO ESTÃO ANEXADO.. | M18: 15 | N18: 20 | O18: 5 | P18: 15 | Q18: 15 | R18: 0 | S18: 10 | T18: 15 | U18: 95 | V18: Muito Alta | W18: Seccionamento de trecho do Setor Taquari
A19: 7900594026 | B19: 79 | C19: PONTE ALTA TOCANTINS | D19: PONTE ALTA TOCANTINS | E19: CENTRO | F19: ETO-PROT 000148/2026 | G19: Equipamento entregue ao COCM | H19: Previsão de substituição 10/07 | I19: Em andamento | J19: Tanque + controle | K19: 1 | L19: PARECER DA PROTEÇÃO:16/07/2026 AJUSTES DISPONIBILIZADOS NO APP DA PROTEÇÃO15/07/2026 EQUIPAMENTO SUBSTITUIDO NA OS ETO-RD-PO 1860 OBRA 031260035414/07/2026 PARECER COCM/ COEP: DE ACORDO COM O EDSON CURCINO FOI FEITA S SUBSTITUIÇÃO DO EQUIPAMENTO , SEGUE PARA PROTEÇÃO ELABORAR AJUSTE10/07 PARECER COEP: EQUIPAMENTO DESLOCADO QUE ESTAVA EM GUARAÍ FOI ALINHADO COM O VALMOR QUE SERIA SUBSTITUIDO DIA 07/07/2026 , FAVOR PASSAR PARA PROTEÇÃO 7900594026PARECER COEP: AGUARDANDO COCM'S PARA ABRIR REQUISIÇÃOPARECER DMSL 10/06/2026: Tem uma nota aberta para esse equipamento solicitando a substituição desde 20/10/2025, como a nota não foi atendida estamos repassando para área responsável. Nota em aberto repassada ETO-COEP 210/2025.Segue nota para verificar intermitência de comunicação nos religadores 7908301026 , 7911120026, 7947959026 , 7908692026, 7900594026 rural- Ponte Alta . | M19: 15 | N19: 20 | O19: 15 | P19: 15 | Q19: 15 | R19: 0 | S19: 0 | T19: 15 | U19: 95 | V19: Muito Alta | W19: Religador responsável pela proteção da barra da SE Ponte Alta (2381 UCs)
A20: 7921040031 | B20: 79 | C20: RIO DOS BOIS | D20: MIRACEMA DO TOCANTINS | E20: CENTRO | F20: CONCLUÍDA | I20: Ok | M20: 15 | N20: 20 | O20: 5 | P20: 15 | Q20: 15 | R20: 10 | S20: 0 | T20: 15 | U20: 95 | V20: Muito Alta | W20: Fonte principal de Rio dos Bois, RL de transferência operando
A21: 7957620015 | B21: 79 | C21: PEDRO AFONSO | D21: GUARAI | E21: NORTE | F21: CONCLUÍDA | I21: Ok | M21: 15 | N21: 20 | O21: 15 | P21: 15 | Q21: 15 | R21: 0 | S21: 0 | T21: 15 | U21: 95 | V21: Muito Alta | W21: Atendimento da RDU de Bom Jesus e parcial da RDU de Pedro Afonso
A22: 7927413001 | B22: 79 | C22: PORTO NACIONAL | D22: PORTO NACIONAL | E22: CENTRO | F22: ETO-COEP 00141/2026 | G22: Em processo de aquisição | H22: Estava aguardando retorno DMSL | J22: Tanque + controle | K22: 1 | L22: PARECER DMSL: *Segue feedback**Equipamento:* RLG 7927413001 *RELÉ TAVRIDA*Data:* 16/04/2026*SID:* 1817/2026*Serviço executado:* Placa de alimentação do equipamento com defeito, VERIFICAR SE É POSSIVEL substituir o equipamento completo.*Equipamento ficou em operação?*_Não*Pendência:*_Sim*Bateria(s) substituída(s)?*_Nao *Equipe:* Benvindo e Kaique-------------------------------------------------------------------------------------------------Religador 7927413001 sem comunicação foi realizado primeiro ataque porem a comunicação não retornou. Favor enviar equipe para devidas trattivas | M22: 15 | N22: 5 | O22: 15 | P22: 15 | Q22: 15 | R22: 10 | S22: 0 | T22: 15 | U22: 90 | V22: Muito Alta | W22: Transferência do Distrito Ind de Porto Nacional e GAs
A23: 7908686014 | B23: 79 | C23: PIUM | D23: PARAISO DO TOCANTINS | E23: CENTRO | F23: ETO-RD-PS 00302/2026 | G23: Equipamento entregue ao COCM | H23: 46226 | I23: Em andamento | J23: Tanque | K23: 1 | L23: 10/07 PARECER COEP: EQUIPAMENTO ENTREGUE AOS COCM´S FAVOR INFORMAR PRAZO DE SUBSTUIÇÃO PARA O DMSL E REPASSAR DEPOIS PARA PROTEÇÃO REALIZAR OS AJUSTES E DESCREVER NA SS O SERVIÇO REALIZADO06/07 PARECER COEP: PREVISÃO DE ENTREGA DE ACORDO COM CALENDÁRIO LOGISITCO NOVO 06/07NOTA DMSL: Favor substituir o tanque, ele não está efetuando os comandos enviados. Não substituir o controle pois o mesmo funciona como repetidor de outros equipamentos.Segue nota para verificar falha de fechamento religador 7908686014- Pium .OBS: equipamento não fechou local e remoto , fica sinalizando no painel para verificar alarmes ! | M23: 15 | N23: 20 | O23: 0 | P23: 15 | Q23: 15 | R23: 10 | S23: 0 | T23: 15 | U23: 90 | V23: Muito Alta | W23: Fonte principal de Pium, RL de transferência operando
A24: 5800440256 | B24: 58 | C24: MATEIROS | D24: PONTE ALTA TOCANTINS | E24: CENTRO | F24: CONCLUÍDA | M24: 20 | N24: 20 | O24: 20 | P24: 10 | Q24: 20 | R24: - | S24: - | T24: - | U24: 90 | V24: Muito Alta | W24: Aumento de reclamações no atendimento de São Felix e Mateiros no período seco
A25: 7943790134 | B25: 79 | C25: ESPERANTINA | D25: AUGUSTINOPOLIS | E25: NORTE | F25: ETO-TELE 00896/2026 | G25: Aguardando comissionamento | I25: Em andamento | J25: Tanque | K25: 1 | L25: PARECER DCMD:Serviço realizado , substituição da parte ativa do RELIGADOR 7943790134 - Favor realizar comissionamento | M25: 15 | N25: 10 | O25: 5 | P25: 15 | Q25: 15 | R25: 10 | S25: 0 | T25: 15 | U25: 85 | V25: Muito Alta | W25: Transferência de Esperantina, fonte principal operando
A26: 7900453110 | B26: 79 | C26: SANTA RITA DO TOCANTINS | D26: PORTO NACIONAL | E26: CENTRO | F26: ETO-COEP 00087/2026 | G26: Em processo de aquisição | H26: Previsão de chegada 20/10/2026 | J26: Tanque | K26: 1 | L26: 10/07/2026 EQUIPAMENTO SELECIONADO PARA COMPRA PARTE ATIVA30/06.PARECER COEP: ALINHADO COM O ALLAN REMANEJAMOS PARTE ATIVA PARA ATENDER 7933726256PARECER COEP: Aproveitar controle cooper se possível em outro local, previsão de chegada do material dia 01/07 para substituiçãoFavor verificar o RL 7900453110, pois o mesmo aceita comando de fechamento, porém fecha em campo e no SCADA continua aberto e só abre através de equipe em campo. Parecer Dmsl:Equipamento está com defeito na parte ativa, não aceita o comando de fechamento. Será necessário substituir o equipamento completo.Equipamento ficou em operação?: _SIM_a pedido do COS ficou em operação, a operação está ciente da necessidade de substituir.Pendência: Sim, será necessário substituir o equipamento. | M26: 15 | N26: 10 | O26: 5 | P26: 15 | Q26: 15 | R26: 10 | S26: 0 | T26: 15 | U26: 85 | V26: Muito Alta | W26: Transferência de Santa Rita, fonte principal operando
A27: 7925871077 | B27: 79 | C27: GOIATINS | D27: ARAGUAINA | E27: NORTE | F27: ETO-COEP 00048/2026 | G27: Aguardando atualização de informação DMSL | J27: Tanque | K27: 1 | L27: 30/06 PARECER COEP: AGUARDANDO RETORNO DO DMSLPARECER DMSL: A PEDIDO DA PCM DO NORTE LARA SOARES REALIZEI A CRIAÇÃO DESSA SS, EM RAZAO DA ANTIGAETO-TELE 337/2026 QUE FOI BAIXADA POR ENGANO DE TAL FORMA SEGUE A MESMA PARA REALIZAR AS TRATATIVAS. PENDENCIA: Religador continua by passado, equipamento está com defeito na parte ativa | M27: 15 | N27: 10 | O27: 15 | P27: 15 | Q27: 15 | R27: 10 | S27: 0 | T27: 0 | U27: 80 | V27: Muito Alta | W27: Transferência de Goiatins e GAs (2492 UCs)
A28: 5803327001 | B28: 58 | C28: PORTO NACIONAL | D28: PORTO NACIONAL | E28: CENTRO | F28: ETO-COEP 00149/2026 | G28: Aguardando confirmação em campo sobre o equipamento | H28: Foi realizado os serviços apontados pelo DMSL? | J28: Controle e aterramento | K28: 1 | L28: 01/07 PARECER COEP: FOI CONFIRMADO COM A OPERAÇÃO QUE O EQUIPAMENTO SEGUIU O FLUXO INTEIRO DE COMISSIONAMENTO, PROTEÇÃO, FAVOR EXPLICAR O QUE FOI REALIZADO E SE EQUIPAMENTO ESTÁ OPERANDO, SENÃO ESTIVER EXPLICAR O QUE FOI FEITO NELE30/06PARECER COEP: REPASSAR DIRETAMENTE PARA OS COCM'SRegulador 5803327001 fora de operação, by passado em campo com painel de comunicação com cabos desconectados tensão 13.8.parecer DMSL: Feedback Equip. EspeciaisRT 5803327001RELÉ RUASid: 4844Data: 19/09/2025Serviço realizado:*Equipamento foi remanejado, 7 km da sua localização sentido Palmas necessário comissionamento completo*Equipamento com um dos cabos umbilicais danificado.* aterramento bucha FC não esta interligada corretamente * para-raios estão no mesmo aterrament2o da bucha FC.* Tranques muito alto e próximo da rede não permitindo o comissionamento com segurança.* Controle alto demais tem que baixar Equipamento ficou em operação?: nãoPendência: sim, precisa comissionar completoOBS | M28: 40 | N28: 0 | O28: 0 | P28: 20 | Q28: 20 | R28: - | S28: - | T28: - | U28: 80 | V28: Alta | W28: Em caso de perca da fonte principal é necessário esse RT para alimentação da Frísia
A29: 7900230155 | B29: 79 | C29: PALMEIRANTE | D29: COLINAS DO TOCANTINS | E29: NORTE | F29: ETO-PROT 00143/2026 | G29: Em fase de ajustes | I29: Em andamento | J29: Tanque e PR do trafo e chave | K29: 1 | L29: 07/07/2026 PARECER COEP: MATERIAL ENVIADO , CONFORME ALINHANDO COM O WANDER REALIZAR SUBSTIUIÇÂO DO EQUIPAMENTO, FAVOR ESCREVER PARECER COCM ANTES DE PASSAR PARA PROTEÇÂO, DO QUE FOI REALIZADO01/07/2026 PARECER COEP: PROBLEMA NO ENVIO DO MATERIAL PARECER DMSL: Religador está com o tanque danificado. Não responde a comandos abertura e fechamento local ou remoto, pois está com sinal de curto circuito. Necessário trocar o equipamento. Para raio do trafo está queimado. Chave de saída da fase C está com o olhal quebrado, necessário substituir a chave. Equipamento ficou bypassado em campo. Aberto entrada e saída, com exceção da fase C de saída que ficou fechada. Favor, substituir equipamento completo por NOJA RC10 e sanar demais pendencias.Senhores Favor verificar RL 7900230155 o mesmo sinalizou aberto no SCADA porem a cidade de Palmeirante estava normal , feito um reset no rl e o mesmo subiu fechado.08/07/2026 PARECER DCMD: EQUIPE ETO-LVGR01 DE GUARAI ESTEVE NO RL 7900230155 DIA 25-06-2026 E FEZ TODAS A PENDENCIAS DO RL, OBS: EQUIPE SO NAO CONECTOU O CABO DO TRAFO NO RL. RL ESTA PRONTO PARA O COMISSIONAMENTO | M29: 15 | N29: 20 | O29: 5 | P29: 15 | Q29: 0 | R29: 10 | S29: 0 | T29: 15 | U29: 80 | V29: Muito Alta | W29: Fonte principal de Palmeirante, RL de transferência operando
A30: 7900543083 | B30: 79 | C30: APARECIDA DO RIO NEGRO | D30: TAQUARALTO | E30: CENTRO | F30: CONCLUÍDA | I30: Ok | M30: 15 | N30: 20 | O30: 5 | P30: 15 | Q30: 0 | R30: 0 | S30: 10 | T30: 15 | U30: 80 | V30: Muito Alta | W30: Atendimento da RDU de Aparecida do Rio Negro
A31: 7900930040 | B31: 79 | C31: ARAGOMINAS | D31: ARAGUAINA | E31: NORTE | F31: CONCLUÍDA | I31: Ok | M31: 15 | N31: 20 | O31: 5 | P31: 15 | Q31: 0 | R31: 0 | S31: 10 | T31: 15 | U31: 80 | V31: Muito Alta | W31: Proteção da baixa do TF de força da SE Aragominas
A32: 7931383086 | B32: 79 | C32: MARIANOPOLIS | D32: DIVINOPOLIS | E32: CENTRO | F32: CONCLUÍDA | I32: Ok | M32: 15 | N32: 20 | O32: 5 | P32: 15 | Q32: 0 | R32: 10 | S32: 0 | T32: 15 | U32: 80 | V32: Muito Alta | W32: Fonte principal de Marianópolis, RL transferência operando
A33: 7908302256 | B33: 79 | C33: MATEIROS | D33: PONTE ALTA TOCANTINS | E33: CENTRO | F33: ETO-TELE 00997/2026 | G33: Primeiro ataque DMSL | L33: RL teve nota baixada (ETO-TELE 970/2026) pore´m eqp continua fora de operação, solicito programação para equipe verificar em campo | M33: 5 | N33: 10 | O33: 5 | P33: 15 | Q33: 15 | R33: 10 | S33: 0 | T33: 15 | U33: 75 | V33: Alta | W33: Isolação de trecho e transferência das cidades de São Felix e Mateiros para gerador, além de atendimento de clientes rurais
A34: 5800371025 | B34: 58 | C34: ARAPOEMA | D34: COLINAS DO TOCANTINS | E34: NORTE | F34: ETO-RD-GR 00766/2026 | G34: Equipamento entregue ao COCM | H34: Aguardando previsão de substituição | I34: Em andamento | J34: Controle | K34: 1 | L34: 16/07/2026 PARECER COEP: ALINHADO COM O KELLITON REALIZAR SUBSTITUIÇÃO DO CONTROLE DE TUPIRAMA, ALINHADO COM O JEAN QUE OS CABOS COMPATIBILIZADORES VÃO CHEGAR 16/08 , ATÉ ESSA DATA MANTER ESSA SS E CONTROLE RUA, DEPOIS REPASSAR PARA O DMSLPARECER COEP: AVALIAR COM O LEANDRO, PROVAVELMENTE SÓ COMPRAPARECER DMSL: Após testes foi constatado defeito nos relés da fase A e B, Modelo Toshiba TBR 1000. Se possível, substituir os relés das 3 fases por controle RUA, disponibilizar os cabos de ligação entre o tanque e o controle para possibilitar a compatibilização do equipamento. Fornecer kit de comunicação, rádio, antena, etc.Segue nota para veriifcar falha em regulador de tensão N: 5800371025 dentro S/E Arapoema , equipamento esta com 2 reles com falha marca toshiba . | M34: 0 | N34: 20 | O34: 20 | P34: 10 | Q34: 20 | R34: - | S34: - | T34: - | U34: 70 | V34: Alta | W34: Aumento de reclamações no atendimento de Arapoema no período seco
A35: 7926089013 | B35: 79 | C35: PARAISO DO TOCANTINS | D35: PARAISO DO TOCANTINS | E35: CENTRO | F35: ETO-COEP 00078/2026 | G35: Em processo de aquisição | J35: Tanque | K35: 1 | L35: PARECER COEP: EQUIPAMENTO SELECIONADO PARA COMPRAPARECER DMSL: Feedback Equip. EspeciaisRLG 7926089013,RELÉ NOJA RC10SID 1805/2026DATA 15/04/2026Serviço Executado: Favor realizar a troca da parte ativa do equipamento --reprogramar para atualizar a base juntamente com escada Equipamento ficou em operação: Não Pendência: sim atualizar a base e subistituir o tanque Bateria(s) substituída(s)? Não Data de Fabricação/Instalação da(s) bateria(s): Equipe: Carliel e João Vitor Fernando e Elson---------------------------------------------------------------------------------ATUALIZAR AJUSTES DO RL 7926089013 LD PARAISO I A PIUM. IMPLEMENTAÇÃO DA FUNÇÃO 27, SUBTENSÃO.AJUSTES DISPONIVEIS NO APP DA PROTEÇÃO. | M35: 15 | N35: 10 | O35: 5 | P35: 15 | Q35: 15 | R35: 10 | S35: 0 | T35: 0 | U35: 70 | V35: Alta | W35: Transferência da RDU de Chapada de Areia (937 UCs) para fonte alternativa
A36: 7925087021 | B36: 79 | C36: PARANA | D36: PEIXE | E36: SUL | F36: ETO-PROT 00152/2026 | G36: Equipamento entregue ao COCM | H36: 46233 | I36: Em andamento | J36: Tanque | K36: 1 | L36: 10/07 PARECER COEP: EQUIPAMENTO ENTREGUE AOS COCM´S FAVOR INFORMAR PRAZO DE SUBSTUIÇÃO PARA O DMSL E REPASSAR DEPOIS PARA PROTEÇÃO REALIZAR OS AJUSTES E DESCREVER NA SS O SERVIÇO REALIZADOPARECER COEP: EM ROTA DE ENTREGA, VERIFICAR PREVISÃO DE CHEGADARealizar a substituição do tanque do equipamento. | M36: 15 | N36: 10 | O36: 5 | P36: 0 | Q36: 15 | R36: 10 | S36: 0 | T36: 15 | U36: 70 | V36: Alta | W36: Primeiro RL do 414R de Paranã, RL a jusante na LD também está bay-passado (630 UCs)
A37: 5801866013 | B37: 58 | C37: PARAISO DO TOCANTINS | D37: PARAISO DO TOCANTINS | E37: CENTRO | F37: ETO-PROT 00151/2026 | G37: Em fase de ajustes | I37: Em andamento | J37: Célula | K37: 1 | L37: 15/07 PARECER COCM, FOI ATENDIDA PELA OS ETO-RD-PS 1616/2026 OBRA-021260053910/07 PARECER COEP: EQUIPAMENTO ENTREGUE AOS COCM´S FAVOR INFORMAR PRAZO DE SUBSTUIÇÃO PARA O DMSL E REPASSAR DEPOIS PARA PROTEÇÃO REALIZAR OS AJUSTES E DESCREVER NA SS O SERVIÇO REALIZADOPARECER COEP: EM PROCESSO DE ENTREGAPARECER DMSL: RT 5801866013Serviço Executado: Feito a medição da malha de terra. Identificado infiltração na caixa de passagem da célula da fase C do banco regulador de tensão, será necessário fazer a substituição da mesma! Ficar atento na hora da substituição, deverá ser substituída a célula do lado da BR.Obs.: Será necessário baixar todo o banco pelo menos um metro, as buchas estão muito próximas a parte energizada não oferecem segurança para equipe no momento do ensaio elétrico.Equipamento ficou em operação?: Não Possui nobreak: SimPossui antena: SimPossui rádio:SimPendência: SimData da bateria: Equipe: Benvindo e Kaique._______________________________________________RT 5801866013BY PASSADO DEVIDO DEFEITO EM CELULA BEMVINDO ESTEVE NO LOCAL JUNTO AO COD .NECESSARIO TRATATIVA PARA MESMA .FASE DANIFICADO C | M37: 0 | N37: 20 | O37: 20 | P37: 20 | Q37: 10 | R37: - | S37: - | T37: - | U37: 70 | V37: Alta | W37: Atendimento da RDU Luzimangues Industrial por fonte alternativa
A38: 5865120195 | B38: 58 | C38: CENTENARIO | D38: GUARAI | E38: NORTE | F38: ETO-PROT 00144/2026 | G38: Em fase de ajustes | J38: Melhoria de aterramento | K38: 1 | L38: PARECER DMSL:PENDÊNCIA: Realizar melhoria no aterramento por ser tratar de um terreno muito arenoso, e há pendências por parte do time da proteção, os ajustes do RT não estão disponíveis para inserção no referido equipamento.DATA DA MANUTENÇÃO: 12/03/202EQUIPE: Brunno e Edeglan.***********************PARECER DA PROTEÇÃO:FAVOR COMISSIONAR REGULADOR 5865120195 – LD Santa Maria Ramal Centenário e Recursolândia – 34,5kV. AJUSTE REALIZADO, DISPONÍVEL NO APP DA PROTEÇÃO.*********************** INSTALADO NA OBRA 0702400720 GENTILEZA, REALIZAR O COMISSIONAMENTO.LAUDO EM ANEXO.COORD EO: 889017, 901685708-07-2026 PARECER: FOI FEITO A MELHORIA NO REGULADOR CONFORME FOTOS EM ANEXO. | M38: 20 | N38: 20 | O38: 20 | P38: 10 | Q38: 0 | R38: - | S38: - | T38: - | U38: 70 | V38: Alta | W38: Atendimento das RDUs de Centenário, Recursolândia e clientes rurais
A39: 5853360007 | B39: 58 | C39: MIRACEMA DO TOCANTINS | D39: MIRACEMA DO TOCANTINS | E39: CENTRO | F39: ETO-RD-PS 00323/2025 | G39: Problema na autorização de passagem | H39: Cliente não autorizou entrar na propriedade | J39: Melhoria de aterramento | K39: 1 | L39: REALIZAR TESTES NO EQUIPAMENTO E CONFERIR MEDIÇÕES DA MALHA DE ATERRAMENTO. ESTANDO OK, COMISSIONAR EQUIPAMENTO E COLOCA-LO EM OPERAÇÃO.AJUSTES DISPONIVEIS NO APP DA PROTEÇÃdmsl : N° do Equipamento:*RT 5853360007 MIRACEMASID: 2493/2025Data: 13/05/2025Serviço Executado Provavelmente ocorreu uma descarga no equipamento comprometendo a malha!Será necessário fazer melhoria da malha de aterramento, fazer toda interligação da mesma! Feito ensaios de isolação das 3 células do equipamento, isolação está ok, quando retornar para colocar em operação levar 3 baterias de 7a.Equipamento ficou em operação?: Não Equipe: Benvindo e Jardel | M39: 0 | N39: 20 | O39: 20 | P39: 10 | Q39: 20 | R39: - | S39: - | T39: - | U39: 70 | V39: Alta | W39: Aumento de reclamações no atendimento de Miracema no período seco
A40: 5800366016 | B40: 58 | C40: WANDERLANDIA | D40: TOCANTINOPOLIS | E40: NORTE | F40: CONCLUÍDA | I40: Ok | M40: 0 | N40: 20 | O40: 20 | P40: 20 | Q40: 10 | R40: - | S40: - | T40: - | U40: 70 | V40: Alta | W40: Aumento de reclamações no atendimento de Wanderlândia no período seco
A41: 7955523028 | B41: 79 | C41: NATIVIDADE | D41: DIANOPOLIS | E41: SUL | F41: CONCLUÍDA | I41: Ok | M41: 15 | N41: 10 | O41: 5 | P41: 15 | Q41: 15 | R41: 10 | S41: 0 | T41: 0 | U41: 70 | V41: Alta | W41: Equipamento para apoio na transferência de cargas na região de Natividade
A42: 7900573047 | B42: 79 | C42: FIGUEIROPOLIS | D42: ALVORADA | E42: SUL | F42: ETO-PROT 00153/2026 | G42: Equipamento entregue ao COCM | H42: 46233 | I42: Em andamento | J42: Tanque + controle | K42: 1 | L42: 10/07 PARECER COEP: EQUIPAMENTO ENTREGUE AOS COCM´S FAVOR INFORMAR PRAZO DE SUBSTUIÇÃO PARA O DMSL E REPASSAR DEPOIS PARA PROTEÇÃO REALIZAR OS AJUSTES E DESCREVER NA SS O SERVIÇO REALIZADOPARECER COEP: AGUARDANDO COCM'S GERAREM AS OBRAS PARA PODER ENTREGAR MATERIALFavor providenciar manutenção no RL 7900573047, o mesmo estar em curto conforme fotos anexadas. Equipamento ficou bay passado em campo.PARECER DMSL: Equipe: FABIO AP./JOÃO MARCOSData Executada: 15/10/2025Serviço Executado:Foi constatado que o equipamento esta queimado na parte ativa placa, tanque e relé. Por favor fazer a substituição pelo Noja RC10. | M42: 5 | N42: 5 | O42: 15 | P42: 0 | Q42: 15 | R42: 10 | S42: 0 | T42: 15 | U42: 65 | V42: Alta | W42: Transferência da Bunge, Saneatins e secadora
A43: 7953610256 | B43: 79 | C43: MATEIROS | D43: PONTE ALTA TOCANTINS | E43: CENTRO | F43: ETO-RD-PO 00208/2026 | G43: Em processo logístico | H43: Aguardando obra COCM | J43: Tanque e cabo umbilical | K43: 1 | L43: 14/07/2026 - PARECER COEP: REALOCAR TANQUE 34,5 SOBRESSALENTE DE PARAÍSO PARA ATENDER PARECER DMSL: Data: 10/03/2026,Serviço Executado: Foi substituído o relé do equipamento, o mesmo estava danificado. Trocado o DPS, o mesmo estava queimado devido ao tanque estar furado. O equipamento ficou em bypass.Equipamento ficou em operação? NãoPendência? Sim, substituir a parte ativa com cordão umbilical.Equipe: Carliel e João VitorSEGUE SS PARA REGULARIZAR AUTOMAÇÃO DO RL 7953610256 NA INTERLIGAÇÃO COM A COELBA (CHAPADA DA MANGABEIRA) - EQUIPE INFOMOU CURTO INTERNO NO GABINETE DJ AC NÃO FECHA | M43: 5 | N43: 5 | O43: 15 | P43: 15 | Q43: 0 | R43: 0 | S43: 10 | T43: 15 | U43: 65 | V43: Alta | W43: Atenidmento da COELBA (Alto potencial de compensação)
A44: 5800438116 | B44: 58 | C44: CHAPADA DA NATIVIDADE | D44: DIANOPOLIS | E44: SUL | F44: ETO-RD-DP 00404/2026 | G44: Equipamento entregue ao COCM | H44: Previsão de substituição 30/07 (Falta confirmar conm Dener e a empreteira) | I44: Em andamento | J44: Célula | K44: 2 | L44: 01/07 PARECER COEP: DENER INFORMOU QUE TEM AS PEÇAS SOBRESSALENTES DE OBRA PARA UTILIZAR, REPASSEREI AO POSTO DO ETO-RD-DP PARA AS TRATATIVAS, FAVOR INFORMAR PREVISÃO DE SUBSTIUIÇÃO E PREENCHER A PLANILHA ASSIM COMO PREENCHER A DESCRIÃO ANTES DE PASSAR PARA PROTEÇÃO FAZER OS AJUSTES30/06PARECER COEP: AGUARDANDO COCM'S CRIAREM OBRA PARA ENTREGA DO MATERIALSegue nota para normalizar falha em regulador N:5800438116 - Chapada da natividade .equipamento está com fase B e C travada .OBS: a fase B esta sinalizando falha , equipamento não insere TAP negativo na fase B e C , o mesmo ficou no TAP zerado e bloqueado .PARECER DMSL (18/08/2025): Foi feito teste de elevar e abaixar nas fases B e C e o mesmo só aceita elevar os taps, constatando que o mercanismo da chave reversoura polaridade está com defeito. Número de série fase B EI7030 e Número de série fase C EI7040. Substituir as fases B e C.Foi constatado que a placa F do controle está com defeito. | M44: 0 | N44: 20 | O44: 20 | P44: 20 | Q44: 0 | R44: - | S44: - | T44: - | U44: 60 | V44: Média | W44: Atendimento da região da Engegold, Nativa, cidade Natividade e Chapada da Natividade (Fonte alternativa)
A45: 5800090147 | B45: 58 | C45: TAIPAS DO TOCANTINS | D45: DIANOPOLIS | E45: SUL | F45: CONCLUÍDA | I45: Ok | M45: 0 | N45: 20 | O45: 20 | P45: 10 | Q45: 10 | R45: - | S45: - | T45: - | U45: 60 | V45: Média | W45: Atendimento de Taipas
A46: 5840227063 | B46: 58 | C46: BANDEIRANTES DO TOCANTINS | D46: COLINAS DO TOCANTINS | E46: NORTE | F46: ETO-COEP 00151/2026 | G46: Primeiro ataque DMSL | L46: SEGUE PARA O DMSL AVALIAR ANTES DE SEGUIRMOS COM O SERVIÇOSEGUE PARA REALIZAR TROCA---------------------------------------------------------Boa noite,Segue SS para tratativas regulador de tensão 5840227063 fase C em curto | M46: 0 | N46: 20 | O46: 20 | P46: 10 | Q46: 10 | R46: - | S46: - | T46: - | U46: 60 | V46: Média | W46: Atendimento da RDU Bandeirantes e clientes rurais
A47: 5846328094 | B47: 58 | C47: PEIXE | D47: PEIXE | E47: SUL | F47: ETO-TELE 00986/2026 | G47: Aguardando comissionamento | I47: Em andamento | J47: Melhoria de aterramento | K47: 1 | L47: COCM SUL - 07/07/2026 - FOI REALIZADO MELHORIA DE ATERRAMENTO E FEITO A MANUTENÇÕES E TODAS AS CHAVES E SUBSTITUIDO OS CONECTORES.PARECER COEP: MELHORIA DE ATERRAMENTO É COCM'S, FAVOR ENCAMINHAR DIRETAMENTE PARA ELES, COCM'S REALIZAR MELHORIA DE ATERRAMENTO POR FAVORPor genteliiza verificar RT 5846328094 situação de equipamento, se encontra by passado em campoPARECER DMSL:Favor, realizar melhoria de aterramento que se encontra alta e substituir todos os conectores das buchas por conectores estrangulador. | M47: 0 | N47: 20 | O47: 20 | P47: 10 | Q47: 10 | R47: - | S47: - | T47: - | U47: 60 | V47: Média | W47: Atendimento da RDU Sucupira e clientes rurais
A48: 5851753086 | B48: 58 | C48: MARIANOPOLIS | D48: DIVINOPOLIS | E48: CENTRO | F48: ETO-TELE 00881/2026 | G48: Aguardando comissionamento | I48: Em andamento | J48: Melhoria de aterramento | K48: 1 | L48: PARECER DMSL: FAVOR SOLUCIONAR PENDENCIAS RT: 5851753086Relé R.U.A Data: _19/05/2026Sid: 2740/2026Possui rádio?: SimPossui antena?: SimPossui módulo nobreak?: SimServiço Executado: * Feito testes no equipamento,o mesmo está normal.* Será necessário fazer melhorias na malha de terra e colocar em operação.Equipamento ficou em operação? Não Pendência: Sim. É necessário fazer melhorias na malha de aterramento.Bateria(s) substituída(s)? _nao Data Fabricação/Instalação da(s) bateria(s): 12/2025Equipe: Jean e BenvindoPARECER DCMD: FEITO MELHORIA NA MALHA DO ATERRAMENTO, FAVOR ENVIAR EQUIPE PARA COLOCA-LO EM OPERAÇÃORT 5851753086MESMO ESTA BY-PASSADO EM CAMPO EQUIPE SINERGIA 086OP01 ESTEVE NO LOCAL APARENTIMENTE SEM DEFEITO APARENTE MESMO FOI BY PASSADO POR TER TIRADO LINHA.DESDE ENTAO MESMO NAO VOLTOU PARA OPERAÇÃO .FAVOR VERIFICAR PARA TESTES POSSIVEIS .PARA QUE O MESMO VOLTA COM DISPONIBILIDADE PARA OPERAÇÃO . | M48: 0 | N48: 20 | O48: 20 | P48: 10 | Q48: 10 | R48: - | S48: - | T48: - | U48: 60 | V48: Média | W48: Atendimento da RDU Marianópolis e clientes rurais
A49: 7903112004 | B49: 79 | C49: ARAGUAINA | D49: ARAGUAINA | E49: NORTE | F49: ETO-COEP 00184/2025 | G49: Em processo logístico | H49: Previsão de entrega 16/07, 1 tanque NOJA sobrando | I49: Em andamento | J49: Tanque | K49: 1 | L49: 20/07 PARECER COEP: EQUIPAMENTO SELECIONADO PARA COMPRAApós testes no RLG 7903112004 foi constatado defeito no mesmo e como se trata de um modelo COOPER FORM6 que está obsoleto e não possuímos peças sobressalentes, faz-se necessária substituição completa por modelo NOJA RC10. | M49: 15 | N49: 10 | O49: 5 | P49: 15 | Q49: 0 | R49: 10 | S49: 0 | T49: 0 | U49: 55 | V49: Alta | W49: Transferência de Babaçulândia, 4 RLs sendo 2 operando
A50: 7920024127 | B50: 79 | C50: PALMEIRAS DO TOCANTINS | D50: TOCANTINOPOLIS | E50: NORTE | F50: ETO-COEP 00120/2025 | G50: Em processo de aquisição | J50: Tanque + controle e chave | K50: 1 | L50: 30/06 PARECER COEP: AGUARDANDO O RETORNO DO DMSL , PARA ENTENDER SE O PROBLEMA É NA COMUNICAÇÃO OU PARTE ATIVA, JÁ QUE O EQUIPAMENTO EM QUESTÃO SEGUE COMUNICANDOPARECER DMSL: Após testes, equipe DMSL constatou que o relé e a parte ativa do equipamento 7920024127 estão com defeito, sendo necessária a substituição completa por um modelo NOJA RC 10. Favor, subsituir também a chave de saída da fase A que está com o anel de abertura quebrado.RL 7920024127 está desarmando em campo e no SCADA continua fechado, só sinaliza aberto no SCADA quando a equipe faz o resert no equipamento em campo. | M50: 15 | N50: 10 | O50: 5 | P50: 15 | Q50: 0 | R50: 10 | S50: 0 | T50: 0 | U50: 55 | V50: Alta | W50: Transferência de Palmeiras, 3 fontes operando
A51: 7927646026 | B51: 79 | C51: PONTE ALTA TOCANTINS | D51: PONTE ALTA TOCANTINS | E51: CENTRO | F51: ETO-COEP 00029/2026 | G51: Em processo de aquisição | J51: Tanque | K51: 1 | L51: PARECER COEP: EQUIPAMENTO SELECIONADO PARA COMPRARELIGADOR BY PASSADO POR DEFEITO, NECESSÁRIO AVALIAÇÃO DO PROBLEMA.parecer dmsl:O religador apresenta defeito no tanque, sendo necessário substituir o tanque o mesmo está tirando a linha, e troca os isoladores. Quando retornar, trazer uma fonte para o equipamento, a mesma foi removida.FICOU EM OPERAÇÃO? NãoPENDÊNCIA: Sim, aguardando peças para substituição. | M51: 15 | N51: 10 | O51: 5 | P51: 0 | Q51: 15 | R51: 0 | S51: 10 | T51: 0 | U51: 55 | V51: Alta | W51: Opção de isolação de São Félix e Mateiros para alimentação por gerador
A52: 7927169001 | B52: 79 | C52: PORTO NACIONAL | D52: PORTO NACIONAL | E52: CENTRO | F52: ETO-PROT 00156/2026 | G52: Concluído DCMD | H52: Previsão de substituição 16/07 | I52: Em andamento | J52: Tanque | L52: PARECER COEP: EQUIPAMENTO ENTREGUE, SEGUE SS PARA O COCM´S , PARA REALIZAR O ATENDIMENTO,FAVOR ADICIONAR O PARECER PARA MANDAR PARA PROTEÇÃOSS ANTIGA: 1500/2025 PARECER DMSL: Serviço Executado: Foi verificado que o tanque do equipamento está danificado, sendo necessário substituir o tanque do equipamento.Equipamento ficou em operação?: NãoPendência: Sim, instalar fonte, disjuntor e DPS, e substituir o tanque.***** Parecer COCM******Subsituido Tranque do RL pela Ordem de Serviço DLP-MPPA01 247/2026 RELATORIO EM ANEXO DA O.S EXECUTORA | M52: 5 | N52: 5 | O52: 15 | P52: 0 | Q52: 15 | R52: 0 | S52: 0 | T52: 15 | U52: 55 | V52: Alta | W52: Transferência dos Grupos A - VLI e Frisia
A53: 7900018004 | B53: 79 | C53: ARAGUAINA | D53: ARAGUAINA | E53: NORTE | F53: CONCLUÍDA | I53: Ok | M53: 15 | N53: 10 | O53: 5 | P53: 15 | Q53: 0 | R53: 10 | S53: 0 | T53: 0 | U53: 55 | V53: Alta | W53: Transferência de Aragominas, 3 fontes operando
A54: 7934698002 | B54: 79 | C54: TOCANTINOPOLIS | D54: TOCANTINOPOLIS | E54: NORTE | F54: CONCLUÍDA | I54: Ok | M54: 5 | N54: 5 | O54: 5 | P54: 0 | Q54: 15 | R54: 0 | S54: 10 | T54: 15 | U54: 55 | V54: Alta | W54: Atendimento do PA Mumbuca (106 UCs), no desarme a jusante penaliza parte da RDU de Tocantinópolis (1384 UCs)
A55: 7930428001 | B55: 79 | C55: PORTO NACIONAL | D55: PORTO NACIONAL | E55: CENTRO | F55: ETO-COEP 00150/2026 | G55: Em processo de aquisição | H55: Estava aguardando retorno DMSL | J55: Tanque | K55: 1 | L55: PARECER DMSL DATA 16/07/2026: será necessário fazer a substituição da parte ativa do equipamento.PARECER COEP: Equipamento Funcionando no SCADA , favor reavaliar a necessidade de substituição e se necessário mandar o modelo do equipamento.Segue nota para substituir Taque do RL-7930428001 na LD Porto Nacional / São João, Identificado pela Int-20253617520441 equipamento dando passagem na fase A ficou bay-passado até substituição, Tensão 34,5kva, Acesso livre. | M55: 5 | N55: 5 | O55: 15 | P55: 0 | Q55: 15 | R55: 10 | S55: 0 | T55: 0 | U55: 50 | V55: Alta | W55: Transferência dos Grupos A - Ramal do Rossato (TF 225kVA e TF 750kVA)
A56: 7936038076 | B56: 79 | C56: DUERE | D56: GURUPI | E56: SUL | F56: CONCLUÍDA | G56: Aguardando atualização de informação DMSL | M56: 5 | N56: 5 | O56: 15 | P56: 0 | Q56: 15 | R56: 10 | S56: 0 | T56: 0 | U56: 50 | V56: Alta | W56: Transferência do Grupo A - Xavante (TF 1087,5 kVA) e outros GA menores
A57: 7955520116 | B57: 79 | C57: CHAPADA DA NATIVIDADE | D57: DIANOPOLIS | E57: SUL | F57: CONCLUÍDA | G57: Em processo de aquisição | H57: Em processo de Aquisição | J57: Tanque | K57: 1 | M57: 5 | N57: 5 | O57: 15 | P57: 0 | Q57: 0 | R57: 10 | S57: 0 | T57: 15 | U57: 50 | V57: Alta | W57: Transferência do Grupo A - Engegold (TF 7500 kVA)
A58: 5800291035 | B58: 58 | C58: MONTE DO CARMO | D58: PONTE ALTA TOCANTINS | E58: CENTRO | F58: ETO-RD-PO 00097/2026 | G58: Melhoria de aterramento | H58: 46232 | J58: Melhoria de aterramento | K58: 1 | L58: PARECER DMSL: Feito testes funcionais nas 3 células do banco as mesmas corresponderam aos testes. Será necessário fazer a correção da malha de terra, baixar o banco completo pois está muito alto dificultando as atividades da equipe, substituir as 3 chaves facas do lado Fonte e as 3 do lado Carga instalar suporte inclinado das chaves para facilitar as manobras. Colocar cinta no controle RUA abaixar o mesmo, pois está muito alto e fixado com um mosquetão oval, quando retornar para colocar em operação levar 3 baterias de 7a e rele rua.Obs.: Fizeram melhoria na malha de terra, mas não está dentro do aceitável! As outras pendências continuam, favor corrigir. Equipamento ficou em operação?: Não - Equipe: Benvindo e Kaique- SS ANTIGA ETO-TELE 358/2026 | M58: 0 | N58: 20 | O58: 20 | P58: 10 | Q58: 0 | R58: - | S58: - | T58: - | U58: 50 | V58: Média | W58: Aumento de reclamações no atendimento de Silvanópolis por Monte do Carmo no período seco
A59: 5827102054 | B59: 58 | C59: PUGMIL | D59: PARAISO DO TOCANTINS | E59: CENTRO | F59: ETO-RD-PS 00289/2026 | G59: Vai ser feito um poço para realizar a melhoria de aterramento 28/07/2026 | H59: 46231 | L59: PARECER COEP:NÃO É POSSÍVEL RETORNAR COM O CONTROLE COMPLETO , MAS DARIA PARA FAZER A MELHORIA NA MALHA DE ATERRAMENTO , ENCAMINHANDO PARA OS COCM'S PARA REALIZAREM A MELHORIAparecer DMSL: :Nobreack com defeito, rele queimado, cabo de comunicação entre o rádio e o rele danificado, malha de aterramento está com a resistência alta!Feito reparo no cabo, substituído nobreack, e rele. Se possível retornar com controle completo pq o q está em campo teve infiltração de água, abrir chamado no scada para atualizar base do equipamento pois o mesmo está com a base antiga, fazer correção da malha de aterramento.Equipamento ficou em operação?: Não Pendência: sim, levar controle novo, fazer correção da malha de terra, levar suporte para fixar antena. OBS | M59: 0 | N59: 20 | O59: 20 | P59: 10 | Q59: 0 | R59: - | S59: - | T59: - | U59: 50 | V59: Média | W59: Aumento de reclamações no atendimento de Pugmil no período seco
A60: 5850308009 | B60: 58 | C60: GUARAI | D60: GUARAI | E60: NORTE | F60: CONCLUÍDA | I60: Ok | M60: 0 | N60: 20 | O60: 20 | P60: 0 | Q60: 10 | R60: - | S60: - | T60: - | U60: 50 | V60: Média | W60: Atendimento de parte da RDU de Guaraí e ramal da PRF/Repetidora
A61: 7900535058 | B61: 79 | C61: SANTA FE DO ARAGUAIA | D61: ARAGUAINA | E61: NORTE | F61: ETO-COEP 00173/2025 | G61: Em processo de aquisição | J61: Controle | K61: 1 | L61: PARECER COEP: EQUIPAMENTO SELECIONADO PARA COMPRAPARECER DMSL: Equipamento 7900535058 encontra-se com o relé danificado, firmware corrompido, o mesmo não inicia. Devido ao fato de não possuirmos mais peças de reposição para religador cooper, se faz necessário a substituição de todo conjunto por um Noja RC10.envar equipe para verificar rlo 7900535058 foi feito primeiro ataque com equipe 040op36 o mesmo esta com RELE TRAVADO E FICOU FORA DE OPERAÇÃO, ATENDE RDR DE SANTA FÉ SAIDA DA CIDADEEQUIPE INFORMOU ABELHAS NA CAIXA DO PAINEL DE COMANDO | M61: 5 | N61: 10 | O61: 5 | P61: 0 | Q61: 15 | R61: 10 | S61: 0 | T61: 0 | U61: 45 | V61: Média | W61: Atendimento 3 povoados, na perca 4 ficam fora (900 UCs)
A62: 7927713200 | B62: 79 | C62: SAO SALVADOR DO TOCANTINS | D62: PEIXE | E62: SUL | F62: CONCLUÍDA | G62: Em processo de aquisição | J62: Tanque | K62: 1 | M62: 5 | N62: 5 | O62: 5 | P62: 0 | Q62: 15 | R62: 10 | S62: 0 | T62: 0 | U62: 40 | V62: Média | W62: Transferência do Ramal do Retiro (246UCs), fonte principal by-passado
A63: 7937102148 | B63: 79 | C63: SAO VALERIO DA NATIVIDADE | D63: PEIXE | E63: SUL | F63: ETO-COEP 00129/2026 | G63: Em processo de aquisição | J63: Tanque | K63: 1 | L63: PARECER COEP: REAVALIAR DISPONIBILIDADE DO EQUIPAMENTO NO SCADA ASSIM COMO , FORNECER MODELO DO EQUIPAMENTO E FAIXA DE TENSÃO PARA COMPRA / AQUISIÇÃOTanque com defeito, realizar substituição do tanque. | M63: 5 | N63: 5 | O63: 5 | P63: 0 | Q63: 15 | R63: 10 | S63: 0 | T63: 0 | U63: 40 | V63: Média | W63: Fonte principal do Ramal Serranópolis (181 UCs), RL de transferência operando
A64: 7944559149 | B64: 79 | C64: CASEARA | D64: DIVINOPOLIS | E64: CENTRO | F64: ETO-COEP 00063/2026 | G64: Em processo de aquisição | J64: Controle | K64: 1 | L64: 14/07/2026 PARECER COEP: EQUIPAMENTO SELECIONADO PARA COMPRA Equipamento ficou em operação?: NãoPendência: Sim será necessário substituir a placaServiço Executado: curto na placa foi tentando recuperar a mesma porém não teve sucesso!Bateria(s)substituída(s)? NÃOEquipe: Kaique e benvido | M64: 5 | N64: 10 | O64: 0 | P64: 0 | Q64: 15 | R64: 10 | S64: 0 | T64: 0 | U64: 40 | V64: Média | W64: Atendimento de cargas rurais entre Caseaarra e Araguacema (221 UCs)
A65: 5800961074 | B65: 58 | C65: DIANOPOLIS | D65: DIANOPOLIS | E65: SUL | F65: ETO-COEP 00221/2025 | G65: Aguardando desativação do Regulador da Obra de Construção | H65: Previsão até dia 20/08 | J65: Células + melhoria de aterramento | K65: 3 | L65: PARECER COEP: EQUIPAMENTO SELECIONADO PARA COMPRASubstituir as 3 células- Melhoria na malha de aterramento - Melhoria no circuito de aterramento qua aterra as células.- Substituir conectores paralelos | M65: 20 | N65: 0 | O65: 0 | P65: 20 | Q65: 0 | R65: - | S65: - | T65: - | U65: 40 | V65: Média | W65: Atendimento da COELBA e GA Alessandro Maurício (1600 kVA)
A66: 7908249152 | B66: 79 | C66: SANTA ROSA DO TOCANTINS | D66: PORTO NACIONAL | E66: CENTRO | F66: ETO-COEP 00038/2026 | G66: Em processo de aquisição | J66: Tanque + controle | K66: 1 | L66: 14/07/2026 PARECER COEP: EQUIPAMENTO SELECIONADO PARA COMPRADMSL:Serviço Executado: Houve um curto no equipamento danificando a parte ativa, será necessário fazer a substituição do equipamento completo ( parte ativa e controle) colocar o um cabo pp novo do trafo até o Dj pois o mesmo está sem condições de uso. Obs:. Foi retirado rádio e rele Equipamento ficou em operação?: Não Pendência: Sim, substituir o equipamento completo. | M66: 5 | N66: 5 | O66: 0 | P66: 0 | Q66: 15 | R66: 10 | S66: 0 | T66: 0 | U66: 35 | V66: Média | W66: Atendimento de zona rural em Santa Rosa (160 UCs)
A67: 7922995039 | B67: 79 | C67: ARAGUATINS | D67: AUGUSTINOPOLIS | E67: NORTE | F67: ETO-PROT 00135/2026 | I67: Em operação | L67: PARECER COEP: Equipamento em operação, instalado com sucesso, segue para Proteção para ajustesPARECER DMSL: Após testes, equipe DMSL constatou que o RLG 7922995039 encontra-se com parte ativa e controle danificados. Favor, realizar substituição completa do equipamento.Troca do sistema de comunicação do equipamento | M67: 5 | N67: 5 | O67: 0 | P67: 0 | Q67: 15 | R67: 10 | S67: 0 | T67: 0 | U67: 35 | V67: Média | W67: Atendimento do PA Esperança Viva (396 UCs)
A68: 7925733015 | B68: 79 | C68: PEDRO AFONSO | D68: GUARAI | E68: NORTE | F68: ETO-COEP 00058/2026 | G68: Em processo de aquisição | J68: Tanque | K68: 1 | L68: PARECER COEP: EQUIPAMENTO SELECIONADO PARA COMPRAPARECER DMSL: FEEDBACK EQUIP. ESPECIAISNº DO EQUIPAMENTO: 7925733015TIPO EQUIPAMENTO: Noja RC10TIPO DE COMUNICAÇÃO: Rádio GEDATA DA MANUTENÇÃO: 24/03/2026SID: 1475/2026DESCRIÇÃO: Tanque do equipamento em CurtoFICOU EM OPERAÇÃO?: Não PENDÊNCIA: Sim, repassar a nota para DCMD substituir tanque.DADOS DIVERGENTES DA PROGRAMAÇÃO: NãoBATERIA SUBSTITUÍDA?: Não TIPO DE BATERIA: Lítio EQUIPE: Edicleber e Jhonata(DEOP)------------------------------------------------------------------------------------------------------religador 7925733015 com defeito, equipe fez abertura da chave de saida do mesmo e ele não aceita fehcamento devido provavel curto-circuito interno, enviar equipe para verificar o mesmo ficou by-pass fechado | M68: 5 | N68: 5 | O68: 0 | P68: 0 | Q68: 15 | R68: 10 | S68: 0 | T68: 0 | U68: 35 | V68: Média | W68: Transferência do Ramal Agrovila (73 UCs)
A69: 7927396052 | B69: 79 | C69: FORMOSO DO ARAGUAIA | D69: FORMOSO DO ARAGUAIA | E69: SUL | F69: ETO-COEP 00045/2026 | G69: Em processo de aquisição | J69: Tanque | K69: 1 | L69: PARECER COEP: EQUIPAMENTO SELECIONADO PARA COMPRAreligador foi bay passado devido mesmo esta saindo fumaca do painel e sem comunicação 7927396052.PARECER DMSL: Após testes, equipe DMSL constatou que apenas o tanque do RLG 7927396052 encontra-se queimado. Favor, substituir parte ativa do equipamento.NS Tanque: 0320123040198 | M69: 5 | N69: 5 | O69: 0 | P69: 0 | Q69: 15 | R69: 10 | S69: 0 | T69: 0 | U69: 35 | V69: Média | W69: Equipamento localizado Fonte principal de atendimento a SE Cobrape
A70: 7933585074 | B70: 79 | C70: DIANOPOLIS | D70: DIANOPOLIS | E70: SUL | F70: ETO-COEP 00024/2026 | G70: Em processo de aquisição | H70: Estava aguardando retorno DMSL | J70: Tanque | K70: 1 | L70: 30/06 PARECER COEP: AGUARDANDO RETORNO DO DMSL.REALIZAR SUBSTITUIÇÃO DO TANQUE, O MESMO ESTÁ COM DEFEITO. | M70: 5 | N70: 5 | O70: 15 | P70: 0 | Q70: 0 | R70: 0 | S70: 10 | T70: 0 | U70: 35 | V70: Média | W70: Atendimento da COELBA
A71: 7942572059 | B71: 79 | C71: TAQUARALTO | D71: TAQUARALTO | E71: CENTRO | F71: ETO-PROT 00155/2026 | G71: Melhoria de aterramento | I71: Em operação | L71: PARECER COEP: EQUIPAMENTO COM MELHORIA DE ATERRAMENTO É COM A ETO-RD-PA , NÃO PASSA PELO FLUXO DE AQUISIÇÃO DO COEP, FAVOR REALIZAR MELHORIA DE ATERRAMENTO ETO-RD-PAPARECER DMSL 19/05/2026: É necessário fazer melhorias na malha de aterramento.segue nota para RL 794252059 o mesmo esta sem comunicaçao, foi feito primeiro ataque, porem a comunicaçao nao voltou, obs ramal do marasca.**** Parcecer do COCM CENTRO-****FEITO A MALHAR DE ATERRAMENTO ATENDIDA PELA ORDEM DE SERVIÇO DLP-MLPA02 91/2026 COM RELATORIO EM ANEXO A O.S | M71: 5 | N71: 5 | O71: 15 | P71: 0 | Q71: 0 | R71: 0 | S71: 10 | T71: 0 | U71: 35 | V71: Média | W71: Atendimento do Ramal do Marasca e GAs (108 UCs)
A72: 7944319149 | B72: 79 | C72: CASEARA | D72: DIVINOPOLIS | E72: CENTRO | F72: CONCLUÍDA | I72: Ok | M72: 5 | N72: 5 | O72: 15 | P72: 0 | Q72: 0 | R72: 0 | S72: 10 | T72: 0 | U72: 35 | V72: Média | W72: Atendimento do Grupo A - Matosul (TF 1500 kVA)
A73: 7955986084 | B73: 79 | C73: DIVINOPOLIS | D73: DIVINOPOLIS | E73: CENTRO | F73: ETO-COEP 00133/2026 | G73: Em processo de aquisição | L73: 14/07/2026 PARECER COEP : SUBSTIUIR CONTROLE COMPLETOPARECER DMSL: Equipamento com a placa de alimentação ca em curto, será necessário substituir a placa do equipamento. (Antiga nota era pra ter sido repassada porém foi baixada indevidamente pela equipe) | M73: 5 | N73: 5 | O73: 0 | P73: 0 | Q73: 15 | R73: 10 | S73: 0 | T73: 0 | U73: 35 | V73: Média | W73: Transferência de cargas do 444R da SE Paraíso I
A74: 7967181127 | B74: 79 | C74: PALMEIRAS DO TOCANTINS | D74: TOCANTINOPOLIS | E74: NORTE | F74: CONCLUÍDA | G74: ETO-RD-AR 1070/2026 | H74: Confirmar com o DMSL | M74: 5 | N74: 5 | O74: 0 | P74: 0 | Q74: 15 | R74: 10 | S74: 0 | T74: 0 | U74: 35 | V74: Média | W74: Transferência de Palmeiras, 3 RLs sendo 2 operando
A75: 7900525015 | B75: 79 | C75: PEDRO AFONSO | D75: GUARAI | E75: NORTE | F75: ETO-COEP 00125/2026 | G75: Em processo de aquisição | J75: Tanque | K75: 1 | L75: PARECER COEP: É PARA REALIZAR A SUBSTITUIÇÃO DO RELIGADOR OU DAS BUCHAS, CASO SEJA BUCHAS , REPASSAR PARA OS COCM'S , CASO NÃO SEJA ESPECIFIQUE O MODELO , E A TENSÃO, FICO NO AGUARDO DO RETORNONota para manutenção substituir religador 7900525015 que está com as buchas de entrada danificadas fase A estourada e bc danificadas Local LD Pedro Afonso A Chaparral | M75: 5 | N75: 5 | O75: 0 | P75: 0 | Q75: 15 | R75: 10 | S75: 0 | T75: 0 | U75: 35 | V75: Média | W75: Tranferência do Ramal do Chaparral (251 UCs)
A76: 7928564039 | B76: 79 | C76: ARAGUATINS | D76: AUGUSTINOPOLIS | E76: NORTE | F76: ETO-COEP 00123/2026 | G76: Em processo de aquisição | J76: Tanque + controle | K76: 1 | L76: PARECER COEP: EQUIPAMENTO SELECIONADO PARA COMPRATroca do sistema de comunicação do equipamentoDMSL 28/07/2025: Equipamento com tanque, modulo e rele com defeito, solicitar troca do equipamento ao DCMD.Fotos vão ser enviadas por e-mail | M76: 5 | N76: 10 | O76: 5 | P76: 0 | Q76: 0 | R76: 10 | S76: 0 | T76: 0 | U76: 30 | V76: Média | W76: Transferência entre 424R Araguatins e 434R Augustinópolis
A77: 7957126085 | B77: 79 | C77: MONTE SANTO DO TOCANTINS | D77: PARAISO DO TOCANTINS | E77: CENTRO | F77: CONCLUÍDA | I77: Ok | M77: 5 | N77: 10 | O77: 5 | P77: 0 | Q77: 0 | R77: 10 | S77: 0 | T77: 0 | U77: 30 | V77: Média | W77: 444R de Paraíso I, atendimento de Monte Santo, devido defeito a RDU está manobrada para o 454R
A78: 5841308190 | B78: 58 | C78: NOVO JARDIM | D78: DIANOPOLIS | E78: SUL | F78: CONCLUÍDA | I78: Desmobilizado | J78: - | M78: 0 | N78: 20 | O78: 0 | P78: 10 | Q78: 0 | R78: - | S78: - | T78: - | U78: 30 | V78: Baixa | W78: Equipamento obsoleto com a entrada da SE Serras Gerais
A79: 5844630060 | B79: 58 | C79: NOVA OLINDA | D79: COLINAS DO TOCANTINS | E79: NORTE | F79: CONCLUÍDA | G79: Em processo logístico | H79: Previsão de entrega 20/07 | J79: Célula | K79: 1 | M79: 20 | N79: 0 | O79: 0 | P79: 10 | Q79: 0 | R79: - | S79: - | T79: - | U79: 30 | V79: Baixa | W79: Atendimento dos ramais PA Remansão e Água Branca
A80: 5855411017 | B80: 58 | C80: BARROLANDIA | D80: MIRACEMA DO TOCANTINS | E80: CENTRO | F80: ETO-COEP 00156/2026 | G80: Equipamento Em operação Confimardo com o Operador com Joelson | H80: Aguardando confirmação sobre execução do COCM | I80: Em andamento | J80: Controle | K80: 1 | L80: 10/07 PARECER COEP: EQUIPAMENTO ENTREGUE AOS COCM´S FAVOR INFORMAR PRAZO DE SUBSTUIÇÃO PARA O DMSL E REPASSAR DEPOIS PARA PROTEÇÃO REALIZAR OS AJUSTES E DESCREVER NA SS O SERVIÇO REALIZADOPARECER COEP: EQUIPAMENTO EM ROTA DE ENTREGASEM COMUNICAÇÃO, FALHA DE ALIMENTAÇÃO - REALIZADO PRIMEIRO ATAQUE SEM SUCESSO.PARECER DMSL: 17/09/2025 Equipamento ficou em operação? Não Pendência: sim. Equipamento ficou Bay passado levar controle COMPLETO para trocar. ellisfran | M80: 0 | N80: 0 | O80: 0 | P80: 10 | Q80: 20 | R80: - | S80: - | T80: - | U80: 30 | V80: Baixa | W80: Atendimento do Assentamento Irmã Adelaide
A81: 7900505026 | B81: 79 | C81: PONTE ALTA TOCANTINS | D81: PONTE ALTA TOCANTINS | E81: CENTRO | F81: CONCLUÍDA | M81: 5 | N81: 5 | O81: 5 | P81: 0 | Q81: 0 | R81: 0 | S81: 10 | T81: 0 | U81: 25 | V81: Baixa | W81: Atendimento do Ramal do Gato (288 UCs) e UFV Videira, no desarme a jusante penaliza a cidade de Pindorama
A82: 7908196047 | B82: 79 | C82: FIGUEIROPOLIS | D82: ALVORADA | E82: SUL | F82: ETO-TELE 01002/2026 | G82: Em processo de aquisição | J82: Tanque + controle | K82: 1 | L82: 13/07/2026 PARECER COEP: EQUIPAMENTO REMANEJADO FAVOR FAZER O COMISSIONAMENTORELIGADOR N° 7908196047 REMANEJADO NA OBRA 0402401150 GENTILEZA, REALIZAR O COMISSIONAMENTO. LAUDO EM ANEXO. COORD EO: 698485, 8657287PARECER DA PROTEÇÃO:AJUSTE DISPONIBILIZADO NO APP DA PROTEÇÃO, NOTA REPASSADA PARA DMSL COMISSIONAR, POLO GURUPI, RL APENAS REMANEJADO DA REDE VELHA PARA REDE NOVA, EQUIPAMENTO COOPER, SE MANTEVE O MESMO NÚMERO DE ATIVO.ENG° IRLLEY CASTELO BRANCO.PARECER DMSL: Constatado curto-circuito no tanque do religador, impedindo as operações de abertura e fechamento do equipamento. Solicita-se a substituição completa do religador, incluindo tanque e unidade de controle. | M82: 5 | N82: 5 | O82: 5 | P82: 0 | Q82: 0 | R82: 0 | S82: 10 | T82: 0 | U82: 25 | V82: Baixa | W82: Seccionamento do Rural e energização do 224R
A83: 7921202014 | B83: 79 | C83: PIUM | D83: PARAISO DO TOCANTINS | E83: CENTRO | F83: ETO-COEP 00132/2026 | G83: Em processo de aquisição | H83: Estava aguardando retorno DMSL | J83: Tanque | K83: 1 | L83: PARECER COEP: EQUIPAMENTO SELECIONADO PARA COMPRA , DEVERIA SER SUBSTITUIDO PARTE ATIVAPARECER DMSL: Serviço Executado: _ indentificado o problema na parte ativa será necessário fazer a substituição da mesmo, feito a medição do aterramento. Preciso substituir para raio da fase c.Equipamento ficou em operação?: _NAOPendência: _SimBateria(s) substituída(s)? _NãoData Fabricação/Instalação da(s) bateria(s):_Equipe: _Benvindo e kaique----------------------------------------------------------------------------------RL com defeito no rele, fica só reiniciando ficou By passado OS atendimento primeiro ataque 106530226 | M83: 5 | N83: 5 | O83: 5 | P83: 0 | Q83: 0 | R83: 10 | S83: 0 | T83: 0 | U83: 25 | V83: Baixa | W83: Atendimento de Clientes rurais (483 UCs)
A84: 7923927122 | B84: 79 | C84: PALMAS | D84: PALMAS | E84: CENTRO | F84: ETO-COEP 00148/2026 | G84: Primeiro ataque DMSL | J84: Tanque | K84: 1 | L84: PARECER DMSL 16/07: Nota solicitada ao DMSL com a informação de que o tanque precisa ser substituído. Estou encaminhando a nota para a área responsável.Segue nota para envia manutenção substituir tanque do RL-7923927122 em curto, Anomalia identificada desarme das LD, s Palmas / Aparecida e Palmas Taquaruçu, Acesso livre, Tensão 34,5kv, Local RL de Interligação entre 424R / 414R. | M84: 15 | N84: 0 | O84: 0 | P84: 0 | Q84: 0 | R84: 10 | S84: 0 | T84: 0 | U84: 25 | V84: Baixa | W84: Transferência entre 414R e 424R SE Palmas II
A85: 7927446001 | B85: 79 | C85: PORTO NACIONAL | D85: PORTO NACIONAL | E85: CENTRO | F85: ETO-COEP 00143/2025 | G85: Em processo de aquisição | H85: Estava aguardando retorno DMSL | J85: Tanque + controle | K85: 1 | L85: 30/06 PARECER COEP: EQUIPAMENTO COMPLETOSegue para verificação RL sem comunicação feito primeiro ataque sem sucesso.PARECER DMSL:Data:* _08/07/2025Serviço Executado: Placa de alimentação danificada, devido a curto, não temos material sobressalente para manutenção! Favor substituir o equipamento completo.Obs.: O rádio ficou dentro do controle, favor orientar a equipe que for substituir colocar dentro do controle novo.Equipamento ficou em operação?: Não Pendência: Sim, substituir equipamento completo. | M85: 5 | N85: 5 | O85: 5 | P85: 0 | Q85: 0 | R85: 10 | S85: 0 | T85: 0 | U85: 25 | V85: Baixa | W85: Alimentação de Monte do Carmo por Porto Nacional
A86: 7928241200 | B86: 79 | C86: SAO SALVADOR DO TOCANTINS | D86: PEIXE | E86: SUL | F86: ETO-COEP 00128/2026 | G86: Em processo de aquisição | H86: Estava aguardando retorno DMSL | J86: Tanque | K86: 1 | L86: PARECER COEP: EQUIPAMENTO SELECIONADO PARA COMPRAPARECER DMSL: Tinha uma nota aberta 422/2025 e logo após a equipe resolver a comunicação ela foi baixada, porém a equipe relatou que ''na estrada ontem o COS nos avisou para voltar que na hora de colocar em operação ele tirou a linha fora. Hoje retornamos nele e fizemos ensaios elétricos e foi constatado que o tanque está em curto. Passa direto aí para o Dcmd para substituição do tanque.'' | M86: 5 | N86: 5 | O86: 5 | P86: 0 | Q86: 0 | R86: 10 | S86: 0 | T86: 0 | U86: 25 | V86: Baixa | W86: Fonte principal do Ramal do Retiro (246UCs), RL transferência by-passado
A87: 7942485096 | B87: 79 | C87: PINDORAMA DO TOCANTINS | D87: PONTE ALTA TOCANTINS | E87: CENTRO | F87: ETO-COEP 00158/2025 | G87: Em processo de aquisição | J87: Tanque | K87: 1 | L87: 30/06 PARECER COEP: EQUIPAMENTO SELECIONADO PARA COMPRARELIGADOR COM DEFEITO 7942485096, ESTA DANDO PASSAGEM ESTANDO ABERTO. NÃO ACEITA COMANDOS. FICOU BY PASSADO EM CAMPO PARA MANUTENÇÃO.PARECER DMSL: Ao testar o tanque, foi constatado que o mesmo está danificado e precisa ser substituído.Substituir somente o tanque. Deixar claro na nota para o dcmd substituir somente o tanque. Não tem necessidade de substituir o controle. | M87: 5 | N87: 5 | O87: 5 | P87: 0 | Q87: 0 | R87: 10 | S87: 0 | T87: 0 | U87: 25 | V87: Baixa | W87: Transferência da PCH Bagagem
A88: 7955430075 | B88: 79 | C88: DOIS IRMAOS DO TOCANTINS | D88: DIVINOPOLIS | E88: CENTRO | F88: CONCLUÍDA | I88: Ok | M88: 5 | N88: 5 | O88: 5 | P88: 0 | Q88: 0 | R88: 0 | S88: 10 | T88: 0 | U88: 25 | V88: Baixa | W88: Atendimento do Ramal do Boleu (13 UCs), no desarme a jusante penaliza parte 303 UCs rurais
A89: 7955686076 | B89: 79 | C89: DUERE | D89: GURUPI | E89: SUL | F89: CONCLUÍDA | I89: Ok | M89: 5 | N89: 5 | O89: 0 | P89: 0 | Q89: 15 | R89: 0 | S89: 0 | T89: 0 | U89: 25 | V89: Baixa | W89: Fonte alternativa de atendimento do Ramal Bacuri (217 UCs)
A90: 7955946007 | B90: 79 | C90: MIRACEMA DO TOCANTINS | D90: MIRACEMA DO TOCANTINS | E90: CENTRO | F90: ETO-COEP 00134/2026 | G90: Em processo de aquisição | J90: Controle | K90: 1 | L90: 13/07/2026 PARECER COEP: SUBSTITUIR CONTOLE OU MANDAR MANUTENCIONAR EM CASO DE PRIORIDADE ALTAPARECER DMSL: Necessário substituir a placa de alimentação ca, a mesma está em curto não conseguimos recuperar. (Antiga nota era pra ter sido repassada porém foi baixada indevidamente pela equipe) | M90: 5 | N90: 5 | O90: 5 | P90: 0 | Q90: 0 | R90: 0 | S90: 10 | T90: 0 | U90: 25 | V90: Baixa | W90: Alimentação do serviço auxiliar da Investco e clientes rurais (260 UCs)
A91: 7901110084 | B91: 79 | C91: DIVINOPOLIS | D91: DIVINOPOLIS | E91: CENTRO | F91: ETO-COEP 00061/2026 | G91: Em processo de aquisição | L91: PARECER COEP: EQUIPAMENTO SELECIONADO PARA COMPRAPARECER DMSL: Serviço Executado: Foi feito análise técnica, testes funcionais e identificado que a parte ativa do equipamento está com defeito. Necessário substituir a parte ativa.FICOU EM OPERAÇÃO? Não- EQUIPE: Carliel e BenvindoSegue SS para verificaçao Rl esta danificado dando passagem de tensão mesmo aberto Sim, quando retornar trazer uma fonte pois a mesma foi removida. | M91: 5 | N91: 5 | O91: 0 | P91: 0 | Q91: 0 | R91: 0 | S91: 10 | T91: 0 | U91: 20 | V91: Baixa | W91: Localizado na fonte principal de atendimento de Divinópolis e Abreulândia
A92: 7908206074 | B92: 79 | C92: DIANOPOLIS | D92: DIANOPOLIS | E92: SUL | F92: CONCLUÍDA | I92: Ok | M92: 5 | N92: 5 | O92: 0 | P92: 0 | Q92: 0 | R92: 0 | S92: 10 | T92: 0 | U92: 20 | V92: Baixa | W92: Atendimento do PA Novo Plano (102 UCs)
A93: 7908708116 | B93: 79 | C93: CHAPADA DA NATIVIDADE | D93: DIANOPOLIS | E93: SUL | F93: CONCLUÍDA | G93: Aguardando atualização de informação DMSL | J93: Tanque e controle | M93: 5 | N93: 5 | O93: 0 | P93: 0 | Q93: 0 | R93: 0 | S93: 10 | T93: 0 | U93: 20 | V93: Baixa | W93: Atendimento do PA Xobo (194 UCs)
A94: 7910027196 | B94: 79 | C94: LAGOA DO TOCANTINS | D94: TAQUARALTO | E94: CENTRO | F94: CONCLUÍDA | G94: ETO-TELE 973/2026 | J94: Completo sem o radio | M94: 5 | N94: 5 | O94: 0 | P94: 0 | Q94: 0 | R94: 0 | S94: 10 | T94: 0 | U94: 20 | V94: Baixa | W94: Atendimento do Ramal do Rio Preto (197 UCs)
A95: 7913662076 | B95: 79 | C95: DUERE | D95: GURUPI | E95: SUL | F95: ETO-COEP 00114/2026 | G95: (REPASSAR PARA ANALISE DMSL) | L95: 30/06 PARECER COEP: AGUARDANDO RETORNO DO DMSL PARA ENTENDER EXATAMENTE O QUE TENHO QUE SUBSTITUIRAberto nota para substituir tanque danificado e chave de entrada fase B danificadaPARECER DMSL: Foi confirmado pela equipe DMSL o defeito do tanque, favor seguir com a substituição e correção da chave de entrada fase B danificada. | M95: 5 | N95: 5 | O95: 0 | P95: 0 | Q95: 0 | R95: 10 | S95: 0 | T95: 0 | U95: 20 | V95: Baixa | W95: Atendimento do Ramal do Bacuri (168 UCs)
A96: 5862236091 | B96: 58 | C96: ALMAS | D96: DIANOPOLIS | E96: SUL | F96: ETO-RD-DP 00457/2026 | G96: Em processo de aquisição | J96: Célula | K96: 1 | L96: PARECER COEP: AGUARDANDO COCM´s GERAREM A OBRA COM ABERTURA CONTABIL DENER SOARESRealizar substituição da FASE B.Célula da fase B estava com a tampa do contador de tape aberta, pegou chuva e molhou os contatos danificando a peça toda. | M96: 0 | N96: 0 | O96: 0 | P96: 20 | Q96: 0 | R96: - | S96: - | T96: - | U96: 20 | V96: Baixa | W96: Atendimento da LD Vale Rio Doce (Nova Aura Mineradora)
A97: 5836786094 | B97: 58 | C97: PEIXE | D97: PEIXE | E97: SUL | F97: ETO-COEP 00095/2026 | G97: Levar para analise de reguladores furtados no Sul | L97: 24/07 PARECER COEP:EQUIPAMENTO EM LOGISTICA DE ENTREGA Favor levar outro regulador de tensão, pois o mesmo foi furtado em campo. | M97: 0 | N97: 0 | O97: 0 | P97: 10 | Q97: 10 | R97: - | S97: - | T97: - | U97: 20 | V97: Baixa | W97: Atendimento de clientes rurais na LD Peixe Angical - Peixe
A98: 7919270014 | B98: 79 | C98: PIUM | D98: PARAISO DO TOCANTINS | E98: CENTRO | F98: ETO-RD-PS 00327/2026 | G98: (REPASSAR PARA ANALISE DMSL) | L98: PARECER COEP: AGUARDANDO RETORNO DO DMSL, EQUIPAMENTO FOI INSTALADO NOVO NA OBRA 0212501060, ENTENDER O PORQUE NÃO FOI REALIZADO COMISSIONAMENTOPARECER DMSL: Substituir Equipamento completo problema na placa de alimentação e na parte ativa, falta colocar placa de identificação correta na topologia, baixar o controle.Equipamento ficou em operação?: naoPendência: simBateria(s) substituída(s)? NÃOEquipe: Kaique/ Benvindo13/07/2026 PARECER COEP: SUBSTITUIÇÃO REALZIADA , FAVOR COMISSIONARPARECER DMSL (22/07/26): Solicito que o laudo de substituição seja anexado, e a SS seja repassada para proteção atribuir a ordem de ajuste, antes de repassar para ETO-TELE.----------------------------------------------PARECER DA PROTEÇÃO: Prosseguir com o comissionamento. Ajustes de religador permanecem os mesmos, disponíveis no APP da Proteção.********************************RELIGADOR N°7919270014 REMANEJADO NA OBRA 0212501060 GENTILEZA, REALIZAR O COMISSIONAMENTO. LAUDO EM ANEXO. COORD EO: 617422, 8830787 | M98: 5 | N98: 5 | O98: 0 | P98: 0 | Q98: 0 | R98: 10 | S98: 0 | T98: 0 | U98: 20 | V98: Baixa | W98: Atendimento de Clientes rurais (48 UCs)
A99: 7926442035 | B99: 79 | C99: MONTE DO CARMO | D99: PONTE ALTA TOCANTINS | E99: CENTRO | F99: ETO-COEP 00051/2026 | G99: Em processo de aquisição | L99: PARECER COEP: EQUIPAMENTO SELECIONADO PARA COMPRAPARECER DMSL: Data: 12/03/2026 Serviço Executado:- Análise técnica constatou:- Parte ativa do equipamento danificada: necessita substituição- Trafo danificado: foi feitos testes nas buchas secundárias o mesmo não chega tensão - Vazamento de óleo - Necessita substituiçãoEquipamento ficou em operação? NãoPendências:- Solicitar limpeza de faixa para acesso ao equipamento- Trocar parte ativa do equipamento- Substituir o trafoEquipe: Carliel e João VitorSegue nota para envia equipe verificar falha de comunicação e automação no RL-7926442035 feito primeiro ataque com equipe 035OP02, porém sem sucesso. | M99: 5 | N99: 5 | O99: 0 | P99: 0 | Q99: 0 | R99: 0 | S99: 10 | T99: 0 | U99: 20 | V99: Baixa | W99: Atenidmento do PA Principado (200 UCs)
A100: 7954668084 | B100: 79 | C100: DIVINOPOLIS | D100: DIVINOPOLIS | E100: CENTRO | F100: CONCLUÍDA | J100: Display | M100: 5 | N100: 5 | O100: 0 | P100: 0 | Q100: 0 | R100: 0 | S100: 10 | U100: 20 | V100: Baixa | W100: Atendimento do PA Piedade (125 UCs)
...

Sheet Planilha1
D2: Parecer COEP | E2: Equipamento entregue ao COCM
A3: Rótulos de Linha | B3: Contagem de Ativo
A4: Muito Alta | B4: 30 | D4: Rótulos de Linha | E4: Contagem de Ativo
A5: Aguardando comissionamento | B5: 4 | D5: Muito Alta | E5: 3
A6: Em fase de ajustes | B6: 3 | D6: Previsão de substituição 07/08 | E6: 2
A7: Em processo de aquisição | B7: 7 | D7: Previsão de substituição 27/08 | E7: 1
A8: Em processo logístico | B8: 1 | D8: Alta | E8: 1
A9: Equipamento entregue ao COCM | B9: 3 | D9: Previsão de substituição 28/07 | E9: 1
A10: Substituido 24/07, pendente laudo | B10: 2 | D10: Média | E10: 1
A11: Concluído | B11: 10 | D11: Previsão de substituição 07/08 | E11: 1
A12: Alta | B12: 21 | D12: Total Geral | E12: 5
A13: Aguardando atualização de informação DMSL | B13: 1
A14: Em fase de ajustes | B14: 5 | D14: Parecer COEP | E14: Em processo logístico
A15: Em processo de aquisição | B15: 5
A16: Em processo logístico | B16: 2 | D16: Rótulos de Linha | E16: Contagem de Ativo
A17: Equipamento entregue ao COCM | B17: 1 | D17: Muito Alta | E17: 1
A18: Primeiro ataque DMSL | B18: 1 | D18: Previsão de entrega 10/08 | E18: 1
A19: Problema na autorização de passagem | B19: 1 | D19: Alta | E19: 2
A20: Substituido 27/07, pendente laudo | B20: 1 | D20: Previsão de entrega 10/08 | E20: 1
A21: Concluído | B21: 4 | D21: Previsão de entrega 10/08, 1 tanque NOJA sobrando | E21: 1
A22: Média | B22: 25 | D22: Baixa | E22: 2
A23: Aguardando comissionamento | B23: 4 | D23: Previsão de entrega 16/08 | E23: 1
A24: Em processo de aquisição | B24: 13 | D24: Previsão de entrega 20/07 | E24: 1
A25: Equipamento entregue ao COCM | B25: 1 | D25: Total Geral | E25: 5
A26: Melhoria de aterramento | B26: 1
A27: Concluído | B27: 6
A28: Baixa | B28: 27
A29: Aguardando atualização de informação DMSL | B29: 1
A30: Aguardando parecer DMSL | B30: 1
A31: Em processo de aquisição | B31: 16
A32: Em processo logístico | B32: 2
A33: REPASSAR O DMSL (EQUIPAMENTO OPERANDO NO SCADA) | B33: 1
A34: Concluído | B34: 6
A35: Total Geral | B35: 103

Sheet Concluídas
A1: ANO_SS | B1: SS_ORIGINAL | C1: DESTINO_SS | D1: COD_RELIGADOR | E1: DTA_ABERTURA | F1: DTA_CONCLUSAO | G1: COD_LOC | H1: LOCALIDADE | I1: POLO | J1: REGIONAL | K1: ALIMENTADOR | L1: DESCRICAO
A2: 2026 | B2: ETO-TELE 00829/2026 | C2: ETO-TELE | D2: 5833578028 | E2: 46150 | F2: 46174 | G2: 28 | H2: NATIVIDADE | I2: DIANOPOLIS | J2: SUL | K2: LD04002091 | L2: Segue nota para verificar falha de comunicação no regulador 5833578028 - Rural - Natividade.equipe operacional foi no local, feito reset , porém não conseguiram normalizar sua comunicação .
A3: 2026 | B3: ETO-TELE 00814/2026 | C3: ETO-TELE | D3: 7913657147 | E3: 46142 | F3: 46175 | G3: 147 | H3: TAIPAS DO TOCANTINS | I3: DIANOPOLIS | J3: SUL | K3: LD05028074 | L3: favor verificar religador 7913657147 foi feito primeiro ataque ja duas vezes e encontra disjuntor desligado liga em seguida desarma.
A4: 2026 | B4: ETO-TELE 00511/2026 | C4: ETO-TELE | D4: 7944353028 | E4: 46119 | F4: 46175 | G4: 28 | H4: NATIVIDADE | I4: DIANOPOLIS | J4: SUL | K4: LD04002091 | L4: Foi feito primeiro ataque no RL 7944353028 e a equipe repassou que o dusjuntor estava desarmado. Foi feito rearme do disjuntor e so voltou a comunicção apos uns 50 minutos , o mesmo ficou bay passado em campo .
A5: 2026 | B5: ETO-TELE 00785/2026 | C5: ETO-TELE | D5: 7931863074 | E5: 46134 | F5: 46176 | G5: 74 | H5: DIANOPOLIS | I5: DIANOPOLIS | J5: SUL | K5: AL01028074 | L5: Religador 7931863074 sem comunicação , feito primeiro ataque o mesmo não retornou a comunicar. favor disponibilizar equipe para devidas tratativas
A6: 2026 | B6: ETO-TELE 00768/2026 | C6: ETO-TELE | D6: 7964803072 | E6: 46127 | F6: 46176 | G6: 72 | H6: CONCEICAO DO TOCANTINS | I6: DIANOPOLIS | J6: SUL | K6: LD01010021 | L6: senhores religador 7964803072 sem comunicaçao feito primeiro ataque sem sucesso , mesmo atende rdu de conceiçao
A7: 2026 | B7: ETO-TELE 00877/2026 | C7: ETO-TELE | D7: 7903572004 | E7: 46173 | F7: 46176 | G7: 4 | H7: ARAGUAINA | I7: ARAGUAINA | J7: NORTE | K7: AL04010004 | L7: segue rl 7903572004 sem comunicação equipe fez primeiro ataque e identificou cabos PP DE ALIMENTAÇÃO C/A oxidado e rompido, display apagado, enviar equipe para fazer correções, RL N/A urgencia devido ser de transferencia de cargas do dj 244R ARA 1 e 224R ARA 3
A8: 2025 | B8: ETO-COEP 00181/2025 | C8: ETO-COEP | D8: 7943790134 | E8: 45902 | F8: 46179 | G8: 134 | H8: ESPERANTINA | I8: AUGUSTINOPOLIS | J8: NORTE | K8: LD02109039 | L8: PARECER DMSL: Após testes realizados, foi constado que o RLG 7943790134 encontra-se com a parte ativa danificada. Favor, realizar substituição do mesmo.Troca do sistema de comunicação do equipamento
A9: 2026 | B9: ETO-TELE 00856/2026 | C9: ETO-TELE | D9: 5843904032 | E9: 46160 | F9: 46183 | G9: 32 | H9: ARAGUACU | I9: FORMOSO DO ARAGUAIA | J9: SUL | K9: AL01008032 | L9: Verificar situação de equipamento by passado, falta comissionamento ???
A10: 2026 | B10: ETO-TELE 00818/2026 | C10: ETO-TELE | D10: 5837543086 | E10: 46146 | F10: 46183 | G10: 86 | H10: MARIANOPOLIS | I10: DIVINOPOLIS | J10: CENTRO | K10: LD05062013 | L10: REGULADOR COM RELÉ APAGADO - REALIZADO PRIMEIRO ATAQUE COORDENADO COM DMSL, PORÉM NÃO FOI POSSÍVEL RESOLVER PROBLEMA.
A11: 2026 | B11: ETO-TELE 00835/2026 | C11: ETO-TELE | D11: 7957920111 | E11: 46152 | F11: 46184 | G11: 111 | H11: PEQUIZEIRO | I11: GUARAI | J11: NORTE | K11: LD03020023 | L11: REALIZADO PRIMEIRO ATAQUE O MESMO RETORNOU A FICAR SEM COMUNICAÇÃO, EQUIPE RELATA QUE NÃO ESTA CHEGANDO TENSÃO NO PAINEL, PROVAVEL FALTA DE NEUTRO DENTRO DO COMANDO.
A12: 2026 | B12: ETO-TELE 00879/2026 | C12: ETO-TELE | D12: 7957620015 | E12: 46174 | F12: 46185 | G12: 15 | H12: PEDRO AFONSO | I12: GUARAI | J12: NORTE | K12: AL02065015 | L12: PARECER DCMD:Servio realizado , favor comissionar Obra: 0712600316PARECER DMSL: A antena do rádio do RLG 7957620015 fica próximo da BT, onde a mesma veio a encostar no cabo da fase o que ocasionou um curto-circuito no rádio, que passou para todos os componentes do controle. Sendo asim se faz necessário a substituição do controle por inteiro, pois o curto danificou o rádio, módulo sim, relé e fonte. Fornecer também além do controle completo, a antena e o cabo umbilical que apresenta sinais de danos.rl 7957620015 com anomalia na antena de comunicação do mesmo, e painel não acende equipe fez primeira ataque e o mesmo não retornou comunicação, rl ficou by passado NECESSITA URGENCIA O MESMO PERTENCE CIRCUITO DO ALIMENTADOR 2 DE PEDRO AFONSO ATEDE RDU DE BOM JESUS
A13: 2026 | B13: ETO-TELE 00609/2026 | C13: ETO-TELE | D13: 7964802072 | E13: 46123 | F13: 46185 | G13: 72 | H13: CONCEICAO DO TOCANTINS | I13: DIANOPOLIS | J13: SUL | K13: LD01010021 | L13: religador 7964802072 sem comunicaçao foi feito primeiro ataque sem sucesso . rural de conceiçao
... A40: 2026 | B40: ETO-RD-AR 01131/2026 | C40: ETO-RD-AR | D40: 5844630060 | E40: 46223 | F40: 46227 | G40: 60 | H40: NOVA OLINDA | I40: COLINAS DO TOCANTINS | J40: NORTE | K40: AL01054060 | L40: 20/07 PARECER COEP: EQUIPAMENTO ENTREGUE AOS COCM´S , AGUARDO A PREVISÃO DE SUSBTITUIÇÃO NA PLANILHA E SUBSTIUIÇÃO DEPOIS SEGUIR COM O FLUXO , DESCREVER A ATIVIDADE REALIZADA E DATA, PASSAR PARA A PROTEÇÃO COM LAUDO EM ANEXO E DEPOIS COMISSIONAR14/07 PARECER COEP: EQUIPAMENTO EM ROTA DE ENTREGAPARECER DMSL: Célula da fase A encontra-se com vazamento de óleo no pé da torneira. Necessário substituição da célula.Aberto nota para verificar vazamento de óleo fase A no RT 5844630060 - RDU Nova Olinda

Sheet Criticidade por Equipamento Joa
A1: Ativo | B1: Coluna1 | C1: Tipo | D1: Localidade | E1: Polo | F1: Regional | G1: SS aberta | H1: Parecer COEP | I1: Observação | J1: Coluna2 | K1: Check de concluídas | L1: Defeito identificado | M1: Quantidade | N1: Descrição SS | O1: Premissa 1 | P1: Premissa 2 | Q1: Premissa 3 | R1: Premissa 4 | S1: Premissa 5 | T1: Premissa 6 | U1: Premissa 7 | V1: Premissa 8 | W1: Priorização | X1: Criticidade | Y1: Observação após análise | AA1: Legenda
A2: 5800090147 | B2: =_xlfn.XLOOKUP(Table2[[#This Row],[Ativo]],Joao!B:B,Joao!Z:Z) -> #N/A | C2: =MID(Table2[[#This Row],[Ativo]],1,2) -> 58 | D2: TAIPAS DO TOCANTINS | E2: DIANOPOLIS | F2: SUL | G2: =IFERROR(_xlfn.XLOOKUP(Table2[[#This Row],[Ativo]],Pendentes[COD_RELIGADOR],Pendentes[SS_ORIGINAL]),"CONCLUÍDA") -> CONCLUÍDA | H2: Cancelada em operação | K2: Ok | N2: =IFERROR(_xlfn.XLOOKUP(Table2[[#This Row],[Ativo]],Pendentes[COD_RELIGADOR],Pendentes[DESCRICAO]),"") | O2: 0 | P2: 20 | Q2: 20 | R2: 10 | S2: 10 | T2: - | U2: - | V2: - | W2: =SUM(Table2[[#This Row],[Premissa 1]:[Premissa 8]]) -> 60 | X2: Média | Y2: Atendimento de Taipas | AA2: (*) | AB2: Não houve ataque do DMSL
A3: 5800291035 | B3: =_xlfn.XLOOKUP(Table2[[#This Row],[Ativo]],Joao!B:B,Joao!Z:Z) -> #N/A | C3: =MID(Table2[[#This Row],[Ativo]],1,2) -> 58 | D3: MONTE DO CARMO | E3: PONTE ALTA TOCANTINS | F3: CENTRO | G3: =IFERROR(_xlfn.XLOOKUP(Table2[[#This Row],[Ativo]],Pendentes[COD_RELIGADOR],Pendentes[SS_ORIGINAL]),"CONCLUÍDA") -> ETO-RD-PO 00097/2026 | H3: Aguardando comissionamento | I3: Concluído Melhoria de aterramento | K3: Em andamento | L3: Melhoria de aterramento | M3: 1 | N3: PARECER DMSL: Feito testes funcionais nas 3 células do banco as mesmas corresponderam aos testes. Será necessário fazer a correção da malha de terra, baixar o banco completo pois está muito alto dificultando as atividades da equipe, substituir as 3 chaves facas do lado Fonte e as 3 do lado Carga instalar suporte inclinado das chaves para facilitar as manobras. Colocar cinta no controle RUA abaixar o mesmo, pois está muito alto e fixado com um mosquetão oval, quando retornar para colocar em operação levar 3 baterias de 7a e rele rua.Obs.: Fizeram melhoria na malha de terra, mas não está dentro do aceitável! As outras pendências continuam, favor corrigir. Equipamento ficou em operação?: Não - Equipe: Benvindo e Kaique- SS ANTIGA ETO-TELE 358/2026 | O3: 0 | P3: 20 | Q3: 20 | R3: 10 | S3: 0 | T3: - | U3: - | V3: - | W3: =SUM(Table2[[#This Row],[Premissa 1]:[Premissa 8]]) -> 50 | X3: Média | Y3: Aumento de reclamações no atendimento de Silvanópolis por Monte do Carmo no período seco
A4: 5800291077 | B4: =_xlfn.XLOOKUP(Table2[[#This Row],[Ativo]],Joao!B:B,Joao!Z:Z) -> #N/A | C4: =MID(Table2[[#This Row],[Ativo]],1,2) -> 58 | D4: GOIATINS | E4: ARAGUAINA | F4: NORTE | G4: =IFERROR(_xlfn.XLOOKUP(Table2[[#This Row],[Ativo]],Pendentes[COD_RELIGADOR],Pendentes[SS_ORIGINAL]),"CONCLUÍDA") -> CONCLUÍDA | H4: Cancelada em operação | K4: Ok | N4: =IFERROR(_xlfn.XLOOKUP(Table2[[#This Row],[Ativo]],Pendentes[COD_RELIGADOR],Pendentes[DESCRICAO]),"") | O4: 40 | P4: 20 | Q4: 20 | R4: 20 | S4: 20 | T4: - | U4: - | V4: - | W4: =SUM(Table2[[#This Row],[Premissa 1]:[Premissa 8]]) -> 120 | X4: Muito Alta | Y4: Aumento de reclamações no atendimento de Goiatins e GAs relevantes na região
A5: 5800366016 | B5: =_xlfn.XLOOKUP(Table2[[#This Row],[Ativo]],Joao!B:B,Joao!Z:Z) -> #N/A | C5: =MID(Table2[[#This Row],[Ativo]],1,2) -> 58 | D5: WANDERLANDIA | E5: TOCANTINOPOLIS | F5: NORTE | G5: =IFERROR(_xlfn.XLOOKUP(Table2[[#This Row],[Ativo]],Pendentes[COD_RELIGADOR],Pendentes[SS_ORIGINAL]),"CONCLUÍDA") -> CONCLUÍDA | H5: Cancelada em operação | K5: Ok | N5: =IFERROR(_xlfn.XLOOKUP(Table2[[#This Row],[Ativo]],Pendentes[COD_RELIGADOR],Pendentes[DESCRICAO]),"") | O5: 0 | P5: 20 | Q5: 20 | R5: 20 | S5: 10 | T5: - | U5: - | V5: - | W5: =SUM(Table2[[#This Row],[Premissa 1]:[Premissa 8]]) -> 70 | X5: Alta | Y5: Aumento de reclamações no atendimento de Wanderlândia no período seco
A6: 5800371025 | B6: =_xlfn.XLOOKUP(Table2[[#This Row],[Ativo]],Joao!B:B,Joao!Z:Z) -> 0 | C6: =MID(Table2[[#This Row],[Ativo]],1,2) -> 58 | D6: ARAPOEMA | E6: COLINAS DO TOCANTINS | F6: NORTE | G6: =IFERROR(_xlfn.XLOOKUP(Table2[[#This Row],[Ativo]],Pendentes[COD_RELIGADOR],Pendentes[SS_ORIGINAL]),"CONCLUÍDA") -> ETO-RD-GR 00766/2026 | H6: Aguardando comissionamento | I6: Concluído Reporte Kelliton | K6: Em andamento | L6: Controle | M6: 1 | N6: =IFERROR(_xlfn.XLOOKUP(Table2[[#This Row],[Ativo]],Pendentes[COD_RELIGADOR],Pendentes[DESCRICAO]),"") -> 16/07/2026 PARECER COEP: ALINHADO COM O KELLITON REALIZAR SUBSTITUIÇÃO DO CONTROLE DE TUPIRAMA, ALINHADO COM O JEAN QUE OS CABOS COMPATIBILIZADORES VÃO CHEGAR 16/08 , ATÉ ESSA DATA MANTER ESSA SS E CONTROLE RUA, DEPOIS REPASSAR PARA O DMSLPARECER COEP: AVALIAR COM O LEANDRO, PROVAVELMENTE SÓ COMPRAPARECER DMSL: Após testes foi constatado defeito nos relés da fase A e B, Modelo Toshiba TBR 1000. Se possível, substituir os relés das 3 fases por controle RUA, disponibilizar os cabos de ligação entre o tanque e o controle para possibilitar a compatibilização do equipamento. Fornecer kit de comunicação, rádio, antena, etc.Segue nota para veriifcar falha em regulador de tensão N: 5800371025 dentro S/E Arapoema , equipamento esta com 2 reles com falha marca toshiba . | O6: 0 | P6: 20 | Q6: 20 | R6: 10 | S6: 20 | T6: - | U6: - | V6: - | W6: =SUM(Table2[[#This Row],[Premissa 1]:[Premissa 8]]) -> 70 | X6: Alta | Y6: Aumento de reclamações no atendimento de Arapoema no período seco
A7: 5800438116 | B7: =_xlfn.XLOOKUP(Table2[[#This Row],[Ativo]],Joao!B:B,Joao!Z:Z) -> NÃO PRECISA REQUISITAR EQUIPAMENTO, VAMOS UTILIZAR EQ RETIRADO DE OBRA DE CONSTRUÇÃO. | C7: =MID(Table2[[#This Row],[Ativo]],1,2) -> 58 | D7: CHAPADA DA NATIVIDADE | E7: DIANOPOLIS | F7: SUL | G7: =IFERROR(_xlfn.XLOOKUP(Table2[[#This Row],[Ativo]],Pendentes[COD_RELIGADOR],Pendentes[SS_ORIGINAL]),"CONCLUÍDA") -> ETO-RD-DP 00404/2026 | H7: Concluído DCMD e DMSL | I7: Reporte Dener | K7: Em andamento | L7: Célula | M7: 2 | N7: =IFERROR(_xlfn.XLOOKUP(Table2[[#This Row],[Ativo]],Pendentes[COD_RELIGADOR],Pendentes[DESCRICAO]),"") -> 01/07 PARECER COEP: DENER INFORMOU QUE TEM AS PEÇAS SOBRESSALENTES DE OBRA PARA UTILIZAR, REPASSEREI AO POSTO DO ETO-RD-DP PARA AS TRATATIVAS, FAVOR INFORMAR PREVISÃO DE SUBSTIUIÇÃO E PREENCHER A PLANILHA ASSIM COMO PREENCHER A DESCRIÃO ANTES DE PASSAR PARA PROTEÇÃO FAZER OS AJUSTES30/06PARECER COEP: AGUARDANDO COCM'S CRIAREM OBRA PARA ENTREGA DO MATERIALSegue nota para normalizar falha em regulador N:5800438116 - Chapada da natividade .equipamento está com fase B e C travada .OBS: a fase B esta sinalizando falha , equipamento não insere TAP negativo na fase B e C , o mesmo ficou no TAP zerado e bloqueado .PARECER DMSL (18/08/2025): Foi feito teste de elevar e abaixar nas fases B e C e o mesmo só aceita elevar os taps, constatando que o mercanismo da chave reversoura polaridade está com defeito. Número de série fase B EI7030 e Número de série fase C EI7040. Substituir as fases B e C.Foi constatado que a placa F do controle está com defeito. | O7: 0 | P7: 20 | Q7: 20 | R7: 20 | S7: 0 | T7: - | U7: - | V7: - | W7: =SUM(Table2[[#This Row],[Premissa 1]:[Premissa 8]]) -> 60 | X7: Média | Y7: Atendimento da região da Engegold, Nativa, cidade Natividade e Chapada da Natividade (Fonte alternativa)
A8: 5800440256 | B8: =_xlfn.XLOOKUP(Table2[[#This Row],[Ativo]],Joao!B:B,Joao!Z:Z) -> #N/A | C8: =MID(Table2[[#This Row],[Ativo]],1,2) -> 58 | D8: MATEIROS | E8: PONTE ALTA TOCANTINS | F8: CENTRO | G8: =IFERROR(_xlfn.XLOOKUP(Table2[[#This Row],[Ativo]],Pendentes[COD_RELIGADOR],Pendentes[SS_ORIGINAL]),"CONCLUÍDA") -> CONCLUÍDA | H8: Cancelada em operação | K8: Ok | N8: =IFERROR(_xlfn.XLOOKUP(Table2[[#This Row],[Ativo]],Pendentes[COD_RELIGADOR],Pendentes[DESCRICAO]),"") | O8: 20 | P8: 20 | Q8: 20 | R8: 10 | S8: 20 | T8: - | U8: - | V8: - | W8: =SUM(Table2[[#This Row],[Premissa 1]:[Premissa 8]]) -> 90 | X8: Muito Alta | Y8: Aumento de reclamações no atendimento de São Felix e Mateiros no período seco
A9: 5800859011 | B9: =_xlfn.XLOOKUP(Table2[[#This Row],[Ativo]],Joao!B:B,Joao!Z:Z) -> 0 | C9: =MID(Table2[[#This Row],[Ativo]],1,2) -> 58 | D9: TUPIRAMA | E9: GUARAI | F9: NORTE | G9: =IFERROR(_xlfn.XLOOKUP(Table2[[#This Row],[Ativo]],Pendentes[COD_RELIGADOR],Pendentes[SS_ORIGINAL]),"CONCLUÍDA") -> ETO-RD-GR 00735/2026 | H9: Concluído DCMD | I9: Equipamento alinhado com o Jean para colocar os cabos compatibilizadores , vamos só instalar o controle e o suporte | J9: Report Kelliton | K9: Em andamento | L9: Controle | M9: 1 | N9: =IFERROR(_xlfn.XLOOKUP(Table2[[#This Row],[Ativo]],Pendentes[COD_RELIGADOR],Pendentes[DESCRICAO]),"") -> 16/07/2026 PARECER COEP: ALINHADO COM O JEAN DO DMSL E O KELLITON , KELLITON IRÁ FAZER A INSTALAÇÃO DO CONTROLE RUA E O JEAN IRÁ REALIZAR O COMISSIONAMENTO , FAZENDO A COMPATIBILIZAÇÃO DOS CABOS ASSIM COMO FICARÁ UM CONTROLE RUA NO NOSSO ESTOQUE SOBRESSALENTE PARA ATENDER O DE ARAPOEMA, ATÉ A CHEGADA DOS CABOS QUE O JEAN ME DEU REPORTE DE QUE SERIA ATÉ O DIA 16/08 , FAVOR COCM'S REALIZAREM A INSTALAÇÃO E GUARDAR CONTROLE RUA SOBRESSALENTE PARA ARAPOEMAPEÇA ENVIADA: CONTROLEPARECER DMSL: *FEEDBACK EQUIP. ESPECIAIS**Nº DO EQUIPAMENTO:* 5800859011*TIPO EQUIPAMENTO:* RT ITB *TIPO DE COMUNICAÇÃO:* Não *DATA DA MANUTENÇÃO:* 09/06/2026*SID:* 3195/2026*DESCRIÇÃO:* _ Foi identificado relé da fase C com defeito conforme orientação da supervisão e necessário realiza retrofit para instalação de controle rua.*FICOU EM OPERAÇÃO* Não*PENDÊNCIA:* Realizado Retrofit *DADOS DIVERGENTES DA PROGRAMAÇÃO:* Não*BATERIA SUBSTITUÍDA?:* Não*TIPO DE BATERIA:**EQUIPE:* Edeglan e Brunno.Observação: trocar por um controle RUA.------------------------------------------------------------------------------------------Enviar equipe do DMSL, para fazer correção no RT 5800859011, o mesmo está com o displey da fase C apagado , dificutando realizar manobras no mesmo, emvirtude disso o mesmo ficou BAY PASSADO EM CAMPO | O9: 40 | P9: 20 | Q9: 20 | R9: 10 | S9: 20 | T9: - | U9: - | V9: - | W9: =SUM(Table2[[#This Row],[Premissa 1]:[Premissa 8]]) -> 110 | X9: Muito Alta | Y9: Atendimento de parte da RDU Guaraí por fonte alternativa
A10: 5800961074 | B10: =_xlfn.XLOOKUP(Table2[[#This Row],[Ativo]],Joao!B:B,Joao!Z:Z) -> #N/A | C10: =MID(Table2[[#This Row],[Ativo]],1,2) -> 58 | D10: DIANOPOLIS | E10: DIANOPOLIS | F10: SUL | G10: =IFERROR(_xlfn.XLOOKUP(Table2[[#This Row],[Ativo]],Pendentes[COD_RELIGADOR],Pendentes[SS_ORIGINAL]),"CONCLUÍDA") -> ETO-COEP 00221/2025 | H10: Equipamento em Logistica | I10: Vamos retirar de uma obra de construção de uma linha antiga e usar na manutenção | K10: Pendente | L10: Células + melhoria de aterramento | M10: 3 | N10: =IFERROR(_xlfn.XLOOKUP(Table2[[#This Row],[Ativo]],Pendentes[COD_RELIGADOR],Pendentes[DESCRICAO]),"") -> PARECER COEP: EQUIPAMENTO SELECIONADO PARA COMPRASubstituir as 3 células- Melhoria na malha de aterramento - Melhoria no circuito de aterramento qua aterra as células.- Substituir conectores paralelos | O10: 20 | P10: 0 | Q10: 0 | R10: 20 | S10: 0 | T10: - | U10: - | V10: - | W10: =SUM(Table2[[#This Row],[Premissa 1]:[Premissa 8]]) -> 40 | X10: Média | Y10: Atendimento da COELBA e GA Alessandro Maurício (1600 kVA)
A11: 5801866013 | B11: =_xlfn.XLOOKUP(Table2[[#This Row],[Ativo]],Joao!B:B,Joao!Z:Z) -> Aguardando previsão de substituição | C11: =MID(Table2[[#This Row],[Ativo]],1,2) -> 58 | D11: PARAISO DO TOCANTINS | E11: PARAISO DO TOCANTINS | F11: CENTRO | G11: =IFERROR(_xlfn.XLOOKUP(Table2[[#This Row],[Ativo]],Pendentes[COD_RELIGADOR],Pendentes[SS_ORIGINAL]),"CONCLUÍDA") -> ETO-PROT 00151/2026 | H11: Em fase de ajustes | K11: Em andamento | L11: Célula | M11: 1 | N11: =IFERROR(_xlfn.XLOOKUP(Table2[[#This Row],[Ativo]],Pendentes[COD_RELIGADOR],Pendentes[DESCRICAO]),"") -> 15/07 PARECER COCM, FOI ATENDIDA PELA OS ETO-RD-PS 1616/2026 OBRA-021260053910/07 PARECER COEP: EQUIPAMENTO ENTREGUE AOS COCM´S FAVOR INFORMAR PRAZO DE SUBSTUIÇÃO PARA O DMSL E REPASSAR DEPOIS PARA PROTEÇÃO REALIZAR OS AJUSTES E DESCREVER NA SS O SERVIÇO REALIZADOPARECER COEP: EM PROCESSO DE ENTREGAPARECER DMSL: RT 5801866013Serviço Executado: Feito a medição da malha de terra. Identificado infiltração na caixa de passagem da célula da fase C do banco regulador de tensão, será necessário fazer a substituição da mesma! Ficar atento na hora da substituição, deverá ser substituída a célula do lado da BR.Obs.: Será necessário baixar todo o banco pelo menos um metro, as buchas estão muito próximas a parte energizada não oferecem segurança para equipe no momento do ensaio elétrico.Equipamento ficou em operação?: Não Possui nobreak: SimPossui antena: SimPossui rádio:SimPendência: SimData da bateria: Equipe: Benvindo e Kaique._______________________________________________RT 5801866013BY PASSADO DEVIDO DEFEITO EM CELULA BEMVINDO ESTEVE NO LOCAL JUNTO AO COD .NECESSARIO TRATATIVA PARA MESMA .FASE DANIFICADO C | O11: 0 | P11: 20 | Q11: 20 | R11: 20 | S11: 10 | T11: - | U11: - | V11: - | W11: =SUM(Table2[[#This Row],[Premissa 1]:[Premissa 8]]) -> 70 | X11: Alta | Y11: Atendimento da RDU Luzimangues Industrial por fonte alternativa
A12: 5803327001 | B12: =_xlfn.XLOOKUP(Table2[[#This Row],[Ativo]],Joao!B:B,Joao!Z:Z) -> #N/A | C12: =MID(Table2[[#This Row],[Ativo]],1,2) -> 58 | D12: PORTO NACIONAL | E12: PORTO NACIONAL | F12: CENTRO | G12: =IFERROR(_xlfn.XLOOKUP(Table2[[#This Row],[Ativo]],Pendentes[COD_RELIGADOR],Pendentes[SS_ORIGINAL]),"CONCLUÍDA") -> ETO-COEP 00149/2026 | H12: Em processo logístico | I12: Aguardando o Marcelo Primo gerar a obra em abertura contabil | K12: Em andamento | L12: Controle e aterramento | M12: 1 | N12: =IFERROR(_xlfn.XLOOKUP(Table2[[#This Row],[Ativo]],Pendentes[COD_RELIGADOR],Pendentes[DESCRICAO]),"") -> 01/07 PARECER COEP: FOI CONFIRMADO COM A OPERAÇÃO QUE O EQUIPAMENTO SEGUIU O FLUXO INTEIRO DE COMISSIONAMENTO, PROTEÇÃO, FAVOR EXPLICAR O QUE FOI REALIZADO E SE EQUIPAMENTO ESTÁ OPERANDO, SENÃO ESTIVER EXPLICAR O QUE FOI FEITO NELE30/06PARECER COEP: REPASSAR DIRETAMENTE PARA OS COCM'SRegulador 5803327001 fora de operação, by passado em campo com painel de comunicação com cabos desconectados tensão 13.8.parecer DMSL: Feedback Equip. EspeciaisRT 5803327001RELÉ RUASid: 4844Data: 19/09/2025Serviço realizado:*Equipamento foi remanejado, 7 km da sua localização sentido Palmas necessário comissionamento completo*Equipamento com um dos cabos umbilicais danificado.* aterramento bucha FC não esta interligada corretamente * para-raios estão no mesmo aterramento da bucha FC.* Tranques muito alto e próximo da rede não permitindo o comissionamento com segurança.* Controle alto demais tem que baixar Equipamento ficou em operação?: nãoPendência: sim, precisa comissionar completoOBS | O12: 40 | P12: 0 | Q12: 0 | R12: 20 | S12: 20 | T12: - | U12: - | V12: - | W12: =SUM(Table2[[#This Row],[Premissa 1]:[Premissa 8]]) -> 80 | X12: Alta | Y12: Em caso de perca da fonte principal é necessário esse RT para alimentação da Frísia
A13: 5820790038 | B13: =_xlfn.XLOOKUP(Table2[[#This Row],[Ativo]],Joao!B:B,Joao!Z:Z) -> #N/A | C13: =MID(Table2[[#This Row],[Ativo]],1,2) -> 58 | D13: TAGUATINGA | E13: DIANOPOLIS | F13: SUL | G13: =IFERROR(_xlfn.XLOOKUP(Table2[[#This Row],[Ativo]],Pendentes[COD_RELIGADOR],Pendentes[SS_ORIGINAL]),"CONCLUÍDA") -> CONCLUÍDA | H13: Cancelada em operação | N13: =IFERROR(_xlfn.XLOOKUP(Table2[[#This Row],[Ativo]],Pendentes[COD_RELIGADOR],Pendentes[DESCRICAO]),"") | W13: =SUM(Table2[[#This Row],[Premissa 1]:[Premissa 8]]) -> 0
A14: 5827102054 | B14: =_xlfn.XLOOKUP(Table2[[#This Row],[Ativo]],Joao!B:B,Joao!Z:Z) -> Cancelar a obra tentar vedação do equipamento Melhoria de aterramento | C14: =MID(Table2[[#This Row],[Ativo]],1,2) -> 58 | D14: PUGMIL | E14: PARAISO DO TOCANTINS | F14: CENTRO | G14: =IFERROR(_xlfn.XLOOKUP(Table2[[#This Row],[Ativo]],Pendentes[COD_RELIGADOR],Pendentes[SS_ORIGINAL]),"CONCLUÍDA") -> ETO-RD-PS 00289/2026 | H14: Aguardando comissionamento | I14: Concluído poço para melhoria de aterramento aberto | L14: Melhoria de aterramento | M14: 1 | N14: =IFERROR(_xlfn.XLOOKUP(Table2[[#This Row],[Ativo]],Pendentes[COD_RELIGADOR],Pendentes[DESCRICAO]),"") -> PARECER COEP:NÃO É POSSÍVEL RETORNAR COM O CONTROLE COMPLETO , MAS DARIA PARA FAZER A MELHORIA NA MALHA DE ATERRAMENTO , ENCAMINHANDO PARA OS COCM'S PARA REALIZAREM A MELHORIAparecer DMSL: :Nobreack com defeito, rele queimado, cabo de comunicação entre o rádio e o rele danificado, malha de aterramento está com a resistência alta!Feito reparo no cabo, substituído nobreack, e rele. Se possível retornar com controle completo pq o q está em campo teve infiltração de água, abrir chamado no scada para atualizar base do equipamento pois o mesmo está com a base antiga, fazer correção da malha de aterramento.Equipamento ficou em operação?: Não Pendência: sim, levar controle novo, fazer correção da malha de terra, levar suporte para fixar antena. OBS | O14: 0 | P14: 20 | Q14: 20 | R14: 10 | S14: 0 | T14: - | U14: - | V14: - | W14: =SUM(Table2[[#This Row],[Premissa 1]:[Premissa 8]]) -> 50 | X14: Média | Y14: Aumento de reclamações no atendimento de Pugmil no período seco
A15: 5836764032 | B15: =_xlfn.XLOOKUP(Table2[[#This Row],[Ativo]],Joao!B:B,Joao!Z:Z) -> #N/A | C15: =MID(Table2[[#This Row],[Ativo]],1,2) -> 58 | D15: ARAGUACU | E15: ALVORADA | F15: SUL | G15: =IFERROR(_xlfn.XLOOKUP(Table2[[#This Row],[Ativo]],Pendentes[COD_RELIGADOR],Pendentes[SS_ORIGINAL]),"CONCLUÍDA") -> CONCLUÍDA | H15: Cancelada em operação | K15: Ok | N15: =IFERROR(_xlfn.XLOOKUP(Table2[[#This Row],[Ativo]],Pendentes[COD_RELIGADOR],Pendentes[DESCRICAO]),"") | O15: 40 | P15: 20 | Q15: 20 | R15: 10 | S15: 20 | T15: - | U15: - | V15: - | W15: =SUM(Table2[[#This Row],[Premissa 1]:[Premissa 8]]) -> 110 | X15: Muito Alta | Y15: Aumento de reclamações no atendimento de Araguaçu no período seco
A16: 5836786094 | B16: =_xlfn.XLOOKUP(Table2[[#This Row],[Ativo]],Joao!B:B,Joao!Z:Z) -> Aguardando criação da Obra | C16: =MID(Table2[[#This Row],[Ativo]],1,2) -> 58 | D16: PEIXE | E16: PEIXE | F16: SUL | G16: =IFERROR(_xlfn.XLOOKUP(Table2[[#This Row],[Ativo]],Pendentes[COD_RELIGADOR],Pendentes[SS_ORIGINAL]),"CONCLUÍDA") -> ETO-COEP 00095/2026 | H16: Em processo logístico | I16: Previsão de entrega 16/08 | K16: Em andamento | L16: Célula | M16: 1 | N16: =IFERROR(_xlfn.XLOOKUP(Table2[[#This Row],[Ativo]],Pendentes[COD_RELIGADOR],Pendentes[DESCRICAO]),"") -> 24/07 PARECER COEP:EQUIPAMENTO EM LOGISTICA DE ENTREGA Favor levar outro regulador de tensão, pois o mesmo foi furtado em campo. | O16: 0 | P16: 0 | Q16: 0 | R16: 10 | S16: 10 | T16: - | U16: - | V16: - | W16: =SUM(Table2[[#This Row],[Premissa 1]:[Premissa 8]]) -> 20 | X16: Baixa | Y16: Atendimento de clientes rurais na LD Peixe Angical - Peixe
A17: 5839141113 | B17: =_xlfn.XLOOKUP(Table2[[#This Row],[Ativo]],Joao!B:B,Joao!Z:Z) -> #N/A | C17: =MID(Table2[[#This Row],[Ativo]],1,2) -> 58 | G17: =IFERROR(_xlfn.XLOOKUP(Table2[[#This Row],[Ativo]],Pendentes[COD_RELIGADOR],Pendentes[SS_ORIGINAL]),"CONCLUÍDA") -> ETO-TELE 00985/2026 | H17: Primeiro ataque DMSL | N17: =IFERROR(_xlfn.XLOOKUP(Table2[[#This Row],[Ativo]],Pendentes[COD_RELIGADOR],Pendentes[DESCRICAO]),"") -> Segue nota para averiguar ajuste regulador de tensão N: 5839141113 - RDU - Couto Magalhães , e verificar falha de comunicação .Equipe operacional verificou que vários transformadores urbanos estão com nível de tensão baixa .Foi feito primeiro ataque regulador está comutando normalmente as 3 fases , porém não está no nível adequado !Em campo regulador estava no Tap R1 - 02 , R2 + 01 , R3 +03Medições feitas :Transformador 5700010113 - NA: 205 NB: 206 NC: 210Transformador 5700011113 - NA: 204 NB: 206 NC: 209Transformador 5700333113 -NA: 205 NB: 207 NC: 208OBS: solicitar equipe para realizar medição aterramento , e verificar ajuste junto ao time proteção . verificar falha de comunicação no equipamento . | W17: =SUM(Table2[[#This Row],[Premissa 1]:[Premissa 8]]) -> 0
A18: 5840227063 | B18: =_xlfn.XLOOKUP(Table2[[#This Row],[Ativo]],Joao!B:B,Joao!Z:Z) -> #N/A | C18: =MID(Table2[[#This Row],[Ativo]],1,2) -> 58 | D18: BANDEIRANTES DO TOCANTINS | E18: COLINAS DO TOCANTINS | F18: NORTE | G18: =IFERROR(_xlfn.XLOOKUP(Table2[[#This Row],[Ativo]],Pendentes[COD_RELIGADOR],Pendentes[SS_ORIGINAL]),"CONCLUÍDA") -> ETO-COEP 00151/2026 | H18: Em processo de aquisição | K18: Pendente | L18: Célula | M18: 1 | N18: =IFERROR(_xlfn.XLOOKUP(Table2[[#This Row],[Ativo]],Pendentes[COD_RELIGADOR],Pendentes[DESCRICAO]),"") -> PARECER DMSL 13/07/2026: Realizados ensaios de isolação nas três células, e foi identificado curto na fase A, sendo necessário a sua substituição. Os cabos das buchas ficaram desconectados para melhor identificação no momento da sua substituiçãSEGUE PARA O DMSL AVALIAR ANTES DE SEGUIRMOS COM O SERVIÇOSEGUE PARA REALIZAR TROCA---------------------------------------------------------Boa noite,Segue SS para tratativas regulador de tensão 5840227063 fase C em curto | O18: 0 | P18: 20 | Q18: 20 | R18: 10 | S18: 10 | T18: - | U18: - | V18: - | W18: =SUM(Table2[[#This Row],[Premissa 1]:[Premissa 8]]) -> 60 | X18: Média | Y18: Atendimento da RDU Bandeirantes e clientes rurais
A19: 5841308190 | B19: =_xlfn.XLOOKUP(Table2[[#This Row],[Ativo]],Joao!B:B,Joao!Z:Z) -> #N/A | C19: =MID(Table2[[#This Row],[Ativo]],1,2) -> 58 | D19: NOVO JARDIM | E19: DIANOPOLIS | F19: SUL | G19: =IFERROR(_xlfn.XLOOKUP(Table2[[#This Row],[Ativo]],Pendentes[COD_RELIGADOR],Pendentes[SS_ORIGINAL]),"CONCLUÍDA") -> CONCLUÍDA | H19: Desmobilizado | I19: Tratativas do Allan | K19: Desmobilizado | L19: - | N19: =IFERROR(_xlfn.XLOOKUP(Table2[[#This Row],[Ativo]],Pendentes[COD_RELIGADOR],Pendentes[DESCRICAO]),"") | O19: 0 | P19: 20 | Q19: 0 | R19: 10 | S19: 0 | T19: - | U19: - | V19: - | W19: =SUM(Table2[[#This Row],[Premissa 1]:[Premissa 8]]) -> 30 | X19: Baixa | Y19: Equipamento obsoleto com a entrada da SE Serras Gerais
A20: 5844630060 | B20: =_xlfn.XLOOKUP(Table2[[#This Row],[Ativo]],Joao!B:B,Joao!Z:Z) -> Entrega 16/07 | C20: =MID(Table2[[#This Row],[Ativo]],1,2) -> 58 | D20: NOVA OLINDA | E20: COLINAS DO TOCANTINS | F20: NORTE | G20: =IFERROR(_xlfn.XLOOKUP(Table2[[#This Row],[Ativo]],Pendentes[COD_RELIGADOR],Pendentes[SS_ORIGINAL]),"CONCLUÍDA") -> CONCLUÍDA | H20: Equipamento entregue aos COCM's | I20: Previsão de entrega 20/07 // Foi entregue a eles verificar o porque eles baixaram | K20: Em andamento | L20: Célula | M20: 1 | N20: =IFERROR(_xlfn.XLOOKUP(Table2[[#This Row],[Ativo]],Pendentes[COD_RELIGADOR],Pendentes[DESCRICAO]),"") | O20: 20 | P20: 0 | Q20: 0 | R20: 10 | S20: 0 | T20: - | U20: - | V20: - | W20: =SUM(Table2[[#This Row],[Premissa 1]:[Premissa 8]]) -> 30 | X20: Baixa | Y20: Atendimento dos ramais PA Remansão e Água Branca
A21: 5846328094 | B21: =_xlfn.XLOOKUP(Table2[[#This Row],[Ativo]],Joao!B:B,Joao!Z:Z) -> #N/A | C21: =MID(Table2[[#This Row],[Ativo]],1,2) -> 58 | D21: PEIXE | E21: PEIXE | F21: SUL | G21: =IFERROR(_xlfn.XLOOKUP(Table2[[#This Row],[Ativo]],Pendentes[COD_RELIGADOR],Pendentes[SS_ORIGINAL]),"CONCLUÍDA") -> ETO-TELE 00986/2026 | H21: Aguardando comissionamento | K21: Em andamento | L21: Melhoria de aterramento | M21: 1 | N21: =IFERROR(_xlfn.XLOOKUP(Table2[[#This Row],[Ativo]],Pendentes[COD_RELIGADOR],Pendentes[DESCRICAO]),"") -> COCM SUL - 07/07/2026 - FOI REALIZADO MELHORIA DE ATERRAMENTO E FEITO A MANUTENÇÕES E TODAS AS CHAVES E SUBSTITUIDO OS CONECTORES.PARECER COEP: MELHORIA DE ATERRAMENTO É COCM'S, FAVOR ENCAMINHAR DIRETAMENTE PARA ELES, COCM'S REALIZAR MELHORIA DE ATERRAMENTO POR FAVORPor genteliiza verificar RT 5846328094 situação de equipamento, se encontra by passado em campoPARECER DMSL:Favor, realizar melhoria de aterramento que se encontra alta e substituir todos os conectores das buchas por conectores estrangulador. | O21: 0 | P21: 20 | Q21: 20 | R21: 10 | S21: 10 | T21: - | U21: - | V21: - | W21: =SUM(Table2[[#This Row],[Premissa 1]:[Premissa 8]]) -> 60 | X21: Média | Y21: Atendimento da RDU Sucupira e clientes rurais
A22: 5848305116 | B22: =_xlfn.XLOOKUP(Table2[[#This Row],[Ativo]],Joao!B:B,Joao!Z:Z) -> #N/A | C22: =MID(Table2[[#This Row],[Ativo]],1,2) -> 58 | G22: =IFERROR(_xlfn.XLOOKUP(Table2[[#This Row],[Ativo]],Pendentes[COD_RELIGADOR],Pendentes[SS_ORIGINAL]),"CONCLUÍDA") -> ETO-TELE 01005/2026 | H22: Primeiro ataque DMSL | N22: =IFERROR(_xlfn.XLOOKUP(Table2[[#This Row],[Ativo]],Pendentes[COD_RELIGADOR],Pendentes[DESCRICAO]),"") -> Segue nota para verificar falha e constantes travamento no regulador de tensão 5848305116 - chapada da Natividade .Foi identificado que regulador está com divergência em TAP"S analógico e digital .Foi executado comandos no relé para comutar TAP na fase AB foi executado no relé , porém não alterou analógico e nem fez barulho algum , a princípio a fase C está normal . | W22: =SUM(Table2[[#This Row],[Premissa 1]:[Premissa 8]]) -> 0
A23: 5850308009 | B23: =_xlfn.XLOOKUP(Table2[[#This Row],[Ativo]],Joao!B:B,Joao!Z:Z) -> Equipamento em operação em campo de acordo com a visita do Luanderson tem fotos Equipamento já em operação , realocar controle de Regulador para Arapoema 5800371025 | C23: =MID(Table2[[#This Row],[Ativo]],1,2) -> 58 | D23: GUARAI | E23: GUARAI | F23: NORTE | G23: =IFERROR(_xlfn.XLOOKUP(Table2[[#This Row],[Ativo]],Pendentes[COD_RELIGADOR],Pendentes[SS_ORIGINAL]),"CONCLUÍDA") -> CONCLUÍDA | H23: Cancelada em operação | K23: Ok | N23: =IFERROR(_xlfn.XLOOKUP(Table2[[#This Row],[Ativo]],Pendentes[COD_RELIGADOR],Pendentes[DESCRICAO]),"") | O23: 0 | P23: 20 | Q23: 20 | R23: 0 | S23: 10 | T23: - | U23: - | V23: - | W23: =SUM(Table2[[#This Row],[Premissa 1]:[Premissa 8]]) -> 50 | X23: Média | Y23: Atendimento de parte da RDU de Guaraí e ramal da PRF/Repetidora
A24: 5851753086 | B24: =_xlfn.XLOOKUP(Table2[[#This Row],[Ativo]],Joao!B:B,Joao!Z:Z) -> #N/A | C24: =MID(Table2[[#This Row],[Ativo]],1,2) -> 58 | D24: MARIANOPOLIS | E24: DIVINOPOLIS | F24: CENTRO | G24: =IFERROR(_xlfn.XLOOKUP(Table2[[#This Row],[Ativo]],Pendentes[COD_RELIGADOR],Pendentes[SS_ORIGINAL]),"CONCLUÍDA") -> ETO-TELE 00881/2026 | H24: Aguardando comissionamento | K24: Em andamento | L24: Melhoria de aterramento | M24: 1 | N24: =IFERROR(_xlfn.XLOOKUP(Table2[[#This Row],[Ativo]],Pendentes[COD_RELIGADOR],Pendentes[DESCRICAO]),"") -> PARECER DMSL: FAVOR SOLUCIONAR PENDENCIAS RT: 5851753086Relé R.U.A Data: _19/05/2026Sid: 2740/2026Possui rádio?: SimPossui antena?: SimPossui módulo nobreak?: SimServiço Executado: * Feito testes no equipamento,o mesmo está normal.* Será necessário fazer melhorias na malha de terra e colocar em operação.Equipamento ficou em operação? Não Pendência: Sim. É necessário fazer melhorias na malha de aterramento.Bateria(s) substituída(s)? _nao Data Fabricação/Instalação da(s) bateria(s): 12/2025Equipe: Jean e BenvindoPARECER DCMD: FEITO MELHORIA NA MALHA DO ATERRAMENTO, FAVOR ENVIAR EQUIPE PARA COLOCA-LO EM OPERAÇÃORT 5851753086MESMO ESTA BY-PASSADO EM CAMPO EQUIPE SINERGIA 086OP01 ESTEVE NO LOCAL APARENTIMENTE SEM DEFEITO APARENTE MESMO FOI BY PASSADO POR TER TIRADO LINHA.DESDE ENTAO MESMO NAO VOLTOU PARA OPERAÇÃO .FAVOR VERIFICAR PARA TESTES POSSIVEIS .PARA QUE O MESMO VOLTA COM DISPONIBILIDADE PARA OPERAÇÃO . | O24: 0 | P24: 20 | Q24: 20 | R24: 10 | S24: 10 | T24: - | U24: - | V24: - | W24: =SUM(Table2[[#This Row],[Premissa 1]:[Premissa 8]]) -> 60 | X24: Média | Y24: Atendimento da RDU Marianópolis e clientes rurais
A25: 5853360007 | B25: =_xlfn.XLOOKUP(Table2[[#This Row],[Ativo]],Joao!B:B,Joao!Z:Z) -> Melhoria de aterramento | C25: =MID(Table2[[#This Row],[Ativo]],1,2) -> 58 | D25: MIRACEMA DO TOCANTINS | E25: MIRACEMA DO TOCANTINS | F25: CENTRO | G25: =IFERROR(_xlfn.XLOOKUP(Table2[[#This Row],[Ativo]],Pendentes[COD_RELIGADOR],Pendentes[SS_ORIGINAL]),"CONCLUÍDA") -> ETO-RD-PS 00323/2025 | H25: Problema na autorização de passagem | I25: Cliente não autorizou entrar na propriedade | L25: Melhoria de aterramento | M25: 1 | N25: =IFERROR(_xlfn.XLOOKUP(Table2[[#This Row],[Ativo]],Pendentes[COD_RELIGADOR],Pendentes[DESCRICAO]),"") -> REALIZAR TESTES NO EQUIPAMENTO E CONFERIR MEDIÇÕES DA MALHA DE ATERRAMENTO. ESTANDO OK, COMISSIONAR EQUIPAMENTO E COLOCA-LO EM OPERAÇÃO.AJUSTES DISPONIVEIS NO APP DA PROTEÇÃdmsl : N° do Equipamento:*RT 5853360007 MIRACEMASID: 2493/2025Data: 13/05/2025Serviço Executado Provavelmente ocorreu uma descarga no equipamento comprometendo a malha!Será necessário fazer melhoria da malha de aterramento, fazer toda interligação da mesma! Feito ensaios de isolação das 3 células do equipamento, isolação está ok, quando retornar para colocar em operação levar 3 baterias de 7a.Equipamento ficou em operação?: Não Equipe: Benvindo e Jardel | O25: 0 | P25: 20 | Q25: 20 | R25: 10 | S25: 20 | T25: - | U25: - | V25: - | W25: =SUM(Table2[[#This Row],[Premissa 1]:[Premissa 8]]) -> 70 | X25: Alta | Y25: Aumento de reclamações no atendimento de Miracema no período seco
A26: 5854566043 | B26: =_xlfn.XLOOKUP(Table2[[#This Row],[Ativo]],Joao!B:B,Joao!Z:Z) -> Aguardando previsão de substituição | C26: =MID(Table2[[#This Row],[Ativo]],1,2) -> 58 | D26: SILVANOPOLIS | E26: PORTO NACIONAL | F26: CENTRO | G26: =IFERROR(_xlfn.XLOOKUP(Table2[[#This Row],[Ativo]],Pendentes[COD_RELIGADOR],Pendentes[SS_ORIGINAL]),"CONCLUÍDA") -> ETO-RD-PO 00213/2026 | H26: Concluído DCMD24/07 | J26: Report Edson | K26: Em andamento | L26: Célula | M26: 1 | N26: =IFERROR(_xlfn.XLOOKUP(Table2[[#This Row],[Ativo]],Pendentes[COD_RELIGADOR],Pendentes[DESCRICAO]),"") -> 22/07/2026 PARECER COEP: EQUIPAMENTO ENTREGUE AOS COCM´SPRAZO DE 7 DIAS CONTANDO O SLA.PARECER COEP: EQUIPAMENTO ENTREGUE AOS COCM´S FAVOR SUSBSTTUIR , E AGUARDO O PRAZO DE PREVISÃO DE SUBSTIUIÇÃOboa noite,segue SS para as devidas tratativas com equipe de manutenção com apoio de equipe de linha viva substituir regulador de tensão 5854566043 queimado célula fase c, LD Porto / Silvanópolis mesmo deverá ser substituído com apoio de equipe de linha viva PARECER DMSL: Foi realizado inspeção visual e ensaios de isolação, relação de transformação e resistência de enrolamento. A fase B está danificada e será necessário substituir a mesma. Malha de aterramento está relativamente boa e conectada. Fase A e C passaram nos ensaios. Substituir fase B. | O26: 40 | P26: 20 | Q26: 20 | R26: 10 | S26: 20 | T26: - | U26: - | V26: - | W26: =SUM(Table2[[#This Row],[Premissa 1]:[Premissa 8]]) -> 110 | X26: Muito Alta | Y26: Aumento de reclamações no atendimento de Silvanópolis por Porto Nacional no período seco (Outra fonte com defeito também)
A27: 5855411017 | B27: =_xlfn.XLOOKUP(Table2[[#This Row],[Ativo]],Joao!B:B,Joao!Z:Z) -> Aguardando previsão de substituição | C27: =MID(Table2[[#This Row],[Ativo]],1,2) -> 58 | D27: BARROLANDIA | E27: MIRACEMA DO TOCANTINS | F27: CENTRO | G27: =IFERROR(_xlfn.XLOOKUP(Table2[[#This Row],[Ativo]],Pendentes[COD_RELIGADOR],Pendentes[SS_ORIGINAL]),"CONCLUÍDA") -> ETO-COEP 00156/2026 | H27: Em processo de aquisição | K27: Pendente | L27: Controle | M27: 1 | N27: =IFERROR(_xlfn.XLOOKUP(Table2[[#This Row],[Ativo]],Pendentes[COD_RELIGADOR],Pendentes[DESCRICAO]),"") -> 20/07 PARECER COCM: NÃO RECEBEMOS MATERIAL10/07 PARECER COEP: EQUIPAMENTO ENTREGUE AOS COCM´S FAVOR INFORMAR PRAZO DE SUBSTUIÇÃO PARA O DMSL E REPASSAR DEPOIS PARA PROTEÇÃO REALIZAR OS AJUSTES E DESCREVER NA SS O SERVIÇO REALIZADOPARECER COEP: EQUIPAMENTO EM ROTA DE ENTREGASEM COMUNICAÇÃO, FALHA DE ALIMENTAÇÃO - REALIZADO PRIMEIRO ATAQUE SEM SUCESSO.PARECER DMSL: 17/09/2025 Equipamento ficou em operação? Não Pendência: sim. Equipamento ficou Bay passado levar controle COMPLETO para trocar. ellisfran | O27: 0 | P27: 0 | Q27: 0 | R27: 10 | S27: 20 | T27: - | U27: - | V27: - | W27: =SUM(Table2[[#This Row],[Premissa 1]:[Premissa 8]]) -> 30 | X27: Baixa | Y27: Atendimento do Assentamento Irmã Adelaide
A28: 5856070091 | B28: =_xlfn.XLOOKUP(Table2[[#This Row],[Ativo]],Joao!B:B,Joao!Z:Z) -> REQUISITAR 03 PEÇAS POIS 02 PÇ FOI RETIRADA PARA INSTALAÇÃO EM OBRA DE CONSTRUÇÃO. | C28: =MID(Table2[[#This Row],[Ativo]],1,2) -> 58 | D28: ALMAS | E28: DIANOPOLIS | F28: SUL | G28: =IFERROR(_xlfn.XLOOKUP(Table2[[#This Row],[Ativo]],Pendentes[COD_RELIGADOR],Pendentes[SS_ORIGINAL]),"CONCLUÍDA") -> ETO-RD-DP 00479/2026 | H28: Equipamento entregue ao COCM | I28: Previsão de substituição 07/08// Nova previsão de entrega 21/08 se a DB Machado for para o Sul | K28: Em andamento | L28: Células + controle | M28: 3 | N28: =IFERROR(_xlfn.XLOOKUP(Table2[[#This Row],[Ativo]],Pendentes[COD_RELIGADOR],Pendentes[DESCRICAO]),"") -> PARECER DMSL: não foi regularizado a instalação do equipamento, nota repassada conforme alinhado com o supervisor.____________________________________________COCMS 26.03.26. SS REPASSADA PARA COEP PROVIDENCIAR MATERIAL. NÃO TEMOS AS PÇ EM ESTOQUE PARA FAZER A SUBSTITUIÇÃO. Solicitação de serviço para reposição de equipamentos furtados .COEP: Equipamento fornecido ao COCM-S para regularização.COCMS: Equipamento substituido conforme solicitado. Gentileza comissionar.PARECER DA PROTEÇÃO:SEGUE NOTA REPASSADA PARA DMSL COMISSIONAR.ENG° IRLLEY CASTELO BRANCOPARECER DMSL(23/09/2025): Feito a parte de comunicação, fechando enlace, configuração do rádio GE. Feito a medição de aterramento. Após uma inspeção, foi identificado que o regulador de tensão está instalado errado, carga está para o lado de fonte e fonte está do lado de carga. O certo é a fonte vim de almas, atualmente está vindo de natividade. Favor fazer a instalação correta. | O28: 40 | P28: 20 | Q28: 20 | R28: 20 | S28: 0 | T28: - | U28: - | V28: - | W28: =SUM(Table2[[#This Row],[Premissa 1]:[Premissa 8]]) -> 100 | X28: Muito Alta | Y28: Atendimento da região da Engegold, Nativa, cidade Natividade e Chapada da Natividade
A29: 5856156091 | B29: =_xlfn.XLOOKUP(Table2[[#This Row],[Ativo]],Joao!B:B,Joao!Z:Z) -> #N/A | C29: =MID(Table2[[#This Row],[Ativo]],1,2) -> 58 | D29: ALMAS | E29: DIANOPOLIS | F29: SUL | G29: =IFERROR(_xlfn.XLOOKUP(Table2[[#This Row],[Ativo]],Pendentes[COD_RELIGADOR],Pendentes[SS_ORIGINAL]),"CONCLUÍDA") -> ETO-RD-DP 00403/2026 | H29: Em processo de aquisição | I29: Furtado 2 vezes | K29: Pendente | L29: Células + controle | M29: 3 | N29: =IFERROR(_xlfn.XLOOKUP(Table2[[#This Row],[Ativo]],Pendentes[COD_RELIGADOR],Pendentes[DESCRICAO]),"") -> DCMD 26.03.2026. SS REPASSADA PARA COEP PROVIDENCIAR MATERIAL. NÃO TEMOS O MATERIAL EM ESTOQUE PARA SUBSTITUIÇÃO. COEP: Equipamento fornecido ao COCM-S para regularização.PARECER COEP: EQUIPAMENTOS JÁ FORNECIDOS PARA OS COCM'S PARA REGULARIZAÇÃOPARECER DA PROTEÇÃO:EQUIPAMENTOS FURTADOS. PARA AQUISIÇÃO DAS CELULAS DE REPOSIÇÃO, FAVOR CONSULTAR OS DADOS DE PLACA EM ANEXO.PARECER DA PROTEÇÃO:COMISISONAR RT 5856156091 LD DIANOPOLIS A NATIVIDADE. NECESSARIO REALIZAR MEDIÇÕES DA RESISTENCIA DA MALHA DE ATERRAMENTO.AJUSTES DISPONIVEIS NO APP DA PROTEÇÃO.RELIGADOR N° 5856156091 INSTALADO NA OBRA 0502400526 GENTILEZA, REALIZAR O COMISSIONAMENTO. LAUDO EM ANEXO. COORD EO: 899501, 8714782 | O29: 0 | P29: 0 | Q29: 0 | R29: 0 | S29: 0 | T29: - | U29: - | V29: - | W29: =SUM(Table2[[#This Row],[Premissa 1]:[Premissa 8]]) -> 0 | X29: Baixa | Y29: Equipamento novo furtado antes de ser colocado em operação
A30: 5858783119 | B30: =_xlfn.XLOOKUP(Table2[[#This Row],[Ativo]],Joao!B:B,Joao!Z:Z) -> Redirecionado para atender 5854566043 e 5862236091 | C30: =MID(Table2[[#This Row],[Ativo]],1,2) -> 58 | D30: SAO BENTO DO TOCANTINS | E30: TOCANTINOPOLIS | F30: NORTE | G30: =IFERROR(_xlfn.XLOOKUP(Table2[[#This Row],[Ativo]],Pendentes[COD_RELIGADOR],Pendentes[SS_ORIGINAL]),"CONCLUÍDA") -> ETO-TELE 01032/2026 | H30: Aguardando parecer DMSL | K30: Pendente | N30: =IFERROR(_xlfn.XLOOKUP(Table2[[#This Row],[Ativo]],Pendentes[COD_RELIGADOR],Pendentes[DESCRICAO]),"") -> 27/07/2026 PARECER COEP: FIZEMOS UMA VISITA AO EQUIPAMENTO , EQUIPAMENTO SE ENCONTRA EM OPERAÇÃO E SEM SINAL DE AVARIA FAVOR AVALIAR PARECER DMSL A SS FOTOS COM O LUANDERSSON OU JOAO ANTONIO LAGARES 20/07 PARECER COEP: EQUIPAMENTO SELECIONADO PARA COMPRA , DEVIDO AO ERRO NA INSTALAÇÃO E O FURTOPARECER DMSL: 16/06/2025-SERVIÇO EXECUTADO: Ao chegar no equipamento para realizar comissionamento, foi constatato que as 3 células estavam com a tampa de inspeção abertas e sem os para-raios. Constatado também que foi furtado todo o óleo isolante das 3 células, sendo necessário a substituição das 3 células. FICOU EM OPERAÇÃO?: Não PENDÊNCIA: Substituir as 3 células | O30: 0 | P30: 0 | Q30: 0 | R30: 0 | S30: 0 | T30: - | U30: - | V30: - | W30: =SUM(Table2[[#This Row],[Premissa 1]:[Premissa 8]]) -> 0 | X30: Baixa | Y30: Equipamento não inserido no SCADA
A31: 5862236091 | B31: =_xlfn.XLOOKUP(Table2[[#This Row],[Ativo]],Joao!B:B,Joao!Z:Z) -> #N/A | C31: =MID(Table2[[#This Row],[Ativo]],1,2) -> 58 | D31: ALMAS | E31: DIANOPOLIS | F31: SUL | G31: =IFERROR(_xlfn.XLOOKUP(Table2[[#This Row],[Ativo]],Pendentes[COD_RELIGADOR],Pendentes[SS_ORIGINAL]),"CONCLUÍDA") -> ETO-RD-DP 00457/2026 | H31: Em processo de aquisição | K31: Pendente | L31: Célula | M31: 1 | N31: =IFERROR(_xlfn.XLOOKUP(Table2[[#This Row],[Ativo]],Pendentes[COD_RELIGADOR],Pendentes[DESCRICAO]),"") -> 20/07 PARECER COEP: EQUIPAMENTO ENTREGUE , FAVOR EDITAR A SS COM A DATA PREVISTA DE SUBSTITUIÇÃO NO PARECER DOS COCM´S Realizar substituição da FASE B.Célula da fase B estava com a tampa do contador de tape aberta, pegou chuva e molhou os contatos danificando a peça toda. | O31: 0 | P31: 0 | Q31: 0 | R31: 20 | S31: 0 | T31: - | U31: - | V31: - | W31: =SUM(Table2[[#This Row],[Premissa 1]:[Premissa 8]]) -> 20 | X31: Baixa | Y31: Atendimento da LD Vale Rio Doce (Nova Aura Mineradora)
A32: 5865120195 | B32: =_xlfn.XLOOKUP(Table2[[#This Row],[Ativo]],Joao!B:B,Joao!Z:Z) -> #N/A | C32: =MID(Table2[[#This Row],[Ativo]],1,2) -> 58 | D32: CENTENARIO | E32: GUARAI | F32: NORTE | G32: =IFERROR(_xlfn.XLOOKUP(Table2[[#This Row],[Ativo]],Pendentes[COD_RELIGADOR],Pendentes[SS_ORIGINAL]),"CONCLUÍDA") -> ETO-PROT 00144/2026 | H32: Em fase de ajustes | K32: Em andamento | L32: Melhoria de aterramento | M32: 1 | N32: =IFERROR(_xlfn.XLOOKUP(Table2[[#This Row],[Ativo]],Pendentes[COD_RELIGADOR],Pendentes[DESCRICAO]),"") -> PARECER DMSL:PENDÊNCIA: Realizar melhoria no aterramento por ser tratar de um terreno muito arenoso, e há pendências por parte do time da proteção, os ajustes do RT não estão disponíveis para inserção no referido equipamento.DATA DA MANUTENÇÃO: 12/03/202EQUIPE: Brunno e Edeglan.***********************PARECER DA PROTEÇÃO:FAVOR COMISSIONAR REGULADOR 5865120195 – LD Santa Maria Ramal Centenário e Recursolândia – 34,5kV. AJUSTE REALIZADO, DISPONÍVEL NO APP DA PROTEÇÃO.*********************** INSTALADO NA OBRA 0702400720 GENTILEZA, REALIZAR O COMISSIONAMENTO.LAUDO EM ANEXO.COORD EO: 889017, 901685708-07-2026 PARECER: FOI FEITO A MELHORIA NO REGULADOR CONFORME FOTOS EM ANEXO. | O32: 20 | P32: 20 | Q32: 20 | R32: 10 | S32: 0 | T32: - | U32: - | V32: - | W32: =SUM(Table2[[#This Row],[Premissa 1]:[Premissa 8]]) -> 70 | X32: Alta | Y32: Atendimento das RDUs de Centenário, Recursolândia e clientes rurais
A33: 7900001096 | B33: =_xlfn.XLOOKUP(Table2[[#This Row],[Ativo]],Joao!B:B,Joao!Z:Z) -> #N/A | C33: =MID(Table2[[#This Row],[Ativo]],1,2) -> 79 | G33: =IFERROR(_xlfn.XLOOKUP(Table2[[#This Row],[Ativo]],Pendentes[COD_RELIGADOR],Pendentes[SS_ORIGINAL]),"CONCLUÍDA") -> ETO-TELE 01018/2026 | H33: Primeiro ataque DMSL | N33: =IFERROR(_xlfn.XLOOKUP(Table2[[#This Row],[Ativo]],Pendentes[COD_RELIGADOR],Pendentes[DESCRICAO]),"") -> Segue nota para falha de comunicação no religador 7900001096 - Rural - Pindorama .Equipamento perdeu a comunicação quando faltou CA , porém mesmo ao retorna o CA não retornou a comunicação !Feito primeiro ataque sem sucesso ! | W33: =SUM(Table2[[#This Row],[Premissa 1]:[Premissa 8]]) -> 0
A34: 7900018004 | B34: =_xlfn.XLOOKUP(Table2[[#This Row],[Ativo]],Joao!B:B,Joao!Z:Z) -> Concluido | C34: =MID(Table2[[#This Row],[Ativo]],1,2) -> 79 | D34: ARAGUAINA | E34: ARAGUAINA | F34: NORTE | G34: =IFERROR(_xlfn.XLOOKUP(Table2[[#This Row],[Ativo]],Pendentes[COD_RELIGADOR],Pendentes[SS_ORIGINAL]),"CONCLUÍDA") -> CONCLUÍDA | H34: Concluído DCMD | I34: Reporte do Wander | K34: Ok | N34: =IFERROR(_xlfn.XLOOKUP(Table2[[#This Row],[Ativo]],Pendentes[COD_RELIGADOR],Pendentes[DESCRICAO]),"") | O34: 15 | P34: 10 | Q34: 5 | R34: 15 | S34: 0 | T34: 10 | U34: 0 | V34: 0 | W34: =SUM(Table2[[#This Row],[Premissa 1]:[Premissa 8]]) -> 55 | X34: Alta | Y34: Transferência de Aragominas, 3 fontes operando
A35: 7900117013 | B35: =_xlfn.XLOOKUP(Table2[[#This Row],[Ativo]],Joao!B:B,Joao!Z:Z) -> Calendário logistco vai sair hoje 29/05/2026, assim que tiver rota de entrga avisamos | C35: =MID(Table2[[#This Row],[Ativo]],1,2) -> 79 | D35: PARAISO DO TOCANTINS | E35: PARAISO DO TOCANTINS | F35: CENTRO | G35: =IFERROR(_xlfn.XLOOKUP(Table2[[#This Row],[Ativo]],Pendentes[COD_RELIGADOR],Pendentes[SS_ORIGINAL]),"CONCLUÍDA") -> ETO-PROT 00154/2026 | H35: Em fase de ajustes | K35: Em andamento | L35: Controle | M35: 1 | N35: =IFERROR(_xlfn.XLOOKUP(Table2[[#This Row],[Ativo]],Pendentes[COD_RELIGADOR],Pendentes[DESCRICAO]),"") -> 15/07 PARECER COCM: EQUIPAMENTO FOI SUBSTITUÍDO OBRA 021260042210/07 PARECER COEP: EQUIPAMENTO ENTREGUE AOS COCM´S FAVOR INFORMAR PRAZO DE SUBSTUIÇÃO PARA O DMSL E REPASSAR DEPOIS PARA PROTEÇÃO REALIZAR OS AJUSTES E DESCREVER NA SS O SERVIÇO REALIZADOPARECER COEP: PREVISÃO DE ENTREGA AOS COCM'S 01/07Segue nota para correção de anomalia e provável substituição de religador , religador 7900117013 -RDU - Paraiso .OBS: equipe DMSL Elisfran estava atualizando firmware no equipamento , porém relé parou de funcionar devido essa atualização , sendo necessário sua substituição .em campo o modelo e cooper Form6 , segundo tecnico deve ser substituído por um Noja .Repassado para o COEP para aquisição do equipamento e posterior repasse para o COCM. | O35: 15 | P35: 20 | Q35: 15 | R35: 15 | S35: 15 | T35: 0 | U35: 0 | V35: 15 | W35: =SUM(Table2[[#This Row],[Premissa 1]:[Premissa 8]]) -> 95 | X35: Muito Alta | Y35: Transferência do 214R de Paraíso I, Centro Comercial de Paraíso
A36: 7900230155 | B36: =_xlfn.XLOOKUP(Table2[[#This Row],[Ativo]],Joao!B:B,Joao!Z:Z) -> Concluido | C36: =MID(Table2[[#This Row],[Ativo]],1,2) -> 79 | D36: PALMEIRANTE | E36: COLINAS DO TOCANTINS | F36: NORTE | G36: =IFERROR(_xlfn.XLOOKUP(Table2[[#This Row],[Ativo]],Pendentes[COD_RELIGADOR],Pendentes[SS_ORIGINAL]),"CONCLUÍDA") -> ETO-PROT 00143/2026 | H36: Em fase de ajustes | I36: Reporte Wandersson | K36: Em andamento | L36: Tanque e PR do trafo e chave | M36: 1 | N36: =IFERROR(_xlfn.XLOOKUP(Table2[[#This Row],[Ativo]],Pendentes[COD_RELIGADOR],Pendentes[DESCRICAO]),"") -> 07/07/2026 PARECER COEP: MATERIAL ENVIADO , CONFORME ALINHANDO COM O WANDER REALIZAR SUBSTIUIÇÂO DO EQUIPAMENTO, FAVOR ESCREVER PARECER COCM ANTES DE PASSAR PARA PROTEÇÂO, DO QUE FOI REALIZADO01/07/2026 PARECER COEP: PROBLEMA NO ENVIO DO MATERIAL PARECER DMSL: Religador está com o tanque danificado. Não responde a comandos abertura e fechamento local ou remoto, pois está com sinal de curto circuito. Necessário trocar o equipamento. Para raio do trafo está queimado. Chave de saída da fase C está com o olhal quebrado, necessário substituir a chave. Equipamento ficou bypassado em campo. Aberto entrada e saída, com exceção da fase C de saída que ficou fechada. Favor, substituir equipamento completo por NOJA RC10 e sanar demais pendencias.Senhores Favor verificar RL 7900230155 o mesmo sinalizou aberto no SCADA porem a cidade de Palmeirante estava normal , feito um reset no rl e o mesmo subiu fechado.08/07/2026 PARECER DCMD: EQUIPE ETO-LVGR01 DE GUARAI ESTEVE NO RL 7900230155 DIA 25-06-2026 E FEZ TODAS A PENDENCIAS DO RL, OBS: EQUIPE SO NAO CONECTOU O CABO DO TRAFO NO RL. RL ESTA PRONTO PARA O COMISSIONAMENTO | O36: 15 | P36: 20 | Q36: 5 | R36: 15 | S36: 0 | T36: 10 | U36: 0 | V36: 15 | W36: =SUM(Table2[[#This Row],[Premissa 1]:[Premissa 8]]) -> 80 | X36: Muito Alta | Y36: Fonte principal de Palmeirante, RL de transferência operando
A37: 7900259096 | B37: =_xlfn.XLOOKUP(Table2[[#This Row],[Ativo]],Joao!B:B,Joao!Z:Z) -> #N/A | C37: =MID(Table2[[#This Row],[Ativo]],1,2) -> 79 | G37: =IFERROR(_xlfn.XLOOKUP(Table2[[#This Row],[Ativo]],Pendentes[COD_RELIGADOR],Pendentes[SS_ORIGINAL]),"CONCLUÍDA") -> ETO-TELE 01021/2026 | H37: Primeiro ataque DMSL | N37: =IFERROR(_xlfn.XLOOKUP(Table2[[#This Row],[Ativo]],Pendentes[COD_RELIGADOR],Pendentes[DESCRICAO]),"") -> Boa noite .Segue nota para verificar falha de comunicação no religador 7900259096 - Pindorama .Equipamento perde a comunicação quando falta CA ! | W37: =SUM(Table2[[#This Row],[Premissa 1]:[Premissa 8]]) -> 0
A38: 7900451096 | B38: =_xlfn.XLOOKUP(Table2[[#This Row],[Ativo]],Joao!B:B,Joao!Z:Z) -> #N/A | C38: =MID(Table2[[#This Row],[Ativo]],1,2) -> 79 | G38: =IFERROR(_xlfn.XLOOKUP(Table2[[#This Row],[Ativo]],Pendentes[COD_RELIGADOR],Pendentes[SS_ORIGINAL]),"CONCLUÍDA") -> ETO-TELE 01020/2026 | H38: Primeiro ataque DMSL | N38: =IFERROR(_xlfn.XLOOKUP(Table2[[#This Row],[Ativo]],Pendentes[COD_RELIGADOR],Pendentes[DESCRICAO]),"") -> Segue nota para verificar falha de comunicação no religador 7900451096 - Rural - Pindorama .Equipamento perde a comunicação quando falta CA ! | W38: =SUM(Table2[[#This Row],[Premissa 1]:[Premissa 8]]) -> 0
