Workbook

Sheet Orçamento
A1: Criticidade | B1: (Tudo) | K1: Equipamento | L1: Backlog | M1: Resolvidos | O1: Entrantes | P1: Pendentes | Q1: Forecast
K2: Religador | L2: 53 | M2: 45 | O2: 35 | P2: =O2+L2-M2 -> 43
A3: Tipo | B3: Status | C3: Contagem de Ativo | D3: Soma de Orçamento Total | K3: Regulador | L3: 27 | M3: 26 | O3: 10 | P3: =O3+L3-M3 -> 11
A4: 58 | B4: Avaliar compra | C4: 2 | D4: 989173.2 | K4: Banco Capacitor | L4: 47 | M4: 1 | O4: 0 | P4: 46
B5: Em logistica (N1>N3) | C5: 6 | D5: 691664.7 | G5: Compras
B6: Reforma | C6: 2 | D6: 213808.1 | G6: 94500
B7: Em execução | C7: 2 | D7: 509586.6 | G7: 87683
A8: 79 | B8: Avaliar compra | C8: 20 | D8: 1229422.1 | E8: 1229422.1 | G8: 398547
B9: Gerado PMA | C9: 20 | D9: 1320983.7 | G9: =SUM(G6:G8) -> 580730 | J9: RL
B10: Em execução | C10: 1 | D10: 15000
A11: Total Geral | C11: 53 | D11: 4969638.5 | M11: Colunas | N11: Setembro | O11: Outubro | P11: Novembro | Q11: Dezembro | R11: Total
M12: Orçado | N12: 5206065 | O12: 5579287.5 | P12: 5821193 | Q12: 6062323.8
C13: BC | D13: 310372.4 | H13: 946651.72 | I13: 8481 | M13: Realizado | T13: RL Pendetes | U13: 43
H14: 959988.26 | I14: 8495 | M14: Forecast | N14: 524586.6 | O14: =691664.7+134944.52 -> 826609.22 | P14: =1443230.22+82181.59+175427.87 -> 1700839.7 | Q14: =1320983.74+100000 -> 1420983.7 | R14: =SUM(M14:Q14) -> 4473019.2 | T14: RT Pendetes | U14: 11
H15: =SUM(H13:H14) -> 1906640 | M15: RL Forecast Backlog Resolvidos | N15: 2 | P15: 20 | Q15: 20 | T15: BC | U15: 46
B16: 8481 | D16: 45 | E16: RL | G16: 2465983.7 | M16: RT Forecast backlog Resolvidos | N16: 1 | O16: 6 | P16: 2
B17: 8495 | E17: RT | G17: 1597242.4 | M17: BC Forecast backog Resolvidos | N17: 3 | O17: 23
C18: =1605000*1.0001745 -> 1605280.1 | D18: 143 | E18: BC | G18: 315372.4 | M18: RL Forecast Entrantes | N18: 2 | O18: 4 | P18: 1 | Q18: 4
B19: Orçamento | C19: 6100000 | G19: =SUM(G16:G18) -> 4378598.5 | M19: RT Forecast Entrantes | N19: 3 | O19: 0 | P19: 1 | Q19: 2
C20: 5983226.1 | M20: BC Forecast Entrantes | N20: 3 | O20: 1 | P20: 2 | Q20: 0 | R20: 0
C21: =C19-C20 -> 116773.88 | D21: 839786.22 | E21: =C18-D21 -> 765493.86 | K21: 1605280.1 | M21: RL Forecast | N21: =43+N18-N15 -> 43 | O21: =N21+O18-O15 -> 47 | P21: =O21+P18-P15 -> 28 | Q21: =P21+Q18-Q15 -> 12 | R21: 12
E22: 765493.86 | M22: RT Forecast | N22: =11-N16+N19 -> 13 | O22: =N22-O16+O19 -> 7 | P22: =O22-P16+P19 -> 6 | Q22: =P22-Q16+Q19 -> 8 | R22: 8
C23: Execução | D23: 524586.6 | M23: BC Forecast | N23: =46 -> 46 | O23: =N23-O17+O20 -> 24 | P23: =O23-P17+P20 -> 26 | Q23: =P23-Q17+Q20 -> 26 | R23: 23
C24: Logistica | D24: 691664.7 | M24: Sem BC | N24: =SUM(N21:N22) -> 56 | O24: =SUM(O21:O22) -> 54 | P24: =SUM(P21:P22) -> 34 | Q24: =SUM(Q21:Q22) -> 20 | R24: =SUM(R21:R22) -> 20
E25: 1605280.1 | M25: Forecast Entrantes Pentes | N25: =SUM(N18:N20)+100 -> 108 | O25: =N25+SUM(O18:O20) -> 113 | P25: =O25+SUM(P18:P20) -> 117 | Q25: =P25+SUM(Q18:Q20) -> 123
M26: Forecast resolvidos | N26: =SUM(N15:N17) -> 6 | O26: =N26+SUM(O15:O17) -> 35 | P26: =O26+SUM(P15:P17) -> 57 | Q26: =P26+SUM(Q15:Q17) -> 77
D27: 6062323.8 | M27: Quantidades Total | N27: =SUM(N21:N23) -> 102 | O27: =SUM(O21:O23) -> 78 | P27: =SUM(P21:P23) -> 60 | Q27: =SUM(Q21:Q23) -> 46 | R27: =SUM(R21:R23) -> 43
D28: 6083299.3 | M28: Orçado | N28: 5206065 | O28: 5579287.5 | P28: 5821193 | Q28: 6062323.8
D29: =D27-D28 -> -20975.48 | M29: Forecast Desembolso | N29: =1605280.07+N14 -> 2129866.7 | O29: =O14+N29-20000 -> 2936475.9 | P29: =P14+O29 -> 4637315.6 | Q29: =Q14+P29 -> 6058299.3 | R29: 6058299.3
C30: 315372.4 | I30: =SUM(J46:J51) -> 3980465.3
M31: Colunas | N31: Setembro | O31: Outubro | P31: Novembro | Q31: Dezembro
M32: BACKLOG | N32: =SUM(P2:P4) -> 100 | O32: =N35 -> 102 | P32: =O35 -> 78 | Q32: =P35 -> 60
M33: ENTRANTE | N33: =SUM(N18:N20) -> 8 | O33: =SUM(O18:O20) -> 5 | P33: =SUM(P18:P20) -> 4 | Q33: =SUM(Q18:Q20) -> 6
M34: RESOLVIDOS | N34: =SUM(N15:N17) -> 6 | O34: =SUM(O15:O17) -> 29 | P34: =SUM(P15:P17) -> 22 | Q34: =SUM(Q15:Q17) -> 20
M35: PENDENTES | N35: =N32+N33-N34 -> 102 | O35: =O32+O33-O34 -> 78 | P35: =P32+P33-P34 -> 60 | Q35: =Q32+Q33-Q34 -> 46
D36: 310372.4 | E36: 23 | M36: ORÇADO | N36: 5206065 | O36: 5579287.5 | P36: 5821193 | Q36: 6062323.8
E37: =10/E36 -> 0.43478261 | F37: 134944.52 | M37: FORECAST DESEMBOLSO | N37: 2129866.7 | O37: 2936475.9 | P37: 4637315.6 | Q37: 6058299.3
A39: OUTUBRO | B39: NOVEMBRO | F39: 175427.88
A40: 10 | B40: 13 | J40: =SUM(D58:G58) -> 4473019.2
E45: 58 | F45: JANEIRO DE 2027 | H45: Avaliar compra | I45: 2 | J45: 989173.2
E46: 58 | F46: Outubro | H46: Em logistica (N1>N3) | I46: 6 | J46: 691664.7
E47: 58 | F47: Novembro | H47: Reforma | I47: 2 | J47: 213808.1
A48: Valor médio RL | E48: 58 | F48: Setembro | H48: Em execução | I48: 2 | J48: 509586.6
A49: Valor Médio RT | E49: 79 | F49: Novembro | H49: Avaliar compra | I49: 20 | J49: 1229422.1 | K49: 1443230.2
E50: 79 | F50: Dezembro | H50: Gerado PMA | I50: 20 | J50: 1320983.7
E51: 79 | F51: Setembro | H51: Em execução | I51: 1 | J51: 15000
C56: 46266 | D56: Setembro | E56: Outubro | F56: Novembro | G56: Dezembro | H56: Forecast Quantidade de Resolvidos | I56: 2027 | U56: Curva de Equipamentos | V56: Entrante | W56: Resolver
B57: Pendentes | D57: 3 | E57: =8+10-2 -> 16 | F57: =20+2+13 -> 35 | G57: 20 | H57: =SUM(D57:G57) -> 74 | I57: 2 | T57: SETEMBRO | U57: 102 | V57: 8 | W57: 6
B58: Total Dinheiro | C58: 1605280.1 | D58: 524586.6 | E58: =691664.7+134944.52 -> 826609.22 | F58: =1443230.22+82181.59+175427.87 -> 1700839.7 | G58: =1320983.74+100000 -> 1420983.7 | H58: =SUM(C58:G58) -> 6078299.3 | I58: 989173.2 | T58: OUTUBRO | U58: 78 | V58: 5 | W58: 29
B59: RL Qtd | D59: 2 | F59: 20 | G59: 20 | T59: NOVEMBRO | U59: 60 | V59: 4 | W59: 22
B60: RT Qtd | D60: 1 | E60: 6 | F60: 2 | T60: DEZEMBRO | U60: 46 | V60: 6 | W60: 20
B61: BC Qtd | E61: 23
A62: Premissas : ultilizando a premissa de queimaremos o mesmo tanto que 2025 | B62: Entrantes RL | D62: 2 | E62: 4 | F62: 1 | G62: 4 | H62: =SUM(C62:G62) -> 11
A63: Premissas : ultilizando a premissa de queimaremos o mesmo tanto que 2026 | B63: Entrantes RT | D63: 3 | E63: 0 | F63: 1 | G63: 2 | H63: =SUM(C63:G63) -> 6 | Q63: =55+46 -> 101
F65: 4473019.3
F66: =SUM(D58:G58) -> 4473019.2
F67: =F65-F66 -> 0.02
F68: 82181.6
C70: Set | D70: Out | E70: Nov | F70: Dez | G70: Total
B71: Qtd Equipamentos | C71: =D57 -> 3 | D71: =E57 -> 16 | E71: =F57 -> 35 | F71: =G57 -> 20 | G71: =SUM(C71:F71) -> 74
B72: Desembolso | C72: =D58 -> 524586.6 | D72: =E58 -> 826609.22 | E72: =F58 -> 1700839.7 | F72: =G58 -> 1420983.7 | G72: =SUM(C72:F72) -> 4473019.2
AB74: Orçado Linha
AB75: Forecast em barra
B84: Set | C84: Out | D84: Nov | E84: Dez | F84: Total
A85: RL | B85: 1 | D85: 20 | E85: 20 | F85: 41
A86: RT | B86: 2 | C86: 6 | D86: 2 | F86: 10
A87: BC | C87: 10 | D87: 13 | F87: 23
A88: Desembolso | B88: 524586.6 | C88: 826609.22 | D88: 1700839.7 | E88: 1420983.7 | F88: 4473019.2
B94: Realizado | C94: Em Execução | D94: Em logistica (N1>N3) | E94: Gerado PMA | F94: Reforma | G94: Emitir compra
A95: RL | B95: 839786.21 | C95: 15000 | D95: - | E95: 1320983.3 | F95: - | G95: 1229422.1
A96: RT | B96: 765493.85 | C96: 509585.6 | D96: 691664.7 | E96: - | F96: 375991.1 | G96: -
A97: BC | B97: - | C97: - | D97: - | E97: 310372.4 | F97: - | G97: -
A98: Soma (acumulada) | B98: 1605280.1 | C98: 2129865.7 | D98: 2821530.4 | E98: 4452886.1 | F98: 4828877.2 | G98: 6058299.3
G99: 6062323.8
G100: =G98-G99 -> -4024.52
AF115: Com BC
P116: Sem BC | AE116: DISPÊNDIO + FORECAST | AF116: ORÇADO | AG116: FORECAST | AH116: ORÇADO AUMULADO | AJ116: Curva de Equipamentos | AK116: Entrante | AL116: Resolvidos
L117: Colunas | M117: FORECAST | N117: FORECAST | O117: ORÇADO AUMULADO | P117: Colunas | Q117: Pendentes | R117: Entrante | S117: Resolvidos | AB117: DESEMBOLSO MENSAL | AD117: BACKLOG 2025 | AE117: 0 | AF117: 0 | AH117: BACKLOG 2025 | AI117: BACKLOG 2025 | AJ117: 76 | AK117: 0 | AL117: 0
L118: BACKLOG 2025 | M118: 0 | O118: 0 | P118: BACKLOG 2025 | Q118: 59 | R118: 0 | S118: 0 | AB118: 0 | AD118: JANEIRO | AE118: 33374.11 | AF118: 633069.38 | AG118: 0 | AH118: 0 | AI118: JANEIRO | AJ118: =AJ117+AK118-AL118 -> 78 | AK118: 7 | AL118: 5
L119: JANEIRO | M119: 33374.11 | N119: =M119 -> 33374.11 | O119: 633069.38 | P119: JANEIRO | Q119: =Q118+R119-S119 -> 65 | R119: 7 | S119: 1 | AD119: FEVEREIRO | AE119: 411751.97 | AF119: 1608127 | AG119: 33374.11 | AH119: 633069.38 | AI119: FEVEREIRO | AJ119: =AJ118+AK119-AL119 -> 82 | AK119: 5 | AL119: 1
L120: FEVEREIRO | M120: 411751.97 | N120: =M120-M119 -> 378377.86 | O120: 1608127 | P120: FEVEREIRO | Q120: =Q119+R120-S120 -> 71 | R120: 8 | S120: 2 | AB120: =AG119 -> 33374.11 | AD120: MARÇO | AE120: 533851.39 | AF120: 2484696.9 | AG120: 411751.97 | AH120: 1608127 | AI120: MARÇO | AJ120: =AJ119+AK120-AL120 -> 88 | AK120: 12 | AL120: 6
L121: MARÇO | M121: 533851.39 | N121: =M121-M120 -> 122099.42 | O121: 2484696.9 | P121: MARÇO | Q121: =Q120+R121-S121 -> 76 | R121: 9 | S121: 4 | AB121: =AG120-AG119 -> 378377.86 | AD121: ABRIL | AE121: 575912.16 | AF121: 3361266.8 | AG121: 533851.39 | AH121: 2484696.9 | AI121: ABRIL | AJ121: =AJ120+AK121-AL121 -> 98 | AK121: 12 | AL121: 2
L122: ABRIL | M122: 575912.16 | N122: =M122-M121 -> 42060.77 | O122: 3361266.8 | P122: ABRIL | Q122: =Q121+R122-S122 -> 80 | R122: 5 | S122: 1 | AB122: =AG121-AG120 -> 122099.42 | AD122: MAIO | AE122: 644774.34 | AF122: 3994336.2 | AG122: 575912.16 | AH122: 3361266.8 | AI122: MAIO | AJ122: =AJ121+AK122-AL122 -> 89 | AK122: 12 | AL122: =16+5 -> 21
L123: MAIO | M123: 644774.34 | N123: =M123-M122 -> 68862.18 | O123: 3994336.2 | P123: MAIO | Q123: =Q122+R123-S123 -> 65 | R123: 1 | S123: 16 | AB123: =AG122-AG121 -> 42060.77 | AD123: JUNHO | AE123: 906340.58 | AF123: 4332841.8 | AG123: 644774.34 | AH123: 3994336.2 | AI123: JUNHO | AJ123: =AJ122+AK123-AL123 -> 86 | AK123: 33 | AL123: =29+7 -> 36
L124: JUNHO | M124: 906340.58 | N124: =M124-M123 -> 261566.24 | O124: 4332841.8 | P124: JUNHO | Q124: =Q123+R124-S124 -> 58 | R124: 2 | S124: 9 | AB124: =AG123-AG122 -> 68862.18 | AD124: JULHO | AE124: 1344410.1 | AF124: 4623766.3 | AG124: 906340.58 | AH124: 4332841.8 | AI124: JULHO | AJ124: =AJ123+AK124-AL124 -> 96 | AK124: 24 | AL124: 14
L125: JULHO | M125: 1344410.1 | N125: =M125-M124 -> 438069.49 | O125: 4623766.3 | P125: JULHO | Q125: =Q124+R125-S125 -> 56 | R125: 4 | S125: 6 | AB125: =AG124-AG123 -> 261566.24 | AD125: AGOSTO | AE125: 1906700.6 | AF125: 4915140.5 | AG125: 1344410.1 | AH125: 4623766.3 | AI125: AGOSTO | AJ125: =AJ124+AK125-AL125 -> 97 | AK125: 10 | AL125: =9 -> 9
L126: AGOSTO | M126: 1906700.6 | N126: =M126-M125 -> 562290.49 | O126: 4915140.5 | P126: AGOSTO | Q126: =Q125+R126-S126 -> 55 | R126: 1 | S126: 2 | AB126: =AG125-AG124 -> 438069.49 | AD126: SETEMBRO | AE126: 2129866.7 | AF126: 5206065 | AG126: 1906700.6 | AH126: 4915140.5 | AI126: SETEMBRO | AJ126: =AJ125+AK126-AL126 -> 99 | AK126: 8 | AL126: 6
L127: SETEMBRO | M127: 2129866.7 | N127: =M127-M126 -> 223166.11 | O127: 5206065 | P127: SETEMBRO | Q127: =Q126+R127-S127 -> 57 | R127: 8 | S127: 6 | AB127: =AG126-AG125 -> 562290.49 | AD127: OUTUBRO | AE127: 2936475.9 | AF127: 5579287.5 | AG127: 2129866.7 | AH127: 5206065 | AI127: OUTUBRO | AJ127: =AJ126+AK127-AL127 -> 75 | AK127: 5 | AL127: 29
L128: OUTUBRO | M128: 2936475.9 | N128: =M128-M127 -> 806609.22 | O128: =5579287.46-315000 -> 5264287.5 | P128: OUTUBRO | Q128: =Q127+R128-S128 -> 60 | R128: 9 | S128: =29-23 -> 6 | AB128: =AG127-AG126 -> 223166.11 | AD128: NOVEMBRO | AE128: 4637315.6 | AF128: 5821193 | AG128: 2936475.9 | AH128: 5579287.5 | AI128: NOVEMBRO | AJ128: =AJ127+AK128-AL128 -> 57 | AK128: 4 | AL128: 22
L129: NOVEMBRO | M129: 4637315.6 | N129: =M129-M128 -> 1700839.7 | O129: 5821193 | P129: NOVEMBRO | Q129: =Q128+R129-S129 -> 43 | R129: 5 | S129: 22 | AB129: =AG128-AG127 -> 806609.22 | AD129: DEZEMBRO | AE129: 6058299.3 | AF129: 6062323.8 | AG129: 4637315.6 | AH129: 5821193 | AI129: DEZEMBRO | AJ129: =AJ128+AK129-AL129 -> 43 | AK129: 6 | AL129: 20
L130: DEZEMBRO | M130: 6058299.3 | N130: =M130-M129-315000 -> 1105983.7 | O130: =6062323.84-315000 -> 5747323.8 | P130: DEZEMBRO | Q130: =Q129+R130-S130 -> 24 | R130: 1 | S130: 20 | AB130: =AG129-AG128 -> 1700839.7

Sheet Apresentação
B1: Realizado | C1: Em Execução | D1: Em logistica (N1>N3) | E1: Gerado PMA | F1: Reforma | G1: Emitir compra
A2: RL | B2: 839786.21 | C2: 15000 | D2: - | E2: 1320983.3 | F2: - | G2: 1229422.1
A3: RT | B3: 765493.85 | C3: 509585.6 | D3: 691664.7 | E3: - | F3: 375991.1 | G3: -
A4: BC | B4: - | C4: - | D4: - | E4: 310372.4 | F4: - | G4: -
B5: =SUM(B2:B4) -> 1605280.1 | C5: =SUM(C2:C4) -> 524585.6 | D5: =SUM(D2:D4) -> 691664.7 | E5: =SUM(E2:E4) -> 1631355.7 | F5: =SUM(F2:F4) -> 375991.1 | G5: =SUM(G2:G4) -> 1229422.1
A6: Soma (acumulada) | B6: =B5 -> 1605280.1 | C6: =B6+C5 -> 2129865.7 | D6: =C6+D5 -> 2821530.4 | E6: =D6+E5 -> 4452886.1 | F6: =E6+F5 -> 4828877.2 | G6: =F6+G5 -> 6058299.3
G7: 6062323.8
G8: =G7-G6 -> 4024.52
A9: TIPO | B9: STATUS | C9: CONTAGEM | D9: VALOR PREVISTO
A10: RL | B10: Em execução | C10: 1 | D10: 15000
B11: Gerado PMA | C11: 20 | D11: 1320983.3
B12: Gerar compra | C12: 20 | D12: 1229422.1
C13: 41 | D13: 2565405.5
A14: RT | B14: Em execução | C14: 2 | D14: 509585.6
B15: Em logistica (N1>N3) | C15: 6 | D15: 691664.7
B16: Reforma | C16: 2 | D16: 375991.1
C17: 10 | D17: 1597241.4
A18: BC | B18: Gerado PMA | C18: 23 | D18: 310372.4
A19: Total Geral | C19: 51 | D19: =D13+D17+D18 -> 4473019.3 | E19: 4478019.3
A24: TIPO | B24: STATUS | C24: CONTAGEM | D24: VALOR PREVISTO
A25: RL | B25: Em execução | C25: 1 | D25: 15000
B26: Gerado PMA | C26: 20 | D26: 1320983.3
B27: Gerar compra | C27: 20 | D27: 1229422.1
C28: 41 | D28: 2565405.9
A29: RT | B29: Em execução | C29: 2 | D29: 509585.6
B30: Em logistica (N1>N3) | C30: 6 | D30: 691664.7
B31: Reforma | C31: 2 | D31: 375991.1
C32: 10 | D32: 1577241.4
A33: BC | B33: Gerado PMA | C33: 23 | D33: 310372.4
A34: Total Geral | C34: 74 | D34: 4453019.7
B39: Realizado | C39: Em Execução | D39: Em logistica (N1>N3) | E39: Gerado PMA | F39: Reforma | G39: Emitir compra
A40: RL | B40: 839786.21 | C40: 15000 | D40: - | E40: 1320983.3 | F40: - | G40: 1229422.1
A41: RT | B41: 765493.85 | C41: 509585.6 | D41: 691664.7 | E41: - | F41: 375991.1 | G41: -
A42: BC | B42: - | C42: - | D42: - | E42: 310372.4 | F42: - | G42: -
A43: Soma (acumulada) | B43: 1605280.1 | C43: 2129865.7 | D43: 2821530.4 | E43: 4452886.1 | F43: 4828877.2 | G43: 6058299.3

Sheet Gestão
A1: Ativo | B1: Marca | C1: Faixa de Tensão | D1: Tipo | E1: Potencia | F1: SS SGM | G1: Criticidade | H1: Status | I1: Defeito | J1: Orçamento MO | K1: Orçamento MAT | L1: Orçamento Total | M1: PMA | N1: Entregue N1? | O1: Gerado Obra? | P1: Gerado EMD? | Q1: Entregue N3? | R1: Concluído COCM? | S1: Enviado para Cadastro | T1: Estudo Proteção | U1: Repassado ao DMSL? | V1: Comissionado? | W1: Índice | X1: SLA_Total | Y1: Dias Pendente | Z1: Status Atendimento | AA1: Responsável | AB1: Status Prazo | AC1: Coluna1 | AD1: Alimentador | AE1: Município | AF1: Polo | AG1: Regional
A2: 7926089013 | B2: NOJA RC10 | C2: 34,5 kV | D2: =LEFT(Table1[[#This Row],[Ativo]],2) -> 79 | F2: ETO-COEP 00078/2026 | G2: Alta | H2: Gerado PMA | I2: Controle 34,5 | J2: 13209.34 | K2: 38094.72 | L2: 51304.06 | M2: 38297 | W2: 34 | X2: 26 | Y2: 143 | Z2: 116 - DIAS AGUARDANDO DCMD | AA2: COEP | AB2: 117 - DIAS FORA DO PRAZO | AD2: LD03062013 - LD PARAISO I A PIUM | AE2: PARAISO DO TOCANTINS | AF2: PARAISO DO TOCANTINS | AG2: CENTRO
A3: 7923673004 | B3: ARTECHE P500 | C3: 13,8 kV | D3: =LEFT(Table1[[#This Row],[Ativo]],2) -> 79 | F3: ETO-COEP 00124/2026 | G3: Muito Alta | H3: Gerado PMA | I3: RL Completo 13,8 | J3: 11016.94 | K3: 55602.54 | L3: 66619.48 | M3: 38294+38296 | W3: 5 | X3: 12 | Y3: 144 | Z3: 40 - DIAS AGUARDANDO DCMD | AA3: COEP | AB3: 132 - DIAS FORA DO PRAZO | AD3: AL04010004 - AL 4 SE ARAGUAINA I | AE3: ARAGUAINA | AF3: ARAGUAINA | AG3: NORTE
A4: 7903569004 | B4: NOJA RC10 | C4: 13,8 kV | D4: =LEFT(Table1[[#This Row],[Ativo]],2) -> 79 | F4: ETO-COEP 00152/2026 | G4: Muito Alta | H4: Gerado PMA | I4: RL Completo 13,8 | J4: 11016.94 | K4: 55602.54 | L4: 66619.48 | M4: 38294+38296 | W4: 11 | X4: 12 | Y4: 28 | Z4: 27 - DIAS AGUARDANDO DCMD | AA4: COEP | AB4: 16 - DIAS FORA DO PRAZO | AD4: AL05010004 - AL 5 SE ARAGUAINA I | AE4: ARAGUAINA | AF4: ARAGUAINA | AG4: NORTE
A5: 5856070091 | B5: ITB | C5: 34,5 kV | D5: =LEFT(Table1[[#This Row],[Ativo]],2) -> 58 | E5: 400 kVA | F5: ETO-RD-DP 00479/2026 | G5: Muito Alta | H5: Em execução | I5: RT Completo 400 34,5 | J5: 200637 | K5: 293949.6 | L5: 494586.6 | M5: 38291+38292 | W5: 10 | X5: 12 | Y5: 395 | Z5: 20 - DIAS AGUARDANDO DCMD | AA5: COCM-S | AB5: 383 - DIAS FORA DO PRAZO | AD5: LD04002091 - LD 04 ALMAS NATIVIDADE AO POV PRINCIPE | AE5: ALMAS | AF5: DIANOPOLIS | AG5: SUL
A6: 7908705049 | B6: COOPER F6 | C6: 13,8 kV | D6: =LEFT(Table1[[#This Row],[Ativo]],2) -> 79 | F6: ETO-RD-DP 00409/2026 | G6: Muito Alta | H6: Gerado PMA | I6: RL Completo 13,8 | J6: 11016.94 | K6: 55602.54 | L6: 66619.48 | M6: 38294+38296 | W6: 15 | X6: 12 | Y6: 397 | Z6: 41 - DIAS AGUARDANDO DCMD | AA6: COCM-S | AB6: 385 - DIAS FORA DO PRAZO | AD6: AL01015049 - AL 1 SE AURORA | AE6: AURORA DO TOCANTINS | AF6: DIANOPOLIS | AG6: SUL
A7: 7947203070 | B7: TAVRIDA | C7: 34,5 kV | D7: =LEFT(Table1[[#This Row],[Ativo]],2) -> 79 | F7: ETO-COEP 00131/2026 | G7: Muito Alta | H7: Gerado PMA | I7: RL Completo 34,5 | J7: 13209.34 | K7: 76246.2 | L7: 89455.54 | M7: 38295+38297 | W7: 9 | X7: 12 | Y7: 267 | Z7: 40 - DIAS AGUARDANDO DCMD | AA7: COEP | AB7: 255 - DIAS FORA DO PRAZO | AD7: LD02065015 | AE7: RIO SONO | AF7: PALMAS | AG7: CENTRO
A8: 7927413001 | B8: NOJA RC10 | C8: 34,5 kV | D8: =LEFT(Table1[[#This Row],[Ativo]],2) -> 79 | F8: ETO-COEP 00141/2026 | G8: Muito Alta | H8: Gerado PMA | I8: RL Completo 34,5 | J8: 13209.34 | K8: 76246.2 | L8: 89455.54 | M8: 38295+38297 | W8: 21 | X8: 12 | Y8: 140 | Z8: 34 - DIAS AGUARDANDO DCMD | AA8: COEP | AB8: 128 - DIAS FORA DO PRAZO | AD8: LD01072001 - LD PORTO NACIONAL A SE PROJETO SAO JOAO | AE8: PORTO NACIONAL | AF8: PORTO NACIONAL | AG8: CENTRO
A9: 7900453110 | B9: COOPER F6 | C9: 34,5 kV | D9: =LEFT(Table1[[#This Row],[Ativo]],2) -> 79 | F9: ETO-COEP 00087/2026 | G9: Muito Alta | H9: Gerado PMA | I9: RL Completo 34,5 | J9: 13209.34 | K9: 76246.2 | L9: 89455.54 | M9: 38295+38297 | W9: 25 | X9: 12 | Y9: 482 | Z9: 111 - DIAS AGUARDANDO DCMD | AA9: COEP | AB9: 470 - DIAS FORA DO PRAZO | AD9: LD03040003 - LD GURUPI A ALIANCA E TREVO DA PRAIA | AE9: SANTA RITA DO TOCANTINS | AF9: PORTO NACIONAL | AG9: CENTRO
A10: 5800440256 | B10: ITB E TOSHIBA | C10: 34,5 kV | D10: =LEFT(Table1[[#This Row],[Ativo]],2) -> 58 | E10: 200 kVA | F10: ETO-COEP 00169/2026 | G10: Muito Alta | H10: Realizado | I10: Célula 200 34,5 | J10: 80318.5 | K10: 51705.75 | L10: 132024.25 | M10: Sem PMA | N10: Sim | O10: 0312600408 | P10: 521995 | Q10: Sim | R10: Sim | S10: Não | W10: 23 | X10: 12 | Y10: 21 | Z10: 10 - DIAS AGUARDANDO DCMD | AA10: COEP | AB10: 9 - DIAS FORA DO PRAZO | AD10: LD03046026 - LD UHE ISAMU A PONTE ALTA | AE10: MATEIROS | AF10: PONTE ALTA TOCANTINS | AG10: CENTRO
A11: 7903112004 | B11: COOPER F6 | C11: 34,5 kV | D11: =LEFT(Table1[[#This Row],[Ativo]],2) -> 79 | F11: ETO-COEP 00184/2025 | G11: Alta | H11: Gerado PMA | I11: RL Completo 34,5 | J11: 13209.34 | K11: 76246.2 | L11: 89455.54 | M11: 38295+38297 | W11: 48 | X11: 26 | Y11: 348 | Z11: 347 - DIAS AGUARDANDO DCMD | AA11: COEP | AB11: 322 - DIAS FORA DO PRAZO | AD11: LD05010004 - LD ARAGUAINA I A BABACULANDIA | AE11: ARAGUAINA | AF11: ARAGUAINA | AG11: NORTE
A12: 7920024127 | B12: SCHNEIDER ADVC | C12: 34,5 kV | D12: =LEFT(Table1[[#This Row],[Ativo]],2) -> 79 | F12: ETO-COEP 00120/2025 | G12: Alta | H12: Gerado PMA | I12: RL Completo 34,5 | J12: 13209.34 | K12: 76246.2 | L12: 89455.54 | M12: 38295+38297 | W12: 49 | X12: 26 | Y12: 441 | Z12: 411 - DIAS AGUARDANDO DCMD | AA12: COEP | AB12: 415 - DIAS FORA DO PRAZO | AD12: LD01084002 - LD TOCANTINOPOLIS A ANANAS | AE12: PALMEIRAS DO TOCANTINS | AF12: TOCANTINOPOLIS | AG12: NORTE
A13: 5803327001 | B13: TOSHIBA | C13: 13,8 kV | D13: =LEFT(Table1[[#This Row],[Ativo]],2) -> 58 | E13: 167 kVA | F13: ETO-COEP 00149/2026 | G13: Alta | H13: Em logistica (N1>N3) | I13: Controle 167 13,8 | J13: 20000 | K13: 23259.6 | L13: 43259.6 | M13: Controle Rua que voltou de dianopólis | N13: Sim | O13: 0712600591 | P13: Ainda Não | Q13: Ainda não | R13: Não | S13: Não | T13: Não | U13: Não | V13: Não | W13: 27 | X13: 26 | Y13: 347 | Z13: 28 - DIAS AGUARDANDO DCMD | AA13: COEP | AB13: 321 - DIAS FORA DO PRAZO | AD13: AL01102271 - AL 01 SE LUZIMANGUES INDUSTRIAL | AE13: PORTO NACIONAL | AF13: PORTO NACIONAL | AG13: CENTRO
A14: 7931608059 | B14: NOJA RC10 | C14: 13,8 kV | D14: =LEFT(Table1[[#This Row],[Ativo]],2) -> 79 | F14: ETO-COEP 00040/2026 | G14: Muito Alta | H14: Gerado PMA | I14: Tanque 13,8 | J14: 11016.94 | K14: 21785.72 | L14: 32802.66 | M14: 38294 | W14: 6 | X14: 12 | Y14: 201 | Z14: 174 - DIAS AGUARDANDO DCMD | AA14: COEP | AB14: 189 - DIAS FORA DO PRAZO | AD14: AL05099059 - AL 5 SE TAQUARALTO I I | AE14: PALMAS | AF14: TAQUARALTO | AG14: CENTRO
A15: 5853360007 | B15: ITB | C15: 34,5 kV | D15: =LEFT(Table1[[#This Row],[Ativo]],2) -> 58 | E15: 400 kVA | F15: ETO-RD-PS 00323/2025 | G15: Alta | H15: Em execução | I15: Acessório 400 34,5 | J15: 0 | K15: 15000 | L15: 15000 | M15: Sem PMA | N15: NA | O15: NA | W15: 38 | X15: 26 | Y15: 475 | Z15: 304 - DIAS AGUARDANDO DCMD | AA15: COCM-C | AB15: 449 - DIAS FORA DO PRAZO | AD15: LD05050008 - LD MIRANORTE A MIRACEMA | AE15: MIRACEMA DO TOCANTINS | AF15: MIRACEMA DO TOCANTINS | AG15: CENTRO
A16: 5840227063 | B16: ITB | C16: 34,5 kV | D16: =LEFT(Table1[[#This Row],[Ativo]],2) -> 58 | E16: 398/400 kVA | F16: ETO-COEP 00151/2026 | G16: Média | H16: Em logistica (N1>N3) | I16: Célula 400 34,5 | J16: 80318.5 | K16: 90230 | L16: 170548.5 | M16: 38292 | N16: Sim | O16: 0612600861 | P16: Ainda Não | Q16: Ainda não | R16: Não | S16: Não | T16: Não | U16: Não | V16: Não | W16: 45 | X16: 86 | Y16: 206 | Z16: 28 - DIAS AGUARDANDO DCMD | AA16: COEP | AB16: 120 - DIAS FORA DO PRAZO | AD16: LD01054060 - LD NOVA OLINDA A ARAPOEMA | AE16: BANDEIRANTES DO TOCANTINS | AF16: COLINAS DO TOCANTINS | AG16: NORTE
A17: 7925744087 | B17: NOJA RC10 | C17: 34,5 kV | D17: =LEFT(Table1[[#This Row],[Ativo]],2) -> 79 | F17: ETO-COEP 00059/2026 | G17: Muito Alta | H17: Gerado PMA | I17: Tanque 34,5 | J17: 13209.34 | K17: 38151.48 | L17: 51360.82 | M17: 38295 | W17: 12 | X17: 12 | Y17: 189 | Z17: 140 - DIAS AGUARDANDO DCMD | AA17: COEP | AB17: 177 - DIAS FORA DO PRAZO | AD17: LD02022033 - LD COLMEIA A COUTO MAGALHAES | AE17: GOIANORTE | AF17: GUARAI | AG17: NORTE
A18: 7925871077 | B18: NOJA RC10 | C18: 34,5 kV | D18: =LEFT(Table1[[#This Row],[Ativo]],2) -> 79 | F18: ETO-COEP 00048/2026 | G18: Muito Alta | H18: Gerado PMA | I18: Tanque 34,5 | J18: 13209.34 | K18: 38151.48 | L18: 51360.82 | M18: 38295 | W18: 26 | X18: 12 | Y18: 154 | Z18: 154 - DIAS AGUARDANDO DCMD | AA18: COEP | AB18: 142 - DIAS FORA DO PRAZO | AD18: LD03105019 - LD POV BIELANDIA A CAMPOS LINDOS | AE18: GOIATINS | AF18: COLINAS DO TOCANTINS | AG18: NORTE
A19: 7927646026 | B19: NOJA RC10 | C19: 34,5 kV | D19: =LEFT(Table1[[#This Row],[Ativo]],2) -> 79 | F19: ETO-COEP 00029/2026 | G19: Alta | H19: Gerado PMA | I19: Tanque 34,5 | J19: 13209.34 | K19: 38151.48 | L19: 51360.82 | M19: 38295 | W19: 50 | X19: 26 | Y19: 220 | Z19: 194 - DIAS AGUARDANDO DCMD | AA19: COEP | AB19: 194 - DIAS FORA DO PRAZO | AD19: LD03046026 - LD UHE ISAMU A PONTE ALTA | AE19: PONTE ALTA TOCANTINS | AF19: PONTE ALTA TOCANTINS | AG19: CENTRO
A20: 7930428001 | B20: NOJA RC10 | C20: 34,5 kV | D20: =LEFT(Table1[[#This Row],[Ativo]],2) -> 79 | F20: ETO-COEP 00150/2026 | G20: Alta | H20: Gerado PMA | I20: Tanque 34,5 | J20: 13209.34 | K20: 38151.48 | L20: 51360.82 | M20: 38295 | W20: 54 | X20: 26 | Y20: 412 | Z20: 28 - DIAS AGUARDANDO DCMD | AA20: COEP | AB20: 386 - DIAS FORA DO PRAZO | AD20: LD01100001 - LD PROJETO SAO JOAO IRRIGACAO | AE20: PORTO NACIONAL | AF20: PORTO NACIONAL | AG20: CENTRO
A21: 7944559149 | B21: NOJA RC10 | C21: 34,5 kV | D21: =LEFT(Table1[[#This Row],[Ativo]],2) -> 79 | F21: ETO-COEP 00063/2026 | G21: Média | H21: Gerado PMA | I21: Controle 34,5 | J21: 13209.34 | K21: 38094.72 | L21: 51304.06 | M21: Sem PMA | W21: 63 | X21: 86 | Y21: 153 | Z21: 139 - DIAS AGUARDANDO DCMD | AA21: COEP | AB21: 67 - DIAS FORA DO PRAZO | AD21: LD01434149 - LD CASEARA A ARAGUACEMA | AE21: CASEARA | AF21: DIVINOPOLIS | AG21: CENTRO
A22: 7955986084 | B22: NOJA RC10 | C22: 34,5 kV | D22: =LEFT(Table1[[#This Row],[Ativo]],2) -> 79 | F22: ETO-COEP 00133/2026 | G22: Média | H22: Avaliar compra | I22: Controle 34,5 | J22: 13209.34 | K22: 38094.72 | L22: 51304.06 | M22: Sem PMA | W22: 72 | X22: 86 | Y22: 40 | Z22: 40 - DIAS AGUARDANDO DCMD | AA22: COEP | AB22: VENCE EM: 46 DIAS | AD22: LD04062013 - LD SE PARAISO I A DIVINOPOLIS | AE22: DIVINOPOLIS | AF22: DIVINOPOLIS | AG22: CENTRO
A23: 7900535058 | B23: COOPER F6 | C23: 34,5 kV | D23: =LEFT(Table1[[#This Row],[Ativo]],2) -> 79 | F23: ETO-COEP 00173/2025 | G23: Média | H23: Gerado PMA | I23: RL Completo 34,5 | J23: 13209.34 | K23: 76246.2 | L23: 89455.54 | M23: Sem PMA | W23: 60 | X23: 86 | Y23: 374 | Z23: 357 - DIAS AGUARDANDO DCMD | AA23: COEP | AB23: 288 - DIAS FORA DO PRAZO | AD23: LD03010004 - LD ARAGUAINA A CARMOLA E ARAGUANA | AE23: SANTA FE DO ARAGUAIA | AF23: ARAGUAINA | AG23: NORTE
A24: 7908249152 | B24: COOPER F6 | C24: 34,5 kV | D24: =LEFT(Table1[[#This Row],[Ativo]],2) -> 79 | F24: ETO-COEP 00038/2026 | G24: Média | H24: Gerado PMA | I24: RL Completo 34,5 | J24: 13209.34 | K24: 76246.2 | L24: 89455.54 | M24: Sem PMA | W24: 65 | X24: 86 | Y24: 207 | Z24: 174 - DIAS AGUARDANDO DCMD | AA24: COEP | AB24: 121 - DIAS FORA DO PRAZO | AD24: LD02072001 - LD PORTO NACIONAL A SILVANOPOLIS | AE24: SANTA ROSA DO TOCANTINS | AF24: PORTO NACIONAL | AG24: CENTRO
A25: 5800961074 | B25: ITB | C25: 34,5 kV | D25: =LEFT(Table1[[#This Row],[Ativo]],2) -> 58 | E25: 200 kVA | F25: ETO-COEP 00221/2025 | G25: Média | H25: Em compra | I25: Célula 200 34,5 | J25: 80318.5 | K25: 51705.75 | L25: 132024.25 | M25: Sem PMA | W25: 64 | X25: 86 | Y25: 255 | Z25: 254 - DIAS AGUARDANDO DCMD | AA25: COEP | AB25: 169 - DIAS FORA DO PRAZO | AD25: LD03028074 - LD DIANOPOLIS A REGIAO GERAIS | AE25: DIANOPOLIS | AF25: DIANOPOLIS | AG25: SUL
A26: 7900525015 | B26: COOPER F6 | C26: 34,5 kV | D26: =LEFT(Table1[[#This Row],[Ativo]],2) -> 79 | F26: ETO-COEP 00125/2026 | G26: Média | H26: Avaliar compra | I26: RL Completo 34,5 | J26: 13209.34 | K26: 76246.2 | L26: 89455.54 | M26: Sem PMA | W26: 74 | X26: 86 | Y26: 126 | Z26: 40 - DIAS AGUARDANDO DCMD | AA26: COEP | AB26: 40 - DIAS FORA DO PRAZO | AD26: LD02065015 | AE26: PEDRO AFONSO | AF26: GUARAI | AG26: NORTE
A27: 7928564039 | B27: NOJA RC10 | C27: 34,5 kV | D27: =LEFT(Table1[[#This Row],[Ativo]],2) -> 79 | F27: ETO-COEP 00123/2026 | G27: Média | H27: Avaliar compra | I27: RL Completo 34,5 | J27: 13209.34 | K27: 76246.2 | L27: 89455.54 | M27: 38295+38297 | W27: 75 | X27: 86 | Y27: 445 | Z27: 40 - DIAS AGUARDANDO DCMD | AA27: COEP | AB27: 359 - DIAS FORA DO PRAZO | AD27: LD02109039 - LD ARAGUATINS A POV SOCO | AE27: ARAGUATINS | AF27: AUGUSTINOPOLIS | AG27: NORTE
A28: 7927713200 | B28: NOJA RC10 | C28: 34,5 kV | D28: =LEFT(Table1[[#This Row],[Ativo]],2) -> 79 | F28: ETO-COEP 00157/2026 | G28: Média | H28: Gerado PMA | I28: Tanque 34,5 | J28: 13209.34 | K28: 38151.48 | L28: 51360.82 | M28: Sem PMA | W28: 61 | X28: 86 | Y28: 21 | Z28: 20 - DIAS AGUARDANDO DCMD | AA28: COEP | AB28: VENCE EM: 65 DIAS | AD28: LD02010021 - LD PARANA A PALMEIROPOLIS | AE28: SAO SALVADOR DO TOCANTINS | AF28: PEIXE | AG28: SUL
A29: 7937102148 | B29: NOJA RC10 | C29: 34,5 kV | D29: =LEFT(Table1[[#This Row],[Ativo]],2) -> 79 | F29: ETO-COEP 00129/2026 | G29: Média | H29: Gerado PMA | I29: Tanque 34,5 | J29: 13209.34 | K29: 38151.48 | L29: 51360.82 | M29: Sem PMA | W29: 62 | X29: 86 | Y29: 242 | Z29: 40 - DIAS AGUARDANDO DCMD | AA29: COEP | AB29: 156 - DIAS FORA DO PRAZO | AD29: LD01066094 - LD UHE PEIXE A SAO VALERIO | AE29: SAO VALERIO DA NATIVIDADE | AF29: PEIXE | AG29: SUL
A30: 7925733015 | B30: NOJA RC10 | C30: 34,5 kV | D30: =LEFT(Table1[[#This Row],[Ativo]],2) -> 79 | F30: ETO-COEP 00058/2026 | G30: Média | H30: Gerado PMA | I30: Tanque 34,5 | J30: 13209.34 | K30: 38151.48 | L30: 51360.82 | M30: 38295 | W30: 67 | X30: 86 | Y30: 157 | Z30: 140 - DIAS AGUARDANDO DCMD | AA30: COEP | AB30: 71 - DIAS FORA DO PRAZO | AD30: LD02065015 | AE30: PEDRO AFONSO | AF30: GUARAI | AG30: NORTE
A31: 7927396052 | B31: NOJA RC10 | C31: 34,5 kV | D31: =LEFT(Table1[[#This Row],[Ativo]],2) -> 79 | F31: ETO-COEP 00045/2026 | G31: Média | H31: Avaliar compra | I31: Tanque 34,5 | J31: 13209.34 | K31: 38151.48 | L31: 51360.82 | M31: 38295 | W31: 68 | X31: 86 | Y31: 181 | Z31: 167 - DIAS AGUARDANDO DCMD | AA31: COEP | AB31: 95 - DIAS FORA DO PRAZO | AD31: LD03036052 - LD FORMOSO A COOPERFORMOSO | AE31: FORMOSO DO ARAGUAIA | AF31: ALVORADA | AG31: SUL
A32: 7933585074 | B32: NOJA RC10 | C32: 34,5 kV | D32: =LEFT(Table1[[#This Row],[Ativo]],2) -> 79 | F32: ETO-COEP 00024/2026 | G32: Média | H32: Avaliar compra | I32: Tanque 34,5 | J32: 13209.34 | K32: 38151.48 | L32: 51360.82 | M32: 38295 | W32: 69 | X32: 86 | Y32: 202 | Z32: 201 - DIAS AGUARDANDO DCMD | AA32: COEP | AB32: 116 - DIAS FORA DO PRAZO | AD32: LD03028074 - LD DIANOPOLIS A REGIAO GERAIS | AE32: DIANOPOLIS | AF32: DIANOPOLIS | AG32: SUL
A33: 5855411017 | B33: ROMAGNOLE | C33: 13,8 kV | D33: =LEFT(Table1[[#This Row],[Ativo]],2) -> 58 | E33: 250 kVA | F33: ETO-COEP 00156/2026 | G33: Baixa | H33: Em logistica (N1>N3) | I33: Controle 200 13,8 | J33: 20000 | K33: 23259.6 | L33: 43259.6 | M33: 38291 | N33: Ainda não | O33: 0212600671 | W33: 79 | X33: 134 | Y33: 348 | Z33: 23 - DIAS AGUARDANDO DCMD | AA33: COEP | AB33: 214 - DIAS FORA DO PRAZO | AD33: AL02017017 - AL 2 SE BARROLANDIA | AE33: BARROLANDIA | AF33: MIRACEMA DO TOCANTINS | AG33: CENTRO
A34: 7908196047 | B34: COOPER F6 | C34: 13,8 kV | D34: =LEFT(Table1[[#This Row],[Ativo]],2) -> 79 | F34: ETO-COEP 00168/2026 | G34: Baixa | H34: Avaliar compra | I34: RL Completo 13,8 | J34: 11016.94 | K34: 55602.54 | L34: 66619.48 | M34: 38294+38296 | W34: 81 | X34: 134 | Y34: 322 | Z34: 13 - DIAS AGUARDANDO DCMD | AA34: COEP | AB34: 188 - DIAS FORA DO PRAZO | AD34: AL02033047 - AL 2 SE FIGUEIROPOLIS | AE34: FIGUEIROPOLIS | AF34: ALVORADA | AG34: SUL
A35: 7921202014 | B35: NOJA RC10 | C35: 34,5 kV | D35: =LEFT(Table1[[#This Row],[Ativo]],2) -> 79 | F35: ETO-COEP 00132/2026 | G35: Baixa | H35: Avaliar compra | I35: Tanque 34,5 | J35: 13209.34 | K35: 38151.48 | L35: 51360.82 | M35: Sem PMA | W35: 82 | X35: 134 | Y35: 183 | Z35: 40 - DIAS AGUARDANDO DCMD | AA35: COEP | AB35: 49 - DIAS FORA DO PRAZO | AD35: LD01025012 - LD CRISTALANDIA A LAGOA DA CONFUSAO | AE35: PIUM | AF35: PARAISO DO TOCANTINS | AG35: CENTRO
A36: 7923927122 | B36: NOJA RC10 | C36: 34,5 kV | D36: =LEFT(Table1[[#This Row],[Ativo]],2) -> 79 | F36: ETO-COEP 00148/2026 | G36: Baixa | H36: Avaliar compra | I36: Tanque 34,5 | J36: 13209.34 | K36: 38151.48 | L36: 51360.82 | M36: Sem PMA | W36: 83 | X36: 134 | Y36: 477 | Z36: 32 - DIAS AGUARDANDO DCMD | AA36: COEP | AB36: 343 - DIAS FORA DO PRAZO | AD36: LD02059122 - LD PALMAS I I A TAQUARALTO | AE36: PALMAS | AF36: PALMAS | AG36: CENTRO
A37: 7927446001 | B37: TAVRIDA | C37: 34,5 kV | D37: =LEFT(Table1[[#This Row],[Ativo]],2) -> 79 | F37: ETO-COEP 00143/2025 | G37: Baixa | H37: Avaliar compra | I37: RL Completo 34,5 | J37: 13209.34 | K37: 76246.2 | L37: 89455.54 | M37: Sem PMA | W37: 84 | X37: 134 | Y37: 417 | Z37: 404 - DIAS AGUARDANDO DCMD | AA37: COEP | AB37: 283 - DIAS FORA DO PRAZO | AD37: LD02072001 - LD PORTO NACIONAL A SILVANOPOLIS | AE37: PORTO NACIONAL | AF37: PORTO NACIONAL | AG37: CENTRO
A38: 7928241200 | B38: NOJA RC10 | C38: 34,5 kV | D38: =LEFT(Table1[[#This Row],[Ativo]],2) -> 79 | F38: ETO-COEP 00128/2026 | G38: Baixa | H38: Avaliar compra | I38: Tanque 34,5 | J38: 13209.34 | K38: 38151.48 | L38: 51360.82 | M38: Sem PMA | W38: 85 | X38: 134 | Y38: 409 | Z38: 40 - DIAS AGUARDANDO DCMD | AA38: COEP | AB38: 275 - DIAS FORA DO PRAZO | AD38: LD02066094 - LD UHE PEIXE A SAO SALVADOR | AE38: SAO SALVADOR DO TOCANTINS | AF38: PEIXE | AG38: SUL
A39: 7942485096 | B39: NOJA RC10 | C39: 34,5 kV | D39: =LEFT(Table1[[#This Row],[Ativo]],2) -> 79 | F39: ETO-COEP 00158/2025 | G39: Baixa | H39: Avaliar compra | I39: Tanque 34,5 | J39: 13209.34 | K39: 38151.48 | L39: 51360.82 | M39: Sem PMA | W39: 86 | X39: 134 | Y39: 521 | Z39: 390 - DIAS AGUARDANDO DCMD | AA39: COEP | AB39: 387 - DIAS FORA DO PRAZO | AD39: LD03046026 - LD UHE ISAMU A PONTE ALTA | AE39: PINDORAMA DO TOCANTINS | AF39: PONTE ALTA TOCANTINS | AG39: CENTRO
A40: 7955946007 | B40: NOJA RC10 | C40: 34,5 kV | D40: =LEFT(Table1[[#This Row],[Ativo]],2) -> 79 | F40: ETO-COEP 00134/2026 | G40: Baixa | H40: Avaliar compra | I40: Controle 34,5 | J40: 13209.34 | K40: 38094.72 | L40: 51304.06 | M40: Sem PMA | W40: 89 | X40: 134 | Y40: 40 | Z40: 40 - DIAS AGUARDANDO DCMD | AA40: COEP | AB40: VENCE EM: 94 DIAS | AD40: LD05050008 - LD MIRANORTE A MIRACEMA | AE40: MIRACEMA DO TOCANTINS | AF40: MIRACEMA DO TOCANTINS | AG40: CENTRO
A41: 7901110084 | B41: NOJA RC10 | C41: 34,5 kV | D41: =LEFT(Table1[[#This Row],[Ativo]],2) -> 79 | F41: ETO-COEP 00061/2026 | G41: Baixa | H41: Avaliar compra | I41: Tanque 34,5 | J41: 13209.34 | K41: 38151.48 | L41: 51360.82 | M41: Sem PMA | W41: 90 | X41: 134 | Y41: 243 | Z41: 139 - DIAS AGUARDANDO DCMD | AA41: COEP | AB41: 109 - DIAS FORA DO PRAZO | AD41: LD04062013 - LD SE PARAISO I A DIVINOPOLIS | AE41: DIVINOPOLIS | AF41: DIVINOPOLIS | AG41: CENTRO
A42: 7910027196 | B42: COOPER F6 | C42: 34,5 kV | D42: =LEFT(Table1[[#This Row],[Ativo]],2) -> 79 | F42: ETO-COEP 00154/2026 | G42: Baixa | H42: Avaliar compra | I42: RL Completo 34,5 | J42: 13209.34 | K42: 76246.2 | L42: 89455.54 | M42: Sem PMA | W42: 93 | X42: 134 | Y42: 40 | Z42: 26 - DIAS AGUARDANDO DCMD | AA42: COEP | AB42: VENCE EM: 94 DIAS | AD42: LD02059122 - LD PALMAS I I A TAQUARALTO | AE42: LAGOA DO TOCANTINS | AF42: TAQUARALTO | AG42: CENTRO
A43: 7913662076 | B43: NOJA RC10 | C43: 13,8 kV | D43: =LEFT(Table1[[#This Row],[Ativo]],2) -> 79 | F43: ETO-COEP 00114/2026 | G43: Baixa | H43: Avaliar compra | I43: Tanque 13,8 | J43: 11016.94 | K43: 21785.72 | L43: 32802.66 | M43: 38294 | W43: 94 | X43: 134 | Y43: 70 | Z43: 67 - DIAS AGUARDANDO DCMD | AA43: COEP | AB43: VENCE EM: 64 DIAS | AD43: AL01031076 - AL 1 SE DUERE | AE43: DUERE | AF43: GURUPI | AG43: SUL
A44: 5862236091 | B44: ITB | C44: 34,5 kV | D44: =LEFT(Table1[[#This Row],[Ativo]],2) -> 58 | E44: 400 kVA | F44: ETO-COEP 00158/2026 | G44: Baixa | H44: Avaliar compra | I44: Célula 400 34,5 | J44: 80318.5 | K44: 90230 | L44: 170548.5 | M44: Sem PMA | N44: NA | O44: NA | P44: Ainda Não | Q44: Ainda não | R44: Não | S44: Não | T44: Não | U44: Não | V44: Não | W44: 95 | X44: 134 | Y44: 252 | Z44: 20 - DIAS AGUARDANDO DCMD | AA44: COEP | AB44: 118 - DIAS FORA DO PRAZO | AD44: LD05002091 - LD ALMAS A RAMAL VALE RIO DOCE | AE44: ALMAS | AF44: DIANOPOLIS | AG44: SUL
A45: 5836786094 | B45: ITB | C45: 34,5 kV | D45: =LEFT(Table1[[#This Row],[Ativo]],2) -> 58 | E45: 398 kVA | F45: ETO-COEP 00095/2026 | G45: Baixa | H45: Reforma | I45: Célula 400 34,5 | J45: 80318.5 | K45: 90230 | L45: 170548.5 | M45: Sem PMA | W45: 96 | X45: 134 | Y45: 123 | Z45: 91 - DIAS AGUARDANDO DCMD | AA45: COEP | AB45: VENCE EM: 11 DIAS | AD45: LD01066094 - LD UHE PEIXE A SAO VALERIO | AE45: PEIXE | AF45: PEIXE | AG45: SUL
A46: 7919270014 | B46: COOPER F6 | C46: 34,5 kV | D46: =LEFT(Table1[[#This Row],[Ativo]],2) -> 79 | F46: ETO-COEP 00159/2026 | G46: Baixa | H46: Avaliar compra | I46: Controle 34,5 | J46: 13209.34 | K46: 38094.72 | L46: 51304.06 | M46: Sem PMA | W46: 97 | X46: 134 | Y46: 173 | Z46: 20 - DIAS AGUARDANDO DCMD | AA46: COEP | AB46: 39 - DIAS FORA DO PRAZO | AD46: LD01047073 - LD LAGOA DA CONFUSAO A BARREIRA DA CRUZ | AE46: PIUM | AF46: PARAISO DO TOCANTINS | AG46: CENTRO
A47: 7926442035 | B47: NOJA RC10 | C47: 34,5 kV | D47: =LEFT(Table1[[#This Row],[Ativo]],2) -> 79 | F47: ETO-COEP 00051/2026 | G47: Baixa | H47: Avaliar compra | I47: Tanque 34,5 | J47: 13209.34 | K47: 38151.48 | L47: 51360.82 | M47: Sem PMA | W47: 98 | X47: 134 | Y47: 180 | Z47: 151 - DIAS AGUARDANDO DCMD | AA47: COEP | AB47: 46 - DIAS FORA DO PRAZO | AD47: LD01051035 - LD MONTE CARMO A SANTA ROSA | AE47: MONTE DO CARMO | AF47: PONTE ALTA TOCANTINS | AG47: CENTRO
A48: 7938137007 | B48: SCHNEIDER ADVC | C48: 13,8 kV | D48: =LEFT(Table1[[#This Row],[Ativo]],2) -> 79 | F48: ETO-COEP 00144/2026 | G48: Baixa | H48: Avaliar compra | I48: RL Completo 13,8 | J48: 11016.94 | K48: 55602.54 | L48: 66619.48 | M48: 38294+38296 | W48: 100 | X48: 134 | Y48: 234 | Z48: 33 - DIAS AGUARDANDO DCMD | AA48: COEP | AB48: 100 - DIAS FORA DO PRAZO | AD48: AL02017017 - AL 2 SE BARROLANDIA | AE48: MIRACEMA DO TOCANTINS | AF48: MIRACEMA DO TOCANTINS | AG48: CENTRO
A49: 5856156091 | B49: ITB | C49: 34,5 kV | D49: =LEFT(Table1[[#This Row],[Ativo]],2) -> 58 | E49: 400 kVA | F49: ETO-COEP 00160/2026 | G49: Baixa | H49: Avaliar compra | I49: RT Completo 400 34,5 | J49: 200637 | K49: 293949.6 | L49: 494586.6 | M49: Sem PMA | W49: 101 | X49: 134 | Y49: 427 | Z49: 20 - DIAS AGUARDANDO DCMD | AA49: COEP | AB49: 293 - DIAS FORA DO PRAZO | AD49: LD04002091 - LD 04 ALMAS NATIVIDADE AO POV PRINCIPE | AE49: ALMAS | AF49: DIANOPOLIS | AG49: SUL
A50: 5858783119 | B50: ITB | C50: 34,5 kV | D50: =LEFT(Table1[[#This Row],[Ativo]],2) -> 58 | E50: 400 kVA | F50: ETO-COEP 00164/2026 | G50: Baixa | H50: Avaliar compra | I50: RT Completo 400 34,5 | J50: 200637 | K50: 293949.6 | L50: 494586.6 | M50: Sem PMA | W50: 102 | X50: 134 | Y50: 511 | Z50: 16 - DIAS AGUARDANDO DCMD | AA50: COEP | AB50: 377 - DIAS FORA DO PRAZO | AD50: LD03005098 - LD ANANAS A CACHOEIRINHA | AE50: SAO BENTO DO TOCANTINS | AF50: TOCANTINOPOLIS | AG50: NORTE
A51: 7930359149 | B51: NOJA RC10 (inferido) | C51: 34,5 kV | D51: =LEFT(Table1[[#This Row],[Ativo]],2) -> 79 | F51: ETO-COEP 00138/2026 | G51: Falta definir | H51: Avaliar compra | I51: RL Completo 34,5 | J51: 13209.34 | K51: 76246.2 | L51: 89455.54 | M51: Sem PMA | W51: 107 | Y51: 54 | Z51: 35 - DIAS AGUARDANDO DCMD | AA51: COEP | AD51: LD03414149 - LD CASEARA A MARIANOPOLIS | AE51: CASEARA | AF51: DIVINOPOLIS | AG51: CENTRO
A52: 7953211079 | B52: NOJA RC10 | C52: 34,5 kV | D52: =LEFT(Table1[[#This Row],[Ativo]],2) -> 79 | F52: ETO-COEP 00147/2026 | G52: Falta definir | H52: Avaliar compra | I52: Controle 34,5 | J52: 13209.34 | K52: 38094.72 | L52: 51304.06 | M52: Sem PMA | W52: 109 | Y52: 33 | Z52: 32 - DIAS AGUARDANDO DCMD | AA52: COEP | AD52: LD03038009 - LD GUARAI I I A PRES KENNEDY | AE52: ITAPIRATINS | AF52: GUARAI | AG52: NORTE
A53: 5825703064 | B53: TOSHIBA | C53: 34,5 kV | D53: =LEFT(Table1[[#This Row],[Ativo]],2) -> 58 | E53: 200 kVA | F53: ETO-COEP 00153/2026 | G53: Falta definir | H53: Reforma | I53: Controle 200 34,5 | J53: 20000 | K53: 23259.6 | L53: 43259.6 | M53: 38291 | W53: 137 | Y53: 56 | Z53: 26 - DIAS AGUARDANDO DCMD | AA53: COEP | AD53: LD02020023 - LD COLINAS A PRES. KENNEDY | AE53: BRASILANDIA DO TOCANTINS | AF53: GUARAI | AG53: NORTE
A54: 7931219078 | B54: NOJA RC10 | C54: 34,5 kV | D54: =LEFT(Table1[[#This Row],[Ativo]],2) -> 79 | F54: ETO-RD-PO 00183/2026 | G54: Falta definir | H54: Em execução | I54: Acessório 34,5 | J54: 0 | K54: 15000 | L54: 15000 | M54: Sem PMA | N54: NA | O54: NA | P54: Ainda Não | Q54: Ainda não | R54: 46279 | S54: Não | T54: Não | U54: Não | W54: 145 | Y54: 420 | Z54: 40 - DIAS AGUARDANDO DCMD | AA54: COCM-C | AD54: LD01065015 - LD PEDRO AFONSO A SANTA.MARIA | AE54: ITACAJA | AF54: GUARAI | AG54: NORTE
E59: Compra | I59: Muito Alta e Alta | J59: Sobra | M59: Média
A60: 7900117013 | B60: 690001 · Tanque / Parte ativa — Religador 13,8 kV | E60: 7 | F60: Completo 34,5 | G60: Controle +Tanque | H60: 3 | I60: Completo 34,5 | J60: =E60-H60 -> 4 | L60: 4 | M60: Completo 34,5 | N60: =J60-L60 -> 0
A61: 7900117013 | B61: 690916 · Controle — Religador 13,8 kV | E61: 6 | F61: Tanque 34,5 | H61: 4 | I61: Tanque 34,5 | J61: =E61-H61 -> 2 | L61: 2 | M61: Tanque 34,5 | Q61: {=+S60Q54Q60:Q61} -> #NAME?
A62: 7900453110 | B62: 690005 · Tanque / Parte ativa — Religador 34,5 kV | E62: 5 | F62: Completo 13,5 | H62: 3 | I62: Completo 13,5 | J62: =E62-H62 -> 2 | M62: Completo 13,5
A63: 7900453110 | B63: 692263 · Controle — Religador 34,5 kV | E63: 3 | F63: Tanque 13,5 | H63: 1 | I63: Tanque 13,5 | J63: =E63-H63 -> 2 | M63: Tanque 13,5
A64: 7900573047 | B64: 690001 · Tanque / Parte ativa — Religador 13,8 kV
A65: 7900573047 | B65: 690916 · Controle — Religador 13,8 kV
A66: 7900594026 | B66: 690005 · Tanque / Parte ativa — Religador 34,5 kV
A67: 7900594026 | B67: 692263 · Controle — Religador 34,5 kV
A68: 7903112004 | B68: 690005 · Tanque / Parte ativa — Religador 34,5 kV
A69: 7903112004 | B69: 692263 · Controle — Religador 34,5 kV
A70: 7908686014 | B70: 690005 · Tanque / Parte ativa — Religador 34,5 kV
A71: 7908705049 | B71: 690001 · Tanque / Parte ativa — Religador 13,8 kV
A72: 7908705049 | B72: 690916 · Controle — Religador 13,8 kV
A73: 7920024127 | B73: 690005 · Tanque / Parte ativa — Religador 34,5 kV
A74: 7920024127 | B74: 692263 · Controle — Religador 34,5 kV
A75: 7920024127 | B75: 90556 · Chave faca
... A99: 5856070091 | B99: 690241 · Célula — Regulador 34,5 kV / 400 kVA

Sheet Base
A1: Status | C1: FAIXA DE TENSÃO | D1: TIPO | E1: Ano2 | F1: Mês | G1: Concat | H1: Qtd RL Fora | I1: Parque RL | J1: RL 13 | K1: RL 34 | L1: Qtd RT 13 | M1: RT13 | N1: RT 34 | O1: Acumulado | Q1: RL 34,5 | R1: RL 13,5
A2: Concluído | C2: 34.500 | D2: RL | E2: 2025 | F2: janeiro | G2: =_xlfn.CONCAT(Tabela17[[#This Row],[FAIXA DE TENSÃO]],Tabela17[[#This Row],[TIPO]],Tabela17[[#This Row],[Ano2]],Tabela17[[#This Row],[Mês]]) -> 34.500RL2025janeiro | H2: 1 | I2: 1281 | J2: 200 | K2: 1081 | L2: 180 | Q2: 1081 | R2: 200 | S2: =Q2/1291 -> 0.8373354 | T2: =1-S2 -> 0.1626646
A3: Em execução | C3: 34.500 | D3: RL | E3: 2025 | F3: fevereiro | G3: =_xlfn.CONCAT(Tabela17[[#This Row],[FAIXA DE TENSÃO]],Tabela17[[#This Row],[TIPO]],Tabela17[[#This Row],[Ano2]],Tabela17[[#This Row],[Mês]]) -> 34.500RL2025fevereiro | H3: 1 | I3: 1281 | J3: 200 | K3: 1081 | L3: 180 | Q3: RT 34,5 | R3: RT 13,8
A4: Em logistica (N1>N3) | C4: 34.500 | D4: RL | E4: 2025 | F4: março | G4: =_xlfn.CONCAT(Tabela17[[#This Row],[FAIXA DE TENSÃO]],Tabela17[[#This Row],[TIPO]],Tabela17[[#This Row],[Ano2]],Tabela17[[#This Row],[Mês]]) -> 34.500RL2025março | H4: 2 | I4: 1281 | J4: 200 | K4: 1081 | L4: 180 | Q4: 137 | R4: =291-137 -> 154
A5: Gerado PMA | C5: 34.500 | D5: RL | E5: 2025 | F5: abril | G5: =_xlfn.CONCAT(Tabela17[[#This Row],[FAIXA DE TENSÃO]],Tabela17[[#This Row],[TIPO]],Tabela17[[#This Row],[Ano2]],Tabela17[[#This Row],[Mês]]) -> 34.500RL2025abril | H5: 2 | I5: 1281 | J5: 200 | K5: 1081 | L5: 180
A6: Reforma | C6: 34.500 | D6: RL | E6: 2025 | F6: maio | G6: =_xlfn.CONCAT(Tabela17[[#This Row],[FAIXA DE TENSÃO]],Tabela17[[#This Row],[TIPO]],Tabela17[[#This Row],[Ano2]],Tabela17[[#This Row],[Mês]]) -> 34.500RL2025maio | H6: 7 | I6: 1281 | J6: 200 | K6: 1081 | L6: 180
A7: Avaliar compra | C7: 34.500 | D7: RL | E7: 2025 | F7: junho | G7: =_xlfn.CONCAT(Tabela17[[#This Row],[FAIXA DE TENSÃO]],Tabela17[[#This Row],[TIPO]],Tabela17[[#This Row],[Ano2]],Tabela17[[#This Row],[Mês]]) -> 34.500RL2025junho | H7: 4 | I7: 1281 | J7: 200 | K7: 1081 | L7: 180 | Q7: Categoria | R7: Tensão (kV) | S7: Valor Material | T7: Mão de obra | U7: Total | V7: Composição | W7: Códigos
C8: 34.500 | D8: RL | E8: 2025 | F8: julho | G8: =_xlfn.CONCAT(Tabela17[[#This Row],[FAIXA DE TENSÃO]],Tabela17[[#This Row],[TIPO]],Tabela17[[#This Row],[Ano2]],Tabela17[[#This Row],[Mês]]) -> 34.500RL2025julho | H8: 5 | I8: 1281 | J8: 200 | K8: 1081 | L8: 180 | Q8: RL Completo 13,8 | R8: 13,8 | S8: 55602.54 | T8: 11016.94 | U8: =SUM(S8:T8) -> 66619.48 | V8: Religador + Controle | W8: 690001 + 690916
C9: 34.500 | D9: RL | E9: 2025 | F9: agosto | G9: =_xlfn.CONCAT(Tabela17[[#This Row],[FAIXA DE TENSÃO]],Tabela17[[#This Row],[TIPO]],Tabela17[[#This Row],[Ano2]],Tabela17[[#This Row],[Mês]]) -> 34.500RL2025agosto | H9: 2 | I9: 1281 | J9: 200 | K9: 1081 | L9: 180 | Q9: RL Completo 34,5 | R9: 34,5 | S9: 76246.2 | T9: 13209.34 | U9: =SUM(S9:T9) -> 89455.54 | V9: Religador + Controle | W9: 690005 + 692263
C10: 34.500 | D10: RL | E10: 2025 | F10: setembro | G10: =_xlfn.CONCAT(Tabela17[[#This Row],[FAIXA DE TENSÃO]],Tabela17[[#This Row],[TIPO]],Tabela17[[#This Row],[Ano2]],Tabela17[[#This Row],[Mês]]) -> 34.500RL2025setembro | H10: 2 | I10: 1281 | J10: 200 | K10: 1081 | L10: 180 | Q10: Tanque 13,8 | R10: 13,8 | S10: 21785.72 | T10: 11016.94 | U10: =SUM(S10:T10) -> 32802.66 | V10: Só religador | W10: 690001
C11: 34.500 | D11: RL | E11: 2025 | F11: outubro | G11: =_xlfn.CONCAT(Tabela17[[#This Row],[FAIXA DE TENSÃO]],Tabela17[[#This Row],[TIPO]],Tabela17[[#This Row],[Ano2]],Tabela17[[#This Row],[Mês]]) -> 34.500RL2025outubro | H11: 4 | I11: 1281 | J11: 200 | K11: 1081 | L11: 180 | Q11: Tanque 34,5 | R11: 34,5 | S11: 38151.48 | T11: 13209.34 | U11: =SUM(S11:T11) -> 51360.82 | V11: Só religador | W11: 690005
C12: 34.500 | D12: RL | E12: 2025 | F12: novembro | G12: =_xlfn.CONCAT(Tabela17[[#This Row],[FAIXA DE TENSÃO]],Tabela17[[#This Row],[TIPO]],Tabela17[[#This Row],[Ano2]],Tabela17[[#This Row],[Mês]]) -> 34.500RL2025novembro | H12: 1 | I12: 1281 | J12: 200 | K12: 1081 | L12: 180 | Q12: Controle 13,8 | R12: 13,8 | S12: 33816.82 | T12: 11016.94 | U12: =SUM(S12:T12) -> 44833.76 | V12: Só controle | W12: 690916
C13: 34.500 | D13: RL | E13: 2025 | F13: dezembro | G13: =_xlfn.CONCAT(Tabela17[[#This Row],[FAIXA DE TENSÃO]],Tabela17[[#This Row],[TIPO]],Tabela17[[#This Row],[Ano2]],Tabela17[[#This Row],[Mês]]) -> 34.500RL2025dezembro | H13: 4 | I13: 1281 | J13: 200 | K13: 1081 | L13: 180 | Q13: Controle 34,5 | R13: 34,5 | S13: 38094.72 | T13: 13209.34 | U13: =SUM(S13:T13) -> 51304.06 | V13: Só controle | W13: 692263
C14: 34.500 | D14: RL | E14: 2026 | F14: janeiro | G14: =_xlfn.CONCAT(Tabela17[[#This Row],[FAIXA DE TENSÃO]],Tabela17[[#This Row],[TIPO]],Tabela17[[#This Row],[Ano2]],Tabela17[[#This Row],[Mês]]) -> 34.500RL2026janeiro | H14: 6 | I14: 1283 | J14: 200 | K14: 1081 | L14: 180
C15: 34.500 | D15: RL | E15: 2026 | F15: fevereiro | G15: =_xlfn.CONCAT(Tabela17[[#This Row],[FAIXA DE TENSÃO]],Tabela17[[#This Row],[TIPO]],Tabela17[[#This Row],[Ano2]],Tabela17[[#This Row],[Mês]]) -> 34.500RL2026fevereiro | H15: 7 | I15: 1283 | J15: 200 | K15: 1081 | L15: 180
C16: 34.500 | D16: RL | E16: 2026 | F16: março | G16: =_xlfn.CONCAT(Tabela17[[#This Row],[FAIXA DE TENSÃO]],Tabela17[[#This Row],[TIPO]],Tabela17[[#This Row],[Ano2]],Tabela17[[#This Row],[Mês]]) -> 34.500RL2026março | H16: 8 | I16: 1285 | J16: 200 | K16: 1081 | L16: 180
C17: 34.500 | D17: RL | E17: 2026 | F17: abril | G17: =_xlfn.CONCAT(Tabela17[[#This Row],[FAIXA DE TENSÃO]],Tabela17[[#This Row],[TIPO]],Tabela17[[#This Row],[Ano2]],Tabela17[[#This Row],[Mês]]) -> 34.500RL2026abril | H17: 3 | I17: 1287 | J17: 200 | K17: 1081 | L17: 180 | Q17: Categoria | R17: Tensão / kVA | S17: R$ por célula | T17: Mão de obra | U17: Total | V17: Composição | W17: Código
C18: 34.500 | D18: RL | E18: 2026 | F18: maio | G18: =_xlfn.CONCAT(Tabela17[[#This Row],[FAIXA DE TENSÃO]],Tabela17[[#This Row],[TIPO]],Tabela17[[#This Row],[Ano2]],Tabela17[[#This Row],[Mês]]) -> 34.500RL2026maio | H18: 0 | I18: 1290 | J18: 200 | K18: 1081 | L18: 180 | Q18: Célula 200 13,8 | R18: 13,8 / 239 kVA | S18: 62113.2 | T18: 51402.14 | U18: =SUM(S18:T18) -> 113515.34 | V18: Celula | W18: 690236
C19: 34.500 | D19: RL | E19: 2026 | F19: junho | G19: =_xlfn.CONCAT(Tabela17[[#This Row],[FAIXA DE TENSÃO]],Tabela17[[#This Row],[TIPO]],Tabela17[[#This Row],[Ano2]],Tabela17[[#This Row],[Mês]]) -> 34.500RL2026junho | H19: 1 | I19: 1291 | J19: 200 | K19: 1081 | L19: 180 | Q19: Célula 167 13,8 | R19: 13,8 / 167 kVA | S19: 27616.62 | T19: 51402.14 | U19: =SUM(S19:T19) -> 79018.76 | W19: 690669
C20: 34.500 | D20: RL | E20: 2026 | F20: julho | G20: =_xlfn.CONCAT(Tabela17[[#This Row],[FAIXA DE TENSÃO]],Tabela17[[#This Row],[TIPO]],Tabela17[[#This Row],[Ano2]],Tabela17[[#This Row],[Mês]]) -> 34.500RL2026julho | H20: 3 | I20: 1294 | J20: 200 | K20: 1081 | L20: 180 | Q20: Célula 200 13,8 | R20: 34,5 / 200 kVA | S20: 51705.75 | T20: 80318.5 | U20: =SUM(S20:T20) -> 132024.25 | W20: 690240
C21: 34.500 | D21: RL | E21: 2026 | F21: agosto | G21: =_xlfn.CONCAT(Tabela17[[#This Row],[FAIXA DE TENSÃO]],Tabela17[[#This Row],[TIPO]],Tabela17[[#This Row],[Ano2]],Tabela17[[#This Row],[Mês]]) -> 34.500RL2026agosto | H21: 0 | I21: 1294 | J21: 200 | K21: 1081 | L21: 180 | Q21: Célula 400 34,5 | R21: 34,5 / 400 kVA | S21: 90230 | T21: 80318.5 | U21: =SUM(S21:T21) -> 170548.5 | W21: 690241
C22: 34.500 | D22: RL | E22: 2026 | F22: setembro | G22: =_xlfn.CONCAT(Tabela17[[#This Row],[FAIXA DE TENSÃO]],Tabela17[[#This Row],[TIPO]],Tabela17[[#This Row],[Ano2]],Tabela17[[#This Row],[Mês]]) -> 34.500RL2026setembro | I22: 1294 | J22: 200 | K22: 1081 | L22: 180 | Q22: Controle 200 13,8 | R22: Relé de Sincronismo | S22: 23259.6 | T22: 20000 | U22: =SUM(S22:T22) -> 43259.6 | V22: Controle (relé sincronismo) | W22: 616033
C23: 34.500 | D23: RL | E23: 2026 | F23: outubro | G23: =_xlfn.CONCAT(Tabela17[[#This Row],[FAIXA DE TENSÃO]],Tabela17[[#This Row],[TIPO]],Tabela17[[#This Row],[Ano2]],Tabela17[[#This Row],[Mês]]) -> 34.500RL2026outubro | I23: 1294 | J23: 200 | K23: 1081 | L23: 180 | Q23: Célula 200 34,5 | R23: 13,8 / 200 kVA | S23: 51705.75 | T23: 80318.5 | U23: =SUM(S23:T23) -> 132024.25 | W23: 690240
C24: 34.500 | D24: RL | E24: 2026 | F24: novembro | G24: =_xlfn.CONCAT(Tabela17[[#This Row],[FAIXA DE TENSÃO]],Tabela17[[#This Row],[TIPO]],Tabela17[[#This Row],[Ano2]],Tabela17[[#This Row],[Mês]]) -> 34.500RL2026novembro | I24: 1294 | J24: 200 | K24: 1081 | L24: 180 | Q24: Controle 167 13,8 | R24: Relé de Sincronismo | S24: 23259.6 | T24: 20000 | U24: =SUM(S24:T24) -> 43259.6
C25: 34.500 | D25: RL | E25: 2026 | F25: dezembro | G25: =_xlfn.CONCAT(Tabela17[[#This Row],[FAIXA DE TENSÃO]],Tabela17[[#This Row],[TIPO]],Tabela17[[#This Row],[Ano2]],Tabela17[[#This Row],[Mês]]) -> 34.500RL2026dezembro | I25: 1294 | J25: 200 | K25: 1081 | L25: 180 | Q25: Controle 200 13,8 | R25: Relé de Sincronismo | S25: 23259.6 | T25: 20000 | U25: =SUM(S25:T25) -> 43259.6
C26: 34.500 | D26: RT | E26: 2025 | F26: janeiro | G26: =_xlfn.CONCAT(Tabela17[[#This Row],[FAIXA DE TENSÃO]],Tabela17[[#This Row],[TIPO]],Tabela17[[#This Row],[Ano2]],Tabela17[[#This Row],[Mês]]) -> 34.500RT2025janeiro | J26: 200 | K26: 1081 | L26: 180 | Q26: Controle 400 34,5 | R26: Relé de Sincronismo | S26: 23259.6 | T26: 20000 | U26: =SUM(S26:T26) -> 43259.6
C27: 34.500 | D27: RT | E27: 2025 | F27: fevereiro | G27: =_xlfn.CONCAT(Tabela17[[#This Row],[FAIXA DE TENSÃO]],Tabela17[[#This Row],[TIPO]],Tabela17[[#This Row],[Ano2]],Tabela17[[#This Row],[Mês]]) -> 34.500RT2025fevereiro | J27: 200 | K27: 1081 | L27: 180 | Q27: RT Completo 400 34,5 | R27: Controle+Célula 34,5 400KVA | S27: 293949.6 | T27: 200637 | U27: =SUM(S27:T27) -> 494586.6
C28: 34.500 | D28: RT | E28: 2025 | F28: março | G28: =_xlfn.CONCAT(Tabela17[[#This Row],[FAIXA DE TENSÃO]],Tabela17[[#This Row],[TIPO]],Tabela17[[#This Row],[Ano2]],Tabela17[[#This Row],[Mês]]) -> 34.500RT2025março | J28: 200 | K28: 1081 | L28: 180 | Q28: Acessório 400 34,5 | R28: Aterramento | S28: 15000 | U28: =SUM(S28:T28) -> 15000
C29: 34.500 | D29: RT | E29: 2025 | F29: abril | G29: =_xlfn.CONCAT(Tabela17[[#This Row],[FAIXA DE TENSÃO]],Tabela17[[#This Row],[TIPO]],Tabela17[[#This Row],[Ano2]],Tabela17[[#This Row],[Mês]]) -> 34.500RT2025abril | J29: 200 | K29: 1081 | L29: 180 | Q29: Aterramento 34,5 | R29: Aterramento | S29: 15000 | U29: =SUM(S29:T29) -> 15000
C30: 34.500 | D30: RT | E30: 2025 | F30: maio | G30: =_xlfn.CONCAT(Tabela17[[#This Row],[FAIXA DE TENSÃO]],Tabela17[[#This Row],[TIPO]],Tabela17[[#This Row],[Ano2]],Tabela17[[#This Row],[Mês]]) -> 34.500RT2025maio | J30: 200 | K30: 1081 | L30: 180 | Q30: Acessório 34,5 | R30: Aterramento | S30: 15000 | U30: =SUM(S30:T30) -> 15000
C31: 34.500 | D31: RT | E31: 2025 | F31: junho | G31: =_xlfn.CONCAT(Tabela17[[#This Row],[FAIXA DE TENSÃO]],Tabela17[[#This Row],[TIPO]],Tabela17[[#This Row],[Ano2]],Tabela17[[#This Row],[Mês]]) -> 34.500RT2025junho | J31: 200 | K31: 1081 | L31: 180 | Q31: Controle 200 34,5 | R31: Relé de Sincronismo | S31: 23259.6 | T31: 20000 | U31: =SUM(S31:T31) -> 43259.6
C32: 34.500 | D32: RT | E32: 2025 | F32: julho | G32: =_xlfn.CONCAT(Tabela17[[#This Row],[FAIXA DE TENSÃO]],Tabela17[[#This Row],[TIPO]],Tabela17[[#This Row],[Ano2]],Tabela17[[#This Row],[Mês]]) -> 34.500RT2025julho | J32: 200 | K32: 1081 | L32: 180
C33: 34.500 | D33: RT | E33: 2025 | F33: agosto | G33: =_xlfn.CONCAT(Tabela17[[#This Row],[FAIXA DE TENSÃO]],Tabela17[[#This Row],[TIPO]],Tabela17[[#This Row],[Ano2]],Tabela17[[#This Row],[Mês]]) -> 34.500RT2025agosto | J33: 200 | K33: 1081 | L33: 180
C34: 34.500 | D34: RT | E34: 2025 | F34: setembro | G34: =_xlfn.CONCAT(Tabela17[[#This Row],[FAIXA DE TENSÃO]],Tabela17[[#This Row],[TIPO]],Tabela17[[#This Row],[Ano2]],Tabela17[[#This Row],[Mês]]) -> 34.500RT2025setembro | J34: 200 | K34: 1081 | L34: 180
C35: 34.500 | D35: RT | E35: 2025 | F35: outubro | G35: =_xlfn.CONCAT(Tabela17[[#This Row],[FAIXA DE TENSÃO]],Tabela17[[#This Row],[TIPO]],Tabela17[[#This Row],[Ano2]],Tabela17[[#This Row],[Mês]]) -> 34.500RT2025outubro | J35: 200 | K35: 1081 | L35: 180
C36: 34.500 | D36: RT | E36: 2025 | F36: novembro | G36: =_xlfn.CONCAT(Tabela17[[#This Row],[FAIXA DE TENSÃO]],Tabela17[[#This Row],[TIPO]],Tabela17[[#This Row],[Ano2]],Tabela17[[#This Row],[Mês]]) -> 34.500RT2025novembro | J36: 200 | K36: 1081 | L36: 180
C37: 34.500 | D37: RT | E37: 2025 | F37: dezembro | G37: =_xlfn.CONCAT(Tabela17[[#This Row],[FAIXA DE TENSÃO]],Tabela17[[#This Row],[TIPO]],Tabela17[[#This Row],[Ano2]],Tabela17[[#This Row],[Mês]]) -> 34.500RT2025dezembro | J37: 200 | K37: 1081 | L37: 180
C38: 34.500 | D38: RT | E38: 2026 | F38: janeiro | G38: =_xlfn.CONCAT(Tabela17[[#This Row],[FAIXA DE TENSÃO]],Tabela17[[#This Row],[TIPO]],Tabela17[[#This Row],[Ano2]],Tabela17[[#This Row],[Mês]]) -> 34.500RT2026janeiro | J38: 200 | K38: 1081
C39: 34.500 | D39: RT | E39: 2026 | F39: fevereiro | G39: =_xlfn.CONCAT(Tabela17[[#This Row],[FAIXA DE TENSÃO]],Tabela17[[#This Row],[TIPO]],Tabela17[[#This Row],[Ano2]],Tabela17[[#This Row],[Mês]]) -> 34.500RT2026fevereiro | J39: 200 | K39: 1081
C40: 34.500 | D40: RT | E40: 2026 | F40: março | G40: =_xlfn.CONCAT(Tabela17[[#This Row],[FAIXA DE TENSÃO]],Tabela17[[#This Row],[TIPO]],Tabela17[[#This Row],[Ano2]],Tabela17[[#This Row],[Mês]]) -> 34.500RT2026março | J40: 200 | K40: 1081
C41: 34.500 | D41: RT | E41: 2026 | F41: abril | G41: =_xlfn.CONCAT(Tabela17[[#This Row],[FAIXA DE TENSÃO]],Tabela17[[#This Row],[TIPO]],Tabela17[[#This Row],[Ano2]],Tabela17[[#This Row],[Mês]]) -> 34.500RT2026abril | J41: 200 | K41: 1081
C42: 34.500 | D42: RT | E42: 2026 | F42: maio | G42: =_xlfn.CONCAT(Tabela17[[#This Row],[FAIXA DE TENSÃO]],Tabela17[[#This Row],[TIPO]],Tabela17[[#This Row],[Ano2]],Tabela17[[#This Row],[Mês]]) -> 34.500RT2026maio | J42: 200 | K42: 1081
C43: 34.500 | D43: RT | E43: 2026 | F43: junho | G43: =_xlfn.CONCAT(Tabela17[[#This Row],[FAIXA DE TENSÃO]],Tabela17[[#This Row],[TIPO]],Tabela17[[#This Row],[Ano2]],Tabela17[[#This Row],[Mês]]) -> 34.500RT2026junho | J43: 200 | K43: 1081
C44: 34.500 | D44: RT | E44: 2026 | F44: julho | G44: =_xlfn.CONCAT(Tabela17[[#This Row],[FAIXA DE TENSÃO]],Tabela17[[#This Row],[TIPO]],Tabela17[[#This Row],[Ano2]],Tabela17[[#This Row],[Mês]]) -> 34.500RT2026julho | J44: 200 | K44: 1081
C45: 34.500 | D45: RT | E45: 2026 | F45: agosto | G45: =_xlfn.CONCAT(Tabela17[[#This Row],[FAIXA DE TENSÃO]],Tabela17[[#This Row],[TIPO]],Tabela17[[#This Row],[Ano2]],Tabela17[[#This Row],[Mês]]) -> 34.500RT2026agosto | J45: 200 | K45: 1081
C46: 34.500 | D46: RT | E46: 2026 | F46: setembro | G46: =_xlfn.CONCAT(Tabela17[[#This Row],[FAIXA DE TENSÃO]],Tabela17[[#This Row],[TIPO]],Tabela17[[#This Row],[Ano2]],Tabela17[[#This Row],[Mês]]) -> 34.500RT2026setembro | J46: 200 | K46: 1081
C47: 34.500 | D47: RT | E47: 2026 | F47: outubro | G47: =_xlfn.CONCAT(Tabela17[[#This Row],[FAIXA DE TENSÃO]],Tabela17[[#This Row],[TIPO]],Tabela17[[#This Row],[Ano2]],Tabela17[[#This Row],[Mês]]) -> 34.500RT2026outubro | J47: 200 | K47: 1081
C48: 34.500 | D48: RT | E48: 2026 | F48: novembro | G48: =_xlfn.CONCAT(Tabela17[[#This Row],[FAIXA DE TENSÃO]],Tabela17[[#This Row],[TIPO]],Tabela17[[#This Row],[Ano2]],Tabela17[[#This Row],[Mês]]) -> 34.500RT2026novembro | J48: 200 | K48: 1081
C49: 34.500 | D49: RT | E49: 2026 | F49: dezembro | G49: =_xlfn.CONCAT(Tabela17[[#This Row],[FAIXA DE TENSÃO]],Tabela17[[#This Row],[TIPO]],Tabela17[[#This Row],[Ano2]],Tabela17[[#This Row],[Mês]]) -> 34.500RT2026dezembro | J49: 200 | K49: 1081
... C97: 13.800 | D97: RT | E97: 2026 | F97: dezembro | G97: =_xlfn.CONCAT(Tabela17[[#This Row],[FAIXA DE TENSÃO]],Tabela17[[#This Row],[TIPO]],Tabela17[[#This Row],[Ano2]],Tabela17[[#This Row],[Mês]]) -> 13.800RT2026dezembro | J97: 200 | K97: 1081

Sheet Estoque
A1: Saldo
A5: Status PMA
A6: Status PMA | B6: Data Requisição | C6: Requisição Web Supply | D6: Status
A7: 38291
A35: PMA | B35: Código | C35: Descrição | D35: Unidade | E35: QT. | F35: Valor Unitário | G35: Valor Total | H35: Finalidade | I35: Data Requisição | J35: Requisição Web Supply | K35: Ativo | L35: Status | M35: Previsão de Chegada no N1
A36: 38291 | B36: 651638 | C36: CONTROLE DE REGULADOR DE TENSAO COM NOBREAK | D36: UN | E36: 3 | F36: 29227.78 | G36: 87683.34 | H36: Material para Manutenção | I36: 46232 | J36: 29734478 | L36: Ex: Em aprovação , Cotação,Aprovação Técnica
A37: 38291 | B37: 651638 | C37: CONTROLE DE REGULADOR DE TENSAO COM NOBREAK | D37: UN | E37: 3 | F37: 29227.78 | G37: 87683.34 | H37: Material para Manutenção | I37: 46232 | J37: 29734478
A38: 38291 | B38: 651638 | C38: CONTROLE DE REGULADOR DE TENSAO COM NOBREAK | D38: UN | E38: 3 | F38: 29227.78 | G38: 87683.34 | H38: Material para Manutenção | I38: 46232 | J38: 29734478
A39: 38292 | B39: 690241 | C39: REGUL TENS AUTOM SIMET RD 1F 19,919KV 400KVA 201A ESTR CL2 | D39: UN | E39: 4 | F39: 99636.75 | G39: 398547 | H39: Material para Manutenção | I39: 46232 | J39: 29734478
A40: 38292 | B40: 690241 | C40: REGUL TENS AUTOM SIMET RD 1F 19,919KV 400KVA 201A ESTR CL2 | D40: UN | E40: 4 | F40: 99636.75 | G40: 398547 | H40: Material para Manutenção | I40: 46232 | J40: 29734478
A41: 38292 | B41: 690241 | C41: REGUL TENS AUTOM SIMET RD 1F 19,919KV 400KVA 201A ESTR CL2 | D41: UN | E41: 4 | F41: 99636.75 | G41: 398547 | H41: Material para Manutenção | I41: 46232 | J41: 29734478
A42: 38292 | B42: 690241 | C42: REGUL TENS AUTOM SIMET RD 1F 19,919KV 400KVA 201A ESTR CL2 | D42: UN | E42: 4 | F42: 99636.75 | G42: 398547 | H42: Material para Manutenção | I42: 46232 | J42: 29734478
A43: 38294 | B43: 690001 | C43: RELIGADOR AUTO EXT 3F LIN VAC 15KV 630A 12,5KA 127VCA | D43: UN | E43: 8 | F43: 21785.72 | G43: 174285.76 | H43: Material para Manutenção | I43: 46232 | J43: 29734495
A44: 38294 | B44: 690001 | C44: RELIGADOR AUTO EXT 3F LIN VAC 15KV 630A 12,5KA 127VCA | D44: UN | E44: 8 | F44: 21785.72 | G44: 174285.76 | H44: Material para Manutenção | I44: 46232 | J44: 29734495
A45: 38294 | B45: 690001 | C45: RELIGADOR AUTO EXT 3F LIN VAC 15KV 630A 12,5KA 127VCA | D45: UN | E45: 8 | F45: 21785.72 | G45: 174285.76 | H45: Material para Manutenção | I45: 46232 | J45: 29734495
A46: 38294 | B46: 690001 | C46: RELIGADOR AUTO EXT 3F LIN VAC 15KV 630A 12,5KA 127VCA | D46: UN | E46: 8 | F46: 21785.72 | G46: 174285.76 | H46: Material para Manutenção | I46: 46232 | J46: 29734495
A47: 38294 | B47: 690001 | C47: RELIGADOR AUTO EXT 3F LIN VAC 15KV 630A 12,5KA 127VCA | D47: UN | E47: 8 | F47: 21785.72 | G47: 174285.76 | H47: Material para Manutenção | I47: 46232 | J47: 29734495
A48: 38294 | B48: 690001 | C48: RELIGADOR AUTO EXT 3F LIN VAC 15KV 630A 12,5KA 127VCA | D48: UN | E48: 8 | F48: 21785.72 | G48: 174285.76 | H48: Material para Manutenção | I48: 46232 | J48: 29734495
... A75: 38297 | B75: 692263 | C75: CONTROLE P/ RELIGADOR LINHA DISTR 36,2KV 115VCA | D75: UN | E75: 7 | F75: 37493.6 | G75: 262455.2 | H75: Material para Manutenção | I75: 46232 | J75: 29734495

Sheet Taxa de Falha
A1: Ano | B1: 2026
A2: Equipamento | B2: (Tudo)
A3: Tensão | B3: (Tudo)
A5: Rótulos de Coluna
A6: janeiro | B6: fevereiro | C6: março | D6: abril | E6: maio | F6: junho | G6: julho | H6: agosto | I6: Total Geral
B68: janeiro | C68: fevereiro | D68: março | E68: abril | F68: maio | G68: junho | H68: julho | I68: agosto | J68: setembro | K68: outubro | L68: novembro | M68: dezembro
A69: % falha - mensal
A70: % falha - acumulada
A71: Taxa de Falha Mensal - RL - 2025
B72: Jan | C72: Fev | D72: Mar | E72: Abr | F72: Mai | G72: Jun | H72: Jul | I72: Ago | J72: Set | K72: Out | L72: Nov | M72: Dez
A73: Novos ativos | B73: 0 | C73: 0 | D73: 0 | E73: 0 | F73: 0 | G73: 0 | H73: 0 | I73: 0 | J73: 0 | K73: 0 | L73: 0 | M73: 0
A74: Parque | B74: 1281 | C74: 1281 | D74: 1281 | E74: 1281 | F74: 1281 | G74: 1281 | H74: 1281 | I74: 1281 | J74: 1281 | K74: 1281 | L74: 1281 | M74: 1281
A75: Falha mês | B75: 1 | C75: 1 | D75: 2 | E75: 2 | F75: 7 | G75: 4 | H75: 5 | I75: 2 | J75: 2 | K75: 4 | L75: 1 | M75: 4
B76: =B75/B74 -> 0.00078064012 | C76: =C75/C74 -> 0.00078064012 | D76: =D75/D74 -> 0.0015612802 | E76: =E75/E74 -> 0.0015612802 | F76: =F75/F74 -> 0.0054644809 | G76: =G75/G74 -> 0.0031225605 | H76: =H75/H74 -> 0.0039032006 | I76: =I75/I74 -> 0.0015612802 | ... M76: =M75/M74 -> 0.0031225605
A77: Taxa de Falha Mensal - RT - 2025
B78: Jan | C78: Fev | D78: Mar | E78: Abr | F78: Mai | G78: Jun | H78: Jul | I78: Ago | J78: Set | K78: Out | L78: Nov | M78: Dez
A79: Novos ativos | B79: 0 | C79: 0 | D79: 0 | E79: 0 | F79: 0 | G79: 0 | H79: 0 | I79: 0 | J79: 0 | K79: 0 | L79: 0 | M79: 0
A80: Parque | B80: 180 | C80: 180 | D80: 180 | E80: 180 | F80: 180 | G80: 180 | H80: 180 | I80: 180 | J80: 180 | K80: 180 | L80: 180 | M80: 180
A81: Falha mês | B81: 0 | C81: 1 | D81: 2 | E81: 0 | F81: 0 | G81: 1 | H81: 3 | I81: 5 | J81: 3 | L81: 1 | M81: 2 | N81: =J81+J75 -> 5 | O81: =K81+K75 -> 4 | P81: =L81+L75 -> 2 | Q81: =M81+M75 -> 6
B82: =B81/B80 -> 0 | C82: =C81/C80 -> 0.0055555556 | D82: =D81/D80 -> 0.011111111 | E82: =E81/E80 -> 0 | F82: =F81/F80 -> 0 | G82: =G81/G80 -> 0.0055555556 | H82: =H81/H80 -> 0.016666667 | I82: =I81/I80 -> 0.027777778 | ... M82: =M81/M80 -> 0.011111111
A84: Taxa de Falha Mensal - RL - 2026
B85: Jan | C85: Fev | D85: Mar | E85: Abr | F85: Mai | G85: Jun | H85: Jul | I85: Ago | J85: Set | K85: Out | L85: Nov | M85: Dez
A86: Novos ativos | B86: {='[1]Expansão EE'!$E$51:$P$51} -> 2 | C86: 0 | D86: 2 | E86: 2 | F86: 3 | G86: 1 | H86: 3 | I86: 3 | J86: 0 | K86: 0 | L86: 0 | M86: 0
A87: Parque | B87: =$M$74+B86 -> 1283 | C87: =B87+C86 -> 1283 | D87: =C87+D86 -> 1285 | E87: =D87+E86 -> 1287 | F87: =E87+F86 -> 1290 | G87: =F87+G86 -> 1291 | H87: =G87+H86 -> 1294 | I87: =H87+I86 -> 1297 | J87: =I87+J86 -> 1297 | ... M87: =L87+M86 -> 1297
A88: Falha mês | B88: 6 | C88: 7 | D88: 8 | E88: 3 | F88: 0 | G88: 1 | H88: 3 | I88: 0
B89: =B88/B87 -> 0.0046765394 | C89: =C88/C87 -> 0.0054559626 | D89: =D88/D87 -> 0.0062256809 | E89: =E88/E87 -> 0.0023310023 | F89: =F88/F87 -> 0 | G89: =G88/G87 -> 0.00077459334 | H89: =H88/H87 -> 0.0023183926 | I89: =I88/I87 -> 0 | ... M89: =M88/M87 -> 0
B90: =B88/B87 -> 0.0046765394 | C90: =C88/C87 -> 0.0054559626 | D90: =D88/D87 -> 0.0062256809 | E90: =E88/E87 -> 0.0023310023 | F90: =F88/F87 -> 0 | G90: =G88/G87 -> 0.00077459334 | H90: =H88/H87 -> 0.0023183926 | I90: =I88/I87 -> 0 | O90: =J81+J75 -> 5 | P90: =K81+K75 -> 4 | Q90: =L81+L75 -> 2 | R90: =M81+M75 -> 6
A91: Taxa de Falha Mensal - RT - 2026
B92: Jan | C92: Fev | D92: Mar | E92: Abr | F92: Mai | G92: Jun | H92: Jul | I92: Ago | J92: Set | K92: Out | L92: Nov | M92: Dez
A93: Novos ativos | B93: {='[1]Expansão EE'!$E$51:$P$51} -> 2 | C93: 0 | D93: 2 | E93: 2 | F93: 3 | G93: 1 | H93: 3 | I93: 3 | J93: 0 | K93: 0 | L93: 0 | M93: 0
A94: Parque | B94: =$M$80+B93 -> 182 | C94: =B94+C93 -> 182 | D94: =C94+D93 -> 184 | E94: =D94+E93 -> 186 | F94: =E94+F93 -> 189 | G94: =F94+G93 -> 190 | H94: =G94+H93 -> 193 | I94: =H94+I93 -> 196 | J94: =I94+J93 -> 196 | ... M94: =L94+M93 -> 196
A95: Falha mês | B95: 1 | C95: 1 | D95: 1 | E95: 2 | F95: 1 | G95: 1 | H95: 1 | I95: 1
B96: =B95/B94 -> 0.0054945055 | C96: =C95/C94 -> 0.0054945055 | D96: =D95/D94 -> 0.0054347826 | E96: =E95/E94 -> 0.010752688 | F96: =F95/F94 -> 0.0052910053 | G96: =G95/G94 -> 0.0052631579 | H96: =H95/H94 -> 0.0051813472 | I96: =I95/I94 -> 0.0051020408 | ... M96: =M95/M94 -> 0
B97: =B95+B88 -> 7 | C97: =C95+C88 -> 8 | D97: =D95+D88 -> 9 | E97: =E95+E88 -> 5 | F97: =F95+F88 -> 1 | G97: =G95+G88 -> 2 | H97: =H95+H88 -> 4 | I97: =I95+I88 -> 1 | ... M97: =M95+M88 -> 0
A99: Taxa de Falha Acumulado- RL - 2025
B100: Jan | C100: Fev | D100: Mar | E100: Abr | F100: Mai | G100: Jun | H100: Jul | I100: Ago | J100: Set | K100: Out | L100: Nov | M100: Dez
A101: Novos ativos | B101: =B73 -> 0 | C101: =C73 -> 0 | D101: =D73 -> 0 | E101: =E73 -> 0 | F101: =F73 -> 0 | G101: =G73 -> 0 | H101: =H73 -> 0 | I101: =I73 -> 0 | ... M101: =M73 -> 0
A102: Parque | B102: =B74 -> 1281 | C102: =C74 -> 1281 | D102: =D74 -> 1281 | E102: =E74 -> 1281 | F102: =F74 -> 1281 | G102: =G74 -> 1281 | H102: =H74 -> 1281 | I102: =I74 -> 1281 | ... M102: =M74 -> 1281
A103: Falha mês | B103: =B75 -> 1 | C103: =C75+B103 -> 2 | D103: =D75+C103 -> 4 | E103: =E75+D103 -> 6 | F103: =F75+E103 -> 13 | G103: =G75+F103 -> 17 | H103: =H75+G103 -> 22 | I103: =I75+H103 -> 24 | J103: =J75+I103 -> 26 | ... M103: =M75+L103 -> 35
B104: =B103/B102 -> 0.00078064012 | C104: =C103/C102 -> 0.0015612802 | D104: =D103/D102 -> 0.0031225605 | E104: =E103/E102 -> 0.0046838407 | F104: =F103/F102 -> 0.010148322 | G104: =G103/G102 -> 0.013270882 | H104: =H103/H102 -> 0.017174083 | I104: =I103/I102 -> 0.018735363 | ... M104: =M103/M102 -> 0.027322404
A105: Taxa de Falha Acumulado - RT - 2025
B106: Jan | C106: Fev | D106: Mar | E106: Abr | F106: Mai | G106: Jun | H106: Jul | I106: Ago | J106: Set | K106: Out | L106: Nov | M106: Dez
A107: Novos ativos | B107: =B79 -> 0 | C107: =C79 -> 0 | D107: =D79 -> 0 | E107: =E79 -> 0 | F107: =F79 -> 0 | G107: =G79 -> 0 | H107: =H79 -> 0 | I107: =I79 -> 0 | ... M107: =M79 -> 0
A108: Parque | B108: =B80 -> 180 | C108: =C80 -> 180 | D108: =D80 -> 180 | E108: =E80 -> 180 | F108: =F80 -> 180 | G108: =G80 -> 180 | H108: =H80 -> 180 | I108: =I80 -> 180 | ... M108: =M80 -> 180
A109: Falha mês | B109: =B81 -> 0 | C109: =C81+B109 -> 1 | D109: =D81+C109 -> 3 | E109: =E81+D109 -> 3 | F109: =F81+E109 -> 3 | G109: =G81+F109 -> 4 | H109: =H81+G109 -> 7 | I109: =I81+H109 -> 12 | J109: =J81+I109 -> 15 | ... M109: =M81+L109 -> 18
B110: =B109/B108 -> 0 | C110: =C109/C108 -> 0.0055555556 | D110: =D109/D108 -> 0.016666667 | E110: =E109/E108 -> 0.016666667 | F110: =F109/F108 -> 0.016666667 | G110: =G109/G108 -> 0.022222222 | H110: =H109/H108 -> 0.038888889 | I110: =I109/I108 -> 0.066666667 | ... M110: =M109/M108 -> 0.1
A112: Taxa de Falha Acumulado- RL - 2026
B113: Jan | C113: Fev | D113: Mar | E113: Abr | F113: Mai | G113: Jun | H113: Jul | I113: Ago | J113: Set | K113: Out | L113: Nov | M113: Dez
A114: Novos ativos | B114: =B86 -> 2 | C114: =C86 -> 0 | D114: =D86 -> 2 | E114: =E86 -> 2 | F114: =F86 -> 3 | G114: =G86 -> 1 | H114: =H86 -> 3 | I114: =I86 -> 3 | ... M114: =M86 -> 0
A115: Parque | B115: =B87 -> 1283 | C115: =C87 -> 1283 | D115: =D87 -> 1285 | E115: =E87 -> 1287 | F115: =F87 -> 1290 | G115: =G87 -> 1291 | H115: =H87 -> 1294 | I115: =I87 -> 1297 | ... M115: =M87 -> 1297
A116: Falha mês | B116: =B88 -> 6 | C116: =B116+C88 -> 13 | D116: =C116+D88 -> 21 | E116: =D116+E88 -> 24 | F116: =E116+F88 -> 24 | G116: =F116+G88 -> 25 | H116: =G116+H88 -> 28 | I116: =H116+I88 -> 28
B117: =B116/B115 -> 0.0046765394 | C117: =C116/C115 -> 0.010132502 | D117: =D116/D115 -> 0.016342412 | E117: =E116/E115 -> 0.018648019 | F117: =F116/F115 -> 0.018604651 | G117: =G116/G115 -> 0.019364833 | H117: =H116/H115 -> 0.021638331 | I117: =I116/I115 -> 0.021588281 | ... M117: =M116/M115 -> 0
A119: Taxa de Falha Acumulado - RT - 2026
B120: Jan | C120: Fev | D120: Mar | E120: Abr | F120: Mai | G120: Jun | H120: Jul | I120: Ago | J120: Set | K120: Out | L120: Nov | M120: Dez
A121: Novos ativos | B121: =B93 -> 2 | C121: =C93 -> 0 | D121: =D93 -> 2 | E121: =E93 -> 2 | F121: =F93 -> 3 | G121: =G93 -> 1 | H121: =H93 -> 3 | I121: =I93 -> 3 | ... M121: =M93 -> 0
A122: Parque | B122: =B94 -> 182 | C122: =C94 -> 182 | D122: =D94 -> 184 | E122: =E94 -> 186 | F122: =F94 -> 189 | G122: =G94 -> 190 | H122: =H94 -> 193 | I122: =I94 -> 196 | ... M122: =M94 -> 196
A123: Falha mês | B123: =B95 -> 1 | C123: =B123+C95 -> 2 | D123: =C123+D95 -> 3 | E123: =D123+E95 -> 5 | F123: =E123+F95 -> 6 | G123: =F123+G95 -> 7 | H123: =G123+H95 -> 8 | I123: =H123+I95 -> 9
B124: =B123/B122 -> 0.0054945055 | C124: =C123/C122 -> 0.010989011 | D124: =D123/D122 -> 0.016304348 | E124: =E123/E122 -> 0.02688172 | F124: =F123/F122 -> 0.031746032 | G124: =G123/G122 -> 0.036842105 | H124: =H123/H122 -> 0.041450777 | I124: =I123/I122 -> 0.045918367 | ... M124: =M123/M122 -> 0

Sheet SLA por equipe
A1: SLA DE MANUTENÇÃO — POR EQUIPE DE CAMPO
A2: Equipe é o posto do COCM que recebeu a demanda. A mediana diz o ritmo normal; o pior atraso diz a cauda.
A4: 2025
A5: Equipe | B5: Entregas | C5: No prazo | D5: Estourou | E5: Em curso | F5: Cumprimento | G5: Mediana de dias | H5: SLA (dias ÷ prazo) | I5: Pior atraso
A6: ETO-RD-PO | B6: 11 | C6: 7 | D6: 4 | E6: 0 | F6: 0.63636364 | G6: 7 | H6: 1.4513619 | I6: 148
A7: ETO-RD-AG | B7: 7 | C7: 6 | D7: 1 | E7: 0 | F7: 0.85714286 | G7: 0 | H7: 0.24725275 | I7: 3
A8: ETO-RD-GU | B8: 7 | C8: 5 | D8: 2 | E8: 0 | F8: 0.71428571 | G8: 4 | H8: 0.76923077 | I8: 53
A9: ETO-RD-PS | B9: 7 | C9: 4 | D9: 3 | E9: 0 | F9: 0.57142857 | G9: 0 | H9: 4.1318681 | I9: 232
A10: DOLP-RD-PA | B10: 6 | C10: 5 | D10: 1 | E10: 0 | F10: 0.83333333 | G10: 13 | H10: 0.50641026 | I10: 12
A11: ETO-RD-AR | B11: 6 | C11: 5 | D11: 1 | E11: 1 | F11: 0.83333333 | G11: 2 | H11: 3.275641 | I11: 468
A12: ETO-RD-GR | B12: 6 | C12: 4 | D12: 2 | E12: 0 | F12: 0.66666667 | G12: 23 | H12: 1.0833333 | I12: 59
A13: ETO-RD-PA | B13: 6 | C13: 3 | D13: 3 | E13: 0 | F13: 0.5 | G13: 35 | H13: 2.4423077 | I13: 236
A14: ETO-RD-DP | B14: 3 | C14: 1 | D14: 2 | E14: 0 | F14: 0.33333333 | G14: 74 | H14: 6.5166667 | I14: 308
A15: ENC-RD-PS | B15: 1 | C15: 1 | D15: 0 | E15: 0 | F15: 1 | G15: 1 | H15: 0.038461538 | I15: 0
A16: TOTAL | B16: 60 | C16: 41 | D16: 19 | E16: 1 | F16: 0.68333333 | G16: 6 | H16: 1.8783873 | I16: 468
A18: 2026
A19: Equipe | B19: Entregas | C19: No prazo | D19: Estourou | E19: Em curso | F19: Cumprimento | G19: Mediana de dias | H19: SLA (dias ÷ prazo) | I19: Pior atraso
A20: ETO-RD-AR | B20: 13 | C20: 11 | D20: 2 | E20: 0 | F20: 0.84615385 | G20: 1 | H20: 0.43122677 | I20: 36
A21: ETO-RD-PS | B21: 13 | C21: 10 | D21: 3 | E21: 0 | F21: 0.76923077 | G21: 1 | H21: 1.0132013 | I21: 87
A22: ETO-RD-PO | B22: 12 | C22: 7 | D22: 5 | E22: 1 | F22: 0.58333333 | G22: 10 | H22: 1.1840796 | I22: 59
A23: ETO-RD-PA | B23: 11 | C23: 7 | D23: 4 | E23: 1 | F23: 0.63636364 | G23: 1 | H23: 1.75 | I23: 100
A24: ETO-RD-DP | B24: 8 | C24: 2 | D24: 6 | E24: 2 | F24: 0.25 | G24: 67 | H24: 2.2473684 | I24: 84
A25: ETO-RD-GR | B25: 6 | C25: 3 | D25: 3 | E25: 0 | F25: 0.5 | G25: 38 | H25: 1.9565217 | I25: 32
A26: ETO-RD-AG | B26: 5 | C26: 5 | D26: 0 | E26: 0 | F26: 1 | G26: 8 | H26: 0.25892857 | I26: 0
A27: ETO-RD-GU | B27: 2 | C27: 1 | D27: 1 | E27: 0 | F27: 0.5 | G27: 87 | H27: 3.7826087 | I27: 72
A28: DG-RD-PO | B28: 1 | C28: 1 | D28: 0 | E28: 0 | F28: 1 | G28: 14 | H28: 0.53846154 | I28: 0
A29: TOTAL | B29: 71 | C29: 47 | D29: 24 | E29: 4 | F29: 0.66197183 | G29: 4 | H29: 1.2300071 | I29: 100
A31: 2025 + 2026
A32: Equipe | B32: Entregas | C32: No prazo | D32: Estourou | E32: Em curso | F32: Cumprimento | G32: Mediana de dias | H32: SLA (dias ÷ prazo) | I32: Pior atraso
A33: ETO-RD-PO | B33: 23 | C33: 14 | D33: 9 | E33: 1 | F33: 0.60869565 | G33: 9 | H33: 1.3340611 | I33: 148
A34: ETO-RD-PS | B34: 20 | C34: 14 | D34: 6 | E34: 0 | F34: 0.7 | G34: 1 | H34: 2.1835052 | I34: 232
A35: ETO-RD-AR | B35: 19 | C35: 16 | D35: 3 | E35: 1 | F35: 0.84210526 | G35: 1 | H35: 1.4752941 | I35: 468
A36: ETO-RD-PA | B36: 17 | C36: 10 | D36: 7 | E36: 1 | F36: 0.58823529 | G36: 1 | H36: 2.037234 | I36: 236
A37: ETO-RD-AG | B37: 12 | C37: 11 | D37: 1 | E37: 0 | F37: 0.91666667 | G37: 1 | H37: 0.25170068 | I37: 3
A38: ETO-RD-GR | B38: 12 | C38: 7 | D38: 5 | E38: 0 | F38: 0.58333333 | G38: 23 | H38: 1.3511111 | I38: 59
A39: ETO-RD-DP | B39: 11 | C39: 3 | D39: 8 | E39: 2 | F39: 0.27272727 | G39: 67 | H39: 3.272 | I39: 308
A40: ETO-RD-GU | B40: 9 | C40: 6 | D40: 3 | E40: 0 | F40: 0.66666667 | G40: 4 | H40: 1.1073171 | I40: 72
A41: DOLP-RD-PA | B41: 6 | C41: 5 | D41: 1 | E41: 0 | F41: 0.83333333 | G41: 13 | H41: 0.50641026 | I41: 12
A42: DG-RD-PO | B42: 1 | C42: 1 | D42: 0 | E42: 0 | F42: 1 | G42: 14 | H42: 0.53846154 | I42: 0
A43: ENC-RD-PS | B43: 1 | C43: 1 | D43: 0 | E43: 0 | F43: 1 | G43: 1 | H43: 0.038461538 | I43: 0
A44: TOTAL | B44: 131 | C44: 88 | D44: 43 | E44: 5 | F44: 0.67175573 | G44: 5 | H44: 1.5652768 | I44: 468

Sheet Falha Equipamentos
A1: Ano/TIPO | B1: Equipamento | C1: Mensal | D1: Parque | E1: Ativo | F1: SS | G1: Tensão | H1: Data | I1: Mês | J1: Ano | K1: Concat | L1: Peça (modo) | M1: Troca feita | N1: Causa raiz | O1: Citação do texto da SS | P1: Nota do analista | Q1: Revisão | R1: Coluna1
A2: RL 2025 | B2: =LEFT(Tabela3[[#This Row],[Ano/TIPO]],2) -> RL | D2: =_xlfn.XLOOKUP(K2,Base!G:G,Base!I:I) -> #N/A | E2: 7900230155 | F2: ETO-COEP 00056/2025 | G2: =_xlfn.XLOOKUP(_xlfn.NUMBERVALUE(Tabela3[[#This Row],[Ativo]]),'[2]Ajustes Reguladores de Tensão'!$A:$A,'[2]Ajustes Reguladores de Tensão'!$I:$I,_xlfn.XLOOKUP(_xlfn.NUMBERVALUE(Tabela3[[#This Row],[Ativo]]),'[2]Ajustes RL Poste'!$A:$A,'[2]Ajustes RL Poste'!$M:$M)) -> 34.500 | H2: 29/03/2025 | I2: =TEXT(Tabela3[[#This Row],[Data]],"mmmm") -> março | J2: =YEAR(Tabela3[[#This Row],[Data]]) -> 2025 | K2: =_xlfn.CONCAT(Tabela3[[#This Row],[Ano]],Tabela3[[#This Row],[Mês]]) -> 2025março | L2: completo | M2: sim | N2: CURTO-CIRCUITO INTERNO | O2: «Não responde a comandos abertura e fechamento local ou remoto, pois está com sinal de curto circuito» | P2: Tanque danificado com sinal de curto-circuito bloqueando comandos; o para-raios do trafo queimado junto sugere surto, mas o laudo não afirma descarga.
A3: RL 2025 | B3: =LEFT(Tabela3[[#This Row],[Ano/TIPO]],2) -> RL | D3: =_xlfn.XLOOKUP(K3,Base!G:G,Base!I:I) -> #N/A | E3: 7900573047 | F3: ETO-COEP 00080/2026 | G3: =_xlfn.XLOOKUP(_xlfn.NUMBERVALUE(Tabela3[[#This Row],[Ativo]]),'[2]Ajustes Reguladores de Tensão'!$A:$A,'[2]Ajustes Reguladores de Tensão'!$I:$I,_xlfn.XLOOKUP(_xlfn.NUMBERVALUE(Tabela3[[#This Row],[Ativo]]),'[2]Ajustes RL Poste'!$A:$A,'[2]Ajustes RL Poste'!$M:$M)) -> 13.800 | H3: 09/10/2025 | I3: =TEXT(Tabela3[[#This Row],[Data]],"mmmm") -> outubro | J3: =YEAR(Tabela3[[#This Row],[Data]]) -> 2025 | K3: =_xlfn.CONCAT(Tabela3[[#This Row],[Ano]],Tabela3[[#This Row],[Mês]]) -> 2025outubro | L3: completo | M3: não | N3: CURTO-CIRCUITO INTERNO | O3: «o mesmo estar em curto conforme fotos anexadas» | P3: Relato de campo com fotos dá o equipamento em curto e o DMSL constata parte ativa, placa, tanque e relé queimados — curto como mecanismo; origem não descrita. | Y3: Rótulos de Linha | Z3: Contagem de Data
A4: RL 2025 | B4: =LEFT(Tabela3[[#This Row],[Ano/TIPO]],2) -> RL | D4: =_xlfn.XLOOKUP(K4,Base!G:G,Base!I:I) -> #N/A | E4: 7908196047 | F4: ETO-COEP 00215/2025 | G4: =_xlfn.XLOOKUP(_xlfn.NUMBERVALUE(Tabela3[[#This Row],[Ativo]]),'[2]Ajustes Reguladores de Tensão'!$A:$A,'[2]Ajustes Reguladores de Tensão'!$I:$I,_xlfn.XLOOKUP(_xlfn.NUMBERVALUE(Tabela3[[#This Row],[Ativo]]),'[2]Ajustes RL Poste'!$A:$A,'[2]Ajustes RL Poste'!$M:$M)) -> 13.800 | H4: 29/09/2025 | I4: =TEXT(Tabela3[[#This Row],[Data]],"mmmm") -> setembro | J4: =YEAR(Tabela3[[#This Row],[Data]]) -> 2025 | K4: =_xlfn.CONCAT(Tabela3[[#This Row],[Ano]],Tabela3[[#This Row],[Mês]]) -> 2025setembro | L4: completo | M4: não | N4: CURTO-CIRCUITO INTERNO | O4: «Constatado curto-circuito no tanque do religador, impedindo as operações de abertura e fechamento do equipamento» | P4: Diagnóstico DMSL explícito de curto-circuito no tanque travando abertura/fechamento; a origem do curto não é detalhada. | Y4: RL 2025 | Z4: 35
A5: RL 2025 | B5: =LEFT(Tabela3[[#This Row],[Ano/TIPO]],2) -> RL | D5: =_xlfn.XLOOKUP(K5,Base!G:G,Base!I:I) -> #N/A | E5: 7923927122 | F5: ETO-COEP 00079/2025 | G5: =_xlfn.XLOOKUP(_xlfn.NUMBERVALUE(Tabela3[[#This Row],[Ativo]]),'[2]Ajustes Reguladores de Tensão'!$A:$A,'[2]Ajustes Reguladores de Tensão'!$I:$I,_xlfn.XLOOKUP(_xlfn.NUMBERVALUE(Tabela3[[#This Row],[Ativo]]),'[2]Ajustes RL Poste'!$A:$A,'[2]Ajustes RL Poste'!$M:$M)) -> 34.500 | H5: 27/04/2025 | I5: =TEXT(Tabela3[[#This Row],[Data]],"mmmm") -> abril | J5: =YEAR(Tabela3[[#This Row],[Data]]) -> 2025 | K5: =_xlfn.CONCAT(Tabela3[[#This Row],[Ano]],Tabela3[[#This Row],[Mês]]) -> 2025abril | L5: tanque | M5: não | N5: CURTO-CIRCUITO INTERNO | O5: «substituir tanque do RL-7923927122 em curto, Anomalia identificada desarme das LD» | P5: Tanque em curto derrubando as LDs Palmas/Aparecida e Taquaruçu — curto interno como mecanismo; origem não descrita. | Y5: RL 2026 | Z5: 28
A6: RL 2025 | B6: =LEFT(Tabela3[[#This Row],[Ano/TIPO]],2) -> RL | D6: =_xlfn.XLOOKUP(K6,Base!G:G,Base!I:I) -> #N/A | E6: 7928241200 | F6: ETO-COEP 00139/2025 | G6: =_xlfn.XLOOKUP(_xlfn.NUMBERVALUE(Tabela3[[#This Row],[Ativo]]),'[2]Ajustes Reguladores de Tensão'!$A:$A,'[2]Ajustes Reguladores de Tensão'!$I:$I,_xlfn.XLOOKUP(_xlfn.NUMBERVALUE(Tabela3[[#This Row],[Ativo]]),'[2]Ajustes RL Poste'!$A:$A,'[2]Ajustes RL Poste'!$M:$M)) -> 34.500 | H6: 04/07/2025 | I6: =TEXT(Tabela3[[#This Row],[Data]],"mmmm") -> julho | J6: =YEAR(Tabela3[[#This Row],[Data]]) -> 2025 | K6: =_xlfn.CONCAT(Tabela3[[#This Row],[Ano]],Tabela3[[#This Row],[Mês]]) -> 2025julho | L6: tanque | M6: não | N6: CURTO-CIRCUITO INTERNO | O6: «fizemos ensaios elétricos e foi constatado que o tanque está em curto» | P6: Ensaios elétricos constataram o tanque em curto depois de o equipamento tirar a linha — curto interno como mecanismo; origem não descrita. | Y6: RT 2025 | Z6: 18
A7: RL 2025 | B7: =LEFT(Tabela3[[#This Row],[Ano/TIPO]],2) -> RL | D7: =_xlfn.XLOOKUP(K7,Base!G:G,Base!I:I) -> #N/A | E7: 7931610122 | F7: ETO-COEP 00083/2026 | G7: =_xlfn.XLOOKUP(_xlfn.NUMBERVALUE(Tabela3[[#This Row],[Ativo]]),'[2]Ajustes Reguladores de Tensão'!$A:$A,'[2]Ajustes Reguladores de Tensão'!$I:$I,_xlfn.XLOOKUP(_xlfn.NUMBERVALUE(Tabela3[[#This Row],[Ativo]]),'[2]Ajustes RL Poste'!$A:$A,'[2]Ajustes RL Poste'!$M:$M)) -> 13.800 | H7: 10/10/2025 | I7: =TEXT(Tabela3[[#This Row],[Data]],"mmmm") -> outubro | J7: =YEAR(Tabela3[[#This Row],[Data]]) -> 2025 | K7: =_xlfn.CONCAT(Tabela3[[#This Row],[Ano]],Tabela3[[#This Row],[Mês]]) -> 2025outubro | L7: tanque | M7: sim | N7: CURTO-CIRCUITO INTERNO | O7: «Houve um curto no equipamento danificando a parte ativa, e antena!» | P7: Curto no equipamento danificou parte ativa e antena; o texto não localiza a origem (dano simultâneo na antena até sugere surto externo, não afirmado). | Y7: RT 2026 | Z7: 9
A8: RL 2025 | B8: =LEFT(Tabela3[[#This Row],[Ano/TIPO]],2) -> RL | D8: =_xlfn.XLOOKUP(K8,Base!G:G,Base!I:I) -> #N/A | E8: 7933766059 | F8: ETO-COEP 00082/2026 | G8: =_xlfn.XLOOKUP(_xlfn.NUMBERVALUE(Tabela3[[#This Row],[Ativo]]),'[2]Ajustes Reguladores de Tensão'!$A:$A,'[2]Ajustes Reguladores de Tensão'!$I:$I,_xlfn.XLOOKUP(_xlfn.NUMBERVALUE(Tabela3[[#This Row],[Ativo]]),'[2]Ajustes RL Poste'!$A:$A,'[2]Ajustes RL Poste'!$M:$M)) -> 13.800 | H8: 08/10/2025 | I8: =TEXT(Tabela3[[#This Row],[Data]],"mmmm") -> outubro | J8: =YEAR(Tabela3[[#This Row],[Data]]) -> 2025 | K8: =_xlfn.CONCAT(Tabela3[[#This Row],[Ano]],Tabela3[[#This Row],[Mês]]) -> 2025outubro | L8: tanque | M8: sim | N8: CURTO-CIRCUITO INTERNO | O8: «Houve um curto na parte ativa do equipamento danificando a mesma, será necessário fazer a substituição somente do tanque, parte ativa.» | P8: O DMSL afirma curto na própria parte ativa danificando-a — mecanismo explícito; a origem do curto não é detalhada. | Q8: Causa mantida (CURTO-CIRCUITO INTERNO); confiança rebaixada de alta para media: 'Houve um curto na parte ativa do equipamento danificando a mesma' é narrativa de evento sem dizer como se constatou — mesmo fraseado e mesmo formato de laudo DMSL do 7931610122, classificado media. Alta fica reservada a curto constatado por ensaio (7928241200, 7908196047). | Y8: Total Geral | Z8: 90
A9: RL 2025 | B9: =LEFT(Tabela3[[#This Row],[Ano/TIPO]],2) -> RL | D9: =_xlfn.XLOOKUP(K9,Base!G:G,Base!I:I) -> #N/A | E9: 7900594026 | F9: ETO-COEP 00210/2025 | G9: =_xlfn.XLOOKUP(_xlfn.NUMBERVALUE(Tabela3[[#This Row],[Ativo]]),'[2]Ajustes Reguladores de Tensão'!$A:$A,'[2]Ajustes Reguladores de Tensão'!$I:$I,_xlfn.XLOOKUP(_xlfn.NUMBERVALUE(Tabela3[[#This Row],[Ativo]]),'[2]Ajustes RL Poste'!$A:$A,'[2]Ajustes RL Poste'!$M:$M)) -> 34.500 | H9: 15/10/2025 | I9: =TEXT(Tabela3[[#This Row],[Data]],"mmmm") -> outubro | J9: =YEAR(Tabela3[[#This Row],[Data]]) -> 2025 | K9: =_xlfn.CONCAT(Tabela3[[#This Row],[Ano]],Tabela3[[#This Row],[Mês]]) -> 2025outubro | L9: controle | M9: sim | N9: DEFEITO ELETRÔNICO (CONTROLE/PLACA/RELÉ) | O9: «o equipamento está com falha na porta de comunicação serial RS 232» | P9: Falha localizada na porta serial RS-232 do relé Cooper Form 6 — defeito de hardware do controle; o porquê da falha não é descrito.
A10: RL 2025 | B10: =LEFT(Tabela3[[#This Row],[Ano/TIPO]],2) -> RL | D10: =_xlfn.XLOOKUP(K10,Base!G:G,Base!I:I) -> #N/A | E10: 7936038076 | F10: ETO-TELE 00074/2025 | G10: =_xlfn.XLOOKUP(_xlfn.NUMBERVALUE(Tabela3[[#This Row],[Ativo]]),'[2]Ajustes Reguladores de Tensão'!$A:$A,'[2]Ajustes Reguladores de Tensão'!$I:$I,_xlfn.XLOOKUP(_xlfn.NUMBERVALUE(Tabela3[[#This Row],[Ativo]]),'[2]Ajustes RL Poste'!$A:$A,'[2]Ajustes RL Poste'!$M:$M)) -> 34.500 | H10: 03/02/2025 | I10: =TEXT(Tabela3[[#This Row],[Data]],"mmmm") -> fevereiro | J10: =YEAR(Tabela3[[#This Row],[Data]]) -> 2025 | K10: =_xlfn.CONCAT(Tabela3[[#This Row],[Ano]],Tabela3[[#This Row],[Mês]]) -> 2025fevereiro | L10: controle | M10: sim | N10: DEFEITO ELETRÔNICO (CONTROLE/PLACA/RELÉ) | O10: «FOI IDENTIFICADO DISPLAY DO RELE APAGADO - ALIMENTAÇÃO CA NORMAL» | P10: Alimentação CA normal com display do relé apagado aponta falha intrínseca da eletrônica do controle; a OS trocou o relé e atualizou o firmware.
A11: RL 2025 | B11: =LEFT(Tabela3[[#This Row],[Ano/TIPO]],2) -> RL | D11: =_xlfn.XLOOKUP(K11,Base!G:G,Base!I:I) -> #N/A | E11: 7957126085 | F11: ETO-COEP 00156/2025 | G11: =_xlfn.XLOOKUP(_xlfn.NUMBERVALUE(Tabela3[[#This Row],[Ativo]]),'[2]Ajustes Reguladores de Tensão'!$A:$A,'[2]Ajustes Reguladores de Tensão'!$I:$I,_xlfn.XLOOKUP(_xlfn.NUMBERVALUE(Tabela3[[#This Row],[Ativo]]),'[2]Ajustes RL Poste'!$A:$A,'[2]Ajustes RL Poste'!$M:$M)) -> 34.500 | H11: 05/06/2025 | I11: =TEXT(Tabela3[[#This Row],[Data]],"mmmm") -> junho | J11: =YEAR(Tabela3[[#This Row],[Data]]) -> 2025 | K11: =_xlfn.CONCAT(Tabela3[[#This Row],[Ano]],Tabela3[[#This Row],[Mês]]) -> 2025junho | L11: controle | M11: não | N11: FALHA DE INSTALAÇÃO / MONTAGEM | O11: «Os para raios da fase B e C estão fechando arco na cruzeta. Curto desceu para o controle danificando os componentes.» | P11: Causa explícita: para-raios arqueando na cruzeta por distância inadequada — o curto desceu e danificou o controle; a correção pede abaixar o tanque para afastar das cruzetas.
A12: RL 2025 | B12: =LEFT(Tabela3[[#This Row],[Ano/TIPO]],2) -> RL | D12: =_xlfn.XLOOKUP(K12,Base!G:G,Base!I:I) -> #N/A | E12: 7957620015 | F12: ETO-COEP 00081/2026 | G12: =_xlfn.XLOOKUP(_xlfn.NUMBERVALUE(Tabela3[[#This Row],[Ativo]]),'[2]Ajustes Reguladores de Tensão'!$A:$A,'[2]Ajustes Reguladores de Tensão'!$I:$I,_xlfn.XLOOKUP(_xlfn.NUMBERVALUE(Tabela3[[#This Row],[Ativo]]),'[2]Ajustes RL Poste'!$A:$A,'[2]Ajustes RL Poste'!$M:$M)) -> 13.800 | H12: 08/05/2025 | I12: =TEXT(Tabela3[[#This Row],[Data]],"mmmm") -> maio | J12: =YEAR(Tabela3[[#This Row],[Data]]) -> 2025 | K12: =_xlfn.CONCAT(Tabela3[[#This Row],[Ano]],Tabela3[[#This Row],[Mês]]) -> 2025maio | L12: controle | M12: sim | N12: FALHA DE INSTALAÇÃO / MONTAGEM | O12: «A antena do rádio do RLG 7957620015 fica próximo da BT, onde a mesma veio a encostar no cabo da fase o que ocasionou um curto-circuito no rádio, que passou para todos os componentes do controle» | P12: Causa explícita: antena instalada próxima da BT encostou no cabo da fase e o curto propagou do rádio para todo o controle — erro de montagem.
A13: RL 2025 | B13: =LEFT(Tabela3[[#This Row],[Ano/TIPO]],2) -> RL | D13: =_xlfn.XLOOKUP(K13,Base!G:G,Base!I:I) -> #N/A | E13: 7900117013 | F13: ETO-COEP 00084/2026 | G13: =_xlfn.XLOOKUP(_xlfn.NUMBERVALUE(Tabela3[[#This Row],[Ativo]]),'[2]Ajustes Reguladores de Tensão'!$A:$A,'[2]Ajustes Reguladores de Tensão'!$I:$I,_xlfn.XLOOKUP(_xlfn.NUMBERVALUE(Tabela3[[#This Row],[Ativo]]),'[2]Ajustes RL Poste'!$A:$A,'[2]Ajustes RL Poste'!$M:$M)) -> 13.800 | H13: 02/07/2025 | I13: =TEXT(Tabela3[[#This Row],[Data]],"mmmm") -> julho | J13: =YEAR(Tabela3[[#This Row],[Data]]) -> 2025 | K13: =_xlfn.CONCAT(Tabela3[[#This Row],[Ano]],Tabela3[[#This Row],[Mês]]) -> 2025julho | L13: completo | M13: sim | N13: FIRMWARE / ATUALIZAÇÃO | O13: «equipe DMSL Elisfran estava atualizando firmware no equipamento , porém relé parou de funcionar devido essa atualização» | P13: Explícito: o relé do Cooper Form6 parou de funcionar durante atualização de firmware feita pela própria equipe DMSL; sem peça de reposição, virou troca completa por Noja.
A14: RL 2025 | B14: =LEFT(Tabela3[[#This Row],[Ano/TIPO]],2) -> RL | D14: =_xlfn.XLOOKUP(K14,Base!G:G,Base!I:I) -> #N/A | E14: 7900535058 | F14: ETO-COEP 00173/2025 | G14: =_xlfn.XLOOKUP(_xlfn.NUMBERVALUE(Tabela3[[#This Row],[Ativo]]),'[2]Ajustes Reguladores de Tensão'!$A:$A,'[2]Ajustes Reguladores de Tensão'!$I:$I,_xlfn.XLOOKUP(_xlfn.NUMBERVALUE(Tabela3[[#This Row],[Ativo]]),'[2]Ajustes RL Poste'!$A:$A,'[2]Ajustes RL Poste'!$M:$M)) -> 34.500 | H14: 08/08/2025 | I14: =TEXT(Tabela3[[#This Row],[Data]],"mmmm") -> agosto | J14: =YEAR(Tabela3[[#This Row],[Data]]) -> 2025 | K14: =_xlfn.CONCAT(Tabela3[[#This Row],[Ano]],Tabela3[[#This Row],[Mês]]) -> 2025agosto | L14: completo | M14: não | N14: FIRMWARE / ATUALIZAÇÃO | O14: «encontra-se com o relé danificado, firmware corrompido, o mesmo não inicia» | P14: O relé não inicia por firmware corrompido (laudo DMSL); a origem da corrupção não é descrita, as abelhas no painel relatadas pela equipe não são vinculadas pelo laudo, e a troca completa decorre da falta de peças Cooper.
A15: RL 2025 | B15: =LEFT(Tabela3[[#This Row],[Ano/TIPO]],2) -> RL | D15: =_xlfn.XLOOKUP(K15,Base!G:G,Base!I:I) -> #N/A | E15: 7900018004 | F15: ETO-COEP 00178/2025 | G15: =_xlfn.XLOOKUP(_xlfn.NUMBERVALUE(Tabela3[[#This Row],[Ativo]]),'[2]Ajustes Reguladores de Tensão'!$A:$A,'[2]Ajustes Reguladores de Tensão'!$I:$I,_xlfn.XLOOKUP(_xlfn.NUMBERVALUE(Tabela3[[#This Row],[Ativo]]),'[2]Ajustes RL Poste'!$A:$A,'[2]Ajustes RL Poste'!$M:$M)) -> 34.500 | H15: 21/08/2025 | I15: =TEXT(Tabela3[[#This Row],[Data]],"mmmm") -> agosto | J15: =YEAR(Tabela3[[#This Row],[Data]]) -> 2025 | K15: =_xlfn.CONCAT(Tabela3[[#This Row],[Ano]],Tabela3[[#This Row],[Mês]]) -> 2025agosto | L15: completo | M15: sim | N15: OBSOLESCÊNCIA (SEM PEÇAS DE REPOSIÇÃO) | O15: «Por se tratar de modelo obsoleto e não termos peça de reposição para religador cooper, se faz necessário a substituição completa por um modelo NOJA RC10» | P15: Defeito no controle sem causa descrita; a substituição completa se dá pela obsolescência do Cooper sem peça de reposição.
A16: RL 2025 | B16: =LEFT(Tabela3[[#This Row],[Ano/TIPO]],2) -> RL | D16: =_xlfn.XLOOKUP(K16,Base!G:G,Base!I:I) -> #N/A | E16: 7903112004 | F16: ETO-COEP 00184/2025 | G16: =_xlfn.XLOOKUP(_xlfn.NUMBERVALUE(Tabela3[[#This Row],[Ativo]]),'[2]Ajustes Reguladores de Tensão'!$A:$A,'[2]Ajustes Reguladores de Tensão'!$I:$I,_xlfn.XLOOKUP(_xlfn.NUMBERVALUE(Tabela3[[#This Row],[Ativo]]),'[2]Ajustes RL Poste'!$A:$A,'[2]Ajustes RL Poste'!$M:$M)) -> 34.500 | H16: 03/09/2025 | I16: =TEXT(Tabela3[[#This Row],[Data]],"mmmm") -> setembro | J16: =YEAR(Tabela3[[#This Row],[Data]]) -> 2025 | K16: =_xlfn.CONCAT(Tabela3[[#This Row],[Ano]],Tabela3[[#This Row],[Mês]]) -> 2025setembro | L16: completo | M16: não | N16: OBSOLESCÊNCIA (SEM PEÇAS DE REPOSIÇÃO) | O16: «como se trata de um modelo COOPER FORM6 que está obsoleto e não possuímos peças sobressalentes, faz-se necessária substituição completa por modelo NOJA RC10» | P16: O texto só dá 'defeito' genérico; o que determina a perda do equipamento completo é a obsolescência do Cooper FORM6 sem sobressalentes — a causa da falha primária não é descrita.
A17: RL 2025 | B17: =LEFT(Tabela3[[#This Row],[Ano/TIPO]],2) -> RL | D17: =_xlfn.XLOOKUP(K17,Base!G:G,Base!I:I) -> #N/A | E17: 7900453110 | F17: ETO-COEP 00087/2026 | G17: =_xlfn.XLOOKUP(_xlfn.NUMBERVALUE(Tabela3[[#This Row],[Ativo]]),'[2]Ajustes Reguladores de Tensão'!$A:$A,'[2]Ajustes Reguladores de Tensão'!$I:$I,_xlfn.XLOOKUP(_xlfn.NUMBERVALUE(Tabela3[[#This Row],[Ativo]]),'[2]Ajustes RL Poste'!$A:$A,'[2]Ajustes RL Poste'!$M:$M)) -> 34.500 | H17: 22/04/2025 | I17: =TEXT(Tabela3[[#This Row],[Data]],"mmmm") -> abril | J17: =YEAR(Tabela3[[#This Row],[Data]]) -> 2025 | K17: =_xlfn.CONCAT(Tabela3[[#This Row],[Ano]],Tabela3[[#This Row],[Mês]]) -> 2025abril | L17: completo | M17: não | N17: SEM CAUSA DESCRITA NO TEXTO | O17: «Equipamento está com defeito na parte ativa, não aceita o comando de fechamento. Será necessário substituir o equipamento completo.» | P17: Defeito na parte ativa que não fecha é modo; nenhum porquê no texto — e a parte ativa comprada foi remanejada para outro ativo.
A18: RL 2025 | B18: =LEFT(Tabela3[[#This Row],[Ano/TIPO]],2) -> RL | D18: =_xlfn.XLOOKUP(K18,Base!G:G,Base!I:I) -> #N/A | E18: 7901110084 | F18: ETO-COEP 00061/2026 | G18: =_xlfn.XLOOKUP(_xlfn.NUMBERVALUE(Tabela3[[#This Row],[Ativo]]),'[2]Ajustes Reguladores de Tensão'!$A:$A,'[2]Ajustes Reguladores de Tensão'!$I:$I,_xlfn.XLOOKUP(_xlfn.NUMBERVALUE(Tabela3[[#This Row],[Ativo]]),'[2]Ajustes RL Poste'!$A:$A,'[2]Ajustes RL Poste'!$M:$M)) -> 34.500 | H18: 17/12/2025 | I18: =TEXT(Tabela3[[#This Row],[Data]],"mmmm") -> dezembro | J18: =YEAR(Tabela3[[#This Row],[Data]]) -> 2025 | K18: =_xlfn.CONCAT(Tabela3[[#This Row],[Ano]],Tabela3[[#This Row],[Mês]]) -> 2025dezembro | L18: tanque | M18: não | N18: SEM CAUSA DESCRITA NO TEXTO | O18: «Rl esta danificado dando passagem de tensão mesmo aberto» | P18: Análise técnica e testes funcionais só constatam a parte ativa com defeito (dá passagem aberto); o formulário confirma que não ficou em operação; sem porquê.
A19: RL 2025 | B19: =LEFT(Tabela3[[#This Row],[Ano/TIPO]],2) -> RL | D19: =_xlfn.XLOOKUP(K19,Base!G:G,Base!I:I) -> #N/A | E19: 7908705049 | F19: ETO-TELE 00824/2025 | G19: =_xlfn.XLOOKUP(_xlfn.NUMBERVALUE(Tabela3[[#This Row],[Ativo]]),'[2]Ajustes Reguladores de Tensão'!$A:$A,'[2]Ajustes Reguladores de Tensão'!$I:$I,_xlfn.XLOOKUP(_xlfn.NUMBERVALUE(Tabela3[[#This Row],[Ativo]]),'[2]Ajustes RL Poste'!$A:$A,'[2]Ajustes RL Poste'!$M:$M)) -> 13.800 | H19: 16/07/2025 | I19: =TEXT(Tabela3[[#This Row],[Data]],"mmmm") -> julho | J19: =YEAR(Tabela3[[#This Row],[Data]]) -> 2025 | K19: =_xlfn.CONCAT(Tabela3[[#This Row],[Ano]],Tabela3[[#This Row],[Mês]]) -> 2025julho | L19: completo | M19: não | N19: SEM CAUSA DESCRITA NO TEXTO | O19: «constatou que o tanque e o relé do mesmo se encontra queimado, providenciar substituição» | P19: Tanque e relé queimados é o modo; a queima simultânea sugere evento elétrico maior, mas o texto não nomeia o agente.
A20: RL 2025 | B20: =LEFT(Tabela3[[#This Row],[Ano/TIPO]],2) -> RL | D20: =_xlfn.XLOOKUP(K20,Base!G:G,Base!I:I) -> #N/A | E20: 7910027196 | F20: ETO-COEP 00154/2026 | G20: =_xlfn.XLOOKUP(_xlfn.NUMBERVALUE(Tabela3[[#This Row],[Ativo]]),'[2]Ajustes Reguladores de Tensão'!$A:$A,'[2]Ajustes Reguladores de Tensão'!$I:$I,_xlfn.XLOOKUP(_xlfn.NUMBERVALUE(Tabela3[[#This Row],[Ativo]]),'[2]Ajustes RL Poste'!$A:$A,'[2]Ajustes RL Poste'!$M:$M)) -> 34.500 | H20: 08/05/2025 | I20: =TEXT(Tabela3[[#This Row],[Data]],"mmmm") -> maio | J20: =YEAR(Tabela3[[#This Row],[Data]]) -> 2025 | K20: =_xlfn.CONCAT(Tabela3[[#This Row],[Ano]],Tabela3[[#This Row],[Mês]]) -> 2025maio | L20: completo | M20: não | N20: SEM CAUSA DESCRITA NO TEXTO | O20: «Necessitando substituição completa em função do defeito de leitura de corrente da fase B» | P20: Modo claro (leitura da fase B incorreta) sem causa firmada — o COEP especula 'erro de calibração', o parecer DMSL mais recente mantém a troca sem confirmar o porquê.
... A24: RL 2025 | B24: =LEFT(Tabela3[[#This Row],[Ano/TIPO]],2) -> RL | D24: =_xlfn.XLOOKUP(K24,Base!G:G,Base!I:I) -> #N/A | E24: 7925871077 | F24: ETO-TELE 00799/2025 | G24: =_xlfn.XLOOKUP(_xlfn.NUMBERVALUE(Tabela3[[#This Row],[Ativo]]),'[2]Ajustes Reguladores de Tensão'!$A:$A,'[2]Ajustes Reguladores de Tensão'!$I:$I,_xlfn.XLOOKUP(_xlfn.NUMBERVALUE(Tabela3[[#This Row],[Ativo]]),'[2]Ajustes RL Poste'!$A:$A,'[2]Ajustes RL Poste'!$M:$M)) -> 34.500 | H24: 10/07/2025 | I24: =TEXT(Tabela3[[#This Row],[Data]],"mmmm") -> julho | J24: =YEAR(Tabela3[[#This Row],[Data]]) -> 2025 | K24: =_xlfn.CONCAT(Tabela3[[#This Row],[Ano]],Tabela3[[#This Row],[Mês]]) -> 2025julho | L24: controle | M24: sim | N24: SEM CAUSA DESCRITA NO TEXTO | O24: «Foi realizado primeiro ataque mais o mesmo continua intermitente.» | P24: A descrição só relata intermitência após o primeiro ataque; a fonte queimada aparece na OS e, mesmo lá, sem a causa da queima.
A25: RL 2025 | B25: =LEFT(Tabela3[[#This Row],[Ano/TIPO]],2) -> RL | D25: =_xlfn.XLOOKUP(K25,Base!G:G,Base!I:I) -> #N/A | E25: 7927446001 | F25: ETO-COEP 00143/2025 | G25: =_xlfn.XLOOKUP(_xlfn.NUMBERVALUE(Tabela3[[#This Row],[Ativo]]),'[2]Ajustes Reguladores de Tensão'!$A:$A,'[2]Ajustes Reguladores de Tensão'!$I:$I,_xlfn.XLOOKUP(_xlfn.NUMBERVALUE(Tabela3[[#This Row],[Ativo]]),'[2]Ajustes RL Poste'!$A:$A,'[2]Ajustes RL Poste'!$M:$M)) -> 34.500 | H25: 26/06/2025 | I25: =TEXT(Tabela3[[#This Row],[Data]],"mmmm") -> junho | J25: =YEAR(Tabela3[[#This Row],[Data]]) -> 2025 | K25: =_xlfn.CONCAT(Tabela3[[#This Row],[Ano]],Tabela3[[#This Row],[Mês]]) -> 2025junho | L25: completo | M25: não | N25: SEM CAUSA DESCRITA NO TEXTO | O25: «Placa de alimentação danificada, devido a curto, não temos material sobressalente para manutenção! Favor substituir o equipamento completo.» | P25: Modo: placa de alimentação danificada 'devido a curto', sem o texto localizar o curto — pode ser interno ou vindo da rede BT pela alimentação, como nos casos das SS 00156/2025 e 00081/2026; a falta de sobressalente levou à troca do equipamento completo. | Q25: De CURTO-CIRCUITO INTERNO (media) para SEM CAUSA DESCRITA NO TEXTO (alta): o laudo diz só 'devido a curto', sem localizar o curto no equipamento. A placa de alimentação é a interface com a BT externa e há dois casos na própria fatia (7957126085 e 7957620015) em que o curto que danificou o controle veio de fora. 'INTERNO' era inferência, não texto; o mecanismo citado fica registrado na nota.
A26: RL 2025 | B26: =LEFT(Tabela3[[#This Row],[Ano/TIPO]],2) -> RL | D26: =_xlfn.XLOOKUP(K26,Base!G:G,Base!I:I) -> #N/A | E26: 7928564039 | F26: ETO-COEP 00162/2025 | G26: =_xlfn.XLOOKUP(_xlfn.NUMBERVALUE(Tabela3[[#This Row],[Ativo]]),'[2]Ajustes Reguladores de Tensão'!$A:$A,'[2]Ajustes Reguladores de Tensão'!$I:$I,_xlfn.XLOOKUP(_xlfn.NUMBERVALUE(Tabela3[[#This Row],[Ativo]]),'[2]Ajustes RL Poste'!$A:$A,'[2]Ajustes RL Poste'!$M:$M)) -> 34.500 | H26: 29/05/2025 | I26: =TEXT(Tabela3[[#This Row],[Data]],"mmmm") -> maio | J26: =YEAR(Tabela3[[#This Row],[Data]]) -> 2025 | K26: =_xlfn.CONCAT(Tabela3[[#This Row],[Ano]],Tabela3[[#This Row],[Mês]]) -> 2025maio | L26: completo | M26: não | N26: SEM CAUSA DESCRITA NO TEXTO | O26: «Equipamento com tanque, modulo e rele com defeito, solicitar troca do equipamento ao DCMD.» | P26: Tanque, módulo e relé 'com defeito' é modo em três peças, sem mecanismo algum descrito.
A27: RL 2025 | B27: =LEFT(Tabela3[[#This Row],[Ano/TIPO]],2) -> RL | D27: =_xlfn.XLOOKUP(K27,Base!G:G,Base!I:I) -> #N/A | E27: 7930428001 | F27: DG-RD-PO 00419/2025 | G27: =_xlfn.XLOOKUP(_xlfn.NUMBERVALUE(Tabela3[[#This Row],[Ativo]]),'[2]Ajustes Reguladores de Tensão'!$A:$A,'[2]Ajustes Reguladores de Tensão'!$I:$I,_xlfn.XLOOKUP(_xlfn.NUMBERVALUE(Tabela3[[#This Row],[Ativo]]),'[2]Ajustes RL Poste'!$A:$A,'[2]Ajustes RL Poste'!$M:$M)) -> 34.500 | H27: 01/07/2025 | I27: =TEXT(Tabela3[[#This Row],[Data]],"mmmm") -> julho | J27: =YEAR(Tabela3[[#This Row],[Data]]) -> 2025 | K27: =_xlfn.CONCAT(Tabela3[[#This Row],[Ano]],Tabela3[[#This Row],[Mês]]) -> 2025julho | L27: tanque | M27: não | N27: SEM CAUSA DESCRITA NO TEXTO | O27: «equipamento dando passagem na fase A ficou bay-passado até substituição» | P27: Dar passagem na fase A é o modo (o interruptor não isola); o texto não diz por que o tanque falhou.
A28: RL 2025 | B28: =LEFT(Tabela3[[#This Row],[Ano/TIPO]],2) -> RL | D28: =_xlfn.XLOOKUP(K28,Base!G:G,Base!I:I) -> #N/A | E28: 7931383086 | F28: ETO-TELE 00505/2025 | G28: =_xlfn.XLOOKUP(_xlfn.NUMBERVALUE(Tabela3[[#This Row],[Ativo]]),'[2]Ajustes Reguladores de Tensão'!$A:$A,'[2]Ajustes Reguladores de Tensão'!$I:$I,_xlfn.XLOOKUP(_xlfn.NUMBERVALUE(Tabela3[[#This Row],[Ativo]]),'[2]Ajustes RL Poste'!$A:$A,'[2]Ajustes RL Poste'!$M:$M)) -> 34.500 | H28: 15/05/2025 | I28: =TEXT(Tabela3[[#This Row],[Data]],"mmmm") -> maio | J28: =YEAR(Tabela3[[#This Row],[Data]]) -> 2025 | K28: =_xlfn.CONCAT(Tabela3[[#This Row],[Ano]],Tabela3[[#This Row],[Mês]]) -> 2025maio | L28: tanque | M28: sim | N28: SEM CAUSA DESCRITA NO TEXTO | O28: «RL 7931383086 perde a comunicaçao quando perde a CA» | P28: A descrição traz só o sintoma inicial (perde comunicação sem CA, hipótese de bateria); o tanque danificado aparece na OS, sem causa.
A29: RL 2025 | B29: =LEFT(Tabela3[[#This Row],[Ano/TIPO]],2) -> RL | D29: =_xlfn.XLOOKUP(K29,Base!G:G,Base!I:I) -> #N/A | E29: 7933585074 | F29: ETO-COEP 00024/2026 | G29: =_xlfn.XLOOKUP(_xlfn.NUMBERVALUE(Tabela3[[#This Row],[Ativo]]),'[2]Ajustes Reguladores de Tensão'!$A:$A,'[2]Ajustes Reguladores de Tensão'!$I:$I,_xlfn.XLOOKUP(_xlfn.NUMBERVALUE(Tabela3[[#This Row],[Ativo]]),'[2]Ajustes RL Poste'!$A:$A,'[2]Ajustes RL Poste'!$M:$M)) -> 34.500 | H29: 27/01/2026 | I29: =TEXT(Tabela3[[#This Row],[Data]],"mmmm") -> janeiro | J29: =YEAR(Tabela3[[#This Row],[Data]]) -> 2026 | K29: =_xlfn.CONCAT(Tabela3[[#This Row],[Ano]],Tabela3[[#This Row],[Mês]]) -> 2026janeiro | L29: tanque | M29: não | N29: SEM CAUSA DESCRITA NO TEXTO | O29: «REALIZAR SUBSTITUIÇÃO DO TANQUE, O MESMO ESTÁ COM DEFEITO.» | P29: Só o modo (tanque com defeito); o 'defeito em curto' registrado em SS irmã de 12/2025 não está nesta descrição.
A30: RL 2025 | B30: =LEFT(Tabela3[[#This Row],[Ano/TIPO]],2) -> RL | D30: =_xlfn.XLOOKUP(K30,Base!G:G,Base!I:I) -> #N/A | E30: 7934698002 | F30: ETO-COEP 00094/2025 | G30: =_xlfn.XLOOKUP(_xlfn.NUMBERVALUE(Tabela3[[#This Row],[Ativo]]),'[2]Ajustes Reguladores de Tensão'!$A:$A,'[2]Ajustes Reguladores de Tensão'!$I:$I,_xlfn.XLOOKUP(_xlfn.NUMBERVALUE(Tabela3[[#This Row],[Ativo]]),'[2]Ajustes RL Poste'!$A:$A,'[2]Ajustes RL Poste'!$M:$M)) -> 13.800 | H30: 06/05/2025 | I30: =TEXT(Tabela3[[#This Row],[Data]],"mmmm") -> maio | J30: =YEAR(Tabela3[[#This Row],[Data]]) -> 2025 | K30: =_xlfn.CONCAT(Tabela3[[#This Row],[Ano]],Tabela3[[#This Row],[Mês]]) -> 2025maio | L30: controle | M30: sim | N30: VANDALISMO | O30: «Substituir caixa de controle do RL 7934698002-RDU TOCANTINÓPOLIS, onde a mesma se encontra destruída em campo» | P30: Caixa de controle destruída restando a carcaça indica agente mecânico externo (vandalismo? abalroamento?), mas o texto não nomeia; a OBS traz o código com dígitos transpostos (7934968002), mesmo ativo e mesma RDU.
A31: RL 2025 | B31: =LEFT(Tabela3[[#This Row],[Ano/TIPO]],2) -> RL | D31: =_xlfn.XLOOKUP(K31,Base!G:G,Base!I:I) -> #N/A | E31: 7937102148 | F31: ETO-COEP 00228/2025 | G31: =_xlfn.XLOOKUP(_xlfn.NUMBERVALUE(Tabela3[[#This Row],[Ativo]]),'[2]Ajustes Reguladores de Tensão'!$A:$A,'[2]Ajustes Reguladores de Tensão'!$I:$I,_xlfn.XLOOKUP(_xlfn.NUMBERVALUE(Tabela3[[#This Row],[Ativo]]),'[2]Ajustes RL Poste'!$A:$A,'[2]Ajustes RL Poste'!$M:$M)) -> 34.500 | H31: 18/12/2025 | I31: =TEXT(Tabela3[[#This Row],[Data]],"mmmm") -> dezembro | J31: =YEAR(Tabela3[[#This Row],[Data]]) -> 2025 | K31: =_xlfn.CONCAT(Tabela3[[#This Row],[Ano]],Tabela3[[#This Row],[Mês]]) -> 2025dezembro | L31: tanque | M31: não | N31: SEM CAUSA DESCRITA NO TEXTO | O31: «Tanque com defeito, realizar substituição do tanque.» | P31: Só o modo — tanque com defeito; nenhum porquê no texto.
A32: RL 2025 | B32: =LEFT(Tabela3[[#This Row],[Ano/TIPO]],2) -> RL | D32: =_xlfn.XLOOKUP(K32,Base!G:G,Base!I:I) -> #N/A | E32: 7938137007 | F32: ETO-TELE 00050/2026 | G32: =_xlfn.XLOOKUP(_xlfn.NUMBERVALUE(Tabela3[[#This Row],[Ativo]]),'[2]Ajustes Reguladores de Tensão'!$A:$A,'[2]Ajustes Reguladores de Tensão'!$I:$I,_xlfn.XLOOKUP(_xlfn.NUMBERVALUE(Tabela3[[#This Row],[Ativo]]),'[2]Ajustes RL Poste'!$A:$A,'[2]Ajustes RL Poste'!$M:$M)) -> 13.800 | H32: 26/12/2025 | I32: =TEXT(Tabela3[[#This Row],[Data]],"mmmm") -> dezembro | J32: =YEAR(Tabela3[[#This Row],[Data]]) -> 2025 | K32: =_xlfn.CONCAT(Tabela3[[#This Row],[Ano]],Tabela3[[#This Row],[Mês]]) -> 2025dezembro | L32: completo | M32: não | N32: SEM CAUSA DESCRITA NO TEXTO | O32: «REALIZAR TROCA DE BATERIA DO EQUIPAMENTO» | P32: A descrição pede só troca de bateria; o problema na parte ativa (bucha da fase A) está na OS, sem causa descrita.
A33: RL 2025 | B33: =LEFT(Tabela3[[#This Row],[Ano/TIPO]],2) -> RL | D33: =_xlfn.XLOOKUP(K33,Base!G:G,Base!I:I) -> #N/A | E33: 7942485096 | F33: ETO-COEP 00158/2025 | G33: =_xlfn.XLOOKUP(_xlfn.NUMBERVALUE(Tabela3[[#This Row],[Ativo]]),'[2]Ajustes Reguladores de Tensão'!$A:$A,'[2]Ajustes Reguladores de Tensão'!$I:$I,_xlfn.XLOOKUP(_xlfn.NUMBERVALUE(Tabela3[[#This Row],[Ativo]]),'[2]Ajustes RL Poste'!$A:$A,'[2]Ajustes RL Poste'!$M:$M)) -> 34.500 | H33: 14/03/2025 | I33: =TEXT(Tabela3[[#This Row],[Data]],"mmmm") -> março | J33: =YEAR(Tabela3[[#This Row],[Data]]) -> 2025 | K33: =_xlfn.CONCAT(Tabela3[[#This Row],[Ano]],Tabela3[[#This Row],[Mês]]) -> 2025março | L33: tanque | M33: não | N33: SEM CAUSA DESCRITA NO TEXTO | O33: «Ao testar o tanque, foi constatado que o mesmo está danificado e precisa ser substituído» | P33: O teste só constata o dano ('danificado'), nenhuma causa no texto — e o DMSL frisa que o controle não precisa ser trocado.
A34: RL 2025 | B34: =LEFT(Tabela3[[#This Row],[Ano/TIPO]],2) -> RL | D34: =_xlfn.XLOOKUP(K34,Base!G:G,Base!I:I) -> #N/A | E34: 7943790134 | F34: ETO-COEP 00181/2025 | G34: =_xlfn.XLOOKUP(_xlfn.NUMBERVALUE(Tabela3[[#This Row],[Ativo]]),'[2]Ajustes Reguladores de Tensão'!$A:$A,'[2]Ajustes Reguladores de Tensão'!$I:$I,_xlfn.XLOOKUP(_xlfn.NUMBERVALUE(Tabela3[[#This Row],[Ativo]]),'[2]Ajustes RL Poste'!$A:$A,'[2]Ajustes RL Poste'!$M:$M)) -> 34.500 | H34: 29/05/2025 | I34: =TEXT(Tabela3[[#This Row],[Data]],"mmmm") -> maio | J34: =YEAR(Tabela3[[#This Row],[Data]]) -> 2025 | K34: =_xlfn.CONCAT(Tabela3[[#This Row],[Ano]],Tabela3[[#This Row],[Mês]]) -> 2025maio | L34: tanque | M34: sim | N34: SEM CAUSA DESCRITA NO TEXTO | O34: «foi constado que o RLG 7943790134 encontra-se com a parte ativa danificada» | P34: Os testes constataram a parte ativa danificada, sem porquê; o vazamento interno da fase C citado na revisão anterior está em outra SS, não nesta descrição.
A35: RL 2025 | B35: =LEFT(Tabela3[[#This Row],[Ano/TIPO]],2) -> RL | D35: =_xlfn.XLOOKUP(K35,Base!G:G,Base!I:I) -> #N/A | E35: 7947203070 | F35: ETO-COEP 00131/2026 | G35: =_xlfn.XLOOKUP(_xlfn.NUMBERVALUE(Tabela3[[#This Row],[Ativo]]),'[2]Ajustes Reguladores de Tensão'!$A:$A,'[2]Ajustes Reguladores de Tensão'!$I:$I,_xlfn.XLOOKUP(_xlfn.NUMBERVALUE(Tabela3[[#This Row],[Ativo]]),'[2]Ajustes RL Poste'!$A:$A,'[2]Ajustes RL Poste'!$M:$M)) -> 34.500 | H35: 23/11/2025 | I35: =TEXT(Tabela3[[#This Row],[Data]],"mmmm") -> novembro | J35: =YEAR(Tabela3[[#This Row],[Data]]) -> 2025 | K35: =_xlfn.CONCAT(Tabela3[[#This Row],[Ano]],Tabela3[[#This Row],[Mês]]) -> 2025novembro | L35: controle | M35: não | N35: SEM CAUSA DESCRITA NO TEXTO | O35: «Foi feito análise técnica, a placa do equipamento está queimada nessesario subistituir o equipamento completo» | P35: Modo: placa do controle queimada, constatada em análise técnica; nenhum porquê da queima no texto. O parecer COEP mais recente (13/07) definiu compra de controle. | Q35: De DEFEITO ELETRÔNICO (media) para SEM CAUSA DESCRITA NO TEXTO (alta): 'placa queimada' é modo de falha (queima), sem diagnóstico funcional nem agente — mesma situação da fonte queimada (7925871077) e do relé queimado (7908705049), que o próprio arquivo classifica SEM CAUSA. DEFEITO ELETRÔNICO fica para diagnóstico funcional específico, como display apagado com CA normal (7936038076) e porta RS-232 falhada (7900594026).
A36: RL 2025 | B36: =LEFT(Tabela3[[#This Row],[Ano/TIPO]],2) -> RL | D36: =_xlfn.XLOOKUP(K36,Base!G:G,Base!I:I) -> #N/A | E36: 7949648145 | F36: ETO-TELE 00630/2025 | G36: =_xlfn.XLOOKUP(_xlfn.NUMBERVALUE(Tabela3[[#This Row],[Ativo]]),'[2]Ajustes Reguladores de Tensão'!$A:$A,'[2]Ajustes Reguladores de Tensão'!$I:$I,_xlfn.XLOOKUP(_xlfn.NUMBERVALUE(Tabela3[[#This Row],[Ativo]]),'[2]Ajustes RL Poste'!$A:$A,'[2]Ajustes RL Poste'!$M:$M)) -> 13.800 | H36: 10/06/2025 | I36: =TEXT(Tabela3[[#This Row],[Data]],"mmmm") -> junho | J36: =YEAR(Tabela3[[#This Row],[Data]]) -> 2025 | K36: =_xlfn.CONCAT(Tabela3[[#This Row],[Ano]],Tabela3[[#This Row],[Mês]]) -> 2025junho | L36: completo | M36: sim | N36: SEM CAUSA DESCRITA NO TEXTO | O36: «FAVOR, REALIZAR SUBSTITUIÇÃO DE RELIGADOR» | P36: Descrição de uma linha só, sem modo nem causa; a execução da troca vem da OS.
A37: RT 2025 | B37: =LEFT(Tabela3[[#This Row],[Ano/TIPO]],2) -> RT | D37: =_xlfn.XLOOKUP(K37,Base!G:G,Base!I:I) -> #N/A | E37: 5800371025 | F37: ETO-COEP 00187/2025 | G37: =_xlfn.XLOOKUP(_xlfn.NUMBERVALUE(Tabela3[[#This Row],[Ativo]]),'[2]Ajustes Reguladores de Tensão'!$A:$A,'[2]Ajustes Reguladores de Tensão'!$I:$I,_xlfn.XLOOKUP(_xlfn.NUMBERVALUE(Tabela3[[#This Row],[Ativo]]),'[2]Ajustes RL Poste'!$A:$A,'[2]Ajustes RL Poste'!$M:$M)) -> 34.500 | H37: 23/08/2025 | I37: =TEXT(Tabela3[[#This Row],[Data]],"mmmm") -> agosto | J37: =YEAR(Tabela3[[#This Row],[Data]]) -> 2025 | K37: =_xlfn.CONCAT(Tabela3[[#This Row],[Ano]],Tabela3[[#This Row],[Mês]]) -> 2025agosto | L37: rele | M37: sim | N37: DEFEITO ELETRÔNICO (CONTROLE/PLACA/RELÉ) | O37: «Após testes foi constatado defeito nos relés da fase A e B, Modelo Toshiba TBR 1000.» | P37: O laudo constata defeito nos relés Toshiba TBR 1000 das fases A e B sem dizer por que falharam — defeito do próprio eletrônico, sem causa mais profunda descrita no texto.
A38: RT 2025 | B38: =LEFT(Tabela3[[#This Row],[Ano/TIPO]],2) -> RT | D38: =_xlfn.XLOOKUP(K38,Base!G:G,Base!I:I) -> #N/A | E38: 5800438116 | F38: ETO-COEP 00171/2025 | G38: =_xlfn.XLOOKUP(_xlfn.NUMBERVALUE(Tabela3[[#This Row],[Ativo]]),'[2]Ajustes Reguladores de Tensão'!$A:$A,'[2]Ajustes Reguladores de Tensão'!$I:$I,_xlfn.XLOOKUP(_xlfn.NUMBERVALUE(Tabela3[[#This Row],[Ativo]]),'[2]Ajustes RL Poste'!$A:$A,'[2]Ajustes RL Poste'!$M:$M)) -> 34.500 | H38: 18/07/2025 | I38: =TEXT(Tabela3[[#This Row],[Data]],"mmmm") -> julho | J38: =YEAR(Tabela3[[#This Row],[Data]]) -> 2025 | K38: =_xlfn.CONCAT(Tabela3[[#This Row],[Ano]],Tabela3[[#This Row],[Mês]]) -> 2025julho | L38: celula | M38: sim | N38: DEFEITO MECÂNICO (CHAVE REVERSORA) | O38: «Foi feito teste de elevar e abaixar nas fases B e C e o mesmo só aceita elevar os taps, constatando que o mercanismo da chave reversoura polaridade está com defeito.» | P38: Fases B/C travadas com causa diagnosticada explícita: defeito no mecanismo da chave reversora de polaridade (placa F do controle também com defeito); a origem do defeito mecânico não é dita.
A39: RT 2025 | B39: =LEFT(Tabela3[[#This Row],[Ano/TIPO]],2) -> RT | D39: =_xlfn.XLOOKUP(K39,Base!G:G,Base!I:I) -> #N/A | E39: 5854566043 | F39: ETO-COEP 00036/2025 | G39: =_xlfn.XLOOKUP(_xlfn.NUMBERVALUE(Tabela3[[#This Row],[Ativo]]),'[2]Ajustes Reguladores de Tensão'!$A:$A,'[2]Ajustes Reguladores de Tensão'!$I:$I,_xlfn.XLOOKUP(_xlfn.NUMBERVALUE(Tabela3[[#This Row],[Ativo]]),'[2]Ajustes RL Poste'!$A:$A,'[2]Ajustes RL Poste'!$M:$M)) -> 34.500 | H39: 21/03/2025 | I39: =TEXT(Tabela3[[#This Row],[Data]],"mmmm") -> março | J39: =YEAR(Tabela3[[#This Row],[Data]]) -> 2025 | K39: =_xlfn.CONCAT(Tabela3[[#This Row],[Ano]],Tabela3[[#This Row],[Mês]]) -> 2025março | L39: celula | M39: sim | N39: DESCARGA ATMOSFÉRICA (RAIO) | O39: «a fase C do regulador 5854566043 está danificada devido a uma descarga atmosférica. Vazou óleo e o mesmo está com coloração escura o que evidencia o seu comprometimento.» | P39: Laudo explícito: fase C danificada por descarga atmosférica, com óleo vazado e escurecido; o código citado é o do próprio ativo da linha.
A40: RT 2025 | B40: =LEFT(Tabela3[[#This Row],[Ano/TIPO]],2) -> RT | D40: =_xlfn.XLOOKUP(K40,Base!G:G,Base!I:I) -> #N/A | E40: 5841308190 | F40: ETO-COEP 00154/2025 | G40: =_xlfn.XLOOKUP(_xlfn.NUMBERVALUE(Tabela3[[#This Row],[Ativo]]),'[2]Ajustes Reguladores de Tensão'!$A:$A,'[2]Ajustes Reguladores de Tensão'!$I:$I,_xlfn.XLOOKUP(_xlfn.NUMBERVALUE(Tabela3[[#This Row],[Ativo]]),'[2]Ajustes RL Poste'!$A:$A,'[2]Ajustes RL Poste'!$M:$M)) -> 34.500 | H40: 21/08/2025 | I40: =TEXT(Tabela3[[#This Row],[Data]],"mmmm") -> agosto | J40: =YEAR(Tabela3[[#This Row],[Data]]) -> 2025 | K40: =_xlfn.CONCAT(Tabela3[[#This Row],[Ano]],Tabela3[[#This Row],[Mês]]) -> 2025agosto | L40: furto | M40: sim | N40: FURTO | O40: «Solicitação de serviço para reposição de equipamentos furtados» | P40: Reposição de equipamento furtado, já substituído pelos COCMs — furto declarado no texto.
A41: RT 2025 | B41: =LEFT(Tabela3[[#This Row],[Ano/TIPO]],2) -> RT | D41: =_xlfn.XLOOKUP(K41,Base!G:G,Base!I:I) -> #N/A | E41: 5841308190 | F41: ETO-COEP 00197/2025 | G41: =_xlfn.XLOOKUP(_xlfn.NUMBERVALUE(Tabela3[[#This Row],[Ativo]]),'[2]Ajustes Reguladores de Tensão'!$A:$A,'[2]Ajustes Reguladores de Tensão'!$I:$I,_xlfn.XLOOKUP(_xlfn.NUMBERVALUE(Tabela3[[#This Row],[Ativo]]),'[2]Ajustes RL Poste'!$A:$A,'[2]Ajustes RL Poste'!$M:$M)) -> 34.500 | H41: 29/09/2025 | I41: =TEXT(Tabela3[[#This Row],[Data]],"mmmm") -> setembro | J41: =YEAR(Tabela3[[#This Row],[Data]]) -> 2025 | K41: =_xlfn.CONCAT(Tabela3[[#This Row],[Ano]],Tabela3[[#This Row],[Mês]]) -> 2025setembro | L41: furto | M41: não | N41: FURTO | O41: «Após alguns análise foi identificado que as 3 fases estava sem óleo, provavelmente foram roubados.» | P41: DMSL achou as 3 fases sem óleo ('provavelmente foram roubados') e o COEP desmobiliza o RT citando 'furtos recorrentes na região' — segundo furto do mesmo ativo no ano; o hedge do laudo é coberto pela decisão do COEP.
A42: RT 2025 | B42: =LEFT(Tabela3[[#This Row],[Ano/TIPO]],2) -> RT | D42: =_xlfn.XLOOKUP(K42,Base!G:G,Base!I:I) -> #N/A | E42: 5856070091 | F42: ETO-COEP 00056/2026 | G42: =_xlfn.XLOOKUP(_xlfn.NUMBERVALUE(Tabela3[[#This Row],[Ativo]]),'[2]Ajustes Reguladores de Tensão'!$A:$A,'[2]Ajustes Reguladores de Tensão'!$I:$I,_xlfn.XLOOKUP(_xlfn.NUMBERVALUE(Tabela3[[#This Row],[Ativo]]),'[2]Ajustes RL Poste'!$A:$A,'[2]Ajustes RL Poste'!$M:$M)) -> 34.500 | H42: 18/07/2025 | I42: =TEXT(Tabela3[[#This Row],[Data]],"mmmm") -> julho | J42: =YEAR(Tabela3[[#This Row],[Data]]) -> 2025 | K42: =_xlfn.CONCAT(Tabela3[[#This Row],[Ano]],Tabela3[[#This Row],[Mês]]) -> 2025julho | L42: furto | M42: sim | N42: FURTO | O42: «Solicitação de serviço para reposição de equipamentos furtados» | P42: SS aberta como reposição de equipamento furtado; o restante do texto é a esteira de reposição e um erro de instalação posterior (fonte/carga invertidas), não a causa original.
A43: RT 2025 | B43: =LEFT(Tabela3[[#This Row],[Ano/TIPO]],2) -> RT | D43: =_xlfn.XLOOKUP(K43,Base!G:G,Base!I:I) -> #N/A | E43: 5856156091 | F43: ETO-COEP 00055/2026 | G43: =_xlfn.XLOOKUP(_xlfn.NUMBERVALUE(Tabela3[[#This Row],[Ativo]]),'[2]Ajustes Reguladores de Tensão'!$A:$A,'[2]Ajustes Reguladores de Tensão'!$I:$I,_xlfn.XLOOKUP(_xlfn.NUMBERVALUE(Tabela3[[#This Row],[Ativo]]),'[2]Ajustes RL Poste'!$A:$A,'[2]Ajustes RL Poste'!$M:$M)) -> 34.500 | H43: 16/06/2025 | I43: =TEXT(Tabela3[[#This Row],[Data]],"mmmm") -> junho | J43: =YEAR(Tabela3[[#This Row],[Data]]) -> 2025 | K43: =_xlfn.CONCAT(Tabela3[[#This Row],[Ano]],Tabela3[[#This Row],[Mês]]) -> 2025junho | L43: furto | M43: não | N43: FURTO | O43: «PARECER DA PROTEÇÃO:EQUIPAMENTOS FURTADOS. PARA AQUISIÇÃO DAS CELULAS DE REPOSIÇÃO, FAVOR CONSULTAR OS DADOS DE PLACA EM ANEXO.» | P43: Parecer da Proteção declara equipamentos furtados e pede células de reposição; o texto chama o ativo de 'religador' por engano, mas o código 5856156091 é o do próprio RT da linha.
A44: RT 2025 | B44: =LEFT(Tabela3[[#This Row],[Ano/TIPO]],2) -> RT | D44: =_xlfn.XLOOKUP(K44,Base!G:G,Base!I:I) -> #N/A | E44: 5858783119 | F44: ETO-COEP 00123/2025 | G44: =_xlfn.XLOOKUP(_xlfn.NUMBERVALUE(Tabela3[[#This Row],[Ativo]]),'[2]Ajustes Reguladores de Tensão'!$A:$A,'[2]Ajustes Reguladores de Tensão'!$I:$I,_xlfn.XLOOKUP(_xlfn.NUMBERVALUE(Tabela3[[#This Row],[Ativo]]),'[2]Ajustes RL Poste'!$A:$A,'[2]Ajustes RL Poste'!$M:$M)) -> 34.500 | H44: 24/03/2025 | I44: =TEXT(Tabela3[[#This Row],[Data]],"mmmm") -> março | J44: =YEAR(Tabela3[[#This Row],[Data]]) -> 2025 | K44: =_xlfn.CONCAT(Tabela3[[#This Row],[Ano]],Tabela3[[#This Row],[Mês]]) -> 2025março | L44: furto | M44: não | N44: FURTO | O44: «Constatado também que foi furtado todo o óleo isolante das 3 células, sendo necessário a substituição das 3 células.» | P44: Tampas de inspeção abertas, para-raios levados e todo o óleo isolante furtado das 3 células; o COEP confirma 'DEVIDO AO ERRO NA INSTALAÇÃO E O FURTO'.
A45: RT 2025 | B45: =LEFT(Tabela3[[#This Row],[Ano/TIPO]],2) -> RT | D45: =_xlfn.XLOOKUP(K45,Base!G:G,Base!I:I) -> #N/A | E45: 5803327001 | F45: ETO-COEP 00021/2026 | G45: =_xlfn.XLOOKUP(_xlfn.NUMBERVALUE(Tabela3[[#This Row],[Ativo]]),'[2]Ajustes Reguladores de Tensão'!$A:$A,'[2]Ajustes Reguladores de Tensão'!$I:$I,_xlfn.XLOOKUP(_xlfn.NUMBERVALUE(Tabela3[[#This Row],[Ativo]]),'[2]Ajustes RL Poste'!$A:$A,'[2]Ajustes RL Poste'!$M:$M)) -> 13.800 | H45: 04/09/2025 | I45: =TEXT(Tabela3[[#This Row],[Data]],"mmmm") -> setembro | J45: =YEAR(Tabela3[[#This Row],[Data]]) -> 2025 | K45: =_xlfn.CONCAT(Tabela3[[#This Row],[Ano]],Tabela3[[#This Row],[Mês]]) -> 2025setembro | L45: controle | M45: não | N45: INSTALAÇÃO / COMISSIONAMENTO INADEQUADO | O45: «Equipamento foi remanejado, 7 km da sua localização sentido Palmas necessário comissionamento completo*Equipamento com um dos cabos umbilicais danificado.» | P45: A razão da troca do controle não é dita, mas o texto detalha remanejamento de 7 km sem comissionamento, cabo umbilical danificado e aterramento da bucha FC mal interligado — falha de instalação, não do equipamento.
A46: RT 2025 | B46: =LEFT(Tabela3[[#This Row],[Ano/TIPO]],2) -> RT | D46: =_xlfn.XLOOKUP(K46,Base!G:G,Base!I:I) -> #N/A | E46: 5800961074 | F46: ETO-COEP 00221/2025 | G46: =_xlfn.XLOOKUP(_xlfn.NUMBERVALUE(Tabela3[[#This Row],[Ativo]]),'[2]Ajustes Reguladores de Tensão'!$A:$A,'[2]Ajustes Reguladores de Tensão'!$I:$I,_xlfn.XLOOKUP(_xlfn.NUMBERVALUE(Tabela3[[#This Row],[Ativo]]),'[2]Ajustes RL Poste'!$A:$A,'[2]Ajustes RL Poste'!$M:$M)) -> 34.500 | H46: 05/12/2025 | I46: =TEXT(Tabela3[[#This Row],[Data]],"mmmm") -> dezembro | J46: =YEAR(Tabela3[[#This Row],[Data]]) -> 2025 | K46: =_xlfn.CONCAT(Tabela3[[#This Row],[Ano]],Tabela3[[#This Row],[Mês]]) -> 2025dezembro | L46: celula | M46: não | N46: SEM CAUSA DESCRITA NO TEXTO | O46: «Substituir as 3 células- Melhoria na malha de aterramento - Melhoria no circuito de aterramento qua aterra as células.» | P46: O texto é só escopo de compra (3 células, melhorias de aterramento, conectores); a melhoria de aterramento sugere deficiência, mas nada liga isso à falha das células — não se chuta laudo.
A47: RT 2025 | B47: =LEFT(Tabela3[[#This Row],[Ano/TIPO]],2) -> RT | D47: =_xlfn.XLOOKUP(K47,Base!G:G,Base!I:I) -> #N/A | E47: 5820790038 | F47: ETO-TELE 00159/2025 | G47: =_xlfn.XLOOKUP(_xlfn.NUMBERVALUE(Tabela3[[#This Row],[Ativo]]),'[2]Ajustes Reguladores de Tensão'!$A:$A,'[2]Ajustes Reguladores de Tensão'!$I:$I,_xlfn.XLOOKUP(_xlfn.NUMBERVALUE(Tabela3[[#This Row],[Ativo]]),'[2]Ajustes RL Poste'!$A:$A,'[2]Ajustes RL Poste'!$M:$M)) -> 34.500 | H47: 19/02/2025 | I47: =TEXT(Tabela3[[#This Row],[Data]],"mmmm") -> fevereiro | J47: =YEAR(Tabela3[[#This Row],[Data]]) -> 2025 | K47: =_xlfn.CONCAT(Tabela3[[#This Row],[Ano]],Tabela3[[#This Row],[Mês]]) -> 2025fevereiro | L47: controle | M47: sim | N47: SEM CAUSA DESCRITA NO TEXTO | O47: «FEITO O PRIMEIRO ATAQUE E PERCEBIDO QUE O MESMO NÃO ESTA COMUNICANDO COM O SCADA. EM CAMPO ESTA COMULTANDO NORMAL» | P47: O texto só dá o sintoma — sem comunicação com o SCADA, comutando normal em campo — e nenhuma razão para a falha de comunicação.
... A49: RT 2025 | B49: =LEFT(Tabela3[[#This Row],[Ano/TIPO]],2) -> RT | D49: =_xlfn.XLOOKUP(K49,Base!G:G,Base!I:I) -> #N/A | E49: 5854566043 | F49: ETO-COEP 00160/2025 | G49: =_xlfn.XLOOKUP(_xlfn.NUMBERVALUE(Tabela3[[#This Row],[Ativo]]),'[2]Ajustes Reguladores de Tensão'!$A:$A,'[2]Ajustes Reguladores de Tensão'!$I:$I,_xlfn.XLOOKUP(_xlfn.NUMBERVALUE(Tabela3[[#This Row],[Ativo]]),'[2]Ajustes RL Poste'!$A:$A,'[2]Ajustes RL Poste'!$M:$M)) -> 34.500 | H49: 23/07/2025 | I49: =TEXT(Tabela3[[#This Row],[Data]],"mmmm") -> julho | J49: =YEAR(Tabela3[[#This Row],[Data]]) -> 2025 | K49: =_xlfn.CONCAT(Tabela3[[#This Row],[Ano]],Tabela3[[#This Row],[Mês]]) -> 2025julho | L49: celula | M49: sim | N49: SEM CAUSA DESCRITA NO TEXTO | O49: «A fase B está danificada e será necessário substituir a mesma. Malha de aterramento está relativamente boa e conectada. Fase A e C passaram nos ensaios.» | P49: Segunda falha do mesmo ativo no ano: a nota de campo fala fase C queimada, mas vale o parecer DMSL mais recente — fase B danificada, A e C aprovadas — e nenhum porquê; o aterramento estava bom.
A50: RT 2025 | B50: =LEFT(Tabela3[[#This Row],[Ano/TIPO]],2) -> RT | D50: =_xlfn.XLOOKUP(K50,Base!G:G,Base!I:I) -> #N/A | E50: 5855411017 | F50: ETO-COEP 00199/2025 | G50: =_xlfn.XLOOKUP(_xlfn.NUMBERVALUE(Tabela3[[#This Row],[Ativo]]),'[2]Ajustes Reguladores de Tensão'!$A:$A,'[2]Ajustes Reguladores de Tensão'!$I:$I,_xlfn.XLOOKUP(_xlfn.NUMBERVALUE(Tabela3[[#This Row],[Ativo]]),'[2]Ajustes RL Poste'!$A:$A,'[2]Ajustes RL Poste'!$M:$M)) -> 13.800 | H50: 03/09/2025 | I50: =TEXT(Tabela3[[#This Row],[Data]],"mmmm") -> setembro | J50: =YEAR(Tabela3[[#This Row],[Data]]) -> 2025 | K50: =_xlfn.CONCAT(Tabela3[[#This Row],[Ano]],Tabela3[[#This Row],[Mês]]) -> 2025setembro | L50: controle | M50: não | N50: SEM CAUSA DESCRITA NO TEXTO | O50: «SEM COMUNICAÇÃO, FALHA DE ALIMENTAÇÃO - REALIZADO PRIMEIRO ATAQUE SEM SUCESSO.» | P50: O texto dá só o sintoma — sem comunicação, falha de alimentação, primeiro ataque sem sucesso — e a pendência de levar controle completo para trocar; onde está o defeito e por que a alimentação falhou não são ditos. | R50: Corrigido de DEFEITO ELETRÔNICO (CONTROLE/PLACA/RELÉ) para SEM CAUSA DESCRITA NO TEXTO. 'Falha de alimentação' é sintoma, não diagnóstico: ninguém constatou defeito no eletrônico (compare 5800371025, onde o DMSL diz 'após testes foi constatado defeito nos relés'). A causa foi inferida do remédio — trocar o controle completo — e remédio não é laudo; a falha de alimentação podia ser externa (trafo auxiliar, cabo). Confiança sobe para alta porque a ausência de causa é certa.
A51: RT 2025 | B51: =LEFT(Tabela3[[#This Row],[Ano/TIPO]],2) -> RT | D51: =_xlfn.XLOOKUP(K51,Base!G:G,Base!I:I) -> #N/A | E51: 5827102054 | F51: ETO-COEP 00216/2025 | G51: =_xlfn.XLOOKUP(_xlfn.NUMBERVALUE(Tabela3[[#This Row],[Ativo]]),'[2]Ajustes Reguladores de Tensão'!$A:$A,'[2]Ajustes Reguladores de Tensão'!$I:$I,_xlfn.XLOOKUP(_xlfn.NUMBERVALUE(Tabela3[[#This Row],[Ativo]]),'[2]Ajustes RL Poste'!$A:$A,'[2]Ajustes RL Poste'!$M:$M)) -> 34.500 | H51: 27/08/2025 | I51: =TEXT(Tabela3[[#This Row],[Data]],"mmmm") -> agosto | J51: =YEAR(Tabela3[[#This Row],[Data]]) -> 2025 | K51: =_xlfn.CONCAT(Tabela3[[#This Row],[Ano]],Tabela3[[#This Row],[Mês]]) -> 2025agosto | L51: rele | M51: sim | N51: UMIDADE / INFILTRAÇÃO | O51: «Se possível retornar com controle completo pq o q está em campo teve infiltração de água» | P51: O relé queimado e o nobreak defeituoso ficam dentro do controle que 'teve infiltração de água' — causa explícita do pedido de controle novo; a resistência alta da malha aparece como agravante, não como causa.
A52: RT 2025 | B52: =LEFT(Tabela3[[#This Row],[Ano/TIPO]],2) -> RT | D52: =_xlfn.XLOOKUP(K52,Base!G:G,Base!I:I) -> #N/A | E52: 5862236091 | F52: ETO-SE-PCM 00065/2025 | G52: =_xlfn.XLOOKUP(_xlfn.NUMBERVALUE(Tabela3[[#This Row],[Ativo]]),'[2]Ajustes Reguladores de Tensão'!$A:$A,'[2]Ajustes Reguladores de Tensão'!$I:$I,_xlfn.XLOOKUP(_xlfn.NUMBERVALUE(Tabela3[[#This Row],[Ativo]]),'[2]Ajustes RL Poste'!$A:$A,'[2]Ajustes RL Poste'!$M:$M)) -> 34.500 | H52: 08/12/2025 | I52: =TEXT(Tabela3[[#This Row],[Data]],"mmmm") -> dezembro | J52: =YEAR(Tabela3[[#This Row],[Data]]) -> 2025 | K52: =_xlfn.CONCAT(Tabela3[[#This Row],[Ano]],Tabela3[[#This Row],[Mês]]) -> 2025dezembro | L52: celula | M52: não | N52: UMIDADE / INFILTRAÇÃO | O52: «Célula da fase B estava com a tampa do contador de tape aberta, pegou chuva e molhou os contatos danificando a peça toda.» | P52: Causa explícita e completa: tampa do contador de tap aberta deixou a chuva molhar os contatos e danificar a célula da fase B — água de chuva, não defeito interno.
A53: RT 2025 | B53: =LEFT(Tabela3[[#This Row],[Ano/TIPO]],2) -> RT | D53: =_xlfn.XLOOKUP(K53,Base!G:G,Base!I:I) -> #N/A | E53: 5800440256 | F53: ETO-TELE 01431/2025 | G53: =_xlfn.XLOOKUP(_xlfn.NUMBERVALUE(Tabela3[[#This Row],[Ativo]]),'[2]Ajustes Reguladores de Tensão'!$A:$A,'[2]Ajustes Reguladores de Tensão'!$I:$I,_xlfn.XLOOKUP(_xlfn.NUMBERVALUE(Tabela3[[#This Row],[Ativo]]),'[2]Ajustes RL Poste'!$A:$A,'[2]Ajustes RL Poste'!$M:$M)) -> 34.500 | H53: 30/11/2025 | I53: =TEXT(Tabela3[[#This Row],[Data]],"mmmm") -> novembro | J53: =YEAR(Tabela3[[#This Row],[Data]]) -> 2025 | K53: =_xlfn.CONCAT(Tabela3[[#This Row],[Ano]],Tabela3[[#This Row],[Mês]]) -> 2025novembro | L53: celula | M53: sim | N53: VAZAMENTO DE ÓLEO / VEDAÇÃO | O53: «o mesmo esta com uma das celulas apresentando vazamento , o equipamento ficou bypassado» | P53: A célula vazou óleo a ponto de causar desarme da LD Ponte Alta–Mateiros e bypass — o vazamento é a falha declarada; a origem exata da perda de vedação não é detalhada.
A54: RT 2025 | B54: =LEFT(Tabela3[[#This Row],[Ano/TIPO]],2) -> RT | D54: =_xlfn.XLOOKUP(K54,Base!G:G,Base!I:I) -> #N/A | E54: 5844630060 | F54: ETO-RD-AR 01131/2026 | G54: =_xlfn.XLOOKUP(_xlfn.NUMBERVALUE(Tabela3[[#This Row],[Ativo]]),'[2]Ajustes Reguladores de Tensão'!$A:$A,'[2]Ajustes Reguladores de Tensão'!$I:$I,_xlfn.XLOOKUP(_xlfn.NUMBERVALUE(Tabela3[[#This Row],[Ativo]]),'[2]Ajustes RL Poste'!$A:$A,'[2]Ajustes RL Poste'!$M:$M)) -> 13.800 | H54: 06/08/2025 | I54: =TEXT(Tabela3[[#This Row],[Data]],"mmmm") -> agosto | J54: =YEAR(Tabela3[[#This Row],[Data]]) -> 2025 | K54: =_xlfn.CONCAT(Tabela3[[#This Row],[Ano]],Tabela3[[#This Row],[Mês]]) -> 2025agosto | L54: celula | M54: sim | N54: VAZAMENTO DE ÓLEO / VEDAÇÃO | O54: «Célula da fase A encontra-se com vazamento de óleo no pé da torneira. Necessário substituição da célula.» | P54: Vazamento de óleo no pé da torneira da fase A declarado pelo DMSL — ponto de vedação; o porquê da perda de vedação não é detalhado.
A55: RT 2026 | B55: =LEFT(Tabela3[[#This Row],[Ano/TIPO]],2) -> RT | D55: =_xlfn.XLOOKUP(K55,Base!G:G,Base!I:I) -> #N/A | E55: 5840227063 | F55: ETO-COEP 00151/2026 | G55: =_xlfn.XLOOKUP(_xlfn.NUMBERVALUE(Tabela3[[#This Row],[Ativo]]),'[2]Ajustes Reguladores de Tensão'!$A:$A,'[2]Ajustes Reguladores de Tensão'!$I:$I,_xlfn.XLOOKUP(_xlfn.NUMBERVALUE(Tabela3[[#This Row],[Ativo]]),'[2]Ajustes RL Poste'!$A:$A,'[2]Ajustes RL Poste'!$M:$M)) -> 34.500 | H55: 13/07/2026 | I55: =TEXT(Tabela3[[#This Row],[Data]],"mmmm") -> julho | J55: =YEAR(Tabela3[[#This Row],[Data]]) -> 2026 | K55: =_xlfn.CONCAT(Tabela3[[#This Row],[Ano]],Tabela3[[#This Row],[Mês]]) -> 2026julho | L55: celula | M55: não | N55: CURTO-CIRCUITO INTERNO | O55: «Realizados ensaios de isolação nas três células, e foi identificado curto na fase A, sendo necessário a sua substituição» | P55: Ensaio de isolação identificou curto na célula (abertura citava fase C, DMSL fechou na A) — falha dielétrica interna comprovada por ensaio; o gatilho do curto não é declarado.
A56: RT 2026 | B56: =LEFT(Tabela3[[#This Row],[Ano/TIPO]],2) -> RT | D56: =_xlfn.XLOOKUP(K56,Base!G:G,Base!I:I) -> #N/A | E56: 5800859011 | F56: ETO-COEP 00115/2026 | G56: =_xlfn.XLOOKUP(_xlfn.NUMBERVALUE(Tabela3[[#This Row],[Ativo]]),'[2]Ajustes Reguladores de Tensão'!$A:$A,'[2]Ajustes Reguladores de Tensão'!$I:$I,_xlfn.XLOOKUP(_xlfn.NUMBERVALUE(Tabela3[[#This Row],[Ativo]]),'[2]Ajustes RL Poste'!$A:$A,'[2]Ajustes RL Poste'!$M:$M)) -> 13.800 | H56: 27/05/2026 | I56: =TEXT(Tabela3[[#This Row],[Data]],"mmmm") -> maio | J56: =YEAR(Tabela3[[#This Row],[Data]]) -> 2026 | K56: =_xlfn.CONCAT(Tabela3[[#This Row],[Ano]],Tabela3[[#This Row],[Mês]]) -> 2026maio | L56: controle | M56: sim | N56: DEFEITO ELETRÔNICO (CONTROLE/PLACA/RELÉ) | O56: «Foi identificado relé da fase C com defeito conforme orientação da supervisão e necessário realiza retrofit para instalação de controle rua.» | P56: DMSL identifica relé da fase C com defeito (display apagado, equipamento bypassado, 'FICOU EM OPERAÇÃO: Não'); saída foi retrofit para controle rua. Por que o relé falhou não é dito.
A57: RT 2026 | B57: =LEFT(Tabela3[[#This Row],[Ano/TIPO]],2) -> RT | D57: =_xlfn.XLOOKUP(K57,Base!G:G,Base!I:I) -> #N/A | E57: 5848305116 | F57: ETO-TELE 00935/2026 | G57: =_xlfn.XLOOKUP(_xlfn.NUMBERVALUE(Tabela3[[#This Row],[Ativo]]),'[2]Ajustes Reguladores de Tensão'!$A:$A,'[2]Ajustes Reguladores de Tensão'!$I:$I,_xlfn.XLOOKUP(_xlfn.NUMBERVALUE(Tabela3[[#This Row],[Ativo]]),'[2]Ajustes RL Poste'!$A:$A,'[2]Ajustes RL Poste'!$M:$M)) -> 34.500 | H57: 17/06/2026 | I57: =TEXT(Tabela3[[#This Row],[Data]],"mmmm") -> junho | J57: =YEAR(Tabela3[[#This Row],[Data]]) -> 2026 | K57: =_xlfn.CONCAT(Tabela3[[#This Row],[Ano]],Tabela3[[#This Row],[Mês]]) -> 2026junho | L57: controle | M57: sim | N57: DEFEITO ELETRÔNICO (CONTROLE/PLACA/RELÉ) | O57: «Na função Auto zero Regulador 2 foi para o TAP 16, em automático demostra comutação indevida e em Falha na Cédula RT2» | P57: Comutação indevida em automático é o controle comandando errado; a correção registrada foi a troca do relé, que normalizou o banco — defeito no relé, sem causa mais profunda no texto.
A58: RT 2026 | B58: =LEFT(Tabela3[[#This Row],[Ano/TIPO]],2) -> RT | D58: =_xlfn.XLOOKUP(K58,Base!G:G,Base!I:I) -> #N/A | E58: 5800090147 | F58: ETO-COEP 00117/2026 | G58: =_xlfn.XLOOKUP(_xlfn.NUMBERVALUE(Tabela3[[#This Row],[Ativo]]),'[2]Ajustes Reguladores de Tensão'!$A:$A,'[2]Ajustes Reguladores de Tensão'!$I:$I,_xlfn.XLOOKUP(_xlfn.NUMBERVALUE(Tabela3[[#This Row],[Ativo]]),'[2]Ajustes RL Poste'!$A:$A,'[2]Ajustes RL Poste'!$M:$M)) -> 34.500 | H58: 02/04/2026 | I58: =TEXT(Tabela3[[#This Row],[Data]],"mmmm") -> abril | J58: =YEAR(Tabela3[[#This Row],[Data]]) -> 2026 | K58: =_xlfn.CONCAT(Tabela3[[#This Row],[Ano]],Tabela3[[#This Row],[Mês]]) -> 2026abril | L58: celula | M58: não | N58: DEFEITO NO MICROSWITCH (SENSOR DE NEUTRO) | O58: «Favor, substituir a célula da fase C do RT 5800090147 pois o microswitch que renconhece o neutro do regulador está com defeito.» | P58: Parecer DMSL (o mais recente) traz o nexo causal com 'pois': a célula sai porque o microswitch que reconhece o neutro falhou; o porquê da falha do microswitch não é dito.
A59: RT 2026 | B59: =LEFT(Tabela3[[#This Row],[Ano/TIPO]],2) -> RT | D59: =_xlfn.XLOOKUP(K59,Base!G:G,Base!I:I) -> #N/A | E59: 5836786094 | F59: ETO-COEP 00095/2026 | G59: =_xlfn.XLOOKUP(_xlfn.NUMBERVALUE(Tabela3[[#This Row],[Ativo]]),'[2]Ajustes Reguladores de Tensão'!$A:$A,'[2]Ajustes Reguladores de Tensão'!$I:$I,_xlfn.XLOOKUP(_xlfn.NUMBERVALUE(Tabela3[[#This Row],[Ativo]]),'[2]Ajustes RL Poste'!$A:$A,'[2]Ajustes RL Poste'!$M:$M)) -> 34.500 | H59: 16/04/2026 | I59: =TEXT(Tabela3[[#This Row],[Data]],"mmmm") -> abril | J59: =YEAR(Tabela3[[#This Row],[Data]]) -> 2026 | K59: =_xlfn.CONCAT(Tabela3[[#This Row],[Ano]],Tabela3[[#This Row],[Mês]]) -> 2026abril | L59: furto | M59: não | N59: FURTO | O59: «Favor levar outro regulador de tensão, pois o mesmo foi furtado em campo.» | P59: Texto inequívoco: o regulador foi furtado em campo; o parecer COEP posterior só trata da logística do substituto.
A60: RT 2026 | B60: =LEFT(Tabela3[[#This Row],[Ano/TIPO]],2) -> RT | D60: =_xlfn.XLOOKUP(K60,Base!G:G,Base!I:I) -> #N/A | E60: 5856070091 | F60: ETO-COEP 00023/2026 | G60: =_xlfn.XLOOKUP(_xlfn.NUMBERVALUE(Tabela3[[#This Row],[Ativo]]),'[2]Ajustes Reguladores de Tensão'!$A:$A,'[2]Ajustes Reguladores de Tensão'!$I:$I,_xlfn.XLOOKUP(_xlfn.NUMBERVALUE(Tabela3[[#This Row],[Ativo]]),'[2]Ajustes RL Poste'!$A:$A,'[2]Ajustes RL Poste'!$M:$M)) -> 34.500 | H60: 26/01/2026 | I60: =TEXT(Tabela3[[#This Row],[Data]],"mmmm") -> janeiro | J60: =YEAR(Tabela3[[#This Row],[Data]]) -> 2026 | K60: =_xlfn.CONCAT(Tabela3[[#This Row],[Ano]],Tabela3[[#This Row],[Mês]]) -> 2026janeiro | L60: furto | M60: não | N60: FURTO | O60: «Regulador 5856070091 furtado as 3 fases» | P60: Furto das três fases do banco, dito com todas as letras; acesso livre na LD Almas-Natividade explica a exposição.
A61: RT 2026 | B61: =LEFT(Tabela3[[#This Row],[Ano/TIPO]],2) -> RT | D61: =_xlfn.XLOOKUP(K61,Base!G:G,Base!I:I) -> #N/A | E61: 5800366016 | F61: ETO-RD-AR 00275/2026 | G61: =_xlfn.XLOOKUP(_xlfn.NUMBERVALUE(Tabela3[[#This Row],[Ativo]]),'[2]Ajustes Reguladores de Tensão'!$A:$A,'[2]Ajustes Reguladores de Tensão'!$I:$I,_xlfn.XLOOKUP(_xlfn.NUMBERVALUE(Tabela3[[#This Row],[Ativo]]),'[2]Ajustes RL Poste'!$A:$A,'[2]Ajustes RL Poste'!$M:$M)) -> 34.500 | H61: 09/02/2026 | I61: =TEXT(Tabela3[[#This Row],[Data]],"mmmm") -> fevereiro | J61: =YEAR(Tabela3[[#This Row],[Data]]) -> 2026 | K61: =_xlfn.CONCAT(Tabela3[[#This Row],[Ano]],Tabela3[[#This Row],[Mês]]) -> 2026fevereiro | L61: celula | M61: sim | N61: SEM CAUSA DESCRITA NO TEXTO | O61: «CELULAR QUEIMADA REGULADOR DE TENSÃO.SUBSTITUIR CELULA REGULADOR DE TENSÃO 5800366016 FASE A.» | P61: Texto dá só o modo — célula queimada — sem uma linha sobre o porquê; engenheiro não chuta laudo.
A62: RT 2026 | B62: =LEFT(Tabela3[[#This Row],[Ano/TIPO]],2) -> RT | D62: =_xlfn.XLOOKUP(K62,Base!G:G,Base!I:I) -> #N/A | E62: 5800440256 | F62: ETO-TELE 01034/2026 | G62: =_xlfn.XLOOKUP(_xlfn.NUMBERVALUE(Tabela3[[#This Row],[Ativo]]),'[2]Ajustes Reguladores de Tensão'!$A:$A,'[2]Ajustes Reguladores de Tensão'!$I:$I,_xlfn.XLOOKUP(_xlfn.NUMBERVALUE(Tabela3[[#This Row],[Ativo]]),'[2]Ajustes RL Poste'!$A:$A,'[2]Ajustes RL Poste'!$M:$M)) -> 34.500 | H62: 06/08/2026 | I62: =TEXT(Tabela3[[#This Row],[Data]],"mmmm") -> agosto | J62: =YEAR(Tabela3[[#This Row],[Data]]) -> 2026 | K62: =_xlfn.CONCAT(Tabela3[[#This Row],[Ano]],Tabela3[[#This Row],[Mês]]) -> 2026agosto | L62: celula | M62: não | N62: SEM CAUSA DESCRITA NO TEXTO | O62: «Substituir célula da Fase B do banco de Regulador de tensão e realizar melhorias na malha de aterramento do Regulador» | P62: Texto dá o modo — célula da fase B defeituosa, tensão oscilando de 16 a 23 kV com reclamação do cliente BRK — e duas prescrições lado a lado no parecer DMSL (trocar a célula E melhorar a malha de aterramento), sem uma linha dizendo que a malha causou a falha da célula. A malha fica registrada como indício na prescrição, não como laudo.
A63: RT 2026 | B63: =LEFT(Tabela3[[#This Row],[Ano/TIPO]],2) -> RT | D63: =_xlfn.XLOOKUP(K63,Base!G:G,Base!I:I) -> #N/A | E63: 5801866013 | F63: ETO-RD-PS 00303/2026 | G63: =_xlfn.XLOOKUP(_xlfn.NUMBERVALUE(Tabela3[[#This Row],[Ativo]]),'[2]Ajustes Reguladores de Tensão'!$A:$A,'[2]Ajustes Reguladores de Tensão'!$I:$I,_xlfn.XLOOKUP(_xlfn.NUMBERVALUE(Tabela3[[#This Row],[Ativo]]),'[2]Ajustes RL Poste'!$A:$A,'[2]Ajustes RL Poste'!$M:$M)) -> 13.800 | H63: 02/03/2026 | I63: =TEXT(Tabela3[[#This Row],[Data]],"mmmm") -> março | J63: =YEAR(Tabela3[[#This Row],[Data]]) -> 2026 | K63: =_xlfn.CONCAT(Tabela3[[#This Row],[Ano]],Tabela3[[#This Row],[Mês]]) -> 2026março | L63: celula | M63: sim | N63: UMIDADE / INFILTRAÇÃO | O63: «Identificado infiltração na caixa de passagem da célula da fase C do banco regulador de tensão, será necessário fazer a substituição da mesma!» | P63: DMSL identificou infiltração na caixa de passagem da célula da fase C — água entrando é a causa direta do defeito que bypassou o banco.
A64: RL 2026 | B64: =LEFT(Tabela3[[#This Row],[Ano/TIPO]],2) -> RL | D64: =_xlfn.XLOOKUP(K64,Base!G:G,Base!I:I) -> #N/A | E64: 7908249152 | F64: ETO-COEP 00038/2026 | G64: =_xlfn.XLOOKUP(_xlfn.NUMBERVALUE(Tabela3[[#This Row],[Ativo]]),'[2]Ajustes Reguladores de Tensão'!$A:$A,'[2]Ajustes Reguladores de Tensão'!$I:$I,_xlfn.XLOOKUP(_xlfn.NUMBERVALUE(Tabela3[[#This Row],[Ativo]]),'[2]Ajustes RL Poste'!$A:$A,'[2]Ajustes RL Poste'!$M:$M)) -> 34.500 | H64: 22/01/2026 | I64: =TEXT(Tabela3[[#This Row],[Data]],"mmmm") -> janeiro | J64: =YEAR(Tabela3[[#This Row],[Data]]) -> 2026 | K64: =_xlfn.CONCAT(Tabela3[[#This Row],[Ano]],Tabela3[[#This Row],[Mês]]) -> 2026janeiro | L64: completo | M64: não | N64: CURTO-CIRCUITO INTERNO | O64: «Houve um curto no equipamento danificando a parte ativa, será necessário fazer a substituição do equipamento completo ( parte ativa e controle)» | P64: DMSL é explícito: um curto no equipamento danificou a parte ativa e exigiu a troca completa. | Q64: Causa mantida (CURTO-CIRCUITO INTERNO), confiança rebaixada de alta para media: 'houve um curto no equipamento danificando a parte ativa' declara o curto mas não o localiza (equipamento inteiro, sem dizer onde nasceu) — sustenta a categoria com confiança média, não alta. Compare com 'tanque em curto' (SS 00058, 00039), onde a localização interna é explícita e a alta se sustenta.
A65: RL 2026 | B65: =LEFT(Tabela3[[#This Row],[Ano/TIPO]],2) -> RL | D65: =_xlfn.XLOOKUP(K65,Base!G:G,Base!I:I) -> #N/A | E65: 7925733015 | F65: ETO-COEP 00058/2026 | G65: =_xlfn.XLOOKUP(_xlfn.NUMBERVALUE(Tabela3[[#This Row],[Ativo]]),'[2]Ajustes Reguladores de Tensão'!$A:$A,'[2]Ajustes Reguladores de Tensão'!$I:$I,_xlfn.XLOOKUP(_xlfn.NUMBERVALUE(Tabela3[[#This Row],[Ativo]]),'[2]Ajustes RL Poste'!$A:$A,'[2]Ajustes RL Poste'!$M:$M)) -> 34.500 | H65: 13/03/2026 | I65: =TEXT(Tabela3[[#This Row],[Data]],"mmmm") -> março | J65: =YEAR(Tabela3[[#This Row],[Data]]) -> 2026 | K65: =_xlfn.CONCAT(Tabela3[[#This Row],[Ano]],Tabela3[[#This Row],[Mês]]) -> 2026março | L65: tanque | M65: não | N65: CURTO-CIRCUITO INTERNO | O65: «DESCRIÇÃO: Tanque do equipamento em Curto» | P65: Formulário DMSL explícito (tanque em curto), coerente com o 'provavel curto-circuito interno' apontado no primeiro ataque.
A66: RL 2026 | B66: =LEFT(Tabela3[[#This Row],[Ano/TIPO]],2) -> RL | D66: =_xlfn.XLOOKUP(K66,Base!G:G,Base!I:I) -> #N/A | E66: 7926089013 | F66: ETO-COEP 00039/2026 | G66: =_xlfn.XLOOKUP(_xlfn.NUMBERVALUE(Tabela3[[#This Row],[Ativo]]),'[2]Ajustes Reguladores de Tensão'!$A:$A,'[2]Ajustes Reguladores de Tensão'!$I:$I,_xlfn.XLOOKUP(_xlfn.NUMBERVALUE(Tabela3[[#This Row],[Ativo]]),'[2]Ajustes RL Poste'!$A:$A,'[2]Ajustes RL Poste'!$M:$M)) -> 34.500 | H66: 24/02/2026 | I66: =TEXT(Tabela3[[#This Row],[Data]],"mmmm") -> fevereiro | J66: =YEAR(Tabela3[[#This Row],[Data]]) -> 2026 | K66: =_xlfn.CONCAT(Tabela3[[#This Row],[Ano]],Tabela3[[#This Row],[Mês]]) -> 2026fevereiro | L66: tanque | M66: não | N66: CURTO-CIRCUITO INTERNO | O66: «foi identificado que o tanque do equipamento entrou em curto o mesmo necessário substituir o tanque» | P66: Análise técnica explícita: o tanque entrou em curto; a origem do curto não é detalhada, mas a causa nomeada no texto é o curto interno.
A67: RL 2026 | B67: =LEFT(Tabela3[[#This Row],[Ano/TIPO]],2) -> RL | D67: =_xlfn.XLOOKUP(K67,Base!G:G,Base!I:I) -> #N/A | E67: 7957021094 | F67: ETO-TELE 00861/2026 | G67: =_xlfn.XLOOKUP(_xlfn.NUMBERVALUE(Tabela3[[#This Row],[Ativo]]),'[2]Ajustes Reguladores de Tensão'!$A:$A,'[2]Ajustes Reguladores de Tensão'!$I:$I,_xlfn.XLOOKUP(_xlfn.NUMBERVALUE(Tabela3[[#This Row],[Ativo]]),'[2]Ajustes RL Poste'!$A:$A,'[2]Ajustes RL Poste'!$M:$M)) -> 34.500 | H67: 10/07/2026 | I67: =TEXT(Tabela3[[#This Row],[Data]],"mmmm") -> julho | J67: =YEAR(Tabela3[[#This Row],[Data]]) -> 2026 | K67: =_xlfn.CONCAT(Tabela3[[#This Row],[Ano]],Tabela3[[#This Row],[Mês]]) -> 2026julho | L67: controle | M67: sim | N67: CURTO-CIRCUITO INTERNO | O67: «SEGUE SS DE RELIGADOR COM CURTO INTERNO, DJUNTOR DE BT NÃO ACEITA.» | P67: Texto explícito em 'curto interno' no circuito de BT (disjuntor não aceitava); a OS resolveu trocando fonte, bateria e relé, então a extensão exata do curto é inferida.
A68: RL 2026 | B68: =LEFT(Tabela3[[#This Row],[Ano/TIPO]],2) -> RL | D68: =_xlfn.XLOOKUP(K68,Base!G:G,Base!I:I) -> #N/A | E68: 7929376022 | F68: ETO-COEP 00068/2026 | G68: =_xlfn.XLOOKUP(_xlfn.NUMBERVALUE(Tabela3[[#This Row],[Ativo]]),'[2]Ajustes Reguladores de Tensão'!$A:$A,'[2]Ajustes Reguladores de Tensão'!$I:$I,_xlfn.XLOOKUP(_xlfn.NUMBERVALUE(Tabela3[[#This Row],[Ativo]]),'[2]Ajustes RL Poste'!$A:$A,'[2]Ajustes RL Poste'!$M:$M)) -> 34.500 | H68: 25/03/2026 | I68: =TEXT(Tabela3[[#This Row],[Data]],"mmmm") -> março | J68: =YEAR(Tabela3[[#This Row],[Data]]) -> 2026 | K68: =_xlfn.CONCAT(Tabela3[[#This Row],[Ano]],Tabela3[[#This Row],[Mês]]) -> 2026março | L68: controle | M68: não | N68: DEFEITO ELETRÔNICO (CONTROLE/PLACA/RELÉ) | O68: «PRIMEIRO ATAQUE IDENTIFICOU QUE RELE ESTA EM CURTO» | P68: Relé em curto (reincidente após a nota 224/2026) levou o DMSL a mandar trocar o controle completo; o porquê do curto no relé não é informado.
A69: RL 2026 | B69: =LEFT(Tabela3[[#This Row],[Ano/TIPO]],2) -> RL | D69: =_xlfn.XLOOKUP(K69,Base!G:G,Base!I:I) -> #N/A | E69: 7930359149 | F69: ETO-COEP 00138/2026 | G69: =_xlfn.XLOOKUP(_xlfn.NUMBERVALUE(Tabela3[[#This Row],[Ativo]]),'[2]Ajustes Reguladores de Tensão'!$A:$A,'[2]Ajustes Reguladores de Tensão'!$I:$I,_xlfn.XLOOKUP(_xlfn.NUMBERVALUE(Tabela3[[#This Row],[Ativo]]),'[2]Ajustes RL Poste'!$A:$A,'[2]Ajustes RL Poste'!$M:$M)) -> #N/A | H69: 07/07/2026 | I69: =TEXT(Tabela3[[#This Row],[Data]],"mmmm") -> julho | J69: =YEAR(Tabela3[[#This Row],[Data]]) -> 2026 | K69: =_xlfn.CONCAT(Tabela3[[#This Row],[Ano]],Tabela3[[#This Row],[Mês]]) -> 2026julho | L69: completo | M69: não | N69: DEFEITO ELETRÔNICO (CONTROLE/PLACA/RELÉ) | O69: «PLACA DO RL ESTA CARBONIZADA COM SINAL DE CURTO.» | P69: O único mecanismo declarado no texto está na placa: 'PLACA DO RL ESTA CARBONIZADA COM SINAL DE CURTO' (camada do primeiro ataque, não contradita pelo parecer DMSL de 07/07). A parte ativa aparece só como 'com defeito', sem porquê. | Q69: Reclassificado de CURTO-CIRCUITO INTERNO para DEFEITO ELETRÔNICO (CONTROLE/PLACA/RELÉ). O curto do texto está localizado na placa — mesmo padrão de 'curto na placa'/'relé em curto' que o próprio classificador pôs em DEFEITO ELETRÔNICO (SS 00064, 00063, 00068). Ler um evento único de curto interno atingindo comando e parte ativa era inferência: o texto não diz que a parte ativa falhou por curto. Citação mantida; confiança media mantida.
A70: RL 2026 | B70: =LEFT(Tabela3[[#This Row],[Ano/TIPO]],2) -> RL | D70: =_xlfn.XLOOKUP(K70,Base!G:G,Base!I:I) -> #N/A | E70: 7944559149 | F70: ETO-COEP 00063/2026 | G70: =_xlfn.XLOOKUP(_xlfn.NUMBERVALUE(Tabela3[[#This Row],[Ativo]]),'[2]Ajustes Reguladores de Tensão'!$A:$A,'[2]Ajustes Reguladores de Tensão'!$I:$I,_xlfn.XLOOKUP(_xlfn.NUMBERVALUE(Tabela3[[#This Row],[Ativo]]),'[2]Ajustes RL Poste'!$A:$A,'[2]Ajustes RL Poste'!$M:$M)) -> 34.500 | H70: 17/03/2026 | I70: =TEXT(Tabela3[[#This Row],[Data]],"mmmm") -> março | J70: =YEAR(Tabela3[[#This Row],[Data]]) -> 2026 | K70: =_xlfn.CONCAT(Tabela3[[#This Row],[Ano]],Tabela3[[#This Row],[Mês]]) -> 2026março | L70: controle | M70: não | N70: DEFEITO ELETRÔNICO (CONTROLE/PLACA/RELÉ) | O70: «Serviço Executado: curto na placa foi tentando recuperar a mesma porém não teve sucesso!» | P70: Curto na placa de alimentação, irrecuperável, é falha eletrônica explícita; o porquê do curto na placa não é informado.
A71: RL 2026 | B71: =LEFT(Tabela3[[#This Row],[Ano/TIPO]],2) -> RL | D71: =_xlfn.XLOOKUP(K71,Base!G:G,Base!I:I) -> #N/A | E71: 7955946007 | F71: ETO-COEP 00064/2026 | G71: =_xlfn.XLOOKUP(_xlfn.NUMBERVALUE(Tabela3[[#This Row],[Ativo]]),'[2]Ajustes Reguladores de Tensão'!$A:$A,'[2]Ajustes Reguladores de Tensão'!$I:$I,_xlfn.XLOOKUP(_xlfn.NUMBERVALUE(Tabela3[[#This Row],[Ativo]]),'[2]Ajustes RL Poste'!$A:$A,'[2]Ajustes RL Poste'!$M:$M)) -> 34.500 | H71: 02/03/2026 | I71: =TEXT(Tabela3[[#This Row],[Data]],"mmmm") -> março | J71: =YEAR(Tabela3[[#This Row],[Data]]) -> 2026 | K71: =_xlfn.CONCAT(Tabela3[[#This Row],[Ano]],Tabela3[[#This Row],[Mês]]) -> 2026março | L71: controle | M71: não | N71: DEFEITO ELETRÔNICO (CONTROLE/PLACA/RELÉ) | O71: «Necessário substituir a placa de alimentação ca, a mesma está em curto não conseguimos recuperar.» | P71: Placa de alimentação CA em curto e irrecuperável é falha eletrônica explícita do controle; o porquê do curto na placa não é dito.
A72: RL 2026 | B72: =LEFT(Tabela3[[#This Row],[Ano/TIPO]],2) -> RL | D72: =_xlfn.XLOOKUP(K72,Base!G:G,Base!I:I) -> #N/A | E72: 7903569004 | F72: ETO-COEP 00060/2026 | G72: =_xlfn.XLOOKUP(_xlfn.NUMBERVALUE(Tabela3[[#This Row],[Ativo]]),'[2]Ajustes Reguladores de Tensão'!$A:$A,'[2]Ajustes Reguladores de Tensão'!$I:$I,_xlfn.XLOOKUP(_xlfn.NUMBERVALUE(Tabela3[[#This Row],[Ativo]]),'[2]Ajustes RL Poste'!$A:$A,'[2]Ajustes RL Poste'!$M:$M)) -> 13.800 | H72: 11/03/2026 | I72: =TEXT(Tabela3[[#This Row],[Data]],"mmmm") -> março | J72: =YEAR(Tabela3[[#This Row],[Data]]) -> 2026 | K72: =_xlfn.CONCAT(Tabela3[[#This Row],[Ano]],Tabela3[[#This Row],[Mês]]) -> 2026março | L72: completo | M72: não | N72: SEM CAUSA DESCRITA NO TEXTO | O72: «Realizar substituição do equipamento todo e parte ativa.» | P72: Só o sintoma (sem comunicação após primeiro ataque) e a ordem de trocar tudo; nenhum laudo do porquê.
A73: RL 2026 | B73: =LEFT(Tabela3[[#This Row],[Ano/TIPO]],2) -> RL | D73: =_xlfn.XLOOKUP(K73,Base!G:G,Base!I:I) -> #N/A | E73: 7908302256 | F73: ETO-COEP 00071/2026 | G73: =_xlfn.XLOOKUP(_xlfn.NUMBERVALUE(Tabela3[[#This Row],[Ativo]]),'[2]Ajustes Reguladores de Tensão'!$A:$A,'[2]Ajustes Reguladores de Tensão'!$I:$I,_xlfn.XLOOKUP(_xlfn.NUMBERVALUE(Tabela3[[#This Row],[Ativo]]),'[2]Ajustes RL Poste'!$A:$A,'[2]Ajustes RL Poste'!$M:$M)) -> 34.500 | H73: 06/04/2026 | I73: =TEXT(Tabela3[[#This Row],[Data]],"mmmm") -> abril | J73: =YEAR(Tabela3[[#This Row],[Data]]) -> 2026 | K73: =_xlfn.CONCAT(Tabela3[[#This Row],[Ano]],Tabela3[[#This Row],[Mês]]) -> 2026abril | L73: tanque | M73: não | N73: SEM CAUSA DESCRITA NO TEXTO | O73: «Serviço Executado: Equipamento com a parte ativa com defeito, será necessário fazer a substituição da mesma!» | P73: Parte ativa com defeito é modo; nada no texto (dominado por dados de configuração de satélite) explica a origem.
A74: RL 2026 | B74: =LEFT(Tabela3[[#This Row],[Ano/TIPO]],2) -> RL | D74: =_xlfn.XLOOKUP(K74,Base!G:G,Base!I:I) -> #N/A | E74: 7908708116 | F74: ETO-COEP 00020/2026 | G74: =_xlfn.XLOOKUP(_xlfn.NUMBERVALUE(Tabela3[[#This Row],[Ativo]]),'[2]Ajustes Reguladores de Tensão'!$A:$A,'[2]Ajustes Reguladores de Tensão'!$I:$I,_xlfn.XLOOKUP(_xlfn.NUMBERVALUE(Tabela3[[#This Row],[Ativo]]),'[2]Ajustes RL Poste'!$A:$A,'[2]Ajustes RL Poste'!$M:$M)) -> 34.500 | H74: 22/01/2026 | I74: =TEXT(Tabela3[[#This Row],[Data]],"mmmm") -> janeiro | J74: =YEAR(Tabela3[[#This Row],[Data]]) -> 2026 | K74: =_xlfn.CONCAT(Tabela3[[#This Row],[Ano]],Tabela3[[#This Row],[Mês]]) -> 2026janeiro | L74: tanque | M74: sim | N74: SEM CAUSA DESCRITA NO TEXTO | O74: «Substituição de tanque e controle, os mesmos estão com defeitos.» | P74: Texto dá só o modo (tanque com defeito) e o parecer COEP mais recente ainda pede explicação do defeito; nenhum porquê registrado.
A75: RL 2026 | B75: =LEFT(Tabela3[[#This Row],[Ano/TIPO]],2) -> RL | D75: =_xlfn.XLOOKUP(K75,Base!G:G,Base!I:I) -> #N/A | E75: 7908708116 | F75: ETO-COEP 00020/2026 | G75: =_xlfn.XLOOKUP(_xlfn.NUMBERVALUE(Tabela3[[#This Row],[Ativo]]),'[2]Ajustes Reguladores de Tensão'!$A:$A,'[2]Ajustes Reguladores de Tensão'!$I:$I,_xlfn.XLOOKUP(_xlfn.NUMBERVALUE(Tabela3[[#This Row],[Ativo]]),'[2]Ajustes RL Poste'!$A:$A,'[2]Ajustes RL Poste'!$M:$M)) -> 34.500 | H75: 22/01/2026 | I75: =TEXT(Tabela3[[#This Row],[Data]],"mmmm") -> janeiro | J75: =YEAR(Tabela3[[#This Row],[Data]]) -> 2026 | K75: =_xlfn.CONCAT(Tabela3[[#This Row],[Ano]],Tabela3[[#This Row],[Mês]]) -> 2026janeiro | L75: controle | M75: não | N75: SEM CAUSA DESCRITA NO TEXTO | O75: «Substituição de tanque e controle, os mesmos estão com defeitos.» | P75: Mesma SS do tanque: 'controle com defeito' é modo de falha, não causa; nada no texto explica a origem.
A76: RL 2026 | B76: =LEFT(Tabela3[[#This Row],[Ano/TIPO]],2) -> RL | D76: =_xlfn.XLOOKUP(K76,Base!G:G,Base!I:I) -> #N/A | E76: 7913662076 | F76: ETO-COEP 00114/2026 | G76: =_xlfn.XLOOKUP(_xlfn.NUMBERVALUE(Tabela3[[#This Row],[Ativo]]),'[2]Ajustes Reguladores de Tensão'!$A:$A,'[2]Ajustes Reguladores de Tensão'!$I:$I,_xlfn.XLOOKUP(_xlfn.NUMBERVALUE(Tabela3[[#This Row],[Ativo]]),'[2]Ajustes RL Poste'!$A:$A,'[2]Ajustes RL Poste'!$M:$M)) -> 13.800 | H76: 08/06/2026 | I76: =TEXT(Tabela3[[#This Row],[Data]],"mmmm") -> junho | J76: =YEAR(Tabela3[[#This Row],[Data]]) -> 2026 | K76: =_xlfn.CONCAT(Tabela3[[#This Row],[Ano]],Tabela3[[#This Row],[Mês]]) -> 2026junho | L76: tanque | M76: não | N76: SEM CAUSA DESCRITA NO TEXTO | O76: «Foi confirmado pela equipe DMSL o defeito do tanque, favor seguir com a substituição e correção da chave de entrada fase B danificada.» | P76: Defeito do tanque confirmado sem explicação da origem; a chave de entrada danificada é peça fora da taxa.
A77: RL 2026 | B77: =LEFT(Tabela3[[#This Row],[Ano/TIPO]],2) -> RL | D77: =_xlfn.XLOOKUP(K77,Base!G:G,Base!I:I) -> #N/A | E77: 7919270014 | F77: ETO-COEP 00074/2026 | G77: =_xlfn.XLOOKUP(_xlfn.NUMBERVALUE(Tabela3[[#This Row],[Ativo]]),'[2]Ajustes Reguladores de Tensão'!$A:$A,'[2]Ajustes Reguladores de Tensão'!$I:$I,_xlfn.XLOOKUP(_xlfn.NUMBERVALUE(Tabela3[[#This Row],[Ativo]]),'[2]Ajustes RL Poste'!$A:$A,'[2]Ajustes RL Poste'!$M:$M)) -> 34.500 | H77: 25/02/2026 | I77: =TEXT(Tabela3[[#This Row],[Data]],"mmmm") -> fevereiro | J77: =YEAR(Tabela3[[#This Row],[Data]]) -> 2026 | K77: =_xlfn.CONCAT(Tabela3[[#This Row],[Ano]],Tabela3[[#This Row],[Mês]]) -> 2026fevereiro | L77: completo | M77: não | N77: SEM CAUSA DESCRITA NO TEXTO | O77: «Substituir Equipamento completo problema na placa de alimentação e na parte ativa» | P77: Dois modos de falha (placa de alimentação e parte ativa) sem nenhum porquê declarado para nenhum deles.
A78: RL 2026 | B78: =LEFT(Tabela3[[#This Row],[Ano/TIPO]],2) -> RL | D78: =_xlfn.XLOOKUP(K78,Base!G:G,Base!I:I) -> #N/A | E78: 7921202014 | F78: ETO-COEP 00088/2026 | G78: =_xlfn.XLOOKUP(_xlfn.NUMBERVALUE(Tabela3[[#This Row],[Ativo]]),'[2]Ajustes Reguladores de Tensão'!$A:$A,'[2]Ajustes Reguladores de Tensão'!$I:$I,_xlfn.XLOOKUP(_xlfn.NUMBERVALUE(Tabela3[[#This Row],[Ativo]]),'[2]Ajustes RL Poste'!$A:$A,'[2]Ajustes RL Poste'!$M:$M)) -> 34.500 | H78: 15/02/2026 | I78: =TEXT(Tabela3[[#This Row],[Data]],"mmmm") -> fevereiro | J78: =YEAR(Tabela3[[#This Row],[Data]]) -> 2026 | K78: =_xlfn.CONCAT(Tabela3[[#This Row],[Ano]],Tabela3[[#This Row],[Mês]]) -> 2026fevereiro | L78: tanque | M78: não | N78: SEM CAUSA DESCRITA NO TEXTO | O78: «indentificado o problema na parte ativa será necessário fazer a substituição da mesmo» | P78: Problema na parte ativa sem porquê; a menção a substituir o pára-raios da fase C é indício fraco demais para atribuir descarga atmosférica.
A79: RL 2026 | B79: =LEFT(Tabela3[[#This Row],[Ano/TIPO]],2) -> RL | D79: =_xlfn.XLOOKUP(K79,Base!G:G,Base!I:I) -> #N/A | E79: 7923673004 | F79: ETO-COEP 00057/2026 | G79: =_xlfn.XLOOKUP(_xlfn.NUMBERVALUE(Tabela3[[#This Row],[Ativo]]),'[2]Ajustes Reguladores de Tensão'!$A:$A,'[2]Ajustes Reguladores de Tensão'!$I:$I,_xlfn.XLOOKUP(_xlfn.NUMBERVALUE(Tabela3[[#This Row],[Ativo]]),'[2]Ajustes RL Poste'!$A:$A,'[2]Ajustes RL Poste'!$M:$M)) -> 13.800 | H79: 26/03/2026 | I79: =TEXT(Tabela3[[#This Row],[Data]],"mmmm") -> março | J79: =YEAR(Tabela3[[#This Row],[Data]]) -> 2026 | K79: =_xlfn.CONCAT(Tabela3[[#This Row],[Ano]],Tabela3[[#This Row],[Mês]]) -> 2026março | L79: controle | M79: não | N79: SEM CAUSA DESCRITA NO TEXTO | O79: «RELIGADOR COM RELÉ DANIFICADO, REALIZAR SUBSTITUIÇÃO» | P79: Relé danificado é o modo de falha; o texto não diz por que danificou.
A80: RL 2026 | B80: =LEFT(Tabela3[[#This Row],[Ano/TIPO]],2) -> RL | D80: =_xlfn.XLOOKUP(K80,Base!G:G,Base!I:I) -> #N/A | E80: 7925871077 | F80: ETO-COEP 00048/2026 | G80: =_xlfn.XLOOKUP(_xlfn.NUMBERVALUE(Tabela3[[#This Row],[Ativo]]),'[2]Ajustes Reguladores de Tensão'!$A:$A,'[2]Ajustes Reguladores de Tensão'!$I:$I,_xlfn.XLOOKUP(_xlfn.NUMBERVALUE(Tabela3[[#This Row],[Ativo]]),'[2]Ajustes RL Poste'!$A:$A,'[2]Ajustes RL Poste'!$M:$M)) -> 34.500 | H80: 16/03/2026 | I80: =TEXT(Tabela3[[#This Row],[Data]],"mmmm") -> março | J80: =YEAR(Tabela3[[#This Row],[Data]]) -> 2026 | K80: =_xlfn.CONCAT(Tabela3[[#This Row],[Ano]],Tabela3[[#This Row],[Mês]]) -> 2026março | L80: tanque | M80: não | N80: SEM CAUSA DESCRITA NO TEXTO | O80: «PENDENCIA: Religador continua by passado, equipamento está com defeito na parte ativa» | P80: SS recriada por baixa indevida da antiga repete só o modo (defeito na parte ativa), sem causa.
A81: RL 2026 | B81: =LEFT(Tabela3[[#This Row],[Ano/TIPO]],2) -> RL | D81: =_xlfn.XLOOKUP(K81,Base!G:G,Base!I:I) -> #N/A | E81: 7926442035 | F81: ETO-TELE 00298/2026 | G81: =_xlfn.XLOOKUP(_xlfn.NUMBERVALUE(Tabela3[[#This Row],[Ativo]]),'[2]Ajustes Reguladores de Tensão'!$A:$A,'[2]Ajustes Reguladores de Tensão'!$I:$I,_xlfn.XLOOKUP(_xlfn.NUMBERVALUE(Tabela3[[#This Row],[Ativo]]),'[2]Ajustes RL Poste'!$A:$A,'[2]Ajustes RL Poste'!$M:$M)) -> 34.500 | H81: 18/02/2026 | I81: =TEXT(Tabela3[[#This Row],[Data]],"mmmm") -> fevereiro | J81: =YEAR(Tabela3[[#This Row],[Data]]) -> 2026 | K81: =_xlfn.CONCAT(Tabela3[[#This Row],[Ano]],Tabela3[[#This Row],[Mês]]) -> 2026fevereiro | L81: tanque | M81: não | N81: SEM CAUSA DESCRITA NO TEXTO | O81: «Parte ativa do equipamento danificada: necessita substituição» | P81: Parte ativa danificada sem porquê; o vazamento de óleo citado é do trafo (auxiliar, fora da taxa), não da parte ativa do religador.
... A83: RL 2026 | B83: =LEFT(Tabela3[[#This Row],[Ano/TIPO]],2) -> RL | D83: =_xlfn.XLOOKUP(K83,Base!G:G,Base!I:I) -> #N/A | E83: 7927396052 | F83: ETO-COEP 00045/2026 | G83: =_xlfn.XLOOKUP(_xlfn.NUMBERVALUE(Tabela3[[#This Row],[Ativo]]),'[2]Ajustes Reguladores de Tensão'!$A:$A,'[2]Ajustes Reguladores de Tensão'!$I:$I,_xlfn.XLOOKUP(_xlfn.NUMBERVALUE(Tabela3[[#This Row],[Ativo]]),'[2]Ajustes RL Poste'!$A:$A,'[2]Ajustes RL Poste'!$M:$M)) -> 34.500 | H83: 17/02/2026 | I83: =TEXT(Tabela3[[#This Row],[Data]],"mmmm") -> fevereiro | J83: =YEAR(Tabela3[[#This Row],[Data]]) -> 2026 | K83: =_xlfn.CONCAT(Tabela3[[#This Row],[Ano]],Tabela3[[#This Row],[Mês]]) -> 2026fevereiro | L83: tanque | M83: não | N83: SEM CAUSA DESCRITA NO TEXTO | O83: «equipe DMSL constatou que apenas o tanque do RLG 7927396052 encontra-se queimado. Favor, substituir parte ativa do equipamento.» | P83: Fumaça no painel e tanque queimado são modo; o texto não explica a origem da queima.
A84: RL 2026 | B84: =LEFT(Tabela3[[#This Row],[Ano/TIPO]],2) -> RL | D84: =_xlfn.XLOOKUP(K84,Base!G:G,Base!I:I) -> #N/A | E84: 7927413001 | F84: ETO-COEP 00141/2026 | G84: =_xlfn.XLOOKUP(_xlfn.NUMBERVALUE(Tabela3[[#This Row],[Ativo]]),'[2]Ajustes Reguladores de Tensão'!$A:$A,'[2]Ajustes Reguladores de Tensão'!$I:$I,_xlfn.XLOOKUP(_xlfn.NUMBERVALUE(Tabela3[[#This Row],[Ativo]]),'[2]Ajustes RL Poste'!$A:$A,'[2]Ajustes RL Poste'!$M:$M)) -> 34.500 | H84: 16/04/2026 | I84: =TEXT(Tabela3[[#This Row],[Data]],"mmmm") -> abril | J84: =YEAR(Tabela3[[#This Row],[Data]]) -> 2026 | K84: =_xlfn.CONCAT(Tabela3[[#This Row],[Ano]],Tabela3[[#This Row],[Mês]]) -> 2026abril | L84: completo | M84: não | N84: SEM CAUSA DESCRITA NO TEXTO | O84: «Placa de alimentação do equipamento com defeito, VERIFICAR SE É POSSIVEL substituir o equipamento completo.» | P84: 'Placa de alimentação com defeito' é modo de falha, não mecanismo: o texto não diz curto, queima nem origem. Mesmo nível de evidência de 'relé danificado' (SS 00057) e 'problema na placa de alimentação' (SS 00074), classificados SEM CAUSA. | Q84: Derrubado de DEFEITO ELETRÔNICO (CONTROLE/PLACA/RELÉ) para SEM CAUSA DESCRITA NO TEXTO. 'Com defeito' não declara mecanismo elétrico nenhum — pela régua ('célula queimada' não sustenta causa, é modo), 'placa com defeito' também não sustenta. Os itens mantidos em DEFEITO ELETRÔNICO têm curto explícito na placa/relé; este não tem. Citação real, mas insuficiente para a causa.
A85: RL 2026 | B85: =LEFT(Tabela3[[#This Row],[Ano/TIPO]],2) -> RL | D85: =_xlfn.XLOOKUP(K85,Base!G:G,Base!I:I) -> #N/A | E85: 7927646026 | F85: ETO-COEP 00029/2026 | G85: =_xlfn.XLOOKUP(_xlfn.NUMBERVALUE(Tabela3[[#This Row],[Ativo]]),'[2]Ajustes Reguladores de Tensão'!$A:$A,'[2]Ajustes Reguladores de Tensão'!$I:$I,_xlfn.XLOOKUP(_xlfn.NUMBERVALUE(Tabela3[[#This Row],[Ativo]]),'[2]Ajustes RL Poste'!$A:$A,'[2]Ajustes RL Poste'!$M:$M)) -> 34.500 | H85: 09/01/2026 | I85: =TEXT(Tabela3[[#This Row],[Data]],"mmmm") -> janeiro | J85: =YEAR(Tabela3[[#This Row],[Data]]) -> 2026 | K85: =_xlfn.CONCAT(Tabela3[[#This Row],[Ano]],Tabela3[[#This Row],[Mês]]) -> 2026janeiro | L85: tanque | M85: não | N85: SEM CAUSA DESCRITA NO TEXTO | O85: «O religador apresenta defeito no tanque, sendo necessário substituir o tanque o mesmo está tirando a linha» | P85: Modo: defeito no tanque que derruba a linha ('está tirando a linha'), com by-pass e troca de isoladores pedida. Nenhum mecanismo declarado — a palavra curto não aparece no texto. | Q85: Derrubado de CURTO-CIRCUITO INTERNO para SEM CAUSA DESCRITA NO TEXTO. A própria nota original admitia 'inferência de curto interno, não dito com todas as letras' — 'tirando a linha' é sintoma (desarme da linha), e deduzir dele falha de isolação interna é o mesmo salto que a régua veda em 'célula queimada' → descarga. Onde o curto conta (SS 00058, 00039, 00038, TELE 00861), o texto o declara; aqui não declara.
A86: RL 2026 | B86: =LEFT(Tabela3[[#This Row],[Ano/TIPO]],2) -> RL | D86: =_xlfn.XLOOKUP(K86,Base!G:G,Base!I:I) -> #N/A | E86: 7931608059 | F86: ETO-COEP 00040/2026 | G86: =_xlfn.XLOOKUP(_xlfn.NUMBERVALUE(Tabela3[[#This Row],[Ativo]]),'[2]Ajustes Reguladores de Tensão'!$A:$A,'[2]Ajustes Reguladores de Tensão'!$I:$I,_xlfn.XLOOKUP(_xlfn.NUMBERVALUE(Tabela3[[#This Row],[Ativo]]),'[2]Ajustes RL Poste'!$A:$A,'[2]Ajustes RL Poste'!$M:$M)) -> 13.800 | H86: 28/01/2026 | I86: =TEXT(Tabela3[[#This Row],[Data]],"mmmm") -> janeiro | J86: =YEAR(Tabela3[[#This Row],[Data]]) -> 2026 | K86: =_xlfn.CONCAT(Tabela3[[#This Row],[Ano]],Tabela3[[#This Row],[Mês]]) -> 2026janeiro | L86: tanque | M86: não | N86: SEM CAUSA DESCRITA NO TEXTO | O86: «foi identificado que o tanque do equipamento está danificado, sendo assim, necessário substituir o tanque e o rádio do equipamento, que está queimado» | P86: Tanque danificado e rádio queimado são modos de falha; nenhum porquê no texto.
A87: RL 2026 | B87: =LEFT(Tabela3[[#This Row],[Ano/TIPO]],2) -> RL | D87: =_xlfn.XLOOKUP(K87,Base!G:G,Base!I:I) -> #N/A | E87: 7933726256 | F87: ETO-PROT 00145/2026 | G87: =_xlfn.XLOOKUP(_xlfn.NUMBERVALUE(Tabela3[[#This Row],[Ativo]]),'[2]Ajustes Reguladores de Tensão'!$A:$A,'[2]Ajustes Reguladores de Tensão'!$I:$I,_xlfn.XLOOKUP(_xlfn.NUMBERVALUE(Tabela3[[#This Row],[Ativo]]),'[2]Ajustes RL Poste'!$A:$A,'[2]Ajustes RL Poste'!$M:$M)) -> 34.500 | H87: 04/04/2026 | I87: =TEXT(Tabela3[[#This Row],[Data]],"mmmm") -> abril | J87: =YEAR(Tabela3[[#This Row],[Data]]) -> 2026 | K87: =_xlfn.CONCAT(Tabela3[[#This Row],[Ano]],Tabela3[[#This Row],[Mês]]) -> 2026abril | L87: tanque | M87: sim | N87: SEM CAUSA DESCRITA NO TEXTO | O87: «Equipamento com defeito na parte ativa, será necessário fazer a substituição da parte ativa» | P87: Defeito na parte ativa sem porquê; a 'melhoria na malha de terra' pedida é recomendação, não causa declarada.
A88: RL 2026 | B88: =LEFT(Tabela3[[#This Row],[Ano/TIPO]],2) -> RL | D88: =_xlfn.XLOOKUP(K88,Base!G:G,Base!I:I) -> #N/A | E88: 7953211079 | F88: ETO-COEP 00147/2026 | G88: =_xlfn.XLOOKUP(_xlfn.NUMBERVALUE(Tabela3[[#This Row],[Ativo]]),'[2]Ajustes Reguladores de Tensão'!$A:$A,'[2]Ajustes Reguladores de Tensão'!$I:$I,_xlfn.XLOOKUP(_xlfn.NUMBERVALUE(Tabela3[[#This Row],[Ativo]]),'[2]Ajustes RL Poste'!$A:$A,'[2]Ajustes RL Poste'!$M:$M)) -> 34.500 | H88: 16/07/2026 | I88: =TEXT(Tabela3[[#This Row],[Data]],"mmmm") -> julho | J88: =YEAR(Tabela3[[#This Row],[Data]]) -> 2026 | K88: =_xlfn.CONCAT(Tabela3[[#This Row],[Ano]],Tabela3[[#This Row],[Mês]]) -> 2026julho | L88: controle | M88: não | N88: SEM CAUSA DESCRITA NO TEXTO | O88: «Segue nota para substituir relé religador avariado marca noja , equipamento N: 7953211079 - Itapiratins .» | P88: Relé Noja avariado informado pelo técnico DMSL, sem laudo do porquê da avaria.
A89: RL 2026 | B89: =LEFT(Tabela3[[#This Row],[Ano/TIPO]],2) -> RL | D89: =_xlfn.XLOOKUP(K89,Base!G:G,Base!I:I) -> #N/A | E89: 7953610256 | F89: ETO-COEP 00050/2026 | G89: =_xlfn.XLOOKUP(_xlfn.NUMBERVALUE(Tabela3[[#This Row],[Ativo]]),'[2]Ajustes Reguladores de Tensão'!$A:$A,'[2]Ajustes Reguladores de Tensão'!$I:$I,_xlfn.XLOOKUP(_xlfn.NUMBERVALUE(Tabela3[[#This Row],[Ativo]]),'[2]Ajustes RL Poste'!$A:$A,'[2]Ajustes RL Poste'!$M:$M)) -> 34.500 | H89: 16/02/2026 | I89: =TEXT(Tabela3[[#This Row],[Data]],"mmmm") -> fevereiro | J89: =YEAR(Tabela3[[#This Row],[Data]]) -> 2026 | K89: =_xlfn.CONCAT(Tabela3[[#This Row],[Ano]],Tabela3[[#This Row],[Mês]]) -> 2026fevereiro | L89: completo | M89: sim | N89: SEM CAUSA DESCRITA NO TEXTO | O89: «Trocado o DPS, o mesmo estava queimado devido ao tanque estar furado.» | P89: A cadeia documentada para no tanque furado (que queimou o DPS e gerou o curto no gabinete); o texto não diz por que o tanque furou — não especulo tiro, vandalismo ou corrosão.
A90: RL 2026 | B90: =LEFT(Tabela3[[#This Row],[Ano/TIPO]],2) -> RL | D90: =_xlfn.XLOOKUP(K90,Base!G:G,Base!I:I) -> #N/A | E90: 7955986084 | F90: ETO-TELE 00323/2026 | G90: =_xlfn.XLOOKUP(_xlfn.NUMBERVALUE(Tabela3[[#This Row],[Ativo]]),'[2]Ajustes Reguladores de Tensão'!$A:$A,'[2]Ajustes Reguladores de Tensão'!$I:$I,_xlfn.XLOOKUP(_xlfn.NUMBERVALUE(Tabela3[[#This Row],[Ativo]]),'[2]Ajustes RL Poste'!$A:$A,'[2]Ajustes RL Poste'!$M:$M)) -> 34.500 | H90: 31/03/2026 | I90: =TEXT(Tabela3[[#This Row],[Data]],"mmmm") -> março | J90: =YEAR(Tabela3[[#This Row],[Data]]) -> 2026 | K90: =_xlfn.CONCAT(Tabela3[[#This Row],[Ano]],Tabela3[[#This Row],[Mês]]) -> 2026março | L90: controle | M90: sim | N90: SEM CAUSA DESCRITA NO TEXTO | O90: «ATUALIZAR AJUSTES DO RL 7955986084 LD PARAISO A DIVINOPOLIS. IMPLEMENTAÇÃO DE PROTEÇÃO DE SUBTENSÃO (27)» | P90: Esta SS é só de ajuste de proteção; a evidência da falha (placa de alimentação CA em curto, substituída) está na OS, fora desta descrição — não uso o que a descrição não traz.
A91: RL 2026 | B91: =LEFT(Tabela3[[#This Row],[Ano/TIPO]],2) -> RL | D91: =_xlfn.XLOOKUP(K91,Base!G:G,Base!I:I) -> #N/A | E91: 7925744087 | F91: ETO-COEP 00059/2026 | G91: =_xlfn.XLOOKUP(_xlfn.NUMBERVALUE(Tabela3[[#This Row],[Ativo]]),'[2]Ajustes Reguladores de Tensão'!$A:$A,'[2]Ajustes Reguladores de Tensão'!$I:$I,_xlfn.XLOOKUP(_xlfn.NUMBERVALUE(Tabela3[[#This Row],[Ativo]]),'[2]Ajustes RL Poste'!$A:$A,'[2]Ajustes RL Poste'!$M:$M)) -> 34.500 | H91: 09/02/2026 | I91: =TEXT(Tabela3[[#This Row],[Data]],"mmmm") -> fevereiro | J91: =YEAR(Tabela3[[#This Row],[Data]]) -> 2026 | K91: =_xlfn.CONCAT(Tabela3[[#This Row],[Ano]],Tabela3[[#This Row],[Mês]]) -> 2026fevereiro | L91: tanque | M91: não | N91: UMIDADE / INFILTRAÇÃO | O91: «foi identificado água dentro da parte interna do tanque e cabo umbilical encharcado de água» | P91: Água dentro do tanque e cabo umbilical encharcado: infiltração explícita como origem da falha do tanque.

Sheet Planilha1
A1: Ano | B1: (Tudo)
A2: SS | B2: (Tudo)
A3: Realizado DCMD | B3: (Tudo)
A4: Posto que fechou | B4: (Tudo)
A6: Contagem de Ativo | B6: Rótulos de Coluna
A7: Rótulos de Linha | B7: SS ATENDIDA | C7: SS CANCELADA | D7: (vazio) | E7: Total Geral
A8: regulador | B8: 10 | C8: 16 | D8: 16 | E8: 42
A9: religador | B9: 20 | C9: 25 | D9: 56 | E9: 101
A10: Total Geral | B10: 30 | C10: 41 | D10: 72 | E10: 143

Sheet Resolvidos
A1: Resolvido (e não voltou) | B1: 71
A2: Na fila do posto | B2: 54
A3: Em outra mesa | B3: 18
A5: Situação | B5: Ativo | C5: Tipo | D5: Localidade | E5: Criticidade | F5: SS | G5: Prazo do SLA Dias | H5: SS COCM | I5: Desde | J5: Ano | K5: Dias | L5: Resolveu e voltou | M5: Como terminou | N5: Posto que fechou | O5: Realizado DCMD | P5: Onde está | Q5: Etapa | R5: Nota
A6: Na fila do posto | B6: 5800291035 | C6: regulador | D6: MONTE DO CARMO | E6: Média | F6: ETO-COEP 00174/2026 | I6: 11/08/2026 | J6: =RIGHT(Tabela4[[#This Row],[Desde]],4) -> 2026 | K6: 7 | L6: SIM | O6: não | R6: resolveu uma demanda no ano e voltou — conta aqui, não nos resolvidos. A resolvida: SS ATENDIDA em 24/03/2026 (ETO-TELE).
A7: Na fila do posto | B7: 5800440256 | C7: regulador | D7: MATEIROS | E7: Muito Alta | F7: ETO-COEP 00169/2026 | I7: 06/08/2026 | J7: =RIGHT(Tabela4[[#This Row],[Desde]],4) -> 2026 | K7: 12 | O7: não
A8: Na fila do posto | B8: 5800961074 | C8: regulador | D8: DIANOPOLIS | E8: Média | F8: ETO-COEP 00221/2025 | I8: 05/12/2025 | J8: =RIGHT(Tabela4[[#This Row],[Desde]],4) -> 2025 | K8: 256 | O8: não
A9: Na fila do posto | B9: 5803327001 | C9: regulador | D9: PORTO NACIONAL | E9: Alta | F9: ETO-COEP 00149/2026 | I9: 20/07/2026 | J9: =RIGHT(Tabela4[[#This Row],[Desde]],4) -> 2026 | K9: 29 | O9: não
A10: Na fila do posto | B10: 5825703064 | C10: regulador | D10: BRASILANDIA DO TOCANTINS | E10: — | F10: ETO-COEP 00153/2026 | I10: 21/07/2026 | J10: =RIGHT(Tabela4[[#This Row],[Desde]],4) -> 2026 | K10: 28 | O10: não
A11: Na fila do posto | B11: 5836786094 | C11: regulador | D11: PEIXE | E11: Baixa | F11: ETO-COEP 00095/2026 | I11: 18/05/2026 | J11: =RIGHT(Tabela4[[#This Row],[Desde]],4) -> 2026 | K11: 92 | O11: não
A12: Na fila do posto | B12: 5840227063 | C12: regulador | D12: BANDEIRANTES DO TOCANTINS | E12: Média | F12: ETO-COEP 00151/2026 | I12: 20/07/2026 | J12: =RIGHT(Tabela4[[#This Row],[Desde]],4) -> 2026 | K12: 29 | O12: não
A13: Na fila do posto | B13: 5855411017 | C13: regulador | D13: BARROLANDIA | E13: Baixa | F13: ETO-COEP 00156/2026 | I13: 24/07/2026 | J13: =RIGHT(Tabela4[[#This Row],[Desde]],4) -> 2026 | K13: 25 | O13: não
A14: Na fila do posto | B14: 5856156091 | C14: regulador | D14: ALMAS | E14: Baixa | F14: ETO-COEP 00160/2026 | I14: 27/07/2026 | J14: =RIGHT(Tabela4[[#This Row],[Desde]],4) -> 2026 | K14: 22 | O14: não
A15: Na fila do posto | B15: 5858783119 | C15: regulador | D15: SAO BENTO DO TOCANTINS | E15: Baixa | F15: ETO-COEP 00164/2026 | I15: 31/07/2026 | J15: =RIGHT(Tabela4[[#This Row],[Desde]],4) -> 2026 | K15: 18 | O15: não
A16: Na fila do posto | B16: 5862236091 | C16: regulador | D16: ALMAS | E16: Baixa | F16: ETO-COEP 00158/2026 | I16: 27/07/2026 | J16: =RIGHT(Tabela4[[#This Row],[Desde]],4) -> 2026 | K16: 22 | O16: não
A17: Na fila do posto | B17: 7900453110 | C17: religador | D17: SANTA RITA DO TOCANTINS | E17: Muito Alta | F17: ETO-COEP 00087/2026 | I17: 27/04/2026 | J17: =RIGHT(Tabela4[[#This Row],[Desde]],4) -> 2026 | K17: 113 | L17: SIM | O17: não | R17: resolveu uma demanda no ano e voltou — conta aqui, não nos resolvidos. A resolvida: SS CANCELADA em 11/08/2026 (ETO-COEP).
A18: Na fila do posto | B18: 7900525015 | C18: religador | D18: PEDRO AFONSO | E18: Média | F18: ETO-COEP 00125/2026 | I18: 07/07/2026 | J18: =RIGHT(Tabela4[[#This Row],[Desde]],4) -> 2026 | K18: 42 | O18: não
A19: Na fila do posto | B19: 7900535058 | C19: religador | D19: SANTA FE DO ARAGUAIA | E19: Média | F19: ETO-COEP 00173/2025 | I19: 25/08/2025 | J19: =RIGHT(Tabela4[[#This Row],[Desde]],4) -> 2025 | K19: 358 | O19: não
A20: Na fila do posto | B20: 7901110084 | C20: religador | D20: DIVINOPOLIS | E20: Baixa | F20: ETO-COEP 00061/2026 | I20: 31/03/2026 | J20: =RIGHT(Tabela4[[#This Row],[Desde]],4) -> 2026 | K20: 140 | O20: não
A21: Na fila do posto | B21: 7903112004 | C21: religador | D21: ARAGUAINA | E21: Alta | F21: ETO-COEP 00184/2025 | I21: 03/09/2025 | J21: =RIGHT(Tabela4[[#This Row],[Desde]],4) -> 2025 | K21: 349 | O21: não
A22: Na fila do posto | B22: 7903569004 | C22: religador | D22: ARAGUAINA | E22: Muito Alta | F22: ETO-COEP 00152/2026 | I22: 20/07/2026 | J22: =RIGHT(Tabela4[[#This Row],[Desde]],4) -> 2026 | K22: 29 | L22: SIM | O22: não | R22: resolveu uma demanda no ano e voltou — conta aqui, não nos resolvidos. A resolvida: SS ATENDIDA em 07/07/2026 (ETO-TELE).
A23: Na fila do posto | B23: 7908196047 | C23: religador | D23: FIGUEIROPOLIS | E23: Baixa | F23: ETO-COEP 00168/2026 | I23: 03/08/2026 | J23: =RIGHT(Tabela4[[#This Row],[Desde]],4) -> 2026 | K23: 15 | O23: não
A24: Na fila do posto | B24: 7908249152 | C24: religador | D24: SANTA ROSA DO TOCANTINS | E24: Média | F24: ETO-COEP 00038/2026 | I24: 24/02/2026 | J24: =RIGHT(Tabela4[[#This Row],[Desde]],4) -> 2026 | K24: 175 | O24: não
A25: Na fila do posto | B25: 7908302256 | C25: religador | D25: MATEIROS | E25: Alta | F25: ETO-COEP 00175/2026 | I25: 11/08/2026 | J25: =RIGHT(Tabela4[[#This Row],[Desde]],4) -> 2026 | K25: 7 | O25: não
A26: Na fila do posto | B26: 7910027196 | C26: religador | D26: LAGOA DO TOCANTINS | E26: Baixa | F26: ETO-COEP 00154/2026 | I26: 22/07/2026 | J26: =RIGHT(Tabela4[[#This Row],[Desde]],4) -> 2026 | K26: 27 | L26: SIM | O26: não | R26: resolveu uma demanda no ano e voltou — conta aqui, não nos resolvidos. A resolvida: SS ATENDIDA em 17/06/2026 (ETO-TELE).
A27: Na fila do posto | B27: 7913662076 | C27: religador | D27: DUERE | E27: Baixa | F27: ETO-COEP 00114/2026 | I27: 10/06/2026 | J27: =RIGHT(Tabela4[[#This Row],[Desde]],4) -> 2026 | K27: 69 | O27: não
A28: Na fila do posto | B28: 7915029003 | C28: religador | D28: GURUPI | E28: — | F28: ETO-COEP 00013/2023 | ETO-COEP 00063/2023 | I28: 27/01/2023 | J28: =RIGHT(Tabela4[[#This Row],[Desde]],4) -> 2023 | K28: 1299 | O28: não
A29: Na fila do posto | B29: 7919270014 | C29: religador | D29: PIUM | E29: Baixa | F29: ETO-COEP 00159/2026 | I29: 27/07/2026 | J29: =RIGHT(Tabela4[[#This Row],[Desde]],4) -> 2026 | K29: 22 | O29: não
A30: Na fila do posto | B30: 7920024127 | C30: religador | D30: PALMEIRAS DO TOCANTINS | E30: Alta | F30: ETO-COEP 00120/2025 | I30: 01/07/2025 | J30: =RIGHT(Tabela4[[#This Row],[Desde]],4) -> 2025 | K30: 413 | O30: não
A31: Na fila do posto | B31: 7921202014 | C31: religador | D31: PIUM | E31: Baixa | F31: ETO-COEP 00132/2026 | I31: 08/07/2026 | J31: =RIGHT(Tabela4[[#This Row],[Desde]],4) -> 2026 | K31: 41 | O31: não
A32: Na fila do posto | B32: 7923673004 | C32: religador | D32: ARAGUAINA | E32: Muito Alta | F32: ETO-COEP 00124/2026 | I32: 07/07/2026 | J32: =RIGHT(Tabela4[[#This Row],[Desde]],4) -> 2026 | K32: 42 | O32: não
A33: Na fila do posto | B33: 7923674004 | C33: religador | D33: ARAGUAINA | E33: — | F33: ETO-COEP 00011/2023 | I33: 25/01/2023 | J33: =RIGHT(Tabela4[[#This Row],[Desde]],4) -> 2023 | K33: 1301 | O33: não
A34: Na fila do posto | B34: 7923927122 | C34: religador | D34: PALMAS | E34: Baixa | F34: ETO-COEP 00148/2026 | I34: 16/07/2026 | J34: =RIGHT(Tabela4[[#This Row],[Desde]],4) -> 2026 | K34: 33 | O34: não
A35: Na fila do posto | B35: 7925733015 | C35: religador | D35: PEDRO AFONSO | E35: Média | F35: ETO-COEP 00058/2026 | I35: 30/03/2026 | J35: =RIGHT(Tabela4[[#This Row],[Desde]],4) -> 2026 | K35: 141 | L35: SIM | O35: não | R35: resolveu uma demanda no ano e voltou — conta aqui, não nos resolvidos. A resolvida: SS CANCELADA em 17/06/2026 (ETO-COEP).
A36: Na fila do posto | B36: 7925744087 | C36: religador | D36: GOIANORTE | E36: Muito Alta | F36: ETO-COEP 00059/2026 | I36: 30/03/2026 | J36: =RIGHT(Tabela4[[#This Row],[Desde]],4) -> 2026 | K36: 141 | O36: não
A37: Na fila do posto | B37: 7925871077 | C37: religador | D37: GOIATINS | E37: Muito Alta | F37: ETO-COEP 00048/2026 | I37: 16/03/2026 | J37: =RIGHT(Tabela4[[#This Row],[Desde]],4) -> 2026 | K37: 155 | O37: não
A38: Na fila do posto | B38: 7926089013 | C38: religador | D38: PARAISO DO TOCANTINS | E38: Alta | F38: ETO-COEP 00078/2026 | I38: 23/04/2026 | J38: =RIGHT(Tabela4[[#This Row],[Desde]],4) -> 2026 | K38: 117 | L38: SIM | O38: não | R38: resolveu uma demanda no ano e voltou — conta aqui, não nos resolvidos. A resolvida: SS CANCELADA em 16/06/2026 (ETO-COEP).
A39: Na fila do posto | B39: 7926442035 | C39: religador | D39: MONTE DO CARMO | E39: Baixa | F39: ETO-COEP 00051/2026 | I39: 18/03/2026 | J39: =RIGHT(Tabela4[[#This Row],[Desde]],4) -> 2026 | K39: 153 | O39: não
A40: Na fila do posto | B40: 7927396052 | C40: religador | D40: FORMOSO DO ARAGUAIA | E40: Média | F40: ETO-COEP 00045/2026 | I40: 02/03/2026 | J40: =RIGHT(Tabela4[[#This Row],[Desde]],4) -> 2026 | K40: 169 | O40: não
A41: Na fila do posto | B41: 7927413001 | C41: religador | D41: PORTO NACIONAL | E41: Muito Alta | F41: ETO-COEP 00141/2026 | I41: 13/07/2026 | J41: =RIGHT(Tabela4[[#This Row],[Desde]],4) -> 2026 | K41: 36 | O41: não
A42: Na fila do posto | B42: 7927446001 | C42: religador | D42: PORTO NACIONAL | E42: Baixa | F42: ETO-COEP 00143/2025 | I42: 08/07/2025 | J42: =RIGHT(Tabela4[[#This Row],[Desde]],4) -> 2025 | K42: 406 | O42: não
A43: Na fila do posto | B43: 7927646026 | C43: religador | D43: PONTE ALTA TOCANTINS | E43: Alta | F43: ETO-COEP 00029/2026 | I43: 04/02/2026 | J43: =RIGHT(Tabela4[[#This Row],[Desde]],4) -> 2026 | K43: 195 | O43: não
A44: Na fila do posto | B44: 7927713200 | C44: religador | D44: SAO SALVADOR DO TOCANTINS | E44: Média | F44: ETO-COEP 00157/2026 | I44: 27/07/2026 | J44: =RIGHT(Tabela4[[#This Row],[Desde]],4) -> 2026 | K44: 22 | L44: SIM | O44: não | R44: resolveu uma demanda no ano e voltou — conta aqui, não nos resolvidos. A resolvida: SS ATENDIDA em 08/07/2026 (ETO-TELE).
A45: Na fila do posto | B45: 7928241200 | C45: religador | D45: SAO SALVADOR DO TOCANTINS | E45: Baixa | F45: ETO-COEP 00128/2026 | I45: 07/07/2026 | J45: =RIGHT(Tabela4[[#This Row],[Desde]],4) -> 2026 | K45: 42 | O45: não
A46: Na fila do posto | B46: 7928564039 | C46: religador | D46: ARAGUATINS | E46: Média | F46: ETO-COEP 00123/2026 | I46: 07/07/2026 | J46: =RIGHT(Tabela4[[#This Row],[Desde]],4) -> 2026 | K46: 42 | O46: não
A47: Na fila do posto | B47: 7930359149 | C47: religador | D47: CASEARA | E47: — | F47: ETO-COEP 00138/2026 | I47: 13/07/2026 | J47: =RIGHT(Tabela4[[#This Row],[Desde]],4) -> 2026 | K47: 36 | O47: não
A48: Na fila do posto | B48: 7930428001 | C48: religador | D48: PORTO NACIONAL | E48: Alta | F48: ETO-COEP 00150/2026 | I48: 20/07/2026 | J48: =RIGHT(Tabela4[[#This Row],[Desde]],4) -> 2026 | K48: 29 | O48: não
A49: Na fila do posto | B49: 7931608059 | C49: religador | D49: TAQUARALTO | E49: Muito Alta | F49: ETO-COEP 00040/2026 | I49: 24/02/2026 | J49: =RIGHT(Tabela4[[#This Row],[Desde]],4) -> 2026 | K49: 175 | L49: SIM | O49: não | R49: resolveu uma demanda no ano e voltou — conta aqui, não nos resolvidos. A resolvida: SS CANCELADA em 17/06/2026 (ETO-COEP).
A50: Na fila do posto | B50: 7933585074 | C50: religador | D50: DIANOPOLIS | E50: Média | F50: ETO-COEP 00024/2026 | I50: 27/01/2026 | J50: =RIGHT(Tabela4[[#This Row],[Desde]],4) -> 2026 | K50: 203 | O50: não
A51: Na fila do posto | B51: 7937102148 | C51: religador | D51: SAO VALERIO DA NATIVIDADE | E51: Média | F51: ETO-COEP 00129/2026 | I51: 07/07/2026 | J51: =RIGHT(Tabela4[[#This Row],[Desde]],4) -> 2026 | K51: 42 | O51: não
A52: Na fila do posto | B52: 7938137007 | C52: religador | D52: MIRACEMA DO TOCANTINS | E52: Baixa | F52: ETO-COEP 00144/2026 | I52: 15/07/2026 | J52: =RIGHT(Tabela4[[#This Row],[Desde]],4) -> 2026 | K52: 34 | O52: não
A53: Na fila do posto | B53: 7942485096 | C53: religador | D53: PINDORAMA DO TOCANTINS | E53: Baixa | F53: ETO-COEP 00158/2025 | I53: 23/07/2025 | J53: =RIGHT(Tabela4[[#This Row],[Desde]],4) -> 2025 | K53: 391 | O53: não
A54: Na fila do posto | B54: 7944559149 | C54: religador | D54: CASEARA | E54: Média | F54: ETO-COEP 00063/2026 | I54: 31/03/2026 | J54: =RIGHT(Tabela4[[#This Row],[Desde]],4) -> 2026 | K54: 140 | O54: não
A55: Na fila do posto | B55: 7947203070 | C55: religador | D55: RIO SONO | E55: Muito Alta | F55: ETO-COEP 00131/2026 | I55: 08/07/2026 | J55: =RIGHT(Tabela4[[#This Row],[Desde]],4) -> 2026 | K55: 41 | O55: não
A56: Na fila do posto | B56: 7953211079 | C56: religador | D56: ITAPIRATINS | E56: — | F56: ETO-COEP 00147/2026 | I56: 16/07/2026 | J56: =RIGHT(Tabela4[[#This Row],[Desde]],4) -> 2026 | K56: 33 | O56: não
A57: Na fila do posto | B57: 7954668084 | C57: religador | D57: DIVINOPOLIS | E57: Baixa | F57: ETO-COEP 00176/2026 | I57: 11/08/2026 | J57: =RIGHT(Tabela4[[#This Row],[Desde]],4) -> 2026 | K57: 7 | L57: SIM | O57: não | R57: resolveu uma demanda no ano e voltou — conta aqui, não nos resolvidos. A resolvida: SS ATENDIDA em 07/07/2026 (ETO-TELE).
A58: Na fila do posto | B58: 7955946007 | C58: religador | D58: MIRACEMA DO TOCANTINS | E58: Baixa | F58: ETO-COEP 00134/2026 | I58: 08/07/2026 | J58: =RIGHT(Tabela4[[#This Row],[Desde]],4) -> 2026 | K58: 41 | L58: SIM | O58: não | R58: resolveu uma demanda no ano e voltou — conta aqui, não nos resolvidos. A resolvida: SS ATENDIDA em 18/03/2026 (ETO-TELE).
A59: Na fila do posto | B59: 7955986084 | C59: religador | D59: DIVINOPOLIS | E59: Média | F59: ETO-COEP 00133/2026 | I59: 08/07/2026 | J59: =RIGHT(Tabela4[[#This Row],[Desde]],4) -> 2026 | K59: 41 | L59: SIM | O59: não | R59: resolveu uma demanda no ano e voltou — conta aqui, não nos resolvidos. A resolvida: SS ATENDIDA em 09/04/2026 (ETO-TELE).
A60: Em outra mesa | B60: 5800371025 | C60: regulador | D60: ARAPOEMA | E60: Alta | F60: ETO-TELE 01040/2026 | I60: 30/07/2026 | J60: =RIGHT(Tabela4[[#This Row],[Desde]],4) -> 2026 | K60: 19 | O60: sim | P60: ETO-TELE | Q60: comissionamento — parte do COEP concluída | R60: SS PENDENTE
A61: Em outra mesa | B61: 5846328094 | C61: regulador | D61: PEIXE | E61: Média | F61: ETO-TELE 00986/2026 | I61: 08/07/2026 | J61: =RIGHT(Tabela4[[#This Row],[Desde]],4) -> 2026 | K61: 41 | O61: sim | P61: ETO-TELE | Q61: comissionamento — parte do COEP concluída | R61: SS PENDENTE
A62: Em outra mesa | B62: 5854566043 | C62: regulador | D62: SILVANOPOLIS | E62: Muito Alta | F62: ETO-PROT 00158/2026 | I62: 28/07/2026 | J62: =RIGHT(Tabela4[[#This Row],[Desde]],4) -> 2026 | K62: 21 | O62: sim | P62: ETO-PROT | Q62: ajuste de proteção — parte do COEP concluída | R62: SS PENDENTE
A63: Em outra mesa | B63: 5856070091 | C63: regulador | D63: ALMAS | E63: Muito Alta | F63: ETO-RD-DP 00479/2026 | I63: 27/07/2026 | J63: =RIGHT(Tabela4[[#This Row],[Desde]],4) -> 2026 | K63: 22 | O63: sim | P63: ETO-RD-DP | Q63: execução com os COCMs | R63: SS PENDENTE
A64: Em outra mesa | B64: 5865120195 | C64: regulador | D64: CENTENARIO | E64: Alta | F64: ETO-SE-PCM 00091/2026 | I64: 17/08/2026 | J64: =RIGHT(Tabela4[[#This Row],[Desde]],4) -> 2026 | K64: 1 | O64: sim | P64: ETO-SE-PCM | Q64: comissionamento — parte do COEP concluída | R64: SS PENDENTE
A65: Em outra mesa | B65: 7900117013 | C65: religador | D65: PARAISO DO TOCANTINS | E65: Muito Alta | F65: ETO-PROT 00154/2026 | I65: 21/07/2026 | J65: =RIGHT(Tabela4[[#This Row],[Desde]],4) -> 2026 | K65: 28 | O65: sim | P65: ETO-PROT | Q65: ajuste de proteção — parte do COEP concluída | R65: SS PENDENTE
A66: Em outra mesa | B66: 7900230155 | C66: religador | D66: PALMEIRANTE | E66: Muito Alta | F66: ETO-SE-PCM 00090/2026 | I66: 17/08/2026 | J66: =RIGHT(Tabela4[[#This Row],[Desde]],4) -> 2026 | K66: 1 | O66: sim | P66: ETO-SE-PCM | Q66: comissionamento — parte do COEP concluída | R66: SS PENDENTE
A67: Em outra mesa | B67: 7900573047 | C67: religador | D67: FIGUEIROPOLIS | E67: Alta | F67: ETO-PROT 00153/2026 | I67: 20/07/2026 | J67: =RIGHT(Tabela4[[#This Row],[Desde]],4) -> 2026 | K67: 29 | O67: sim | P67: ETO-PROT | Q67: ajuste de proteção — parte do COEP concluída | R67: SS PENDENTE
A68: Em outra mesa | B68: 7900594026 | C68: religador | D68: PONTE ALTA TOCANTINS | E68: Muito Alta | F68: ETO-SE-PA 00107/2026 | I68: 16/07/2026 | J68: =RIGHT(Tabela4[[#This Row],[Desde]],4) -> 2026 | K68: 33 | O68: sim | P68: ETO-SE-PA | Q68: comissionamento — parte do COEP concluída | R68: SS PENDENTE
A69: Em outra mesa | B69: 7905357122 | C69: religador | D69: PALMAS | E69: — | F69: ETO-RD-PA 00352/2026 | I69: 22/05/2026 | J69: =RIGHT(Tabela4[[#This Row],[Desde]],4) -> 2026 | K69: 88 | O69: sim | P69: ETO-RD-PA | Q69: execução com os COCMs | R69: SS PENDENTE
A70: Em outra mesa | B70: 7908686014 | C70: religador | D70: PIUM | E70: Muito Alta | F70: ETO-PROT 00159/2026 | I70: 28/07/2026 | J70: =RIGHT(Tabela4[[#This Row],[Desde]],4) -> 2026 | K70: 21 | O70: sim | P70: ETO-PROT | Q70: ajuste de proteção — parte do COEP concluída | R70: SS PENDENTE
A71: Em outra mesa | B71: 7908705049 | C71: religador | D71: AURORA DO TOCANTINS | E71: Muito Alta | F71: ETO-RD-DP 00409/2026 | I71: 06/07/2026 | J71: =RIGHT(Tabela4[[#This Row],[Desde]],4) -> 2026 | K71: 43 | O71: sim | P71: ETO-RD-DP | Q71: execução com os COCMs | R71: SS PENDENTE
... A77: Em outra mesa | B77: 7953610256 | C77: religador | D77: MATEIROS | E77: Alta | F77: ETO-PROT 00157/2026 | I77: 28/07/2026 | J77: =RIGHT(Tabela4[[#This Row],[Desde]],4) -> 2026 | K77: 21 | O77: sim | P77: ETO-PROT | Q77: ajuste de proteção — parte do COEP concluída | R77: SS PENDENTE
A78: Resolvido | B78: 5800090147 | C78: regulador | D78: TAIPAS DO TOCANTINS | E78: Média | F78: ETO-COEP 00117/2026 | I78: 13/07/2026 | J78: =RIGHT(Tabela4[[#This Row],[Desde]],4) -> 2026 | K78: 102 | M78: SS CANCELADA | N78: ETO-COEP | O78: sim | R78: cancelada, com leitura que confirma volta à operação
A79: Resolvido | B79: 5800291077 | C79: regulador | D79: GOIATINS | E79: Muito Alta | F79: ETO-TELE 00413/2026 | I79: 31/03/2026 | J79: =RIGHT(Tabela4[[#This Row],[Desde]],4) -> 2026 | K79: 49 | M79: SS ATENDIDA | N79: ETO-TELE | O79: não | R79: SS atendida — serviço executado; a nota aberta depois é reincidência, demanda nova · nota pendente em outro posto (ETO-TELE 00498/2026 (ETO-TELE), ETO-RD-AR 00841/2026 (ETO-RD-AR), ETO-TELE 00854/2026 (ETO-TELE)) — outra frente, não derruba (régua 22/08)
A80: Resolvido | B80: 5800366016 | C80: regulador | D80: WANDERLANDIA | E80: Alta | F80: ETO-TELE 00804/2026 | I80: 06/05/2026 | J80: =RIGHT(Tabela4[[#This Row],[Desde]],4) -> 2026 | K80: 235 | M80: SS ATENDIDA | N80: ETO-TELE | O80: não | R80: SS atendida — serviço executado
A81: Resolvido | B81: 5800438116 | C81: regulador | D81: CHAPADA DA NATIVIDADE | E81: Média | F81: ETO-TELE 01039/2026 | I81: 13/08/2026 | J81: =RIGHT(Tabela4[[#This Row],[Desde]],4) -> 2026 | K81: 390 | M81: SS ATENDIDA | N81: ETO-TELE | O81: sim | R81: SS atendida — serviço executado
A82: Resolvido | B82: 5800859011 | C82: regulador | D82: TUPIRAMA | E82: Muito Alta | F82: ETO-TELE 01037/2026 | I82: 13/08/2026 | J82: =RIGHT(Tabela4[[#This Row],[Desde]],4) -> 2026 | K82: 77 | M82: SS ATENDIDA | N82: ETO-TELE | O82: sim | R82: SS atendida — serviço executado
A83: Resolvido | B83: 5801866013 | C83: regulador | D83: PARAISO DO TOCANTINS | E83: Alta | F83: ETO-RD-PS 00303/2026 | I83: 14/07/2026 | J83: =RIGHT(Tabela4[[#This Row],[Desde]],4) -> 2026 | K83: 133 | M83: SS ATENDIDA | N83: ETO-RD-PS | O83: sim | R83: SS atendida — serviço executado · nota pendente em outro posto (ETO-PROT 00151/2026 (ETO-PROT)) — outra frente, não derruba (régua 22/08)
A84: Resolvido | B84: 5820044123 | C84: regulador | D84: AGUIARNOPOLIS | E84: — | F84: ETO-COEP 00202/2025 | I84: 30/06/2026 | J84: =RIGHT(Tabela4[[#This Row],[Desde]],4) -> 2026 | K84: 270 | M84: SS CANCELADA | N84: ETO-COEP | O84: sim | R84: resolvido por cancelamento — nenhuma nota nova no COEP depois
A85: Resolvido | B85: 5827102054 | C85: regulador | D85: PUGMIL | E85: Média | F85: ETO-RD-PS 00289/2026 | I85: 28/07/2026 | J85: =RIGHT(Tabela4[[#This Row],[Desde]],4) -> 2026 | K85: 334 | M85: SS ATENDIDA | N85: ETO-RD-PS | O85: sim | R85: SS atendida — serviço executado · nota pendente em outro posto (ETO-PROT 00164/2026 (ETO-PROT)) — outra frente, não derruba (régua 22/08)
A86: Resolvido | B86: 5833723026 | C86: regulador | D86: PONTE ALTA DO TOCANTINS | E86: — | F86: ETO-COEP 00126/2024 | I86: 22/05/2026 | J86: =RIGHT(Tabela4[[#This Row],[Desde]],4) -> 2026 | K86: 617 | M86: SS CANCELADA | N86: ETO-COEP | O86: sim | R86: resolvido por cancelamento — nenhuma nota nova no COEP depois
A87: Resolvido | B87: 5835587001 | C87: regulador | D87: PORTO NACIONAL | E87: — | F87: ETO-COEP 00198/2025 | I87: 30/06/2026 | J87: =RIGHT(Tabela4[[#This Row],[Desde]],4) -> 2026 | K87: 293 | M87: SS CANCELADA | N87: ETO-COEP | O87: sim | R87: resolvido por cancelamento — nenhuma nota nova no COEP depois
A88: Resolvido | B88: 5836764032 | C88: regulador | D88: ARAGUACU | E88: Muito Alta | F88: ETO-TELE 00807/2026 | I88: 20/05/2026 | J88: =RIGHT(Tabela4[[#This Row],[Desde]],4) -> 2026 | K88: 302 | M88: SS ATENDIDA | N88: ETO-TELE | O88: sim | R88: SS atendida — serviço executado
A89: Resolvido | B89: 5841308190 | C89: regulador | D89: NOVO JARDIM | E89: Baixa | F89: ETO-COEP 00197/2025 | I89: 18/03/2026 | J89: =RIGHT(Tabela4[[#This Row],[Desde]],4) -> 2026 | K89: 242 | M89: SS ATENDIDA | N89: ETO-COEP | O89: não | R89: SS atendida — serviço executado
... A148: Resolvido | B148: 7967181127 | C148: religador | D148: PALMEIRAS DO TOCANTINS | E148: Média | F148: ETO-RD-AG 00670/2026 | I148: 01/07/2026 | J148: =RIGHT(Tabela4[[#This Row],[Desde]],4) -> 2026 | K148: 159 | M148: SS ATENDIDA | N148: ETO-RD-AG | O148: sim | R148: SS atendida — serviço executado; a nota aberta depois é reincidência, demanda nova · nota pendente em outro posto (ETO-RD-AG 00630/2026 (ETO-RD-AG), ETO-RD-AG 00670/2026 (ETO-RD-AG), ETO-RD-AR 01070/2026 (ETO-RD-AR)) — outra frente, não derruba (régua 22/08)
K158: 6
K159: 7
K160: 8
K161: 3
K162: 0
K163: 1
K164: 3
K165: 0

Sheet BASE SS_OS
A1: NUMERO_SS | B1: NUMERO_OS | C1: NUM_OBRA | D1: ORIGEM_SS | E1: DEFEITO_SS | F1: ORIGEM | G1: DEFEITO | H1: ESQUEMA | I1: TASK | J1: ANO | K1: ORG_SOLIC | L1: COD_EQUIPE | M1: ALIMENTADOR | N1: NUM_TRAFO | O1: COORD_X | P1: COORD_Y | Q1: COD_GIS | R1: CRITICIDADE_SS | S1: SITUACAO_SS | T1: DATA_ABERTURA_SS | U1: DATA_TERMINO_SS | V1: DATA_LIMITE_SS | W1: DESCICAO_DO_ATIVO | X1: LOCALIDADE | Y1: SOLICITANTE | Z1: RURA_URBANO | AA1: TIPOSS | AB1: DESCRIPTION_SS | AC1: DESCRICAO_OS | AD1: NS_RETIRADO | AE1: TOMBAMENTO_RETIRADO | AF1: FABRICANTE_INSTALADO | AG1: FABRICANTE_RETIRADO | AH1: DATA_FABRICACAO_INSTALADO | AI1: DATA_FABRICACAO_RETIRADO | AJ1: NS_INSTALADO | AK1: TOMBAMENTO_INSTALADO | AL1: NUM_INT | AM1: REFORMADORA_DESAT | AN1: REFORMADORA_DESAT_1 | AO1: DATA_REFORMA_INST | AP1: DATA_REFORMA_RET | AQ1: POTENCIA_INST | AR1: POTENCIA_RET | AS1: FEITO_COLA_E_FITA | AT1: QTD_CLIENTES | AU1: ATERRAMENTO_ESTA_CONECTADO_AO_TANQUE_DO_TRAFO | AV1: EQUIPAMENTO_APRESENTA_VAZAMENTO_DE_OLEO | AW1: EXISTE_VEGETAÇÃO_TOCANDO_A_REDE_BT_OU_MT | AX1: FEZ_MELHORIA_DE_ATERRAMENTO | AY1: INSTALOU_ALGUM_ESPAÇADOR | AZ1: PARA_RAIOS_INSTALADO_SUBSTITUIDO | BA1: PROVÁVEL_MOTIVO_DO_DEFEITO | BB1: QUAL_ELO_INSTALADO_NO_LOCAL | BC1: TIPO_DE_BARRAMENTO | BD1: MEDIÇÃO_DE_ATERRAMENTO_ANTES_X1 | BE1: MEDIÇÃO_DE_ATERRAMENTO_ANTES_X2 | BF1: MEDIÇÃO_DE_ATERRAMENTO_ANTES_X3 | BG1: MEDIÇÃO_DE_ATERRAMENTO_X1 | BH1: MEDIÇÃO_DE_ATERRAMENTO_X2 | BI1: MEDIÇÃO_DE_ATERRAMENTO_X3 | BJ1: TRAFO_INSTALADO_É_REFORMADO | BK1: REFORMADORA_INSTALADO | BL1: TRANSFORMADOR_RETIRADO_É_REFORMADO | BM1: Coluna1
A2: ETO-RD-AR 01440/2026 | D2: REGULADOR DE TENSÃO | E2: ILEGÍVEL | J2: 2026 | K2: COI | L2: ETO-RD-AR | M2: AL01054060 | N2: 5844630060 | O2: 792803 | P2: 9144437 | Q2: 190-29126245 | R2: EMERGENCIAL | S2: SS PENDENTE | T2: 46283.718 | V2: 46286.718 | W2: REGULADOR DE TENSAO DE DIST. - 13.8 | X2: NOVA OLINDA | Y2: DIOMAR FERREIRA PEREIRA | Z2: RURAL | AA2: INDISPONIBILIDADE PARA OPERAÇÃO | AB2: 18/09/2026 PARECER COEP: REPASSANDO PARA O POSTO DOS COCM´S PARA DEVIDA TRATATIVA , NECESSITA APENAS CONEXÃO MT PARECER DMSL: FEEDBACK EQUIP. ESPECIAISNº DO EQUIPAMENTO: 5844630060TIPO EQUIPAMENTO: RT RUATIPO DE COMUNICAÇÃO: Radio GE IPDATA DA MANUTENÇÃO: 11/09/2026SID: 5815/2026DESCRIÇÃO: Realizado ensaio de isolação da célula C, a mesma está com o isolamento bom. Sendo assim necessário que a Linha Viva faça a reconexão o cabo na chave faca de saída da fase C, pois a mesma se desprendeu.FICOU EM OPERAÇÃO?: Não. Bypassado.PENDÊNCIA: Reconectar cabo na chave faca da fase C. DADOS DIVERGENTES DA PROGRAMAÇÃO: NãoTIPO DE BATERIA: ChumboEQUIPE: Edeglan e Brunno.___________________________________________________Segue nota para verificar falha em comandos via supervisório e constantes travamento no regulador de tensão 5844630060 - rural- Nova Olinda .Foi executado comandos no relé via supervisório, porém sem sucesso , em campo o equipamento está com a fase B travada no -16 .Obs: equipamento ficou fora de operação bay passado , favor agilizar atendimento !
A3: ETO-COEP 00201/2026 | D3: RELÉ | E3: INSPEÇÃO VISUAL | J3: 2026 | K3: COI | L3: ETO-COEP | M3: LD01065015 | N3: 7931219078 | O3: 857972 | P3: 9047058 | Q3: 190-17404165 | R3: EMERGENCIAL | S3: SS PENDENTE | T3: 46282.593 | V3: 46285.593 | W3: BLOCO RELIGADOR DE LINHA | X3: ITACAJA | Y3: SAMUEL PINTO GOMES | Z3: RURAL | AA3: INDISPONIBILIDADE PARA OPERAÇÃO | AB3: 17/09/2026 PARECER COEP: EQUIPAMENTO JÁ ERA PRA TER SIDO RESOLVIDO PELOS COCM´S, NO ENTANTO ,ALINHAMOS DO DIA 11/09 COM KELLITON PARA REALIZAR A SUBSTITUIÇÃO DO TRAFO AUXILIARPARECER DMSL: *FEEDBACK EQUIP. ESPECIAIS**Nº DO EQUIPAMENTO:* 7931219078*TIPO EQUIPAMENTO:* Noja RC10*TIPO DE COMUNICAÇÃO:* Rádio GE IP*DATA DA MANUTENÇÃO:* 17/09/2026*SID:* 5806/2026*DESCRIÇÃO:* _Realizada atualização da base e feito comissionamento com SCADA (Carlos). Porém o equipamento ficou fora de operação e Bay passado devido o transformador está com problema.OBS: nota repassada para substituir o transformador.*FICOU EM OPERAÇÃO?:* Não..*PENDÊNCIA:* Abrir nota para substituir o transformador.*DADOS DIVERGENTES DA PROGRAMAÇÃO:* Não*TIPO DE BATERIA:* Lítio*EQUIPE:* Edeglan e Brunno._________________________________________Segue nota para envia equipe verificar RL-7931219078 equipamento não está fechando em campo somente no ADMS, Feito teste com equipe 104op01 local RL fechar normal porém não sinalizar no AMDS, ficou bay passado até regularização.
A4: ETO-RD-PA 00583/2026 | D4: RELIGADOR | E4: ILEGÍVEL | J4: 2026 | K4: COI | L4: ETO-RD-PA | M4: AL06060122 | N4: 7905320122 | O4: 790866 | P4: 8875822 | Q4: 190-17421383 | R4: EMERGENCIAL | S4: SS PENDENTE | T4: 46282.355 | V4: 46285.355 | W4: RELIGADOR DE LINHA - 27kV | X4: PALMAS | Y4: DIOMAR FERREIRA PEREIRA | Z4: URBANO | AA4: INDISPONIBILIDADE PARA OPERAÇÃO | AB4: Segue nota para verificar falha sinalização status religador 7905320122 - rdu- Palmas .Pendência: chave de entrada fase b do religador danificado impossível de fazer manobra. Favor abrir a nota pra trocar a mesma e verificar as outras. Não foi possível fazer os testes funcionais.
A5: ETO-COEP 00197/2026 | J5: 2026 | K5: MANUT | L5: ETO-COEP | M5: AL01015049 | N5: 7908705049 | O5: 998978 | P5: 8589651 | Q5: 190-17414963 | R5: PROGRAMAVEL | S5: SS PENDENTE | T5: 46278.629 | V5: 46678.629 | W5: BLOCO RELIGADOR DE LINHA | X5: AURORA DO TOCANTINS | Y5: Lorrane Sousa Gonçalves | Z5: RURAL | AA5: INDISPONIBILIDADE PARA OPERAÇÃO | AB5: COCMS 13/09EQUIPAMENTO ENTREGUE VEIO ERRADO. NÃO TEM SUPORTE DE FIXAÇÃO.EQUIPAMENTO ENTREGUE, SOLICITO PREVISÃO PARA SUBSTITUIÇÃO:PARECER COEP: PREVISÃO DE ENTREGA AOS COCM'S 01/07Manutenção no RL 7908705049PARECER DMSL(28/08/2025): Equipe foi fazer manutenção no RL e constatou que o tanque e o relé do mesmo se encontra queimado, providenciar substituição.PARECER COCMS 30/04/2026CRIADO OBRA 0512600135 PARA REQUISIÇÃO MATERIAL
A6: ETO-COEP 00195/2026 | D6: RELIGADOR | E6: COMANDO DE RELIGAMENTO COM FALHA | J6: 2026 | K6: COI | L6: ETO-COEP | M6: LD02010153 | N6: 7949808058 | O6: 717238 | P6: 9203805 | Q6: 190-25330474 | R6: EMERGENCIAL | S6: SS PENDENTE | T6: 46274.355 | V6: 46277.355 | W6: RELIGADOR DE LINHA - 38kV | X6: SANTA FE DO ARAGUAIA | Y6: DIONES COSTA SILVA | Z6: RURAL | AA6: INDISPONIBILIDADE PARA OPERAÇÃO | AB6: 16/09/2026 PARECER COEP: EQUIPAMENTO EM PROCESSO DE AQUISIÇÃOSTATUS : PREVISÃO DE SUBSTITUIÇÃO ATÉ DIA 13/11/2026PARECER DMSL: FEEDBACK EQUIP. ESPECIAISNº DO EQUIPAMENTO: 7949808058TIPO EQUIPAMENTO: Noja RC 10TIPO DE COMUNICAÇÃO: Terminal Orbicom DATA DA MANUTENÇÃO: 31/08/2026SID: 5446/2026SERVIÇO EXECUTADO: _Foi constatado que o tanque está danificado o mesmo não está abrindo pelo controle local e nem pelo bloqueio mecânico.FICOU EM OPERAÇÃO?: NãoPENDÊNCIA: Sim. Repassar nota para o DCMD substituir a parte ativa do equipamento.DADOS DIVERGENTES DA PROGRAMAÇÃO: NãoBATERIA SUBSTITUÍDA?: NaoTIPO DE BATERIA: Lítio EQUIPE: Edeglan e Brunno.___________________________________________SEGUE SS PARA VERIFICAR ANOMALIA NO RL 7949808058 NA LD ARAPOEMA / SANTA FÉ ANOMALIA: FOI FEITO PRIMEIRO ATAQUE, COMUNICAÇÃO DO RL NÃO VOLTOU E AO TENTAR EXECUTAR COMANDO LOCAL DE ABERTURA O MESMO NÃO ABRIU, FOI FEITO TENTATIVA DE ABERTURA MECANICA (PELA ARGOLA) E O MESMO NÃO ABROU. POR GENTILEZA VERIFICAR
A7: ETO-COEP 00187/2026 | J7: 2026 | K7: SCADA | L7: ETO-COEP | M7: AL01065015 | N7: 5800859011 | O7: 797626 | P7: 9011795 | Q7: 190-15786844 | R7: EMERGENCIAL | S7: SS PENDENTE | T7: 46261.398 | V7: 46264.398 | W7: REGULADOR DE TENSAO DE DIST. - 13.8 | X7: TUPIRAMA | Y7: LARA SOARES FARIAS | Z7: RURAL | AA7: INDISPONIBILIDADE PARA OPERAÇÃO | AB7: 04/09/2026 PARECER COEP: EQUIPAMENTO EM LOGISTICA , AGUARDANDO A GERAÇÃO DE OBRA EM ABERTURA CONTÁBIL PELO COCM*FEEDBACK EQUIP. ESPECIAIS**Nº DO EQUIPAMENTO:* 5800859011*TIPO EQUIPAMENTO:* RT ITB RUA 01*TIPO DE COMUNICAÇÃO:* Rádio GE IP*DATA DA MANUTENÇÃO:* 13/08/2026*SID:* 4877/2026*DESCRIÇÃO:* Retrofit, realizado instalação dos cabos compatibilizadores, porém fase A e B apresentaram defeito durante dos testes funcionais, fase A só comuta 14 TAP, fase B com corrente do comutador interna solto, N° série 3634 fase A, N° série 3627*FICOU EM OPERAÇÃO?:* Não*PENDÊNCIA:* Solicitar a substituição ao DCMD das células fase A e B*DADOS DIVERGENTES DA PROGRAMAÇÃO:* *BATERIA SUBSTITUÍDA?:* Não*TIPO DE BATERIA:* Chumbo*EQUIPE:* Edicleber e AdeiltonOBS: Nota ETO-TELE 01037/2026, baixada indevidamente.
A8: ETO-COEP 00168/2026 | D8: RELIGADOR | J8: 2026 | K8: COPC | L8: ETO-COEP | M8: AL02033047 | N8: 7908196047 | O8: 698485 | P8: 8657287 | Q8: 190-19172792 | R8: ALTA | S8: SS PENDENTE | T8: 46237.704 | V8: 46297.704 | W8: BLOCO RELIGADOR DE LINHA | X8: FIGUEIROPOLIS | Y8: Leonardo Sousa de Lima | Z8: RURAL | AA8: INDISPONIBILIDADE PARA OPERAÇÃO | AB8: 03/08/2026 PARECER DMSL: FOI CONFIRMADO PELO VONES DO DCMD QUE O EQUIPAMENTO AINDA NÃO FOI SUBSTITUÍDO. FAVOR, APÓS SUBSTITUIÇÃO, REPASSAR A NOTA PARA A PROTEÇÃO PARA REVISAR OS AJUSTES, POIS TRATA-SE DE ALTERAÇÃO DO MODELO DO EQUIPAMENTO.13/07/2026 PARECER COEP: EQUIPAMENTO REMANEJADO FAVOR FAZER O COMISSIONAMENTORELIGADOR N° 7908196047 REMANEJADO NA OBRA 0402401150 GENTILEZA, REALIZAR O COMISSIONAMENTO. LAUDO EM ANEXO. COORD EO: 698485, 8657287PARECER DA PROTEÇÃO:AJUSTE DISPONIBILIZADO NO APP DA PROTEÇÃO, NOTA REPASSADA PARA DMSL COMISSIONAR, POLO GURUPI, RL APENAS REMANEJADO DA REDE VELHA PARA REDE NOVA, EQUIPAMENTO COOPER, SE MANTEVE O MESMO NÚMERO DE ATIVO.ENG° IRLLEY CASTELO BRANCO.PARECER DMSL: Constatado curto-circuito no tanque do religador, impedindo as operações de abertura e fechamento do equipamento. Solicita-se a substituição completa do religador, incluindo tanque e unidade de controle.
A9: ETO-COEP 00164/2026 | D9: REGULADOR DE TENSÃO | J9: 2026 | K9: COPC | L9: ETO-COEP | M9: LD03005098 | N9: 5858783119 | O9: 845266 | P9: 9339297 | Q9: 190-57123183 | R9: ALTA | S9: SS PENDENTE | T9: 46234.698 | V9: 46294.698 | W9: REGULADOR DE TENSAO DE DIST. - 34.5 | X9: SAO BENTO DO TOCANTINS | Y9: Thais Jordanna Jesus Silva | Z9: RURAL | AA9: INDISPONIBILIDADE PARA OPERAÇÃO | AB9: 04/09/2026 PARECER COEP: EQUIPAMENTO SELECIONADO PARA REFORMA PARECER DMSL 31/07/2026: RT 5858783119 SE ECONTRA NA MESMA SITUAÇÃO INFORMADA NO DIA 16/06/2026. FAVOR, REGULARIZAR A SITUAÇÃO DO EQUIPAMENTO, SUBSTITUINDO OS 3 TANQUES E INSTALAR NOVOS PARA-RAIOS.27/07/2026 PARECER COEP: FIZEMOS UMA VISITA AO EQUIPAMENTO , EQUIPAMENTO SE ENCONTRA EM OPERAÇÃO E SEM SINAL DE AVARIA FAVOR AVALIAR PARECER DMSL A SS FOTOS COM O LUANDERSSON OU JOAO ANTONIO LAGARES 20/07 PARECER COEP: EQUIPAMENTO SELECIONADO PARA COMPRA , DEVIDO AO ERRO NA INSTALAÇÃO E O FURTOPARECER DMSL: 16/06/2025-SERVIÇO EXECUTADO: Ao chegar no equipamento para realizar comissionamento, foi constatato que as 3 células estavam com a tampa de inspeção abertas e sem os para-raios. Constatado também que foi furtado todo o óleo isolante das 3 células, sendo necessário a substituição das 3 células. FICOU EM OPERAÇÃO?: Não PENDÊNCIA: Substituir as 3 células
A10: ETO-COEP 00160/2026 | D10: REGULADOR DE TENSÃO | J10: 2026 | K10: COPC | L10: ETO-COEP | M10: LD04002091 | N10: 5856156091 | O10: 899501 | P10: 8714782 | Q10: 190-38238593 | R10: PROGRAMAVEL | S10: SS PENDENTE | T10: 46230.87 | V10: 46630.87 | W10: REGULADOR DE TENSAO DE DIST. - 34.5 | X10: ALMAS | Y10: Leonardo Sousa de Lima | Z10: RURAL | AA10: INDISPONIBILIDADE PARA OPERAÇÃO | AB10: 27/07/2026 PARECER COEP: EQUIPAMENTO SELECIONADO PARA COMPRA,PORÉM PODEMOS DESATIVAR DE ACORDO COM A ASPODCMD 26.03.2026. SS REPASSADA PARA COEP PROVIDENCIAR MATERIAL. NÃO TEMOS O MATERIAL EM ESTOQUE PARA SUBSTITUIÇÃO. COEP: Equipamento fornecido ao COCM-S para regularização.PARECER COEP: EQUIPAMENTOS JÁ FORNECIDOS PARA OS COCM'S PARA REGULARIZAÇÃOPARECER DA PROTEÇÃO:EQUIPAMENTOS FURTADOS. PARA AQUISIÇÃO DAS CELULAS DE REPOSIÇÃO, FAVOR CONSULTAR OS DADOS DE PLACA EM ANEXO.PARECER DA PROTEÇÃO:COMISISONAR RT 5856156091 LD DIANOPOLIS A NATIVIDADE. NECESSARIO REALIZAR MEDIÇÕES DA RESISTENCIA DA MALHA DE ATERRAMENTO.AJUSTES DISPONIVEIS NO APP DA PROTEÇÃO.RELIGADOR N° 5856156091 INSTALADO NA OBRA 0502400526 GENTILEZA, REALIZAR O COMISSIONAMENTO. LAUDO EM ANEXO. COORD EO: 899501, 8714782
A11: ETO-COEP 00159/2026 | D11: RELIGADOR | J11: 2026 | K11: COPC | L11: ETO-COEP | M11: LD01047073 | N11: 7919270014 | O11: 617420 | P11: 8830790 | Q11: 190-17407946 | R11: ALTA | S11: SS PENDENTE | T11: 46230.863 | V11: 46290.863 | W11: BLOCO RELIGADOR DE LINHA | X11: LAGOA DA CONFUSAO | Y11: Leonardo Sousa de Lima | Z11: RURAL | AA11: INDISPONIBILIDADE PARA OPERAÇÃO | AB11: 27/07/2026 PARECER COEP: EM PROCESSO DE AQUISIÇÃO , COMPLETOPARECER COEP: AGUARDANDO RETORNO DO DMSL, EQUIPAMENTO FOI INSTALADO NOVO NA OBRA 0212501060, ENTENDER O PORQUE NÃO FOI REALIZADO COMISSIONAMENTOPARECER DMSL: Substituir Equipamento completo problema na placa de alimentação e na parte ativa, falta colocar placa de identificação correta na topologia, baixar o controle.Equipamento ficou em operação?: naoPendência: simBateria(s) substituída(s)? NÃOEquipe: Kaique/ Benvindo13/07/2026 PARECER COEP: SUBSTITUIÇÃO REALZIADA , FAVOR COMISSIONARPARECER DMSL (22/07/26): Solicito que o laudo de substituição seja anexado, e a SS seja repassada para proteção atribuir a ordem de ajuste, antes de repassar para ETO-TELE.----------------------------------------------PARECER DA PROTEÇÃO: Prosseguir com o comissionamento. Ajustes de religador permanecem os mesmos, disponíveis no APP da Proteção.********************************RELIGADOR N°7919270014 REMANEJADO NA OBRA 0212501060 GENTILEZA, REALIZAR O COMISSIONAMENTO. LAUDO EM ANEXO. COORD EO: 617422, 8830787
A12: ETO-COEP 00158/2026 | J12: 2026 | K12: SCADA | L12: ETO-COEP | M12: LD05002091 | N12: 5862236091 | O12: 914121 | P12: 8704596 | Q12: 190-52618825 | R12: PROGRAMAVEL | S12: SS PENDENTE | T12: 46230.858 | V12: 46630.858 | W12: REGULADOR DE TENSAO DE DIST. - 34.5 | X12: ALMAS | Y12: LARA SOARES FARIAS | Z12: RURAL | AA12: INDISPONIBILIDADE PARA OPERAÇÃO | AB12: 11/09/2026 PARECER COEP: FOI ALINHADO COM O LEANDRO QUE UTILIZAMOS AS DUAS CELULAS PRA OUTRA OBRA DE CONSTRUÇÃO LOGO NÃO VAMOS CONSEGUIR MANUTENCIONAR ESSE RT ESSE ANO04/09 PARECER COEP: EQUIPAMENTO EM LOGISTICA , UTILIZAREMOS 1/2 CÉLULAS QUE ESTAVAM COM DIONES27/07 PARECER COEP: PEÇAS REDIRECIONADAS 5856070091 PRIORIDADE MAIOR20/07 PARECER COEP: EQUIPAMENTO ENTREGUE , FAVOR EDITAR A SS COM A DATA PREVISTA DE SUBSTITUIÇÃO NO PARECER DOS COCM´S Realizar substituição da FASE B.Célula da fase B estava com a tampa do contador de tape aberta, pegou chuva e molhou os contatos danificando a peça toda.
A13: ETO-COEP 00157/2026 | D13: RELIGADOR | E13: INSPEÇÃO VISUAL | J13: 2026 | K13: COI | L13: ETO-COEP | M13: LD02010021 | N13: 7927713200 | O13: 794667 | P13: 8603359 | Q13: 190-17337960 | R13: EMERGENCIAL | S13: SS PENDENTE | T13: 46230.823 | V13: 46233.823 | W13: BLOCO RELIGADOR DE LINHA | X13: SAO SALVADOR DO TOCANTINS | Y13: VINICIUS DE MORAIS NERY | Z13: RURAL | AA13: INDISPONIBILIDADE PARA OPERAÇÃO | AB13: segue SS para REALIZAR SUBSTITUIÇÃO DO TANQUE do RL 7927713200 danificado , com equipe de manutencao tensao 34,5kv mesmo atende Povoado retiro na rural de sao salvador .
A14: ETO-RD-DP 00479/2026 | J14: 2026 | K14: COI | L14: ETO-RD-DP | M14: LD04002091 | N14: 5856070091 | O14: 905857 | P14: 8717852 | Q14: 190-55087821 | R14: BAIXA | S14: SS PENDENTE | T14: 46230.725 | V14: 46410.725 | W14: REGULADOR DE TENSAO DE DIST. - 34.5 | X14: ALMAS | Y14: LEONARDO SIQUEIRA AMORIM | Z14: RURAL | AA14: INDISPONIBILIDADE PARA OPERAÇÃO | AB14: PARECER DMSL: não foi regularizado a instalação do equipamento, nota repassada conforme alinhado com o supervisor.____________________________________________COCMS 26.03.26. SS REPASSADA PARA COEP PROVIDENCIAR MATERIAL. NÃO TEMOS AS PÇ EM ESTOQUE PARA FAZER A SUBSTITUIÇÃO. Solicitação de serviço para reposição de equipamentos furtados .COEP: Equipamento fornecido ao COCM-S para regularização.COCMS: Equipamento substituido conforme solicitado. Gentileza comissionar.PARECER DA PROTEÇÃO:SEGUE NOTA REPASSADA PARA DMSL COMISSIONAR.ENG° IRLLEY CASTELO BRANCOPARECER DMSL(23/09/2025): Feito a parte de comunicação, fechando enlace, configuração do rádio GE. Feito a medição de aterramento. Após uma inspeção, foi identificado que o regulador de tensão está instalado errado, carga está para o lado de fonte e fonte está do lado de carga. O certo é a fonte vim de almas, atualmente está vindo de natividade. Favor fazer a instalação correta.
