Workbook
Name embs4: 'Ajustes Reguladores de Tensão'!$L$140
Name embs4: 'Ajustes Reguladores de Tensão'!$L$63

Sheet 1007ALLan
A1: Ativo | B1: Tipo | C1: Localidade | D1: Polo | E1: Regional | F1: SS aberta | G1: Parecer COEP | H1: Observação | I1: Check de concluídas | J1: Defeito identificado | K1: Descrição SS | L1: Premissa 1 | M1: Premissa 2 | N1: Premissa 3 | O1: Premissa 4 | P1: Premissa 5 | Q1: Premissa 6 | R1: Premissa 7 | S1: Premissa 8 | T1: Priorização | U1: Criticidade | V1: Observação após análise | X1: Legenda
A2: 7923673004 | B2: =MID(Table12[[#This Row],[Ativo]],1,2) -> 79 | C2: ARAGUAINA | D2: ARAGUAINA | E2: NORTE | F2: =IFERROR(_xlfn.XLOOKUP(Table12[[#This Row],[Ativo]],[2]!Pendentes[COD_RELIGADOR],[2]!Pendentes[SS_ORIGINAL]),"CONCLUÍDA") -> ETO-COEP 00124/2026 | G2: Aguardando atualização de informação DMSL | K2: =IFERROR(_xlfn.XLOOKUP(Table12[[#This Row],[Ativo]],[2]!Pendentes[COD_RELIGADOR],[2]!Pendentes[DESCRICAO]),"") -> PARECER COEP: Verificar Disponibilidade de equipamento no Scada e enviar modelo e tensão para a compra.RELIGADOR COM RELÉ DANIFICADO, REALIZAR SUBSTITUIÇÃO | L2: 15 | M2: 20 | N2: 15 | O2: 15 | P2: 15 | Q2: 10 | R2: 0 | S2: 15 | T2: =SUM(Table12[[#This Row],[Premissa 1]:[Premissa 8]]) -> 105 | U2: Muito Alta | V2: Transferência de cargas na RDU de Araguaína (2797 UCs) | X2: (*) | Y2: Não houve ataque do DMSL
A3: 7947203070 | B3: =MID(Table12[[#This Row],[Ativo]],1,2) -> 79 | C3: RIO SONO | D3: TAQUARALTO | E3: CENTRO | F3: =IFERROR(_xlfn.XLOOKUP(Table12[[#This Row],[Ativo]],[2]!Pendentes[COD_RELIGADOR],[2]!Pendentes[SS_ORIGINAL]),"CONCLUÍDA") -> ETO-COEP 00131/2026 | G3: Aguardando atualização de informação DMSL | H3: DMSL verificando sobre as placas em estoque | K3: =IFERROR(_xlfn.XLOOKUP(Table12[[#This Row],[Ativo]],[2]!Pendentes[COD_RELIGADOR],[2]!Pendentes[DESCRICAO]),"") -> 13/07 PARECER COEP: SELECIONADO PARA COMPRA CONTROLE favor verificar RL 7947203070, sem comunicaçao, feito 1° ataque pela equipe 070OP01 e nao retornou a comunicaçao , linformaçao no Scada de bateria.PARECER DMSL: Foi feito análise técnica, a placa do equipamento está queimada nessesario subistituir o equipamento completo -Carliel e Benvindo-05/02 | L3: 10 | M3: 20 | N3: 15 | O3: 15 | P3: 15 | Q3: 10 | R3: 0 | S3: 15 | T3: =SUM(Table12[[#This Row],[Premissa 1]:[Premissa 8]]) -> 100 | U3: Muito Alta | V3: Transferência da RDU de Lizarda (1650 UCs) para fonte alternativa
A4: 7903569004 | B4: =MID(Table12[[#This Row],[Ativo]],1,2) -> 79 | C4: ARAGUAINA | D4: ARAGUAINA | E4: NORTE | F4: =IFERROR(_xlfn.XLOOKUP(Table12[[#This Row],[Ativo]],[2]!Pendentes[COD_RELIGADOR],[2]!Pendentes[SS_ORIGINAL]),"CONCLUÍDA") -> ETO-COEP 00152/2026 | G4: Aguardando atualização de informação DMSL | K4: =IFERROR(_xlfn.XLOOKUP(Table12[[#This Row],[Ativo]],[2]!Pendentes[COD_RELIGADOR],[2]!Pendentes[DESCRICAO]),"") -> PARECER COEP 28/07/2026 : EQUIPAMENTO SELECIONADO PARA COMPRAEquipamento baypassado PARECER DMSL em 12/03: Realizar substituição do equipamento todo e parte ativa. | L4: 15 | M4: 20 | N4: 5 | O4: 15 | P4: 15 | Q4: 10 | R4: 0 | S4: 15 | T4: =SUM(Table12[[#This Row],[Premissa 1]:[Premissa 8]]) -> 95 | U4: Muito Alta | V4: Transferência dos bairros JD Santa Helena, Jd Filadelfiae Setor Caraja em Araguaína (2053 UCs), AL 254R de AR I e AL 214R de AR III
A5: 7927413001 | B5: =MID(Table12[[#This Row],[Ativo]],1,2) -> 79 | C5: PORTO NACIONAL | D5: PORTO NACIONAL | E5: CENTRO | F5: =IFERROR(_xlfn.XLOOKUP(Table12[[#This Row],[Ativo]],[2]!Pendentes[COD_RELIGADOR],[2]!Pendentes[SS_ORIGINAL]),"CONCLUÍDA") -> ETO-COEP 00141/2026 | G5: Aguardando atualização de informação DMSL | H5: DMSL verificando sobre as placas em estoque | K5: =IFERROR(_xlfn.XLOOKUP(Table12[[#This Row],[Ativo]],[2]!Pendentes[COD_RELIGADOR],[2]!Pendentes[DESCRICAO]),"") -> 22/07/2026 EQUIPAMENTO SLEECIONADO PARA COMPRAPARECER DMSL: *Segue feedback**Equipamento:* RLG 7927413001 *RELÉ TAVRIDA*Data:* 16/04/2026*SID:* 1817/2026*Serviço executado:* Placa de alimentação do equipamento com defeito, VERIFICAR SE É POSSIVEL substituir o equipamento completo.*Equipamento ficou em operação?*_Não*Pendência:*_Sim*Bateria(s) substituída(s)?*_Nao *Equipe:* Benvindo e Kaique-------------------------------------------------------------------------------------------------Religador 7927413001 sem comunicação foi realizado primeiro ataque porem a comunicação não retornou. Favor enviar equipe para devidas trattivas | L5: 15 | M5: 5 | N5: 15 | O5: 15 | P5: 15 | Q5: 10 | R5: 0 | S5: 15 | T5: =SUM(Table12[[#This Row],[Premissa 1]:[Premissa 8]]) -> 90 | U5: Muito Alta | V5: Transferência do Distrito Ind de Porto Nacional e GAs
A6: 7925871077 | B6: =MID(Table12[[#This Row],[Ativo]],1,2) -> 79 | C6: GOIATINS | D6: ARAGUAINA | E6: NORTE | F6: =IFERROR(_xlfn.XLOOKUP(Table12[[#This Row],[Ativo]],[2]!Pendentes[COD_RELIGADOR],[2]!Pendentes[SS_ORIGINAL]),"CONCLUÍDA") -> ETO-COEP 00048/2026 | G6: Aguardando atualização de informação DMSL | K6: =IFERROR(_xlfn.XLOOKUP(Table12[[#This Row],[Ativo]],[2]!Pendentes[COD_RELIGADOR],[2]!Pendentes[DESCRICAO]),"") -> 27/07 PARECER COEP: EM PROCESSO DE AQUISIÇÃOPARECER DMSL: A PEDIDO DA PCM DO NORTE LARA SOARES REALIZEI A CRIAÇÃO DESSA SS, EM RAZAO DA ANTIGAETO-TELE 337/2026 QUE FOI BAIXADA POR ENGANO DE TAL FORMA SEGUE A MESMA PARA REALIZAR AS TRATATIVAS. PENDENCIA: Religador continua by passado, equipamento está com defeito na parte ativa | L6: 15 | M6: 10 | N6: 15 | O6: 15 | P6: 15 | Q6: 10 | R6: 0 | S6: 0 | T6: =SUM(Table12[[#This Row],[Premissa 1]:[Premissa 8]]) -> 80 | U6: Muito Alta | V6: Transferência de Goiatins e GAs (2492 UCs)
A7: 7908302256 | B7: =MID(Table12[[#This Row],[Ativo]],1,2) -> 79 | C7: MATEIROS | D7: PONTE ALTA TOCANTINS | E7: CENTRO | F7: =IFERROR(_xlfn.XLOOKUP(Table12[[#This Row],[Ativo]],[2]!Pendentes[COD_RELIGADOR],[2]!Pendentes[SS_ORIGINAL]),"CONCLUÍDA") -> CONCLUÍDA | G7: Aguardando atualização de informação DMSL | H7: ETO-TELE 970/2026 concluída e equipamento fora de operação | K7: =IFERROR(_xlfn.XLOOKUP(Table12[[#This Row],[Ativo]],[2]!Pendentes[COD_RELIGADOR],[2]!Pendentes[DESCRICAO]),"") | L7: 5 | M7: 10 | N7: 5 | O7: 15 | P7: 15 | Q7: 10 | R7: 0 | S7: 15 | T7: =SUM(Table12[[#This Row],[Premissa 1]:[Premissa 8]]) -> 75 | U7: Alta | V7: Isolação de trecho e transferência das cidades de São Felix e Mateiros para gerador, além de atendimento de clientes rurais
A8: 7903112004 | B8: =MID(Table12[[#This Row],[Ativo]],1,2) -> 79 | C8: ARAGUAINA | D8: ARAGUAINA | E8: NORTE | F8: =IFERROR(_xlfn.XLOOKUP(Table12[[#This Row],[Ativo]],[2]!Pendentes[COD_RELIGADOR],[2]!Pendentes[SS_ORIGINAL]),"CONCLUÍDA") -> ETO-COEP 00184/2025 | G8: Aguardando atualização de informação DMSL | H8: 1 tanque NOJA sobrando | I8: Em andamento | J8: Tanque cooper | K8: =IFERROR(_xlfn.XLOOKUP(Table12[[#This Row],[Ativo]],[2]!Pendentes[COD_RELIGADOR],[2]!Pendentes[DESCRICAO]),"") -> 20/07 PARECER COEP: EQUIPAMENTO SELECIONADO PARA COMPRAApós testes no RLG 7903112004 foi constatado defeito no mesmo e como se trata de um modelo COOPER FORM6 que está obsoleto e não possuímos peças sobressalentes, faz-se necessária substituição completa por modelo NOJA RC10. | L8: 15 | M8: 10 | N8: 5 | O8: 15 | P8: 0 | Q8: 10 | R8: 0 | S8: 0 | T8: =SUM(Table12[[#This Row],[Premissa 1]:[Premissa 8]]) -> 55 | U8: Alta | V8: Transferência de Babaçulândia, 4 RLs sendo 2 operando
A9: 7920024127 | B9: =MID(Table12[[#This Row],[Ativo]],1,2) -> 79 | C9: PALMEIRAS DO TOCANTINS | D9: TOCANTINOPOLIS | E9: NORTE | F9: =IFERROR(_xlfn.XLOOKUP(Table12[[#This Row],[Ativo]],[2]!Pendentes[COD_RELIGADOR],[2]!Pendentes[SS_ORIGINAL]),"CONCLUÍDA") -> ETO-COEP 00120/2025 | G9: Aguardando atualização de informação DMSL | H9: DMSL verificando problema na parte ativa e comunicação | J9: Tanque, relé e chave | K9: =IFERROR(_xlfn.XLOOKUP(Table12[[#This Row],[Ativo]],[2]!Pendentes[COD_RELIGADOR],[2]!Pendentes[DESCRICAO]),"") -> 30/06 PARECER COEP: AGUARDANDO O RETORNO DO DMSL , PARA ENTENDER SE O PROBLEMA É NA COMUNICAÇÃO OU PARTE ATIVA, JÁ QUE O EQUIPAMENTO EM QUESTÃO SEGUE COMUNICANDOPARECER DMSL: Após testes, equipe DMSL constatou que o relé e a parte ativa do equipamento 7920024127 estão com defeito, sendo necessária a substituição completa por um modelo NOJA RC 10. Favor, subsituir também a chave de saída da fase A que está com o anel de abertura quebrado.RL 7920024127 está desarmando em campo e no SCADA continua fechado, só sinaliza aberto no SCADA quando a equipe faz o resert no equipamento em campo. | L9: 15 | M9: 10 | N9: 5 | O9: 15 | P9: 0 | Q9: 10 | R9: 0 | S9: 0 | T9: =SUM(Table12[[#This Row],[Premissa 1]:[Premissa 8]]) -> 55 | U9: Alta | V9: Transferência de Palmeiras, 3 fontes operando
A10: 7930428001 | B10: =MID(Table12[[#This Row],[Ativo]],1,2) -> 79 | C10: PORTO NACIONAL | D10: PORTO NACIONAL | E10: CENTRO | F10: =IFERROR(_xlfn.XLOOKUP(Table12[[#This Row],[Ativo]],[2]!Pendentes[COD_RELIGADOR],[2]!Pendentes[SS_ORIGINAL]),"CONCLUÍDA") -> ETO-COEP 00150/2026 | G10: Aguardando atualização de informação DMSL | J10: Tanque | K10: =IFERROR(_xlfn.XLOOKUP(Table12[[#This Row],[Ativo]],[2]!Pendentes[COD_RELIGADOR],[2]!Pendentes[DESCRICAO]),"") -> PARECER DMSL DATA 16/07/2026: será necessário fazer a substituição da parte ativa do equipamento.PARECER COEP: Equipamento Funcionando no SCADA , favor reavaliar a necessidade de substituição e se necessário mandar o modelo do equipamento.Segue nota para substituir Taque do RL-7930428001 na LD Porto Nacional / São João, Identificado pela Int-20253617520441 equipamento dando passagem na fase A ficou bay-passado até substituição, Tensão 34,5kva, Acesso livre. | L10: 5 | M10: 5 | N10: 15 | O10: 0 | P10: 15 | Q10: 10 | R10: 0 | S10: 0 | T10: =SUM(Table12[[#This Row],[Premissa 1]:[Premissa 8]]) -> 50 | U10: Alta | V10: Transferência dos Grupos A - Ramal do Rossato (TF 225kVA e TF 750kVA)
A11: 7936038076 | B11: =MID(Table12[[#This Row],[Ativo]],1,2) -> 79 | C11: DUERE | D11: GURUPI | E11: SUL | F11: =IFERROR(_xlfn.XLOOKUP(Table12[[#This Row],[Ativo]],[2]!Pendentes[COD_RELIGADOR],[2]!Pendentes[SS_ORIGINAL]),"CONCLUÍDA") -> CONCLUÍDA | G11: Aguardando atualização de informação DMSL | J11: Tanque | K11: =IFERROR(_xlfn.XLOOKUP(Table12[[#This Row],[Ativo]],[2]!Pendentes[COD_RELIGADOR],[2]!Pendentes[DESCRICAO]),"") | L11: 5 | M11: 5 | N11: 15 | O11: 0 | P11: 15 | Q11: 10 | R11: 0 | S11: 0 | T11: =SUM(Table12[[#This Row],[Premissa 1]:[Premissa 8]]) -> 50 | U11: Alta | V11: Transferência do Grupo A - Xavante (TF 1087,5 kVA) e outros GA menores
A12: 7943790134 | B12: =MID(Table12[[#This Row],[Ativo]],1,2) -> 79 | C12: ESPERANTINA | D12: AUGUSTINOPOLIS | E12: NORTE | F12: =IFERROR(_xlfn.XLOOKUP(Table12[[#This Row],[Ativo]],[2]!Pendentes[COD_RELIGADOR],[2]!Pendentes[SS_ORIGINAL]),"CONCLUÍDA") -> ETO-TELE 00896/2026 | G12: Aguardando comissionamento | J12: Tanque | K12: =IFERROR(_xlfn.XLOOKUP(Table12[[#This Row],[Ativo]],[2]!Pendentes[COD_RELIGADOR],[2]!Pendentes[DESCRICAO]),"") -> PARECER DCMD:Serviço realizado , substituição da parte ativa do RELIGADOR 7943790134 - Favor realizar comissionamento | L12: 15 | M12: 10 | N12: 5 | O12: 15 | P12: 15 | Q12: 10 | R12: 0 | S12: 15 | T12: =SUM(Table12[[#This Row],[Premissa 1]:[Premissa 8]]) -> 85 | U12: Muito Alta | V12: Transferência de Esperantina, fonte principal operando
A13: 5856070091 | B13: =MID(Table12[[#This Row],[Ativo]],1,2) -> 58 | C13: ALMAS | D13: DIANOPOLIS | E13: SUL | F13: =IFERROR(_xlfn.XLOOKUP(Table12[[#This Row],[Ativo]],[2]!Pendentes[COD_RELIGADOR],[2]!Pendentes[SS_ORIGINAL]),"CONCLUÍDA") -> ETO-RD-DP 00479/2026 | G13: Aguardando confirmação em campo sobre o equipamento | H13: Conexão invertida entre fonte e carga | J13: Conexão invertida | K13: =IFERROR(_xlfn.XLOOKUP(Table12[[#This Row],[Ativo]],[2]!Pendentes[COD_RELIGADOR],[2]!Pendentes[DESCRICAO]),"") -> PARECER DMSL: não foi regularizado a instalação do equipamento, nota repassada conforme alinhado com o supervisor.____________________________________________COCMS 26.03.26. SS REPASSADA PARA COEP PROVIDENCIAR MATERIAL. NÃO TEMOS AS PÇ EM ESTOQUE PARA FAZER A SUBSTITUIÇÃO. Solicitação de serviço para reposição de equipamentos furtados .COEP: Equipamento fornecido ao COCM-S para regularização.COCMS: Equipamento substituido conforme solicitado. Gentileza comissionar.PARECER DA PROTEÇÃO:SEGUE NOTA REPASSADA PARA DMSL COMISSIONAR.ENG° IRLLEY CASTELO BRANCOPARECER DMSL(23/09/2025): Feito a parte de comunicação, fechando enlace, configuração do rádio GE. Feito a medição de aterramento. Após uma inspeção, foi identificado que o regulador de tensão está instalado errado, carga está para o lado de fonte e fonte está do lado de carga. O certo é a fonte vim de almas, atualmente está vindo de natividade. Favor fazer a instalação correta. | L13: 40 | M13: 20 | N13: 20 | O13: 20 | P13: 0 | Q13: - | R13: - | S13: - | T13: =SUM(Table12[[#This Row],[Premissa 1]:[Premissa 8]]) -> 100 | U13: Muito Alta | V13: Atendimento da região da Engegold, Nativa, cidade Natividade e Chapada da Natividade
A14: 5803327001 | B14: =MID(Table12[[#This Row],[Ativo]],1,2) -> 58 | C14: PORTO NACIONAL | D14: PORTO NACIONAL | E14: CENTRO | F14: =IFERROR(_xlfn.XLOOKUP(Table12[[#This Row],[Ativo]],[2]!Pendentes[COD_RELIGADOR],[2]!Pendentes[SS_ORIGINAL]),"CONCLUÍDA") -> ETO-COEP 00149/2026 | G14: Aguardando confirmação em campo sobre o equipamento | H14: Foi realizado os serviços apontados pelo DMSL? | J14: Controle e aterramento | K14: =IFERROR(_xlfn.XLOOKUP(Table12[[#This Row],[Ativo]],[2]!Pendentes[COD_RELIGADOR],[2]!Pendentes[DESCRICAO]),"") -> 01/07 PARECER COEP: FOI CONFIRMADO COM A OPERAÇÃO QUE O EQUIPAMENTO SEGUIU O FLUXO INTEIRO DE COMISSIONAMENTO, PROTEÇÃO, FAVOR EXPLICAR O QUE FOI REALIZADO E SE EQUIPAMENTO ESTÁ OPERANDO, SENÃO ESTIVER EXPLICAR O QUE FOI FEITO NELE30/06PARECER COEP: REPASSAR DIRETAMENTE PARA OS COCM'SRegulador 5803327001 fora de operação, by passado em campo com painel de comunicação com cabos desconectados tensão 13.8.parecer DMSL: Feedback Equip. EspeciaisRT 5803327001RELÉ RUASid: 4844Data: 19/09/2025Serviço realizado:*Equipamento foi remanejado, 7 km da sua localização sentido Palmas necessário comissionamento completo*Equipamento com um dos cabos umbilicais danificado.* aterramento bucha FC não esta interligada corretamente * para-raios estão no mesmo aterramento da bucha FC.* Tranques muito alto e próximo da rede não permitindo o comissionamento com segurança.* Controle alto demais tem que baixar Equipamento ficou em operação?: nãoPendência: sim, precisa comissionar completoOBS | L14: 40 | M14: 0 | N14: 0 | O14: 20 | P14: 20 | Q14: - | R14: - | S14: - | T14: =SUM(Table12[[#This Row],[Premissa 1]:[Premissa 8]]) -> 80 | U14: Alta | V14: Em caso de perca da fonte principal é necessário esse RT para alimentação da Frísia
A15: 5854566043 | B15: =MID(Table12[[#This Row],[Ativo]],1,2) -> 58 | C15: SILVANOPOLIS | D15: PORTO NACIONAL | E15: CENTRO | F15: =IFERROR(_xlfn.XLOOKUP(Table12[[#This Row],[Ativo]],[2]!Pendentes[COD_RELIGADOR],[2]!Pendentes[SS_ORIGINAL]),"CONCLUÍDA") -> ETO-PROT 00158/2026 | G15: Em processo de aquisição | J15: 1 célula | K15: =IFERROR(_xlfn.XLOOKUP(Table12[[#This Row],[Ativo]],[2]!Pendentes[COD_RELIGADOR],[2]!Pendentes[DESCRICAO]),"") -> 24/07/2026 - PARECE COCM: EQUIPAMENTO SUBSTITUIDO NA OBRA 0312600352 OS: ETO-RD-PO 1873/202622/07/2026 PARECER COEP: EQUIPAMENTO ENTREGUE AOS COCM´SPRAZO DE 7 DIAS CONTANDO O SLA.PARECER COEP: EQUIPAMENTO ENTREGUE AOS COCM´S FAVOR SUSBSTTUIR , E AGUARDO O PRAZO DE PREVISÃO DE SUBSTIUIÇÃOboa noite,segue SS para as devidas tratativas com equipe de manutenção com apoio de equipe de linha viva substituir regulador de tensão 5854566043 queimado célula fase c, LD Porto / Silvanópolis mesmo deverá ser substituído com apoio de equipe de linha viva PARECER DMSL: Foi realizado inspeção visual e ensaios de isolação, relação de transformação e resistência de enrolamento. A fase B está danificada e será necessário substituir a mesma. Malha de aterramento está relativamente boa e conectada. Fase A e C passaram nos ensaios. Substituir fase B. | L15: 40 | M15: 20 | N15: 20 | O15: 10 | P15: 20 | Q15: - | R15: - | S15: - | T15: =SUM(Table12[[#This Row],[Premissa 1]:[Premissa 8]]) -> 110 | U15: Muito Alta | V15: Aumento de reclamações no atendimento de Silvanópolis por Porto Nacional no período seco (Outra fonte com defeito também)
A16: 7931608059 | B16: =MID(Table12[[#This Row],[Ativo]],1,2) -> 79 | C16: TAQUARALTO | D16: TAQUARALTO | E16: CENTRO | F16: =IFERROR(_xlfn.XLOOKUP(Table12[[#This Row],[Ativo]],[2]!Pendentes[COD_RELIGADOR],[2]!Pendentes[SS_ORIGINAL]),"CONCLUÍDA") -> ETO-COEP 00040/2026 | G16: Em processo de aquisição | J16: Tanque e rádio | K16: =IFERROR(_xlfn.XLOOKUP(Table12[[#This Row],[Ativo]],[2]!Pendentes[COD_RELIGADOR],[2]!Pendentes[DESCRICAO]),"") -> PARECER COEP: EQUIPAMENTO SELECIONADO PARA COMPRADMSL:Serviço Executado: Foi feita uma análise técnica no equipamento, devido à falta de comunicação. Também foi identificado que o tanque do equipamento está danificado, sendo assim, necessário substituir o tanque e o rádio do equipamento, que está queimado, sendo necessário substituir também. | L16: 15 | M16: 20 | N16: 15 | O16: 15 | P16: 15 | Q16: 10 | R16: 0 | S16: 15 | T16: =SUM(Table12[[#This Row],[Premissa 1]:[Premissa 8]]) -> 105 | U16: Muito Alta | V16: Transferência dos bairros Morada do Sol, Vale do Sol, Morada do Sol II, Nova Esperança, Sõa João, Araras I e II e Jardim Laila em Taquaralto (6033 UCs)
A17: 7925744087 | B17: =MID(Table12[[#This Row],[Ativo]],1,2) -> 79 | C17: GOIANORTE | D17: GUARAI | E17: NORTE | F17: =IFERROR(_xlfn.XLOOKUP(Table12[[#This Row],[Ativo]],[2]!Pendentes[COD_RELIGADOR],[2]!Pendentes[SS_ORIGINAL]),"CONCLUÍDA") -> ETO-COEP 00059/2026 | G17: Em processo de aquisição | K17: =IFERROR(_xlfn.XLOOKUP(Table12[[#This Row],[Ativo]],[2]!Pendentes[COD_RELIGADOR],[2]!Pendentes[DESCRICAO]),"") -> PARECER COEP: EQUIPAMENTO SELECIONADO PARA COMPRAPARECER DMSL: FEEDBACK EQUIP. ESPECIAISNº DO EQUIPAMENTO: 7925744087TIPO EQUIPAMENTO: Noja RC 10TIPO DE COMUNICAÇÃO: Radio GE IPDATA DA MANUTENÇÃO: 19/02/2026SID: 735/2026 DESCRIÇÃO: foi identificado água dentro da parte interna do tanque e cabo umbilical encharcado de água foi passado essas informações para COS.FICOU EM OPERAÇÃO?: Não PENDÊNCIA: Sim substituir tanque e cabo umbilicalDADOS DIVERGENTES DA PROGRAMAÇÃO: NãoBATERIA SUBSTITUÍDA?: Não DATA DA BATERIA: 07/05/2025TIPO DE BATERIA: Lítio EQUIPE: Edeglan e Janio-------------------------------------------------------------------------------------------------RELIGADOR SEM COMUNICAÇÃO, APOS PRIMEIRO ATAQUE RETORNA E FICAR INDEFINIDO. | L17: 15 | M17: 20 | N17: 5 | O17: 15 | P17: 15 | Q17: 10 | R17: 0 | S17: 15 | T17: =SUM(Table12[[#This Row],[Premissa 1]:[Premissa 8]]) -> 95 | U17: Muito Alta | V17: Transferência de Goianorte, fonte principal operando
A18: 7900453110 | B18: =MID(Table12[[#This Row],[Ativo]],1,2) -> 79 | C18: SANTA RITA DO TOCANTINS | D18: PORTO NACIONAL | E18: CENTRO | F18: =IFERROR(_xlfn.XLOOKUP(Table12[[#This Row],[Ativo]],[2]!Pendentes[COD_RELIGADOR],[2]!Pendentes[SS_ORIGINAL]),"CONCLUÍDA") -> ETO-COEP 00087/2026 | G18: Em processo de aquisição | H18: Foi redirecionado para priorizar o RL 7933726256 | J18: Tanque | K18: =IFERROR(_xlfn.XLOOKUP(Table12[[#This Row],[Ativo]],[2]!Pendentes[COD_RELIGADOR],[2]!Pendentes[DESCRICAO]),"") -> 10/07/2026 EQUIPAMENTO SELECIONADO PARA COMPRA PARTE ATIVA30/06.PARECER COEP: ALINHADO COM O ALLAN REMANEJAMOS PARTE ATIVA PARA ATENDER 7933726256PARECER COEP: Aproveitar controle cooper se possível em outro local, previsão de chegada do material dia 01/07 para substituiçãoFavor verificar o RL 7900453110, pois o mesmo aceita comando de fechamento, porém fecha em campo e no SCADA continua aberto e só abre através de equipe em campo. Parecer Dmsl:Equipamento está com defeito na parte ativa, não aceita o comando de fechamento. Será necessário substituir o equipamento completo.Equipamento ficou em operação?: _SIM_a pedido do COS ficou em operação, a operação está ciente da necessidade de substituir.Pendência: Sim, será necessário substituir o equipamento. | L18: 15 | M18: 10 | N18: 5 | O18: 15 | P18: 15 | Q18: 10 | R18: 0 | S18: 15 | T18: =SUM(Table12[[#This Row],[Premissa 1]:[Premissa 8]]) -> 85 | U18: Muito Alta | V18: Transferência de Santa Rita, fonte principal operando
A19: 5800371025 | B19: =MID(Table12[[#This Row],[Ativo]],1,2) -> 58 | C19: ARAPOEMA | D19: COLINAS DO TOCANTINS | E19: NORTE | F19: =IFERROR(_xlfn.XLOOKUP(Table12[[#This Row],[Ativo]],[2]!Pendentes[COD_RELIGADOR],[2]!Pendentes[SS_ORIGINAL]),"CONCLUÍDA") -> ETO-TELE 01040/2026 | G19: Em processo de aquisição | J19: Relé e fiquei em duvida sobre kit | K19: =IFERROR(_xlfn.XLOOKUP(Table12[[#This Row],[Ativo]],[2]!Pendentes[COD_RELIGADOR],[2]!Pendentes[DESCRICAO]),"") -> 16/07/2026 PARECER COEP: ALINHADO COM O KELLITON REALIZAR SUBSTITUIÇÃO DO CONTROLE DE TUPIRAMA, ALINHADO COM O JEAN QUE OS CABOS COMPATIBILIZADORES VÃO CHEGAR 16/08 , ATÉ ESSA DATA MANTER ESSA SS E CONTROLE RUA, DEPOIS REPASSAR PARA O DMSLPARECER COEP: AVALIAR COM O LEANDRO, PROVAVELMENTE SÓ COMPRAPARECER DMSL: Após testes foi constatado defeito nos relés da fase A e B, Modelo Toshiba TBR 1000. Se possível, substituir os relés das 3 fases por controle RUA, disponibilizar os cabos de ligação entre o tanque e o controle para possibilitar a compatibilização do equipamento. Fornecer kit de comunicação, rádio, antena, etc.Segue nota para veriifcar falha em regulador de tensão N: 5800371025 dentro S/E Arapoema , equipamento esta com 2 reles com falha marca toshiba .Parecer DCMD: foi substituido célula 30/07/2026. o mesmo está liberado para ser colocado em operação | L19: 0 | M19: 20 | N19: 20 | O19: 10 | P19: 20 | Q19: - | R19: - | S19: - | T19: =SUM(Table12[[#This Row],[Premissa 1]:[Premissa 8]]) -> 70 | U19: Alta | V19: Aumento de reclamações no atendimento de Arapoema no período seco
A20: 7926089013 | B20: =MID(Table12[[#This Row],[Ativo]],1,2) -> 79 | C20: PARAISO DO TOCANTINS | D20: PARAISO DO TOCANTINS | E20: CENTRO | F20: =IFERROR(_xlfn.XLOOKUP(Table12[[#This Row],[Ativo]],[2]!Pendentes[COD_RELIGADOR],[2]!Pendentes[SS_ORIGINAL]),"CONCLUÍDA") -> ETO-COEP 00078/2026 | G20: Em processo de aquisição | J20: Tanque | K20: =IFERROR(_xlfn.XLOOKUP(Table12[[#This Row],[Ativo]],[2]!Pendentes[COD_RELIGADOR],[2]!Pendentes[DESCRICAO]),"") -> PARECER COEP: EQUIPAMENTO SELECIONADO PARA COMPRAPARECER DMSL: Feedback Equip. EspeciaisRLG 7926089013,RELÉ NOJA RC10SID 1805/2026DATA 15/04/2026Serviço Executado: Favor realizar a troca da parte ativa do equipamento --reprogramar para atualizar a base juntamente com escada Equipamento ficou em operação: Não Pendência: sim atualizar a base e subistituir o tanque Bateria(s) substituída(s)? Não Data de Fabricação/Instalação da(s) bateria(s): Equipe: Carliel e João Vitor Fernando e Elson---------------------------------------------------------------------------------ATUALIZAR AJUSTES DO RL 7926089013 LD PARAISO I A PIUM. IMPLEMENTAÇÃO DA FUNÇÃO 27, SUBTENSÃO.AJUSTES DISPONIVEIS NO APP DA PROTEÇÃO. | L20: 15 | M20: 10 | N20: 5 | O20: 15 | P20: 15 | Q20: 10 | R20: 0 | S20: 0 | T20: =SUM(Table12[[#This Row],[Premissa 1]:[Premissa 8]]) -> 70 | U20: Alta | V20: Transferência da RDU de Chapada de Areia (937 UCs) para fonte alternativa
A21: 7927646026 | B21: =MID(Table12[[#This Row],[Ativo]],1,2) -> 79 | C21: PONTE ALTA TOCANTINS | D21: PONTE ALTA TOCANTINS | E21: CENTRO | F21: =IFERROR(_xlfn.XLOOKUP(Table12[[#This Row],[Ativo]],[2]!Pendentes[COD_RELIGADOR],[2]!Pendentes[SS_ORIGINAL]),"CONCLUÍDA") -> ETO-COEP 00029/2026 | G21: Em processo de aquisição | J21: Tanque | K21: =IFERROR(_xlfn.XLOOKUP(Table12[[#This Row],[Ativo]],[2]!Pendentes[COD_RELIGADOR],[2]!Pendentes[DESCRICAO]),"") -> PARECER COEP: EQUIPAMENTO SELECIONADO PARA COMPRARELIGADOR BY PASSADO POR DEFEITO, NECESSÁRIO AVALIAÇÃO DO PROBLEMA.parecer dmsl:O religador apresenta defeito no tanque, sendo necessário substituir o tanque o mesmo está tirando a linha, e troca os isoladores. Quando retornar, trazer uma fonte para o equipamento, a mesma foi removida.FICOU EM OPERAÇÃO? NãoPENDÊNCIA: Sim, aguardando peças para substituição. | L21: 15 | M21: 10 | N21: 5 | O21: 0 | P21: 15 | Q21: 0 | R21: 10 | S21: 0 | T21: =SUM(Table12[[#This Row],[Premissa 1]:[Premissa 8]]) -> 55 | U21: Alta | V21: Opção de isolação de São Félix e Mateiros para alimentação por gerador
A22: 5800859011 | B22: =MID(Table12[[#This Row],[Ativo]],1,2) -> 58 | C22: TUPIRAMA | D22: GUARAI | E22: NORTE | F22: =IFERROR(_xlfn.XLOOKUP(Table12[[#This Row],[Ativo]],[2]!Pendentes[COD_RELIGADOR],[2]!Pendentes[SS_ORIGINAL]),"CONCLUÍDA") -> CONCLUÍDA | G22: Em processo logístico | H22: Aguardando obra COCM | J22: Controle | K22: =IFERROR(_xlfn.XLOOKUP(Table12[[#This Row],[Ativo]],[2]!Pendentes[COD_RELIGADOR],[2]!Pendentes[DESCRICAO]),"") | L22: 40 | M22: 20 | N22: 20 | O22: 10 | P22: 20 | Q22: - | R22: - | S22: - | T22: =SUM(Table12[[#This Row],[Premissa 1]:[Premissa 8]]) -> 110 | U22: Muito Alta | V22: Atendimento de parte da RDU Guaraí por fonte alternativa
A23: 7900117013 | B23: =MID(Table12[[#This Row],[Ativo]],1,2) -> 79 | C23: PARAISO DO TOCANTINS | D23: PARAISO DO TOCANTINS | E23: CENTRO | F23: =IFERROR(_xlfn.XLOOKUP(Table12[[#This Row],[Ativo]],[2]!Pendentes[COD_RELIGADOR],[2]!Pendentes[SS_ORIGINAL]),"CONCLUÍDA") -> ETO-PROT 00154/2026 | G23: Em processo logístico | H23: Previsão de entrega 07/07 | I23: Em andamento | J23: Relé Cooper | K23: =IFERROR(_xlfn.XLOOKUP(Table12[[#This Row],[Ativo]],[2]!Pendentes[COD_RELIGADOR],[2]!Pendentes[DESCRICAO]),"") -> 15/07 PARECER COCM: EQUIPAMENTO FOI SUBSTITUÍDO OBRA 021260042210/07 PARECER COEP: EQUIPAMENTO ENTREGUE AOS COCM´S FAVOR INFORMAR PRAZO DE SUBSTUIÇÃO PARA O DMSL E REPASSAR DEPOIS PARA PROTEÇÃO REALIZAR OS AJUSTES E DESCREVER NA SS O SERVIÇO REALIZADOPARECER COEP: PREVISÃO DE ENTREGA AOS COCM'S 01/07Segue nota para correção de anomalia e provável substituição de religador , religador 7900117013 -RDU - Paraiso .OBS: equipe DMSL Elisfran estava atualizando firmware no equipamento , porém relé parou de funcionar devido essa atualização , sendo necessário sua substituição .em campo o modelo e cooper Form6 , segundo tecnico deve ser substituído por um Noja .Repassado para o COEP para aquisição do equipamento e posterior repasse para o COCM. | L23: 15 | M23: 20 | N23: 15 | O23: 15 | P23: 15 | Q23: 0 | R23: 0 | S23: 15 | T23: =SUM(Table12[[#This Row],[Premissa 1]:[Premissa 8]]) -> 95 | U23: Muito Alta | V23: Transferência do 214R de Paraíso I, Centro Comercial de Paraíso
A24: 7929376022 | B24: =MID(Table12[[#This Row],[Ativo]],1,2) -> 79 | C24: BABACULANDIA | D24: ARAGUAINA | E24: NORTE | F24: =IFERROR(_xlfn.XLOOKUP(Table12[[#This Row],[Ativo]],[2]!Pendentes[COD_RELIGADOR],[2]!Pendentes[SS_ORIGINAL]),"CONCLUÍDA") -> ETO-TELE 01107/2026 | G24: Em processo logístico | H24: Aproveitar tanque sobrando em Palmeirante | I24: Em andamento | K24: =IFERROR(_xlfn.XLOOKUP(Table12[[#This Row],[Ativo]],[2]!Pendentes[COD_RELIGADOR],[2]!Pendentes[DESCRICAO]),"") -> 13/08/2026 PARECER COEP: EQUIPAMENTO FOI TROCADO A PEÇA , CONFIRMAMOS COM O LEONARDO DE ARAGUAÍNA , LAUDO EM ANEXO , FAVOR REALIZAR COMISSIONAMENTOPARECER COEP: PROBLEMA NO ENVIO COCM'S CONTROLE ENVIADO FOI O NOJA , DEVIDO A FALTA DO MODELO NA SS (GRAVE)PARECER DMSL: *FEEDBACK EQUIP. ESPECIAIS**Nº DO EQUIPAMENTO:* 7929376022 *DATA DA MANUTENÇÃO:* 02/04/2026*SID:* 1677/2026*DESCRIÇÃO:* Trocar controle completo*PENDÊNCIA:* Sim.*DADOS DIVERGENTES DA PROGRAMAÇÃO:* Não*BATERIA SUBSTITUÍDA?:* Não*EQUIPE:* Adeilton e Edicleber __________________________________________________________POR GENTILEZA ATENDER SOLICITAÇÃO PRIMEIRO ATAQUE IDENTIFICOU QUE RELE ESTA EM CURTO NOTA ABERTA 224/2026 FOI BAIXADA POREM NÃO FOI CORRIGIDO PROBLEMA EM CAMPO. | L24: 15 | M24: 20 | N24: 5 | O24: 15 | P24: 15 | Q24: 10 | R24: 0 | S24: 15 | T24: =SUM(Table12[[#This Row],[Premissa 1]:[Premissa 8]]) -> 95 | U24: Muito Alta | V24: Transferência de Babaçulândia, fonte principal operando
A25: 7908686014 | B25: =MID(Table12[[#This Row],[Ativo]],1,2) -> 79 | C25: PIUM | D25: PARAISO DO TOCANTINS | E25: CENTRO | F25: =IFERROR(_xlfn.XLOOKUP(Table12[[#This Row],[Ativo]],[2]!Pendentes[COD_RELIGADOR],[2]!Pendentes[SS_ORIGINAL]),"CONCLUÍDA") -> ETO-PROT 00159/2026 | G25: Em processo logístico | H25: Previsão de entrega 07/07 | I25: Em andamento | J25: Tanque | K25: =IFERROR(_xlfn.XLOOKUP(Table12[[#This Row],[Ativo]],[2]!Pendentes[COD_RELIGADOR],[2]!Pendentes[DESCRICAO]),"") -> 24/07 PARECER COCM: EQUIPAMENTO FOI SUBSTITUIDO OBRA 021260042510/07 PARECER COEP: EQUIPAMENTO ENTREGUE AOS COCM´S FAVOR INFORMAR PRAZO DE SUBSTUIÇÃO PARA O DMSL E REPASSAR DEPOIS PARA PROTEÇÃO REALIZAR OS AJUSTES E DESCREVER NA SS O SERVIÇO REALIZADO06/07 PARECER COEP: PREVISÃO DE ENTREGA DE ACORDO COM CALENDÁRIO LOGISITCO NOVO 06/07NOTA DMSL: Favor substituir o tanque, ele não está efetuando os comandos enviados. Não substituir o controle pois o mesmo funciona como repetidor de outros equipamentos.Segue nota para verificar falha de fechamento religador 7908686014- Pium .OBS: equipamento não fechou local e remoto , fica sinalizando no painel para verificar alarmes ! | L25: 15 | M25: 20 | N25: 0 | O25: 15 | P25: 15 | Q25: 10 | R25: 0 | S25: 15 | T25: =SUM(Table12[[#This Row],[Premissa 1]:[Premissa 8]]) -> 90 | U25: Muito Alta | V25: Fonte principal de Pium, RL de transferência operando
A26: 7925087021 | B26: =MID(Table12[[#This Row],[Ativo]],1,2) -> 79 | C26: PARANA | D26: PEIXE | E26: SUL | F26: =IFERROR(_xlfn.XLOOKUP(Table12[[#This Row],[Ativo]],[2]!Pendentes[COD_RELIGADOR],[2]!Pendentes[SS_ORIGINAL]),"CONCLUÍDA") -> ETO-PROT 00152/2026 | G26: Em processo logístico | H26: Previsão de entrega 07/07 | I26: Em andamento | J26: Tanque | K26: =IFERROR(_xlfn.XLOOKUP(Table12[[#This Row],[Ativo]],[2]!Pendentes[COD_RELIGADOR],[2]!Pendentes[DESCRICAO]),"") -> 10/07 PARECER COEP: EQUIPAMENTO ENTREGUE AOS COCM´S FAVOR INFORMAR PRAZO DE SUBSTUIÇÃO PARA O DMSL E REPASSAR DEPOIS PARA PROTEÇÃO REALIZAR OS AJUSTES E DESCREVER NA SS O SERVIÇO REALIZADOPARECER COEP: EM ROTA DE ENTREGA, VERIFICAR PREVISÃO DE CHEGADARealizar a substituição do tanque do equipamento. | L26: 15 | M26: 10 | N26: 5 | O26: 0 | P26: 15 | Q26: 10 | R26: 0 | S26: 15 | T26: =SUM(Table12[[#This Row],[Premissa 1]:[Premissa 8]]) -> 70 | U26: Alta | V26: Primeiro RL do 414R de Paranã, RL a jusante na LD também está bay-passado (630 UCs)
A27: 5801866013 | B27: =MID(Table12[[#This Row],[Ativo]],1,2) -> 58 | C27: PARAISO DO TOCANTINS | D27: PARAISO DO TOCANTINS | E27: CENTRO | F27: =IFERROR(_xlfn.XLOOKUP(Table12[[#This Row],[Ativo]],[2]!Pendentes[COD_RELIGADOR],[2]!Pendentes[SS_ORIGINAL]),"CONCLUÍDA") -> ETO-PROT 00151/2026 | G27: Em processo logístico | H27: Aguardando EMD para envio do material | J27: 1 célula | K27: =IFERROR(_xlfn.XLOOKUP(Table12[[#This Row],[Ativo]],[2]!Pendentes[COD_RELIGADOR],[2]!Pendentes[DESCRICAO]),"") -> 15/07 PARECER COCM, FOI ATENDIDA PELA OS ETO-RD-PS 1616/2026 OBRA-021260053910/07 PARECER COEP: EQUIPAMENTO ENTREGUE AOS COCM´S FAVOR INFORMAR PRAZO DE SUBSTUIÇÃO PARA O DMSL E REPASSAR DEPOIS PARA PROTEÇÃO REALIZAR OS AJUSTES E DESCREVER NA SS O SERVIÇO REALIZADOPARECER COEP: EM PROCESSO DE ENTREGAPARECER DMSL: RT 5801866013Serviço Executado: Feito a medição da malha de terra. Identificado infiltração na caixa de passagem da célula da fase C do banco regulador de tensão, será necessário fazer a substituição da mesma! Ficar atento na hora da substituição, deverá ser substituída a célula do lado da BR.Obs.: Será necessário baixar todo o banco pelo menos um metro, as buchas estão muito próximas a parte energizada não oferecem segurança para equipe no momento do ensaio elétrico.Equipamento ficou em operação?: Não Possui nobreak: SimPossui antena: SimPossui rádio:SimPendência: SimData da bateria: Equipe: Benvindo e Kaique._______________________________________________RT 5801866013BY PASSADO DEVIDO DEFEITO EM CELULA BEMVINDO ESTEVE NO LOCAL JUNTO AO COD .NECESSARIO TRATATIVA PARA MESMA .FASE DANIFICADO C | L27: 0 | M27: 20 | N27: 20 | O27: 20 | P27: 10 | Q27: - | R27: - | S27: - | T27: =SUM(Table12[[#This Row],[Premissa 1]:[Premissa 8]]) -> 70 | U27: Alta | V27: Atendimento da RDU Luzimangues Industrial por fonte alternativa
A28: 7900573047 | B28: =MID(Table12[[#This Row],[Ativo]],1,2) -> 79 | C28: FIGUEIROPOLIS | D28: ALVORADA | E28: SUL | F28: =IFERROR(_xlfn.XLOOKUP(Table12[[#This Row],[Ativo]],[2]!Pendentes[COD_RELIGADOR],[2]!Pendentes[SS_ORIGINAL]),"CONCLUÍDA") -> ETO-PROT 00153/2026 | G28: Em processo logístico | H28: Previsão de entrega 07/07 | I28: Em andamento | J28: Tanque e relé | K28: =IFERROR(_xlfn.XLOOKUP(Table12[[#This Row],[Ativo]],[2]!Pendentes[COD_RELIGADOR],[2]!Pendentes[DESCRICAO]),"") -> 10/07 PARECER COEP: EQUIPAMENTO ENTREGUE AOS COCM´S FAVOR INFORMAR PRAZO DE SUBSTUIÇÃO PARA O DMSL E REPASSAR DEPOIS PARA PROTEÇÃO REALIZAR OS AJUSTES E DESCREVER NA SS O SERVIÇO REALIZADOPARECER COEP: AGUARDANDO COCM'S GERAREM AS OBRAS PARA PODER ENTREGAR MATERIALFavor providenciar manutenção no RL 7900573047, o mesmo estar em curto conforme fotos anexadas. Equipamento ficou bay passado em campo.PARECER DMSL: Equipe: FABIO AP./JOÃO MARCOSData Executada: 15/10/2025Serviço Executado:Foi constatado que o equipamento esta queimado na parte ativa placa, tanque e relé. Por favor fazer a substituição pelo Noja RC10. | L28: 5 | M28: 5 | N28: 15 | O28: 0 | P28: 15 | Q28: 10 | R28: 0 | S28: 15 | T28: =SUM(Table12[[#This Row],[Premissa 1]:[Premissa 8]]) -> 65 | U28: Alta | V28: Transferência da Bunge, Saneatins e secadora
A29: 7953610256 | B29: =MID(Table12[[#This Row],[Ativo]],1,2) -> 79 | C29: MATEIROS | D29: PONTE ALTA TOCANTINS | E29: CENTRO | F29: =IFERROR(_xlfn.XLOOKUP(Table12[[#This Row],[Ativo]],[2]!Pendentes[COD_RELIGADOR],[2]!Pendentes[SS_ORIGINAL]),"CONCLUÍDA") -> ETO-PROT 00157/2026 | G29: Em processo logístico | H29: Aguardando obra COCM | K29: =IFERROR(_xlfn.XLOOKUP(Table12[[#This Row],[Ativo]],[2]!Pendentes[COD_RELIGADOR],[2]!Pendentes[DESCRICAO]),"") -> 24/07/2026 - PARECE COCM: EQUIPAMENTO SUBSTIUIDO NA OS:ETO-RD-PO 2020/202614/07/2026 - PARECER COEP: REALOCAR TANQUE 34,5 SOBRESSALENTE DE PARAÍSO PARA ATENDER PARECER DMSL: Data: 10/03/2026,Serviço Executado: Foi substituído o relé do equipamento, o mesmo estava danificado. Trocado o DPS, o mesmo estava queimado devido ao tanque estar furado. O equipamento ficou em bypass.Equipamento ficou em operação? NãoPendência? Sim, substituir a parte ativa com cordão umbilical.Equipe: Carliel e João VitorSEGUE SS PARA REGULARIZAR AUTOMAÇÃO DO RL 7953610256 NA INTERLIGAÇÃO COM A COELBA (CHAPADA DA MANGABEIRA) - EQUIPE INFOMOU CURTO INTERNO NO GABINETE DJ AC NÃO FECHA | L29: 5 | M29: 5 | N29: 15 | O29: 15 | P29: 0 | Q29: 0 | R29: 10 | S29: 15 | T29: =SUM(Table12[[#This Row],[Premissa 1]:[Premissa 8]]) -> 65 | U29: Alta | V29: Atenidmento da COELBA (Alto potencial de compensação)
A30: 7927169001 | B30: =MID(Table12[[#This Row],[Ativo]],1,2) -> 79 | C30: PORTO NACIONAL | D30: PORTO NACIONAL | E30: CENTRO | F30: =IFERROR(_xlfn.XLOOKUP(Table12[[#This Row],[Ativo]],[2]!Pendentes[COD_RELIGADOR],[2]!Pendentes[SS_ORIGINAL]),"CONCLUÍDA") -> ETO-PROT 00156/2026 | G30: Em processo logístico | H30: Previsão de entrega 07/07 | I30: Em andamento | J30: Tanque | K30: =IFERROR(_xlfn.XLOOKUP(Table12[[#This Row],[Ativo]],[2]!Pendentes[COD_RELIGADOR],[2]!Pendentes[DESCRICAO]),"") -> PARECER COEP: EQUIPAMENTO ENTREGUE, SEGUE SS PARA O COCM´S , PARA REALIZAR O ATENDIMENTO,FAVOR ADICIONAR O PARECER PARA MANDAR PARA PROTEÇÃOSS ANTIGA: 1500/2025 PARECER DMSL: Serviço Executado: Foi verificado que o tanque do equipamento está danificado, sendo necessário substituir o tanque do equipamento.Equipamento ficou em operação?: NãoPendência: Sim, instalar fonte, disjuntor e DPS, e substituir o tanque.***** Parecer COCM******Subsituido Tranque do RL pela Ordem de Serviço DLP-MPPA01 247/2026 RELATORIO EM ANEXO DA O.S EXECUTORA | L30: 5 | M30: 5 | N30: 15 | O30: 0 | P30: 15 | Q30: 0 | R30: 0 | S30: 15 | T30: =SUM(Table12[[#This Row],[Premissa 1]:[Premissa 8]]) -> 55 | U30: Alta | V30: Transferência dos Grupos A - VLI e Frisia
A31: 7955520116 | B31: =MID(Table12[[#This Row],[Ativo]],1,2) -> 79 | C31: CHAPADA DA NATIVIDADE | D31: DIANOPOLIS | E31: SUL | F31: =IFERROR(_xlfn.XLOOKUP(Table12[[#This Row],[Ativo]],[2]!Pendentes[COD_RELIGADOR],[2]!Pendentes[SS_ORIGINAL]),"CONCLUÍDA") -> CONCLUÍDA | G31: Em processo logístico | H31: Aguardando obra COCM e PARECER DO DMSL | J31: Tanque | K31: =IFERROR(_xlfn.XLOOKUP(Table12[[#This Row],[Ativo]],[2]!Pendentes[COD_RELIGADOR],[2]!Pendentes[DESCRICAO]),"") | L31: 5 | M31: 5 | N31: 15 | O31: 0 | P31: 0 | Q31: 10 | R31: 0 | S31: 15 | T31: =SUM(Table12[[#This Row],[Premissa 1]:[Premissa 8]]) -> 50 | U31: Alta | V31: Transferência do Grupo A - Engegold (TF 7500 kVA)
A32: 7931610122 | B32: =MID(Table12[[#This Row],[Ativo]],1,2) -> 79 | C32: PALMAS | D32: PALMAS | E32: CENTRO | F32: =IFERROR(_xlfn.XLOOKUP(Table12[[#This Row],[Ativo]],[2]!Pendentes[COD_RELIGADOR],[2]!Pendentes[SS_ORIGINAL]),"CONCLUÍDA") -> CONCLUÍDA | G32: Equipamento entregue ao COCM | I32: Em andamento | J32: Tanque e antena | K32: =IFERROR(_xlfn.XLOOKUP(Table12[[#This Row],[Ativo]],[2]!Pendentes[COD_RELIGADOR],[2]!Pendentes[DESCRICAO]),"") | L32: 15 | M32: 20 | N32: 15 | O32: 15 | P32: 15 | Q32: 10 | R32: 0 | S32: 15 | T32: =SUM(Table12[[#This Row],[Premissa 1]:[Premissa 8]]) -> 105 | U32: Muito Alta | V32: Transferência entre 284R SE Palmas IV e 2294R SE Palmas II
A33: 7908705049 | B33: =MID(Table12[[#This Row],[Ativo]],1,2) -> 79 | C33: AURORA DO TOCANTINS | D33: DIANOPOLIS | E33: SUL | F33: =IFERROR(_xlfn.XLOOKUP(Table12[[#This Row],[Ativo]],[2]!Pendentes[COD_RELIGADOR],[2]!Pendentes[SS_ORIGINAL]),"CONCLUÍDA") -> ETO-RD-DP 00409/2026 | G33: Equipamento entregue ao COCM | H33: Previsão para substituição | I33: Em andamento | J33: Tanque e relé | K33: =IFERROR(_xlfn.XLOOKUP(Table12[[#This Row],[Ativo]],[2]!Pendentes[COD_RELIGADOR],[2]!Pendentes[DESCRICAO]),"") -> EQUIPAMENTO ENTREGUE, SOLICITO PREVISÃO PARA SUBSTITUIÇÃO:PARECER COEP: PREVISÃO DE ENTREGA AOS COCM'S 01/07Manutenção no RL 7908705049PARECER DMSL(28/08/2025): Equipe foi fazer manutenção no RL e constatou que o tanque e o relé do mesmo se encontra queimado, providenciar substituição.PARECER COCMS 30/04/2026CRIADO OBRA 0512600135 PARA REQUISIÇÃO MATERIAL | L33: 15 | M33: 20 | N33: 5 | O33: 15 | P33: 15 | Q33: 0 | R33: 10 | S33: 15 | T33: =SUM(Table12[[#This Row],[Premissa 1]:[Premissa 8]]) -> 95 | U33: Muito Alta | V33: Proteção da baixa do TF de força da SE Aurora
A34: 7933726256 | B34: =MID(Table12[[#This Row],[Ativo]],1,2) -> 79 | C34: MATEIROS | D34: PONTE ALTA TOCANTINS | E34: CENTRO | F34: =IFERROR(_xlfn.XLOOKUP(Table12[[#This Row],[Ativo]],[2]!Pendentes[COD_RELIGADOR],[2]!Pendentes[SS_ORIGINAL]),"CONCLUÍDA") -> ETO-SE-PCM 00092/2026 | G34: Equipamento entregue ao COCM | H34: Destinada parte ativa do RL 7900453110 | I34: Em andamento | K34: =IFERROR(_xlfn.XLOOKUP(Table12[[#This Row],[Ativo]],[2]!Pendentes[COD_RELIGADOR],[2]!Pendentes[DESCRICAO]),"") -> 17/08/2026 PARECER DA PROTEÇÃO:NOTA REPASSADA PARA DMSL COMISSIONARENG° IRLLEY CASTELO BRANCO07/07 Equipamento foi substituido na OS: ETO-RD-PO 1859/2026 OBRA 031260035101/07 PARECER COEP: REDIRECIONADO PARA O POSTO DO COCM´S EQUIPAMENTO CHEGOU NO LOCAL, FAVOR ENTRAR EM CONTATO COM O DMSL, DEVIDO A URGÊNCIA DO EQUIPAMENTO EM OPERAÇÃO.30/06 PARECER COEP: DEVIDO A ALINHAMENTO COM COI UTILIZAREMOS PARTE ATIVA QUE ORIGINALMENTE FOI ENCOMENDADA PARA 7933726256PARECER DMSL: N° do Equipamento: _RLG 7933726256 MateirosTipo de Equipamento: _RLG NOJA RC 10 REL IIData: _06/05/2026SID: _2288/2026-Serviço Executado: _Equipamento com defeito na parte ativa, será necessário fazer a substituição da parte ativa e fazer melhoria na malha de terra!Equipamento ficou em operação?: _NaoPendência: _SimBateria(s) substituída(s)? NÃOData Fabricação/Instalação da(s) bateria(s):_06/2025Equipe: _Benvindo e Almir-------------------------------------------------------------------------------Religador 7933726256, sem comunicação apos primeiroa ataque não retornou as comunicação. | L34: 15 | M34: 10 | N34: 15 | O34: 15 | P34: 15 | Q34: 10 | R34: 0 | S34: 15 | T34: =SUM(Table12[[#This Row],[Premissa 1]:[Premissa 8]]) -> 95 | U34: Muito Alta | V34: Transferência da cidade de Mateiros (733 UCs) para o gerador
A35: 7933766059 | B35: =MID(Table12[[#This Row],[Ativo]],1,2) -> 79 | C35: TAQUARALTO | D35: TAQUARALTO | E35: CENTRO | F35: =IFERROR(_xlfn.XLOOKUP(Table12[[#This Row],[Ativo]],[2]!Pendentes[COD_RELIGADOR],[2]!Pendentes[SS_ORIGINAL]),"CONCLUÍDA") -> CONCLUÍDA | G35: Equipamento entregue ao COCM | I35: Em andamento | J35: Tanque | K35: =IFERROR(_xlfn.XLOOKUP(Table12[[#This Row],[Ativo]],[2]!Pendentes[COD_RELIGADOR],[2]!Pendentes[DESCRICAO]),"") | L35: 15 | M35: 20 | N35: 5 | O35: 15 | P35: 15 | Q35: 0 | R35: 10 | S35: 15 | T35: =SUM(Table12[[#This Row],[Premissa 1]:[Premissa 8]]) -> 95 | U35: Muito Alta | V35: Seccionamento de trecho do Setor Taquari
A36: 7900594026 | B36: =MID(Table12[[#This Row],[Ativo]],1,2) -> 79 | C36: PONTE ALTA TOCANTINS | D36: PONTE ALTA TOCANTINS | E36: CENTRO | F36: =IFERROR(_xlfn.XLOOKUP(Table12[[#This Row],[Ativo]],[2]!Pendentes[COD_RELIGADOR],[2]!Pendentes[SS_ORIGINAL]),"CONCLUÍDA") -> ETO-SE-PA 00107/2026 | G36: Equipamento entregue ao COCM | H36: Previsão para substituição 10/07 | I36: Em andamento | K36: =IFERROR(_xlfn.XLOOKUP(Table12[[#This Row],[Ativo]],[2]!Pendentes[COD_RELIGADOR],[2]!Pendentes[DESCRICAO]),"") -> PARECER DA PROTEÇÃO:16/07/2026 AJUSTES DISPONIBILIZADOS NO APP DA PROTEÇÃO15/07/2026 EQUIPAMENTO SUBSTITUIDO NA OS ETO-RD-PO 1860 OBRA 031260035414/07/2026 PARECER COCM/ COEP: DE ACORDO COM O EDSON CURCINO FOI FEITA S SUBSTITUIÇÃO DO EQUIPAMENTO , SEGUE PARA PROTEÇÃO ELABORAR AJUSTE10/07 PARECER COEP: EQUIPAMENTO DESLOCADO QUE ESTAVA EM GUARAÍ FOI ALINHADO COM O VALMOR QUE SERIA SUBSTITUIDO DIA 07/07/2026 , FAVOR PASSAR PARA PROTEÇÃO 7900594026PARECER COEP: AGUARDANDO COCM'S PARA ABRIR REQUISIÇÃOPARECER DMSL 10/06/2026: Tem uma nota aberta para esse equipamento solicitando a substituição desde 20/10/2025, como a nota não foi atendida estamos repassando para área responsável. Nota em aberto repassada ETO-COEP 210/2025.Segue nota para verificar intermitência de comunicação nos religadores 7908301026 , 7911120026, 7947959026 , 7908692026, 7900594026 rural- Ponte Alta . | L36: 15 | M36: 20 | N36: 15 | O36: 15 | P36: 15 | Q36: 0 | R36: 0 | S36: 15 | T36: =SUM(Table12[[#This Row],[Premissa 1]:[Premissa 8]]) -> 95 | U36: Muito Alta | V36: Religador responsável pela proteção da barra da SE Ponte Alta (2381 UCs)
A37: 7900230155 | B37: =MID(Table12[[#This Row],[Ativo]],1,2) -> 79 | C37: PALMEIRANTE | D37: COLINAS DO TOCANTINS | E37: NORTE | F37: =IFERROR(_xlfn.XLOOKUP(Table12[[#This Row],[Ativo]],[2]!Pendentes[COD_RELIGADOR],[2]!Pendentes[SS_ORIGINAL]),"CONCLUÍDA") -> ETO-TELE 01131/2026 | G37: Execução COCM´s | H37: ETO-682/2026 | J37: Tanque e PR do trafo e chave | K37: =IFERROR(_xlfn.XLOOKUP(Table12[[#This Row],[Ativo]],[2]!Pendentes[COD_RELIGADOR],[2]!Pendentes[DESCRICAO]),"") -> PARECER DA PROTEÇÃO - 17/08/2026:SEGUE NOTA PARA COMISSIONAMENTO JUNTO COM TIME SCADA, EQUIPAMENTO JA NO DESENHO ADMS.ENG° IRLLEY CASTELO BRANCO07/07/2026 PARECER COEP: MATERIAL ENVIADO , CONFORME ALINHANDO COM O WANDER REALIZAR SUBSTIUIÇÂO DO EQUIPAMENTO, FAVOR ESCREVER PARECER COCM ANTES DE PASSAR PARA PROTEÇÂO, DO QUE FOI REALIZADO01/07/2026 PARECER COEP: PROBLEMA NO ENVIO DO MATERIAL PARECER DMSL: Religador está com o tanque danificado. Não responde a comandos abertura e fechamento local ou remoto, pois está com sinal de curto circuito. Necessário trocar o equipamento. Para raio do trafo está queimado. Chave de saída da fase C está com o olhal quebrado, necessário substituir a chave. Equipamento ficou bypassado em campo. Aberto entrada e saída, com exceção da fase C de saída que ficou fechada. Favor, substituir equipamento completo por NOJA RC10 e sanar demais pendencias.Senhores Favor verificar RL 7900230155 o mesmo sinalizou aberto no SCADA porem a cidade de Palmeirante estava normal , feito um reset no rl e o mesmo subiu fechado.08/07/2026 PARECER DCMD: EQUIPE ETO-LVGR01 DE GUARAI ESTEVE NO RL 7900230155 DIA 25-06-2026 E FEZ TODAS A PENDENCIAS DO RL, OBS: EQUIPE SO NAO CONECTOU O CABO DO TRAFO NO RL. RL ESTA PRONTO PARA O COMISSIONAMENTO | L37: 15 | M37: 20 | N37: 5 | O37: 15 | P37: 0 | Q37: 10 | R37: 0 | S37: 15 | T37: =SUM(Table12[[#This Row],[Premissa 1]:[Premissa 8]]) -> 80 | U37: Muito Alta | V37: Fonte principal de Palmeirante, RL de transferência operando
A38: 5865120195 | B38: =MID(Table12[[#This Row],[Ativo]],1,2) -> 58 | C38: CENTENARIO | D38: GUARAI | E38: NORTE | F38: =IFERROR(_xlfn.XLOOKUP(Table12[[#This Row],[Ativo]],[2]!Pendentes[COD_RELIGADOR],[2]!Pendentes[SS_ORIGINAL]),"CONCLUÍDA") -> ETO-TELE 01132/2026 | G38: Melhoria de aterramento | J38: Melhoria de aterramento | K38: =IFERROR(_xlfn.XLOOKUP(Table12[[#This Row],[Ativo]],[2]!Pendentes[COD_RELIGADOR],[2]!Pendentes[DESCRICAO]),"") -> PARECER DMSL:PENDÊNCIA: Realizar melhoria no aterramento por ser tratar de um terreno muito arenoso, e há pendências por parte do time da proteção, os ajustes do RT não estão disponíveis para inserção no referido equipamento.DATA DA MANUTENÇÃO: 12/03/202EQUIPE: Brunno e Edeglan.***********************PARECER DA PROTEÇÃO - 17/08/2026:FAVOR COMISSIONAR REGULADOR 5865120195 – LD Santa Maria Ramal Centenário e Recursolândia – 34,5kV. AJUSTE REALIZADO, DISPONÍVEL NO APP DA PROTEÇÃO.*********************** INSTALADO NA OBRA 0702400720 GENTILEZA, REALIZAR O COMISSIONAMENTO.LAUDO EM ANEXO.COORD EO: 889017, 901685708-07-2026 PARECER: FOI FEITO A MELHORIA NO REGULADOR CONFORME FOTOS EM ANEXO. | L38: 20 | M38: 20 | N38: 20 | O38: 10 | P38: 0 | Q38: - | R38: - | S38: - | T38: =SUM(Table12[[#This Row],[Premissa 1]:[Premissa 8]]) -> 70 | U38: Alta | V38: Atendimento das RDUs de Centenário, Recursolândia e clientes rurais
A39: 5853360007 | B39: =MID(Table12[[#This Row],[Ativo]],1,2) -> 58 | C39: MIRACEMA DO TOCANTINS | D39: MIRACEMA DO TOCANTINS | E39: CENTRO | F39: =IFERROR(_xlfn.XLOOKUP(Table12[[#This Row],[Ativo]],[2]!Pendentes[COD_RELIGADOR],[2]!Pendentes[SS_ORIGINAL]),"CONCLUÍDA") -> ETO-RD-PS 00323/2025 | G39: Problema na autorização de passagem | H39: Cliente não autorizou entrar na propriedade | J39: Melhoria de aterramento | K39: =IFERROR(_xlfn.XLOOKUP(Table12[[#This Row],[Ativo]],[2]!Pendentes[COD_RELIGADOR],[2]!Pendentes[DESCRICAO]),"") -> REALIZAR TESTES NO EQUIPAMENTO E CONFERIR MEDIÇÕES DA MALHA DE ATERRAMENTO. ESTANDO OK, COMISSIONAR EQUIPAMENTO E COLOCA-LO EM OPERAÇÃO.AJUSTES DISPONIVEIS NO APP DA PROTEÇÃdmsl : N° do Equipamento:*RT 5853360007 MIRACEMASID: 2493/2025Data: 13/05/2025Serviço Executado Provavelmente ocorreu uma descarga no equipamento comprometendo a malha!Será necessário fazer melhoria da malha de aterramento, fazer toda interligação da mesma! Feito ensaios de isolação das 3 células do equipamento, isolação está ok, quando retornar para colocar em operação levar 3 baterias de 7a.Equipamento ficou em operação?: Não Equipe: Benvindo e Jardel | L39: 0 | M39: 20 | N39: 20 | O39: 10 | P39: 20 | Q39: - | R39: - | S39: - | T39: =SUM(Table12[[#This Row],[Premissa 1]:[Premissa 8]]) -> 70 | U39: Alta | V39: Aumento de reclamações no atendimento de Miracema no período seco
A40: 5800291077 | B40: =MID(Table12[[#This Row],[Ativo]],1,2) -> 58 | C40: GOIATINS | D40: ARAGUAINA | E40: NORTE | F40: =IFERROR(_xlfn.XLOOKUP(Table12[[#This Row],[Ativo]],[2]!Pendentes[COD_RELIGADOR],[2]!Pendentes[SS_ORIGINAL]),"CONCLUÍDA") -> CONCLUÍDA | I40: Ok | K40: =IFERROR(_xlfn.XLOOKUP(Table12[[#This Row],[Ativo]],[2]!Pendentes[COD_RELIGADOR],[2]!Pendentes[DESCRICAO]),"") | L40: 40 | M40: 20 | N40: 20 | O40: 20 | P40: 20 | Q40: - | R40: - | S40: - | T40: =SUM(Table12[[#This Row],[Premissa 1]:[Premissa 8]]) -> 120 | U40: Muito Alta | V40: Aumento de reclamações no atendimento de Goiatins e GAs relevantes na região
A41: 5836764032 | B41: =MID(Table12[[#This Row],[Ativo]],1,2) -> 58 | C41: ARAGUACU | D41: ALVORADA | E41: SUL | F41: =IFERROR(_xlfn.XLOOKUP(Table12[[#This Row],[Ativo]],[2]!Pendentes[COD_RELIGADOR],[2]!Pendentes[SS_ORIGINAL]),"CONCLUÍDA") -> CONCLUÍDA | I41: Ok | K41: =IFERROR(_xlfn.XLOOKUP(Table12[[#This Row],[Ativo]],[2]!Pendentes[COD_RELIGADOR],[2]!Pendentes[DESCRICAO]),"") | L41: 40 | M41: 20 | N41: 20 | O41: 10 | P41: 20 | Q41: - | R41: - | S41: - | T41: =SUM(Table12[[#This Row],[Premissa 1]:[Premissa 8]]) -> 110 | U41: Muito Alta | V41: Aumento de reclamações no atendimento de Araguaçu no período seco
A42: 7900648055 | B42: =MID(Table12[[#This Row],[Ativo]],1,2) -> 79 | C42: ARAGUACEMA | D42: DIVINOPOLIS | E42: CENTRO | F42: =IFERROR(_xlfn.XLOOKUP(Table12[[#This Row],[Ativo]],[2]!Pendentes[COD_RELIGADOR],[2]!Pendentes[SS_ORIGINAL]),"CONCLUÍDA") -> CONCLUÍDA | K42: =IFERROR(_xlfn.XLOOKUP(Table12[[#This Row],[Ativo]],[2]!Pendentes[COD_RELIGADOR],[2]!Pendentes[DESCRICAO]),"") | L42: 15 | M42: 20 | N42: 15 | O42: 15 | P42: 15 | Q42: 10 | R42: 0 | S42: 15 | T42: =SUM(Table12[[#This Row],[Premissa 1]:[Premissa 8]]) -> 105 | U42: Muito Alta | V42: Transferência da RDU de Araguacema (1506 UCs)
A43: 7921040031 | B43: =MID(Table12[[#This Row],[Ativo]],1,2) -> 79 | C43: RIO DOS BOIS | D43: MIRACEMA DO TOCANTINS | E43: CENTRO | F43: =IFERROR(_xlfn.XLOOKUP(Table12[[#This Row],[Ativo]],[2]!Pendentes[COD_RELIGADOR],[2]!Pendentes[SS_ORIGINAL]),"CONCLUÍDA") -> CONCLUÍDA | I43: Ok | K43: =IFERROR(_xlfn.XLOOKUP(Table12[[#This Row],[Ativo]],[2]!Pendentes[COD_RELIGADOR],[2]!Pendentes[DESCRICAO]),"") | L43: 15 | M43: 20 | N43: 5 | O43: 15 | P43: 15 | Q43: 10 | R43: 0 | S43: 15 | T43: =SUM(Table12[[#This Row],[Premissa 1]:[Premissa 8]]) -> 95 | U43: Muito Alta | V43: Fonte principal de Rio dos Bois, RL de transferência operando
A44: 5800438116 | B44: =MID(Table12[[#This Row],[Ativo]],1,2) -> 58 | C44: CHAPADA DA NATIVIDADE | D44: DIANOPOLIS | E44: SUL | F44: =IFERROR(_xlfn.XLOOKUP(Table12[[#This Row],[Ativo]],[2]!Pendentes[COD_RELIGADOR],[2]!Pendentes[SS_ORIGINAL]),"CONCLUÍDA") -> CONCLUÍDA | G44: Em processo logístico | H44: Aguardando obra COCM | J44: 2 Celula | K44: =IFERROR(_xlfn.XLOOKUP(Table12[[#This Row],[Ativo]],[2]!Pendentes[COD_RELIGADOR],[2]!Pendentes[DESCRICAO]),"") | L44: 0 | M44: 20 | N44: 20 | O44: 20 | P44: 0 | Q44: - | R44: - | S44: - | T44: =SUM(Table12[[#This Row],[Premissa 1]:[Premissa 8]]) -> 60 | U44: Média | V44: Atendimento da região da Engegold, Nativa, cidade Natividade e Chapada da Natividade (Fonte alternativa)
A45: 5800090147 | B45: =MID(Table12[[#This Row],[Ativo]],1,2) -> 58 | C45: TAIPAS DO TOCANTINS | D45: DIANOPOLIS | E45: SUL | F45: =IFERROR(_xlfn.XLOOKUP(Table12[[#This Row],[Ativo]],[2]!Pendentes[COD_RELIGADOR],[2]!Pendentes[SS_ORIGINAL]),"CONCLUÍDA") -> CONCLUÍDA | G45: Aguardando atualização de informação DMSL | K45: =IFERROR(_xlfn.XLOOKUP(Table12[[#This Row],[Ativo]],[2]!Pendentes[COD_RELIGADOR],[2]!Pendentes[DESCRICAO]),"") | L45: 0 | M45: 20 | N45: 20 | O45: 10 | P45: 10 | Q45: - | R45: - | S45: - | T45: =SUM(Table12[[#This Row],[Premissa 1]:[Premissa 8]]) -> 60 | U45: Média | V45: Atendimento de Taipas
A46: 5840227063 | B46: =MID(Table12[[#This Row],[Ativo]],1,2) -> 58 | C46: BANDEIRANTES DO TOCANTINS | D46: COLINAS DO TOCANTINS | E46: NORTE | F46: =IFERROR(_xlfn.XLOOKUP(Table12[[#This Row],[Ativo]],[2]!Pendentes[COD_RELIGADOR],[2]!Pendentes[SS_ORIGINAL]),"CONCLUÍDA") -> ETO-COEP 00151/2026 | G46: Primeiro ataque DMSL | K46: =IFERROR(_xlfn.XLOOKUP(Table12[[#This Row],[Ativo]],[2]!Pendentes[COD_RELIGADOR],[2]!Pendentes[DESCRICAO]),"") -> PARECER COEP 27/07/2026 : EM PROCESSO DE AQUISIÇÃOPARECER DMSL 13/07/2026: Realizados ensaios de isolação nas três células, e foi identificado curto na fase A, sendo necessário a sua substituição. Os cabos das buchas ficaram desconectados para melhor identificação no momento da sua substituiçãSEGUE PARA O DMSL AVALIAR ANTES DE SEGUIRMOS COM O SERVIÇOSEGUE PARA REALIZAR TROCA---------------------------------------------------------Boa noite,Segue SS para tratativas regulador de tensão 5840227063 fase C em curto | L46: 0 | M46: 20 | N46: 20 | O46: 10 | P46: 10 | Q46: - | R46: - | S46: - | T46: =SUM(Table12[[#This Row],[Premissa 1]:[Premissa 8]]) -> 60 | U46: Média | V46: Atendimento da RDU Bandeirantes e clientes rurais
A47: 5846328094 | B47: =MID(Table12[[#This Row],[Ativo]],1,2) -> 58 | C47: PEIXE | D47: PEIXE | E47: SUL | F47: =IFERROR(_xlfn.XLOOKUP(Table12[[#This Row],[Ativo]],[2]!Pendentes[COD_RELIGADOR],[2]!Pendentes[SS_ORIGINAL]),"CONCLUÍDA") -> ETO-TELE 00986/2026 | G47: Melhoria de aterramento | K47: =IFERROR(_xlfn.XLOOKUP(Table12[[#This Row],[Ativo]],[2]!Pendentes[COD_RELIGADOR],[2]!Pendentes[DESCRICAO]),"") -> COCM SUL - 07/07/2026 - FOI REALIZADO MELHORIA DE ATERRAMENTO E FEITO A MANUTENÇÕES E TODAS AS CHAVES E SUBSTITUIDO OS CONECTORES.PARECER COEP: MELHORIA DE ATERRAMENTO É COCM'S, FAVOR ENCAMINHAR DIRETAMENTE PARA ELES, COCM'S REALIZAR MELHORIA DE ATERRAMENTO POR FAVORPor genteliiza verificar RT 5846328094 situação de equipamento, se encontra by passado em campoPARECER DMSL:Favor, realizar melhoria de aterramento que se encontra alta e substituir todos os conectores das buchas por conectores estrangulador. | L47: 0 | M47: 20 | N47: 20 | O47: 10 | P47: 10 | Q47: - | R47: - | S47: - | T47: =SUM(Table12[[#This Row],[Premissa 1]:[Premissa 8]]) -> 60 | U47: Média | V47: Atendimento da RDU Sucupira e clientes rurais
A48: 5851753086 | B48: =MID(Table12[[#This Row],[Ativo]],1,2) -> 58 | C48: MARIANOPOLIS | D48: DIVINOPOLIS | E48: CENTRO | F48: =IFERROR(_xlfn.XLOOKUP(Table12[[#This Row],[Ativo]],[2]!Pendentes[COD_RELIGADOR],[2]!Pendentes[SS_ORIGINAL]),"CONCLUÍDA") -> CONCLUÍDA | G48: Aguardando comissionamento | K48: =IFERROR(_xlfn.XLOOKUP(Table12[[#This Row],[Ativo]],[2]!Pendentes[COD_RELIGADOR],[2]!Pendentes[DESCRICAO]),"") | L48: 0 | M48: 20 | N48: 20 | O48: 10 | P48: 10 | Q48: - | R48: - | S48: - | T48: =SUM(Table12[[#This Row],[Premissa 1]:[Premissa 8]]) -> 60 | U48: Média | V48: Atendimento da RDU Marianópolis e clientes rurais
A49: 7957620015 | B49: =MID(Table12[[#This Row],[Ativo]],1,2) -> 79 | C49: PEDRO AFONSO | D49: GUARAI | E49: NORTE | F49: =IFERROR(_xlfn.XLOOKUP(Table12[[#This Row],[Ativo]],[2]!Pendentes[COD_RELIGADOR],[2]!Pendentes[SS_ORIGINAL]),"CONCLUÍDA") -> CONCLUÍDA | I49: Ok | K49: =IFERROR(_xlfn.XLOOKUP(Table12[[#This Row],[Ativo]],[2]!Pendentes[COD_RELIGADOR],[2]!Pendentes[DESCRICAO]),"") | L49: 15 | M49: 20 | N49: 15 | O49: 15 | P49: 15 | Q49: 0 | R49: 0 | S49: 15 | T49: =SUM(Table12[[#This Row],[Premissa 1]:[Premissa 8]]) -> 95 | U49: Muito Alta | V49: Atendimento da RDU de Bom Jesus e parcial da RDU de Pedro Afonso
A50: 5800440256 | B50: =MID(Table12[[#This Row],[Ativo]],1,2) -> 58 | C50: MATEIROS | D50: PONTE ALTA TOCANTINS | E50: CENTRO | F50: =IFERROR(_xlfn.XLOOKUP(Table12[[#This Row],[Ativo]],[2]!Pendentes[COD_RELIGADOR],[2]!Pendentes[SS_ORIGINAL]),"CONCLUÍDA") -> ETO-COEP 00169/2026 | K50: =IFERROR(_xlfn.XLOOKUP(Table12[[#This Row],[Ativo]],[2]!Pendentes[COD_RELIGADOR],[2]!Pendentes[DESCRICAO]),"") -> PARECER DMSL 06/08: Substituir célula da Fase B do banco de Regulador de tensão e realizar melhorias na malha de aterramento do ReguladorBoa noite,Segue SS para as devidas tratativas, verificar flutuação de tensão do regulador 5800440256 pois a tensão está oscilando de 16kv a 23kv favor verificar esta anomalia pois cliente BRK está abrindo reclamação todas as noites. | L50: 20 | M50: 20 | N50: 20 | O50: 10 | P50: 20 | Q50: - | R50: - | S50: - | T50: =SUM(Table12[[#This Row],[Premissa 1]:[Premissa 8]]) -> 90 | U50: Muito Alta | V50: Aumento de reclamações no atendimento de São Felix e Mateiros no período seco
A51: 7900543083 | B51: =MID(Table12[[#This Row],[Ativo]],1,2) -> 79 | C51: APARECIDA DO RIO NEGRO | D51: TAQUARALTO | E51: CENTRO | F51: =IFERROR(_xlfn.XLOOKUP(Table12[[#This Row],[Ativo]],[2]!Pendentes[COD_RELIGADOR],[2]!Pendentes[SS_ORIGINAL]),"CONCLUÍDA") -> CONCLUÍDA | I51: Ok | K51: =IFERROR(_xlfn.XLOOKUP(Table12[[#This Row],[Ativo]],[2]!Pendentes[COD_RELIGADOR],[2]!Pendentes[DESCRICAO]),"") | L51: 15 | M51: 20 | N51: 5 | O51: 15 | P51: 0 | Q51: 0 | R51: 10 | S51: 15 | T51: =SUM(Table12[[#This Row],[Premissa 1]:[Premissa 8]]) -> 80 | U51: Muito Alta | V51: Atendimento da RDU de Aparecida do Rio Negro
A52: 7900930040 | B52: =MID(Table12[[#This Row],[Ativo]],1,2) -> 79 | C52: ARAGOMINAS | D52: ARAGUAINA | E52: NORTE | F52: =IFERROR(_xlfn.XLOOKUP(Table12[[#This Row],[Ativo]],[2]!Pendentes[COD_RELIGADOR],[2]!Pendentes[SS_ORIGINAL]),"CONCLUÍDA") -> CONCLUÍDA | I52: Ok | K52: =IFERROR(_xlfn.XLOOKUP(Table12[[#This Row],[Ativo]],[2]!Pendentes[COD_RELIGADOR],[2]!Pendentes[DESCRICAO]),"") | L52: 15 | M52: 20 | N52: 5 | O52: 15 | P52: 0 | Q52: 0 | R52: 10 | S52: 15 | T52: =SUM(Table12[[#This Row],[Premissa 1]:[Premissa 8]]) -> 80 | U52: Muito Alta | V52: Proteção da baixa do TF de força da SE Aragominas
A53: 7931383086 | B53: =MID(Table12[[#This Row],[Ativo]],1,2) -> 79 | C53: MARIANOPOLIS | D53: DIVINOPOLIS | E53: CENTRO | F53: =IFERROR(_xlfn.XLOOKUP(Table12[[#This Row],[Ativo]],[2]!Pendentes[COD_RELIGADOR],[2]!Pendentes[SS_ORIGINAL]),"CONCLUÍDA") -> CONCLUÍDA | I53: Ok | K53: =IFERROR(_xlfn.XLOOKUP(Table12[[#This Row],[Ativo]],[2]!Pendentes[COD_RELIGADOR],[2]!Pendentes[DESCRICAO]),"") | L53: 15 | M53: 20 | N53: 5 | O53: 15 | P53: 0 | Q53: 10 | R53: 0 | S53: 15 | T53: =SUM(Table12[[#This Row],[Premissa 1]:[Premissa 8]]) -> 80 | U53: Muito Alta | V53: Fonte principal de Marianópolis, RL transferência operando
A54: 5800366016 | B54: =MID(Table12[[#This Row],[Ativo]],1,2) -> 58 | C54: WANDERLANDIA | D54: TOCANTINOPOLIS | E54: NORTE | F54: =IFERROR(_xlfn.XLOOKUP(Table12[[#This Row],[Ativo]],[2]!Pendentes[COD_RELIGADOR],[2]!Pendentes[SS_ORIGINAL]),"CONCLUÍDA") -> CONCLUÍDA | I54: Ok | K54: =IFERROR(_xlfn.XLOOKUP(Table12[[#This Row],[Ativo]],[2]!Pendentes[COD_RELIGADOR],[2]!Pendentes[DESCRICAO]),"") | L54: 0 | M54: 20 | N54: 20 | O54: 20 | P54: 10 | Q54: - | R54: - | S54: - | T54: =SUM(Table12[[#This Row],[Premissa 1]:[Premissa 8]]) -> 70 | U54: Alta | V54: Aumento de reclamações no atendimento de Wanderlândia no período seco
A55: 7955523028 | B55: =MID(Table12[[#This Row],[Ativo]],1,2) -> 79 | C55: NATIVIDADE | D55: DIANOPOLIS | E55: SUL | F55: =IFERROR(_xlfn.XLOOKUP(Table12[[#This Row],[Ativo]],[2]!Pendentes[COD_RELIGADOR],[2]!Pendentes[SS_ORIGINAL]),"CONCLUÍDA") -> CONCLUÍDA | I55: Ok | K55: =IFERROR(_xlfn.XLOOKUP(Table12[[#This Row],[Ativo]],[2]!Pendentes[COD_RELIGADOR],[2]!Pendentes[DESCRICAO]),"") | L55: 15 | M55: 10 | N55: 5 | O55: 15 | P55: 15 | Q55: 10 | R55: 0 | S55: 0 | T55: =SUM(Table12[[#This Row],[Premissa 1]:[Premissa 8]]) -> 70 | U55: Alta | V55: Equipamento para apoio na transferência de cargas na região de Natividade
A56: 7900018004 | B56: =MID(Table12[[#This Row],[Ativo]],1,2) -> 79 | C56: ARAGUAINA | D56: ARAGUAINA | E56: NORTE | F56: =IFERROR(_xlfn.XLOOKUP(Table12[[#This Row],[Ativo]],[2]!Pendentes[COD_RELIGADOR],[2]!Pendentes[SS_ORIGINAL]),"CONCLUÍDA") -> CONCLUÍDA | I56: Ok | K56: =IFERROR(_xlfn.XLOOKUP(Table12[[#This Row],[Ativo]],[2]!Pendentes[COD_RELIGADOR],[2]!Pendentes[DESCRICAO]),"") | L56: 15 | M56: 10 | N56: 5 | O56: 15 | P56: 0 | Q56: 10 | R56: 0 | S56: 0 | T56: =SUM(Table12[[#This Row],[Premissa 1]:[Premissa 8]]) -> 55 | U56: Alta | V56: Transferência de Aragominas, 3 fontes operando
A57: 7934698002 | B57: =MID(Table12[[#This Row],[Ativo]],1,2) -> 79 | C57: TOCANTINOPOLIS | D57: TOCANTINOPOLIS | E57: NORTE | F57: =IFERROR(_xlfn.XLOOKUP(Table12[[#This Row],[Ativo]],[2]!Pendentes[COD_RELIGADOR],[2]!Pendentes[SS_ORIGINAL]),"CONCLUÍDA") -> CONCLUÍDA | I57: Ok | J57: Controle | K57: =IFERROR(_xlfn.XLOOKUP(Table12[[#This Row],[Ativo]],[2]!Pendentes[COD_RELIGADOR],[2]!Pendentes[DESCRICAO]),"") | L57: 5 | M57: 5 | N57: 5 | O57: 0 | P57: 15 | Q57: 0 | R57: 10 | S57: 15 | T57: =SUM(Table12[[#This Row],[Premissa 1]:[Premissa 8]]) -> 55 | U57: Alta | V57: Atendimento do PA Mumbuca (106 UCs), no desarme a jusante penaliza parte da RDU de Tocantinópolis (1384 UCs)
A58: 5800291035 | B58: =MID(Table12[[#This Row],[Ativo]],1,2) -> 58 | C58: MONTE DO CARMO | D58: PONTE ALTA TOCANTINS | E58: CENTRO | F58: =IFERROR(_xlfn.XLOOKUP(Table12[[#This Row],[Ativo]],[2]!Pendentes[COD_RELIGADOR],[2]!Pendentes[SS_ORIGINAL]),"CONCLUÍDA") -> CONCLUÍDA | G58: SS REALIZADA encaminharem ou para proteção ou para ETO-TELE | J58: Melhoria de aterramento | K58: =IFERROR(_xlfn.XLOOKUP(Table12[[#This Row],[Ativo]],[2]!Pendentes[COD_RELIGADOR],[2]!Pendentes[DESCRICAO]),"") | L58: 0 | M58: 20 | N58: 20 | O58: 10 | P58: 0 | Q58: - | R58: - | S58: - | T58: =SUM(Table12[[#This Row],[Premissa 1]:[Premissa 8]]) -> 50 | U58: Média | V58: Aumento de reclamações no atendimento de Silvanópolis por Monte do Carmo no período seco
A59: 5827102054 | B59: =MID(Table12[[#This Row],[Ativo]],1,2) -> 58 | C59: PUGMIL | D59: PARAISO DO TOCANTINS | E59: CENTRO | F59: =IFERROR(_xlfn.XLOOKUP(Table12[[#This Row],[Ativo]],[2]!Pendentes[COD_RELIGADOR],[2]!Pendentes[SS_ORIGINAL]),"CONCLUÍDA") -> ETO-PROT 00164/2026 | G59: ETO-RD-PS 289/2026 (Aguardando retorno dos COCM's) | J59: Controle e melhoria de aterramento | K59: =IFERROR(_xlfn.XLOOKUP(Table12[[#This Row],[Ativo]],[2]!Pendentes[COD_RELIGADOR],[2]!Pendentes[DESCRICAO]),"") -> PARECER COCM: FOI SUBSTITUÍDO OS EQUIPAMENTO FEITO A MELHORIA DO ATERRAMENTO ATENDIDO PELA OBRA N-0212600609PARECER COEP:NÃO É POSSÍVEL RETORNAR COM O CONTROLE COMPLETO , MAS DARIA PARA FAZER A MELHORIA NA MALHA DE ATERRAMENTO , ENCAMINHANDO PARA OS COCM'S PARA REALIZAREM A MELHORIAparecer DMSL: :Nobreack com defeito, rele queimado, cabo de comunicação entre o rádio e o rele danificado, malha de aterramento está com a resistência alta!Feito reparo no cabo, substituído nobreack, e rele. Se possível retornar com controle completo pq o q está em campo teve infiltração de água, abrir chamado no scada para atualizar base do equipamento pois o mesmo está com a base antiga, fazer correção da malha de aterramento.Equipamento ficou em operação?: Não Pendência: sim, levar controle novo, fazer correção da malha de terra, levar suporte para fixar antena. OBS | L59: 0 | M59: 20 | N59: 20 | O59: 10 | P59: 0 | Q59: - | R59: - | S59: - | T59: =SUM(Table12[[#This Row],[Premissa 1]:[Premissa 8]]) -> 50 | U59: Média | V59: Aumento de reclamações no atendimento de Pugmil no período seco
A60: 5850308009 | B60: =MID(Table12[[#This Row],[Ativo]],1,2) -> 58 | C60: GUARAI | D60: GUARAI | E60: NORTE | F60: =IFERROR(_xlfn.XLOOKUP(Table12[[#This Row],[Ativo]],[2]!Pendentes[COD_RELIGADOR],[2]!Pendentes[SS_ORIGINAL]),"CONCLUÍDA") -> CONCLUÍDA | G60: Aguardando atualização de informação DMSL | I60: Em operação | J60: Controle | K60: =IFERROR(_xlfn.XLOOKUP(Table12[[#This Row],[Ativo]],[2]!Pendentes[COD_RELIGADOR],[2]!Pendentes[DESCRICAO]),"") | L60: 0 | M60: 20 | N60: 20 | O60: 0 | P60: 10 | Q60: - | R60: - | S60: - | T60: =SUM(Table12[[#This Row],[Premissa 1]:[Premissa 8]]) -> 50 | U60: Média | V60: Atendimento de parte da RDU de Guaraí e ramal da PRF/Repetidora
A61: 7900535058 | B61: =MID(Table12[[#This Row],[Ativo]],1,2) -> 79 | C61: SANTA FE DO ARAGUAIA | D61: ARAGUAINA | E61: NORTE | F61: =IFERROR(_xlfn.XLOOKUP(Table12[[#This Row],[Ativo]],[2]!Pendentes[COD_RELIGADOR],[2]!Pendentes[SS_ORIGINAL]),"CONCLUÍDA") -> ETO-COEP 00173/2025 | G61: Em proceso de Aquisição | J61: Relé Cooper | K61: =IFERROR(_xlfn.XLOOKUP(Table12[[#This Row],[Ativo]],[2]!Pendentes[COD_RELIGADOR],[2]!Pendentes[DESCRICAO]),"") -> PARECER COEP: EQUIPAMENTO SELECIONADO PARA COMPRAPARECER DMSL: Equipamento 7900535058 encontra-se com o relé danificado, firmware corrompido, o mesmo não inicia. Devido ao fato de não possuirmos mais peças de reposição para religador cooper, se faz necessário a substituição de todo conjunto por um Noja RC10.envar equipe para verificar rlo 7900535058 foi feito primeiro ataque com equipe 040op36 o mesmo esta com RELE TRAVADO E FICOU FORA DE OPERAÇÃO, ATENDE RDR DE SANTA FÉ SAIDA DA CIDADEEQUIPE INFORMOU ABELHAS NA CAIXA DO PAINEL DE COMANDO | L61: 5 | M61: 10 | N61: 5 | O61: 0 | P61: 15 | Q61: 10 | R61: 0 | S61: 0 | T61: =SUM(Table12[[#This Row],[Premissa 1]:[Premissa 8]]) -> 45 | U61: Média | V61: Atendimento 3 povoados, na perca 4 ficam fora (900 UCs)
A62: 7927713200 | B62: =MID(Table12[[#This Row],[Ativo]],1,2) -> 79 | C62: SAO SALVADOR DO TOCANTINS | D62: PEIXE | E62: SUL | F62: =IFERROR(_xlfn.XLOOKUP(Table12[[#This Row],[Ativo]],[2]!Pendentes[COD_RELIGADOR],[2]!Pendentes[SS_ORIGINAL]),"CONCLUÍDA") -> ETO-COEP 00157/2026 | G62: Aguardando atualização de informação DMSL | J62: Tanque | K62: =IFERROR(_xlfn.XLOOKUP(Table12[[#This Row],[Ativo]],[2]!Pendentes[COD_RELIGADOR],[2]!Pendentes[DESCRICAO]),"") -> segue SS para REALIZAR SUBSTITUIÇÃO DO TANQUE do RL 7927713200 danificado , com equipe de manutencao tensao 34,5kv mesmo atende Povoado retiro na rural de sao salvador . | L62: 5 | M62: 5 | N62: 5 | O62: 0 | P62: 15 | Q62: 10 | R62: 0 | S62: 0 | T62: =SUM(Table12[[#This Row],[Premissa 1]:[Premissa 8]]) -> 40 | U62: Média | V62: Transferência do Ramal do Retiro (246UCs), fonte principal by-passado
A63: 7937102148 | B63: =MID(Table12[[#This Row],[Ativo]],1,2) -> 79 | C63: SAO VALERIO DA NATIVIDADE | D63: PEIXE | E63: SUL | F63: =IFERROR(_xlfn.XLOOKUP(Table12[[#This Row],[Ativo]],[2]!Pendentes[COD_RELIGADOR],[2]!Pendentes[SS_ORIGINAL]),"CONCLUÍDA") -> ETO-COEP 00129/2026 | G63: ETO-TELE 977/2026 | J63: Tanque | K63: =IFERROR(_xlfn.XLOOKUP(Table12[[#This Row],[Ativo]],[2]!Pendentes[COD_RELIGADOR],[2]!Pendentes[DESCRICAO]),"") -> PARECER COEP: REAVALIAR DISPONIBILIDADE DO EQUIPAMENTO NO SCADA ASSIM COMO , FORNECER MODELO DO EQUIPAMENTO E FAIXA DE TENSÃO PARA COMPRA / AQUISIÇÃOTanque com defeito, realizar substituição do tanque. | L63: 5 | M63: 5 | N63: 5 | O63: 0 | P63: 15 | Q63: 10 | R63: 0 | S63: 0 | T63: =SUM(Table12[[#This Row],[Premissa 1]:[Premissa 8]]) -> 40 | U63: Média | V63: Fonte principal do Ramal Serranópolis (181 UCs), RL de transferência operando
A64: 7944559149 | B64: =MID(Table12[[#This Row],[Ativo]],1,2) -> 79 | C64: CASEARA | D64: DIVINOPOLIS | E64: CENTRO | F64: =IFERROR(_xlfn.XLOOKUP(Table12[[#This Row],[Ativo]],[2]!Pendentes[COD_RELIGADOR],[2]!Pendentes[SS_ORIGINAL]),"CONCLUÍDA") -> ETO-COEP 00063/2026 | G64: (EQUIPAMENTO PARA ANALISE DO DMSL) | K64: =IFERROR(_xlfn.XLOOKUP(Table12[[#This Row],[Ativo]],[2]!Pendentes[COD_RELIGADOR],[2]!Pendentes[DESCRICAO]),"") -> 14/07/2026 PARECER COEP: EQUIPAMENTO SELECIONADO PARA COMPRA Equipamento ficou em operação?: NãoPendência: Sim será necessário substituir a placaServiço Executado: curto na placa foi tentando recuperar a mesma porém não teve sucesso!Bateria(s)substituída(s)? NÃOEquipe: Kaique e benvido | L64: 5 | M64: 10 | N64: 0 | O64: 0 | P64: 15 | Q64: 10 | R64: 0 | S64: 0 | T64: =SUM(Table12[[#This Row],[Premissa 1]:[Premissa 8]]) -> 40 | U64: Média | V64: Atendimento de cargas rurais entre Caseaarra e Araguacema (221 UCs)
A65: 5800961074 | B65: =MID(Table12[[#This Row],[Ativo]],1,2) -> 58 | C65: DIANOPOLIS | D65: DIANOPOLIS | E65: SUL | F65: =IFERROR(_xlfn.XLOOKUP(Table12[[#This Row],[Ativo]],[2]!Pendentes[COD_RELIGADOR],[2]!Pendentes[SS_ORIGINAL]),"CONCLUÍDA") -> ETO-COEP 00221/2025 | G65: (COMPRA) | J65: 3 células e conectores | K65: =IFERROR(_xlfn.XLOOKUP(Table12[[#This Row],[Ativo]],[2]!Pendentes[COD_RELIGADOR],[2]!Pendentes[DESCRICAO]),"") -> PARECER COEP: EQUIPAMENTO SELECIONADO PARA COMPRASubstituir as 3 células- Melhoria na malha de aterramento - Melhoria no circuito de aterramento qua aterra as células.- Substituir conectores paralelos | L65: 20 | M65: 0 | N65: 0 | O65: 20 | P65: 0 | Q65: - | R65: - | S65: - | T65: =SUM(Table12[[#This Row],[Premissa 1]:[Premissa 8]]) -> 40 | U65: Média | V65: Atendimento da COELBA e GA Alessandro Maurício (1600 kVA)
A66: 7908249152 | B66: =MID(Table12[[#This Row],[Ativo]],1,2) -> 79 | C66: SANTA ROSA DO TOCANTINS | D66: PORTO NACIONAL | E66: CENTRO | F66: =IFERROR(_xlfn.XLOOKUP(Table12[[#This Row],[Ativo]],[2]!Pendentes[COD_RELIGADOR],[2]!Pendentes[SS_ORIGINAL]),"CONCLUÍDA") -> ETO-COEP 00038/2026 | G66: (EQUIPAMENTO PARA ANALISE DO DMSL) | J66: Tanque e controle | K66: =IFERROR(_xlfn.XLOOKUP(Table12[[#This Row],[Ativo]],[2]!Pendentes[COD_RELIGADOR],[2]!Pendentes[DESCRICAO]),"") -> 14/07/2026 PARECER COEP: EQUIPAMENTO SELECIONADO PARA COMPRADMSL:Serviço Executado: Houve um curto no equipamento danificando a parte ativa, será necessário fazer a substituição do equipamento completo ( parte ativa e controle) colocar o um cabo pp novo do trafo até o Dj pois o mesmo está sem condições de uso. Obs:. Foi retirado rádio e rele Equipamento ficou em operação?: Não Pendência: Sim, substituir o equipamento completo. | L66: 5 | M66: 5 | N66: 0 | O66: 0 | P66: 15 | Q66: 10 | R66: 0 | S66: 0 | T66: =SUM(Table12[[#This Row],[Premissa 1]:[Premissa 8]]) -> 35 | U66: Média | V66: Atendimento de zona rural em Santa Rosa (160 UCs)
A67: 7922995039 | B67: =MID(Table12[[#This Row],[Ativo]],1,2) -> 79 | C67: ARAGUATINS | D67: AUGUSTINOPOLIS | E67: NORTE | F67: =IFERROR(_xlfn.XLOOKUP(Table12[[#This Row],[Ativo]],[2]!Pendentes[COD_RELIGADOR],[2]!Pendentes[SS_ORIGINAL]),"CONCLUÍDA") -> CONCLUÍDA | G67: Concluído , em operação repassado ETO-PROT 135/2026 | I67: Em operação | J67: Completo | K67: =IFERROR(_xlfn.XLOOKUP(Table12[[#This Row],[Ativo]],[2]!Pendentes[COD_RELIGADOR],[2]!Pendentes[DESCRICAO]),"") | L67: 5 | M67: 5 | N67: 0 | O67: 0 | P67: 15 | Q67: 10 | R67: 0 | S67: 0 | T67: =SUM(Table12[[#This Row],[Premissa 1]:[Premissa 8]]) -> 35 | U67: Média | V67: Atendimento do PA Esperança Viva (396 UCs)
A68: 7925733015 | B68: =MID(Table12[[#This Row],[Ativo]],1,2) -> 79 | C68: PEDRO AFONSO | D68: GUARAI | E68: NORTE | F68: =IFERROR(_xlfn.XLOOKUP(Table12[[#This Row],[Ativo]],[2]!Pendentes[COD_RELIGADOR],[2]!Pendentes[SS_ORIGINAL]),"CONCLUÍDA") -> ETO-COEP 00058/2026 | G68: Em processo de aquisição | K68: =IFERROR(_xlfn.XLOOKUP(Table12[[#This Row],[Ativo]],[2]!Pendentes[COD_RELIGADOR],[2]!Pendentes[DESCRICAO]),"") -> PARECER COEP: EQUIPAMENTO SELECIONADO PARA COMPRAPARECER DMSL: FEEDBACK EQUIP. ESPECIAISNº DO EQUIPAMENTO: 7925733015TIPO EQUIPAMENTO: Noja RC10TIPO DE COMUNICAÇÃO: Rádio GEDATA DA MANUTENÇÃO: 24/03/2026SID: 1475/2026DESCRIÇÃO: Tanque do equipamento em CurtoFICOU EM OPERAÇÃO?: Não PENDÊNCIA: Sim, repassar a nota para DCMD substituir tanque.DADOS DIVERGENTES DA PROGRAMAÇÃO: NãoBATERIA SUBSTITUÍDA?: Não TIPO DE BATERIA: Lítio EQUIPE: Edicleber e Jhonata(DEOP)------------------------------------------------------------------------------------------------------religador 7925733015 com defeito, equipe fez abertura da chave de saida do mesmo e ele não aceita fehcamento devido provavel curto-circuito interno, enviar equipe para verificar o mesmo ficou by-pass fechado | L68: 5 | M68: 5 | N68: 0 | O68: 0 | P68: 15 | Q68: 10 | R68: 0 | S68: 0 | T68: =SUM(Table12[[#This Row],[Premissa 1]:[Premissa 8]]) -> 35 | U68: Média | V68: Transferência do Ramal Agrovila (73 UCs)
A69: 7927396052 | B69: =MID(Table12[[#This Row],[Ativo]],1,2) -> 79 | C69: FORMOSO DO ARAGUAIA | D69: FORMOSO DO ARAGUAIA | E69: SUL | F69: =IFERROR(_xlfn.XLOOKUP(Table12[[#This Row],[Ativo]],[2]!Pendentes[COD_RELIGADOR],[2]!Pendentes[SS_ORIGINAL]),"CONCLUÍDA") -> ETO-COEP 00045/2026 | G69: Em processo de aquisição | J69: Tanque | K69: =IFERROR(_xlfn.XLOOKUP(Table12[[#This Row],[Ativo]],[2]!Pendentes[COD_RELIGADOR],[2]!Pendentes[DESCRICAO]),"") -> PARECER COEP: EQUIPAMENTO SELECIONADO PARA COMPRAreligador foi bay passado devido mesmo esta saindo fumaca do painel e sem comunicação 7927396052.PARECER DMSL: Após testes, equipe DMSL constatou que apenas o tanque do RLG 7927396052 encontra-se queimado. Favor, substituir parte ativa do equipamento.NS Tanque: 0320123040198 | L69: 5 | M69: 5 | N69: 0 | O69: 0 | P69: 15 | Q69: 10 | R69: 0 | S69: 0 | T69: =SUM(Table12[[#This Row],[Premissa 1]:[Premissa 8]]) -> 35 | U69: Média | V69: Equipamento localizado Fonte principal de atendimento a SE Cobrape
A70: 7933585074 | B70: =MID(Table12[[#This Row],[Ativo]],1,2) -> 79 | C70: DIANOPOLIS | D70: DIANOPOLIS | E70: SUL | F70: =IFERROR(_xlfn.XLOOKUP(Table12[[#This Row],[Ativo]],[2]!Pendentes[COD_RELIGADOR],[2]!Pendentes[SS_ORIGINAL]),"CONCLUÍDA") -> ETO-COEP 00024/2026 | G70: (EQUIPAMENTO PARA ANALISE DO DMSL) | J70: Tanque | K70: =IFERROR(_xlfn.XLOOKUP(Table12[[#This Row],[Ativo]],[2]!Pendentes[COD_RELIGADOR],[2]!Pendentes[DESCRICAO]),"") -> 30/06 PARECER COEP: EQUIPAMENTO SELECIONADO PARA COMPRAREALIZAR SUBSTITUIÇÃO DO TANQUE, O MESMO ESTÁ COM DEFEITO. | L70: 5 | M70: 5 | N70: 15 | O70: 0 | P70: 0 | Q70: 0 | R70: 10 | S70: 0 | T70: =SUM(Table12[[#This Row],[Premissa 1]:[Premissa 8]]) -> 35 | U70: Média | V70: Atendimento da COELBA
A71: 7942572059 | B71: =MID(Table12[[#This Row],[Ativo]],1,2) -> 79 | C71: TAQUARALTO | D71: TAQUARALTO | E71: CENTRO | F71: =IFERROR(_xlfn.XLOOKUP(Table12[[#This Row],[Ativo]],[2]!Pendentes[COD_RELIGADOR],[2]!Pendentes[SS_ORIGINAL]),"CONCLUÍDA") -> ETO-PROT 00155/2026 | G71: Melhoria de aterramento | I71: Em operação | K71: =IFERROR(_xlfn.XLOOKUP(Table12[[#This Row],[Ativo]],[2]!Pendentes[COD_RELIGADOR],[2]!Pendentes[DESCRICAO]),"") -> PARECER COEP: EQUIPAMENTO COM MELHORIA DE ATERRAMENTO É COM A ETO-RD-PA , NÃO PASSA PELO FLUXO DE AQUISIÇÃO DO COEP, FAVOR REALIZAR MELHORIA DE ATERRAMENTO ETO-RD-PAPARECER DMSL 19/05/2026: É necessário fazer melhorias na malha de aterramento.segue nota para RL 794252059 o mesmo esta sem comunicaçao, foi feito primeiro ataque, porem a comunicaçao nao voltou, obs ramal do marasca.**** Parcecer do COCM CENTRO-****FEITO A MALHAR DE ATERRAMENTO ATENDIDA PELA ORDEM DE SERVIÇO DLP-MLPA02 91/2026 COM RELATORIO EM ANEXO A O.S | L71: 5 | M71: 5 | N71: 15 | O71: 0 | P71: 0 | Q71: 0 | R71: 10 | S71: 0 | T71: =SUM(Table12[[#This Row],[Premissa 1]:[Premissa 8]]) -> 35 | U71: Média | V71: Atendimento do Ramal do Marasca e GAs (108 UCs)
A72: 7944319149 | B72: =MID(Table12[[#This Row],[Ativo]],1,2) -> 79 | C72: CASEARA | D72: DIVINOPOLIS | E72: CENTRO | F72: =IFERROR(_xlfn.XLOOKUP(Table12[[#This Row],[Ativo]],[2]!Pendentes[COD_RELIGADOR],[2]!Pendentes[SS_ORIGINAL]),"CONCLUÍDA") -> CONCLUÍDA | I72: Ok | J72: Tanque | K72: =IFERROR(_xlfn.XLOOKUP(Table12[[#This Row],[Ativo]],[2]!Pendentes[COD_RELIGADOR],[2]!Pendentes[DESCRICAO]),"") | L72: 5 | M72: 5 | N72: 15 | O72: 0 | P72: 0 | Q72: 0 | R72: 10 | S72: 0 | T72: =SUM(Table12[[#This Row],[Premissa 1]:[Premissa 8]]) -> 35 | U72: Média | V72: Atendimento do Grupo A - Matosul (TF 1500 kVA)
A73: 7955986084 | B73: =MID(Table12[[#This Row],[Ativo]],1,2) -> 79 | C73: DIVINOPOLIS | D73: DIVINOPOLIS | E73: CENTRO | F73: =IFERROR(_xlfn.XLOOKUP(Table12[[#This Row],[Ativo]],[2]!Pendentes[COD_RELIGADOR],[2]!Pendentes[SS_ORIGINAL]),"CONCLUÍDA") -> ETO-COEP 00133/2026 | G73: ETO-TELE 968/2026 | K73: =IFERROR(_xlfn.XLOOKUP(Table12[[#This Row],[Ativo]],[2]!Pendentes[COD_RELIGADOR],[2]!Pendentes[DESCRICAO]),"") -> 14/07/2026 PARECER COEP : SUBSTIUIR CONTROLE COMPLETOPARECER DMSL: Equipamento com a placa de alimentação ca em curto, será necessário substituir a placa do equipamento. (Antiga nota era pra ter sido repassada porém foi baixada indevidamente pela equipe) | L73: 5 | M73: 5 | N73: 0 | O73: 0 | P73: 15 | Q73: 10 | R73: 0 | S73: 0 | T73: =SUM(Table12[[#This Row],[Premissa 1]:[Premissa 8]]) -> 35 | U73: Média | V73: Transferência de cargas do 444R da SE Paraíso I
A74: 7967181127 | B74: =MID(Table12[[#This Row],[Ativo]],1,2) -> 79 | C74: PALMEIRAS DO TOCANTINS | D74: TOCANTINOPOLIS | E74: NORTE | F74: =IFERROR(_xlfn.XLOOKUP(Table12[[#This Row],[Ativo]],[2]!Pendentes[COD_RELIGADOR],[2]!Pendentes[SS_ORIGINAL]),"CONCLUÍDA") -> CONCLUÍDA | G74: ETO-RD-AR 1070/2026 | K74: =IFERROR(_xlfn.XLOOKUP(Table12[[#This Row],[Ativo]],[2]!Pendentes[COD_RELIGADOR],[2]!Pendentes[DESCRICAO]),"") | L74: 5 | M74: 5 | N74: 0 | O74: 0 | P74: 15 | Q74: 10 | R74: 0 | S74: 0 | T74: =SUM(Table12[[#This Row],[Premissa 1]:[Premissa 8]]) -> 35 | U74: Média | V74: Transferência de Palmeiras, 3 RLs sendo 2 operando
A75: 7900525015 | B75: =MID(Table12[[#This Row],[Ativo]],1,2) -> 79 | C75: PEDRO AFONSO | D75: GUARAI | E75: NORTE | F75: =IFERROR(_xlfn.XLOOKUP(Table12[[#This Row],[Ativo]],[2]!Pendentes[COD_RELIGADOR],[2]!Pendentes[SS_ORIGINAL]),"CONCLUÍDA") -> ETO-COEP 00125/2026 | G75: ETO-TELE 971/2026 | K75: =IFERROR(_xlfn.XLOOKUP(Table12[[#This Row],[Ativo]],[2]!Pendentes[COD_RELIGADOR],[2]!Pendentes[DESCRICAO]),"") -> PARECER COEP: É PARA REALIZAR A SUBSTITUIÇÃO DO RELIGADOR OU DAS BUCHAS, CASO SEJA BUCHAS , REPASSAR PARA OS COCM'S , CASO NÃO SEJA ESPECIFIQUE O MODELO , E A TENSÃO, FICO NO AGUARDO DO RETORNONota para manutenção substituir religador 7900525015 que está com as buchas de entrada danificadas fase A estourada e bc danificadas Local LD Pedro Afonso A Chaparral | L75: 5 | M75: 5 | N75: 0 | O75: 0 | P75: 15 | Q75: 10 | R75: 0 | S75: 0 | T75: =SUM(Table12[[#This Row],[Premissa 1]:[Premissa 8]]) -> 35 | U75: Média | V75: Tranferência do Ramal do Chaparral (251 UCs)
A76: 7928564039 | B76: =MID(Table12[[#This Row],[Ativo]],1,2) -> 79 | C76: ARAGUATINS | D76: AUGUSTINOPOLIS | E76: NORTE | F76: =IFERROR(_xlfn.XLOOKUP(Table12[[#This Row],[Ativo]],[2]!Pendentes[COD_RELIGADOR],[2]!Pendentes[SS_ORIGINAL]),"CONCLUÍDA") -> ETO-COEP 00123/2026 | G76: ETO- TELE 967/2026 | J76: Tanque, relé e modulo | K76: =IFERROR(_xlfn.XLOOKUP(Table12[[#This Row],[Ativo]],[2]!Pendentes[COD_RELIGADOR],[2]!Pendentes[DESCRICAO]),"") -> PARECER COEP: EQUIPAMENTO SELECIONADO PARA COMPRATroca do sistema de comunicação do equipamentoDMSL 28/07/2025: Equipamento com tanque, modulo e rele com defeito, solicitar troca do equipamento ao DCMD.Fotos vão ser enviadas por e-mail | L76: 5 | M76: 10 | N76: 5 | O76: 0 | P76: 0 | Q76: 10 | R76: 0 | S76: 0 | T76: =SUM(Table12[[#This Row],[Premissa 1]:[Premissa 8]]) -> 30 | U76: Média | V76: Transferência entre 424R Araguatins e 434R Augustinópolis
A77: 7957126085 | B77: =MID(Table12[[#This Row],[Ativo]],1,2) -> 79 | C77: MONTE SANTO DO TOCANTINS | D77: PARAISO DO TOCANTINS | E77: CENTRO | F77: =IFERROR(_xlfn.XLOOKUP(Table12[[#This Row],[Ativo]],[2]!Pendentes[COD_RELIGADOR],[2]!Pendentes[SS_ORIGINAL]),"CONCLUÍDA") -> CONCLUÍDA | G77: Previsão de entrega aos COCM's 01/07 | I77: Em andamento | J77: Relé, controle e ajuste | K77: =IFERROR(_xlfn.XLOOKUP(Table12[[#This Row],[Ativo]],[2]!Pendentes[COD_RELIGADOR],[2]!Pendentes[DESCRICAO]),"") | L77: 5 | M77: 10 | N77: 5 | O77: 0 | P77: 0 | Q77: 10 | R77: 0 | S77: 0 | T77: =SUM(Table12[[#This Row],[Premissa 1]:[Premissa 8]]) -> 30 | U77: Média | V77: 444R de Paraíso I, atendimento de Monte Santo, devido defeito a RDU está manobrada para o 454R
A78: 5841308190 | B78: =MID(Table12[[#This Row],[Ativo]],1,2) -> 58 | C78: NOVO JARDIM | D78: DIANOPOLIS | E78: SUL | F78: =IFERROR(_xlfn.XLOOKUP(Table12[[#This Row],[Ativo]],[2]!Pendentes[COD_RELIGADOR],[2]!Pendentes[SS_ORIGINAL]),"CONCLUÍDA") -> CONCLUÍDA | I78: Desmobilizado | J78: - | K78: =IFERROR(_xlfn.XLOOKUP(Table12[[#This Row],[Ativo]],[2]!Pendentes[COD_RELIGADOR],[2]!Pendentes[DESCRICAO]),"") | L78: 0 | M78: 20 | N78: 0 | O78: 10 | P78: 0 | Q78: - | R78: - | S78: - | T78: =SUM(Table12[[#This Row],[Premissa 1]:[Premissa 8]]) -> 30 | U78: Baixa | V78: Equipamento obsoleto com a entrada da SE Serras Gerais
A79: 5844630060 | B79: =MID(Table12[[#This Row],[Ativo]],1,2) -> 58 | C79: NOVA OLINDA | D79: COLINAS DO TOCANTINS | E79: NORTE | F79: =IFERROR(_xlfn.XLOOKUP(Table12[[#This Row],[Ativo]],[2]!Pendentes[COD_RELIGADOR],[2]!Pendentes[SS_ORIGINAL]),"CONCLUÍDA") -> ETO-TELE 01102/2026 | G79: Em processo logístico | J79: 1 celula | K79: =IFERROR(_xlfn.XLOOKUP(Table12[[#This Row],[Ativo]],[2]!Pendentes[COD_RELIGADOR],[2]!Pendentes[DESCRICAO]),"") -> Segue nota para verificar falha em comandos via supervisório e constantes travamento no regulador de tensão 5844630060 - rural- Nova Olinda .Foi executado comandos no relé via supervisório, porém sem sucesso , em campo o equipamento está com a fase B travada no -16 .Obs: equipamento ficou fora de operação bay passado , favor agilizar atendimento ! | L79: 20 | M79: 0 | N79: 0 | O79: 10 | P79: 0 | Q79: - | R79: - | S79: - | T79: =SUM(Table12[[#This Row],[Premissa 1]:[Premissa 8]]) -> 30 | U79: Baixa | V79: Atendimento dos ramais PA Remansão e Água Branca
A80: 5855411017 | B80: =MID(Table12[[#This Row],[Ativo]],1,2) -> 58 | C80: BARROLANDIA | D80: MIRACEMA DO TOCANTINS | E80: CENTRO | F80: =IFERROR(_xlfn.XLOOKUP(Table12[[#This Row],[Ativo]],[2]!Pendentes[COD_RELIGADOR],[2]!Pendentes[SS_ORIGINAL]),"CONCLUÍDA") -> ETO-COEP 00156/2026 | G80: Aguardando a criação da Obra para abrir a requisição | J80: Controle | K80: =IFERROR(_xlfn.XLOOKUP(Table12[[#This Row],[Ativo]],[2]!Pendentes[COD_RELIGADOR],[2]!Pendentes[DESCRICAO]),"") -> 20/07 PARECER COCM: NÃO RECEBEMOS MATERIAL10/07 PARECER COEP: EQUIPAMENTO ENTREGUE AOS COCM´S FAVOR INFORMAR PRAZO DE SUBSTUIÇÃO PARA O DMSL E REPASSAR DEPOIS PARA PROTEÇÃO REALIZAR OS AJUSTES E DESCREVER NA SS O SERVIÇO REALIZADOPARECER COEP: EQUIPAMENTO EM ROTA DE ENTREGASEM COMUNICAÇÃO, FALHA DE ALIMENTAÇÃO - REALIZADO PRIMEIRO ATAQUE SEM SUCESSO.PARECER DMSL: 17/09/2025 Equipamento ficou em operação? Não Pendência: sim. Equipamento ficou Bay passado levar controle COMPLETO para trocar. ellisfran | L80: 0 | M80: 0 | N80: 0 | O80: 10 | P80: 20 | Q80: - | R80: - | S80: - | T80: =SUM(Table12[[#This Row],[Premissa 1]:[Premissa 8]]) -> 30 | U80: Baixa | V80: Atendimento do Assentamento Irmã Adelaide
A81: 7900505026 | B81: =MID(Table12[[#This Row],[Ativo]],1,2) -> 79 | C81: PONTE ALTA TOCANTINS | D81: PONTE ALTA TOCANTINS | E81: CENTRO | F81: =IFERROR(_xlfn.XLOOKUP(Table12[[#This Row],[Ativo]],[2]!Pendentes[COD_RELIGADOR],[2]!Pendentes[SS_ORIGINAL]),"CONCLUÍDA") -> CONCLUÍDA | G81: ETO-PROT 00136 | J81: Completo | K81: =IFERROR(_xlfn.XLOOKUP(Table12[[#This Row],[Ativo]],[2]!Pendentes[COD_RELIGADOR],[2]!Pendentes[DESCRICAO]),"") | L81: 5 | M81: 5 | N81: 5 | O81: 0 | P81: 0 | Q81: 0 | R81: 10 | S81: 0 | T81: =SUM(Table12[[#This Row],[Premissa 1]:[Premissa 8]]) -> 25 | U81: Baixa | V81: Atendimento do Ramal do Gato (288 UCs) e UFV Videira, no desarme a jusante penaliza a cidade de Pindorama
A82: 7908196047 | B82: =MID(Table12[[#This Row],[Ativo]],1,2) -> 79 | C82: FIGUEIROPOLIS | D82: ALVORADA | E82: SUL | F82: =IFERROR(_xlfn.XLOOKUP(Table12[[#This Row],[Ativo]],[2]!Pendentes[COD_RELIGADOR],[2]!Pendentes[SS_ORIGINAL]),"CONCLUÍDA") -> ETO-COEP 00168/2026 | J82: Completo | K82: =IFERROR(_xlfn.XLOOKUP(Table12[[#This Row],[Ativo]],[2]!Pendentes[COD_RELIGADOR],[2]!Pendentes[DESCRICAO]),"") -> 03/08/2026 PARECER DMSL: FOI CONFIRMADO PELO VONES DO DCMD QUE O EQUIPAMENTO AINDA NÃO FOI SUBSTITUÍDO. FAVOR, APÓS SUBSTITUIÇÃO, REPASSAR A NOTA PARA A PROTEÇÃO PARA REVISAR OS AJUSTES, POIS TRATA-SE DE ALTERAÇÃO DO MODELO DO EQUIPAMENTO.13/07/2026 PARECER COEP: EQUIPAMENTO REMANEJADO FAVOR FAZER O COMISSIONAMENTORELIGADOR N° 7908196047 REMANEJADO NA OBRA 0402401150 GENTILEZA, REALIZAR O COMISSIONAMENTO. LAUDO EM ANEXO. COORD EO: 698485, 8657287PARECER DA PROTEÇÃO:AJUSTE DISPONIBILIZADO NO APP DA PROTEÇÃO, NOTA REPASSADA PARA DMSL COMISSIONAR, POLO GURUPI, RL APENAS REMANEJADO DA REDE VELHA PARA REDE NOVA, EQUIPAMENTO COOPER, SE MANTEVE O MESMO NÚMERO DE ATIVO.ENG° IRLLEY CASTELO BRANCO.PARECER DMSL: Constatado curto-circuito no tanque do religador, impedindo as operações de abertura e fechamento do equipamento. Solicita-se a substituição completa do religador, incluindo tanque e unidade de controle. | L82: 5 | M82: 5 | N82: 5 | O82: 0 | P82: 0 | Q82: 0 | R82: 10 | S82: 0 | T82: =SUM(Table12[[#This Row],[Premissa 1]:[Premissa 8]]) -> 25 | U82: Baixa | V82: Seccionamento do Rural e energização do 224R
A83: 7921202014 | B83: =MID(Table12[[#This Row],[Ativo]],1,2) -> 79 | C83: PIUM | D83: PARAISO DO TOCANTINS | E83: CENTRO | F83: =IFERROR(_xlfn.XLOOKUP(Table12[[#This Row],[Ativo]],[2]!Pendentes[COD_RELIGADOR],[2]!Pendentes[SS_ORIGINAL]),"CONCLUÍDA") -> ETO-COEP 00132/2026 | G83: ETO-TELE 972/2026 | K83: =IFERROR(_xlfn.XLOOKUP(Table12[[#This Row],[Ativo]],[2]!Pendentes[COD_RELIGADOR],[2]!Pendentes[DESCRICAO]),"") -> PARECER COEP: EQUIPAMENTO SELECIONADO PARA COMPRA , DEVERIA SER SUBSTITUIDO PARTE ATIVAPARECER DMSL: Serviço Executado: _ indentificado o problema na parte ativa será necessário fazer a substituição da mesmo, feito a medição do aterramento. Preciso substituir para raio da fase c.Equipamento ficou em operação?: _NAOPendência: _SimBateria(s) substituída(s)? _NãoData Fabricação/Instalação da(s) bateria(s):_Equipe: _Benvindo e kaique----------------------------------------------------------------------------------RL com defeito no rele, fica só reiniciando ficou By passado OS atendimento primeiro ataque 106530226 | L83: 5 | M83: 5 | N83: 5 | O83: 0 | P83: 0 | Q83: 10 | R83: 0 | S83: 0 | T83: =SUM(Table12[[#This Row],[Premissa 1]:[Premissa 8]]) -> 25 | U83: Baixa | V83: Atendimento de Clientes rurais (483 UCs)
A84: 7923927122 | B84: =MID(Table12[[#This Row],[Ativo]],1,2) -> 79 | C84: PALMAS | D84: PALMAS | E84: CENTRO | F84: =IFERROR(_xlfn.XLOOKUP(Table12[[#This Row],[Ativo]],[2]!Pendentes[COD_RELIGADOR],[2]!Pendentes[SS_ORIGINAL]),"CONCLUÍDA") -> ETO-COEP 00148/2026 | G84: SEM PARECER TÉCNICO DMSL | J84: tanque | K84: =IFERROR(_xlfn.XLOOKUP(Table12[[#This Row],[Ativo]],[2]!Pendentes[COD_RELIGADOR],[2]!Pendentes[DESCRICAO]),"") -> PARECER DMSL 16/07: Nota solicitada ao DMSL com a informação de que o tanque precisa ser substituído. Estou encaminhando a nota para a área responsável.Segue nota para envia manutenção substituir tanque do RL-7923927122 em curto, Anomalia identificada desarme das LD, s Palmas / Aparecida e Palmas Taquaruçu, Acesso livre, Tensão 34,5kv, Local RL de Interligação entre 424R / 414R. | L84: 15 | M84: 0 | N84: 0 | O84: 0 | P84: 0 | Q84: 10 | R84: 0 | S84: 0 | T84: =SUM(Table12[[#This Row],[Premissa 1]:[Premissa 8]]) -> 25 | U84: Baixa | V84: Transferência entre 414R e 424R SE Palmas II
A85: 7927446001 | B85: =MID(Table12[[#This Row],[Ativo]],1,2) -> 79 | C85: PORTO NACIONAL | D85: PORTO NACIONAL | E85: CENTRO | F85: =IFERROR(_xlfn.XLOOKUP(Table12[[#This Row],[Ativo]],[2]!Pendentes[COD_RELIGADOR],[2]!Pendentes[SS_ORIGINAL]),"CONCLUÍDA") -> ETO-COEP 00143/2025 | G85: (REPASSAR NOVAMENTE A ANÁLISE DO DMSL) | J85: Parte ativa danificada | K85: =IFERROR(_xlfn.XLOOKUP(Table12[[#This Row],[Ativo]],[2]!Pendentes[COD_RELIGADOR],[2]!Pendentes[DESCRICAO]),"") -> 30/06 PARECER COEP: EQUIPAMENTO COMPLETOSegue para verificação RL sem comunicação feito primeiro ataque sem sucesso.PARECER DMSL:Data:* _08/07/2025Serviço Executado: Placa de alimentação danificada, devido a curto, não temos material sobressalente para manutenção! Favor substituir o equipamento completo.Obs.: O rádio ficou dentro do controle, favor orientar a equipe que for substituir colocar dentro do controle novo.Equipamento ficou em operação?: Não Pendência: Sim, substituir equipamento completo. | L85: 5 | M85: 5 | N85: 5 | O85: 0 | P85: 0 | Q85: 10 | R85: 0 | S85: 0 | T85: =SUM(Table12[[#This Row],[Premissa 1]:[Premissa 8]]) -> 25 | U85: Baixa | V85: Alimentação de Monte do Carmo por Porto Nacional
A86: 7928241200 | B86: =MID(Table12[[#This Row],[Ativo]],1,2) -> 79 | C86: SAO SALVADOR DO TOCANTINS | D86: PEIXE | E86: SUL | F86: =IFERROR(_xlfn.XLOOKUP(Table12[[#This Row],[Ativo]],[2]!Pendentes[COD_RELIGADOR],[2]!Pendentes[SS_ORIGINAL]),"CONCLUÍDA") -> ETO-COEP 00128/2026 | G86: ETO-TELE 974/2026 | J86: tanque | K86: =IFERROR(_xlfn.XLOOKUP(Table12[[#This Row],[Ativo]],[2]!Pendentes[COD_RELIGADOR],[2]!Pendentes[DESCRICAO]),"") -> PARECER COEP: EQUIPAMENTO SELECIONADO PARA COMPRAPARECER DMSL: Tinha uma nota aberta 422/2025 e logo após a equipe resolver a comunicação ela foi baixada, porém a equipe relatou que ''na estrada ontem o COS nos avisou para voltar que na hora de colocar em operação ele tirou a linha fora. Hoje retornamos nele e fizemos ensaios elétricos e foi constatado que o tanque está em curto. Passa direto aí para o Dcmd para substituição do tanque.'' | L86: 5 | M86: 5 | N86: 5 | O86: 0 | P86: 0 | Q86: 10 | R86: 0 | S86: 0 | T86: =SUM(Table12[[#This Row],[Premissa 1]:[Premissa 8]]) -> 25 | U86: Baixa | V86: Fonte principal do Ramal do Retiro (246UCs), RL transferência by-passado
A87: 7942485096 | B87: =MID(Table12[[#This Row],[Ativo]],1,2) -> 79 | C87: PINDORAMA DO TOCANTINS | D87: PONTE ALTA TOCANTINS | E87: CENTRO | F87: =IFERROR(_xlfn.XLOOKUP(Table12[[#This Row],[Ativo]],[2]!Pendentes[COD_RELIGADOR],[2]!Pendentes[SS_ORIGINAL]),"CONCLUÍDA") -> ETO-COEP 00158/2025 | G87: Em processo de aquisição | J87: Parte ativa danificada (tanque) | K87: =IFERROR(_xlfn.XLOOKUP(Table12[[#This Row],[Ativo]],[2]!Pendentes[COD_RELIGADOR],[2]!Pendentes[DESCRICAO]),"") -> 30/06 PARECER COEP: EQUIPAMENTO SELECIONADO PARA COMPRARELIGADOR COM DEFEITO 7942485096, ESTA DANDO PASSAGEM ESTANDO ABERTO. NÃO ACEITA COMANDOS. FICOU BY PASSADO EM CAMPO PARA MANUTENÇÃO.PARECER DMSL: Ao testar o tanque, foi constatado que o mesmo está danificado e precisa ser substituído.Substituir somente o tanque. Deixar claro na nota para o dcmd substituir somente o tanque. Não tem necessidade de substituir o controle. | L87: 5 | M87: 5 | N87: 5 | O87: 0 | P87: 0 | Q87: 10 | R87: 0 | S87: 0 | T87: =SUM(Table12[[#This Row],[Premissa 1]:[Premissa 8]]) -> 25 | U87: Baixa | V87: Transferência da PCH Bagagem
A88: 7955430075 | B88: =MID(Table12[[#This Row],[Ativo]],1,2) -> 79 | C88: DOIS IRMAOS DO TOCANTINS | D88: DIVINOPOLIS | E88: CENTRO | F88: =IFERROR(_xlfn.XLOOKUP(Table12[[#This Row],[Ativo]],[2]!Pendentes[COD_RELIGADOR],[2]!Pendentes[SS_ORIGINAL]),"CONCLUÍDA") -> CONCLUÍDA | G88: ETO-TELE 964/2026 | I88: Em operação | J88: tanque | K88: =IFERROR(_xlfn.XLOOKUP(Table12[[#This Row],[Ativo]],[2]!Pendentes[COD_RELIGADOR],[2]!Pendentes[DESCRICAO]),"") | L88: 5 | M88: 5 | N88: 5 | O88: 0 | P88: 0 | Q88: 0 | R88: 10 | S88: 0 | T88: =SUM(Table12[[#This Row],[Premissa 1]:[Premissa 8]]) -> 25 | U88: Baixa | V88: Atendimento do Ramal do Boleu (13 UCs), no desarme a jusante penaliza parte 303 UCs rurais
A89: 7955686076 | B89: =MID(Table12[[#This Row],[Ativo]],1,2) -> 79 | C89: DUERE | D89: GURUPI | E89: SUL | F89: =IFERROR(_xlfn.XLOOKUP(Table12[[#This Row],[Ativo]],[2]!Pendentes[COD_RELIGADOR],[2]!Pendentes[SS_ORIGINAL]),"CONCLUÍDA") -> CONCLUÍDA | I89: Ok | J89: - | K89: =IFERROR(_xlfn.XLOOKUP(Table12[[#This Row],[Ativo]],[2]!Pendentes[COD_RELIGADOR],[2]!Pendentes[DESCRICAO]),"") | L89: 5 | M89: 5 | N89: 0 | O89: 0 | P89: 15 | Q89: 0 | R89: 0 | S89: 0 | T89: =SUM(Table12[[#This Row],[Premissa 1]:[Premissa 8]]) -> 25 | U89: Baixa | V89: Fonte alternativa de atendimento do Ramal Bacuri (217 UCs)
A90: 7955946007 | B90: =MID(Table12[[#This Row],[Ativo]],1,2) -> 79 | C90: MIRACEMA DO TOCANTINS | D90: MIRACEMA DO TOCANTINS | E90: CENTRO | F90: =IFERROR(_xlfn.XLOOKUP(Table12[[#This Row],[Ativo]],[2]!Pendentes[COD_RELIGADOR],[2]!Pendentes[SS_ORIGINAL]),"CONCLUÍDA") -> ETO-COEP 00134/2026 | G90: ETO-TELE 969/2026 | K90: =IFERROR(_xlfn.XLOOKUP(Table12[[#This Row],[Ativo]],[2]!Pendentes[COD_RELIGADOR],[2]!Pendentes[DESCRICAO]),"") -> 13/07/2026 PARECER COEP: SUBSTITUIR CONTOLE OU MANDAR MANUTENCIONAR EM CASO DE PRIORIDADE ALTAPARECER DMSL: Necessário substituir a placa de alimentação ca, a mesma está em curto não conseguimos recuperar. (Antiga nota era pra ter sido repassada porém foi baixada indevidamente pela equipe) | L90: 5 | M90: 5 | N90: 5 | O90: 0 | P90: 0 | Q90: 0 | R90: 10 | S90: 0 | T90: =SUM(Table12[[#This Row],[Premissa 1]:[Premissa 8]]) -> 25 | U90: Baixa | V90: Alimentação do serviço auxiliar da Investco e clientes rurais (260 UCs)
A91: 7901110084 | B91: =MID(Table12[[#This Row],[Ativo]],1,2) -> 79 | C91: DIVINOPOLIS | D91: DIVINOPOLIS | E91: CENTRO | F91: =IFERROR(_xlfn.XLOOKUP(Table12[[#This Row],[Ativo]],[2]!Pendentes[COD_RELIGADOR],[2]!Pendentes[SS_ORIGINAL]),"CONCLUÍDA") -> ETO-COEP 00061/2026 | G91: Em proceso de Aquisição | K91: =IFERROR(_xlfn.XLOOKUP(Table12[[#This Row],[Ativo]],[2]!Pendentes[COD_RELIGADOR],[2]!Pendentes[DESCRICAO]),"") -> PARECER COEP: EQUIPAMENTO SELECIONADO PARA COMPRAPARECER DMSL: Serviço Executado: Foi feito análise técnica, testes funcionais e identificado que a parte ativa do equipamento está com defeito. Necessário substituir a parte ativa.FICOU EM OPERAÇÃO? Não- EQUIPE: Carliel e BenvindoSegue SS para verificaçao Rl esta danificado dando passagem de tensão mesmo aberto Sim, quando retornar trazer uma fonte pois a mesma foi removida. | L91: 5 | M91: 5 | N91: 0 | O91: 0 | P91: 0 | Q91: 0 | R91: 10 | S91: 0 | T91: =SUM(Table12[[#This Row],[Premissa 1]:[Premissa 8]]) -> 20 | U91: Baixa | V91: Localizado na fonte principal de atendimento de Divinópolis e Abreulândia
A92: 7908206074 | B92: =MID(Table12[[#This Row],[Ativo]],1,2) -> 79 | C92: DIANOPOLIS | D92: DIANOPOLIS | E92: SUL | F92: =IFERROR(_xlfn.XLOOKUP(Table12[[#This Row],[Ativo]],[2]!Pendentes[COD_RELIGADOR],[2]!Pendentes[SS_ORIGINAL]),"CONCLUÍDA") -> CONCLUÍDA | G92: Em Operação confirmado com os COCM's | I92: Em operação | J92: Tanque | K92: =IFERROR(_xlfn.XLOOKUP(Table12[[#This Row],[Ativo]],[2]!Pendentes[COD_RELIGADOR],[2]!Pendentes[DESCRICAO]),"") | L92: 5 | M92: 5 | N92: 0 | O92: 0 | P92: 0 | Q92: 0 | R92: 10 | S92: 0 | T92: =SUM(Table12[[#This Row],[Premissa 1]:[Premissa 8]]) -> 20 | U92: Baixa | V92: Atendimento do PA Novo Plano (102 UCs)
A93: 7908708116 | B93: =MID(Table12[[#This Row],[Ativo]],1,2) -> 79 | C93: CHAPADA DA NATIVIDADE | D93: DIANOPOLIS | E93: SUL | F93: =IFERROR(_xlfn.XLOOKUP(Table12[[#This Row],[Ativo]],[2]!Pendentes[COD_RELIGADOR],[2]!Pendentes[SS_ORIGINAL]),"CONCLUÍDA") -> ETO-PROT 00165/2026 | G93: Aguardando atualização de informação DMSL | J93: Tanque e controle | K93: =IFERROR(_xlfn.XLOOKUP(Table12[[#This Row],[Ativo]],[2]!Pendentes[COD_RELIGADOR],[2]!Pendentes[DESCRICAO]),"") -> COCMS: 12/08/2026PART ATIVA DO RELIGADOR FOI SUBSTITUIDA.GENTILEZA COMISSIONAR EQUIPAMENTO. SUBSTITUIR PARTE ATIVA DO RELIGADOR 7908708116. LV. ABRIR JUNTE DE ENTRADA E SAIDA DO RELIGADOR PARA POSSIBILITAR SUBSTITUIÇÃO DO MESMO. | L93: 5 | M93: 5 | N93: 0 | O93: 0 | P93: 0 | Q93: 0 | R93: 10 | S93: 0 | T93: =SUM(Table12[[#This Row],[Premissa 1]:[Premissa 8]]) -> 20 | U93: Baixa | V93: Atendimento do PA Xobo (194 UCs)
A94: 7910027196 | B94: =MID(Table12[[#This Row],[Ativo]],1,2) -> 79 | C94: LAGOA DO TOCANTINS | D94: TAQUARALTO | E94: CENTRO | F94: =IFERROR(_xlfn.XLOOKUP(Table12[[#This Row],[Ativo]],[2]!Pendentes[COD_RELIGADOR],[2]!Pendentes[SS_ORIGINAL]),"CONCLUÍDA") -> ETO-COEP 00154/2026 | G94: ETO-TELE 973/2026 | J94: Completo sem o radio | K94: =IFERROR(_xlfn.XLOOKUP(Table12[[#This Row],[Ativo]],[2]!Pendentes[COD_RELIGADOR],[2]!Pendentes[DESCRICAO]),"") -> 13/07/2026 PARECER COEP: NÃO FAZ SENTIDO FAZER A TROCA DE EQUIPAMENTO COMPLETO APENAS POR CAUSA DA FASE B , QUE PARECE SER UM ERRO DE CALIBRAÇÃO.PARECER DMSL: EQUIPAMENTO FICOU EM OPERACAO, RESTABELCIDO PELA KAROL ação remota com a velp porém ele também deve ser realizado substituição por conta da fase B 7910027196 ta com a leitura incorreta na tensão da fase B. Subsituição do Equipamento Completo exceto o Radio. (Antiga nota era pra ter sido repassada porém foi baixada indevidamente pela equipe)PARECER DMSL(22/07/26): O religador está fora de operação desde 11/2025. Necessitando substituição completa em função do defeito de leitura de corrente da fase B. Preservar apenas o radio e antena. | L94: 5 | M94: 5 | N94: 0 | O94: 0 | P94: 0 | Q94: 0 | R94: 10 | S94: 0 | T94: =SUM(Table12[[#This Row],[Premissa 1]:[Premissa 8]]) -> 20 | U94: Baixa | V94: Atendimento do Ramal do Rio Preto (197 UCs)
A95: 7913662076 | B95: =MID(Table12[[#This Row],[Ativo]],1,2) -> 79 | C95: DUERE | D95: GURUPI | E95: SUL | F95: =IFERROR(_xlfn.XLOOKUP(Table12[[#This Row],[Ativo]],[2]!Pendentes[COD_RELIGADOR],[2]!Pendentes[SS_ORIGINAL]),"CONCLUÍDA") -> ETO-COEP 00114/2026 | G95: (REPASSAR PARA ANALISE DMSL) | K95: =IFERROR(_xlfn.XLOOKUP(Table12[[#This Row],[Ativo]],[2]!Pendentes[COD_RELIGADOR],[2]!Pendentes[DESCRICAO]),"") -> 27/07 PARECER COEP: TANQUE DANIFICADO DA 13,5Aberto nota para substituir tanque danificado e chave de entrada fase B danificadaPARECER DMSL: Foi confirmado pela equipe DMSL o defeito do tanque, favor seguir com a substituição e correção da chave de entrada fase B danificada. | L95: 5 | M95: 5 | N95: 0 | O95: 0 | P95: 0 | Q95: 10 | R95: 0 | S95: 0 | T95: =SUM(Table12[[#This Row],[Premissa 1]:[Premissa 8]]) -> 20 | U95: Baixa | V95: Atendimento do Ramal do Bacuri (168 UCs)
A96: 5862236091 | B96: =MID(Table12[[#This Row],[Ativo]],1,2) -> 58 | C96: ALMAS | D96: DIANOPOLIS | E96: SUL | F96: =IFERROR(_xlfn.XLOOKUP(Table12[[#This Row],[Ativo]],[2]!Pendentes[COD_RELIGADOR],[2]!Pendentes[SS_ORIGINAL]),"CONCLUÍDA") -> ETO-COEP 00158/2026 | G96: Em processo logistico | H96: Aguardando geração da EMD | J96: 1 celula | K96: =IFERROR(_xlfn.XLOOKUP(Table12[[#This Row],[Ativo]],[2]!Pendentes[COD_RELIGADOR],[2]!Pendentes[DESCRICAO]),"") -> 27/07 PARECER COEP: PEÇAS REDIRECIONADAS 5856070091 PRIORIDADE MAIOR20/07 PARECER COEP: EQUIPAMENTO ENTREGUE , FAVOR EDITAR A SS COM A DATA PREVISTA DE SUBSTITUIÇÃO NO PARECER DOS COCM´S Realizar substituição da FASE B.Célula da fase B estava com a tampa do contador de tape aberta, pegou chuva e molhou os contatos danificando a peça toda. | L96: 0 | M96: 0 | N96: 0 | O96: 20 | P96: 0 | Q96: - | R96: - | S96: - | T96: =SUM(Table12[[#This Row],[Premissa 1]:[Premissa 8]]) -> 20 | U96: Baixa | V96: Atendimento da LD Vale Rio Doce (Nova Aura Mineradora)
A97: 5836786094 | B97: =MID(Table12[[#This Row],[Ativo]],1,2) -> 58 | C97: PEIXE | D97: PEIXE | E97: SUL | F97: =IFERROR(_xlfn.XLOOKUP(Table12[[#This Row],[Ativo]],[2]!Pendentes[COD_RELIGADOR],[2]!Pendentes[SS_ORIGINAL]),"CONCLUÍDA") -> ETO-COEP 00095/2026 | G97: Levar para analise de religadores furtados no Sul | K97: =IFERROR(_xlfn.XLOOKUP(Table12[[#This Row],[Ativo]],[2]!Pendentes[COD_RELIGADOR],[2]!Pendentes[DESCRICAO]),"") -> 24/07 PARECER COEP:EQUIPAMENTO EM LOGISTICA DE ENTREGA Favor levar outro regulador de tensão, pois o mesmo foi furtado em campo. | L97: 0 | M97: 0 | N97: 0 | O97: 10 | P97: 10 | Q97: - | R97: - | S97: - | T97: =SUM(Table12[[#This Row],[Premissa 1]:[Premissa 8]]) -> 20 | U97: Baixa | V97: Atendimento de clientes rurais na LD Peixe Angical - Peixe
A98: 7919270014 | B98: =MID(Table12[[#This Row],[Ativo]],1,2) -> 79 | C98: PIUM | D98: PARAISO DO TOCANTINS | E98: CENTRO | F98: =IFERROR(_xlfn.XLOOKUP(Table12[[#This Row],[Ativo]],[2]!Pendentes[COD_RELIGADOR],[2]!Pendentes[SS_ORIGINAL]),"CONCLUÍDA") -> ETO-COEP 00159/2026 | G98: (REPASSAR PARA ANALISE DMSL) | K98: =IFERROR(_xlfn.XLOOKUP(Table12[[#This Row],[Ativo]],[2]!Pendentes[COD_RELIGADOR],[2]!Pendentes[DESCRICAO]),"") -> 27/07/2026 PARECER COEP: EM PROCESSO DE AQUISIÇÃO , COMPLETOPARECER COEP: AGUARDANDO RETORNO DO DMSL, EQUIPAMENTO FOI INSTALADO NOVO NA OBRA 0212501060, ENTENDER O PORQUE NÃO FOI REALIZADO COMISSIONAMENTOPARECER DMSL: Substituir Equipamento completo problema na placa de alimentação e na parte ativa, falta colocar placa de identificação correta na topologia, baixar o controle.Equipamento ficou em operação?: naoPendência: simBateria(s) substituída(s)? NÃOEquipe: Kaique/ Benvindo13/07/2026 PARECER COEP: SUBSTITUIÇÃO REALZIADA , FAVOR COMISSIONARPARECER DMSL (22/07/26): Solicito que o laudo de substituição seja anexado, e a SS seja repassada para proteção atribuir a ordem de ajuste, antes de repassar para ETO-TELE.----------------------------------------------PARECER DA PROTEÇÃO: Prosseguir com o comissionamento. Ajustes de religador permanecem os mesmos, disponíveis no APP da Proteção.********************************RELIGADOR N°7919270014 REMANEJADO NA OBRA 0212501060 GENTILEZA, REALIZAR O COMISSIONAMENTO. LAUDO EM ANEXO. COORD EO: 617422, 8830787 | L98: 5 | M98: 5 | N98: 0 | O98: 0 | P98: 0 | Q98: 10 | R98: 0 | S98: 0 | T98: =SUM(Table12[[#This Row],[Premissa 1]:[Premissa 8]]) -> 20 | U98: Baixa | V98: Atendimento de Clientes rurais (48 UCs)
A99: 7926442035 | B99: =MID(Table12[[#This Row],[Ativo]],1,2) -> 79 | C99: MONTE DO CARMO | D99: PONTE ALTA TOCANTINS | E99: CENTRO | F99: =IFERROR(_xlfn.XLOOKUP(Table12[[#This Row],[Ativo]],[2]!Pendentes[COD_RELIGADOR],[2]!Pendentes[SS_ORIGINAL]),"CONCLUÍDA") -> ETO-COEP 00051/2026 | G99: Em processo de aquisição | K99: =IFERROR(_xlfn.XLOOKUP(Table12[[#This Row],[Ativo]],[2]!Pendentes[COD_RELIGADOR],[2]!Pendentes[DESCRICAO]),"") -> PARECER COEP: EQUIPAMENTO SELECIONADO PARA COMPRAPARECER DMSL: Data: 12/03/2026 Serviço Executado:- Análise técnica constatou:- Parte ativa do equipamento danificada: necessita substituição- Trafo danificado: foi feitos testes nas buchas secundárias o mesmo não chega tensão - Vazamento de óleo - Necessita substituiçãoEquipamento ficou em operação? NãoPendências:- Solicitar limpeza de faixa para acesso ao equipamento- Trocar parte ativa do equipamento- Substituir o trafoEquipe: Carliel e João VitorSegue nota para envia equipe verificar falha de comunicação e automação no RL-7926442035 feito primeiro ataque com equipe 035OP02, porém sem sucesso. | L99: 5 | M99: 5 | N99: 0 | O99: 0 | P99: 0 | Q99: 0 | R99: 10 | S99: 0 | T99: =SUM(Table12[[#This Row],[Premissa 1]:[Premissa 8]]) -> 20 | U99: Baixa | V99: Atenidmento do PA Principado (200 UCs)
A100: 7954668084 | B100: =MID(Table12[[#This Row],[Ativo]],1,2) -> 79 | C100: DIVINOPOLIS | D100: DIVINOPOLIS | E100: CENTRO | F100: =IFERROR(_xlfn.XLOOKUP(Table12[[#This Row],[Ativo]],[2]!Pendentes[COD_RELIGADOR],[2]!Pendentes[SS_ORIGINAL]),"CONCLUÍDA") -> CONCLUÍDA | J100: Display | K100: =IFERROR(_xlfn.XLOOKUP(Table12[[#This Row],[Ativo]],[2]!Pendentes[COD_RELIGADOR],[2]!Pendentes[DESCRICAO]),"") | L100: 5 | M100: 5 | N100: 0 | O100: 0 | P100: 0 | Q100: 0 | R100: 10 | T100: =SUM(Table12[[#This Row],[Premissa 1]:[Premissa 8]]) -> 20 | U100: Baixa | V100: Atendimento do PA Piedade (125 UCs)
...

Sheet BASE SS_OS
A1: NUMERO_SS | B1: NUMERO_OS | C1: NUM_OBRA | D1: ORIGEM_SS | E1: DEFEITO_SS | F1: ORIGEM | G1: DEFEITO | H1: ESQUEMA | I1: TASK | J1: ANO | K1: ORG_SOLIC | L1: COD_EQUIPE | M1: ALIMENTADOR | N1: NUM_TRAFO | O1: COORD_X | P1: COORD_Y | Q1: COD_GIS | R1: CRITICIDADE_SS | S1: SITUACAO_SS | T1: DATA_ABERTURA_SS | U1: DATA_TERMINO_SS | V1: DATA_LIMITE_SS | W1: DESCICAO_DO_ATIVO | X1: LOCALIDADE | Y1: SOLICITANTE | Z1: RURA_URBANO | AA1: TIPOSS | AB1: DESCRIPTION
A2: ETO-COEP 00117/2026 | J2: 2026 | K2: COI | L2: ETO-COEP | M2: LD05028074 | N2: 5800090147 | O2: 941293 | P2: 8659898 | Q2: 190-15787264 | R2: EMERGENCIAL | S2: SS PENDENTE | T2: 46188.582 | V2: 46191.582 | W2: REGULADOR DE TENSAO DE DIST. - 34.5 | X2: TAIPAS DO TOCANTINS | Y2: ZENILSON MOREIRA SANTOS | Z2: RURAL | AA2: INDISPONIBILIDADE PARA OPERAÇÃO | AB2: PARECER COEP: AGUARDANDO RETORNO DO DMSLREGULADOR 5800090147 SEM COMUNICAÇÃO E TRAVANDO TAP´S - REALIZAO PRIMEIRO ATAQUE SEM SUCESSO.PARECER DMSL: Favor, substituir a célula da fase C do RT 5800090147 pois o microswitch que renconhece o neutro do regulador está com defeito.Equipamento ficou operando devido ser possível manobrar de forma manual.
A3: ETO-RD-PO 00097/2026 | J3: 2026 | K3: MANUT | L3: ETO-RD-PO | M3: LD01051035 | N3: 5800291035 | O3: 819396 | P3: 8780710 | Q3: 190-30990216 | R3: PROGRAMAVEL | S3: SS PENDENTE | T3: 46112.442 | V3: 46512.442 | W3: REGULADOR DE TENSAO DE DIST. - 34.5 | X3: MONTE DO CARMO | Y3: JULIA GRAZYELLE BRITO OLIVEIRA | Z3: RURAL | AA3: INDISPONIBILIDADE PARA OPERAÇÃO | AB3: PARECER DMSL: Feito testes funcionais nas 3 células do banco as mesmas corresponderam aos testes. Será necessário fazer a correção da malha de terra, baixar o banco completo pois está muito alto dificultando as atividades da equipe, substituir as 3 chaves facas do lado Fonte e as 3 do lado Carga instalar suporte inclinado das chaves para facilitar as manobras. Colocar cinta no controle RUA abaixar o mesmo, pois está muito alto e fixado com um mosquetão oval, quando retornar para colocar em operação levar 3 baterias de 7a e rele rua.Obs.: Fizeram melhoria na malha de terra, mas não está dentro do aceitável! As outras pendências continuam, favor corrigir. Equipamento ficou em operação?: Não - Equipe: Benvindo e Kaique- SS ANTIGA ETO-TELE 358/2026
A4: ETO-COEP 00187/2025 | D4: REGULADOR DE TENSÃO | E4: ILEGÍVEL | J4: 2025 | K4: COI | L4: ETO-COEP | M4: LD02010153 | N4: 5800371025 | O4: 714151 | P4: 9152942 | Q4: 190-15773574 | R4: EMERGENCIAL | S4: SS PENDENTE | T4: 45905.614 | V4: 45908.614 | W4: REGULADOR DE TENSAO DE DIST. - 34.5 | X4: ARAPOEMA | Y4: DIOMAR FERREIRA PEREIRA | Z4: URBANO | AA4: INDISPONIBILIDADE PARA OPERAÇÃO | AB4: PARECER COEP: AVALIAR COM O LEANDRO, PROVAVELMENTE SÓ COMPRAPARECER DMSL: Após testes foi constatado defeito nos relés da fase A e B, Modelo Toshiba TBR 1000. Se possível, substituir os relés das 3 fases por controle RUA, disponibilizar os cabos de ligação entre o tanque e o controle para possibilitar a compatibilização do equipamento. Fornecer kit de comunicação, rádio, antena, etc.Segue nota para veriifcar falha em regulador de tensão N: 5800371025 dentro S/E Arapoema , equipamento esta com 2 reles com falha marca toshiba .
A5: ETO-RD-DP 00404/2026 | D5: REGULADOR DE TENSÃO | E5: ILEGÍVEL | J5: 2026 | K5: COI | L5: ETO-RD-DP | M5: LD04002091 | N5: 5800438116 | O5: 859820 | P5: 8711174 | Q5: 190-32303850 | R5: PROGRAMAVEL | S5: SS PENDENTE | T5: 46204.504 | V5: 46604.504 | W5: REGULADOR DE TENSAO DE DIST. - 34.5 | X5: CHAPADA DA NATIVIDADE | Y5: DIOMAR FERREIRA PEREIRA | Z5: RURAL | AA5: INDISPONIBILIDADE PARA OPERAÇÃO | AB5: 01/07 PARECER COEP: DENER INFORMOU QUE TEM AS PEÇAS SOBRESSALENTES DE OBRA PARA UTILIZAR, REPASSEREI AO POSTO DO ETO-RD-DP PARA AS TRATATIVAS, FAVOR INFORMAR PREVISÃO DE SUBSTIUIÇÃO E PREENCHER A PLANILHA ASSIM COMO PREENCHER A DESCRIÃO ANTES DE PASSAR PARA PROTEÇÃO FAZER OS AJUSTES30/06PARECER COEP: AGUARDANDO COCM'S CRIAREM OBRA PARA ENTREGA DO MATERIALSegue nota para normalizar falha em regulador N:5800438116 - Chapada da natividade .equipamento está com fase B e C travada .OBS: a fase B esta sinalizando falha , equipamento não insere TAP negativo na fase B e C , o mesmo ficou no TAP zerado e bloqueado .PARECER DMSL (18/08/2025): Foi feito teste de elevar e abaixar nas fases B e C e o mesmo só aceita elevar os taps, constatando que o mercanismo da chave reversoura polaridade está com defeito. Número de série fase B EI7030 e Número de série fase C EI7040. Substituir as fases B e C.Foi constatado que a placa F do controle está com defeito.
A6: ETO-COEP 00115/2026 | D6: DEFEITO ELETRICO | E6: RELÉ REGULADOR DE TENSÃO | J6: 2026 | K6: COI | L6: ETO-COEP | M6: AL01065015 | N6: 5800859011 | O6: 797626 | P6: 9011795 | Q6: 190-15787179 | R6: EMERGENCIAL | S6: SS PENDENTE | T6: 46185.625 | V6: 46188.625 | W6: REGULADOR DE TENSAO DE DIST. - 13.8 | X6: TUPIRAMA | Y6: DELIO NUNES OSCAR | Z6: RURAL | AA6: INDISPONIBILIDADE PARA OPERAÇÃO | AB6: PARECER COEP: EQUIPAMENTO EM ROTA DE ENTREGAPARECER DMSL: *FEEDBACK EQUIP. ESPECIAIS**Nº DO EQUIPAMENTO:* 5800859011*TIPO EQUIPAMENTO:* RT ITB *TIPO DE COMUNICAÇÃO:* Não *DATA DA MANUTENÇÃO:* 09/06/2026*SID:* 3195/2026*DESCRIÇÃO:* _ Foi identificado relé da fase C com defeito conforme orientação da supervisão e necessário realiza retrofit para instalação de controle rua.*FICOU EM OPERAÇÃO* Não*PENDÊNCIA:* Realizado Retrofit *DADOS DIVERGENTES DA PROGRAMAÇÃO:* Não*BATERIA SUBSTITUÍDA?:* Não*TIPO DE BATERIA:**EQUIPE:* Edeglan e Brunno.Observação: trocar por um controle RUA.------------------------------------------------------------------------------------------Enviar equipe do DMSL, para fazer correção no RT 5800859011, o mesmo está com o displey da fase C apagado , dificutando realizar manobras no mesmo, emvirtude disso o mesmo ficou BAY PASSADO EM CAMPO
A7: ETO-COEP 00221/2025 | J7: 2025 | K7: SCADA | L7: ETO-COEP | M7: LD03028074 | N7: 5800961074 | O7: 971526 | P7: 8714400 | Q7: 190-15814905 | R7: PROGRAMAVEL | S7: SS PENDENTE | T7: 45996.663 | V7: 46396.663 | W7: REGULADOR DE TENSAO DE DIST. - 34.5 | X7: DIANOPOLIS | Y7: LARA SOARES FARIAS | Z7: RURAL | AA7: INDISPONIBILIDADE PARA OPERAÇÃO | AB7: PARECER COEP: EQUIPAMENTO SELECIONADO PARA COMPRASubstituir as 3 células- Melhoria na malha de aterramento - Melhoria no circuito de aterramento qua aterra as células.- Substituir conectores paralelos
A8: ETO-COEP 00077/2026 | D8: EQUIPAMENTO | E8: QUEIMADO | J8: 2026 | K8: COI | L8: ETO-COEP | M8: AL03062013 | N8: 5801866013 | O8: 733022 | P8: 8870961 | Q8: 190-35644534 | R8: EMERGENCIAL | S8: SS PENDENTE | T8: 46132.325 | V8: 46135.325 | W8: REGULADOR DE TENSAO DE DIST. - 13.8 | X8: PARAISO DO TOCANTINS | Y8: Felipe Batista Ferrreira | Z8: RURAL | AA8: INDISPONIBILIDADE PARA OPERAÇÃO | AB8: PARECER COEP: EM PROCESSO DE ENTREGAPARECER DMSL: RT 5801866013Serviço Executado: Feito a medição da malha de terra. Identificado infiltração na caixa de passagem da célula da fase C do banco regulador de tensão, será necessário fazer a substituição da mesma! Ficar atento na hora da substituição, deverá ser substituída a célula do lado da BR.Obs.: Será necessário baixar todo o banco pelo menos um metro, as buchas estão muito próximas a parte energizada não oferecem segurança para equipe no momento do ensaio elétrico.Equipamento ficou em operação?: Não Possui nobreak: SimPossui antena: SimPossui rádio:SimPendência: SimData da bateria: Equipe: Benvindo e Kaique._______________________________________________RT 5801866013BY PASSADO DEVIDO DEFEITO EM CELULA BEMVINDO ESTEVE NO LOCAL JUNTO AO COD .NECESSARIO TRATATIVA PARA MESMA .FASE DANIFICADO C
A9: ETO-RD-PA 00434/2026 | D9: FORA DE SERVIÇO | E9: RELÉ REGULADOR DE TENSÃO | J9: 2026 | K9: COI | L9: ETO-RD-PA | M9: AL01102271 | N9: 5803327001 | O9: 770823 | P9: 8872358 | Q9: 190-15851809 | R9: EMERGENCIAL | S9: SS PENDENTE | T9: 46204.507 | V9: 46207.507 | W9: REGULADOR DE TENSAO DE DIST. - 13.8 | X9: PORTO NACIONAL | Y9: HELDER SILVA CARVALHO | Z9: RURAL | AA9: INDISPONIBILIDADE PARA OPERAÇÃO | AB9: 01/07 PARECER COEP: FOI CONFIRMADO COM A OPERAÇÃO QUE O EQUIPAMENTO SEGUIU O FLUXO INTEIRO DE COMISSIONAMENTO, PROTEÇÃO, FAVOR EXPLICAR O QUE FOI REALIZADO E SE EQUIPAMENTO ESTÁ OPERANDO, SENÃO ESTIVER EXPLICAR O QUE FOI FEITO NELE30/06PARECER COEP: REPASSAR DIRETAMENTE PARA OS COCM'SRegulador 5803327001 fora de operação, by passado em campo com painel de comunicação com cabos desconectados tensão 13.8.parecer DMSL: Feedback Equip. EspeciaisRT 5803327001RELÉ RUASid: 4844Data: 19/09/2025Serviço realizado:*Equipamento foi remanejado, 7 km da sua localização sentido Palmas necessário comissionamento completo*Equipamento com um dos cabos umbilicais danificado.* aterramento bucha FC não esta interligada corretamente * para-raios estão no mesmo aterramento da bucha FC.* Tranques muito alto e próximo da rede não permitindo o comissionamento com segurança.* Controle alto demais tem que baixar Equipamento ficou em operação?: nãoPendência: sim, precisa comissionar completoOBS; reprogramar equipamento.Bateria(s) substituída(s) NÃOEquipe: Ellisfran, Ana Maria PARECER DMSL: Data 03/12/2025-Equipe: Carliel e BenvindoServiço executado foi ensaiado as três células Equipamento ficou em operação: Não Pendência: sim, Instalar controle completo, e fazer melhoria na malhar de aterramento
A10: ETO-RD-PS 00289/2026 | D10: OUTROS | J10: 2026 | K10: MANUT | L10: ETO-RD-PS | M10: LD01062013 | N10: 5827102054 | O10: 730120 | P10: 8847453 | Q10: 190-15843147 | R10: ALTA | S10: SS PENDENTE | T10: 46202.723 | V10: 46262.723 | W10: REGULADOR DE TENSAO DE DIST. - 34.5 | X10: PUGMIL | Y10: JULIA GRAZYELLE BRITO OLIVEIRA | Z10: RURAL | AA10: INDISPONIBILIDADE PARA OPERAÇÃO | AB10: PARECER COEP:NÃO É POSSÍVEL RETORNAR COM O CONTROLE COMPLETO , MAS DARIA PARA FAZER A MELHORIA NA MALHA DE ATERRAMENTO , ENCAMINHANDO PARA OS COCM'S PARA REALIZAREM A MELHORIAparecer DMSL: :Nobreack com defeito, rele queimado, cabo de comunicação entre o rádio e o rele danificado, malha de aterramento está com a resistência alta!Feito reparo no cabo, substituído nobreack, e rele. Se possível retornar com controle completo pq o q está em campo teve infiltração de água, abrir chamado no scada para atualizar base do equipamento pois o mesmo está com a base antiga, fazer correção da malha de aterramento.Equipamento ficou em operação?: Não Pendência: sim, levar controle novo, fazer correção da malha de terra, levar suporte para fixar antena. OBS; reprogramar equipamento.Bateria(s) substituída(s) simEquipe: Benvindo e Carliel SOLICITAMOS CONTROLE COMPLETO
A11: ETO-COEP 00095/2026 | D11: REGULADOR DE TENSÃO | E11: ILEGÍVEL | J11: 2026 | K11: COI | L11: ETO-COEP | M11: LD01066094 | N11: 5836786094 | O11: 782353 | P11: 8664418 | Q11: 190-34648613 | R11: EMERGENCIAL | S11: SS PENDENTE | T11: 46160.578 | V11: 46163.578 | W11: REGULADOR DE TENSAO DE DIST. - 34.5 | X11: PEIXE | Y11: IZAIAS SANTOS BRAGA JUNIOR | Z11: RURAL | AA11: INDISPONIBILIDADE PARA OPERAÇÃO | AB11: PARECER COEP: EQUIPAMENTO FURTADO LEVAR PARA ANÁLISE COM O LEANDRO, NO ENTANTO SEGUE NA CATEGORIA DE COMPRA.Favor levar outro regulador de tensão, pois o mesmo foi furtado em campo.
A12: ETO-COEP 00167/2025 | J12: 2025 | K12: COI | L12: ETO-COEP | M12: AL01054060 | N12: 5844630060 | O12: 792803 | P12: 9144437 | Q12: 190-29126245 | R12: EMERGENCIAL | S12: SS PENDENTE | T12: 45877.703 | V12: 45880.703 | W12: REGULADOR DE TENSAO DE DIST. - 13.8 | X12: NOVA OLINDA | Y12: CASSIO GOMES BONFIM | Z12: RURAL | AA12: INDISPONIBILIDADE PARA OPERAÇÃO | AB12: PARECER COEP: EQUIPAMENTO EM ROTA DE ENTREGAPARECER DMSL: Célula da fase A encontra-se com vazamento de óleo no pé da torneira. Necessário substituição da célula.Aberto nota para verificar vazamento de óleo fase A no RT 5844630060 - RDU Nova Olinda
A13: ETO-COEP 00127/2026 | D13: OUTROS | E13: COMUTAÇÃO INDEVIDA | J13: 2026 | K13: COI | L13: ETO-COEP | M13: AL01038009 | N13: 5850308009 | O13: 775230 | P13: 9023715 | Q13: 190-72598729 | R13: EMERGENCIAL | S13: SS PENDENTE | T13: 46210.649 | V13: 46213.649 | W13: REGULADOR DE TENSAO DE DIST. - 13.8 | X13: GUARAI | Y13: CLESIO CARVALHO MOURA | Z13: URBANO | AA13: INDISPONIBILIDADE PARA OPERAÇÃO | AB13: PARECER COEP: Equipamento em operaçãpo no SCADAPARECER DMSL: Após testes, foi constatado que o RT 5850308009 encontra-se com controle danificado, sendo necessária substituição do mesmo.Regulador de tensão 5850308009 quando esta em Automatico esta deixa um fase muito baixa. foi deixado uma fase Manual e transferida parte do alimentaor.
A14: ETO-RD-PS 00323/2025 | D14: REGULADOR DE TENSÃO | E14: RELÉ REGULADOR DE TENSÃO | J14: 2025 | K14: COI | L14: ETO-RD-PS | M14: LD05050008 | N14: 5853360007 | O14: 782525 | P14: 8944001 | Q14: 190-36538096 | R14: PROGRAMAVEL | S14: SS PENDENTE | T14: 45946.701 | V14: 46346.701 | W14: REGULADOR DE TENSAO DE DIST. - 34.5 | X14: MIRACEMA DO TOCANTINS | Y14: ZENILSON MOREIRA SANTOS | Z14: RURAL | AA14: INDISPONIBILIDADE PARA OPERAÇÃO | AB14: REALIZAR TESTES NO EQUIPAMENTO E CONFERIR MEDIÇÕES DA MALHA DE ATERRAMENTO. ESTANDO OK, COMISSIONAR EQUIPAMENTO E COLOCA-LO EM OPERAÇÃO.AJUSTES DISPONIVEIS NO APP DA PROTEÇÃdmsl : N° do Equipamento:*RT 5853360007 MIRACEMASID: 2493/2025Data: 13/05/2025Serviço Executado Provavelmente ocorreu uma descarga no equipamento comprometendo a malha!Será necessário fazer melhoria da malha de aterramento, fazer toda interligação da mesma! Feito ensaios de isolação das 3 células do equipamento, isolação está ok, quando retornar para colocar em operação levar 3 baterias de 7a.Equipamento ficou em operação?: Não Equipe: Benvindo e Jardel
A15: ETO-COEP 00160/2025 | D15: REGULADOR DE TENSÃO | E15: QUEIMADO | J15: 2025 | K15: COI | L15: ETO-COEP | M15: LD02072001 | N15: 5854566043 | O15: 807104 | P15: 8767918 | Q15: 190-15797426 | R15: EMERGENCIAL | S15: SS PENDENTE | T15: 45863.592 | V15: 45866.592 | W15: REGULADOR DE TENSAO DE DIST. - 34.5 | X15: SILVANOPOLIS | Y15: DANIEL DAS NEVES TEIXEIRA | Z15: RURAL | AA15: INDISPONIBILIDADE PARA OPERAÇÃO | AB15: PARECER COEP: EQUIPAMENTO SELECIONADO PARA COMPRAboa noite,segue SS para as devidas tratativas com equipe de manutenção com apoio de equipe de linha viva substituir regulador de tensão 5854566043 queimado célula fase c, LD Porto / Silvanópolis mesmo deverá ser substituído com apoio de equipe de linha viva PARECER DMSL: Foi realizado inspeção visual e ensaios de isolação, relação de transformação e resistência de enrolamento. A fase B está danificada e será necessário substituir a mesma. Malha de aterramento está relativamente boa e conectada. Fase A e C passaram nos ensaios. Substituir fase B.
A16: ETO-COEP 00199/2025 | J16: 2025 | K16: COI | L16: ETO-COEP | M16: AL02017017 | N16: 5855411017 | O16: 754714 | P16: 8906531 | Q16: 190-31114527 | R16: EMERGENCIAL | S16: SS PENDENTE | T16: 45930.615 | V16: 45933.615 | W16: REGULADOR DE TENSAO DE DIST. - 13.8 | X16: BARROLANDIA | Y16: ZENILSON MOREIRA SANTOS | Z16: RURAL | AA16: INDISPONIBILIDADE PARA OPERAÇÃO | AB16: PARECER COEP: EQUIPAMENTO EM ROTA DE ENTREGASEM COMUNICAÇÃO, FALHA DE ALIMENTAÇÃO - REALIZADO PRIMEIRO ATAQUE SEM SUCESSO.PARECER DMSL: 17/09/2025 Equipamento ficou em operação? Não Pendência: sim. Equipamento ficou Bay passado levar controle COMPLETO para trocar. ellisfran
A17: ETO-COEP 00130/2026 | J17: 2026 | K17: COI | L17: ETO-COEP | M17: LD04002091 | N17: 5856070091 | O17: 905857 | P17: 8717852 | Q17: 190-55087821 | R17: BAIXA | S17: SS PENDENTE | T17: 46210.72 | V17: 46390.72 | W17: REGULADOR DE TENSAO DE DIST. - 34.5 | X17: ALMAS | Y17: LEONARDO SIQUEIRA AMORIM | Z17: RURAL | AA17: INDISPONIBILIDADE PARA OPERAÇÃO | AB17: PARECER DMSL: não foi regularizado a instalação do equipamento, nota repassada conforme alinhado com o supervisor.____________________________________________COCMS 26.03.26. SS REPASSADA PARA COEP PROVIDENCIAR MATERIAL. NÃO TEMOS AS PÇ EM ESTOQUE PARA FAZER A SUBSTITUIÇÃO. Solicitação de serviço para reposição de equipamentos furtados .COEP: Equipamento fornecido ao COCM-S para regularização.COCMS: Equipamento substituido conforme solicitado. Gentileza comissionar.PARECER DA PROTEÇÃO:SEGUE NOTA REPASSADA PARA DMSL COMISSIONAR.ENG° IRLLEY CASTELO BRANCOPARECER DMSL(23/09/2025): Feito a parte de comunicação, fechando enlace, configuração do rádio GE. Feito a medição de aterramento. Após uma inspeção, foi identificado que o regulador de tensão está instalado errado, carga está para o lado de fonte e fonte está do lado de carga. O certo é a fonte vim de almas, atualmente está vindo de natividade. Favor fazer a instalação correta.
A18: ETO-RD-DP 00403/2026 | D18: REGULADOR DE TENSÃO | J18: 2026 | K18: COPC | L18: ETO-RD-DP | M18: LD04002091 | N18: 5856156091 | O18: 899501 | P18: 8714782 | Q18: 190-38238593 | R18: PROGRAMAVEL | S18: SS PENDENTE | T18: 46202.737 | V18: 46602.737 | W18: REGULADOR DE TENSAO DE DIST. - 34.5 | X18: ALMAS | Y18: Leonardo Sousa de Lima | Z18: RURAL | AA18: INDISPONIBILIDADE PARA OPERAÇÃO | AB18: DCMD 26.03.2026. SS REPASSADA PARA COEP PROVIDENCIAR MATERIAL. NÃO TEMOS O MATERIAL EM ESTOQUE PARA SUBSTITUIÇÃO. COEP: Equipamento fornecido ao COCM-S para regularização.PARECER COEP: EQUIPAMENTOS JÁ FORNECIDOS PARA OS COCM'S PARA REGULARIZAÇÃOPARECER DA PROTEÇÃO:EQUIPAMENTOS FURTADOS. PARA AQUISIÇÃO DAS CELULAS DE REPOSIÇÃO, FAVOR CONSULTAR OS DADOS DE PLACA EM ANEXO.PARECER DA PROTEÇÃO:COMISISONAR RT 5856156091 LD DIANOPOLIS A NATIVIDADE. NECESSARIO REALIZAR MEDIÇÕES DA RESISTENCIA DA MALHA DE ATERRAMENTO.AJUSTES DISPONIVEIS NO APP DA PROTEÇÃO.RELIGADOR N° 5856156091 INSTALADO NA OBRA 0502400526 GENTILEZA, REALIZAR O COMISSIONAMENTO. LAUDO EM ANEXO. COORD EO: 899501, 8714782
A19: ETO-COEP 00123/2025 | D19: REGULADOR DE TENSÃO | J19: 2025 | K19: COPC | L19: ETO-COEP | M19: LD03005098 | N19: 5858783119 | O19: 845266 | P19: 9339297 | Q19: 190-57123183 | R19: ALTA | S19: SS PENDENTE | T19: 45841.594 | V19: 45901.594 | W19: REGULADOR DE TENSAO DE DIST. - 34.5 | X19: SAO BENTO DO TOCANTINS | Y19: Thais Jordanna Jesus Silva | Z19: RURAL | AA19: INDISPONIBILIDADE PARA OPERAÇÃO | AB19: PARECER COEP: ERRO NA INSTALAÇÃO EQUIPAMENTO SELECIONADO PARA COMPRAPARECER DMSL: 16/06/2025-SERVIÇO EXECUTADO: Ao chegar no equipamento para realizar comissionamento, foi constatato que as 3 células estavam com a tampa de inspeção abertas e sem os para-raios. Constatado também que foi furtado todo o óleo isolante das 3 células, sendo necessário a substituição das 3 células. FICOU EM OPERAÇÃO?: Não PENDÊNCIA: Substituir as 3 células
A20: ETO-RD-PA 00326/2026 | D20: REGULADOR DE TENSÃO | J20: 2026 | K20: COPC | L20: ETO-RD-PA | M20: AL01102271 | N20: 5860621001 | O20: 752964 | P20: 8877090 | Q20: 190-35910322 | R20: ALTA | S20: SS PENDENTE | T20: 46157.6 | V20: 46217.6 | W20: REGULADOR DE TENSAO DE DIST. - 13.8 | X20: PORTO NACIONAL | Y20: Leonardo Sousa de Lima | Z20: RURAL | AA20: COMISSIONAMENTO | AB20: PARECER DMSL: 31/03/2026Serviço Executado: realizado a medição da malha de aterramento e vistoria do equipamento.Equipamento ficou em operação?: Não Possui nobreak: SimPossui antena: SimPossui rádio:NãoPendência:* Abaixar o controle rua* ¿Abaixar as 3 células do banco regulador de tensão, pois além de dificultar o trabalho da equipe no momento dos ensaios elétricos não oferece segurança.Equipe: Benvindo e Kaique-------------------------------------------------------------------------------------------------------PARECER DA PROTEÇÃO:COMISSIONAR RT 5860621001 AL 01 SE LUZIMANGUES INDUSTRIAL. NECESSARIO CONFERIR MALHA DE ATERRAMENTO ANTES DE INSERIR O ATIVO NO SISTEMA.AJUSTES DISPONIVEIS NO APP DA PROTEÇÃO.REGULADOR N° 5860621001 INSTALADO NA OBRA 0202300494 GENTILEZA, REALIZAR O COMISSIONAMENTO. LAUDO EM ANEXO. COORD EO: 752965, 8877090PARECER DMSL: Feedback Equip. EspeciaisRT 5860621001RELÉ RUAData: 22/08/2025Serviço Executado: realizado a medição da malha de aterramento e vistoria do equipamento.Equipamento ficou em operação?: Não Possui nobreak: SimPossui antena: SimPossui rádio:NãoPendência:1 - abaixar os 3 tanques2 - abaixar o controle3 - instalar aterramento para o FC e carcaça4 - Aterrar o controle5 - cabos de conexão das buchas estão muito próximos podendo ocasionar curto6 - Distância de segurança entre as buchas e as chaves é inadequada.7 - Não contém cabo da antena8 - Não contém rádio9 - Não contém os conectores para confecção dos cabos10 - Não contém placa de topologia nem numeração pintada no poste para identificação do equipamentoEquipe: Ana Maria e Ellisfran
A21: ETO-COEP 00223/2025 | J21: 2025 | K21: SCADA | L21: ETO-COEP | M21: LD05002091 | N21: 5862236091 | O21: 914121 | P21: 8704596 | Q21: 190-52618825 | R21: PROGRAMAVEL | S21: SS PENDENTE | T21: 45999.468 | V21: 46399.468 | W21: REGULADOR DE TENSAO DE DIST. - 34.5 | X21: ALMAS | Y21: LARA SOARES FARIAS | Z21: RURAL | AA21: INDISPONIBILIDADE PARA OPERAÇÃO | AB21: PARECER COEP: AGUARDANDO COCM´s GERAREM A OBRA COM ABERTURA CONTABIL DENER SOARESRealizar substituição da FASE B.Célula da fase B estava com a tampa do contador de tape aberta, pegou chuva e molhou os contatos danificando a peça toda.
A22: ETO-RD-GR 00538/2026 | D22: REGULADOR DE TENSÃO | J22: 2026 | K22: COPC | L22: ETO-RD-GR | M22: LD01065015 | N22: 5865120195 | O22: 889017 | P22: 9016857 | Q22: 190-38281711 | R22: ALTA | S22: SS PENDENTE | T22: 46160.366 | V22: 46220.366 | W22: REGULADOR DE TENSAO DE DIST. - 34.5 | X22: CENTENARIO | Y22: Leonardo Sousa de Lima | Z22: RURAL | AA22: INDISPONIBILIDADE PARA OPERAÇÃO | AB22: PARECER DMSL:PENDÊNCIA: Realizar melhoria no aterramento por ser tratar de um terreno muito arenoso, e há pendências por parte do time da proteção, os ajustes do RT não estão disponíveis para inserção no referido equipamento.DATA DA MANUTENÇÃO: 12/03/202EQUIPE: Brunno e Edeglan.***********************PARECER DA PROTEÇÃO:FAVOR COMISSIONAR REGULADOR 5865120195 – LD Santa Maria Ramal Centenário e Recursolândia – 34,5kV. AJUSTE REALIZADO, DISPONÍVEL NO APP DA PROTEÇÃO.*********************** INSTALADO NA OBRA 0702400720 GENTILEZA, REALIZAR O COMISSIONAMENTO.LAUDO EM ANEXO.COORD EO: 889017, 9016857
A23: ETO-COEP 00084/2026 | D23: RELÉ | E23: ILEGÍVEL | J23: 2026 | K23: COI | L23: ETO-COEP | M23: AL01062013 | N23: 7900117013 | O23: 731274 | P23: 8875436 | Q23: 190-17421714 | R23: ALTA | S23: SS PENDENTE | T23: 46136.678 | V23: 46196.678 | W23: RELIGADOR DE LINHA - 15,0kV | X23: PARAISO DO TOCANTINS | Y23: DIOMAR FERREIRA PEREIRA | Z23: URBANO | AA23: INDISPONIBILIDADE PARA OPERAÇÃO | AB23: PARECER COEP: PREVISÃO DE ENTREGA AOS COCM'S 01/07Segue nota para correção de anomalia e provável substituição de religador , religador 7900117013 -RDU - Paraiso .OBS: equipe DMSL Elisfran estava atualizando firmware no equipamento , porém relé parou de funcionar devido essa atualização , sendo necessário sua substituição .em campo o modelo e cooper Form6 , segundo tecnico deve ser substituído por um Noja .Repassado para o COEP para aquisição do equipamento e posterior repasse para o COCM.
A24: ETO-COEP 00087/2026 | D24: RELÉ | E24: INSPEÇÃO VISUAL | J24: 2026 | K24: COI | L24: ETO-COEP | M24: LD03040003 | N24: 7900453110 | O24: 727212 | P24: 8773164 | Q24: 190-17412271 | R24: EMERGENCIAL | S24: SS PENDENTE | T24: 46139.616 | V24: 46142.616 | W24: BLOCO RELIGADOR DE LINHA | X24: SANTA RITA DO TOCANTINS | Y24: WESLEY MARCAL MENDES DE OLIVEI | Z24: RURAL | AA24: INDISPONIBILIDADE PARA OPERAÇÃO | AB24: 30/06.PARECER COEP: ALINHADO COM O ALLAN REMANEJAMOS PARTE ATIVA PARA ATENDER 7933726256PARECER COEP: Aproveitar controle cooper se possível em outro local, previsão de chegada do material dia 01/07 para substituiçãoFavor verificar o RL 7900453110, pois o mesmo aceita comando de fechamento, porém fecha em campo e no SCADA continua aberto e só abre através de equipe em campo. Parecer Dmsl:Equipamento está com defeito na parte ativa, não aceita o comando de fechamento. Será necessário substituir o equipamento completo.Equipamento ficou em operação?: _SIM_a pedido do COS ficou em operação, a operação está ciente da necessidade de substituir.Pendência: Sim, será necessário substituir o equipamento.
A25: ETO-COEP 00125/2026 | D25: BUCHA MT - CARGA (C) | E25: QUEIMADO | J25: 2026 | K25: COI | L25: ETO-COEP | M25: LD02424015 | N25: 7900525015 | O25: 835984 | P25: 8971402 | Q25: 190-17404244 | R25: EMERGENCIAL | S25: SS PENDENTE | T25: 46210.644 | V25: 46213.644 | W25: BLOCO RELIGADOR DE LINHA | X25: PEDRO AFONSO | Y25: CLEIDSON RODRIGUES VIEIRA | Z25: RURAL | AA25: INDISPONIBILIDADE PARA OPERAÇÃO | AB25: PARECER COEP: É PARA REALIZAR A SUBSTITUIÇÃO DO RELIGADOR OU DAS BUCHAS, CASO SEJA BUCHAS , REPASSAR PARA OS COCM'S , CASO NÃO SEJA ESPECIFIQUE O MODELO , E A TENSÃO, FICO NO AGUARDO DO RETORNONota para manutenção substituir religador 7900525015 que está com as buchas de entrada danificadas fase A estourada e bc danificadas Local LD Pedro Afonso A Chaparral
A26: ETO-COEP 00102/2025 | D26: FORA DE SERVIÇO | J26: 2025 | K26: MANUT | L26: ETO-COEP | M26: LD02010004 | N26: 7900532053 | O26: 799329 | P26: 9250367 | Q26: 190-17512744 | R26: ALTA | S26: SS PENDENTE | T26: 45803.621 | V26: 45863.621 | W26: RELIGADOR DE LINHA - 38kV | X26: PIRAQUE | Y26: EDNA MARIA DOS SANTOS PINTO | Z26: URBANO | AA26: INDISPONIBILIDADE PARA OPERAÇÃO | AB26: 30/06-EQUIPAMENTO EM OPERAÇÃO NO SCADA, AGUARDANDO RESPOSTA DO DMSL PARA SEGUIR COM AS TRATATIVASFavor, realizar substituição completa do RLG 7900532053 que encontra-se com defeito devido entrada de água no cordão umbilical e danos causados por abelhas. O rádio também precisa ser fornecido pois o existente está danificado.
A27: ETO-COEP 00173/2025 | D27: RELÉ | E27: CIRCUITO DE COMANDO | J27: 2025 | K27: COI | L27: ETO-COEP | M27: LD03010004 | N27: 7900535058 | O27: 750473 | P27: 9212030 | Q27: 190-17513181 | R27: EMERGENCIAL | S27: SS PENDENTE | T27: 45894.368 | V27: 45897.368 | W27: RELIGADOR DE LINHA - 38kV | X27: SANTA FE DO ARAGUAIA | Y27: ARTHUR MAGALHAES DAS DORES | Z27: RURAL | AA27: INDISPONIBILIDADE PARA OPERAÇÃO | AB27: PARECER COEP: EQUIPAMENTO SELECIONADO PARA COMPRAPARECER DMSL: Equipamento 7900535058 encontra-se com o relé danificado, firmware corrompido, o mesmo não inicia. Devido ao fato de não possuirmos mais peças de reposição para religador cooper, se faz necessário a substituição de todo conjunto por um Noja RC10.envar equipe para verificar rlo 7900535058 foi feito primeiro ataque com equipe 040op36 o mesmo esta com RELE TRAVADO E FICOU FORA DE OPERAÇÃO, ATENDE RDR DE SANTA FÉ SAIDA DA CIDADEEQUIPE INFORMOU ABELHAS NA CAIXA DO PAINEL DE COMANDO
A28: ETO-COEP 00080/2026 | J28: 2026 | K28: COI | L28: ETO-COEP | M28: AL02033047 | N28: 7900573047 | O28: 698555 | P28: 8657414 | Q28: 190-19172791 | R28: EMERGENCIAL | S28: SS PENDENTE | T28: 46136.37 | V28: 46139.37 | W28: BLOCO RELIGADOR DE LINHA | X28: FIGUEIROPOLIS | Y28: ANTONIO FAGNER ALVES RIBEIRO | Z28: RURAL | AA28: INDISPONIBILIDADE PARA OPERAÇÃO | AB28: PARECER COEP: AGUARDANDO COCM'S GERAREM AS OBRAS PARA PODER ENTREGAR MATERIALFavor providenciar manutenção no RL 7900573047, o mesmo estar em curto conforme fotos anexadas. Equipamento ficou bay passado em campo.PARECER DMSL: Equipe: FABIO AP./JOÃO MARCOSData Executada: 15/10/2025Serviço Executado:Foi constatado que o equipamento esta queimado na parte ativa placa, tanque e relé. Por favor fazer a substituição pelo Noja RC10.
A29: ETO-COEP 00113/2026 | D29: RELIGADOR | E29: ILEGÍVEL | J29: 2026 | K29: COI | L29: ETO-COEP | M29: LD03046026 | N29: 7900594026 | O29: 879287 | P29: 8809524 | Q29: 190-17512671 | R29: EMERGENCIAL | S29: SS PENDENTE | T29: 46183.467 | V29: 46186.467 | W29: RELIGADOR DE LINHA - 38kV | X29: PONTE ALTA DO TOCANTINS | Y29: DIOMAR FERREIRA PEREIRA | Z29: URBANO | AA29: INDISPONIBILIDADE PARA OPERAÇÃO | AB29: PARECER COEP: AGUARDANDO COCM'S PARA ABRIR REQUISIÇÃOPARECER DMSL 10/06/2026: Tem uma nota aberta para esse equipamento solicitando a substituição desde 20/10/2025, como a nota não foi atendida estamos repassando para área responsável. Nota em aberto repassada ETO-COEP 210/2025.Segue nota para verificar intermitência de comunicação nos religadores 7908301026 , 7911120026, 7947959026 , 7908692026, 7900594026 rural- Ponte Alta .
A30: ETO-COEP 00061/2026 | D30: BUCHAS DE PASSAGEM | E30: CORROSÃO / OXIDAÇÃO | J30: 2026 | K30: COI | L30: ETO-COEP | M30: LD04062013 | N30: 7901110084 | O30: 695579 | P30: 8916959 | Q30: 190-17407509 | R30: EMERGENCIAL | S30: SS PENDENTE | T30: 46112.402 | V30: 46115.402 | W30: BLOCO RELIGADOR DE LINHA | X30: DIVINOPOLIS DO TOCANTINS | Y30: JANES FERREIRA DA SILVA | Z30: RURAL | AA30: INDISPONIBILIDADE PARA OPERAÇÃO | AB30: PARECER COEP: EQUIPAMENTO SELECIONADO PARA COMPRAPARECER DMSL: Serviço Executado: Foi feito análise técnica, testes funcionais e identificado que a parte ativa do equipamento está com defeito. Necessário substituir a parte ativa.FICOU EM OPERAÇÃO? Não- EQUIPE: Carliel e BenvindoSegue SS para verificaçao Rl esta danificado dando passagem de tensão mesmo aberto Sim, quando retornar trazer uma fonte pois a mesma foi removida.
A31: ETO-COEP 00184/2025 | J31: 2025 | K31: MANUT | L31: ETO-COEP | M31: LD05010004 | N31: 7903112004 | O31: 823110 | P31: 9189383 | Q31: 190-17512526 | R31: PROGRAMAVEL | S31: SS PENDENTE | T31: 45903.725 | V31: 46303.725 | W31: RELIGADOR DE LINHA - 38kV | X31: ARAGUAINA | Y31: EDNA MARIA DOS SANTOS PINTO | Z31: RURAL | AA31: INDISPONIBILIDADE PARA OPERAÇÃO | AB31: PARECER COEP: AGUARAR RETORNo RETORNO DMSLApós testes no RLG 7903112004 foi constatado defeito no mesmo e como se trata de um modelo COOPER FORM6 que está obsoleto e não possuímos peças sobressalentes, faz-se necessária substituição completa por modelo NOJA RC10.
A32: ETO-RD-PA 00352/2026 | D32: RELÉ | E32: AJUSTE DE PROTEÇÃO INCORRETO | J32: 2026 | K32: COI | L32: ETO-RD-PA | M32: AL03097122 | N32: 7905357122 | O32: 793135 | P32: 8865229 | Q32: 190-17421490 | R32: EMERGENCIAL | S32: SS PENDENTE | T32: 46164.598 | V32: 46167.598 | W32: RELIGADOR DE LINHA - 19 | X32: PALMAS | Y32: JANES FERREIRA DA SILVA | Z32: URBANO | AA32: AJUSTES DE PROTEÇÃO | AB32: PARECER DMSL: Foi alinhado com Irlley da proteção que será necessário substituir o equipamento RLG 7905357122 pois o relé possui limitações no ajuste e por não ser possível acessá-lo para coletar eventos, se tratando de um modelo obsoleto. Foi alinhado que o equipamento permanecerá em operação até que seja substituído. Favor, realizar substiuição por um modelo NOJA RC10 e programar a poda de árvores próxima do equipamento.Boa noite Segue SS para verificação de ajuste de proteção do RL 7905357122 poste a abalroado de ID 57407652 os cabos MT ficou encostanto na arvore pegando fogo e o RL não atuou a proteção.Parecer da proteção:Conferir os ajustes de proteção do RC01, reincidente em não abrir.Realizar teste funcional com mala de carga.Eng° Irlley Castelo Branco
A33: ETO-COEP 00122/2026 | D33: RELIGADOR | J33: 2026 | K33: COPC | L33: ETO-COEP | M33: AL02033047 | N33: 7908196047 | O33: 698485 | P33: 8657287 | Q33: 190-19172792 | R33: ALTA | S33: SS PENDENTE | T33: 46205.746 | V33: 46265.746 | W33: BLOCO RELIGADOR DE LINHA | X33: FIGUEIROPOLIS | Y33: Leonardo Sousa de Lima | Z33: RURAL | AA33: COMISSIONAMENTO | AB33: RELIGADOR N° 7908196047 REMANEJADO NA OBRA 0402401150 GENTILEZA, REALIZAR O COMISSIONAMENTO. LAUDO EM ANEXO. COORD EO: 698485, 8657287PARECER DA PROTEÇÃO:AJUSTE DISPONIBILIZADO NO APP DA PROTEÇÃO, NOTA REPASSADA PARA DMSL COMISSIONAR, POLO GURUPI, RL APENAS REMANEJADO DA REDE VELHA PARA REDE NOVA, EQUIPAMENTO COOPER, SE MANTEVE O MESMO NÚMERO DE ATIVO.ENG° IRLLEY CASTELO BRANCO.PARECER DMSL: Constatado curto-circuito no tanque do religador, impedindo as operações de abertura e fechamento do equipamento. Solicita-se a substituição completa do religador, incluindo tanque e unidade de controle.
A34: ETO-COEP 00038/2026 | J34: 2026 | K34: MANUT | L34: ETO-COEP | M34: LD02072001 | N34: 7908249152 | O34: 805385 | P34: 8737798 | Q34: 190-17512853 | R34: ALTA | S34: SS PENDENTE | T34: 46077.478 | V34: 46137.478 | W34: RELIGADOR DE LINHA - 38kV | X34: SANTA ROSA DO TOCANTINS | Y34: JULIA GRAZYELLE BRITO OLIVEIRA | Z34: RURAL | AA34: INDISPONIBILIDADE PARA OPERAÇÃO | AB34: PARECER COEP: AGUARDANDO RETORNO DMSL, SERIA A COMPRA DA PARTE ATIVA+ CONTROLE+RADIO +RELE?DMSL:Serviço Executado: Houve um curto no equipamento danificando a parte ativa, será necessário fazer a substituição do equipamento completo ( parte ativa e controle) colocar o um cabo pp novo do trafo até o Dj pois o mesmo está sem condições de uso. Obs:. Foi retirado rádio e rele Equipamento ficou em operação?: Não Pendência: Sim, substituir o equipamento completo.
A35: ETO-COEP 00135/2026 | J35: 2026 | K35: MANUT | L35: ETO-COEP | M35: LD03046026 | N35: 7908302256 | O35: 936573 | P35: 8838426 | Q35: 190-28327585 | R35: PROGRAMAVEL | S35: SS PENDENTE | T35: 46211.437 | V35: 46611.437 | W35: RELIGADOR DE LINHA - 34,5kV | X35: MATEIROS | Y35: Lorrane Sousa Gonçalves | Z35: RURAL | AA35: SOLICITAÇÃO DE SERVIÇO | AB35: PARECER DMSL: Equipamento com a parte ativa com defeito, será necessário fazer a substituição da mesma. (Antiga nota era pra ter sido repassada porém foi baixada indevidamente pela equipe)
A36: ETO-COEP 00086/2026 | D36: RELIGADOR | E36: ILEGÍVEL | J36: 2026 | K36: COI | L36: ETO-COEP | M36: LD02025012 | N36: 7908686014 | O36: 698568 | P36: 8845185 | Q36: 190-17512665 | R36: EMERGENCIAL | S36: SS PENDENTE | T36: 46136.68 | V36: 46139.68 | W36: RELIGADOR DE LINHA - 38kV | X36: PIUM | Y36: DIOMAR FERREIRA PEREIRA | Z36: URBANO | AA36: INDISPONIBILIDADE PARA OPERAÇÃO | AB36: 06/07 PARECER COEP: PREVISÃO DE ENTREGA DE ACORDO COM CALENDÁRIO LOGISITCO NOVO 06/07NOTA DMSL: Favor substituir o tanque, ele não está efetuando os comandos enviados. Não substituir o controle pois o mesmo funciona como repetidor de outros equipamentos.Segue nota para verificar falha de fechamento religador 7908686014- Pium .OBS: equipamento não fechou local e remoto , fica sinalizando no painel para verificar alarmes !
A37: ETO-RD-DP 00409/2026 | J37: 2026 | K37: MANUT | L37: ETO-RD-DP | M37: AL01015049 | N37: 7908705049 | O37: 998978 | P37: 8589651 | Q37: 190-17414963 | R37: PROGRAMAVEL | S37: SS PENDENTE | T37: 46209.726 | V37: 46609.726 | W37: BLOCO RELIGADOR DE LINHA | X37: AURORA DO TOCANTINS | Y37: Lorrane Sousa Gonçalves | Z37: RURAL | AA37: INDISPONIBILIDADE PARA OPERAÇÃO | AB37: EQUIPAMENTO ENTREGUE, SOLICITO PREVISÃO PARA SUBSTITUIÇÃO:PARECER COEP: PREVISÃO DE ENTREGA AOS COCM'S 01/07Manutenção no RL 7908705049PARECER DMSL(28/08/2025): Equipe foi fazer manutenção no RL e constatou que o tanque e o relé do mesmo se encontra queimado, providenciar substituição.PARECER COCMS 30/04/2026CRIADO OBRA 0512600135 PARA REQUISIÇÃO MATERIAL
A38: ETO-COEP 00136/2026 | J38: 2026 | K38: MANUT | L38: ETO-COEP | M38: LD02059122 | N38: 7910027196 | O38: 876869 | P38: 8859703 | Q38: 190-17512828 | R38: PROGRAMAVEL | S38: SS PENDENTE | T38: 46211.439 | V38: 46611.439 | W38: RELIGADOR DE LINHA - 38kV | X38: LAGOA DO TOCANTINS | Y38: Lorrane Sousa Gonçalves | Z38: URBANO | AA38: SOLICITAÇÃO DE SERVIÇO | AB38: PARECER DMSL: EQUIPAMENTO FICOU EM OPERACAO, RESTABELCIDO PELA KAROL ação remota com a velp porém ele também deve ser realizado substituição por conta da fase B 7910027196 ta com a leitura incorreta na tensão da fase B. Subsituição do Equipamento Completo exceto o Radio. (Antiga nota era pra ter sido repassada porém foi baixada indevidamente pela equipe)
A39: DG-RD-PO 00444/2026 | D39: ATERRAMENTO | E39: DANIFICADO(A) | J39: 2026 | K39: COI | L39: DG-RD-PO | M39: LD03046026 | N39: 7911120026 | O39: 879271 | P39: 8809603 | Q39: 190-17512741 | R39: EMERGENCIAL | S39: SS PENDENTE | T39: 46204.742 | V39: 46207.742 | W39: RELIGADOR DE LINHA - 38kV | X39: PONTE ALTA DO TOCANTINS | Y39: DIOMAR FERREIRA PEREIRA | Z39: URBANO | AA39: INDISPONIBILIDADE PARA OPERAÇÃO | AB39: Segue nota para recuperar malha de aterramento no RL 7911120026 RDU- Ponte Alta .OBS: Provavelmente foi furtado cabos de aterramento .
A40: ETO-COEP 00114/2026 | J40: 2026 | K40: COI | L40: ETO-COEP | M40: AL01031076 | N40: 7913662076 | O40: 689369 | P40: 8746092 | Q40: 190-17421709 | R40: EMERGENCIAL | S40: SS PENDENTE | T40: 46183.66 | V40: 46186.66 | W40: RELIGADOR DE LINHA - 19 | X40: DUERE | Y40: CASSIO GOMES BONFIM | Z40: URBANO | AA40: INDISPONIBILIDADE PARA OPERAÇÃO | AB40: 30/06 PARECER COEP: AGUARDANDO RETORNO DO DMSL PARA ENTENDER EXATAMENTE O QUE TENHO QUE SUBSTITUIRAberto nota para substituir tanque danificado e chave de entrada fase B danificadaPARECER DMSL: Foi confirmado pela equipe DMSL o defeito do tanque, favor seguir com a substituição e correção da chave de entrada fase B danificada.
A41: ETO-COEP 00074/2026 | D41: RELIGADOR | J41: 2026 | K41: COPC | L41: ETO-COEP | M41: LD01047073 | N41: 7919270014 | O41: 617420 | P41: 8830790 | Q41: 190-17407946 | R41: ALTA | S41: SS PENDENTE | T41: 46129.383 | V41: 46189.383 | W41: BLOCO RELIGADOR DE LINHA | X41: LAGOA DA CONFUSAO | Y41: Leonardo Sousa de Lima | Z41: RURAL | AA41: INDISPONIBILIDADE PARA OPERAÇÃO | AB41: PARECER COEP: AGUARDANDO RETORNO DO DMSL, EQUIPAMENTO FOI INSTALADO NOVO NA OBRA 0212501060, ENTENDER O PORQUE NÃO FOI REALIZADO COMISSIONAMENTOPARECER DMSL: Substituir Equipamento completo problema na placa de alimentação e na parte ativa, falta colocar placa de identificação correta na topologia, baixar o controle.Equipamento ficou em operação?: naoPendência: simBateria(s) substituída(s)? NÃOEquipe: Kaique/ Benvindo----------------------------------------------PARECER DA PROTEÇÃO: Prosseguir com o comissionamento. Ajustes de religador permanecem os mesmos, disponíveis no APP da Proteção.********************************RELIGADOR N°7919270014 REMANEJADO NA OBRA 0212501060 GENTILEZA, REALIZAR O COMISSIONAMENTO. LAUDO EM ANEXO. COORD EO: 617422, 8830787
A42: ETO-COEP 00120/2025 | D42: RELÉ | E42: INSPEÇÃO VISUAL | J42: 2025 | K42: COI | L42: ETO-COEP | M42: LD01084002 | N42: 7920024127 | O42: 881575 | P42: 9268477 | Q42: 190-17413318 | R42: EMERGENCIAL | S42: SS PENDENTE | T42: 45839.597 | V42: 45842.597 | W42: BLOCO RELIGADOR DE LINHA | X42: PALMEIRAS DO TOCANTINS | Y42: WESLEY MARCAL MENDES DE OLIVEI | Z42: URBANO | AA42: INDISPONIBILIDADE PARA OPERAÇÃO | AB42: 30/06 PARECER COEP: AGUARDANDO O RETORNO DO DMSL , PARA ENTENDER SE O PROBLEMA É NA COMUNICAÇÃO OU PARTE ATIVA, JÁ QUE O EQUIPAMENTO EM QUESTÃO SEGUE COMUNICANDOPARECER DMSL: Após testes, equipe DMSL constatou que o relé e a parte ativa do equipamento 7920024127 estão com defeito, sendo necessária a substituição completa por um modelo NOJA RC 10. Favor, subsituir também a chave de saída da fase A que está com o anel de abertura quebrado.RL 7920024127 está desarmando em campo e no SCADA continua fechado, só sinaliza aberto no SCADA quando a equipe faz o resert no equipamento em campo.
A43: ETO-COEP 00132/2026 | J43: 2026 | K43: COI | L43: ETO-COEP | M43: LD01025012 | N43: 7921202014 | Q43: EQP-7921202014 | R43: EMERGENCIAL | S43: SS PENDENTE | T43: 46211.427 | V43: 46214.427 | W43: RELIGADOR 34,5 KV | Y43: WANDERLEY TAVARES DA SILVA | AA43: INDISPONIBILIDADE PARA OPERAÇÃO | AB43: PARECER COEP: PROBLEMA IDENTIFICADO É NA PARTE ATIVA? OU NO RELIGADOR? FAVOR VERIFICAR SE EQUIPAMENTO ESTÁ EM OPERAÇÃO NO SCADA, OU SE É NECESSARIO APENAS A MELHORIA DE ATERRAMENTO PARECER DMSL: Serviço Executado: _ indentificado o problema na parte ativa será necessário fazer a substituição da mesmo, feito a medição do aterramento. Preciso substituir para raio da fase c.Equipamento ficou em operação?: _NAOPendência: _SimBateria(s) substituída(s)? _NãoData Fabricação/Instalação da(s) bateria(s):_Equipe: _Benvindo e kaique----------------------------------------------------------------------------------RL com defeito no rele, fica só reiniciando ficou By passado OS atendimento primeiro ataque 106530226
A44: ETO-COEP 00124/2026 | J44: 2026 | K44: SCADA | L44: ETO-COEP | M44: AL04010004 | N44: 7923673004 | O44: 808350 | P44: 9204335 | Q44: 190-17421632 | R44: PROGRAMAVEL | S44: SS PENDENTE | T44: 46210.642 | V44: 46610.642 | W44: RELIGADOR DE LINHA - 15,0kV | X44: ARAGUAINA | Y44: LARA SOARES FARIAS | Z44: URBANO | AA44: INDISPONIBILIDADE PARA OPERAÇÃO | AB44: PARECER COEP: Verificar Disponibilidade de equipamento no Scada e enviar modelo e tensão para a compra.RELIGADOR COM RELÉ DANIFICADO, REALIZAR SUBSTITUIÇÃO
A45: ETO-COEP 00079/2025 | D45: RELIGADOR | E45: QUEIMADO | J45: 2025 | K45: COI | L45: ETO-COEP | M45: LD02059122 | N45: 7923927122 | O45: 798247 | P45: 8867579 | Q45: 190-17403330 | R45: EMERGENCIAL | S45: SS PENDENTE | T45: 45776.576 | V45: 45779.576 | W45: BLOCO RELIGADOR DE LINHA | X45: PALMAS | Y45: SAMUEL PINTO GOMES | Z45: RURAL | AA45: INDISPONIBILIDADE PARA OPERAÇÃO | AB45: 30/06 PARECER COEP: EQUIPAMENTO SEM PARECER TECNICO DO DMSLSegue nota para envia manutenção substituir tanque do RL-7923927122 em curto, Anomalia identificada desarme das LD, s Palmas / Aparecida e Palmas Taquaruçu, Acesso livre, Tensão 34,5kv, Local RL de Interligação entre 424R / 414R.
A46: ETO-COEP 00222/2025 | J46: 2025 | K46: SCADA | L46: ETO-COEP | M46: LD01010021 | N46: 7925087021 | O46: 852524 | P46: 8629048 | Q46: 190-17514129 | R46: PROGRAMAVEL | S46: SS PENDENTE | T46: 45999.427 | V46: 46399.427 | W46: RELIGADOR DE LINHA - 34,5kV | X46: PARANA | Y46: LARA SOARES FARIAS | Z46: RURAL | AA46: INDISPONIBILIDADE PARA OPERAÇÃO | AB46: PARECER COEP: EM ROTA DE ENTREGA, VERIFICAR PREVISÃO DE CHEGADARealizar a substituição do tanque do equipamento.
A47: ETO-COEP 00058/2026 | D47: RELIGADOR | E47: QUEIMADO | J47: 2026 | K47: COI | L47: ETO-COEP | M47: LD01414015 | N47: 7925733015 | O47: 813445 | P47: 8984037 | Q47: 190-17404247 | R47: EMERGENCIAL | S47: SS PENDENTE | T47: 46111.413 | V47: 46114.413 | W47: BLOCO RELIGADOR DE LINHA | X47: PEDRO AFONSO | Y47: ARTHUR MAGALHAES DAS DORES | Z47: RURAL | AA47: INDISPONIBILIDADE PARA OPERAÇÃO | AB47: PARECER COEP: EQUIPAMENTO SELECIONADO PARA COMPRAPARECER DMSL: FEEDBACK EQUIP. ESPECIAISNº DO EQUIPAMENTO: 7925733015TIPO EQUIPAMENTO: Noja RC10TIPO DE COMUNICAÇÃO: Rádio GEDATA DA MANUTENÇÃO: 24/03/2026SID: 1475/2026DESCRIÇÃO: Tanque do equipamento em CurtoFICOU EM OPERAÇÃO?: Não PENDÊNCIA: Sim, repassar a nota para DCMD substituir tanque.DADOS DIVERGENTES DA PROGRAMAÇÃO: NãoBATERIA SUBSTITUÍDA?: Não TIPO DE BATERIA: Lítio EQUIPE: Edicleber e Jhonata(DEOP)------------------------------------------------------------------------------------------------------religador 7925733015 com defeito, equipe fez abertura da chave de saida do mesmo e ele não aceita fehcamento devido provavel curto-circuito interno, enviar equipe para verificar o mesmo ficou by-pass fechado
A48: ETO-COEP 00059/2026 | D48: RELÉ | E48: FALTANDO | J48: 2026 | K48: COI | L48: ETO-COEP | M48: LD02022033 | N48: 7925744087 | O48: 727489 | P48: 9029671 | Q48: 190-17408622 | R48: EMERGENCIAL | S48: SS PENDENTE | T48: 46111.432 | V48: 46114.432 | W48: BLOCO RELIGADOR DE LINHA | X48: GOIANORTE | Y48: CLESIO CARVALHO MOURA | Z48: URBANO | AA48: INDISPONIBILIDADE PARA OPERAÇÃO | AB48: PARECER COEP: EQUIPAMENTO SELECIONADO PARA COMPRAPARECER DMSL: FEEDBACK EQUIP. ESPECIAISNº DO EQUIPAMENTO: 7925744087TIPO EQUIPAMENTO: Noja RC 10TIPO DE COMUNICAÇÃO: Radio GE IPDATA DA MANUTENÇÃO: 19/02/2026SID: 735/2026 DESCRIÇÃO: foi identificado água dentro da parte interna do tanque e cabo umbilical encharcado de água foi passado essas informações para COS.FICOU EM OPERAÇÃO?: Não PENDÊNCIA: Sim substituir tanque e cabo umbilicalDADOS DIVERGENTES DA PROGRAMAÇÃO: NãoBATERIA SUBSTITUÍDA?: Não DATA DA BATERIA: 07/05/2025TIPO DE BATERIA: Lítio EQUIPE: Edeglan e Janio-------------------------------------------------------------------------------------------------RELIGADOR SEM COMUNICAÇÃO, APOS PRIMEIRO ATAQUE RETORNA E FICAR INDEFINIDO.
A49: ETO-COEP 00048/2026 | J49: 2026 | K49: MANUT | L49: ETO-COEP | M49: LD03105019 | N49: 7925871077 | O49: 905716 | P49: 9145475 | Q49: 190-17512510 | R49: PROGRAMAVEL | S49: SS PENDENTE | T49: 46097.58 | V49: 46497.58 | W49: RELIGADOR DE LINHA - 38kV | X49: GOIATINS | Y49: JULIA GRAZYELLE BRITO OLIVEIRA | Z49: URBANO | AA49: INDISPONIBILIDADE PARA OPERAÇÃO | AB49: 30/06 PARECER COEP: AGUARDANDO RETORNO DO DMSLPARECER DMSL: A PEDIDO DA PCM DO NORTE LARA SOARES REALIZEI A CRIAÇÃO DESSA SS, EM RAZAO DA ANTIGAETO-TELE 337/2026 QUE FOI BAIXADA POR ENGANO DE TAL FORMA SEGUE A MESMA PARA REALIZAR AS TRATATIVAS. PENDENCIA: Religador continua by passado, equipamento está com defeito na parte ativa
A50: ETO-COEP 00078/2026 | D50: RELIGADOR | E50: RELÉ DE PROTEÇÃO | J50: 2026 | K50: COPO | L50: ETO-COEP | M50: LD03062013 | N50: 7926089013 | O50: 718799 | P50: 8867765 | Q50: 190-17512949 | R50: ALTA | S50: SS PENDENTE | T50: 46135.332 | V50: 46195.332 | W50: RELIGADOR DE LINHA - 38kV | X50: PARAISO DO TOCANTINS | Y50: CLEBSON ALVES DUARTE | Z50: RURAL | AA50: INDISPONIBILIDADE PARA OPERAÇÃO | AB50: PARECER COEP: EQUIPAMENTO SELECIONADO PARA COMPRAPARECER DMSL: Feedback Equip. EspeciaisRLG 7926089013,RELÉ NOJA RC10SID 1805/2026DATA 15/04/2026Serviço Executado: Favor realizar a troca da parte ativa do equipamento --reprogramar para atualizar a base juntamente com escada Equipamento ficou em operação: Não Pendência: sim atualizar a base e subistituir o tanque Bateria(s) substituída(s)? Não Data de Fabricação/Instalação da(s) bateria(s): Equipe: Carliel e João Vitor Fernando e Elson---------------------------------------------------------------------------------ATUALIZAR AJUSTES DO RL 7926089013 LD PARAISO I A PIUM. IMPLEMENTAÇÃO DA FUNÇÃO 27, SUBTENSÃO.AJUSTES DISPONIVEIS NO APP DA PROTEÇÃO.
A51: ETO-COEP 00051/2026 | D51: RELIGADOR | E51: OUTROS | J51: 2026 | K51: COI | L51: ETO-COEP | M51: LD01051035 | N51: 7926442035 | O51: 819553 | P51: 8782076 | Q51: 190-17513078 | R51: EMERGENCIAL | S51: SS PENDENTE | T51: 46099.677 | V51: 46102.677 | W51: RELIGADOR DE LINHA - 34,5kV | X51: MONTE DO CARMO | Y51: SAMUEL PINTO GOMES | Z51: RURAL | AA51: INDISPONIBILIDADE PARA OPERAÇÃO | AB51: PARECER COEP: EQUIPAMENTO SELECIONADO PARA COMPRAPARECER DMSL: Data: 12/03/2026 Serviço Executado:- Análise técnica constatou:- Parte ativa do equipamento danificada: necessita substituição- Trafo danificado: foi feitos testes nas buchas secundárias o mesmo não chega tensão - Vazamento de óleo - Necessita substituiçãoEquipamento ficou em operação? NãoPendências:- Solicitar limpeza de faixa para acesso ao equipamento- Trocar parte ativa do equipamento- Substituir o trafoEquipe: Carliel e João VitorSegue nota para envia equipe verificar falha de comunicação e automação no RL-7926442035 feito primeiro ataque com equipe 035OP02, porém sem sucesso.
A52: ETO-RD-PA 00432/2026 | J52: 2026 | K52: MANUT | L52: ETO-RD-PA | M52: AL01102271 | N52: 7927169001 | O52: 766063 | P52: 8872437 | Q52: 190-17421624 | R52: EMERGENCIAL | S52: SS PENDENTE | T52: 46204.483 | V52: 46207.483 | W52: RELIGADOR DE LINHA - 19 | X52: PORTO NACIONAL | Y52: JULIA GRAZYELLE BRITO OLIVEIRA | Z52: RURAL | AA52: INDISPONIBILIDADE PARA OPERAÇÃO | AB52: PARECER COEP: EQUIPAMENTO ENTREGUE, SEGUE SS PARA O COCM´S , PARA REALIZAR O ATENDIMENTO,FAVOR ADICIONAR O PARECER PARA MANDAR PARA PROTEÇÃOSS ANTIGA: 1500/2025 PARECER DMSL: Serviço Executado: Foi verificado que o tanque do equipamento está danificado, sendo necessário substituir o tanque do equipamento.Equipamento ficou em operação?: NãoPendência: Sim, instalar fonte, disjuntor e DPS, e substituir o tanque.
A53: ETO-COEP 00045/2026 | D53: RELIGADOR | E53: INSPEÇÃO VISUAL | J53: 2026 | K53: COI | L53: ETO-COEP | M53: LD03036052 | N53: 7927396052 | O53: 645739 | P53: 8723116 | Q53: 190-21148967 | R53: EMERGENCIAL | S53: SS PENDENTE | T53: 46083.893 | V53: 46086.893 | W53: BLOCO RELIGADOR DE LINHA | X53: FORMOSO DO ARAGUAIA | Y53: ZELITO ALVES DELGADO | Z53: RURAL | AA53: INDISPONIBILIDADE PARA OPERAÇÃO | AB53: PARECER COEP: EQUIPAMENTO SELECIONADO PARA COMPRAreligador foi bay passado devido mesmo esta saindo fumaca do painel e sem comunicação 7927396052.PARECER DMSL: Após testes, equipe DMSL constatou que apenas o tanque do RLG 7927396052 encontra-se queimado. Favor, substituir parte ativa do equipamento.NS Tanque: 0320123040198
A54: ETO-RD-PO 00118/2026 | D54: RELÉ | E54: FALTANDO | J54: 2026 | K54: COI | L54: ETO-RD-PO | M54: LD01072001 | N54: 7927413001 | O54: 787930 | P54: 8828052 | Q54: 190-17408527 | R54: ALTA | S54: SS PENDENTE | T54: 46135.429 | V54: 46195.429 | W54: BLOCO RELIGADOR DE LINHA | X54: PORTO NACIONAL | Y54: Leonardo Oliveira Bezerra Mato | Z54: RURAL | AA54: INDISPONIBILIDADE PARA OPERAÇÃO | AB54: PARECER DMSL: *Segue feedback**Equipamento:* RLG 7927413001 *RELÉ TAVRIDA*Data:* 16/04/2026*SID:* 1817/2026*Serviço executado:* Placa de alimentação do equipamento com defeito, VERIFICAR SE É POSSIVEL substituir o equipamento completo.*Equipamento ficou em operação?*_Não*Pendência:*_Sim*Bateria(s) substituída(s)?*_Nao *Equipe:* Benvindo e Kaique-------------------------------------------------------------------------------------------------Religador 7927413001 sem comunicação foi realizado primeiro ataque porem a comunicação não retornou. Favor enviar equipe para devidas trattivas
A55: ETO-COEP 00143/2025 | D55: RELÉ | E55: ILEGÍVEL | J55: 2025 | K55: COI | L55: ETO-COEP | M55: LD02072001 | N55: 7927446001 | O55: 792922 | P55: 8790506 | Q55: 190-17412374 | R55: EMERGENCIAL | S55: SS PENDENTE | T55: 45846.727 | V55: 45849.727 | W55: BLOCO RELIGADOR DE LINHA | X55: PORTO NACIONAL | Y55: JANES FERREIRA DA SILVA | Z55: RURAL | AA55: INDISPONIBILIDADE PARA OPERAÇÃO | AB55: 30/06 PARECER COEP: AGUARDANDO RETORNO DO DMSL PARA SEGUIR COM AS TRATATIVAS, JÁ QUE NÃO TEMOS CERTEZA SE É SOMENTE A PLCA OU O EQUIPAMENTO COMPLETOSegue para verificação RL sem comunicação feito primeiro ataque sem sucesso.PARECER DMSL:Data:* _08/07/2025Serviço Executado: Placa de alimentação danificada, devido a curto, não temos material sobressalente para manutenção! Favor substituir o equipamento completo.Obs.: O rádio ficou dentro do controle, favor orientar a equipe que for substituir colocar dentro do controle novo.Equipamento ficou em operação?: Não Pendência: Sim, substituir equipamento completo.
A56: ETO-COEP 00029/2026 | J56: 2026 | K56: COI | L56: ETO-COEP | M56: LD03046026 | N56: 7927646026 | O56: 918776 | P56: 8841819 | Q56: 190-37070331 | R56: EMERGENCIAL | S56: SS PENDENTE | T56: 46057.369 | V56: 46060.369 | W56: RELIGADOR DE LINHA - 38kV | X56: PONTE ALTA DO TOCANTINS | Y56: ZENILSON MOREIRA SANTOS | Z56: RURAL | AA56: INDISPONIBILIDADE PARA OPERAÇÃO | AB56: PARECER COEP: EQUIPAMENTO SELECIONADO PARA COMPRARELIGADOR BY PASSADO POR DEFEITO, NECESSÁRIO AVALIAÇÃO DO PROBLEMA.parecer dmsl:O religador apresenta defeito no tanque, sendo necessário substituir o tanque o mesmo está tirando a linha, e troca os isoladores. Quando retornar, trazer uma fonte para o equipamento, a mesma foi removida.FICOU EM OPERAÇÃO? NãoPENDÊNCIA: Sim, aguardando peças para substituição.
A57: ETO-COEP 00128/2026 | D57: RELIGADOR | E57: ILEGÍVEL | J57: 2026 | K57: MANUT | L57: ETO-COEP | M57: LD02066094 | N57: 7928241200 | O57: 794701 | P57: 8603487 | Q57: 190-17410002 | R57: ALTA | S57: SS PENDENTE | T57: 46210.655 | V57: 46270.655 | W57: BLOCO RELIGADOR DE LINHA | X57: SAO SALVADOR DO TOCANTINS | Y57: Lorrane Sousa Gonçalves | Z57: RURAL | AA57: INDISPONIBILIDADE PARA OPERAÇÃO | AB57: PARECER COEP: FAVOR REAVALIAR DISPONIBILIDADE DO EQUIPAMENTO DO SCADA E DIZER MARCA ,MODELO E TENSÃO DO EQUIPAMENTOPARECER DMSL: Tinha uma nota aberta 422/2025 e logo após a equipe resolver a comunicação ela foi baixada, porém a equipe relatou que ''na estrada ontem o COS nos avisou para voltar que na hora de colocar em operação ele tirou a linha fora. Hoje retornamos nele e fizemos ensaios elétricos e foi constatado que o tanque está em curto. Passa direto aí para o Dcmd para substituição do tanque.''
A58: ETO-COEP 00123/2026 | D58: RELIGADOR | J58: 2026 | K58: MANUT | L58: ETO-COEP | M58: LD02109039 | N58: 7928564039 | O58: 825557 | P58: 9381653 | Q58: 190-17513063 | R58: ALTA | S58: SS PENDENTE | T58: 46210.641 | V58: 46270.641 | W58: RELIGADOR DE LINHA - 38kV | X58: ARAGUATINS | Y58: EDNA MARIA DOS SANTOS PINTO | Z58: RURAL | AA58: INDISPONIBILIDADE PARA OPERAÇÃO | AB58: PARECER COEP: QUAL O MODELO DO EQUIPAMENTO? QUAL A FAIXA DE TENSÃO ? O QUE SERIA SISTEMA DE COMUNICAÇÃO COMPLETO?Troca do sistema de comunicação do equipamentoDMSL 28/07/2025: Equipamento com tanque, modulo e rele com defeito, solicitar troca do equipamento ao DCMD.Fotos vão ser enviadas por e-mail
A59: ETO-COEP 00120/2026 | J59: 2026 | L59: ETO-COEP | M59: LD05010004 | N59: 7929376022 | O59: 858418 | P59: 9201747 | Q59: 190-17408409 | R59: EMERGENCIAL | S59: SS PENDENTE | T59: 46203.691 | V59: 46206.691 | W59: BLOCO RELIGADOR DE LINHA | X59: BABACULANDIA | Y59: GERCILIO PEDROZA JUNIOR | Z59: URBANO | AA59: INDISPONIBILIDADE PARA OPERAÇÃO | AB59: PARECER COEP: PROBLEMA NO ENVIO COCM'S CONTROLE ENVIADO FOI O NOJA , DEVIDO A FALTA DO MODELO NA SS (GRAVE)PARECER DMSL: *FEEDBACK EQUIP. ESPECIAIS**Nº DO EQUIPAMENTO:* 7929376022 *DATA DA MANUTENÇÃO:* 02/04/2026*SID:* 1677/2026*DESCRIÇÃO:* Trocar controle completo*PENDÊNCIA:* Sim.*DADOS DIVERGENTES DA PROGRAMAÇÃO:* Não*BATERIA SUBSTITUÍDA?:* Não*EQUIPE:* Adeilton e Edicleber __________________________________________________________POR GENTILEZA ATENDER SOLICITAÇÃO PRIMEIRO ATAQUE IDENTIFICOU QUE RELE ESTA EM CURTO NOTA ABERTA 224/2026 FOI BAIXADA POREM NÃO FOI CORRIGIDO PROBLEMA EM CAMPO.
A60: ETO-RD-PO 00183/2026 | D60: RELIGADOR | E60: FALTANDO | J60: 2026 | K60: COI | L60: ETO-RD-PO | M60: LD01065015 | N60: 7931219078 | O60: 857972 | P60: 9047058 | Q60: 190-17404165 | R60: EMERGENCIAL | S60: SS PENDENTE | T60: 46211.478 | V60: 46214.478 | W60: BLOCO RELIGADOR DE LINHA | X60: ITACAJA | Y60: GERALDO JOSE DE FARIA | Z60: RURAL | AA60: EM OPERAÇÃO COM ANOMALIA | AB60: 08/07/2026 PARECER COEP: SUBSTITUIÇÃO DE TRAFO AUXILIAR ENCAMINHADO PARA REALIZAR A TROCA , FAVOR COLOCAR O PARECER AQUI E MANDAR DEPOIS PARA PROTEÇÃO , POR FAVORPARECER COEP: SUBSTITUIÇÃO DO TRAFO É DIRETO COM OS COCM'S, NÃO TEM COMPRA DE EQUIPAMENTO ESPECIAL.PARECER DMSL (25/07/2025): Realizada atualização da base do relé. Feito comissionamento com SCADA (Kauana) e testes com COS (Daniel). Equipamento reinserido no SEP sem anomalias. PENDÊNCIA: Sim. Substituir Trafo auxiliar, pois o mesmo está com vazamento significativo de óleo isolante, o que irá causar a avaria podendo afetar todo controle do religador.FAZER INSPEÇÃO E MANUTENÇÃO DO RL 7931219078. RELIGADOR CHAVE ESTA MUDANDO SOZINHA PARA LOCAL.
A61: ETO-RD-PO 00180/2026 | D61: RELIGADOR | E61: FALTANDO | J61: 2026 | K61: COI | L61: ETO-RD-PO | M61: LD01065015 | N61: 7931219078 | O61: 857972 | P61: 9047058 | Q61: 190-17404165 | R61: EMERGENCIAL | S61: SS PENDENTE | T61: 46202.786 | V61: 46205.786 | W61: BLOCO RELIGADOR DE LINHA | X61: ITACAJA | Y61: GERALDO JOSE DE FARIA | Z61: RURAL | AA61: EM OPERAÇÃO COM ANOMALIA | AB61: PARECER COEP: SUBSTITUIÇÃO DO TRAFO É DIRETO COM OS COCM'S, NÃO TEM COMPRA DE EQUIPAMENTO ESPECIAL.PARECER DMSL (25/07/2025): Realizada atualização da base do relé. Feito comissionamento com SCADA (Kauana) e testes com COS (Daniel). Equipamento reinserido no SEP sem anomalias. PENDÊNCIA: Sim. Substituir Trafo auxiliar, pois o mesmo está com vazamento significativo de óleo isolante, o que irá causar a avaria podendo afetar todo controle do religador.FAZER INSPEÇÃO E MANUTENÇÃO DO RL 7931219078. RELIGADOR CHAVE ESTA MUDANDO SOZINHA PARA LOCAL.
A62: ETO-COEP 00040/2026 | J62: 2026 | K62: MANUT | L62: ETO-COEP | M62: AL05099059 | N62: 7931608059 | O62: 796501 | P62: 8854562 | Q62: 190-17421389 | R62: EMERGENCIAL | S62: SS PENDENTE | T62: 46077.487 | V62: 46080.487 | W62: RELIGADOR DE LINHA - 13,8kV | X62: PALMAS | Y62: JULIA GRAZYELLE BRITO OLIVEIRA | Z62: URBANO | AA62: INDISPONIBILIDADE PARA OPERAÇÃO | AB62: PARECER COEP: EQUIPAMENTO SELECIONADO PARA COMPRADMSL:Serviço Executado: Foi feita uma análise técnica no equipamento, devido à falta de comunicação. Também foi identificado que o tanque do equipamento está danificado, sendo assim, necessário substituir o tanque e o rádio do equipamento, que está queimado, sendo necessário substituir também.
A63: DOLP-RD-PA 00728/2026 | D63: RELÉ | E63: ATERRAMENTO ROMPIDO/SEM CONEXÃO | J63: 2026 | K63: COCM | L63: DOLP-RD-PA | M63: AL08060122 | N63: 7931610122 | O63: 793159 | P63: 8874945 | Q63: 190-17421623 | R63: URGENTE | S63: SS PENDENTE | T63: 46209.638 | V63: 46216.638 | W63: RELIGADOR DE LINHA - 19 | X63: PALMAS | Y63: MARCELO COSTA PRIMO | Z63: URBANO | AA63: AVISO DE ANOMALIA | AB63: 30/06 PARECER COEP: EQUIPAMENTO ENTREGUE, SEGUE SS PARA O COCM´S , PARA REALIZAR O ATENDIMENTO,FAVOR ADICIONAR O PARECER PARA MANDAR PARA PROTEÇÃOBom dia,Segue SS para verificação RL sem comunicação com painel apagado equipe DEOP fez primeiro ataque sem sucesso RL 7931610122 RDU de Palmas.Feedback Equipamentos Especiais DMSL: *RLG 7931610122 RDU Palmas*Noja rc10 Data: 14/10/2025SID: 5412Dados de comunicação divergentes da programação: Não. Serviço Executado: Houve um curto no equipamento danificando a parte ativa, e antena! Será necessário fazer a substituição somente da parte ativa (tanque) e da antena.Equipamento ficou em operação?: Não Pendência: Sim, substituir a parte ativa.Bateria(s) substituída(s)?: NãoData Fabricação/Instalação da(s) bateria(s): 2024Equipe: Benvindo, Juliano e Sérgio.*Equipamento ficou em operação?:*Nao Pendência: Sim, substituir parte ativa.Equipe: Benvindo, Juliano e Sérgio.
A64: ETO-RD-PA 00433/2026 | D64: RELIGADOR | E64: CORROSÃO / OXIDAÇÃO | J64: 2026 | K64: COI | L64: ETO-RD-PA | M64: AL08060122 | N64: 7931610122 | O64: 793159 | P64: 8874945 | Q64: 190-17408268 | R64: EMERGENCIAL | S64: SS PENDENTE | T64: 46204.484 | V64: 46207.484 | W64: BLOCO RELIGADOR DE LINHA | X64: PALMAS | Y64: JANES FERREIRA DA SILVA | Z64: URBANO | AA64: INDISPONIBILIDADE PARA OPERAÇÃO | AB64: 30/06 PARECER COEP: EQUIPAMENTO ENTREGUE, SEGUE SS PARA O COCM´S , PARA REALIZAR O ATENDIMENTO,FAVOR ADICIONAR O PARECER PARA MANDAR PARA PROTEÇÃOBom dia,Segue SS para verificação RL sem comunicação com painel apagado equipe DEOP fez primeiro ataque sem sucesso RL 7931610122 RDU de Palmas.Feedback Equipamentos Especiais DMSL: *RLG 7931610122 RDU Palmas*Noja rc10 Data: 14/10/2025SID: 5412Dados de comunicação divergentes da programação: Não. Serviço Executado: Houve um curto no equipamento danificando a parte ativa, e antena! Será necessário fazer a substituição somente da parte ativa (tanque) e da antena.Equipamento ficou em operação?: Não Pendência: Sim, substituir a parte ativa.Bateria(s) substituída(s)?: NãoData Fabricação/Instalação da(s) bateria(s): 2024Equipe: Benvindo, Juliano e Sérgio.
A65: ETO-COEP 00024/2026 | J65: 2026 | K65: SCADA | L65: ETO-COEP | M65: LD03028074 | N65: 7933585074 | O65: 986342 | P65: 8726425 | Q65: 190-59145750 | R65: EMERGENCIAL | S65: SS PENDENTE | T65: 46049.69 | V65: 46052.69 | W65: RELIGADOR DE LINHA - 38kV | X65: DIANOPOLIS | Y65: LARA SOARES FARIAS | Z65: RURAL | AA65: INDISPONIBILIDADE PARA OPERAÇÃO | AB65: 30/06 PARECER COEP: AGUARDANDO RETORNO DO DMSL.REALIZAR SUBSTITUIÇÃO DO TANQUE, O MESMO ESTÁ COM DEFEITO.
A66: ETO-RD-PO 00181/2026 | D66: ARMÁRIO DE CONTROLE | E66: FALTANDO | J66: 2026 | K66: COI | L66: ETO-RD-PO | M66: LD03046026 | N66: 7933726256 | O66: 1001156 | P66: 8830620 | Q66: 190-17412746 | R66: EMERGENCIAL | S66: SS PENDENTE | T66: 46204.498 | V66: 46207.498 | W66: BLOCO RELIGADOR DE LINHA | X66: MATEIROS | Y66: CLESIO CARVALHO MOURA | Z66: RURAL | AA66: INDISPONIBILIDADE PARA OPERAÇÃO | AB66: 01/07 PARECER COEP: REDIRECIONADO PARA O POSTO DO COCM´S EQUIPAMENTO CHEGOU NO LOCAL, FAVOR ENTRAR EM CONTATO COM O DMSL, DEVIDO A URGÊNCIA DO EQUIPAMENTO EM OPERAÇÃO.30/06 PARECER COEP: DEVIDO A ALINHAMENTO COM COI UTILIZAREMOS PARTE ATIVA QUE ORIGINALMENTE FOI ENCOMENDADA PARA 7933726256PARECER DMSL: N° do Equipamento: _RLG 7933726256 MateirosTipo de Equipamento: _RLG NOJA RC 10 REL IIData: _06/05/2026SID: _2288/2026-Serviço Executado: _Equipamento com defeito na parte ativa, será necessário fazer a substituição da parte ativa e fazer melhoria na malha de terra!Equipamento ficou em operação?: _NaoPendência: _SimBateria(s) substituída(s)? NÃOData Fabricação/Instalação da(s) bateria(s):_06/2025Equipe: _Benvindo e Almir-------------------------------------------------------------------------------Religador 7933726256, sem comunicação apos primeiroa ataque não retornou as comunicação.
A67: DOLP-RD-PA 00727/2026 | D67: BUCHA MT - CARGA (C) | E67: BORNE DANIFICADO | J67: 2026 | K67: COCM | L67: DOLP-RD-PA | M67: AL01099059 | N67: 7933766059 | O67: 792195 | P67: 8855224 | Q67: 190-58832149 | R67: URGENTE | S67: SS PENDENTE | T67: 46209.634 | V67: 46216.634 | W67: RELIGADOR DE LINHA - 15,0kV | X67: PALMAS | Y67: MARCELO COSTA PRIMO | Z67: URBANO | AA67: AVISO DE ANOMALIA | AB67: PARECER COEP: EQUIPAMENTO ENTREGUE, SEGUE SS PARA O COCM´S , PARA REALIZAR O ATENDIMENTO,FAVOR ADICIONAR O PARECER PARA MANDAR PARA PROTEÇÃOSegue SS para verficar religador de poste 7933766059.Religador esta com defeito na parte ativa no tanque Porte gentilezaenviar equipe verificar.Endereço: TaquariPARECER DMSL: RLG 7933766059 RELÉ NOJA RC 10Mestre 2 Rep. taquaruçu GESID: 5457/2025Data: 15/10/2025Serviço Executado: Houve um curto na parte ativa do equipamento danificando a mesma, será necessário fazer a substituição somente do tanque, parte ativa.
A68: ETO-RD-PA 00431/2026 | D68: BUCHA MT - CARGA (C) | E68: INSPEÇÃO VISUAL | J68: 2026 | K68: COI | L68: ETO-RD-PA | M68: AL01099059 | N68: 7933766059 | O68: 792195 | P68: 8855224 | Q68: 190-17409267 | R68: EMERGENCIAL | S68: SS PENDENTE | T68: 46204.481 | V68: 46207.481 | W68: BLOCO RELIGADOR DE LINHA | X68: PALMAS | Y68: HERIK BUARQUE DOS SANTOS | Z68: URBANO | AA68: INDISPONIBILIDADE PARA OPERAÇÃO | AB68: PARECER COEP: EQUIPAMENTO ENTREGUE, SEGUE SS PARA O COCM´S , PARA REALIZAR O ATENDIMENTO,FAVOR ADICIONAR O PARECER PARA MANDAR PARA PROTEÇÃOSegue SS para verficar religador de poste 7933766059.Religador esta com defeito na parte ativa no tanque Porte gentilezaenviar equipe verificar.Endereço: TaquariPARECER DMSL: RLG 7933766059 RELÉ NOJA RC 10Mestre 2 Rep. taquaruçu GESID: 5457/2025Data: 15/10/2025Serviço Executado: Houve um curto na parte ativa do equipamento danificando a mesma, será necessário fazer a substituição somente do tanque, parte ativa.*Equipamento ficou em operação?:*Nao Pendência: Sim, substituir parte ativa.Equipe: Benvindo, Juliano e Sérgio.
A69: ETO-COEP 00129/2026 | J69: 2026 | K69: SCADA | L69: ETO-COEP | M69: LD01066094 | N69: 7937102148 | O69: 823519 | P69: 8668465 | Q69: 190-20409576 | R69: PROGRAMAVEL | S69: SS PENDENTE | T69: 46210.66 | V69: 46610.66 | W69: RELIGADOR DE LINHA - 38kV | X69: SAO VALERIO | Y69: LARA SOARES FARIAS | Z69: RURAL | AA69: INDISPONIBILIDADE PARA OPERAÇÃO | AB69: PARECER COEP: REAVALIAR DISPONIBILIDADE DO EQUIPAMENTO NO SCADA ASSIM COMO , FORNECER MODELO DO EQUIPAMENTO E FAIXA DE TENSÃO PARA COMPRA / AQUISIÇÃOTanque com defeito, realizar substituição do tanque.
A70: ETO-COEP 00158/2025 | D70: RELÉ | E70: QUEIMADO | J70: 2025 | K70: COI | L70: ETO-COEP | M70: LD03046026 | N70: 7942485096 | O70: 870890 | P70: 8743808 | Q70: 190-32192324 | R70: EMERGENCIAL | S70: SS PENDENTE | T70: 45861.444 | V70: 45864.444 | W70: BLOCO RELIGADOR DE LINHA | X70: PINDORAMA DO TOCANTINS | Y70: GERALDO JOSE DE FARIA | Z70: RURAL | AA70: INDISPONIBILIDADE PARA OPERAÇÃO | AB70: 30/06 PARECER COEP: EQUIPAMENTO SELECIONADO PARA COMPRARELIGADOR COM DEFEITO 7942485096, ESTA DANDO PASSAGEM ESTANDO ABERTO. NÃO ACEITA COMANDOS. FICOU BY PASSADO EM CAMPO PARA MANUTENÇÃO.PARECER DMSL: Ao testar o tanque, foi constatado que o mesmo está danificado e precisa ser substituído.Substituir somente o tanque. Deixar claro na nota para o dcmd substituir somente o tanque. Não tem necessidade de substituir o controle.
A71: ETO-RD-PA 00427/2026 | D71: RELIGADOR | E71: INSPEÇÃO VISUAL | J71: 2026 | K71: MANUT | L71: ETO-RD-PA | M71: LD02059122 | N71: 7942572059 | O71: 839744 | P71: 8865329 | Q71: 190-17403393 | R71: EMERGENCIAL | S71: SS PENDENTE | T71: 46202.78 | V71: 46205.78 | W71: BLOCO RELIGADOR DE LINHA | X71: PALMAS | Y71: MARCO ANTONIO LOURENCO CAMPOS | Z71: RURAL | AA71: INDISPONIBILIDADE PARA OPERAÇÃO | AB71: PARECER COEP: EQUIPAMENTO COM MELHORIA DE ATERRAMENTO É COM A ETO-RD-PA , NÃO PASSA PELO FLUXO DE AQUISIÇÃO DO COEP, FAVOR REALIZAR MELHORIA DE ATERRAMENTO ETO-RD-PAPARECER DMSL 19/05/2026: É necessário fazer melhorias na malha de aterramento.segue nota para RL 794252059 o mesmo esta sem comunicaçao, foi feito primeiro ataque, porem a comunicaçao nao voltou, obs ramal do marasca.
A72: ETO-COEP 00063/2026 | J72: 2026 | K72: MANUT | L72: ETO-COEP | M72: LD01434149 | N72: 7944559149 | O72: 630275 | P72: 8986227 | Q72: 190-35120642 | R72: PROGRAMAVEL | S72: SS PENDENTE | T72: 46112.457 | V72: 46512.457 | W72: RELIGADOR DE LINHA - 38kV | X72: CASEARA | Y72: JULIA GRAZYELLE BRITO OLIVEIRA | Z72: RURAL | AA72: INDISPONIBILIDADE PARA OPERAÇÃO | AB72: 30/06 PARECER COEP: AGUARDANDO RETORNO DO DMSL , PARA VIABILIZAR TROCA APENAS DA PLACA , POIS EXISTEM 5 NO SALDO DE ESTOQUEEquipamento ficou em operação?: NãoPendência: Sim será necessário substituir a placaServiço Executado: curto na placa foi tentando recuperar a mesma porém não teve sucesso!Bateria(s)substituída(s)? NÃOEquipe: Kaique e benvido
A73: ETO-COEP 00131/2026 | D73: RELIGADOR | E73: INSPEÇÃO VISUAL | J73: 2026 | K73: COI | L73: ETO-COEP | M73: LD02065015 | N73: 7947203070 | O73: 851948 | P73: 8950905 | Q73: 190-68154393 | R73: EMERGENCIAL | S73: SS PENDENTE | T73: 46211.426 | V73: 46214.426 | W73: BLOCO RELIGADOR DE LINHA | X73: RIO SONO | Y73: LAISON OLIVEIRA CARVALHO | Z73: RURAL | AA73: INDISPONIBILIDADE PARA OPERAÇÃO | AB73: PARECER COEP: QUAL O MODELO DA PLACA OU CÓDIGO DO MATERIAL?EXISTE DIFERENÇA DE MODELO OU POTÊNCIA?favor verificar RL 7947203070, sem comunicaçao, feito 1° ataque pela equipe 070OP01 e nao retornou a comunicaçao , linformaçao no Scada de bateria.PARECER DMSL: Foi feito análise técnica, a placa do equipamento está queimada nessesario subistituir o equipamento completo -Carliel e Benvindo-05/02
A74: ETO-COEP 00050/2026 | D74: RELIGADOR | E74: INSPEÇÃO VISUAL | J74: 2026 | K74: COI | L74: ETO-COEP | M74: LD03046026 | N74: 7953610256 | O74: 1068871 | P74: 8855553 | Q74: 190-43820334 | R74: EMERGENCIAL | S74: SS PENDENTE | T74: 46099.673 | V74: 46102.673 | W74: BLOCO RELIGADOR DE LINHA | X74: MATEIROS | Y74: DIONES COSTA SILVA | Z74: RURAL | AA74: INDISPONIBILIDADE PARA OPERAÇÃO | AB74: PARECER COEP: AGUARDANDO COCM'S GERAREM A OBRA PARA ENTREGA DO MATERIALPARECER DMSL: Data: 10/03/2026,Serviço Executado: Foi substituído o relé do equipamento, o mesmo estava danificado. Trocado o DPS, o mesmo estava queimado devido ao tanque estar furado. O equipamento ficou em bypass.Equipamento ficou em operação? NãoPendência? Sim, substituir a parte ativa com cordão umbilical.Equipe: Carliel e João VitorSEGUE SS PARA REGULARIZAR AUTOMAÇÃO DO RL 7953610256 NA INTERLIGAÇÃO COM A COELBA (CHAPADA DA MANGABEIRA) - EQUIPE INFOMOU CURTO INTERNO NO GABINETE DJ AC NÃO FECHA
A75: ETO-COEP 00134/2026 | J75: 2026 | K75: MANUT | L75: ETO-COEP | M75: LD05050008 | N75: 7955946007 | O75: 787602 | P75: 8929207 | Q75: 190-40659920 | R75: PROGRAMAVEL | S75: SS PENDENTE | T75: 46211.436 | V75: 46611.436 | W75: RELIGADOR DE LINHA - 38kV | X75: MIRACEMA DO TOCANTINS | Y75: Lorrane Sousa Gonçalves | Z75: RURAL | AA75: SOLICITAÇÃO DE SERVIÇO | AB75: PARECER DMSL: Necessário substituir a placa de alimentação ca, a mesma está em curto não conseguimos recuperar. (Antiga nota era pra ter sido repassada porém foi baixada indevidamente pela equipe)
A76: ETO-COEP 00133/2026 | J76: 2026 | K76: MANUT | L76: ETO-COEP | M76: LD04062013 | N76: 7955986084 | O76: 695371 | P76: 8916924 | Q76: 190-28065672 | R76: PROGRAMAVEL | S76: SS PENDENTE | T76: 46211.434 | V76: 46611.434 | W76: RELIGADOR DE LINHA - 38kV | X76: DIVINOPOLIS DO TOCANTINS | Y76: Lorrane Sousa Gonçalves | Z76: RURAL | AA76: SOLICITAÇÃO DE SERVIÇO | AB76: PARECER DMSL: Equipamento com a placa de alimentação ca em curto, será necessário substituir a placa do equipamento. (Antiga nota era pra ter sido repassada porém foi baixada indevidamente pela equipe)
A77: ETO-COEP 00156/2025 | J77: 2025 | K77: COI | L77: ETO-COEP | M77: LD04062013 | N77: 7957126085 | O77: 720258 | P77: 8893131 | Q77: 190-48432153 | R77: EMERGENCIAL | S77: SS PENDENTE | T77: 45860.721 | V77: 45863.721 | W77: RELIGADOR DE LINHA - 38kV | X77: MONTE SANTO DO TOCANTINS | Y77: ZENILSON MOREIRA SANTOS | Z77: URBANO | AA77: INDISPONIBILIDADE PARA OPERAÇÃO | AB77: 20/06PARECER COEP: EMD 510216PREVISÃO DE CHEGADA COCM'S 01/07RELIGADOR COM RELÉ QUEIMADO - EQUIPAMENTO BY PASSADO. PARECER DMSL:N° do Equipamento: 7957126085Data: 17/06/2025Localidade: RDU Monte SantoServiço Executado:"Os para raios da fase B e C estão fechando arco na cruzeta. Curto desceu para o controle danificando os componentes. Necessário substituir controle completo, substituir cabo de alimentação da BT e abaixar o tanque para afastar das cruzetas. Solicitar também ao DCMD para verificar se os para raios estão danificados."Ana Maria e Rayr já tinha ido no local anteriormente, na data 14/05/25 e fizeram o diagnostico acima. Equipamento ficou em operação?: NÃO
A78: ETO-RD-PA 00246/2026 | D78: RELIGADOR | J78: 2026 | K78: COPC | L78: ETO-RD-PA | M78: AL05097122 | N78: 7961785122 | O78: 792261 | P78: 8868642 | Q78: 190-17409191 | R78: ALTA | S78: SS PENDENTE | T78: 46126.393 | V78: 46186.393 | W78: BLOCO RELIGADOR DE LINHA | X78: PALMAS | Y78: Leonardo Sousa de Lima | Z78: URBANO | AA78: COMISSIONAMENTO | AB78: RELIGADOR N° 7961785122 REMANEJADO NA OBRA 0102401076 GENTILEZA, REALIZAR O COMISSIONAMENTO. LAUDO EM ANEXO. COORD EO: 792261, 8868643PARECER DA PROTEÇÃO:COORD TS: 792319, 8868633, AJUSTE DISPONIBILIZADO NO APP DA DA PROTEÇÃO, NOTA REPASSADA PARA DMSL COMISSIONAR, POLO PALMAS.ENG° IRLLEY CASTELO BRANCO. PARACER DMSL: DEIXAMOS O EQUIPAMENTO COMISSIONADO E EM OPERAÇÃO, ESTAMOS REPASSANDO A NOTA PARA QUE POSSAM VERIFICAR A PENDENCIA. PARECER DMSL:SERVIÇO REALIZADO:Foi feito o comissionamento do equipamento com scada, realizado testes de comandos local e remotamente.Equipamento ficou em operação?:sim Pendência:sim*#Controle está faltando aterramento.* fibra para melhoria das mesmas.*Observação:Bateria(s) substituída(s)? simData Fabricação/Instalação da(s) bateria(s): 29/08/2025Equipe: Ellisfran/ Ana Maria

Sheet Plan1
A1: Ativo | B1: TIPO | C1: Criticidade | D1: Dias Pendente | E1: Status Atendimento | F1: Responsável | G1: SS SGM | H1: Município | I1: Polo | J1: Regional | K1: DESCRIÇÃO
A2: 7908686014 | B2: RL | C2: Baixo | D2: 631 | E2: 74 - DIAS AGUARDANDO DCMD | F2: COEP | G2: ETO-COEP 00086/2026 | H2: PIUM | I2: PARAISO DO TOCANTINS | J2: CENTRO | K2: 06/07 PARECER COEP: PREVISÃO DE ENTREGA DE ACORDO COM CALENDÁRIO LOGISITCO NOVO 06/07NOTA DMSL: Favor substituir o tanque, ele não está efetuando os comandos enviados. Não substituir o controle pois o mesmo funciona como repetidor de outros equipamentos.Segue nota para verificar falha de fechamento religador 7908686014- Pium .OBS: equipamento não fechou local e remoto , fica sinalizando no painel para verificar alarmes !
A3: 7900535058 | B3: RL | C3: Alto | D3: 334 | E3: 317 - DIAS AGUARDANDO DCMD | F3: COEP | G3: ETO-COEP 00173/2025 | H3: SANTA FE DO ARAGUAIA | I3: ARAGUAINA | J3: NORTE | K3: PARECER COEP: EQUIPAMENTO SELECIONADO PARA COMPRAPARECER DMSL: Equipamento 7900535058 encontra-se com o relé danificado, firmware corrompido, o mesmo não inicia. Devido ao fato de não possuirmos mais peças de reposição para religador cooper, se faz necessário a substituição de todo conjunto por um Noja RC10.envar equipe para verificar rlo 7900535058 foi feito primeiro ataque com equipe 040op36 o mesmo esta com RELE TRAVADO E FICOU FORA DE OPERAÇÃO, ATENDE RDR DE SANTA FÉ SAIDA DA CIDADEEQUIPE INFORMOU ABELHAS NA CAIXA DO PAINEL DE COMANDO
A4: 7953610256 | B4: RL | C4: Muito Alto | D4: 142 | E4: 111 - DIAS AGUARDANDO DCMD | F4: COEP | G4: ETO-COEP 00050/2026 | H4: MATEIROS | I4: PONTE ALTA TOCANTINS | J4: CENTRO | K4: PARECER COEP: AGUARDANDO COCM'S GERAREM A OBRA PARA ENTREGA DO MATERIALPARECER DMSL: Data: 10/03/2026,Serviço Executado: Foi substituído o relé do equipamento, o mesmo estava danificado. Trocado o DPS, o mesmo estava queimado devido ao tanque estar furado. O equipamento ficou em bypass.Equipamento ficou em operação? NãoPendência? Sim, substituir a parte ativa com cordão umbilical.Equipe: Carliel e João VitorSEGUE SS PARA REGULARIZAR AUTOMAÇÃO DO RL 7953610256 NA INTERLIGAÇÃO COM A COELBA (CHAPADA DA MANGABEIRA) - EQUIPE INFOMOU CURTO INTERNO NO GABINETE DJ AC NÃO FECHA
A5: 7942485096 | B5: RL | C5: Baixo | D5: 481 | E5: 350 - DIAS AGUARDANDO DCMD | F5: COEP | G5: ETO-COEP 00158/2025 | H5: PINDORAMA DO TOCANTINS | I5: PONTE ALTA TOCANTINS | J5: CENTRO | K5: 30/06 PARECER COEP: EQUIPAMENTO SELECIONADO PARA COMPRARELIGADOR COM DEFEITO 7942485096, ESTA DANDO PASSAGEM ESTANDO ABERTO. NÃO ACEITA COMANDOS. FICOU BY PASSADO EM CAMPO PARA MANUTENÇÃO.PARECER DMSL: Ao testar o tanque, foi constatado que o mesmo está danificado e precisa ser substituído.Substituir somente o tanque. Deixar claro na nota para o dcmd substituir somente o tanque. Não tem necessidade de substituir o controle.
A6: 5858783119 | B6: RT | D6: 471 | E6: 369 - DIAS AGUARDANDO DCMD | F6: COEP | G6: ETO-COEP 00123/2025 | H6: SAO BENTO DO TOCANTINS | I6: TOCANTINOPOLIS | J6: NORTE | K6: PARECER COEP: ERRO NA INSTALAÇÃO EQUIPAMENTO SELECIONADO PARA COMPRAPARECER DMSL: 16/06/2025-SERVIÇO EXECUTADO: Ao chegar no equipamento para realizar comissionamento, foi constatato que as 3 células estavam com a tampa de inspeção abertas e sem os para-raios. Constatado também que foi furtado todo o óleo isolante das 3 células, sendo necessário a substituição das 3 células. FICOU EM OPERAÇÃO?: Não PENDÊNCIA: Substituir as 3 células
A7: 7900230155 | B7: RL | C7: Baixo | D7: 466 | E7: 0 - DIAS AGUARDANDO DCMD | F7: PROTECAO | G7: ETO-RD-GR 00685/2026 | H7: PALMEIRANTE | I7: COLINAS DO TOCANTINS | J7: NORTE | K7: #N/A
A8: 5853360007 | B8: RT | C8: Medio | D8: 435 | E8: 264 - DIAS AGUARDANDO DCMD | F8: COCM-C | G8: ETO-RD-PS 00323/2025 | H8: MIRACEMA DO TOCANTINS | I8: MIRACEMA DO TOCANTINS | J8: CENTRO | K8: REALIZAR TESTES NO EQUIPAMENTO E CONFERIR MEDIÇÕES DA MALHA DE ATERRAMENTO. ESTANDO OK, COMISSIONAR EQUIPAMENTO E COLOCA-LO EM OPERAÇÃO.AJUSTES DISPONIVEIS NO APP DA PROTEÇÃdmsl : N° do Equipamento:*RT 5853360007 MIRACEMASID: 2493/2025Data: 13/05/2025Serviço Executado Provavelmente ocorreu uma descarga no equipamento comprometendo a malha!Será necessário fazer melhoria da malha de aterramento, fazer toda interligação da mesma! Feito ensaios de isolação das 3 células do equipamento, isolação está ok, quando retornar para colocar em operação levar 3 baterias de 7a.Equipamento ficou em operação?: Não Equipe: Benvindo e Jardel
A9: 7900453110 | B9: RL | C9: Baixo | D9: 442 | E9: 71 - DIAS AGUARDANDO DCMD | F9: COEP | G9: ETO-COEP 00087/2026 | H9: SANTA RITA DO TOCANTINS | I9: PORTO NACIONAL | J9: CENTRO | K9: 30/06.PARECER COEP: ALINHADO COM O ALLAN REMANEJAMOS PARTE ATIVA PARA ATENDER 7933726256PARECER COEP: Aproveitar controle cooper se possível em outro local, previsão de chegada do material dia 01/07 para substituiçãoFavor verificar o RL 7900453110, pois o mesmo aceita comando de fechamento, porém fecha em campo e no SCADA continua aberto e só abre através de equipe em campo. Parecer Dmsl:Equipamento está com defeito na parte ativa, não aceita o comando de fechamento. Será necessário substituir o equipamento completo.Equipamento ficou em operação?: _SIM_a pedido do COS ficou em operação, a operação está ciente da necessidade de substituir.Pendência: Sim, será necessário substituir o equipamento.
A10: 7923927122 | B10: RL | C10: Baixo | D10: 437 | E10: 435 - DIAS AGUARDANDO DCMD | F10: COEP | G10: ETO-COEP 00079/2025 | H10: PALMAS | I10: PALMAS | J10: CENTRO | K10: 30/06 PARECER COEP: EQUIPAMENTO SEM PARECER TECNICO DO DMSLSegue nota para envia manutenção substituir tanque do RL-7923927122 em curto, Anomalia identificada desarme das LD, s Palmas / Aparecida e Palmas Taquaruçu, Acesso livre, Tensão 34,5kv, Local RL de Interligação entre 424R / 414R.
A11: 7900117013 | B11: RL | C11: Alto | D11: 371 | E11: 74 - DIAS AGUARDANDO DCMD | F11: COEP | G11: ETO-COEP 00084/2026 | H11: PARAISO DO TOCANTINS | I11: PARAISO DO TOCANTINS | J11: CENTRO | K11: PARECER COEP: PREVISÃO DE ENTREGA AOS COCM'S 01/07Segue nota para correção de anomalia e provável substituição de religador , religador 7900117013 -RDU - Paraiso .OBS: equipe DMSL Elisfran estava atualizando firmware no equipamento , porém relé parou de funcionar devido essa atualização , sendo necessário sua substituição .em campo o modelo e cooper Form6 , segundo tecnico deve ser substituído por um Noja .Repassado para o COEP para aquisição do equipamento e posterior repasse para o COCM.
A12: 7922995039 | B12: RL | C12: Medio | D12: 405 | E12: 8 - DIAS AGUARDANDO DEOP | F12: PROTECAO | G12: ETO-PROT 00135/2026 | H12: ARAGUATINS | I12: AUGUSTINOPOLIS | J12: NORTE | K12: #N/A
A13: 7900532053 | B13: RL | C13: Baixo | D13: 408 | E13: 407 - DIAS AGUARDANDO DCMD | F13: COEP | G13: ETO-COEP 00102/2025 | H13: PIRAQUE | I13: TOCANTINOPOLIS | J13: NORTE | K13: 30/06-EQUIPAMENTO EM OPERAÇÃO NO SCADA, AGUARDANDO RESPOSTA DO DMSL PARA SEGUIR COM AS TRATATIVASFavor, realizar substituição completa do RLG 7900532053 que encontra-se com defeito devido entrada de água no cordão umbilical e danos causados por abelhas. O rádio também precisa ser fornecido pois o existente está danificado.
A14: 7920024127 | B14: RL | C14: Medio | D14: 401 | E14: 371 - DIAS AGUARDANDO DCMD | F14: COEP | G14: ETO-COEP 00120/2025 | H14: PALMEIRAS DO TOCANTINS | I14: TOCANTINOPOLIS | J14: NORTE | K14: 30/06 PARECER COEP: AGUARDANDO O RETORNO DO DMSL , PARA ENTENDER SE O PROBLEMA É NA COMUNICAÇÃO OU PARTE ATIVA, JÁ QUE O EQUIPAMENTO EM QUESTÃO SEGUE COMUNICANDOPARECER DMSL: Após testes, equipe DMSL constatou que o relé e a parte ativa do equipamento 7920024127 estão com defeito, sendo necessária a substituição completa por um modelo NOJA RC 10. Favor, subsituir também a chave de saída da fase A que está com o anel de abertura quebrado.RL 7920024127 está desarmando em campo e no SCADA continua fechado, só sinaliza aberto no SCADA quando a equipe faz o resert no equipamento em campo.
A15: 7928564039 | B15: RL | C15: Baixo | D15: 405 | E15: 0 - DIAS AGUARDANDO DCMD | F15: COEP | G15: ETO-COEP 00123/2026 | H15: ARAGUATINS | I15: AUGUSTINOPOLIS | J15: NORTE | K15: PARECER COEP: QUAL O MODELO DO EQUIPAMENTO? QUAL A FAIXA DE TENSÃO ? O QUE SERIA SISTEMA DE COMUNICAÇÃO COMPLETO?Troca do sistema de comunicação do equipamentoDMSL 28/07/2025: Equipamento com tanque, modulo e rele com defeito, solicitar troca do equipamento ao DCMD.Fotos vão ser enviadas por e-mail
A16: 7957126085 | B16: RL | C16: Baixo | D16: 398 | E16: 350 - DIAS AGUARDANDO DCMD | F16: COEP | G16: ETO-COEP 00156/2025 | H16: MONTE SANTO DO TOCANTINS | I16: PARAISO DO TOCANTINS | J16: CENTRO | K16: 20/06PARECER COEP: EMD 510216PREVISÃO DE CHEGADA COCM'S 01/07RELIGADOR COM RELÉ QUEIMADO - EQUIPAMENTO BY PASSADO. PARECER DMSL:N° do Equipamento: 7957126085Data: 17/06/2025Localidade: RDU Monte SantoServiço Executado:"Os para raios da fase B e C estão fechando arco na cruzeta. Curto desceu para o controle danificando os componentes. Necessário substituir controle completo, substituir cabo de alimentação da BT e abaixar o tanque para afastar das cruzetas. Solicitar também ao DCMD para verificar se os para raios estão danificados."Ana Maria e Rayr já tinha ido no local anteriormente, na data 14/05/25 e fizeram o diagnostico acima. Equipamento ficou em operação?: NÃO
A17: 5856156091 | B17: RT | D17: 387 | E17: 8 - DIAS AGUARDANDO DCMD | F17: COCM-S | G17: ETO-RD-DP 00403/2026 | H17: ALMAS | I17: DIANOPOLIS | J17: SUL | K17: DCMD 26.03.2026. SS REPASSADA PARA COEP PROVIDENCIAR MATERIAL. NÃO TEMOS O MATERIAL EM ESTOQUE PARA SUBSTITUIÇÃO. COEP: Equipamento fornecido ao COCM-S para regularização.PARECER COEP: EQUIPAMENTOS JÁ FORNECIDOS PARA OS COCM'S PARA REGULARIZAÇÃOPARECER DA PROTEÇÃO:EQUIPAMENTOS FURTADOS. PARA AQUISIÇÃO DAS CELULAS DE REPOSIÇÃO, FAVOR CONSULTAR OS DADOS DE PLACA EM ANEXO.PARECER DA PROTEÇÃO:COMISISONAR RT 5856156091 LD DIANOPOLIS A NATIVIDADE. NECESSARIO REALIZAR MEDIÇÕES DA RESISTENCIA DA MALHA DE ATERRAMENTO.AJUSTES DISPONIVEIS NO APP DA PROTEÇÃO.RELIGADOR N° 5856156091 INSTALADO NA OBRA 0502400526 GENTILEZA, REALIZAR O COMISSIONAMENTO. LAUDO EM ANEXO. COORD EO: 899501, 8714782
A18: 5854566043 | B18: RT | C18: Alto | D18: 350 | E18: 347 - DIAS AGUARDANDO DCMD | F18: COEP | G18: ETO-COEP 00160/2025 | H18: SILVANOPOLIS | I18: PORTO NACIONAL | J18: CENTRO | K18: PARECER COEP: EQUIPAMENTO SELECIONADO PARA COMPRAboa noite,segue SS para as devidas tratativas com equipe de manutenção com apoio de equipe de linha viva substituir regulador de tensão 5854566043 queimado célula fase c, LD Porto / Silvanópolis mesmo deverá ser substituído com apoio de equipe de linha viva PARECER DMSL: Foi realizado inspeção visual e ensaios de isolação, relação de transformação e resistência de enrolamento. A fase B está danificada e será necessário substituir a mesma. Malha de aterramento está relativamente boa e conectada. Fase A e C passaram nos ensaios. Substituir fase B.
A19: 7927446001 | B19: RL | C19: Baixo | D19: 377 | E19: 364 - DIAS AGUARDANDO DCMD | F19: COEP | G19: ETO-COEP 00143/2025 | H19: PORTO NACIONAL | I19: PORTO NACIONAL | J19: CENTRO | K19: 30/06 PARECER COEP: AGUARDANDO RETORNO DO DMSL PARA SEGUIR COM AS TRATATIVAS, JÁ QUE NÃO TEMOS CERTEZA SE É SOMENTE A PLCA OU O EQUIPAMENTO COMPLETOSegue para verificação RL sem comunicação feito primeiro ataque sem sucesso.PARECER DMSL:Data:* _08/07/2025Serviço Executado: Placa de alimentação danificada, devido a curto, não temos material sobressalente para manutenção! Favor substituir o equipamento completo.Obs.: O rádio ficou dentro do controle, favor orientar a equipe que for substituir colocar dentro do controle novo.Equipamento ficou em operação?: Não Pendência: Sim, substituir equipamento completo.
A20: 7930428001 | B20: RL | C20: Baixo | D20: 372 | E20: 8 - DIAS AGUARDANDO DMSL | F20: DMSL | G20: ETO-TELE 00965/2026 | H20: PORTO NACIONAL | I20: PORTO NACIONAL | J20: CENTRO | K20: #N/A
A21: 7928241200 | B21: RL | C21: Baixo | D21: 369 | E21: 0 - DIAS AGUARDANDO DCMD | F21: COEP | G21: ETO-COEP 00128/2026 | H21: SAO SALVADOR DO TOCANTINS | I21: PEIXE | J21: SUL | K21: PARECER COEP: FAVOR REAVALIAR DISPONIBILIDADE DO EQUIPAMENTO DO SCADA E DIZER MARCA ,MODELO E TENSÃO DO EQUIPAMENTOPARECER DMSL: Tinha uma nota aberta 422/2025 e logo após a equipe resolver a comunicação ela foi baixada, porém a equipe relatou que ''na estrada ontem o COS nos avisou para voltar que na hora de colocar em operação ele tirou a linha fora. Hoje retornamos nele e fizemos ensaios elétricos e foi constatado que o tanque está em curto. Passa direto aí para o Dcmd para substituição do tanque.''
A22: 5800371025 | B22: RT | C22: Alto | D22: 319 | E22: 305 - DIAS AGUARDANDO DCMD | F22: COEP | G22: ETO-COEP 00187/2025 | H22: ARAPOEMA | I22: COLINAS DO TOCANTINS | J22: NORTE | K22: PARECER COEP: AVALIAR COM O LEANDRO, PROVAVELMENTE SÓ COMPRAPARECER DMSL: Após testes foi constatado defeito nos relés da fase A e B, Modelo Toshiba TBR 1000. Se possível, substituir os relés das 3 fases por controle RUA, disponibilizar os cabos de ligação entre o tanque e o controle para possibilitar a compatibilização do equipamento. Fornecer kit de comunicação, rádio, antena, etc.Segue nota para veriifcar falha em regulador de tensão N: 5800371025 dentro S/E Arapoema , equipamento esta com 2 reles com falha marca toshiba .
A23: 7955520116 | B23: RL | C23: Baixo | D23: 362 | E23: 8 - DIAS AGUARDANDO DMSL | F23: DMSL | G23: ETO-TELE 00961/2026 | H23: CHAPADA DA NATIVIDADE | I23: DIANOPOLIS | J23: SUL | K23: #N/A
A24: 5844630060 | B24: RT | C24: Medio | D24: 336 | E24: 333 - DIAS AGUARDANDO DCMD | F24: COEP | G24: ETO-COEP 00167/2025 | H24: NOVA OLINDA | I24: COLINAS DO TOCANTINS | J24: NORTE | K24: PARECER COEP: EQUIPAMENTO EM ROTA DE ENTREGAPARECER DMSL: Célula da fase A encontra-se com vazamento de óleo no pé da torneira. Necessário substituição da célula.Aberto nota para verificar vazamento de óleo fase A no RT 5844630060 - RDU Nova Olinda
A25: 7908705049 | B25: RL | C25: Baixo | D25: 357 | E25: 1 - DIAS AGUARDANDO DCMD | F25: COCM-S | G25: ETO-RD-DP 00409/2026 | H25: AURORA DO TOCANTINS | I25: DIANOPOLIS | J25: SUL | K25: EQUIPAMENTO ENTREGUE, SOLICITO PREVISÃO PARA SUBSTITUIÇÃO:PARECER COEP: PREVISÃO DE ENTREGA AOS COCM'S 01/07Manutenção no RL 7908705049PARECER DMSL(28/08/2025): Equipe foi fazer manutenção no RL e constatou que o tanque e o relé do mesmo se encontra queimado, providenciar substituição.PARECER COCMS 30/04/2026CRIADO OBRA 0512600135 PARA REQUISIÇÃO MATERIAL
A26: 5800438116 | B26: RT | C26: Baixo | D26: 355 | E26: 7 - DIAS AGUARDANDO DCMD | F26: COCM-S | G26: ETO-RD-DP 00404/2026 | H26: CHAPADA DA NATIVIDADE | I26: DIANOPOLIS | J26: SUL | K26: 01/07 PARECER COEP: DENER INFORMOU QUE TEM AS PEÇAS SOBRESSALENTES DE OBRA PARA UTILIZAR, REPASSEREI AO POSTO DO ETO-RD-DP PARA AS TRATATIVAS, FAVOR INFORMAR PREVISÃO DE SUBSTIUIÇÃO E PREENCHER A PLANILHA ASSIM COMO PREENCHER A DESCRIÃO ANTES DE PASSAR PARA PROTEÇÃO FAZER OS AJUSTES30/06PARECER COEP: AGUARDANDO COCM'S CRIAREM OBRA PARA ENTREGA DO MATERIALSegue nota para normalizar falha em regulador N:5800438116 - Chapada da natividade .equipamento está com fase B e C travada .OBS: a fase B esta sinalizando falha , equipamento não insere TAP negativo na fase B e C , o mesmo ficou no TAP zerado e bloqueado .PARECER DMSL (18/08/2025): Foi feito teste de elevar e abaixar nas fases B e C e o mesmo só aceita elevar os taps, constatando que o mercanismo da chave reversoura polaridade está com defeito. Número de série fase B EI7030 e Número de série fase C EI7040. Substituir as fases B e C.Foi constatado que a placa F do controle está com defeito.
A27: 5856070091 | B27: RT | D27: 355 | E27: 0 - DIAS AGUARDANDO DCMD | F27: COEP | G27: ETO-COEP 00130/2026 | H27: ALMAS | I27: DIANOPOLIS | J27: SUL | K27: PARECER DMSL: não foi regularizado a instalação do equipamento, nota repassada conforme alinhado com o supervisor.____________________________________________COCMS 26.03.26. SS REPASSADA PARA COEP PROVIDENCIAR MATERIAL. NÃO TEMOS AS PÇ EM ESTOQUE PARA FAZER A SUBSTITUIÇÃO. Solicitação de serviço para reposição de equipamentos furtados .COEP: Equipamento fornecido ao COCM-S para regularização.COCMS: Equipamento substituido conforme solicitado. Gentileza comissionar.PARECER DA PROTEÇÃO:SEGUE NOTA REPASSADA PARA DMSL COMISSIONAR.ENG° IRLLEY CASTELO BRANCOPARECER DMSL(23/09/2025): Feito a parte de comunicação, fechando enlace, configuração do rádio GE. Feito a medição de aterramento. Após uma inspeção, foi identificado que o regulador de tensão está instalado errado, carga está para o lado de fonte e fonte está do lado de carga. O certo é a fonte vim de almas, atualmente está vindo de natividade. Favor fazer a instalação correta.
A28: 5850308009 | B28: RT | C28: Baixo | D28: 327 | E28: 0 - DIAS AGUARDANDO DCMD | F28: COEP | G28: ETO-COEP 00127/2026 | H28: GUARAI | I28: GUARAI | J28: NORTE | K28: PARECER COEP: Equipamento em operaçãpo no SCADAPARECER DMSL: Após testes, foi constatado que o RT 5850308009 encontra-se com controle danificado, sendo necessária substituição do mesmo.Regulador de tensão 5850308009 quando esta em Automatico esta deixa um fase muito baixa. foi deixado uma fase Manual e transferida parte do alimentaor.
A29: 5827102054 | B29: RT | C29: Baixo | D29: 315 | E29: 8 - DIAS AGUARDANDO DCMD | F29: COCM-C | G29: ETO-RD-PS 00289/2026 | H29: PUGMIL | I29: PARAISO DO TOCANTINS | J29: CENTRO | K29: PARECER COEP:NÃO É POSSÍVEL RETORNAR COM O CONTROLE COMPLETO , MAS DARIA PARA FAZER A MELHORIA NA MALHA DE ATERRAMENTO , ENCAMINHANDO PARA OS COCM'S PARA REALIZAREM A MELHORIAparecer DMSL: :Nobreack com defeito, rele queimado, cabo de comunicação entre o rádio e o rele danificado, malha de aterramento está com a resistência alta!Feito reparo no cabo, substituído nobreack, e rele. Se possível retornar com controle completo pq o q está em campo teve infiltração de água, abrir chamado no scada para atualizar base do equipamento pois o mesmo está com a base antiga, fazer correção da malha de aterramento.Equipamento ficou em operação?: Não Pendência: sim, levar controle novo, fazer correção da malha de terra, levar suporte para fixar antena. OBS; reprogramar equipamento.Bateria(s) substituída(s) simEquipe: Benvindo e Carliel SOLICITAMOS CONTROLE COMPLETO
A30: 7903112004 | B30: RL | C30: Medio | D30: 308 | E30: 307 - DIAS AGUARDANDO DCMD | F30: COEP | G30: ETO-COEP 00184/2025 | H30: ARAGUAINA | I30: ARAGUAINA | J30: NORTE | K30: PARECER COEP: AGUARAR RETORNo RETORNO DMSLApós testes no RLG 7903112004 foi constatado defeito no mesmo e como se trata de um modelo COOPER FORM6 que está obsoleto e não possuímos peças sobressalentes, faz-se necessária substituição completa por modelo NOJA RC10.
A31: 5803327001 | B31: RT | C31: Baixo | D31: 307 | E31: 7 - DIAS AGUARDANDO DCMD | F31: COCM-C | G31: ETO-RD-PA 00434/2026 | H31: PORTO NACIONAL | I31: PORTO NACIONAL | J31: CENTRO | K31: 01/07 PARECER COEP: FOI CONFIRMADO COM A OPERAÇÃO QUE O EQUIPAMENTO SEGUIU O FLUXO INTEIRO DE COMISSIONAMENTO, PROTEÇÃO, FAVOR EXPLICAR O QUE FOI REALIZADO E SE EQUIPAMENTO ESTÁ OPERANDO, SENÃO ESTIVER EXPLICAR O QUE FOI FEITO NELE30/06PARECER COEP: REPASSAR DIRETAMENTE PARA OS COCM'SRegulador 5803327001 fora de operação, by passado em campo com painel de comunicação com cabos desconectados tensão 13.8.parecer DMSL: Feedback Equip. EspeciaisRT 5803327001RELÉ RUASid: 4844Data: 19/09/2025Serviço realizado:*Equipamento foi remanejado, 7 km da sua localização sentido Palmas necessário comissionamento completo*Equipamento com um dos cabos umbilicais danificado.* aterramento bucha FC não esta interligada corretamente * para-raios estão no mesmo aterramento da bucha FC.* Tranques muito alto e próximo da rede não permitindo o comissionamento com segurança.* Controle alto demais tem que baixar Equipamento ficou em operação?: nãoPendência: sim, precisa comissionar completoOBS; reprogramar equipamento.Bateria(s) substituída(s) NÃOEquipe: Ellisfran, Ana Maria PARECER DMSL: Data 03/12/2025-Equipe: Carliel e BenvindoServiço executado foi ensaiado as três células Equipamento ficou em operação: Não Pendência: sim, Instalar controle completo, e fazer melhoria na malhar de aterramento
A32: 5855411017 | B32: RT | C32: Baixo | D32: 308 | E32: 280 - DIAS AGUARDANDO DCMD | F32: COEP | G32: ETO-COEP 00199/2025 | H32: BARROLANDIA | I32: MIRACEMA DO TOCANTINS | J32: CENTRO | K32: PARECER COEP: EQUIPAMENTO EM ROTA DE ENTREGASEM COMUNICAÇÃO, FALHA DE ALIMENTAÇÃO - REALIZADO PRIMEIRO ATAQUE SEM SUCESSO.PARECER DMSL: 17/09/2025 Equipamento ficou em operação? Não Pendência: sim. Equipamento ficou Bay passado levar controle COMPLETO para trocar. ellisfran
A33: 7933766059 | B33: RL | C33: Medio | D33: 273 | E33: 7 - DIAS AGUARDANDO DCMD | F33: COCM-C | G33: ETO-RD-PA 00431/2026 | H33: PALMAS | I33: TAQUARALTO | J33: CENTRO | K33: PARECER COEP: EQUIPAMENTO ENTREGUE, SEGUE SS PARA O COCM´S , PARA REALIZAR O ATENDIMENTO,FAVOR ADICIONAR O PARECER PARA MANDAR PARA PROTEÇÃOSegue SS para verficar religador de poste 7933766059.Religador esta com defeito na parte ativa no tanque Porte gentilezaenviar equipe verificar.Endereço: TaquariPARECER DMSL: RLG 7933766059 RELÉ NOJA RC 10Mestre 2 Rep. taquaruçu GESID: 5457/2025Data: 15/10/2025Serviço Executado: Houve um curto na parte ativa do equipamento danificando a mesma, será necessário fazer a substituição somente do tanque, parte ativa.*Equipamento ficou em operação?:*Nao Pendência: Sim, substituir parte ativa.Equipe: Benvindo, Juliano e Sérgio.
A34: 7931610122 | B34: RL | C34: Medio | D34: 271 | E34: 7 - DIAS AGUARDANDO DCMD | F34: COCM-C | G34: ETO-RD-PA 00433/2026 | H34: PALMAS | I34: PALMAS | J34: CENTRO | K34: 30/06 PARECER COEP: EQUIPAMENTO ENTREGUE, SEGUE SS PARA O COCM´S , PARA REALIZAR O ATENDIMENTO,FAVOR ADICIONAR O PARECER PARA MANDAR PARA PROTEÇÃOBom dia,Segue SS para verificação RL sem comunicação com painel apagado equipe DEOP fez primeiro ataque sem sucesso RL 7931610122 RDU de Palmas.Feedback Equipamentos Especiais DMSL: *RLG 7931610122 RDU Palmas*Noja rc10 Data: 14/10/2025SID: 5412Dados de comunicação divergentes da programação: Não. Serviço Executado: Houve um curto no equipamento danificando a parte ativa, e antena! Será necessário fazer a substituição somente da parte ativa (tanque) e da antena.Equipamento ficou em operação?: Não Pendência: Sim, substituir a parte ativa.Bateria(s) substituída(s)?: NãoData Fabricação/Instalação da(s) bateria(s): 2024Equipe: Benvindo, Juliano e Sérgio.
A35: 7900573047 | B35: RL | C35: Baixo | D35: 272 | E35: 75 - DIAS AGUARDANDO DCMD | F35: COEP | G35: ETO-COEP 00080/2026 | H35: FIGUEIROPOLIS | I35: ALVORADA | J35: SUL | K35: PARECER COEP: AGUARDANDO COCM'S GERAREM AS OBRAS PARA PODER ENTREGAR MATERIALFavor providenciar manutenção no RL 7900573047, o mesmo estar em curto conforme fotos anexadas. Equipamento ficou bay passado em campo.PARECER DMSL: Equipe: FABIO AP./JOÃO MARCOSData Executada: 15/10/2025Serviço Executado:Foi constatado que o equipamento esta queimado na parte ativa placa, tanque e relé. Por favor fazer a substituição pelo Noja RC10.
A36: 7947203070 | B36: RL | C36: Medio | D36: 227 | E36: 0 - DIAS AGUARDANDO DCMD | F36: COEP | G36: ETO-COEP 00131/2026 | H36: RIO SONO | I36: PALMAS | J36: CENTRO | K36: PARECER COEP: QUAL O MODELO DA PLACA OU CÓDIGO DO MATERIAL?EXISTE DIFERENÇA DE MODELO OU POTÊNCIA?favor verificar RL 7947203070, sem comunicaçao, feito 1° ataque pela equipe 070OP01 e nao retornou a comunicaçao , linformaçao no Scada de bateria.PARECER DMSL: Foi feito análise técnica, a placa do equipamento está queimada nessesario subistituir o equipamento completo -Carliel e Benvindo-05/02
A37: 7938137007 | B37: RL | C37: Alto | D37: 194 | E37: 34 - DIAS AGUARDANDO DMSL | F37: DMSL | G37: ETO-TELE 00888/2026 | H37: MIRACEMA DO TOCANTINS | I37: MIRACEMA DO TOCANTINS | J37: CENTRO | K37: #N/A
A38: 7925087021 | B38: RL | C38: Medio | D38: 212 | E38: 212 - DIAS AGUARDANDO DCMD | F38: COEP | G38: ETO-COEP 00222/2025 | H38: PARANA | I38: PEIXE | J38: SUL | K38: PARECER COEP: EM ROTA DE ENTREGA, VERIFICAR PREVISÃO DE CHEGADARealizar a substituição do tanque do equipamento.
A39: 5800961074 | B39: RT | C39: Baixo | D39: 215 | E39: 214 - DIAS AGUARDANDO DCMD | F39: COEP | G39: ETO-COEP 00221/2025 | H39: DIANOPOLIS | I39: DIANOPOLIS | J39: SUL | K39: PARECER COEP: EQUIPAMENTO SELECIONADO PARA COMPRASubstituir as 3 células- Melhoria na malha de aterramento - Melhoria no circuito de aterramento qua aterra as células.- Substituir conectores paralelos
A40: 7927713200 | B40: RL | C40: Baixo | D40: 219 | E40: 8 - DIAS AGUARDANDO DMSL | F40: DMSL | G40: ETO-TELE 00960/2026 | H40: SAO SALVADOR DO TOCANTINS | I40: PEIXE | J40: SUL | K40: #N/A
A41: 7937102148 | B41: RL | C41: Medio | D41: 202 | E41: 0 - DIAS AGUARDANDO DCMD | F41: COEP | G41: ETO-COEP 00129/2026 | H41: SAO VALERIO DA NATIVIDADE | I41: PEIXE | J41: SUL | K41: PARECER COEP: REAVALIAR DISPONIBILIDADE DO EQUIPAMENTO NO SCADA ASSIM COMO , FORNECER MODELO DO EQUIPAMENTO E FAIXA DE TENSÃO PARA COMPRA / AQUISIÇÃOTanque com defeito, realizar substituição do tanque.
A42: 5862236091 | B42: RT | D42: 212 | E42: 212 - DIAS AGUARDANDO DCMD | F42: COEP | G42: ETO-COEP 00223/2025 | H42: ALMAS | I42: DIANOPOLIS | J42: SUL | K42: PARECER COEP: AGUARDANDO COCM´s GERAREM A OBRA COM ABERTURA CONTABIL DENER SOARESRealizar substituição da FASE B.Célula da fase B estava com a tampa do contador de tape aberta, pegou chuva e molhou os contatos danificando a peça toda.
A43: 5840227063 | B43: RT | C43: Alto | D43: 166 | E43: 19 - DIAS AGUARDANDO DMSL | F43: DMSL | G43: ETO-TELE 00942/2026 | H43: BANDEIRANTES DO TOCANTINS | I43: COLINAS DO TOCANTINS | J43: NORTE | K43: #N/A
A44: 7901110084 | B44: RL | C44: Baixo | D44: 203 | E44: 99 - DIAS AGUARDANDO DCMD | F44: COEP | G44: ETO-COEP 00061/2026 | H44: DIVINOPOLIS | I44: DIVINOPOLIS | J44: CENTRO | K44: PARECER COEP: EQUIPAMENTO SELECIONADO PARA COMPRAPARECER DMSL: Serviço Executado: Foi feito análise técnica, testes funcionais e identificado que a parte ativa do equipamento está com defeito. Necessário substituir a parte ativa.FICOU EM OPERAÇÃO? Não- EQUIPE: Carliel e BenvindoSegue SS para verificaçao Rl esta danificado dando passagem de tensão mesmo aberto Sim, quando retornar trazer uma fonte pois a mesma foi removida.
A45: 7931608059 | B45: RL | C45: Alto | D45: 161 | E45: 134 - DIAS AGUARDANDO DCMD | F45: COEP | G45: ETO-COEP 00040/2026 | H45: PALMAS | I45: TAQUARALTO | J45: CENTRO | K45: PARECER COEP: EQUIPAMENTO SELECIONADO PARA COMPRADMSL:Serviço Executado: Foi feita uma análise técnica no equipamento, devido à falta de comunicação. Também foi identificado que o tanque do equipamento está danificado, sendo assim, necessário substituir o tanque e o rádio do equipamento, que está queimado, sendo necessário substituir também.
A46: 5820790038 | B46: RT | C46: Muito Alto | D46: 11 | E46: 10 - DIAS AGUARDANDO DEOP | F46: PROTECAO | G46: ETO-PROT 00134/2026 | H46: TAGUATINGA | I46: DIANOPOLIS | J46: SUL | K46: #N/A
